Workbook

Sheet Mode opératoire
B1: MODE OPERATOIRE
B2: La description d'une position sortante dans un dossier agent, nécessite la MAJ des données portées par les 3 sous-rubriques suivantes : Position statutaire/situation administrative Détachement, affectation ou MAD sortant Compteurs de périodes de positions/situations La spécification métier regroupe au sein d'un évènement unique l'articulation des RG mobilisant des données appartenant à ces trois sous-rubriques. Ainsi, le métier considère que les données associées à ces trois sous rubriques sont mises à jour dans la même transaction. Les positions concernées sont les codes de positions mobilisés dans l'axe1.

Sheet Axe 1 Enchainement des RG
A1: Version | B1: Type de mise à jour | C1: Date de mise à jour | D1: Identifiant Domaine | E1: Libellé du Domaine | F1: Identifiant Sous-domaine | G1: Libellé du Sous-domaine | H1: Identifiant Evénement | I1: Libellé de l'évènement | J1: Libellé condition déclenchement Evènement | K1: Condition déclenchement Evènement | L1: Identifiant type d'évènement | M1: Libellé type d'évènement | N1: Type de mise à jour | O1: Libellé condition déclenchement Type Evènement | P1: Condition déclenchement Type Evènement | Q1: Libellé Population | R1: Codification Population | S1: Général / Particulier | T1: Passant / Exclu | U1: Date de début | V1: Date de fin | W1: Règles mobilisées | X1: Identifiant Règle de contrôle intellectuel 1 | Y1: Libellé Règle de contrôle intellectuel 1 | Z1: Identifiant Règle de contrôle intellectuel 2 | AA1: Libellé Règle de contrôle intellectuel 2 | AB1: Identifiant Règle de contrôle intellectuel 3 | AC1: Libellé Règle de contrôle intellectuel 3 | AD1: Identifiant Règle de contrôle intellectuel 4 | AE1: Libellé Règle de contrôle intellectuel 4 | AF1: Identifiant Règle de contrôle intellectuel 5 | AG1: Libellé Règle de contrôle intellectuel 5 | AH1: Identifiant Règle de contrôle intellectuel 6 | AI1: Libellé Règle de contrôle intellectuel 6 | AJ1: Identifiant Règle de contrôle intellectuel 7 | AK1: Libellé Règle de contrôle intellectuel 7 | AL1: Identifiant Règle de contrôle intellectuel 8 | AM1: Libellé Règle de contrôle intellectuel 8 | AN1: Identifiant Règle de contrôle intellectuel 9 | AO1: Libellé Règle de contrôle intellectuel 9 | AP1: Identifiant Règle de contrôle intellectuel 10 | AQ1: Libellé Règle de contrôle intellectuel 10 | AR1: Identifiant Règle de contrôle intellectuel 11 | AS1: Libellé Règle de contrôle intellectuel 11 | AT1: Identifiant Règle de contrôle intellectuel 12 | AU1: Libellé Règle de contrôle intellectuel 12 | AV1: Identifiant Règle de contrôle intellectuel 13 | AW1: Libellé Règle de contrôle intellectuel 13 | AX1: Identifiant Règle de contrôle intellectuel 14 | AY1: Libellé Règle de contrôle intellectuel 14 | AZ1: Identifiant Règle de contrôle intellectuel 15 | BA1: Libellé Règle de contrôle intellectuel 15 | BB1: Identifiant Règle de condition 1 | BC1: Libellé Règle de condition 1 | BD1: Identifiant Règle de condition 2 | BE1: Libellé Règle de condition 2 | BF1: Identifiant Règle de condition 3 | BG1: Libellé Règle de condition 3 | BH1: Identifiant Règle de condition 4 | BI1: Libellé Règle de condition 4 | BJ1: Identifiant Règle de condition 5 | BK1: Libellé Règle de condition 5 | BL1: Identifiant Règle de condition 6 | BM1: Libellé Règle de condition 6 | BN1: Identifiant Règle de condition 7 | BO1: Libellé Règle de condition 7 | BP1: Identifiant Règle de condition 8 | BQ1: Libellé Règle de condition 8 | BR1: Identifiant Règle de contrôle 1 | BS1: Libellé Règle de contrôle 1 | BT1: Identifiant Règle de contrôle 2 | BU1: Libellé Règle de contrôle 2 | BV1: Identifiant Règle de contrôle 3 | BW1: Libellé Règle de contrôle 3 | BX1: Identifiant Règle de contrôle 4 | BY1: Libellé Règle de contrôle 4 | BZ1: Identifiant Règle de contrôle 5 | CA1: Libellé Règle de contrôle 5 | CB1: Identifiant Règle de contrôle 6 | CC1: Libellé Règle de contrôle 6 | CD1: Identifiant Règle de contrôle 7 | CE1: Libellé Règle de contrôle 7 | CF1: Identifiant Règle de contrôle 8 | CG1: Libellé Règle de contrôle 8 | CH1: Identifiant Règle de contrôle 9 | CI1: Libellé Règle de contrôle 9 | CJ1: Identifiant Règle de contrôle 10 | CK1: Libellé Règle de contrôle 10 | CL1: Identifiant Règle de contrôle 11 | CM1: Libellé Règle de contrôle 11 | CN1: Identifiant Règle de contrôle 12 | CO1: Libellé Règle de contrôle 12 | CP1: Identifiant Règle de contrôle 13 | CQ1: Libellé Règle de contrôle 13 | CR1: Identifiant Règle de contrôle 14 | CS1: Libellé Règle de contrôle 14 | CT1: FIME | CU1: Statut de travail
A2: 23.00.00 | B2: M | C2: 45071.719 | D2: D0004 | E2: Position | F2: S0017 | G2: Mise à disposition sortante | H2: E0202 | I2: MAD sortante à titre gratuit auprès d'une autre administration ou d'un EPA de l'Etat | J2: Position administrative saisie égale à 'MAD sortante à titre gratuit auprès d'une autre administration ou d'un EPA de l'Etat' | K2: A_POS_POSIAD [Saisi] = 'MAD11' | L2: T0592 | M2: MADS à titre gratuit auprès d'une autre administration ou d'un EPA de l'Etat - Demande | N2: Création Modification | O2: Indicateur Renouvellement Position est non activé ET l'indicateur de renouvellement saisi est différent de l'indicateur de renouvellement avant saisie | P2: A_POS_INDREN [Saisi] = '0' ET A_POS_INDREN [Saisi] <> A_POS_INDREN [Valeur avant saisie] | Q2: Titulaire ou magistrat | R2: P0001 | S2: Général | T2: Passant | U2: 40725 | V2: 44497 | W2: MAD_I_001 ET MAD_I_002 ET MAD_I_003 ET MAD_I_006 ET MAD_I_009 ET MAD_I_004 ET MAD_I_005 ET MAD_I_008 ET MAD_I_007 ET MAD_I_026 ET MAD_I_025 ET MAD_I_027 ET MAD_D_011 ET MAD_D_411 ET MAD_D_001 ET POS_C_004 ET POS_C_005 ET POS_C_007 ET POS_C_010 ET POS_C_012 ET POS_C_022 ET POS_C_037 ET POS_C_111 ET POS_C_431 ET POS_C_434 | X2: MAD_I_001 | Y2: =VLOOKUP(X2,'Axe 2 Règles de gestion'!$D$2:$F$271,3, FALSE) -> Les statuts particuliers peuvent prévoir des conditions d'âge ou d'ancienneté comme pré requis à une mise à disposition sortante. | Z2: MAD_I_002 | AA2: =VLOOKUP(Z2,'Axe 2 Règles de gestion'!$D$2:$F$271,3, FALSE) -> L'agent peut être mis à disposition d'un ou plusieurs organismes d'accueil. | AB2: MAD_I_003 | AC2: =VLOOKUP(AB2,'Axe 2 Règles de gestion'!$D$2:$F$271,3, FALSE) -> L'agent peut être mis à disposition pour tout ou partie de son service. | AD2: MAD_I_006 | AE2: =VLOOKUP(AD2,'Axe 2 Règles de gestion'!$D$2:$F$271,3, FALSE) -> L'accord du ou des organismes d'accueil est nécessaire. | AF2: MAD_I_009 | AG2: =VLOOKUP(AF2,'Axe 2 Règles de gestion'!$D$2:$F$271,3, FALSE) -> En cas de pluralité d'organismes d'accueil, autant de conventions sont nécessaires. | AH2: MAD_I_004 | AI2: =VLOOKUP(AH2,'Axe 2 Règles de gestion'!$D$2:$F$271,3, FALSE) -> La convention ou les conventions doivent être transmises à l'agent avant signature. | AJ2: MAD_I_005 | AK2: =VLOOKUP(AJ2,'Axe 2 Règles de gestion'!$D$2:$F$271,3, FALSE) -> L'accord de l'agent est nécessaire. | AL2: MAD_I_008 | AM2: =VLOOKUP(AL2,'Axe 2 Règles de gestion'!$D$2:$F$271,3, FALSE) -> Une convention entre l'organisme d'origine et l'organisme d'accueil doit être signée. | AN2: MAD_I_007 | AO2: =VLOOKUP(AN2,'Axe 2 Règles de gestion'!$D$2:$F$271,3, FALSE) -> La mise à disposition est prononcée par arrêté du ministre dont relève l'agent, ou par arrêté du préfet dont relève l'agent, ou par décision de l'autorité investie du pouvoir de nomination dans l'établissement. | AP2: MAD_I_026 | AQ2: =VLOOKUP(AP2,'Axe 2 Règles de gestion'!$D$2:$F$271,3, FALSE) -> La modification d'un des éléments constitutifs de la convention doit faire l'objet d'un avenant à cette convention. | AR2: MAD_I_025 | AS2: =VLOOKUP(AR2,'Axe 2 Règles de gestion'!$D$2:$F$271,3, FALSE) -> Tout avenant implique la même procédure notamment l'accord de l'agent et du (ou des) organisme(s) d'accueil, les arrêtés ou les décisions. | AT2: MAD_I_027 | AU2: =VLOOKUP(AT2,'Axe 2 Règles de gestion'!$D$2:$F$271,3, FALSE) -> Les avenants à la convention doivent être transmis à l'agent avant signature. | BB2: MAD_D_011 | BC2: =VLOOKUP(BB2,'Axe 2 Règles de gestion'!$D$2:$F$271,3, FALSE) -> La durée prévisionnelle est fixée à 3 ans maximum renouvelable pour chaque période. | BD2: MAD_D_411 | BE2: =VLOOKUP(BD2,'Axe 2 Règles de gestion'!$D$2:$F$271,3, FALSE) -> La durée réelle est fixée à 3 ans maximum renouvelable pour chaque période. | BF2: MAD_D_001 | BG2: =VLOOKUP(BF2,'Axe 2 Règles de gestion'!$D$2:$F$271,3, FALSE) -> L'agent doit être en activité. | BR2: POS_C_004 | BS2: =VLOOKUP(BR2,'Axe 2 Règles de gestion'!$D$2:$F$271,3, FALSE) -> La date de début de position doit être antérieure ou égale à la date de fin prévisionnelle de position. | BT2: POS_C_005 | BU2: =VLOOKUP(BT2,'Axe 2 Règles de gestion'!$D$2:$F$271,3, FALSE) -> La date de début de la position doit être postérieure ou égale à la date d'entrée dans la FPE ou dans la carrière militaire. | BV2: POS_C_007 | BW2: =VLOOKUP(BV2,'Axe 2 Règles de gestion'!$D$2:$F$271,3, FALSE) -> La date de fin réelle de la position doit être antérieure à la date limite de départ à la retraite. | BX2: POS_C_010 | BY2: =VLOOKUP(BX2,'Axe 2 Règles de gestion'!$D$2:$F$271,3, FALSE) -> La date de début de position doit être antérieure ou égale à la date de fin réelle de position. | BZ2: POS_C_012 | CA2: =VLOOKUP(BZ2,'Axe 2 Règles de gestion'!$D$2:$F$271,3, FALSE) -> La date de fin prévisionnelle de la position doit être antérieure à la date limite de départ à la retraite. | CB2: POS_C_022 | CC2: =VLOOKUP(CB2,'Axe 2 Règles de gestion'!$D$2:$F$271,3, FALSE) -> La date de début de position est à J+1 de la date de fin de position de l'occurrence précédente. | CD2: POS_C_037 | CE2: =VLOOKUP(CD2,'Axe 2 Règles de gestion'!$D$2:$F$271,3, FALSE) -> Les champs "Type d'organisme d'accueil" et "Pays" de l'organisme d'accueil doivent être renseignés. | CF2: POS_C_111 | CG2: =VLOOKUP(CF2,'Axe 2 Règles de gestion'!$D$2:$F$271,3, FALSE) -> La date de fin ou la date de fin prévisionnelle doit être saisie. | CH2: POS_C_431 | CI2: =VLOOKUP(CH2,'Axe 2 Règles de gestion'!$D$2:$F$271,3, FALSE) -> Les champs "Ministère (ou institution de la République) d'accueil", "Corps d'accueil en détachement" et "Grade d'accueil en détachement" ou "Ministère (ou institution de la République) d'accueil", "Emploi fonctionnel d'accueil en détachement" et "Groupe dans un emploi fonctionnel d'accueil" sont renseignés si le "Type d'organisme d'accueil" est valorisé à FPE. | CJ2: POS_C_434 | CK2: =VLOOKUP(CJ2,'Axe 2 Règles de gestion'!$D$2:$F$271,3, FALSE) -> Le champ "Organisme d'accueil" doit être alimenté si le type d'organisme d'accueil est égal à 'Autre organisme', 'Fonction publique d'un état de l'Union Européenne' ou 'Fonction publique Européenne'.
A3: 23.00.00 | B3: A | C3: 45071.719 | D3: D0004 | E3: Position | F3: S0017 | G3: Mise à disposition sortante | H3: E0202 | I3: MAD sortante à titre gratuit auprès d'une autre administration ou d'un EPA de l'Etat | J3: Position administrative saisie égale à 'MAD sortante à titre gratuit auprès d'une autre administration ou d'un EPA de l'Etat' | K3: A_POS_POSIAD [Saisi] = 'MAD11' | L3: T0592 | M3: MADS à titre gratuit auprès d'une autre administration ou d'un EPA de l'Etat - Demande | N3: Création Modification | O3: Indicateur Renouvellement Position est non activé ET l'indicateur de renouvellement saisi est différent de l'indicateur de renouvellement avant saisie | P3: A_POS_INDREN [Saisi] = '0' ET A_POS_INDREN [Saisi] <> A_POS_INDREN [Valeur avant saisie] | Q3: Titulaire ou magistrat | R3: P0001 | S3: Général | T3: Passant | U3: 44498 | W3: MAD_I_001 ET MAD_I_002 ET MAD_I_003 ET MAD_I_006 ET MAD_I_009 ET MAD_I_004 ET MAD_I_005 ET MAD_I_008 ET MAD_I_007 ET MAD_I_026 ET MAD_I_025 ET MAD_I_027 ET MAD_D_011 ET MAD_D_411 ET MAD_D_001 ET POS_C_004 ET POS_C_005 ET POS_C_007 ET POS_C_010 ET POS_C_012 ET POS_C_022 ET POS_C_037 ET POS_C_111 ET POS_C_431 ET POS_C_434 | X3: MAD_I_001 | Y3: =VLOOKUP(X3,'Axe 2 Règles de gestion'!$D$2:$F$271,3, FALSE) -> Les statuts particuliers peuvent prévoir des conditions d'âge ou d'ancienneté comme pré requis à une mise à disposition sortante. | Z3: MAD_I_002 | AA3: =VLOOKUP(Z3,'Axe 2 Règles de gestion'!$D$2:$F$271,3, FALSE) -> L'agent peut être mis à disposition d'un ou plusieurs organismes d'accueil. | AB3: MAD_I_003 | AC3: =VLOOKUP(AB3,'Axe 2 Règles de gestion'!$D$2:$F$271,3, FALSE) -> L'agent peut être mis à disposition pour tout ou partie de son service. | AD3: MAD_I_006 | AE3: =VLOOKUP(AD3,'Axe 2 Règles de gestion'!$D$2:$F$271,3, FALSE) -> L'accord du ou des organismes d'accueil est nécessaire. | AF3: MAD_I_009 | AG3: =VLOOKUP(AF3,'Axe 2 Règles de gestion'!$D$2:$F$271,3, FALSE) -> En cas de pluralité d'organismes d'accueil, autant de conventions sont nécessaires. | AH3: MAD_I_004 | AI3: =VLOOKUP(AH3,'Axe 2 Règles de gestion'!$D$2:$F$271,3, FALSE) -> La convention ou les conventions doivent être transmises à l'agent avant signature. | AJ3: MAD_I_005 | AK3: =VLOOKUP(AJ3,'Axe 2 Règles de gestion'!$D$2:$F$271,3, FALSE) -> L'accord de l'agent est nécessaire. | AL3: MAD_I_008 | AM3: =VLOOKUP(AL3,'Axe 2 Règles de gestion'!$D$2:$F$271,3, FALSE) -> Une convention entre l'organisme d'origine et l'organisme d'accueil doit être signée. | AN3: MAD_I_007 | AO3: =VLOOKUP(AN3,'Axe 2 Règles de gestion'!$D$2:$F$271,3, FALSE) -> La mise à disposition est prononcée par arrêté du ministre dont relève l'agent, ou par arrêté du préfet dont relève l'agent, ou par décision de l'autorité investie du pouvoir de nomination dans l'établissement. | AP3: MAD_I_026 | AQ3: =VLOOKUP(AP3,'Axe 2 Règles de gestion'!$D$2:$F$271,3, FALSE) -> La modification d'un des éléments constitutifs de la convention doit faire l'objet d'un avenant à cette convention. | AR3: MAD_I_025 | AS3: =VLOOKUP(AR3,'Axe 2 Règles de gestion'!$D$2:$F$271,3, FALSE) -> Tout avenant implique la même procédure notamment l'accord de l'agent et du (ou des) organisme(s) d'accueil, les arrêtés ou les décisions. | AT3: MAD_I_027 | AU3: =VLOOKUP(AT3,'Axe 2 Règles de gestion'!$D$2:$F$271,3, FALSE) -> Les avenants à la convention doivent être transmis à l'agent avant signature. | BB3: MAD_D_011 | BC3: =VLOOKUP(BB3,'Axe 2 Règles de gestion'!$D$2:$F$271,3, FALSE) -> La durée prévisionnelle est fixée à 3 ans maximum renouvelable pour chaque période. | BD3: MAD_D_411 | BE3: =VLOOKUP(BD3,'Axe 2 Règles de gestion'!$D$2:$F$271,3, FALSE) -> La durée réelle est fixée à 3 ans maximum renouvelable pour chaque période. | BF3: MAD_D_001 | BG3: =VLOOKUP(BF3,'Axe 2 Règles de gestion'!$D$2:$F$271,3, FALSE) -> L'agent doit être en activité. | BR3: POS_C_004 | BS3: =VLOOKUP(BR3,'Axe 2 Règles de gestion'!$D$2:$F$271,3, FALSE) -> La date de début de position doit être antérieure ou égale à la date de fin prévisionnelle de position. | BT3: POS_C_005 | BU3: =VLOOKUP(BT3,'Axe 2 Règles de gestion'!$D$2:$F$271,3, FALSE) -> La date de début de la position doit être postérieure ou égale à la date d'entrée dans la FPE ou dans la carrière militaire. | BV3: POS_C_007 | BW3: =VLOOKUP(BV3,'Axe 2 Règles de gestion'!$D$2:$F$271,3, FALSE) -> La date de fin réelle de la position doit être antérieure à la date limite de départ à la retraite. | BX3: POS_C_010 | BY3: =VLOOKUP(BX3,'Axe 2 Règles de gestion'!$D$2:$F$271,3, FALSE) -> La date de début de position doit être antérieure ou égale à la date de fin réelle de position. | BZ3: POS_C_012 | CA3: =VLOOKUP(BZ3,'Axe 2 Règles de gestion'!$D$2:$F$271,3, FALSE) -> La date de fin prévisionnelle de la position doit être antérieure à la date limite de départ à la retraite. | CB3: POS_C_022 | CC3: =VLOOKUP(CB3,'Axe 2 Règles de gestion'!$D$2:$F$271,3, FALSE) -> La date de début de position est à J+1 de la date de fin de position de l'occurrence précédente. | CD3: POS_C_037 | CE3: =VLOOKUP(CD3,'Axe 2 Règles de gestion'!$D$2:$F$271,3, FALSE) -> Les champs "Type d'organisme d'accueil" et "Pays" de l'organisme d'accueil doivent être renseignés. | CF3: POS_C_111 | CG3: =VLOOKUP(CF3,'Axe 2 Règles de gestion'!$D$2:$F$271,3, FALSE) -> La date de fin ou la date de fin prévisionnelle doit être saisie. | CH3: POS_C_431 | CI3: =VLOOKUP(CH3,'Axe 2 Règles de gestion'!$D$2:$F$271,3, FALSE) -> Les champs "Ministère (ou institution de la République) d'accueil", "Corps d'accueil en détachement" et "Grade d'accueil en détachement" ou "Ministère (ou institution de la République) d'accueil", "Emploi fonctionnel d'accueil en détachement" et "Groupe dans un emploi fonctionnel d'accueil" sont renseignés si le "Type d'organisme d'accueil" est valorisé à FPE. | CJ3: POS_C_434 | CK3: =VLOOKUP(CJ3,'Axe 2 Règles de gestion'!$D$2:$F$271,3, FALSE) -> Le champ "Organisme d'accueil" doit être alimenté si le type d'organisme d'accueil est égal à 'Autre organisme', 'Fonction publique d'un état de l'Union Européenne' ou 'Fonction publique Européenne'.
A4: 23.00.00 | B4: M | C4: 45071.722 | D4: D0004 | E4: Position | F4: S0017 | G4: Mise à disposition sortante | H4: E0202 | I4: MAD sortante à titre gratuit auprès d'une autre administration ou d'un EPA de l'Etat | J4: Position administrative saisie égale à 'MAD sortante à titre gratuit auprès d'une autre administration ou d'un EPA de l'Etat' | K4: A_POS_POSIAD [Saisi] = 'MAD11' | L4: T0593 | M4: MADS à titre gratuit auprès d'une autre administration ou d'un EPA de l'Etat - Renouvellement | N4: Création Modification | O4: Indicateur Renouvellement Position est activé ET l'indicateur de renouvellement saisi est différent de l'indicateur de renouvellement avant saisie | P4: A_POS_INDREN [Saisi] = '1' ET A_POS_INDREN [Saisi] <> A_POS_INDREN [Valeur avant saisie] | Q4: Titulaire ou magistrat | R4: P0001 | S4: Général | T4: Passant | U4: 40725 | V4: 44497 | W4: MAD_I_005 ET MAD_I_006 ET MAD_I_026 ET MAD_I_025 ET MAD_I_027 ET MAD_D_011 ET MAD_D_411 ET POS_C_004 ET POS_C_005 ET POS_C_007 ET POS_C_010 ET POS_C_012 ET POS_C_022 ET POS_C_037 ET POS_C_111 ET POS_C_431 ET POS_C_434 | X4: MAD_I_005 | Y4: =VLOOKUP(X4,'Axe 2 Règles de gestion'!$D$2:$F$271,3, FALSE) -> L'accord de l'agent est nécessaire. | Z4: MAD_I_006 | AA4: =VLOOKUP(Z4,'Axe 2 Règles de gestion'!$D$2:$F$271,3, FALSE) -> L'accord du ou des organismes d'accueil est nécessaire. | AB4: MAD_I_026 | AC4: =VLOOKUP(AB4,'Axe 2 Règles de gestion'!$D$2:$F$271,3, FALSE) -> La modification d'un des éléments constitutifs de la convention doit faire l'objet d'un avenant à cette convention. | AD4: MAD_I_025 | AE4: =VLOOKUP(AD4,'Axe 2 Règles de gestion'!$D$2:$F$271,3, FALSE) -> Tout avenant implique la même procédure notamment l'accord de l'agent et du (ou des) organisme(s) d'accueil, les arrêtés ou les décisions. | AF4: MAD_I_027 | AG4: =VLOOKUP(AF4,'Axe 2 Règles de gestion'!$D$2:$F$271,3, FALSE) -> Les avenants à la convention doivent être transmis à l'agent avant signature. | BB4: MAD_D_011 | BC4: =VLOOKUP(BB4,'Axe 2 Règles de gestion'!$D$2:$F$271,3, FALSE) -> La durée prévisionnelle est fixée à 3 ans maximum renouvelable pour chaque période. | BD4: MAD_D_411 | BE4: =VLOOKUP(BD4,'Axe 2 Règles de gestion'!$D$2:$F$271,3, FALSE) -> La durée réelle est fixée à 3 ans maximum renouvelable pour chaque période. | BR4: POS_C_004 | BS4: =VLOOKUP(BR4,'Axe 2 Règles de gestion'!$D$2:$F$271,3, FALSE) -> La date de début de position doit être antérieure ou égale à la date de fin prévisionnelle de position. | BT4: POS_C_005 | BU4: =VLOOKUP(BT4,'Axe 2 Règles de gestion'!$D$2:$F$271,3, FALSE) -> La date de début de la position doit être postérieure ou égale à la date d'entrée dans la FPE ou dans la carrière militaire. | BV4: POS_C_007 | BW4: =VLOOKUP(BV4,'Axe 2 Règles de gestion'!$D$2:$F$271,3, FALSE) -> La date de fin réelle de la position doit être antérieure à la date limite de départ à la retraite. | BX4: POS_C_010 | BY4: =VLOOKUP(BX4,'Axe 2 Règles de gestion'!$D$2:$F$271,3, FALSE) -> La date de début de position doit être antérieure ou égale à la date de fin réelle de position. | BZ4: POS_C_012 | CA4: =VLOOKUP(BZ4,'Axe 2 Règles de gestion'!$D$2:$F$271,3, FALSE) -> La date de fin prévisionnelle de la position doit être antérieure à la date limite de départ à la retraite. | CB4: POS_C_022 | CC4: =VLOOKUP(CB4,'Axe 2 Règles de gestion'!$D$2:$F$271,3, FALSE) -> La date de début de position est à J+1 de la date de fin de position de l'occurrence précédente. | CD4: POS_C_037 | CE4: =VLOOKUP(CD4,'Axe 2 Règles de gestion'!$D$2:$F$271,3, FALSE) -> Les champs "Type d'organisme d'accueil" et "Pays" de l'organisme d'accueil doivent être renseignés. | CF4: POS_C_111 | CG4: =VLOOKUP(CF4,'Axe 2 Règles de gestion'!$D$2:$F$271,3, FALSE) -> La date de fin ou la date de fin prévisionnelle doit être saisie. | CH4: POS_C_431 | CI4: =VLOOKUP(CH4,'Axe 2 Règles de gestion'!$D$2:$F$271,3, FALSE) -> Les champs "Ministère (ou institution de la République) d'accueil", "Corps d'accueil en détachement" et "Grade d'accueil en détachement" ou "Ministère (ou institution de la République) d'accueil", "Emploi fonctionnel d'accueil en détachement" et "Groupe dans un emploi fonctionnel d'accueil" sont renseignés si le "Type d'organisme d'accueil" est valorisé à FPE. | CJ4: POS_C_434 | CK4: =VLOOKUP(CJ4,'Axe 2 Règles de gestion'!$D$2:$F$271,3, FALSE) -> Le champ "Organisme d'accueil" doit être alimenté si le type d'organisme d'accueil est égal à 'Autre organisme', 'Fonction publique d'un état de l'Union Européenne' ou 'Fonction publique Européenne'.
A5: 23.00.00 | B5: A | C5: 45071.722 | D5: D0004 | E5: Position | F5: S0017 | G5: Mise à disposition sortante | H5: E0202 | I5: MAD sortante à titre gratuit auprès d'une autre administration ou d'un EPA de l'Etat | J5: Position administrative saisie égale à 'MAD sortante à titre gratuit auprès d'une autre administration ou d'un EPA de l'Etat' | K5: A_POS_POSIAD [Saisi] = 'MAD11' | L5: T0593 | M5: MADS à titre gratuit auprès d'une autre administration ou d'un EPA de l'Etat - Renouvellement | N5: Création Modification | O5: Indicateur Renouvellement Position est activé ET l'indicateur de renouvellement saisi est différent de l'indicateur de renouvellement avant saisie | P5: A_POS_INDREN [Saisi] = '1' ET A_POS_INDREN [Saisi] <> A_POS_INDREN [Valeur avant saisie] | Q5: Titulaire ou magistrat | R5: P0001 | S5: Général | T5: Passant | U5: 44498 | W5: MAD_I_005 ET MAD_I_006 ET MAD_I_026 ET MAD_I_025 ET MAD_I_027 ET MAD_D_011 ET MAD_D_411 ET POS_C_004 ET POS_C_005 ET POS_C_007 ET POS_C_010 ET POS_C_012 ET POS_C_022 ET POS_C_037 ET POS_C_111 ET POS_C_431 ET POS_C_434 | X5: MAD_I_005 | Y5: =VLOOKUP(X5,'Axe 2 Règles de gestion'!$D$2:$F$271,3, FALSE) -> L'accord de l'agent est nécessaire. | Z5: MAD_I_006 | AA5: =VLOOKUP(Z5,'Axe 2 Règles de gestion'!$D$2:$F$271,3, FALSE) -> L'accord du ou des organismes d'accueil est nécessaire. | AB5: MAD_I_026 | AC5: =VLOOKUP(AB5,'Axe 2 Règles de gestion'!$D$2:$F$271,3, FALSE) -> La modification d'un des éléments constitutifs de la convention doit faire l'objet d'un avenant à cette convention. | AD5: MAD_I_025 | AE5: =VLOOKUP(AD5,'Axe 2 Règles de gestion'!$D$2:$F$271,3, FALSE) -> Tout avenant implique la même procédure notamment l'accord de l'agent et du (ou des) organisme(s) d'accueil, les arrêtés ou les décisions. | AF5: MAD_I_027 | AG5: =VLOOKUP(AF5,'Axe 2 Règles de gestion'!$D$2:$F$271,3, FALSE) -> Les avenants à la convention doivent être transmis à l'agent avant signature. | BB5: MAD_D_011 | BC5: =VLOOKUP(BB5,'Axe 2 Règles de gestion'!$D$2:$F$271,3, FALSE) -> La durée prévisionnelle est fixée à 3 ans maximum renouvelable pour chaque période. | BD5: MAD_D_411 | BE5: =VLOOKUP(BD5,'Axe 2 Règles de gestion'!$D$2:$F$271,3, FALSE) -> La durée réelle est fixée à 3 ans maximum renouvelable pour chaque période. | BR5: POS_C_004 | BS5: =VLOOKUP(BR5,'Axe 2 Règles de gestion'!$D$2:$F$271,3, FALSE) -> La date de début de position doit être antérieure ou égale à la date de fin prévisionnelle de position. | BT5: POS_C_005 | BU5: =VLOOKUP(BT5,'Axe 2 Règles de gestion'!$D$2:$F$271,3, FALSE) -> La date de début de la position doit être postérieure ou égale à la date d'entrée dans la FPE ou dans la carrière militaire. | BV5: POS_C_007 | BW5: =VLOOKUP(BV5,'Axe 2 Règles de gestion'!$D$2:$F$271,3, FALSE) -> La date de fin réelle de la position doit être antérieure à la date limite de départ à la retraite. | BX5: POS_C_010 | BY5: =VLOOKUP(BX5,'Axe 2 Règles de gestion'!$D$2:$F$271,3, FALSE) -> La date de début de position doit être antérieure ou égale à la date de fin réelle de position. | BZ5: POS_C_012 | CA5: =VLOOKUP(BZ5,'Axe 2 Règles de gestion'!$D$2:$F$271,3, FALSE) -> La date de fin prévisionnelle de la position doit être antérieure à la date limite de départ à la retraite. | CB5: POS_C_022 | CC5: =VLOOKUP(CB5,'Axe 2 Règles de gestion'!$D$2:$F$271,3, FALSE) -> La date de début de position est à J+1 de la date de fin de position de l'occurrence précédente. | CD5: POS_C_037 | CE5: =VLOOKUP(CD5,'Axe 2 Règles de gestion'!$D$2:$F$271,3, FALSE) -> Les champs "Type d'organisme d'accueil" et "Pays" de l'organisme d'accueil doivent être renseignés. | CF5: POS_C_111 | CG5: =VLOOKUP(CF5,'Axe 2 Règles de gestion'!$D$2:$F$271,3, FALSE) -> La date de fin ou la date de fin prévisionnelle doit être saisie. | CH5: POS_C_431 | CI5: =VLOOKUP(CH5,'Axe 2 Règles de gestion'!$D$2:$F$271,3, FALSE) -> Les champs "Ministère (ou institution de la République) d'accueil", "Corps d'accueil en détachement" et "Grade d'accueil en détachement" ou "Ministère (ou institution de la République) d'accueil", "Emploi fonctionnel d'accueil en détachement" et "Groupe dans un emploi fonctionnel d'accueil" sont renseignés si le "Type d'organisme d'accueil" est valorisé à FPE. | CJ5: POS_C_434 | CK5: =VLOOKUP(CJ5,'Axe 2 Règles de gestion'!$D$2:$F$271,3, FALSE) -> Le champ "Organisme d'accueil" doit être alimenté si le type d'organisme d'accueil est égal à 'Autre organisme', 'Fonction publique d'un état de l'Union Européenne' ou 'Fonction publique Européenne'.
A6: 20.00.00 | B6: M | C6: 43152.5 | D6: D0004 | E6: Position | F6: S0017 | G6: Mise à disposition sortante | H6: E0202 | I6: MAD sortante à titre gratuit auprès d'une autre administration ou d'un EPA de l'Etat | J6: Position administrative saisie égale à 'MAD sortante à titre gratuit auprès d'une autre administration ou d'un EPA de l'Etat' | K6: A_POS_POSIAD [Saisi] = 'MAD11' | L6: T0594 | M6: MADS à titre gratuit auprès d'une autre administration ou d'un EPA de l'Etat - Fin | N6: Modification | O6: L'indicateur de renouvellement saisi est égal à l'indicateur de renouvellement avant saisie | P6: A_POS_INDREN [Saisi] = A_POS_INDREN [Valeur avant saisie] | Q6: Titulaire ou magistrat | R6: P0001 | S6: Général | T6: Passant | U6: 40725 | W6: MAD_I_028 ET MAD_I_029 ET MAD_I_030 ET MAD_I_031 ET MAD_I_032 ET MAD_I_034 ET MAD_D_011 ET MAD_D_411 ET POS_C_004 ET POS_C_007 ET POS_C_010 ET POS_C_012 ET POS_C_037 ET POS_C_111 ET POS_C_431 ET POS_C_434 | X6: MAD_I_028 | Y6: =VLOOKUP(X6,'Axe 2 Règles de gestion'!$D$2:$F$271,3, FALSE) -> La mise à disposition peut prendre fin de manière anticipée à l'initiative de l'agent, de l'administration d'origine ou de l'organisme d'accueil. | Z6: MAD_I_029 | AA6: =VLOOKUP(Z6,'Axe 2 Règles de gestion'!$D$2:$F$271,3, FALSE) -> En cas de pluralité d'organismes d'accueil, la fin anticipée de la mise à disposition peut s'appliquer vis-à-vis d'une partie seulement d'entre eux. Dans ce cas, les autres organismes d'accueil doivent en être informés. | AB6: MAD_I_030 | AC6: =VLOOKUP(AB6,'Axe 2 Règles de gestion'!$D$2:$F$271,3, FALSE) -> Si un préavis est prévu dans la convention, il doit être respecté. | AD6: MAD_I_031 | AE6: =VLOOKUP(AD6,'Axe 2 Règles de gestion'!$D$2:$F$271,3, FALSE) -> En cas de faute disciplinaire, la mise à disposition peut prendre fin sans préavis par accord entre l'administration d'origine et l'organisme d'accueil. | AF6: MAD_I_032 | AG6: =VLOOKUP(AF6,'Axe 2 Règles de gestion'!$D$2:$F$271,3, FALSE) -> L'agent est affecté soit aux mêmes fonctions dans son service d'origine soit dans l'un des emplois que son grade lui donne vocation à occuper. | AH6: MAD_I_034 | AI6: =VLOOKUP(AH6,'Axe 2 Règles de gestion'!$D$2:$F$271,3, FALSE) -> L'agent mis à disposition qui accepte la proposition d'intégration émise par son administration d'accueil est intégré dans un corps comparable à son corps d'origine. | BB6: MAD_D_011 | BC6: =VLOOKUP(BB6,'Axe 2 Règles de gestion'!$D$2:$F$271,3, FALSE) -> La durée prévisionnelle est fixée à 3 ans maximum renouvelable pour chaque période. | BD6: MAD_D_411 | BE6: =VLOOKUP(BD6,'Axe 2 Règles de gestion'!$D$2:$F$271,3, FALSE) -> La durée réelle est fixée à 3 ans maximum renouvelable pour chaque période. | BR6: POS_C_004 | BS6: =VLOOKUP(BR6,'Axe 2 Règles de gestion'!$D$2:$F$271,3, FALSE) -> La date de début de position doit être antérieure ou égale à la date de fin prévisionnelle de position. | BT6: POS_C_007 | BU6: =VLOOKUP(BT6,'Axe 2 Règles de gestion'!$D$2:$F$271,3, FALSE) -> La date de fin réelle de la position doit être antérieure à la date limite de départ à la retraite. | BV6: POS_C_010 | BW6: =VLOOKUP(BV6,'Axe 2 Règles de gestion'!$D$2:$F$271,3, FALSE) -> La date de début de position doit être antérieure ou égale à la date de fin réelle de position. | BX6: POS_C_012 | BY6: =VLOOKUP(BX6,'Axe 2 Règles de gestion'!$D$2:$F$271,3, FALSE) -> La date de fin prévisionnelle de la position doit être antérieure à la date limite de départ à la retraite. | BZ6: POS_C_037 | CA6: =VLOOKUP(BZ6,'Axe 2 Règles de gestion'!$D$2:$F$271,3, FALSE) -> Les champs "Type d'organisme d'accueil" et "Pays" de l'organisme d'accueil doivent être renseignés. | CB6: POS_C_111 | CC6: =VLOOKUP(CB6,'Axe 2 Règles de gestion'!$D$2:$F$271,3, FALSE) -> La date de fin ou la date de fin prévisionnelle doit être saisie. | CD6: POS_C_431 | CE6: =VLOOKUP(CD6,'Axe 2 Règles de gestion'!$D$2:$F$271,3, FALSE) -> Les champs "Ministère (ou institution de la République) d'accueil", "Corps d'accueil en détachement" et "Grade d'accueil en détachement" ou "Ministère (ou institution de la République) d'accueil", "Emploi fonctionnel d'accueil en détachement" et "Groupe dans un emploi fonctionnel d'accueil" sont renseignés si le "Type d'organisme d'accueil" est valorisé à FPE. | CF6: POS_C_434 | CG6: =VLOOKUP(CF6,'Axe 2 Règles de gestion'!$D$2:$F$271,3, FALSE) -> Le champ "Organisme d'accueil" doit être alimenté si le type d'organisme d'accueil est égal à 'Autre organisme', 'Fonction publique d'un état de l'Union Européenne' ou 'Fonction publique Européenne'.
A7: 20.00.00 | B7: M | C7: 43152.5 | D7: D0004 | E7: Position | F7: S0017 | G7: Mise à disposition sortante | H7: E0202 | I7: MAD sortante à titre gratuit auprès d'une autre administration ou d'un EPA de l'Etat | J7: Position administrative saisie égale à 'MAD sortante à titre gratuit auprès d'une autre administration ou d'un EPA de l'Etat' | K7: A_POS_POSIAD [Saisi] = 'MAD11' | L7: T0592 | M7: MADS à titre gratuit auprès d'une autre administration ou d'un EPA de l'Etat - Demande | N7: Création Modification | O7: Indicateur Renouvellement Position est non activé ET l'indicateur de renouvellement saisi est différent de l'indicateur de renouvellement avant saisie | P7: A_POS_INDREN [Saisi] = '0' ET A_POS_INDREN [Saisi] <> A_POS_INDREN [Valeur avant saisie] | Q7: Contractuel | R7: P0003 | S7: Général | T7: Passant | U7: 40725 | V7: 41721 | W7: MAD_D_019 ET MAD_D_816 ET MAD_D_014 ET POS_C_100 ET POS_C_004 ET POS_C_006 ET POS_C_007 ET POS_C_009 ET POS_C_010 ET POS_C_012 ET POS_C_022 ET POS_C_037 ET POS_C_106 ET POS_C_111 ET POS_C_431 ET POS_C_434 | BB7: MAD_D_019 | BC7: =VLOOKUP(BB7,'Axe 2 Règles de gestion'!$D$2:$F$271,3, FALSE) -> La durée prévisionnelle est fixée à 3 ans maximum renouvelable pour chaque période. | BD7: MAD_D_816 | BE7: =VLOOKUP(BD7,'Axe 2 Règles de gestion'!$D$2:$F$271,3, FALSE) -> La durée réelle est fixée à 3 ans maximum renouvelable pour chaque période. | BF7: MAD_D_014 | BG7: =VLOOKUP(BF7,'Axe 2 Règles de gestion'!$D$2:$F$271,3, FALSE) -> Le type de contrat doit être un CDI. | BR7: POS_C_100 | BS7: =VLOOKUP(BR7,'Axe 2 Règles de gestion'!$D$2:$F$271,3, FALSE) -> Lors de la demande initiale, l'agent doit être en activité. | BT7: POS_C_004 | BU7: =VLOOKUP(BT7,'Axe 2 Règles de gestion'!$D$2:$F$271,3, FALSE) -> La date de début de position doit être antérieure ou égale à la date de fin prévisionnelle de position. | BV7: POS_C_006 | BW7: =VLOOKUP(BV7,'Axe 2 Règles de gestion'!$D$2:$F$271,3, FALSE) -> La date de fin réelle de la position doit être antérieure ou égale à la date de fin réelle ou prévisionnelle du lien juridique. | BX7: POS_C_007 | BY7: =VLOOKUP(BX7,'Axe 2 Règles de gestion'!$D$2:$F$271,3, FALSE) -> La date de fin réelle de la position doit être antérieure à la date limite de départ à la retraite. | BZ7: POS_C_009 | CA7: =VLOOKUP(BZ7,'Axe 2 Règles de gestion'!$D$2:$F$271,3, FALSE) -> La date de début de la position doit être postérieure ou égale à la date de début du lien juridique. | CB7: POS_C_010 | CC7: =VLOOKUP(CB7,'Axe 2 Règles de gestion'!$D$2:$F$271,3, FALSE) -> La date de début de position doit être antérieure ou égale à la date de fin réelle de position. | CD7: POS_C_012 | CE7: =VLOOKUP(CD7,'Axe 2 Règles de gestion'!$D$2:$F$271,3, FALSE) -> La date de fin prévisionnelle de la position doit être antérieure à la date limite de départ à la retraite. | CF7: POS_C_022 | CG7: =VLOOKUP(CF7,'Axe 2 Règles de gestion'!$D$2:$F$271,3, FALSE) -> La date de début de position est à J+1 de la date de fin de position de l'occurrence précédente. | CH7: POS_C_037 | CI7: =VLOOKUP(CH7,'Axe 2 Règles de gestion'!$D$2:$F$271,3, FALSE) -> Les champs "Type d'organisme d'accueil" et "Pays" de l'organisme d'accueil doivent être renseignés. | CJ7: POS_C_106 | CK7: =VLOOKUP(CJ7,'Axe 2 Règles de gestion'!$D$2:$F$271,3, FALSE) -> La date de fin prévisionnelle de la position doit être antérieure ou égale à la date de fin réelle ou prévisionnelle du lien juridique. | CL7: POS_C_111 | CM7: =VLOOKUP(CL7,'Axe 2 Règles de gestion'!$D$2:$F$271,3, FALSE) -> La date de fin ou la date de fin prévisionnelle doit être saisie. | CN7: POS_C_431 | CO7: =VLOOKUP(CN7,'Axe 2 Règles de gestion'!$D$2:$F$271,3, FALSE) -> Les champs "Ministère (ou institution de la République) d'accueil", "Corps d'accueil en détachement" et "Grade d'accueil en détachement" ou "Ministère (ou institution de la République) d'accueil", "Emploi fonctionnel d'accueil en détachement" et "Groupe dans un emploi fonctionnel d'accueil" sont renseignés si le "Type d'organisme d'accueil" est valorisé à FPE. | CP7: POS_C_434 | CQ7: =VLOOKUP(CP7,'Axe 2 Règles de gestion'!$D$2:$F$271,3, FALSE) -> Le champ "Organisme d'accueil" doit être alimenté si le type d'organisme d'accueil est égal à 'Autre organisme', 'Fonction publique d'un état de l'Union Européenne' ou 'Fonction publique Européenne'.
A8: 22.10.00 | B8: M | C8: 44832.36 | D8: D0004 | E8: Position | F8: S0017 | G8: Mise à disposition sortante | H8: E0202 | I8: MAD sortante à titre gratuit auprès d'une autre administration ou d'un EPA de l'Etat | J8: Position administrative saisie égale à 'MAD sortante à titre gratuit auprès d'une autre administration ou d'un EPA de l'Etat' | K8: A_POS_POSIAD [Saisi] = 'MAD11' | L8: T0592 | M8: MADS à titre gratuit auprès d'une autre administration ou d'un EPA de l'Etat - Demande | N8: Création Modification | O8: Indicateur Renouvellement Position est non activé ET l'indicateur de renouvellement saisi est différent de l'indicateur de renouvellement avant saisie | P8: A_POS_INDREN [Saisi] = '0' ET A_POS_INDREN [Saisi] <> A_POS_INDREN [Valeur avant saisie] | Q8: Contractuel | R8: P0003 | S8: Général | T8: Passant | U8: 41722 | V8: 44677 | W8: MAD_I_012 ET MAD_I_013 ET MAD_I_014 ET MAD_D_019 ET MAD_D_816 ET MAD_D_014 ET POS_C_100 ET POS_C_004 ET POS_C_006 ET POS_C_007 ET POS_C_009 ET POS_C_010 ET POS_C_012 ET POS_C_022 ET POS_C_037 ET POS_C_106 ET POS_C_111 ET POS_C_431 ET POS_C_434 | X8: MAD_I_012 | Y8: =VLOOKUP(X8,'Axe 2 Règles de gestion'!$D$2:$F$271,3, FALSE) -> L'accord de l'agent est nécessaire. | Z8: MAD_I_013 | AA8: =VLOOKUP(Z8,'Axe 2 Règles de gestion'!$D$2:$F$271,3, FALSE) -> L'accord du ou des organismes d'accueil est nécessaire. | AB8: MAD_I_014 | AC8: =VLOOKUP(AB8,'Axe 2 Règles de gestion'!$D$2:$F$271,3, FALSE) -> Une convention entre l'organisme d'origine et l'organisme d'accueil doit être signée. | BB8: MAD_D_019 | BC8: =VLOOKUP(BB8,'Axe 2 Règles de gestion'!$D$2:$F$271,3, FALSE) -> La durée prévisionnelle est fixée à 3 ans maximum renouvelable pour chaque période. | BD8: MAD_D_816 | BE8: =VLOOKUP(BD8,'Axe 2 Règles de gestion'!$D$2:$F$271,3, FALSE) -> La durée réelle est fixée à 3 ans maximum renouvelable pour chaque période. | BF8: MAD_D_014 | BG8: =VLOOKUP(BF8,'Axe 2 Règles de gestion'!$D$2:$F$271,3, FALSE) -> Le type de contrat doit être un CDI. | BR8: POS_C_100 | BS8: =VLOOKUP(BR8,'Axe 2 Règles de gestion'!$D$2:$F$271,3, FALSE) -> Lors de la demande initiale, l'agent doit être en activité. | BT8: POS_C_004 | BU8: =VLOOKUP(BT8,'Axe 2 Règles de gestion'!$D$2:$F$271,3, FALSE) -> La date de début de position doit être antérieure ou égale à la date de fin prévisionnelle de position. | BV8: POS_C_006 | BW8: =VLOOKUP(BV8,'Axe 2 Règles de gestion'!$D$2:$F$271,3, FALSE) -> La date de fin réelle de la position doit être antérieure ou égale à la date de fin réelle ou prévisionnelle du lien juridique. | BX8: POS_C_007 | BY8: =VLOOKUP(BX8,'Axe 2 Règles de gestion'!$D$2:$F$271,3, FALSE) -> La date de fin réelle de la position doit être antérieure à la date limite de départ à la retraite. | BZ8: POS_C_009 | CA8: =VLOOKUP(BZ8,'Axe 2 Règles de gestion'!$D$2:$F$271,3, FALSE) -> La date de début de la position doit être postérieure ou égale à la date de début du lien juridique. | CB8: POS_C_010 | CC8: =VLOOKUP(CB8,'Axe 2 Règles de gestion'!$D$2:$F$271,3, FALSE) -> La date de début de position doit être antérieure ou égale à la date de fin réelle de position. | CD8: POS_C_012 | CE8: =VLOOKUP(CD8,'Axe 2 Règles de gestion'!$D$2:$F$271,3, FALSE) -> La date de fin prévisionnelle de la position doit être antérieure à la date limite de départ à la retraite. | CF8: POS_C_022 | CG8: =VLOOKUP(CF8,'Axe 2 Règles de gestion'!$D$2:$F$271,3, FALSE) -> La date de début de position est à J+1 de la date de fin de position de l'occurrence précédente. | CH8: POS_C_037 | CI8: =VLOOKUP(CH8,'Axe 2 Règles de gestion'!$D$2:$F$271,3, FALSE) -> Les champs "Type d'organisme d'accueil" et "Pays" de l'organisme d'accueil doivent être renseignés. | CJ8: POS_C_106 | CK8: =VLOOKUP(CJ8,'Axe 2 Règles de gestion'!$D$2:$F$271,3, FALSE) -> La date de fin prévisionnelle de la position doit être antérieure ou égale à la date de fin réelle ou prévisionnelle du lien juridique. | CL8: POS_C_111 | CM8: =VLOOKUP(CL8,'Axe 2 Règles de gestion'!$D$2:$F$271,3, FALSE) -> La date de fin ou la date de fin prévisionnelle doit être saisie. | CN8: POS_C_431 | CO8: =VLOOKUP(CN8,'Axe 2 Règles de gestion'!$D$2:$F$271,3, FALSE) -> Les champs "Ministère (ou institution de la République) d'accueil", "Corps d'accueil en détachement" et "Grade d'accueil en détachement" ou "Ministère (ou institution de la République) d'accueil", "Emploi fonctionnel d'accueil en détachement" et "Groupe dans un emploi fonctionnel d'accueil" sont renseignés si le "Type d'organisme d'accueil" est valorisé à FPE. | CP8: POS_C_434 | CQ8: =VLOOKUP(CP8,'Axe 2 Règles de gestion'!$D$2:$F$271,3, FALSE) -> Le champ "Organisme d'accueil" doit être alimenté si le type d'organisme d'accueil est égal à 'Autre organisme', 'Fonction publique d'un état de l'Union Européenne' ou 'Fonction publique Européenne'.
A9: 22.10.00 | B9: A | C9: 44832.361 | D9: D0004 | E9: Position | F9: S0017 | G9: Mise à disposition sortante | H9: E0202 | I9: MAD sortante à titre gratuit auprès d'une autre administration ou d'un EPA de l'Etat | J9: Position administrative saisie égale à 'MAD sortante à titre gratuit auprès d'une autre administration ou d'un EPA de l'Etat' | K9: A_POS_POSIAD [Saisi] = 'MAD11' | L9: T0592 | M9: MADS à titre gratuit auprès d'une autre administration ou d'un EPA de l'Etat - Demande | N9: Création Modification | O9: Indicateur Renouvellement Position est non activé ET l'indicateur de renouvellement saisi est différent de l'indicateur de renouvellement avant saisie | P9: A_POS_INDREN [Saisi] = '0' ET A_POS_INDREN [Saisi] <> A_POS_INDREN [Valeur avant saisie] | Q9: Contractuel | R9: P0003 | S9: Général | T9: Passant | U9: 44678 | W9: MAD_I_021 ET MAD_I_012 ET MAD_I_013 ET MAD_I_014 ET MAD_D_019 ET MAD_D_816 ET MAD_D_014 ET POS_C_100 ET POS_C_004 ET POS_C_006 ET POS_C_007 ET POS_C_009 ET POS_C_010 ET POS_C_012 ET POS_C_022 ET POS_C_037 ET POS_C_106 ET POS_C_111 ET POS_C_431 ET POS_C_434 | X9: MAD_I_021 | Y9: =VLOOKUP(X9,'Axe 2 Règles de gestion'!$D$2:$F$271,3, FALSE) -> L'agent peut être mis à disposition d'un ou plusieurs organismes d'accueil. | Z9: MAD_I_012 | AA9: =VLOOKUP(Z9,'Axe 2 Règles de gestion'!$D$2:$F$271,3, FALSE) -> L'accord de l'agent est nécessaire. | AB9: MAD_I_013 | AC9: =VLOOKUP(AB9,'Axe 2 Règles de gestion'!$D$2:$F$271,3, FALSE) -> L'accord du ou des organismes d'accueil est nécessaire. | AD9: MAD_I_014 | AE9: =VLOOKUP(AD9,'Axe 2 Règles de gestion'!$D$2:$F$271,3, FALSE) -> Une convention entre l'organisme d'origine et l'organisme d'accueil doit être signée. | BB9: MAD_D_019 | BC9: =VLOOKUP(BB9,'Axe 2 Règles de gestion'!$D$2:$F$271,3, FALSE) -> La durée prévisionnelle est fixée à 3 ans maximum renouvelable pour chaque période. | BD9: MAD_D_816 | BE9: =VLOOKUP(BD9,'Axe 2 Règles de gestion'!$D$2:$F$271,3, FALSE) -> La durée réelle est fixée à 3 ans maximum renouvelable pour chaque période. | BF9: MAD_D_014 | BG9: =VLOOKUP(BF9,'Axe 2 Règles de gestion'!$D$2:$F$271,3, FALSE) -> Le type de contrat doit être un CDI. | BR9: POS_C_100 | BS9: =VLOOKUP(BR9,'Axe 2 Règles de gestion'!$D$2:$F$271,3, FALSE) -> Lors de la demande initiale, l'agent doit être en activité. | BT9: POS_C_004 | BU9: =VLOOKUP(BT9,'Axe 2 Règles de gestion'!$D$2:$F$271,3, FALSE) -> La date de début de position doit être antérieure ou égale à la date de fin prévisionnelle de position. | BV9: POS_C_006 | BW9: =VLOOKUP(BV9,'Axe 2 Règles de gestion'!$D$2:$F$271,3, FALSE) -> La date de fin réelle de la position doit être antérieure ou égale à la date de fin réelle ou prévisionnelle du lien juridique. | BX9: POS_C_007 | BY9: =VLOOKUP(BX9,'Axe 2 Règles de gestion'!$D$2:$F$271,3, FALSE) -> La date de fin réelle de la position doit être antérieure à la date limite de départ à la retraite. | BZ9: POS_C_009 | CA9: =VLOOKUP(BZ9,'Axe 2 Règles de gestion'!$D$2:$F$271,3, FALSE) -> La date de début de la position doit être postérieure ou égale à la date de début du lien juridique. | CB9: POS_C_010 | CC9: =VLOOKUP(CB9,'Axe 2 Règles de gestion'!$D$2:$F$271,3, FALSE) -> La date de début de position doit être antérieure ou égale à la date de fin réelle de position. | CD9: POS_C_012 | CE9: =VLOOKUP(CD9,'Axe 2 Règles de gestion'!$D$2:$F$271,3, FALSE) -> La date de fin prévisionnelle de la position doit être antérieure à la date limite de départ à la retraite. | CF9: POS_C_022 | CG9: =VLOOKUP(CF9,'Axe 2 Règles de gestion'!$D$2:$F$271,3, FALSE) -> La date de début de position est à J+1 de la date de fin de position de l'occurrence précédente. | CH9: POS_C_037 | CI9: =VLOOKUP(CH9,'Axe 2 Règles de gestion'!$D$2:$F$271,3, FALSE) -> Les champs "Type d'organisme d'accueil" et "Pays" de l'organisme d'accueil doivent être renseignés. | CJ9: POS_C_106 | CK9: =VLOOKUP(CJ9,'Axe 2 Règles de gestion'!$D$2:$F$271,3, FALSE) -> La date de fin prévisionnelle de la position doit être antérieure ou égale à la date de fin réelle ou prévisionnelle du lien juridique. | CL9: POS_C_111 | CM9: =VLOOKUP(CL9,'Axe 2 Règles de gestion'!$D$2:$F$271,3, FALSE) -> La date de fin ou la date de fin prévisionnelle doit être saisie. | CN9: POS_C_431 | CO9: =VLOOKUP(CN9,'Axe 2 Règles de gestion'!$D$2:$F$271,3, FALSE) -> Les champs "Ministère (ou institution de la République) d'accueil", "Corps d'accueil en détachement" et "Grade d'accueil en détachement" ou "Ministère (ou institution de la République) d'accueil", "Emploi fonctionnel d'accueil en détachement" et "Groupe dans un emploi fonctionnel d'accueil" sont renseignés si le "Type d'organisme d'accueil" est valorisé à FPE. | CP9: POS_C_434 | CQ9: =VLOOKUP(CP9,'Axe 2 Règles de gestion'!$D$2:$F$271,3, FALSE) -> Le champ "Organisme d'accueil" doit être alimenté si le type d'organisme d'accueil est égal à 'Autre organisme', 'Fonction publique d'un état de l'Union Européenne' ou 'Fonction publique Européenne'.
A10: 20.00.00 | B10: M | C10: 43152.5 | D10: D0004 | E10: Position | F10: S0017 | G10: Mise à disposition sortante | H10: E0202 | I10: MAD sortante à titre gratuit auprès d'une autre administration ou d'un EPA de l'Etat | J10: Position administrative saisie égale à 'MAD sortante à titre gratuit auprès d'une autre administration ou d'un EPA de l'Etat' | K10: A_POS_POSIAD [Saisi] = 'MAD11' | L10: T0593 | M10: MADS à titre gratuit auprès d'une autre administration ou d'un EPA de l'Etat - Renouvellement | N10: Création Modification | O10: Indicateur Renouvellement Position est activé ET l'indicateur de renouvellement saisi est différent de l'indicateur de renouvellement avant saisie | P10: A_POS_INDREN [Saisi] = '1' ET A_POS_INDREN [Saisi] <> A_POS_INDREN [Valeur avant saisie] | Q10: Contractuel | R10: P0003 | S10: Général | T10: Passant | U10: 40725 | V10: 41721 | W10: MAD_D_019 ET MAD_D_816 ET MAD_D_014 ET MAD_D_039 ET MAD_D_817 ET POS_C_004 ET POS_C_006 ET POS_C_007 ET POS_C_009 ET POS_C_010 ET POS_C_012 ET POS_C_022 ET POS_C_037 ET POS_C_106 ET POS_C_111 ET POS_C_431 ET POS_C_434 | BB10: MAD_D_019 | BC10: =VLOOKUP(BB10,'Axe 2 Règles de gestion'!$D$2:$F$271,3, FALSE) -> La durée prévisionnelle est fixée à 3 ans maximum renouvelable pour chaque période. | BD10: MAD_D_816 | BE10: =VLOOKUP(BD10,'Axe 2 Règles de gestion'!$D$2:$F$271,3, FALSE) -> La durée réelle est fixée à 3 ans maximum renouvelable pour chaque période. | BF10: MAD_D_014 | BG10: =VLOOKUP(BF10,'Axe 2 Règles de gestion'!$D$2:$F$271,3, FALSE) -> Le type de contrat doit être un CDI. | BH10: MAD_D_039 | BI10: =VLOOKUP(BH10,'Axe 2 Règles de gestion'!$D$2:$F$271,3, FALSE) -> La durée totale prévisionnelle de la mise à disposition ne peut excéder 6 années consécutives. | BJ10: MAD_D_817 | BK10: =VLOOKUP(BJ10,'Axe 2 Règles de gestion'!$D$2:$F$271,3, FALSE) -> La durée totale réelle de la mise à disposition ne peut excéder 6 années consécutives. | BR10: POS_C_004 | BS10: =VLOOKUP(BR10,'Axe 2 Règles de gestion'!$D$2:$F$271,3, FALSE) -> La date de début de position doit être antérieure ou égale à la date de fin prévisionnelle de position. | BT10: POS_C_006 | BU10: =VLOOKUP(BT10,'Axe 2 Règles de gestion'!$D$2:$F$271,3, FALSE) -> La date de fin réelle de la position doit être antérieure ou égale à la date de fin réelle ou prévisionnelle du lien juridique. | BV10: POS_C_007 | BW10: =VLOOKUP(BV10,'Axe 2 Règles de gestion'!$D$2:$F$271,3, FALSE) -> La date de fin réelle de la position doit être antérieure à la date limite de départ à la retraite. | BX10: POS_C_009 | BY10: =VLOOKUP(BX10,'Axe 2 Règles de gestion'!$D$2:$F$271,3, FALSE) -> La date de début de la position doit être postérieure ou égale à la date de début du lien juridique. | BZ10: POS_C_010 | CA10: =VLOOKUP(BZ10,'Axe 2 Règles de gestion'!$D$2:$F$271,3, FALSE) -> La date de début de position doit être antérieure ou égale à la date de fin réelle de position. | CB10: POS_C_012 | CC10: =VLOOKUP(CB10,'Axe 2 Règles de gestion'!$D$2:$F$271,3, FALSE) -> La date de fin prévisionnelle de la position doit être antérieure à la date limite de départ à la retraite. | CD10: POS_C_022 | CE10: =VLOOKUP(CD10,'Axe 2 Règles de gestion'!$D$2:$F$271,3, FALSE) -> La date de début de position est à J+1 de la date de fin de position de l'occurrence précédente. | CF10: POS_C_037 | CG10: =VLOOKUP(CF10,'Axe 2 Règles de gestion'!$D$2:$F$271,3, FALSE) -> Les champs "Type d'organisme d'accueil" et "Pays" de l'organisme d'accueil doivent être renseignés. | CH10: POS_C_106 | CI10: =VLOOKUP(CH10,'Axe 2 Règles de gestion'!$D$2:$F$271,3, FALSE) -> La date de fin prévisionnelle de la position doit être antérieure ou égale à la date de fin réelle ou prévisionnelle du lien juridique. | CJ10: POS_C_111 | CK10: =VLOOKUP(CJ10,'Axe 2 Règles de gestion'!$D$2:$F$271,3, FALSE) -> La date de fin ou la date de fin prévisionnelle doit être saisie. | CL10: POS_C_431 | CM10: =VLOOKUP(CL10,'Axe 2 Règles de gestion'!$D$2:$F$271,3, FALSE) -> Les champs "Ministère (ou institution de la République) d'accueil", "Corps d'accueil en détachement" et "Grade d'accueil en détachement" ou "Ministère (ou institution de la République) d'accueil", "Emploi fonctionnel d'accueil en détachement" et "Groupe dans un emploi fonctionnel d'accueil" sont renseignés si le "Type d'organisme d'accueil" est valorisé à FPE. | CN10: POS_C_434 | CO10: =VLOOKUP(CN10,'Axe 2 Règles de gestion'!$D$2:$F$271,3, FALSE) -> Le champ "Organisme d'accueil" doit être alimenté si le type d'organisme d'accueil est égal à 'Autre organisme', 'Fonction publique d'un état de l'Union Européenne' ou 'Fonction publique Européenne'.
A11: 20.00.00 | B11: M | C11: 43152.5 | D11: D0004 | E11: Position | F11: S0017 | G11: Mise à disposition sortante | H11: E0202 | I11: MAD sortante à titre gratuit auprès d'une autre administration ou d'un EPA de l'Etat | J11: Position administrative saisie égale à 'MAD sortante à titre gratuit auprès d'une autre administration ou d'un EPA de l'Etat' | K11: A_POS_POSIAD [Saisi] = 'MAD11' | L11: T0593 | M11: MADS à titre gratuit auprès d'une autre administration ou d'un EPA de l'Etat - Renouvellement | N11: Création Modification | O11: Indicateur Renouvellement Position est activé ET l'indicateur de renouvellement saisi est différent de l'indicateur de renouvellement avant saisie | P11: A_POS_INDREN [Saisi] = '1' ET A_POS_INDREN [Saisi] <> A_POS_INDREN [Valeur avant saisie] | Q11: Contractuel | R11: P0003 | S11: Général | T11: Passant | U11: 41722 | W11: MAD_D_019 ET MAD_D_816 ET MAD_D_221 ET MAD_D_818 ET MAD_D_014 ET POS_C_004 ET POS_C_006 ET POS_C_007 ET POS_C_009 ET POS_C_010 ET POS_C_012 ET POS_C_022 ET POS_C_037 ET POS_C_106 ET POS_C_111 ET POS_C_431 ET POS_C_434 | BB11: MAD_D_019 | BC11: =VLOOKUP(BB11,'Axe 2 Règles de gestion'!$D$2:$F$271,3, FALSE) -> La durée prévisionnelle est fixée à 3 ans maximum renouvelable pour chaque période. | BD11: MAD_D_816 | BE11: =VLOOKUP(BD11,'Axe 2 Règles de gestion'!$D$2:$F$271,3, FALSE) -> La durée réelle est fixée à 3 ans maximum renouvelable pour chaque période. | BF11: MAD_D_221 | BG11: =VLOOKUP(BF11,'Axe 2 Règles de gestion'!$D$2:$F$271,3, FALSE) -> La durée totale prévisionnelle de la mise à disposition ne peut excéder 10 années consécutives. | BH11: MAD_D_818 | BI11: =VLOOKUP(BH11,'Axe 2 Règles de gestion'!$D$2:$F$271,3, FALSE) -> La durée totale réelle de la mise à disposition ne peut excéder 10 années consécutives. | BJ11: MAD_D_014 | BK11: =VLOOKUP(BJ11,'Axe 2 Règles de gestion'!$D$2:$F$271,3, FALSE) -> Le type de contrat doit être un CDI. | BR11: POS_C_004 | BS11: =VLOOKUP(BR11,'Axe 2 Règles de gestion'!$D$2:$F$271,3, FALSE) -> La date de début de position doit être antérieure ou égale à la date de fin prévisionnelle de position. | BT11: POS_C_006 | BU11: =VLOOKUP(BT11,'Axe 2 Règles de gestion'!$D$2:$F$271,3, FALSE) -> La date de fin réelle de la position doit être antérieure ou égale à la date de fin réelle ou prévisionnelle du lien juridique. | BV11: POS_C_007 | BW11: =VLOOKUP(BV11,'Axe 2 Règles de gestion'!$D$2:$F$271,3, FALSE) -> La date de fin réelle de la position doit être antérieure à la date limite de départ à la retraite. | BX11: POS_C_009 | BY11: =VLOOKUP(BX11,'Axe 2 Règles de gestion'!$D$2:$F$271,3, FALSE) -> La date de début de la position doit être postérieure ou égale à la date de début du lien juridique. | BZ11: POS_C_010 | CA11: =VLOOKUP(BZ11,'Axe 2 Règles de gestion'!$D$2:$F$271,3, FALSE) -> La date de début de position doit être antérieure ou égale à la date de fin réelle de position. | CB11: POS_C_012 | CC11: =VLOOKUP(CB11,'Axe 2 Règles de gestion'!$D$2:$F$271,3, FALSE) -> La date de fin prévisionnelle de la position doit être antérieure à la date limite de départ à la retraite. | CD11: POS_C_022 | CE11: =VLOOKUP(CD11,'Axe 2 Règles de gestion'!$D$2:$F$271,3, FALSE) -> La date de début de position est à J+1 de la date de fin de position de l'occurrence précédente. | CF11: POS_C_037 | CG11: =VLOOKUP(CF11,'Axe 2 Règles de gestion'!$D$2:$F$271,3, FALSE) -> Les champs "Type d'organisme d'accueil" et "Pays" de l'organisme d'accueil doivent être renseignés. | CH11: POS_C_106 | CI11: =VLOOKUP(CH11,'Axe 2 Règles de gestion'!$D$2:$F$271,3, FALSE) -> La date de fin prévisionnelle de la position doit être antérieure ou égale à la date de fin réelle ou prévisionnelle du lien juridique. | CJ11: POS_C_111 | CK11: =VLOOKUP(CJ11,'Axe 2 Règles de gestion'!$D$2:$F$271,3, FALSE) -> La date de fin ou la date de fin prévisionnelle doit être saisie. | CL11: POS_C_431 | CM11: =VLOOKUP(CL11,'Axe 2 Règles de gestion'!$D$2:$F$271,3, FALSE) -> Les champs "Ministère (ou institution de la République) d'accueil", "Corps d'accueil en détachement" et "Grade d'accueil en détachement" ou "Ministère (ou institution de la République) d'accueil", "Emploi fonctionnel d'accueil en détachement" et "Groupe dans un emploi fonctionnel d'accueil" sont renseignés si le "Type d'organisme d'accueil" est valorisé à FPE. | CN11: POS_C_434 | CO11: =VLOOKUP(CN11,'Axe 2 Règles de gestion'!$D$2:$F$271,3, FALSE) -> Le champ "Organisme d'accueil" doit être alimenté si le type d'organisme d'accueil est égal à 'Autre organisme', 'Fonction publique d'un état de l'Union Européenne' ou 'Fonction publique Européenne'. | CU11: Finalisé
A12: 20.00.00 | B12: M | C12: 43152.5 | D12: D0004 | E12: Position | F12: S0017 | G12: Mise à disposition sortante | H12: E0202 | I12: MAD sortante à titre gratuit auprès d'une autre administration ou d'un EPA de l'Etat | J12: Position administrative saisie égale à 'MAD sortante à titre gratuit auprès d'une autre administration ou d'un EPA de l'Etat' | K12: A_POS_POSIAD [Saisi] = 'MAD11' | L12: T0594 | M12: MADS à titre gratuit auprès d'une autre administration ou d'un EPA de l'Etat - Fin | N12: Modification | O12: L'indicateur de renouvellement saisi est égal à l'indicateur de renouvellement avant saisie | P12: A_POS_INDREN [Saisi] = A_POS_INDREN [Valeur avant saisie] | Q12: Contractuel | R12: P0003 | S12: Général | T12: Passant | U12: 40725 | V12: 41721 | W12: MAD_D_019 ET MAD_D_816 ET MAD_D_014 ET MAD_D_039 ET MAD_D_817 ET POS_C_004 ET POS_C_006 ET POS_C_007 ET POS_C_010 ET POS_C_012 ET POS_C_037 ET POS_C_106 ET POS_C_111 ET POS_C_431 ET POS_C_434 | BB12: MAD_D_019 | BC12: =VLOOKUP(BB12,'Axe 2 Règles de gestion'!$D$2:$F$271,3, FALSE) -> La durée prévisionnelle est fixée à 3 ans maximum renouvelable pour chaque période. | BD12: MAD_D_816 | BE12: =VLOOKUP(BD12,'Axe 2 Règles de gestion'!$D$2:$F$271,3, FALSE) -> La durée réelle est fixée à 3 ans maximum renouvelable pour chaque période. | BF12: MAD_D_014 | BG12: =VLOOKUP(BF12,'Axe 2 Règles de gestion'!$D$2:$F$271,3, FALSE) -> Le type de contrat doit être un CDI. | BH12: MAD_D_039 | BI12: =VLOOKUP(BH12,'Axe 2 Règles de gestion'!$D$2:$F$271,3, FALSE) -> La durée totale prévisionnelle de la mise à disposition ne peut excéder 6 années consécutives. | BJ12: MAD_D_817 | BK12: =VLOOKUP(BJ12,'Axe 2 Règles de gestion'!$D$2:$F$271,3, FALSE) -> La durée totale réelle de la mise à disposition ne peut excéder 6 années consécutives. | BR12: POS_C_004 | BS12: =VLOOKUP(BR12,'Axe 2 Règles de gestion'!$D$2:$F$271,3, FALSE) -> La date de début de position doit être antérieure ou égale à la date de fin prévisionnelle de position. | BT12: POS_C_006 | BU12: =VLOOKUP(BT12,'Axe 2 Règles de gestion'!$D$2:$F$271,3, FALSE) -> La date de fin réelle de la position doit être antérieure ou égale à la date de fin réelle ou prévisionnelle du lien juridique. | BV12: POS_C_007 | BW12: =VLOOKUP(BV12,'Axe 2 Règles de gestion'!$D$2:$F$271,3, FALSE) -> La date de fin réelle de la position doit être antérieure à la date limite de départ à la retraite. | BX12: POS_C_010 | BY12: =VLOOKUP(BX12,'Axe 2 Règles de gestion'!$D$2:$F$271,3, FALSE) -> La date de début de position doit être antérieure ou égale à la date de fin réelle de position. | BZ12: POS_C_012 | CA12: =VLOOKUP(BZ12,'Axe 2 Règles de gestion'!$D$2:$F$271,3, FALSE) -> La date de fin prévisionnelle de la position doit être antérieure à la date limite de départ à la retraite. | CB12: POS_C_037 | CC12: =VLOOKUP(CB12,'Axe 2 Règles de gestion'!$D$2:$F$271,3, FALSE) -> Les champs "Type d'organisme d'accueil" et "Pays" de l'organisme d'accueil doivent être renseignés. | CD12: POS_C_106 | CE12: =VLOOKUP(CD12,'Axe 2 Règles de gestion'!$D$2:$F$271,3, FALSE) -> La date de fin prévisionnelle de la position doit être antérieure ou égale à la date de fin réelle ou prévisionnelle du lien juridique. | CF12: POS_C_111 | CG12: =VLOOKUP(CF12,'Axe 2 Règles de gestion'!$D$2:$F$271,3, FALSE) -> La date de fin ou la date de fin prévisionnelle doit être saisie. | CH12: POS_C_431 | CI12: =VLOOKUP(CH12,'Axe 2 Règles de gestion'!$D$2:$F$271,3, FALSE) -> Les champs "Ministère (ou institution de la République) d'accueil", "Corps d'accueil en détachement" et "Grade d'accueil en détachement" ou "Ministère (ou institution de la République) d'accueil", "Emploi fonctionnel d'accueil en détachement" et "Groupe dans un emploi fonctionnel d'accueil" sont renseignés si le "Type d'organisme d'accueil" est valorisé à FPE. | CJ12: POS_C_434 | CK12: =VLOOKUP(CJ12,'Axe 2 Règles de gestion'!$D$2:$F$271,3, FALSE) -> Le champ "Organisme d'accueil" doit être alimenté si le type d'organisme d'accueil est égal à 'Autre organisme', 'Fonction publique d'un état de l'Union Européenne' ou 'Fonction publique Européenne'.
A13: 20.00.00 | B13: M | C13: 43152.5 | D13: D0004 | E13: Position | F13: S0017 | G13: Mise à disposition sortante | H13: E0202 | I13: MAD sortante à titre gratuit auprès d'une autre administration ou d'un EPA de l'Etat | J13: Position administrative saisie égale à 'MAD sortante à titre gratuit auprès d'une autre administration ou d'un EPA de l'Etat' | K13: A_POS_POSIAD [Saisi] = 'MAD11' | L13: T0594 | M13: MADS à titre gratuit auprès d'une autre administration ou d'un EPA de l'Etat - Fin | N13: Modification | O13: L'indicateur de renouvellement saisi est égal à l'indicateur de renouvellement avant saisie | P13: A_POS_INDREN [Saisi] = A_POS_INDREN [Valeur avant saisie] | Q13: Contractuel | R13: P0003 | S13: Général | T13: Passant | U13: 41722 | W13: MAD_I_037 ET MAD_I_038 ET MAD_I_039 ET MAD_I_040 ET MAD_D_019 ET MAD_D_816 ET MAD_D_221 ET MAD_D_818 ET MAD_D_014 ET POS_C_004 ET POS_C_006 ET POS_C_007 ET POS_C_010 ET POS_C_012 ET POS_C_037 ET POS_C_106 ET POS_C_111 ET POS_C_431 ET POS_C_434 | X13: MAD_I_037 | Y13: =VLOOKUP(X13,'Axe 2 Règles de gestion'!$D$2:$F$271,3, FALSE) -> La mise à disposition peut prendre fin de manière anticipée à l'initiative de l'agent, de l'administration d'origine ou de l'organisme d'accueil. | Z13: MAD_I_038 | AA13: =VLOOKUP(Z13,'Axe 2 Règles de gestion'!$D$2:$F$271,3, FALSE) -> Si un préavis est prévu dans la convention, il doit être respecté. | AB13: MAD_I_039 | AC13: =VLOOKUP(AB13,'Axe 2 Règles de gestion'!$D$2:$F$271,3, FALSE) -> En cas de faute disciplinaire, la mise à disposition peut prendre fin sans préavis par accord entre l'administration d'origine et l'organisme d'accueil. | AD13: MAD_I_040 | AE13: =VLOOKUP(AD13,'Axe 2 Règles de gestion'!$D$2:$F$271,3, FALSE) -> L'agent est réemployé pour exercer les fonctions précédemment exercées, ou à défaut sur un poste équivalent de son administration d'origine. | BB13: MAD_D_019 | BC13: =VLOOKUP(BB13,'Axe 2 Règles de gestion'!$D$2:$F$271,3, FALSE) -> La durée prévisionnelle est fixée à 3 ans maximum renouvelable pour chaque période. | BD13: MAD_D_816 | BE13: =VLOOKUP(BD13,'Axe 2 Règles de gestion'!$D$2:$F$271,3, FALSE) -> La durée réelle est fixée à 3 ans maximum renouvelable pour chaque période. | BF13: MAD_D_221 | BG13: =VLOOKUP(BF13,'Axe 2 Règles de gestion'!$D$2:$F$271,3, FALSE) -> La durée totale prévisionnelle de la mise à disposition ne peut excéder 10 années consécutives. | BH13: MAD_D_818 | BI13: =VLOOKUP(BH13,'Axe 2 Règles de gestion'!$D$2:$F$271,3, FALSE) -> La durée totale réelle de la mise à disposition ne peut excéder 10 années consécutives. | BJ13: MAD_D_014 | BK13: =VLOOKUP(BJ13,'Axe 2 Règles de gestion'!$D$2:$F$271,3, FALSE) -> Le type de contrat doit être un CDI. | BR13: POS_C_004 | BS13: =VLOOKUP(BR13,'Axe 2 Règles de gestion'!$D$2:$F$271,3, FALSE) -> La date de début de position doit être antérieure ou égale à la date de fin prévisionnelle de position. | BT13: POS_C_006 | BU13: =VLOOKUP(BT13,'Axe 2 Règles de gestion'!$D$2:$F$271,3, FALSE) -> La date de fin réelle de la position doit être antérieure ou égale à la date de fin réelle ou prévisionnelle du lien juridique. | BV13: POS_C_007 | BW13: =VLOOKUP(BV13,'Axe 2 Règles de gestion'!$D$2:$F$271,3, FALSE) -> La date de fin réelle de la position doit être antérieure à la date limite de départ à la retraite. | BX13: POS_C_010 | BY13: =VLOOKUP(BX13,'Axe 2 Règles de gestion'!$D$2:$F$271,3, FALSE) -> La date de début de position doit être antérieure ou égale à la date de fin réelle de position. | BZ13: POS_C_012 | CA13: =VLOOKUP(BZ13,'Axe 2 Règles de gestion'!$D$2:$F$271,3, FALSE) -> La date de fin prévisionnelle de la position doit être antérieure à la date limite de départ à la retraite. | CB13: POS_C_037 | CC13: =VLOOKUP(CB13,'Axe 2 Règles de gestion'!$D$2:$F$271,3, FALSE) -> Les champs "Type d'organisme d'accueil" et "Pays" de l'organisme d'accueil doivent être renseignés. | CD13: POS_C_106 | CE13: =VLOOKUP(CD13,'Axe 2 Règles de gestion'!$D$2:$F$271,3, FALSE) -> La date de fin prévisionnelle de la position doit être antérieure ou égale à la date de fin réelle ou prévisionnelle du lien juridique. | CF13: POS_C_111 | CG13: =VLOOKUP(CF13,'Axe 2 Règles de gestion'!$D$2:$F$271,3, FALSE) -> La date de fin ou la date de fin prévisionnelle doit être saisie. | CH13: POS_C_431 | CI13: =VLOOKUP(CH13,'Axe 2 Règles de gestion'!$D$2:$F$271,3, FALSE) -> Les champs "Ministère (ou institution de la République) d'accueil", "Corps d'accueil en détachement" et "Grade d'accueil en détachement" ou "Ministère (ou institution de la République) d'accueil", "Emploi fonctionnel d'accueil en détachement" et "Groupe dans un emploi fonctionnel d'accueil" sont renseignés si le "Type d'organisme d'accueil" est valorisé à FPE. | CJ13: POS_C_434 | CK13: =VLOOKUP(CJ13,'Axe 2 Règles de gestion'!$D$2:$F$271,3, FALSE) -> Le champ "Organisme d'accueil" doit être alimenté si le type d'organisme d'accueil est égal à 'Autre organisme', 'Fonction publique d'un état de l'Union Européenne' ou 'Fonction publique Européenne'.
A14: 17.10.00 | B14: A | C14: 43152.5 | D14: D0004 | E14: Position | F14: S0017 | G14: Mise à disposition sortante | H14: E0202 | I14: MAD sortante à titre gratuit auprès d'une autre administration ou d'un EPA de l'Etat | J14: Position administrative saisie égale à 'MAD sortante à titre gratuit auprès d'une autre administration ou d'un EPA de l'Etat' | K14: A_POS_POSIAD [Saisi] = 'MAD11' | L14: T0592 | M14: MADS à titre gratuit auprès d'une autre administration ou d'un EPA de l'Etat - Demande | N14: Création Modification | O14: Indicateur Renouvellement Position est non activé ET l'indicateur de renouvellement saisi est différent de l'indicateur de renouvellement avant saisie | P14: A_POS_INDREN [Saisi] = '0' ET A_POS_INDREN [Saisi] <> A_POS_INDREN [Valeur avant saisie] | Q14: Stagiaire ou auditeur ou élève | R14: P0004 | S14: Général | T14: Exclu | U14: 40725
A15: 17.10.00 | B15: A | C15: 43152.5 | D15: D0004 | E15: Position | F15: S0017 | G15: Mise à disposition sortante | H15: E0202 | I15: MAD sortante à titre gratuit auprès d'une autre administration ou d'un EPA de l'Etat | J15: Position administrative saisie égale à 'MAD sortante à titre gratuit auprès d'une autre administration ou d'un EPA de l'Etat' | K15: A_POS_POSIAD [Saisi] = 'MAD11' | L15: T0593 | M15: MADS à titre gratuit auprès d'une autre administration ou d'un EPA de l'Etat - Renouvellement | N15: Création Modification | O15: Indicateur Renouvellement Position est activé ET l'indicateur de renouvellement saisi est différent de l'indicateur de renouvellement avant saisie | P15: A_POS_INDREN [Saisi] = '1' ET A_POS_INDREN [Saisi] <> A_POS_INDREN [Valeur avant saisie] | Q15: Stagiaire ou auditeur ou élève | R15: P0004 | S15: Général | T15: Exclu | U15: 40725
A16: 17.10.00 | B16: A | C16: 43152.5 | D16: D0004 | E16: Position | F16: S0017 | G16: Mise à disposition sortante | H16: E0202 | I16: MAD sortante à titre gratuit auprès d'une autre administration ou d'un EPA de l'Etat | J16: Position administrative saisie égale à 'MAD sortante à titre gratuit auprès d'une autre administration ou d'un EPA de l'Etat' | K16: A_POS_POSIAD [Saisi] = 'MAD11' | L16: T0594 | M16: MADS à titre gratuit auprès d'une autre administration ou d'un EPA de l'Etat - Fin | N16: Modification | O16: L'indicateur de renouvellement saisi est égal à l'indicateur de renouvellement avant saisie | P16: A_POS_INDREN [Saisi] = A_POS_INDREN [Valeur avant saisie] | Q16: Stagiaire ou auditeur ou élève | R16: P0004 | S16: Général | T16: Exclu | U16: 40725
A17: 17.10.00 | B17: A | C17: 43189.5 | D17: D0004 | E17: Position | F17: S0017 | G17: Mise à disposition sortante | H17: E0202 | I17: MAD sortante à titre gratuit auprès d'une autre administration ou d'un EPA de l'Etat | J17: Position administrative saisie égale à 'MAD sortante à titre gratuit auprès d'une autre administration ou d'un EPA de l'Etat' | K17: A_POS_POSIAD [Saisi] = 'MAD11' | L17: T0592 | M17: MADS à titre gratuit auprès d'une autre administration ou d'un EPA de l'Etat - Demande | N17: Création Modification | O17: Indicateur Renouvellement Position est non activé ET l'indicateur de renouvellement saisi est différent de l'indicateur de renouvellement avant saisie | P17: A_POS_INDREN [Saisi] = '0' ET A_POS_INDREN [Saisi] <> A_POS_INDREN [Valeur avant saisie] | Q17: Ouvrier d'état | R17: P0005 | S17: Général | T17: Exclu | U17: 40725
A18: 17.10.00 | B18: A | C18: 43189.5 | D18: D0004 | E18: Position | F18: S0017 | G18: Mise à disposition sortante | H18: E0202 | I18: MAD sortante à titre gratuit auprès d'une autre administration ou d'un EPA de l'Etat | J18: Position administrative saisie égale à 'MAD sortante à titre gratuit auprès d'une autre administration ou d'un EPA de l'Etat' | K18: A_POS_POSIAD [Saisi] = 'MAD11' | L18: T0593 | M18: MADS à titre gratuit auprès d'une autre administration ou d'un EPA de l'Etat - Renouvellement | N18: Création Modification | O18: Indicateur Renouvellement Position est activé ET l'indicateur de renouvellement saisi est différent de l'indicateur de renouvellement avant saisie | P18: A_POS_INDREN [Saisi] = '1' ET A_POS_INDREN [Saisi] <> A_POS_INDREN [Valeur avant saisie] | Q18: Ouvrier d'état | R18: P0005 | S18: Général | T18: Exclu | U18: 40725
A19: 17.10.00 | B19: A | C19: 43189.5 | D19: D0004 | E19: Position | F19: S0017 | G19: Mise à disposition sortante | H19: E0202 | I19: MAD sortante à titre gratuit auprès d'une autre administration ou d'un EPA de l'Etat | J19: Position administrative saisie égale à 'MAD sortante à titre gratuit auprès d'une autre administration ou d'un EPA de l'Etat' | K19: A_POS_POSIAD [Saisi] = 'MAD11' | L19: T0594 | M19: MADS à titre gratuit auprès d'une autre administration ou d'un EPA de l'Etat - Fin | N19: Modification | O19: L'indicateur de renouvellement saisi est égal à l'indicateur de renouvellement avant saisie | P19: A_POS_INDREN [Saisi] = A_POS_INDREN [Valeur avant saisie] | Q19: Ouvrier d'état | R19: P0005 | S19: Général | T19: Exclu | U19: 40725
A20: 20.00.00 | B20: M | C20: 43152.5 | D20: D0004 | E20: Position | F20: S0017 | G20: Mise à disposition sortante | H20: E0202 | I20: MAD sortante à titre gratuit auprès d'une autre administration ou d'un EPA de l'Etat | J20: Position administrative saisie égale à 'MAD sortante à titre gratuit auprès d'une autre administration ou d'un EPA de l'Etat' | K20: A_POS_POSIAD [Saisi] = 'MAD11' | L20: T0592 | M20: MADS à titre gratuit auprès d'une autre administration ou d'un EPA de l'Etat - Demande | N20: Création Modification | O20: Indicateur Renouvellement Position est non activé ET l'indicateur de renouvellement saisi est différent de l'indicateur de renouvellement avant saisie | P20: A_POS_INDREN [Saisi] = '0' ET A_POS_INDREN [Saisi] <> A_POS_INDREN [Valeur avant saisie] | Q20: Magistrat de l'ordre judiciaire | R20: P0007 | S20: Particulier | T20: Passant | U20: 40725 | W20: MAD_I_048 ET MAD_I_049 ET MAD_I_050 ET MAD_I_051 ET MAD_I_052 ET MAD_I_053 ET MAD_I_054 ET MAD_I_080 ET MAD_I_081 ET MAD_D_145 ET MAD_D_445 ET MAD_D_137 ET POS_C_004 ET POS_C_005 ET POS_C_007 ET POS_C_010 ET POS_C_012 ET POS_C_022 ET POS_C_037 ET POS_C_111 ET POS_C_431 ET POS_C_434 | X20: MAD_I_048 | Y20: =VLOOKUP(X20,'Axe 2 Règles de gestion'!$D$2:$F$271,3, FALSE) -> La mise à disposition auprès d'un cabinet ministériel n'est possible qu'après 4 ans de services effectifs. | Z20: MAD_I_049 | AA20: =VLOOKUP(Z20,'Axe 2 Règles de gestion'!$D$2:$F$271,3, FALSE) -> L'accord de l'agent est nécessaire. | AB20: MAD_I_050 | AC20: =VLOOKUP(AB20,'Axe 2 Règles de gestion'!$D$2:$F$271,3, FALSE) -> Une convention entre l'organisme d'origine et l'organisme d'accueil doit être signée. | AD20: MAD_I_051 | AE20: =VLOOKUP(AD20,'Axe 2 Règles de gestion'!$D$2:$F$271,3, FALSE) -> En cas de pluralité d'organismes d'accueil, autant de conventions sont nécessaires. | AF20: MAD_I_052 | AG20: =VLOOKUP(AF20,'Axe 2 Règles de gestion'!$D$2:$F$271,3, FALSE) -> La convention ou les conventions doivent être transmises à l'agent avant signature. | AH20: MAD_I_053 | AI20: =VLOOKUP(AH20,'Axe 2 Règles de gestion'!$D$2:$F$271,3, FALSE) -> Tout avenant implique la même procédure notamment l'accord de l'agent et du (ou des) organisme(s) d'accueil, les arrêtés ou les décisions. | AJ20: MAD_I_054 | AK20: =VLOOKUP(AJ20,'Axe 2 Règles de gestion'!$D$2:$F$271,3, FALSE) -> La mise à disposition peut prendre fin avant le terme prévu à la demande du magistrat, ou de l'administration d'origine, ou de l'organisme d'accueil. | AL20: MAD_I_080 | AM20: =VLOOKUP(AL20,'Axe 2 Règles de gestion'!$D$2:$F$271,3, FALSE) -> L'organisme d'accueil rembourse à l'administration d'origine la rémunération de l'agent ainsi que les cotisations et contributions afférentes. | AN20: MAD_I_081 | AO20: =VLOOKUP(AN20,'Axe 2 Règles de gestion'!$D$2:$F$271,3, FALSE) -> En cas de pluralité d'organismes d'accueil, le remboursement de chacun se fait au prorata de la quotité de travail. | BB20: MAD_D_145 | BC20: =VLOOKUP(BB20,'Axe 2 Règles de gestion'!$D$2:$F$271,3, FALSE) -> La durée prévisionnelle est fixée à 3 ans maximum renouvelable pour chaque période. | BD20: MAD_D_445 | BE20: =VLOOKUP(BD20,'Axe 2 Règles de gestion'!$D$2:$F$271,3, FALSE) -> La durée réelle est fixée à 3 ans maximum renouvelable pour chaque période. | BF20: MAD_D_137 | BG20: =VLOOKUP(BF20,'Axe 2 Règles de gestion'!$D$2:$F$271,3, FALSE) -> L'agent doit être en activité. | BR20: POS_C_004 | BS20: =VLOOKUP(BR20,'Axe 2 Règles de gestion'!$D$2:$F$271,3, FALSE) -> La date de début de position doit être antérieure ou égale à la date de fin prévisionnelle de position. | BT20: POS_C_005 | BU20: =VLOOKUP(BT20,'Axe 2 Règles de gestion'!$D$2:$F$271,3, FALSE) -> La date de début de la position doit être postérieure ou égale à la date d'entrée dans la FPE ou dans la carrière militaire. | BV20: POS_C_007 | BW20: =VLOOKUP(BV20,'Axe 2 Règles de gestion'!$D$2:$F$271,3, FALSE) -> La date de fin réelle de la position doit être antérieure à la date limite de départ à la retraite. | BX20: POS_C_010 | BY20: =VLOOKUP(BX20,'Axe 2 Règles de gestion'!$D$2:$F$271,3, FALSE) -> La date de début de position doit être antérieure ou égale à la date de fin réelle de position. | BZ20: POS_C_012 | CA20: =VLOOKUP(BZ20,'Axe 2 Règles de gestion'!$D$2:$F$271,3, FALSE) -> La date de fin prévisionnelle de la position doit être antérieure à la date limite de départ à la retraite. | CB20: POS_C_022 | CC20: =VLOOKUP(CB20,'Axe 2 Règles de gestion'!$D$2:$F$271,3, FALSE) -> La date de début de position est à J+1 de la date de fin de position de l'occurrence précédente. | CD20: POS_C_037 | CE20: =VLOOKUP(CD20,'Axe 2 Règles de gestion'!$D$2:$F$271,3, FALSE) -> Les champs "Type d'organisme d'accueil" et "Pays" de l'organisme d'accueil doivent être renseignés. | CF20: POS_C_111 | CG20: =VLOOKUP(CF20,'Axe 2 Règles de gestion'!$D$2:$F$271,3, FALSE) -> La date de fin ou la date de fin prévisionnelle doit être saisie. | CH20: POS_C_431 | CI20: =VLOOKUP(CH20,'Axe 2 Règles de gestion'!$D$2:$F$271,3, FALSE) -> Les champs "Ministère (ou institution de la République) d'accueil", "Corps d'accueil en détachement" et "Grade d'accueil en détachement" ou "Ministère (ou institution de la République) d'accueil", "Emploi fonctionnel d'accueil en détachement" et "Groupe dans un emploi fonctionnel d'accueil" sont renseignés si le "Type d'organisme d'accueil" est valorisé à FPE. | CJ20: POS_C_434 | CK20: =VLOOKUP(CJ20,'Axe 2 Règles de gestion'!$D$2:$F$271,3, FALSE) -> Le champ "Organisme d'accueil" doit être alimenté si le type d'organisme d'accueil est égal à 'Autre organisme', 'Fonction publique d'un état de l'Union Européenne' ou 'Fonction publique Européenne'.
A21: 20.00.00 | B21: M | C21: 43152.5 | D21: D0004 | E21: Position | F21: S0017 | G21: Mise à disposition sortante | H21: E0202 | I21: MAD sortante à titre gratuit auprès d'une autre administration ou d'un EPA de l'Etat | J21: Position administrative saisie égale à 'MAD sortante à titre gratuit auprès d'une autre administration ou d'un EPA de l'Etat' | K21: A_POS_POSIAD [Saisi] = 'MAD11' | L21: T0593 | M21: MADS à titre gratuit auprès d'une autre administration ou d'un EPA de l'Etat - Renouvellement | N21: Création Modification | O21: Indicateur Renouvellement Position est activé ET l'indicateur de renouvellement saisi est différent de l'indicateur de renouvellement avant saisie | P21: A_POS_INDREN [Saisi] = '1' ET A_POS_INDREN [Saisi] <> A_POS_INDREN [Valeur avant saisie] | Q21: Magistrat de l'ordre judiciaire | R21: P0007 | S21: Particulier | T21: Passant | U21: 40725 | W21: MAD_I_049 ET MAD_I_050 ET MAD_D_145 ET MAD_D_445 ET POS_C_004 ET POS_C_005 ET POS_C_007 ET POS_C_010 ET POS_C_012 ET POS_C_022 ET POS_C_037 ET POS_C_111 ET POS_C_431 ET POS_C_434 | X21: MAD_I_049 | Y21: =VLOOKUP(X21,'Axe 2 Règles de gestion'!$D$2:$F$271,3, FALSE) -> L'accord de l'agent est nécessaire. | Z21: MAD_I_050 | AA21: =VLOOKUP(Z21,'Axe 2 Règles de gestion'!$D$2:$F$271,3, FALSE) -> Une convention entre l'organisme d'origine et l'organisme d'accueil doit être signée. | BB21: MAD_D_145 | BC21: =VLOOKUP(BB21,'Axe 2 Règles de gestion'!$D$2:$F$271,3, FALSE) -> La durée prévisionnelle est fixée à 3 ans maximum renouvelable pour chaque période. | BD21: MAD_D_445 | BE21: =VLOOKUP(BD21,'Axe 2 Règles de gestion'!$D$2:$F$271,3, FALSE) -> La durée réelle est fixée à 3 ans maximum renouvelable pour chaque période. | BR21: POS_C_004 | BS21: =VLOOKUP(BR21,'Axe 2 Règles de gestion'!$D$2:$F$271,3, FALSE) -> La date de début de position doit être antérieure ou égale à la date de fin prévisionnelle de position. | BT21: POS_C_005 | BU21: =VLOOKUP(BT21,'Axe 2 Règles de gestion'!$D$2:$F$271,3, FALSE) -> La date de début de la position doit être postérieure ou égale à la date d'entrée dans la FPE ou dans la carrière militaire. | BV21: POS_C_007 | BW21: =VLOOKUP(BV21,'Axe 2 Règles de gestion'!$D$2:$F$271,3, FALSE) -> La date de fin réelle de la position doit être antérieure à la date limite de départ à la retraite. | BX21: POS_C_010 | BY21: =VLOOKUP(BX21,'Axe 2 Règles de gestion'!$D$2:$F$271,3, FALSE) -> La date de début de position doit être antérieure ou égale à la date de fin réelle de position. | BZ21: POS_C_012 | CA21: =VLOOKUP(BZ21,'Axe 2 Règles de gestion'!$D$2:$F$271,3, FALSE) -> La date de fin prévisionnelle de la position doit être antérieure à la date limite de départ à la retraite. | CB21: POS_C_022 | CC21: =VLOOKUP(CB21,'Axe 2 Règles de gestion'!$D$2:$F$271,3, FALSE) -> La date de début de position est à J+1 de la date de fin de position de l'occurrence précédente. | CD21: POS_C_037 | CE21: =VLOOKUP(CD21,'Axe 2 Règles de gestion'!$D$2:$F$271,3, FALSE) -> Les champs "Type d'organisme d'accueil" et "Pays" de l'organisme d'accueil doivent être renseignés. | CF21: POS_C_111 | CG21: =VLOOKUP(CF21,'Axe 2 Règles de gestion'!$D$2:$F$271,3, FALSE) -> La date de fin ou la date de fin prévisionnelle doit être saisie. | CH21: POS_C_431 | CI21: =VLOOKUP(CH21,'Axe 2 Règles de gestion'!$D$2:$F$271,3, FALSE) -> Les champs "Ministère (ou institution de la République) d'accueil", "Corps d'accueil en détachement" et "Grade d'accueil en détachement" ou "Ministère (ou institution de la République) d'accueil", "Emploi fonctionnel d'accueil en détachement" et "Groupe dans un emploi fonctionnel d'accueil" sont renseignés si le "Type d'organisme d'accueil" est valorisé à FPE. | CJ21: POS_C_434 | CK21: =VLOOKUP(CJ21,'Axe 2 Règles de gestion'!$D$2:$F$271,3, FALSE) -> Le champ "Organisme d'accueil" doit être alimenté si le type d'organisme d'accueil est égal à 'Autre organisme', 'Fonction publique d'un état de l'Union Européenne' ou 'Fonction publique Européenne'.
A22: 20.00.00 | B22: M | C22: 43152.5 | D22: D0004 | E22: Position | F22: S0017 | G22: Mise à disposition sortante | H22: E0202 | I22: MAD sortante à titre gratuit auprès d'une autre administration ou d'un EPA de l'Etat | J22: Position administrative saisie égale à 'MAD sortante à titre gratuit auprès d'une autre administration ou d'un EPA de l'Etat' | K22: A_POS_POSIAD [Saisi] = 'MAD11' | L22: T0594 | M22: MADS à titre gratuit auprès d'une autre administration ou d'un EPA de l'Etat - Fin | N22: Modification | O22: L'indicateur de renouvellement saisi est égal à l'indicateur de renouvellement avant saisie | P22: A_POS_INDREN [Saisi] = A_POS_INDREN [Valeur avant saisie] | Q22: Magistrat de l'ordre judiciaire | R22: P0007 | S22: Particulier | T22: Passant | U22: 40725 | W22: MAD_I_054 ET MAD_I_055 ET MAD_I_056 ET MAD_I_057 ET MAD_I_059 ET MAD_D_145 ET MAD_D_445 ET POS_C_004 ET POS_C_007 ET POS_C_010 ET POS_C_012 ET POS_C_037 ET POS_C_111 ET POS_C_431 ET POS_C_434 | X22: MAD_I_054 | Y22: =VLOOKUP(X22,'Axe 2 Règles de gestion'!$D$2:$F$271,3, FALSE) -> La mise à disposition peut prendre fin avant le terme prévu à la demande du magistrat, ou de l'administration d'origine, ou de l'organisme d'accueil. | Z22: MAD_I_055 | AA22: =VLOOKUP(Z22,'Axe 2 Règles de gestion'!$D$2:$F$271,3, FALSE) -> Il peut être mis fin à la mise à disposition avant le terme fixé, sous réserve du respect des règles de préavis éventuellement prévues dans la convention. | AB22: MAD_I_056 | AC22: =VLOOKUP(AB22,'Axe 2 Règles de gestion'!$D$2:$F$271,3, FALSE) -> En cas de faute disciplinaire, la mise à disposition prend fin sans préavis par accord entre l'administration d'origine et l'organisme d'accueil. | AD22: MAD_I_057 | AE22: =VLOOKUP(AD22,'Axe 2 Règles de gestion'!$D$2:$F$271,3, FALSE) -> L'agent est affecté soit aux mêmes fonctions dans son service d'origine soit dans l'un des emplois que son grade lui donne vocation à occuper. | AF22: MAD_I_059 | AG22: =VLOOKUP(AF22,'Axe 2 Règles de gestion'!$D$2:$F$271,3, FALSE) -> L'agent mis à disposition qui accepte la proposition d'intégration émise par son administration d'accueil est intégré dans un corps comparable à son corps d'origine. | BB22: MAD_D_145 | BC22: =VLOOKUP(BB22,'Axe 2 Règles de gestion'!$D$2:$F$271,3, FALSE) -> La durée prévisionnelle est fixée à 3 ans maximum renouvelable pour chaque période. | BD22: MAD_D_445 | BE22: =VLOOKUP(BD22,'Axe 2 Règles de gestion'!$D$2:$F$271,3, FALSE) -> La durée réelle est fixée à 3 ans maximum renouvelable pour chaque période. | BR22: POS_C_004 | BS22: =VLOOKUP(BR22,'Axe 2 Règles de gestion'!$D$2:$F$271,3, FALSE) -> La date de début de position doit être antérieure ou égale à la date de fin prévisionnelle de position. | BT22: POS_C_007 | BU22: =VLOOKUP(BT22,'Axe 2 Règles de gestion'!$D$2:$F$271,3, FALSE) -> La date de fin réelle de la position doit être antérieure à la date limite de départ à la retraite. | BV22: POS_C_010 | BW22: =VLOOKUP(BV22,'Axe 2 Règles de gestion'!$D$2:$F$271,3, FALSE) -> La date de début de position doit être antérieure ou égale à la date de fin réelle de position. | BX22: POS_C_012 | BY22: =VLOOKUP(BX22,'Axe 2 Règles de gestion'!$D$2:$F$271,3, FALSE) -> La date de fin prévisionnelle de la position doit être antérieure à la date limite de départ à la retraite. | BZ22: POS_C_037 | CA22: =VLOOKUP(BZ22,'Axe 2 Règles de gestion'!$D$2:$F$271,3, FALSE) -> Les champs "Type d'organisme d'accueil" et "Pays" de l'organisme d'accueil doivent être renseignés. | CB22: POS_C_111 | CC22: =VLOOKUP(CB22,'Axe 2 Règles de gestion'!$D$2:$F$271,3, FALSE) -> La date de fin ou la date de fin prévisionnelle doit être saisie. | CD22: POS_C_431 | CE22: =VLOOKUP(CD22,'Axe 2 Règles de gestion'!$D$2:$F$271,3, FALSE) -> Les champs "Ministère (ou institution de la République) d'accueil", "Corps d'accueil en détachement" et "Grade d'accueil en détachement" ou "Ministère (ou institution de la République) d'accueil", "Emploi fonctionnel d'accueil en détachement" et "Groupe dans un emploi fonctionnel d'accueil" sont renseignés si le "Type d'organisme d'accueil" est valorisé à FPE. | CF22: POS_C_434 | CG22: =VLOOKUP(CF22,'Axe 2 Règles de gestion'!$D$2:$F$271,3, FALSE) -> Le champ "Organisme d'accueil" doit être alimenté si le type d'organisme d'accueil est égal à 'Autre organisme', 'Fonction publique d'un état de l'Union Européenne' ou 'Fonction publique Européenne'.
A23: 17.10.00 | B23: A | C23: 43152.5 | D23: D0004 | E23: Position | F23: S0017 | G23: Mise à disposition sortante | H23: E0202 | I23: MAD sortante à titre gratuit auprès d'une autre administration ou d'un EPA de l'Etat | J23: Position administrative saisie égale à 'MAD sortante à titre gratuit auprès d'une autre administration ou d'un EPA de l'Etat' | K23: A_POS_POSIAD [Saisi] = 'MAD11' | L23: T0592 | M23: MADS à titre gratuit auprès d'une autre administration ou d'un EPA de l'Etat - Demande | N23: Création Modification | O23: Indicateur Renouvellement Position est non activé ET l'indicateur de renouvellement saisi est différent de l'indicateur de renouvellement avant saisie | P23: A_POS_INDREN [Saisi] = '0' ET A_POS_INDREN [Saisi] <> A_POS_INDREN [Valeur avant saisie] | Q23: Personnel civil payé à l'acte ou à la tâche | R23: P0054 | S23: Particulier | T23: Exclu | U23: 40725
A24: 17.10.00 | B24: A | C24: 43152.5 | D24: D0004 | E24: Position | F24: S0017 | G24: Mise à disposition sortante | H24: E0202 | I24: MAD sortante à titre gratuit auprès d'une autre administration ou d'un EPA de l'Etat | J24: Position administrative saisie égale à 'MAD sortante à titre gratuit auprès d'une autre administration ou d'un EPA de l'Etat' | K24: A_POS_POSIAD [Saisi] = 'MAD11' | L24: T0593 | M24: MADS à titre gratuit auprès d'une autre administration ou d'un EPA de l'Etat - Renouvellement | N24: Création Modification | O24: Indicateur Renouvellement Position est activé ET l'indicateur de renouvellement saisi est différent de l'indicateur de renouvellement avant saisie | P24: A_POS_INDREN [Saisi] = '1' ET A_POS_INDREN [Saisi] <> A_POS_INDREN [Valeur avant saisie] | Q24: Personnel civil payé à l'acte ou à la tâche | R24: P0054 | S24: Particulier | T24: Exclu | U24: 40725
A25: 17.10.00 | B25: A | C25: 43152.5 | D25: D0004 | E25: Position | F25: S0017 | G25: Mise à disposition sortante | H25: E0202 | I25: MAD sortante à titre gratuit auprès d'une autre administration ou d'un EPA de l'Etat | J25: Position administrative saisie égale à 'MAD sortante à titre gratuit auprès d'une autre administration ou d'un EPA de l'Etat' | K25: A_POS_POSIAD [Saisi] = 'MAD11' | L25: T0594 | M25: MADS à titre gratuit auprès d'une autre administration ou d'un EPA de l'Etat - Fin | N25: Modification | O25: L'indicateur de renouvellement saisi est égal à l'indicateur de renouvellement avant saisie | P25: A_POS_INDREN [Saisi] = A_POS_INDREN [Valeur avant saisie] | Q25: Personnel civil payé à l'acte ou à la tâche | R25: P0054 | S25: Particulier | T25: Exclu | U25: 40725
A26: 25.10.00 | B26: M | C26: 45999.685 | D26: D0004 | E26: Position | F26: S0017 | G26: Mise à disposition sortante | H26: E0202 | I26: MAD sortante à titre gratuit auprès d'une autre administration ou d'un EPA de l'Etat | J26: Position administrative saisie égale à 'MAD sortante à titre gratuit auprès d'une autre administration ou d'un EPA de l'Etat' | K26: A_POS_POSIAD [Saisi] = 'MAD11' | L26: T0592 | M26: MADS à titre gratuit auprès d'une autre administration ou d'un EPA de l'Etat - Demande | N26: Création Modification | O26: Indicateur Renouvellement Position est non activé ET l'indicateur de renouvellement saisi est différent de l'indicateur de renouvellement avant saisie | P26: A_POS_INDREN [Saisi] = '0' ET A_POS_INDREN [Saisi] <> A_POS_INDREN [Valeur avant saisie] | Q26: Ouvrier des parcs et ateliers confirmé ou stagiaire | R26: P0143 | S26: Particulier | T26: Passant | U26: 40859 | W26: MAD_I_281 ET MAD_I_070 ET MAD_I_071 ET MAD_I_091 ET MAD_I_092 ET MAD_D_187 ET MAD_D_201 ET POS_C_009 ET POS_C_004 ET POS_C_010 ET POS_C_007 ET POS_C_012 ET POS_C_106 ET POS_C_006 ET POS_C_431 ET POS_C_434 ET POS_C_022 ET POS_C_111 ET POS_C_037 ET POS_C_100 | X26: MAD_I_281 | Y26: =VLOOKUP(X26,'Axe 2 Règles de gestion'!$D$2:$F$271,3, FALSE) -> L'agent peut demander à être mis à disposition auprès des administrations de l'Etat et de ses établissements publics. | Z26: MAD_I_070 | AA26: =VLOOKUP(Z26,'Axe 2 Règles de gestion'!$D$2:$F$271,3, FALSE) -> L'agent doit effectuer une demande. | AB26: MAD_I_071 | AC26: =VLOOKUP(AB26,'Axe 2 Règles de gestion'!$D$2:$F$271,3, FALSE) -> Une convention entre l'organisme d'origine et l'organisme d'accueil doit être signée. | AD26: MAD_I_091 | AE26: =VLOOKUP(AD26,'Axe 2 Règles de gestion'!$D$2:$F$271,3, FALSE) -> La modification d'un des éléments constitutifs de la convention doit faire l'objet d'un avenant à cette convention. | AF26: MAD_I_092 | AG26: =VLOOKUP(AF26,'Axe 2 Règles de gestion'!$D$2:$F$271,3, FALSE) -> La convention et, le cas échéant, ses avenants sont, avant leur signature, transmis à l'agent dans des conditions lui permettant d'exprimer, par écrit, son accord sur la nature des activités qui lui sont confiées et ses conditions d'emploi. | BB26: MAD_D_187 | BC26: =VLOOKUP(BB26,'Axe 2 Règles de gestion'!$D$2:$F$271,3, FALSE) -> La durée prévisionnelle est fixée à 3 ans maximum renouvelable pour chaque période. | BD26: MAD_D_201 | BE26: =VLOOKUP(BD26,'Axe 2 Règles de gestion'!$D$2:$F$271,3, FALSE) -> La durée réelle est fixée à 3 ans maximum renouvelable pour chaque période. | BR26: POS_C_009 | BS26: =VLOOKUP(BR26,'Axe 2 Règles de gestion'!$D$2:$F$271,3, FALSE) -> La date de début de la position doit être postérieure ou égale à la date de début du lien juridique. | BT26: POS_C_004 | BU26: =VLOOKUP(BT26,'Axe 2 Règles de gestion'!$D$2:$F$271,3, FALSE) -> La date de début de position doit être antérieure ou égale à la date de fin prévisionnelle de position. | BV26: POS_C_010 | BW26: =VLOOKUP(BV26,'Axe 2 Règles de gestion'!$D$2:$F$271,3, FALSE) -> La date de début de position doit être antérieure ou égale à la date de fin réelle de position. | BX26: POS_C_007 | BY26: =VLOOKUP(BX26,'Axe 2 Règles de gestion'!$D$2:$F$271,3, FALSE) -> La date de fin réelle de la position doit être antérieure à la date limite de départ à la retraite. | BZ26: POS_C_012 | CA26: =VLOOKUP(BZ26,'Axe 2 Règles de gestion'!$D$2:$F$271,3, FALSE) -> La date de fin prévisionnelle de la position doit être antérieure à la date limite de départ à la retraite. | CB26: POS_C_106 | CC26: =VLOOKUP(CB26,'Axe 2 Règles de gestion'!$D$2:$F$271,3, FALSE) -> La date de fin prévisionnelle de la position doit être antérieure ou égale à la date de fin réelle ou prévisionnelle du lien juridique. | CD26: POS_C_006 | CE26: =VLOOKUP(CD26,'Axe 2 Règles de gestion'!$D$2:$F$271,3, FALSE) -> La date de fin réelle de la position doit être antérieure ou égale à la date de fin réelle ou prévisionnelle du lien juridique. | CF26: POS_C_431 | CG26: =VLOOKUP(CF26,'Axe 2 Règles de gestion'!$D$2:$F$271,3, FALSE) -> Les champs "Ministère (ou institution de la République) d'accueil", "Corps d'accueil en détachement" et "Grade d'accueil en détachement" ou "Ministère (ou institution de la République) d'accueil", "Emploi fonctionnel d'accueil en détachement" et "Groupe dans un emploi fonctionnel d'accueil" sont renseignés si le "Type d'organisme d'accueil" est valorisé à FPE. | CH26: POS_C_434 | CI26: =VLOOKUP(CH26,'Axe 2 Règles de gestion'!$D$2:$F$271,3, FALSE) -> Le champ "Organisme d'accueil" doit être alimenté si le type d'organisme d'accueil est égal à 'Autre organisme', 'Fonction publique d'un état de l'Union Européenne' ou 'Fonction publique Européenne'. | CJ26: POS_C_022 | CK26: =VLOOKUP(CJ26,'Axe 2 Règles de gestion'!$D$2:$F$271,3, FALSE) -> La date de début de position est à J+1 de la date de fin de position de l'occurrence précédente. | CL26: POS_C_111 | CM26: =VLOOKUP(CL26,'Axe 2 Règles de gestion'!$D$2:$F$271,3, FALSE) -> La date de fin ou la date de fin prévisionnelle doit être saisie. | CN26: POS_C_037 | CO26: =VLOOKUP(CN26,'Axe 2 Règles de gestion'!$D$2:$F$271,3, FALSE) -> Les champs "Type d'organisme d'accueil" et "Pays" de l'organisme d'accueil doivent être renseignés. | CP26: POS_C_100 | CQ26: =VLOOKUP(CP26,'Axe 2 Règles de gestion'!$D$2:$F$271,3, FALSE) -> Lors de la demande initiale, l'agent doit être en activité. | CT26: 2025-122
A27: 25.10.00 | B27: A | C27: 45999.572 | D27: D0004 | E27: Position | F27: S0017 | G27: Mise à disposition sortante | H27: E0202 | I27: MAD sortante à titre gratuit auprès d'une autre administration ou d'un EPA de l'Etat | J27: Position administrative saisie égale à 'MAD sortante à titre gratuit auprès d'une autre administration ou d'un EPA de l'Etat' | K27: A_POS_POSIAD [Saisi] = 'MAD11' | L27: T0593 | M27: MADS à titre gratuit auprès d'une autre administration ou d'un EPA de l'Etat - Renouvellement | N27: Création Modification | O27: Indicateur Renouvellement Position est activé ET l'indicateur de renouvellement saisi est différent de l'indicateur de renouvellement avant saisie | P27: A_POS_INDREN [Saisi] = '1' ET A_POS_INDREN [Saisi] <> A_POS_INDREN [Valeur avant saisie] | Q27: Ouvrier des parcs et ateliers confirmé ou stagiaire | R27: P0143 | S27: Particulier | T27: Passant | U27: 40859 | W27: MAD_I_074 ET MAD_D_187 ET MAD_D_201 ET POS_C_009 ET POS_C_004 ET POS_C_010 ET POS_C_007 ET POS_C_012 ET POS_C_106 ET POS_C_006 ET POS_C_431 ET POS_C_434 ET POS_C_022 ET POS_C_111 ET POS_C_037 | X27: MAD_I_074 | Y27: =VLOOKUP(X27,'Axe 2 Règles de gestion'!$D$2:$F$271,3, FALSE) -> En cas d'intention de renouvellement, la demande de l'agent doit se faire 6 mois avant l'expiration de sa mise à disposition. | BB27: MAD_D_187 | BC27: =VLOOKUP(BB27,'Axe 2 Règles de gestion'!$D$2:$F$271,3, FALSE) -> La durée prévisionnelle est fixée à 3 ans maximum renouvelable pour chaque période. | BD27: MAD_D_201 | BE27: =VLOOKUP(BD27,'Axe 2 Règles de gestion'!$D$2:$F$271,3, FALSE) -> La durée réelle est fixée à 3 ans maximum renouvelable pour chaque période. | BR27: POS_C_009 | BS27: =VLOOKUP(BR27,'Axe 2 Règles de gestion'!$D$2:$F$271,3, FALSE) -> La date de début de la position doit être postérieure ou égale à la date de début du lien juridique. | BT27: POS_C_004 | BU27: =VLOOKUP(BT27,'Axe 2 Règles de gestion'!$D$2:$F$271,3, FALSE) -> La date de début de position doit être antérieure ou égale à la date de fin prévisionnelle de position. | BV27: POS_C_010 | BW27: =VLOOKUP(BV27,'Axe 2 Règles de gestion'!$D$2:$F$271,3, FALSE) -> La date de début de position doit être antérieure ou égale à la date de fin réelle de position. | BX27: POS_C_007 | BY27: =VLOOKUP(BX27,'Axe 2 Règles de gestion'!$D$2:$F$271,3, FALSE) -> La date de fin réelle de la position doit être antérieure à la date limite de départ à la retraite. | BZ27: POS_C_012 | CA27: =VLOOKUP(BZ27,'Axe 2 Règles de gestion'!$D$2:$F$271,3, FALSE) -> La date de fin prévisionnelle de la position doit être antérieure à la date limite de départ à la retraite. | CB27: POS_C_106 | CC27: =VLOOKUP(CB27,'Axe 2 Règles de gestion'!$D$2:$F$271,3, FALSE) -> La date de fin prévisionnelle de la position doit être antérieure ou égale à la date de fin réelle ou prévisionnelle du lien juridique. | CD27: POS_C_006 | CE27: =VLOOKUP(CD27,'Axe 2 Règles de gestion'!$D$2:$F$271,3, FALSE) -> La date de fin réelle de la position doit être antérieure ou égale à la date de fin réelle ou prévisionnelle du lien juridique. | CF27: POS_C_431 | CG27: =VLOOKUP(CF27,'Axe 2 Règles de gestion'!$D$2:$F$271,3, FALSE) -> Les champs "Ministère (ou institution de la République) d'accueil", "Corps d'accueil en détachement" et "Grade d'accueil en détachement" ou "Ministère (ou institution de la République) d'accueil", "Emploi fonctionnel d'accueil en détachement" et "Groupe dans un emploi fonctionnel d'accueil" sont renseignés si le "Type d'organisme d'accueil" est valorisé à FPE. | CH27: POS_C_434 | CI27: =VLOOKUP(CH27,'Axe 2 Règles de gestion'!$D$2:$F$271,3, FALSE) -> Le champ "Organisme d'accueil" doit être alimenté si le type d'organisme d'accueil est égal à 'Autre organisme', 'Fonction publique d'un état de l'Union Européenne' ou 'Fonction publique Européenne'. | CJ27: POS_C_022 | CK27: =VLOOKUP(CJ27,'Axe 2 Règles de gestion'!$D$2:$F$271,3, FALSE) -> La date de début de position est à J+1 de la date de fin de position de l'occurrence précédente. | CL27: POS_C_111 | CM27: =VLOOKUP(CL27,'Axe 2 Règles de gestion'!$D$2:$F$271,3, FALSE) -> La date de fin ou la date de fin prévisionnelle doit être saisie. | CN27: POS_C_037 | CO27: =VLOOKUP(CN27,'Axe 2 Règles de gestion'!$D$2:$F$271,3, FALSE) -> Les champs "Type d'organisme d'accueil" et "Pays" de l'organisme d'accueil doivent être renseignés. | CT27: 2025-122
A28: 25.10.00 | B28: M | C28: 45999.687 | D28: D0004 | E28: Position | F28: S0017 | G28: Mise à disposition sortante | H28: E0202 | I28: MAD sortante à titre gratuit auprès d'une autre administration ou d'un EPA de l'Etat | J28: Position administrative saisie égale à 'MAD sortante à titre gratuit auprès d'une autre administration ou d'un EPA de l'Etat' | K28: A_POS_POSIAD [Saisi] = 'MAD11' | L28: T0594 | M28: MADS à titre gratuit auprès d'une autre administration ou d'un EPA de l'Etat - Fin | N28: Modification | O28: L'indicateur de renouvellement saisi est égal à l'indicateur de renouvellement avant saisie | P28: A_POS_INDREN [Saisi] = A_POS_INDREN [Valeur avant saisie] | Q28: Ouvrier des parcs et ateliers confirmé ou stagiaire | R28: P0143 | S28: Particulier | T28: Passant | U28: 40859 | W28: MAD_I_075 ET MAD_I_093 ET MAD_I_076 ET MAD_I_279 ET MAD_I_280 ET MAD_D_187 ET MAD_D_201 ET POS_C_004 ET POS_C_010 ET POS_C_007 ET POS_C_012 ET POS_C_106 ET POS_C_006 ET POS_C_431 ET POS_C_434 ET POS_C_111 ET POS_C_037 | X28: MAD_I_075 | Y28: =VLOOKUP(X28,'Axe 2 Règles de gestion'!$D$2:$F$271,3, FALSE) -> La mise à disposition peut prendre fin avant le terme prévu sur la demande de l'agent, du ministère d'origine ou du ministère d'accueil. | Z28: MAD_I_093 | AA28: =VLOOKUP(Z28,'Axe 2 Règles de gestion'!$D$2:$F$271,3, FALSE) -> La mise à disposition peut prendre fin en cas de faute disciplinaire sans préavis par accord entre le ministère d'origine et le ministère d'accueil. | AB28: MAD_I_076 | AC28: =VLOOKUP(AB28,'Axe 2 Règles de gestion'!$D$2:$F$271,3, FALSE) -> En cas d'intention de réemploi, la demande de l'agent doit se faire 6 mois avant l'expiration de sa mise à disposition. | AD28: MAD_I_279 | AE28: =VLOOKUP(AD28,'Axe 2 Règles de gestion'!$D$2:$F$271,3, FALSE) -> A l'issue de la mise à disposition, l'agent est réemployé au sein de son administration d'origine, sur un emploi correspondant à sa qualification. | AF28: MAD_I_280 | AG28: =VLOOKUP(AF28,'Axe 2 Règles de gestion'!$D$2:$F$271,3, FALSE) -> Toutefois, en cas de non-respect par l'agent du délai prévu pour faire connaitre son intention de réemploi, l'agent est réintégré à la première vacance dans un emploi correspondant à sa qualification. | BB28: MAD_D_187 | BC28: =VLOOKUP(BB28,'Axe 2 Règles de gestion'!$D$2:$F$271,3, FALSE) -> La durée prévisionnelle est fixée à 3 ans maximum renouvelable pour chaque période. | BD28: MAD_D_201 | BE28: =VLOOKUP(BD28,'Axe 2 Règles de gestion'!$D$2:$F$271,3, FALSE) -> La durée réelle est fixée à 3 ans maximum renouvelable pour chaque période. | BR28: POS_C_004 | BS28: =VLOOKUP(BR28,'Axe 2 Règles de gestion'!$D$2:$F$271,3, FALSE) -> La date de début de position doit être antérieure ou égale à la date de fin prévisionnelle de position. | BT28: POS_C_010 | BU28: =VLOOKUP(BT28,'Axe 2 Règles de gestion'!$D$2:$F$271,3, FALSE) -> La date de début de position doit être antérieure ou égale à la date de fin réelle de position. | BV28: POS_C_007 | BW28: =VLOOKUP(BV28,'Axe 2 Règles de gestion'!$D$2:$F$271,3, FALSE) -> La date de fin réelle de la position doit être antérieure à la date limite de départ à la retraite. | BX28: POS_C_012 | BY28: =VLOOKUP(BX28,'Axe 2 Règles de gestion'!$D$2:$F$271,3, FALSE) -> La date de fin prévisionnelle de la position doit être antérieure à la date limite de départ à la retraite. | BZ28: POS_C_106 | CA28: =VLOOKUP(BZ28,'Axe 2 Règles de gestion'!$D$2:$F$271,3, FALSE) -> La date de fin prévisionnelle de la position doit être antérieure ou égale à la date de fin réelle ou prévisionnelle du lien juridique. | CB28: POS_C_006 | CC28: =VLOOKUP(CB28,'Axe 2 Règles de gestion'!$D$2:$F$271,3, FALSE) -> La date de fin réelle de la position doit être antérieure ou égale à la date de fin réelle ou prévisionnelle du lien juridique. | CD28: POS_C_431 | CE28: =VLOOKUP(CD28,'Axe 2 Règles de gestion'!$D$2:$F$271,3, FALSE) -> Les champs "Ministère (ou institution de la République) d'accueil", "Corps d'accueil en détachement" et "Grade d'accueil en détachement" ou "Ministère (ou institution de la République) d'accueil", "Emploi fonctionnel d'accueil en détachement" et "Groupe dans un emploi fonctionnel d'accueil" sont renseignés si le "Type d'organisme d'accueil" est valorisé à FPE. | CF28: POS_C_434 | CG28: =VLOOKUP(CF28,'Axe 2 Règles de gestion'!$D$2:$F$271,3, FALSE) -> Le champ "Organisme d'accueil" doit être alimenté si le type d'organisme d'accueil est égal à 'Autre organisme', 'Fonction publique d'un état de l'Union Européenne' ou 'Fonction publique Européenne'. | CH28: POS_C_111 | CI28: =VLOOKUP(CH28,'Axe 2 Règles de gestion'!$D$2:$F$271,3, FALSE) -> La date de fin ou la date de fin prévisionnelle doit être saisie. | CJ28: POS_C_037 | CK28: =VLOOKUP(CJ28,'Axe 2 Règles de gestion'!$D$2:$F$271,3, FALSE) -> Les champs "Type d'organisme d'accueil" et "Pays" de l'organisme d'accueil doivent être renseignés. | CT28: 2025-122
A29: 17.10.00 | B29: A | C29: 43152.5 | D29: D0004 | E29: Position | F29: S0017 | G29: Mise à disposition sortante | H29: E0202 | I29: MAD sortante à titre gratuit auprès d'une autre administration ou d'un EPA de l'Etat | J29: Position administrative saisie égale à 'MAD sortante à titre gratuit auprès d'une autre administration ou d'un EPA de l'Etat' | K29: A_POS_POSIAD [Saisi] = 'MAD11' | L29: T0592 | M29: MADS à titre gratuit auprès d'une autre administration ou d'un EPA de l'Etat - Demande | N29: Création Modification | O29: Indicateur Renouvellement Position est non activé ET l'indicateur de renouvellement saisi est différent de l'indicateur de renouvellement avant saisie | P29: A_POS_INDREN [Saisi] = '0' ET A_POS_INDREN [Saisi] <> A_POS_INDREN [Valeur avant saisie] | Q29: Maître du privé - Education | R29: P0199 | S29: Particulier | T29: Exclu | U29: 40725
A30: 17.10.00 | B30: A | C30: 43152.5 | D30: D0004 | E30: Position | F30: S0017 | G30: Mise à disposition sortante | H30: E0202 | I30: MAD sortante à titre gratuit auprès d'une autre administration ou d'un EPA de l'Etat | J30: Position administrative saisie égale à 'MAD sortante à titre gratuit auprès d'une autre administration ou d'un EPA de l'Etat' | K30: A_POS_POSIAD [Saisi] = 'MAD11' | L30: T0593 | M30: MADS à titre gratuit auprès d'une autre administration ou d'un EPA de l'Etat - Renouvellement | N30: Création Modification | O30: Indicateur Renouvellement Position est activé ET l'indicateur de renouvellement saisi est différent de l'indicateur de renouvellement avant saisie | P30: A_POS_INDREN [Saisi] = '1' ET A_POS_INDREN [Saisi] <> A_POS_INDREN [Valeur avant saisie] | Q30: Maître du privé - Education | R30: P0199 | S30: Particulier | T30: Exclu | U30: 40725
A31: 17.10.00 | B31: A | C31: 43152.5 | D31: D0004 | E31: Position | F31: S0017 | G31: Mise à disposition sortante | H31: E0202 | I31: MAD sortante à titre gratuit auprès d'une autre administration ou d'un EPA de l'Etat | J31: Position administrative saisie égale à 'MAD sortante à titre gratuit auprès d'une autre administration ou d'un EPA de l'Etat' | K31: A_POS_POSIAD [Saisi] = 'MAD11' | L31: T0594 | M31: MADS à titre gratuit auprès d'une autre administration ou d'un EPA de l'Etat - Fin | N31: Modification | O31: L'indicateur de renouvellement saisi est égal à l'indicateur de renouvellement avant saisie | P31: A_POS_INDREN [Saisi] = A_POS_INDREN [Valeur avant saisie] | Q31: Maître du privé - Education | R31: P0199 | S31: Particulier | T31: Exclu | U31: 40725
A32: 20.00.00 | B32: A | C32: 44018.442 | D32: D0004 | E32: Position | F32: S0017 | G32: Mise à disposition sortante | H32: E0202 | I32: MAD sortante à titre gratuit auprès d'une autre administration ou d'un EPA de l'Etat | J32: Position administrative saisie égale à 'MAD sortante à titre gratuit auprès d'une autre administration ou d'un EPA de l'Etat' | K32: A_POS_POSIAD [Saisi] = 'MAD11' | L32: T0592 | M32: MADS à titre gratuit auprès d'une autre administration ou d'un EPA de l'Etat - Demande | N32: Création Modification | O32: Indicateur Renouvellement Position est non activé ET l'indicateur de renouvellement saisi est différent de l'indicateur de renouvellement avant saisie | P32: A_POS_INDREN [Saisi] = '0' ET A_POS_INDREN [Saisi] <> A_POS_INDREN [Valeur avant saisie] | Q32: Contractuel recruté sur contrat de projet | R32: P0241 | S32: Particulier | T32: Exclu | U32: 43890
A33: 20.00.00 | B33: A | C33: 44018.442 | D33: D0004 | E33: Position | F33: S0017 | G33: Mise à disposition sortante | H33: E0202 | I33: MAD sortante à titre gratuit auprès d'une autre administration ou d'un EPA de l'Etat | J33: Position administrative saisie égale à 'MAD sortante à titre gratuit auprès d'une autre administration ou d'un EPA de l'Etat' | K33: A_POS_POSIAD [Saisi] = 'MAD11' | L33: T0593 | M33: MADS à titre gratuit auprès d'une autre administration ou d'un EPA de l'Etat - Renouvellement | N33: Création Modification | O33: Indicateur Renouvellement Position est activé ET l'indicateur de renouvellement saisi est différent de l'indicateur de renouvellement avant saisie | P33: A_POS_INDREN [Saisi] = '1' ET A_POS_INDREN [Saisi] <> A_POS_INDREN [Valeur avant saisie] | Q33: Contractuel recruté sur contrat de projet | R33: P0241 | S33: Particulier | T33: Exclu | U33: 43890
A34: 20.00.00 | B34: A | C34: 44018.444 | D34: D0004 | E34: Position | F34: S0017 | G34: Mise à disposition sortante | H34: E0202 | I34: MAD sortante à titre gratuit auprès d'une autre administration ou d'un EPA de l'Etat | J34: Position administrative saisie égale à 'MAD sortante à titre gratuit auprès d'une autre administration ou d'un EPA de l'Etat' | K34: A_POS_POSIAD [Saisi] = 'MAD11' | L34: T0594 | M34: MADS à titre gratuit auprès d'une autre administration ou d'un EPA de l'Etat - Fin | N34: Modification | O34: L'indicateur de renouvellement saisi est égal à l'indicateur de renouvellement avant saisie | P34: A_POS_INDREN [Saisi] = A_POS_INDREN [Valeur avant saisie] | Q34: Contractuel recruté sur contrat de projet | R34: P0241 | S34: Particulier | T34: Exclu | U34: 43890
A35: 23.00.00 | B35: M | C35: 45072.445 | D35: D0004 | E35: Position | F35: S0017 | G35: Mise à disposition sortante | H35: E0203 | I35: MAD sortante avec remboursement auprès d'une autre administration ou d'un EPA de l'Etat | J35: Position administrative saisie égale à 'MAD sortante avec remboursement auprès d'une autre administration ou d'un EPA de l'Etat' | K35: A_POS_POSIAD [Saisi] = 'MAD51' | L35: T0596 | M35: MADS avec remboursement auprès d'une autre administration ou d'un EPA de l'Etat - Demande | N35: Création Modification | O35: Indicateur Renouvellement Position est non activé ET l'indicateur de renouvellement saisi est différent de l'indicateur de renouvellement avant saisie | P35: A_POS_INDREN [Saisi] = '0' ET A_POS_INDREN [Saisi] <> A_POS_INDREN [Valeur avant saisie] | Q35: Titulaire ou magistrat | R35: P0001 | S35: Général | T35: Passant | U35: 40725 | V35: 44497 | W35: MAD_I_001 ET MAD_I_002 ET MAD_I_003 ET MAD_I_006 ET MAD_I_009 ET MAD_I_004 ET MAD_I_005 ET MAD_I_008 ET MAD_I_007 ET MAD_I_026 ET MAD_I_025 ET MAD_I_027 ET MAD_I_080 ET MAD_I_081 ET MAD_D_011 ET MAD_D_411 ET MAD_D_001 ET POS_C_004 ET POS_C_005 ET POS_C_007 ET POS_C_010 ET POS_C_012 ET POS_C_022 ET POS_C_037 ET POS_C_111 ET POS_C_431 ET POS_C_434 | X35: MAD_I_001 | Y35: =VLOOKUP(X35,'Axe 2 Règles de gestion'!$D$2:$F$271,3, FALSE) -> Les statuts particuliers peuvent prévoir des conditions d'âge ou d'ancienneté comme pré requis à une mise à disposition sortante. | Z35: MAD_I_002 | AA35: =VLOOKUP(Z35,'Axe 2 Règles de gestion'!$D$2:$F$271,3, FALSE) -> L'agent peut être mis à disposition d'un ou plusieurs organismes d'accueil. | AB35: MAD_I_003 | AC35: =VLOOKUP(AB35,'Axe 2 Règles de gestion'!$D$2:$F$271,3, FALSE) -> L'agent peut être mis à disposition pour tout ou partie de son service. | AD35: MAD_I_006 | AE35: =VLOOKUP(AD35,'Axe 2 Règles de gestion'!$D$2:$F$271,3, FALSE) -> L'accord du ou des organismes d'accueil est nécessaire. | AF35: MAD_I_009 | AG35: =VLOOKUP(AF35,'Axe 2 Règles de gestion'!$D$2:$F$271,3, FALSE) -> En cas de pluralité d'organismes d'accueil, autant de conventions sont nécessaires. | AH35: MAD_I_004 | AI35: =VLOOKUP(AH35,'Axe 2 Règles de gestion'!$D$2:$F$271,3, FALSE) -> La convention ou les conventions doivent être transmises à l'agent avant signature. | AJ35: MAD_I_005 | AK35: =VLOOKUP(AJ35,'Axe 2 Règles de gestion'!$D$2:$F$271,3, FALSE) -> L'accord de l'agent est nécessaire. | AL35: MAD_I_008 | AM35: =VLOOKUP(AL35,'Axe 2 Règles de gestion'!$D$2:$F$271,3, FALSE) -> Une convention entre l'organisme d'origine et l'organisme d'accueil doit être signée. | AN35: MAD_I_007 | AO35: =VLOOKUP(AN35,'Axe 2 Règles de gestion'!$D$2:$F$271,3, FALSE) -> La mise à disposition est prononcée par arrêté du ministre dont relève l'agent, ou par arrêté du préfet dont relève l'agent, ou par décision de l'autorité investie du pouvoir de nomination dans l'établissement. | AP35: MAD_I_026 | AQ35: =VLOOKUP(AP35,'Axe 2 Règles de gestion'!$D$2:$F$271,3, FALSE) -> La modification d'un des éléments constitutifs de la convention doit faire l'objet d'un avenant à cette convention. | AR35: MAD_I_025 | AS35: =VLOOKUP(AR35,'Axe 2 Règles de gestion'!$D$2:$F$271,3, FALSE) -> Tout avenant implique la même procédure notamment l'accord de l'agent et du (ou des) organisme(s) d'accueil, les arrêtés ou les décisions. | AT35: MAD_I_027 | AU35: =VLOOKUP(AT35,'Axe 2 Règles de gestion'!$D$2:$F$271,3, FALSE) -> Les avenants à la convention doivent être transmis à l'agent avant signature. | AV35: MAD_I_080 | AW35: =VLOOKUP(AV35,'Axe 2 Règles de gestion'!$D$2:$F$271,3, FALSE) -> L'organisme d'accueil rembourse à l'administration d'origine la rémunération de l'agent ainsi que les cotisations et contributions afférentes. | AX35: MAD_I_081 | AY35: =VLOOKUP(AX35,'Axe 2 Règles de gestion'!$D$2:$F$271,3, FALSE) -> En cas de pluralité d'organismes d'accueil, le remboursement de chacun se fait au prorata de la quotité de travail. | BB35: MAD_D_011 | BC35: =VLOOKUP(BB35,'Axe 2 Règles de gestion'!$D$2:$F$271,3, FALSE) -> La durée prévisionnelle est fixée à 3 ans maximum renouvelable pour chaque période. | BD35: MAD_D_411 | BE35: =VLOOKUP(BD35,'Axe 2 Règles de gestion'!$D$2:$F$271,3, FALSE) -> La durée réelle est fixée à 3 ans maximum renouvelable pour chaque période. | BF35: MAD_D_001 | BG35: =VLOOKUP(BF35,'Axe 2 Règles de gestion'!$D$2:$F$271,3, FALSE) -> L'agent doit être en activité. | BR35: POS_C_004 | BS35: =VLOOKUP(BR35,'Axe 2 Règles de gestion'!$D$2:$F$271,3, FALSE) -> La date de début de position doit être antérieure ou égale à la date de fin prévisionnelle de position. | BT35: POS_C_005 | BU35: =VLOOKUP(BT35,'Axe 2 Règles de gestion'!$D$2:$F$271,3, FALSE) -> La date de début de la position doit être postérieure ou égale à la date d'entrée dans la FPE ou dans la carrière militaire. | BV35: POS_C_007 | BW35: =VLOOKUP(BV35,'Axe 2 Règles de gestion'!$D$2:$F$271,3, FALSE) -> La date de fin réelle de la position doit être antérieure à la date limite de départ à la retraite. | BX35: POS_C_010 | BY35: =VLOOKUP(BX35,'Axe 2 Règles de gestion'!$D$2:$F$271,3, FALSE) -> La date de début de position doit être antérieure ou égale à la date de fin réelle de position. | BZ35: POS_C_012 | CA35: =VLOOKUP(BZ35,'Axe 2 Règles de gestion'!$D$2:$F$271,3, FALSE) -> La date de fin prévisionnelle de la position doit être antérieure à la date limite de départ à la retraite. | CB35: POS_C_022 | CC35: =VLOOKUP(CB35,'Axe 2 Règles de gestion'!$D$2:$F$271,3, FALSE) -> La date de début de position est à J+1 de la date de fin de position de l'occurrence précédente. | CD35: POS_C_037 | CE35: =VLOOKUP(CD35,'Axe 2 Règles de gestion'!$D$2:$F$271,3, FALSE) -> Les champs "Type d'organisme d'accueil" et "Pays" de l'organisme d'accueil doivent être renseignés. | CF35: POS_C_111 | CG35: =VLOOKUP(CF35,'Axe 2 Règles de gestion'!$D$2:$F$271,3, FALSE) -> La date de fin ou la date de fin prévisionnelle doit être saisie. | CH35: POS_C_431 | CI35: =VLOOKUP(CH35,'Axe 2 Règles de gestion'!$D$2:$F$271,3, FALSE) -> Les champs "Ministère (ou institution de la République) d'accueil", "Corps d'accueil en détachement" et "Grade d'accueil en détachement" ou "Ministère (ou institution de la République) d'accueil", "Emploi fonctionnel d'accueil en détachement" et "Groupe dans un emploi fonctionnel d'accueil" sont renseignés si le "Type d'organisme d'accueil" est valorisé à FPE. | CJ35: POS_C_434 | CK35: =VLOOKUP(CJ35,'Axe 2 Règles de gestion'!$D$2:$F$271,3, FALSE) -> Le champ "Organisme d'accueil" doit être alimenté si le type d'organisme d'accueil est égal à 'Autre organisme', 'Fonction publique d'un état de l'Union Européenne' ou 'Fonction publique Européenne'.
A36: 23.00.00 | B36: A | C36: 45072.445 | D36: D0004 | E36: Position | F36: S0017 | G36: Mise à disposition sortante | H36: E0203 | I36: MAD sortante avec remboursement auprès d'une autre administration ou d'un EPA de l'Etat | J36: Position administrative saisie égale à 'MAD sortante avec remboursement auprès d'une autre administration ou d'un EPA de l'Etat' | K36: A_POS_POSIAD [Saisi] = 'MAD51' | L36: T0596 | M36: MADS avec remboursement auprès d'une autre administration ou d'un EPA de l'Etat - Demande | N36: Création Modification | O36: Indicateur Renouvellement Position est non activé ET l'indicateur de renouvellement saisi est différent de l'indicateur de renouvellement avant saisie | P36: A_POS_INDREN [Saisi] = '0' ET A_POS_INDREN [Saisi] <> A_POS_INDREN [Valeur avant saisie] | Q36: Titulaire ou magistrat | R36: P0001 | S36: Général | T36: Passant | U36: 44498 | W36: MAD_I_001 ET MAD_I_002 ET MAD_I_003 ET MAD_I_006 ET MAD_I_009 ET MAD_I_004 ET MAD_I_005 ET MAD_I_008 ET MAD_I_007 ET MAD_I_026 ET MAD_I_025 ET MAD_I_027 ET MAD_I_080 ET MAD_I_081 ET MAD_D_011 ET MAD_D_411 ET MAD_D_001 ET POS_C_004 ET POS_C_005 ET POS_C_007 ET POS_C_010 ET POS_C_012 ET POS_C_022 ET POS_C_037 ET POS_C_111 ET POS_C_431 ET POS_C_434 | X36: MAD_I_001 | Y36: =VLOOKUP(X36,'Axe 2 Règles de gestion'!$D$2:$F$271,3, FALSE) -> Les statuts particuliers peuvent prévoir des conditions d'âge ou d'ancienneté comme pré requis à une mise à disposition sortante. | Z36: MAD_I_002 | AA36: =VLOOKUP(Z36,'Axe 2 Règles de gestion'!$D$2:$F$271,3, FALSE) -> L'agent peut être mis à disposition d'un ou plusieurs organismes d'accueil. | AB36: MAD_I_003 | AC36: =VLOOKUP(AB36,'Axe 2 Règles de gestion'!$D$2:$F$271,3, FALSE) -> L'agent peut être mis à disposition pour tout ou partie de son service. | AD36: MAD_I_006 | AE36: =VLOOKUP(AD36,'Axe 2 Règles de gestion'!$D$2:$F$271,3, FALSE) -> L'accord du ou des organismes d'accueil est nécessaire. | AF36: MAD_I_009 | AG36: =VLOOKUP(AF36,'Axe 2 Règles de gestion'!$D$2:$F$271,3, FALSE) -> En cas de pluralité d'organismes d'accueil, autant de conventions sont nécessaires. | AH36: MAD_I_004 | AI36: =VLOOKUP(AH36,'Axe 2 Règles de gestion'!$D$2:$F$271,3, FALSE) -> La convention ou les conventions doivent être transmises à l'agent avant signature. | AJ36: MAD_I_005 | AK36: =VLOOKUP(AJ36,'Axe 2 Règles de gestion'!$D$2:$F$271,3, FALSE) -> L'accord de l'agent est nécessaire. | AL36: MAD_I_008 | AM36: =VLOOKUP(AL36,'Axe 2 Règles de gestion'!$D$2:$F$271,3, FALSE) -> Une convention entre l'organisme d'origine et l'organisme d'accueil doit être signée. | AN36: MAD_I_007 | AO36: =VLOOKUP(AN36,'Axe 2 Règles de gestion'!$D$2:$F$271,3, FALSE) -> La mise à disposition est prononcée par arrêté du ministre dont relève l'agent, ou par arrêté du préfet dont relève l'agent, ou par décision de l'autorité investie du pouvoir de nomination dans l'établissement. | AP36: MAD_I_026 | AQ36: =VLOOKUP(AP36,'Axe 2 Règles de gestion'!$D$2:$F$271,3, FALSE) -> La modification d'un des éléments constitutifs de la convention doit faire l'objet d'un avenant à cette convention. | AR36: MAD_I_025 | AS36: =VLOOKUP(AR36,'Axe 2 Règles de gestion'!$D$2:$F$271,3, FALSE) -> Tout avenant implique la même procédure notamment l'accord de l'agent et du (ou des) organisme(s) d'accueil, les arrêtés ou les décisions. | AT36: MAD_I_027 | AU36: =VLOOKUP(AT36,'Axe 2 Règles de gestion'!$D$2:$F$271,3, FALSE) -> Les avenants à la convention doivent être transmis à l'agent avant signature. | AV36: MAD_I_080 | AW36: =VLOOKUP(AV36,'Axe 2 Règles de gestion'!$D$2:$F$271,3, FALSE) -> L'organisme d'accueil rembourse à l'administration d'origine la rémunération de l'agent ainsi que les cotisations et contributions afférentes. | AX36: MAD_I_081 | AY36: =VLOOKUP(AX36,'Axe 2 Règles de gestion'!$D$2:$F$271,3, FALSE) -> En cas de pluralité d'organismes d'accueil, le remboursement de chacun se fait au prorata de la quotité de travail. | BB36: MAD_D_011 | BC36: =VLOOKUP(BB36,'Axe 2 Règles de gestion'!$D$2:$F$271,3, FALSE) -> La durée prévisionnelle est fixée à 3 ans maximum renouvelable pour chaque période. | BD36: MAD_D_411 | BE36: =VLOOKUP(BD36,'Axe 2 Règles de gestion'!$D$2:$F$271,3, FALSE) -> La durée réelle est fixée à 3 ans maximum renouvelable pour chaque période. | BF36: MAD_D_001 | BG36: =VLOOKUP(BF36,'Axe 2 Règles de gestion'!$D$2:$F$271,3, FALSE) -> L'agent doit être en activité. | BR36: POS_C_004 | BS36: =VLOOKUP(BR36,'Axe 2 Règles de gestion'!$D$2:$F$271,3, FALSE) -> La date de début de position doit être antérieure ou égale à la date de fin prévisionnelle de position. | BT36: POS_C_005 | BU36: =VLOOKUP(BT36,'Axe 2 Règles de gestion'!$D$2:$F$271,3, FALSE) -> La date de début de la position doit être postérieure ou égale à la date d'entrée dans la FPE ou dans la carrière militaire. | BV36: POS_C_007 | BW36: =VLOOKUP(BV36,'Axe 2 Règles de gestion'!$D$2:$F$271,3, FALSE) -> La date de fin réelle de la position doit être antérieure à la date limite de départ à la retraite. | BX36: POS_C_010 | BY36: =VLOOKUP(BX36,'Axe 2 Règles de gestion'!$D$2:$F$271,3, FALSE) -> La date de début de position doit être antérieure ou égale à la date de fin réelle de position. | BZ36: POS_C_012 | CA36: =VLOOKUP(BZ36,'Axe 2 Règles de gestion'!$D$2:$F$271,3, FALSE) -> La date de fin prévisionnelle de la position doit être antérieure à la date limite de départ à la retraite. | CB36: POS_C_022 | CC36: =VLOOKUP(CB36,'Axe 2 Règles de gestion'!$D$2:$F$271,3, FALSE) -> La date de début de position est à J+1 de la date de fin de position de l'occurrence précédente. | CD36: POS_C_037 | CE36: =VLOOKUP(CD36,'Axe 2 Règles de gestion'!$D$2:$F$271,3, FALSE) -> Les champs "Type d'organisme d'accueil" et "Pays" de l'organisme d'accueil doivent être renseignés. | CF36: POS_C_111 | CG36: =VLOOKUP(CF36,'Axe 2 Règles de gestion'!$D$2:$F$271,3, FALSE) -> La date de fin ou la date de fin prévisionnelle doit être saisie. | CH36: POS_C_431 | CI36: =VLOOKUP(CH36,'Axe 2 Règles de gestion'!$D$2:$F$271,3, FALSE) -> Les champs "Ministère (ou institution de la République) d'accueil", "Corps d'accueil en détachement" et "Grade d'accueil en détachement" ou "Ministère (ou institution de la République) d'accueil", "Emploi fonctionnel d'accueil en détachement" et "Groupe dans un emploi fonctionnel d'accueil" sont renseignés si le "Type d'organisme d'accueil" est valorisé à FPE. | CJ36: POS_C_434 | CK36: =VLOOKUP(CJ36,'Axe 2 Règles de gestion'!$D$2:$F$271,3, FALSE) -> Le champ "Organisme d'accueil" doit être alimenté si le type d'organisme d'accueil est égal à 'Autre organisme', 'Fonction publique d'un état de l'Union Européenne' ou 'Fonction publique Européenne'.
A37: 23.00.00 | B37: M | C37: 45072.447 | D37: D0004 | E37: Position | F37: S0017 | G37: Mise à disposition sortante | H37: E0203 | I37: MAD sortante avec remboursement auprès d'une autre administration ou d'un EPA de l'Etat | J37: Position administrative saisie égale à 'MAD sortante avec remboursement auprès d'une autre administration ou d'un EPA de l'Etat' | K37: A_POS_POSIAD [Saisi] = 'MAD51' | L37: T0597 | M37: MADS avec remboursement auprès d'une autre administration ou d'un EPA de l'Etat - Renouvellement | N37: Création Modification | O37: Indicateur Renouvellement Position est activé ET l'indicateur de renouvellement saisi est différent de l'indicateur de renouvellement avant saisie | P37: A_POS_INDREN [Saisi] = '1' ET A_POS_INDREN [Saisi] <> A_POS_INDREN [Valeur avant saisie] | Q37: Titulaire ou magistrat | R37: P0001 | S37: Général | T37: Passant | U37: 40725 | V37: 44497 | W37: MAD_I_005 ET MAD_I_006 ET MAD_I_026 ET MAD_I_025 ET MAD_I_027 ET MAD_D_011 ET MAD_D_411 ET POS_C_004 ET POS_C_005 ET POS_C_007 ET POS_C_010 ET POS_C_012 ET POS_C_022 ET POS_C_037 ET POS_C_111 ET POS_C_431 ET POS_C_434 | X37: MAD_I_005 | Y37: =VLOOKUP(X37,'Axe 2 Règles de gestion'!$D$2:$F$271,3, FALSE) -> L'accord de l'agent est nécessaire. | Z37: MAD_I_006 | AA37: =VLOOKUP(Z37,'Axe 2 Règles de gestion'!$D$2:$F$271,3, FALSE) -> L'accord du ou des organismes d'accueil est nécessaire. | AB37: MAD_I_026 | AC37: =VLOOKUP(AB37,'Axe 2 Règles de gestion'!$D$2:$F$271,3, FALSE) -> La modification d'un des éléments constitutifs de la convention doit faire l'objet d'un avenant à cette convention. | AD37: MAD_I_025 | AE37: =VLOOKUP(AD37,'Axe 2 Règles de gestion'!$D$2:$F$271,3, FALSE) -> Tout avenant implique la même procédure notamment l'accord de l'agent et du (ou des) organisme(s) d'accueil, les arrêtés ou les décisions. | AF37: MAD_I_027 | AG37: =VLOOKUP(AF37,'Axe 2 Règles de gestion'!$D$2:$F$271,3, FALSE) -> Les avenants à la convention doivent être transmis à l'agent avant signature. | BB37: MAD_D_011 | BC37: =VLOOKUP(BB37,'Axe 2 Règles de gestion'!$D$2:$F$271,3, FALSE) -> La durée prévisionnelle est fixée à 3 ans maximum renouvelable pour chaque période. | BD37: MAD_D_411 | BE37: =VLOOKUP(BD37,'Axe 2 Règles de gestion'!$D$2:$F$271,3, FALSE) -> La durée réelle est fixée à 3 ans maximum renouvelable pour chaque période. | BR37: POS_C_004 | BS37: =VLOOKUP(BR37,'Axe 2 Règles de gestion'!$D$2:$F$271,3, FALSE) -> La date de début de position doit être antérieure ou égale à la date de fin prévisionnelle de position. | BT37: POS_C_005 | BU37: =VLOOKUP(BT37,'Axe 2 Règles de gestion'!$D$2:$F$271,3, FALSE) -> La date de début de la position doit être postérieure ou égale à la date d'entrée dans la FPE ou dans la carrière militaire. | BV37: POS_C_007 | BW37: =VLOOKUP(BV37,'Axe 2 Règles de gestion'!$D$2:$F$271,3, FALSE) -> La date de fin réelle de la position doit être antérieure à la date limite de départ à la retraite. | BX37: POS_C_010 | BY37: =VLOOKUP(BX37,'Axe 2 Règles de gestion'!$D$2:$F$271,3, FALSE) -> La date de début de position doit être antérieure ou égale à la date de fin réelle de position. | BZ37: POS_C_012 | CA37: =VLOOKUP(BZ37,'Axe 2 Règles de gestion'!$D$2:$F$271,3, FALSE) -> La date de fin prévisionnelle de la position doit être antérieure à la date limite de départ à la retraite. | CB37: POS_C_022 | CC37: =VLOOKUP(CB37,'Axe 2 Règles de gestion'!$D$2:$F$271,3, FALSE) -> La date de début de position est à J+1 de la date de fin de position de l'occurrence précédente. | CD37: POS_C_037 | CE37: =VLOOKUP(CD37,'Axe 2 Règles de gestion'!$D$2:$F$271,3, FALSE) -> Les champs "Type d'organisme d'accueil" et "Pays" de l'organisme d'accueil doivent être renseignés. | CF37: POS_C_111 | CG37: =VLOOKUP(CF37,'Axe 2 Règles de gestion'!$D$2:$F$271,3, FALSE) -> La date de fin ou la date de fin prévisionnelle doit être saisie. | CH37: POS_C_431 | CI37: =VLOOKUP(CH37,'Axe 2 Règles de gestion'!$D$2:$F$271,3, FALSE) -> Les champs "Ministère (ou institution de la République) d'accueil", "Corps d'accueil en détachement" et "Grade d'accueil en détachement" ou "Ministère (ou institution de la République) d'accueil", "Emploi fonctionnel d'accueil en détachement" et "Groupe dans un emploi fonctionnel d'accueil" sont renseignés si le "Type d'organisme d'accueil" est valorisé à FPE. | CJ37: POS_C_434 | CK37: =VLOOKUP(CJ37,'Axe 2 Règles de gestion'!$D$2:$F$271,3, FALSE) -> Le champ "Organisme d'accueil" doit être alimenté si le type d'organisme d'accueil est égal à 'Autre organisme', 'Fonction publique d'un état de l'Union Européenne' ou 'Fonction publique Européenne'.
A38: 23.00.00 | B38: A | C38: 45072.447 | D38: D0004 | E38: Position | F38: S0017 | G38: Mise à disposition sortante | H38: E0203 | I38: MAD sortante avec remboursement auprès d'une autre administration ou d'un EPA de l'Etat | J38: Position administrative saisie égale à 'MAD sortante avec remboursement auprès d'une autre administration ou d'un EPA de l'Etat' | K38: A_POS_POSIAD [Saisi] = 'MAD51' | L38: T0597 | M38: MADS avec remboursement auprès d'une autre administration ou d'un EPA de l'Etat - Renouvellement | N38: Création Modification | O38: Indicateur Renouvellement Position est activé ET l'indicateur de renouvellement saisi est différent de l'indicateur de renouvellement avant saisie | P38: A_POS_INDREN [Saisi] = '1' ET A_POS_INDREN [Saisi] <> A_POS_INDREN [Valeur avant saisie] | Q38: Titulaire ou magistrat | R38: P0001 | S38: Général | T38: Passant | U38: 44498 | W38: MAD_I_005 ET MAD_I_006 ET MAD_I_026 ET MAD_I_025 ET MAD_I_027 ET MAD_D_011 ET MAD_D_411 ET POS_C_004 ET POS_C_005 ET POS_C_007 ET POS_C_010 ET POS_C_012 ET POS_C_022 ET POS_C_037 ET POS_C_111 ET POS_C_431 ET POS_C_434 | X38: MAD_I_005 | Y38: =VLOOKUP(X38,'Axe 2 Règles de gestion'!$D$2:$F$271,3, FALSE) -> L'accord de l'agent est nécessaire. | Z38: MAD_I_006 | AA38: =VLOOKUP(Z38,'Axe 2 Règles de gestion'!$D$2:$F$271,3, FALSE) -> L'accord du ou des organismes d'accueil est nécessaire. | AB38: MAD_I_026 | AC38: =VLOOKUP(AB38,'Axe 2 Règles de gestion'!$D$2:$F$271,3, FALSE) -> La modification d'un des éléments constitutifs de la convention doit faire l'objet d'un avenant à cette convention. | AD38: MAD_I_025 | AE38: =VLOOKUP(AD38,'Axe 2 Règles de gestion'!$D$2:$F$271,3, FALSE) -> Tout avenant implique la même procédure notamment l'accord de l'agent et du (ou des) organisme(s) d'accueil, les arrêtés ou les décisions. | AF38: MAD_I_027 | AG38: =VLOOKUP(AF38,'Axe 2 Règles de gestion'!$D$2:$F$271,3, FALSE) -> Les avenants à la convention doivent être transmis à l'agent avant signature. | BB38: MAD_D_011 | BC38: =VLOOKUP(BB38,'Axe 2 Règles de gestion'!$D$2:$F$271,3, FALSE) -> La durée prévisionnelle est fixée à 3 ans maximum renouvelable pour chaque période. | BD38: MAD_D_411 | BE38: =VLOOKUP(BD38,'Axe 2 Règles de gestion'!$D$2:$F$271,3, FALSE) -> La durée réelle est fixée à 3 ans maximum renouvelable pour chaque période. | BR38: POS_C_004 | BS38: =VLOOKUP(BR38,'Axe 2 Règles de gestion'!$D$2:$F$271,3, FALSE) -> La date de début de position doit être antérieure ou égale à la date de fin prévisionnelle de position. | BT38: POS_C_005 | BU38: =VLOOKUP(BT38,'Axe 2 Règles de gestion'!$D$2:$F$271,3, FALSE) -> La date de début de la position doit être postérieure ou égale à la date d'entrée dans la FPE ou dans la carrière militaire. | BV38: POS_C_007 | BW38: =VLOOKUP(BV38,'Axe 2 Règles de gestion'!$D$2:$F$271,3, FALSE) -> La date de fin réelle de la position doit être antérieure à la date limite de départ à la retraite. | BX38: POS_C_010 | BY38: =VLOOKUP(BX38,'Axe 2 Règles de gestion'!$D$2:$F$271,3, FALSE) -> La date de début de position doit être antérieure ou égale à la date de fin réelle de position. | BZ38: POS_C_012 | CA38: =VLOOKUP(BZ38,'Axe 2 Règles de gestion'!$D$2:$F$271,3, FALSE) -> La date de fin prévisionnelle de la position doit être antérieure à la date limite de départ à la retraite. | CB38: POS_C_022 | CC38: =VLOOKUP(CB38,'Axe 2 Règles de gestion'!$D$2:$F$271,3, FALSE) -> La date de début de position est à J+1 de la date de fin de position de l'occurrence précédente. | CD38: POS_C_037 | CE38: =VLOOKUP(CD38,'Axe 2 Règles de gestion'!$D$2:$F$271,3, FALSE) -> Les champs "Type d'organisme d'accueil" et "Pays" de l'organisme d'accueil doivent être renseignés. | CF38: POS_C_111 | CG38: =VLOOKUP(CF38,'Axe 2 Règles de gestion'!$D$2:$F$271,3, FALSE) -> La date de fin ou la date de fin prévisionnelle doit être saisie. | CH38: POS_C_431 | CI38: =VLOOKUP(CH38,'Axe 2 Règles de gestion'!$D$2:$F$271,3, FALSE) -> Les champs "Ministère (ou institution de la République) d'accueil", "Corps d'accueil en détachement" et "Grade d'accueil en détachement" ou "Ministère (ou institution de la République) d'accueil", "Emploi fonctionnel d'accueil en détachement" et "Groupe dans un emploi fonctionnel d'accueil" sont renseignés si le "Type d'organisme d'accueil" est valorisé à FPE. | CJ38: POS_C_434 | CK38: =VLOOKUP(CJ38,'Axe 2 Règles de gestion'!$D$2:$F$271,3, FALSE) -> Le champ "Organisme d'accueil" doit être alimenté si le type d'organisme d'accueil est égal à 'Autre organisme', 'Fonction publique d'un état de l'Union Européenne' ou 'Fonction publique Européenne'.
A39: 20.00.00 | B39: M | C39: 43152.5 | D39: D0004 | E39: Position | F39: S0017 | G39: Mise à disposition sortante | H39: E0203 | I39: MAD sortante avec remboursement auprès d'une autre administration ou d'un EPA de l'Etat | J39: Position administrative saisie égale à 'MAD sortante avec remboursement auprès d'une autre administration ou d'un EPA de l'Etat' | K39: A_POS_POSIAD [Saisi] = 'MAD51' | L39: T0598 | M39: MADS avec remboursement auprès d'une autre administration ou d'un EPA de l'Etat - Fin | N39: Modification | O39: L'indicateur de renouvellement saisi est égal à l'indicateur de renouvellement avant saisie | P39: A_POS_INDREN [Saisi] = A_POS_INDREN [Valeur avant saisie] | Q39: Titulaire ou magistrat | R39: P0001 | S39: Général | T39: Passant | U39: 40725 | W39: MAD_I_028 ET MAD_I_029 ET MAD_I_030 ET MAD_I_031 ET MAD_I_032 ET MAD_I_034 ET MAD_D_011 ET MAD_D_411 ET POS_C_004 ET POS_C_007 ET POS_C_010 ET POS_C_012 ET POS_C_037 ET POS_C_111 ET POS_C_431 ET POS_C_434 | X39: MAD_I_028 | Y39: =VLOOKUP(X39,'Axe 2 Règles de gestion'!$D$2:$F$271,3, FALSE) -> La mise à disposition peut prendre fin de manière anticipée à l'initiative de l'agent, de l'administration d'origine ou de l'organisme d'accueil. | Z39: MAD_I_029 | AA39: =VLOOKUP(Z39,'Axe 2 Règles de gestion'!$D$2:$F$271,3, FALSE) -> En cas de pluralité d'organismes d'accueil, la fin anticipée de la mise à disposition peut s'appliquer vis-à-vis d'une partie seulement d'entre eux. Dans ce cas, les autres organismes d'accueil doivent en être informés. | AB39: MAD_I_030 | AC39: =VLOOKUP(AB39,'Axe 2 Règles de gestion'!$D$2:$F$271,3, FALSE) -> Si un préavis est prévu dans la convention, il doit être respecté. | AD39: MAD_I_031 | AE39: =VLOOKUP(AD39,'Axe 2 Règles de gestion'!$D$2:$F$271,3, FALSE) -> En cas de faute disciplinaire, la mise à disposition peut prendre fin sans préavis par accord entre l'administration d'origine et l'organisme d'accueil. | AF39: MAD_I_032 | AG39: =VLOOKUP(AF39,'Axe 2 Règles de gestion'!$D$2:$F$271,3, FALSE) -> L'agent est affecté soit aux mêmes fonctions dans son service d'origine soit dans l'un des emplois que son grade lui donne vocation à occuper. | AH39: MAD_I_034 | AI39: =VLOOKUP(AH39,'Axe 2 Règles de gestion'!$D$2:$F$271,3, FALSE) -> L'agent mis à disposition qui accepte la proposition d'intégration émise par son administration d'accueil est intégré dans un corps comparable à son corps d'origine. | BB39: MAD_D_011 | BC39: =VLOOKUP(BB39,'Axe 2 Règles de gestion'!$D$2:$F$271,3, FALSE) -> La durée prévisionnelle est fixée à 3 ans maximum renouvelable pour chaque période. | BD39: MAD_D_411 | BE39: =VLOOKUP(BD39,'Axe 2 Règles de gestion'!$D$2:$F$271,3, FALSE) -> La durée réelle est fixée à 3 ans maximum renouvelable pour chaque période. | BR39: POS_C_004 | BS39: =VLOOKUP(BR39,'Axe 2 Règles de gestion'!$D$2:$F$271,3, FALSE) -> La date de début de position doit être antérieure ou égale à la date de fin prévisionnelle de position. | BT39: POS_C_007 | BU39: =VLOOKUP(BT39,'Axe 2 Règles de gestion'!$D$2:$F$271,3, FALSE) -> La date de fin réelle de la position doit être antérieure à la date limite de départ à la retraite. | BV39: POS_C_010 | BW39: =VLOOKUP(BV39,'Axe 2 Règles de gestion'!$D$2:$F$271,3, FALSE) -> La date de début de position doit être antérieure ou égale à la date de fin réelle de position. | BX39: POS_C_012 | BY39: =VLOOKUP(BX39,'Axe 2 Règles de gestion'!$D$2:$F$271,3, FALSE) -> La date de fin prévisionnelle de la position doit être antérieure à la date limite de départ à la retraite. | BZ39: POS_C_037 | CA39: =VLOOKUP(BZ39,'Axe 2 Règles de gestion'!$D$2:$F$271,3, FALSE) -> Les champs "Type d'organisme d'accueil" et "Pays" de l'organisme d'accueil doivent être renseignés. | CB39: POS_C_111 | CC39: =VLOOKUP(CB39,'Axe 2 Règles de gestion'!$D$2:$F$271,3, FALSE) -> La date de fin ou la date de fin prévisionnelle doit être saisie. | CD39: POS_C_431 | CE39: =VLOOKUP(CD39,'Axe 2 Règles de gestion'!$D$2:$F$271,3, FALSE) -> Les champs "Ministère (ou institution de la République) d'accueil", "Corps d'accueil en détachement" et "Grade d'accueil en détachement" ou "Ministère (ou institution de la République) d'accueil", "Emploi fonctionnel d'accueil en détachement" et "Groupe dans un emploi fonctionnel d'accueil" sont renseignés si le "Type d'organisme d'accueil" est valorisé à FPE. | CF39: POS_C_434 | CG39: =VLOOKUP(CF39,'Axe 2 Règles de gestion'!$D$2:$F$271,3, FALSE) -> Le champ "Organisme d'accueil" doit être alimenté si le type d'organisme d'accueil est égal à 'Autre organisme', 'Fonction publique d'un état de l'Union Européenne' ou 'Fonction publique Européenne'.
A40: 20.00.00 | B40: M | C40: 43152.5 | D40: D0004 | E40: Position | F40: S0017 | G40: Mise à disposition sortante | H40: E0203 | I40: MAD sortante avec remboursement auprès d'une autre administration ou d'un EPA de l'Etat | J40: Position administrative saisie égale à 'MAD sortante avec remboursement auprès d'une autre administration ou d'un EPA de l'Etat' | K40: A_POS_POSIAD [Saisi] = 'MAD51' | L40: T0596 | M40: MADS avec remboursement auprès d'une autre administration ou d'un EPA de l'Etat - Demande | N40: Création Modification | O40: Indicateur Renouvellement Position est non activé ET l'indicateur de renouvellement saisi est différent de l'indicateur de renouvellement avant saisie | P40: A_POS_INDREN [Saisi] = '0' ET A_POS_INDREN [Saisi] <> A_POS_INDREN [Valeur avant saisie] | Q40: Contractuel | R40: P0003 | S40: Général | T40: Passant | U40: 40725 | V40: 41721 | W40: MAD_D_019 ET MAD_D_816 ET MAD_D_014 ET POS_C_100 ET POS_C_004 ET POS_C_006 ET POS_C_007 ET POS_C_009 ET POS_C_010 ET POS_C_012 ET POS_C_022 ET POS_C_037 ET POS_C_106 ET POS_C_111 ET POS_C_431 ET POS_C_434 | BB40: MAD_D_019 | BC40: =VLOOKUP(BB40,'Axe 2 Règles de gestion'!$D$2:$F$271,3, FALSE) -> La durée prévisionnelle est fixée à 3 ans maximum renouvelable pour chaque période. | BD40: MAD_D_816 | BE40: =VLOOKUP(BD40,'Axe 2 Règles de gestion'!$D$2:$F$271,3, FALSE) -> La durée réelle est fixée à 3 ans maximum renouvelable pour chaque période. | BF40: MAD_D_014 | BG40: =VLOOKUP(BF40,'Axe 2 Règles de gestion'!$D$2:$F$271,3, FALSE) -> Le type de contrat doit être un CDI. | BR40: POS_C_100 | BS40: =VLOOKUP(BR40,'Axe 2 Règles de gestion'!$D$2:$F$271,3, FALSE) -> Lors de la demande initiale, l'agent doit être en activité. | BT40: POS_C_004 | BU40: =VLOOKUP(BT40,'Axe 2 Règles de gestion'!$D$2:$F$271,3, FALSE) -> La date de début de position doit être antérieure ou égale à la date de fin prévisionnelle de position. | BV40: POS_C_006 | BW40: =VLOOKUP(BV40,'Axe 2 Règles de gestion'!$D$2:$F$271,3, FALSE) -> La date de fin réelle de la position doit être antérieure ou égale à la date de fin réelle ou prévisionnelle du lien juridique. | BX40: POS_C_007 | BY40: =VLOOKUP(BX40,'Axe 2 Règles de gestion'!$D$2:$F$271,3, FALSE) -> La date de fin réelle de la position doit être antérieure à la date limite de départ à la retraite. | BZ40: POS_C_009 | CA40: =VLOOKUP(BZ40,'Axe 2 Règles de gestion'!$D$2:$F$271,3, FALSE) -> La date de début de la position doit être postérieure ou égale à la date de début du lien juridique. | CB40: POS_C_010 | CC40: =VLOOKUP(CB40,'Axe 2 Règles de gestion'!$D$2:$F$271,3, FALSE) -> La date de début de position doit être antérieure ou égale à la date de fin réelle de position. | CD40: POS_C_012 | CE40: =VLOOKUP(CD40,'Axe 2 Règles de gestion'!$D$2:$F$271,3, FALSE) -> La date de fin prévisionnelle de la position doit être antérieure à la date limite de départ à la retraite. | CF40: POS_C_022 | CG40: =VLOOKUP(CF40,'Axe 2 Règles de gestion'!$D$2:$F$271,3, FALSE) -> La date de début de position est à J+1 de la date de fin de position de l'occurrence précédente. | CH40: POS_C_037 | CI40: =VLOOKUP(CH40,'Axe 2 Règles de gestion'!$D$2:$F$271,3, FALSE) -> Les champs "Type d'organisme d'accueil" et "Pays" de l'organisme d'accueil doivent être renseignés. | CJ40: POS_C_106 | CK40: =VLOOKUP(CJ40,'Axe 2 Règles de gestion'!$D$2:$F$271,3, FALSE) -> La date de fin prévisionnelle de la position doit être antérieure ou égale à la date de fin réelle ou prévisionnelle du lien juridique. | CL40: POS_C_111 | CM40: =VLOOKUP(CL40,'Axe 2 Règles de gestion'!$D$2:$F$271,3, FALSE) -> La date de fin ou la date de fin prévisionnelle doit être saisie. | CN40: POS_C_431 | CO40: =VLOOKUP(CN40,'Axe 2 Règles de gestion'!$D$2:$F$271,3, FALSE) -> Les champs "Ministère (ou institution de la République) d'accueil", "Corps d'accueil en détachement" et "Grade d'accueil en détachement" ou "Ministère (ou institution de la République) d'accueil", "Emploi fonctionnel d'accueil en détachement" et "Groupe dans un emploi fonctionnel d'accueil" sont renseignés si le "Type d'organisme d'accueil" est valorisé à FPE. | CP40: POS_C_434 | CQ40: =VLOOKUP(CP40,'Axe 2 Règles de gestion'!$D$2:$F$271,3, FALSE) -> Le champ "Organisme d'accueil" doit être alimenté si le type d'organisme d'accueil est égal à 'Autre organisme', 'Fonction publique d'un état de l'Union Européenne' ou 'Fonction publique Européenne'.
A41: 22.10.00 | B41: M | C41: 44832.365 | D41: D0004 | E41: Position | F41: S0017 | G41: Mise à disposition sortante | H41: E0203 | I41: MAD sortante avec remboursement auprès d'une autre administration ou d'un EPA de l'Etat | J41: Position administrative saisie égale à 'MAD sortante avec remboursement auprès d'une autre administration ou d'un EPA de l'Etat' | K41: A_POS_POSIAD [Saisi] = 'MAD51' | L41: T0596 | M41: MADS avec remboursement auprès d'une autre administration ou d'un EPA de l'Etat - Demande | N41: Création Modification | O41: Indicateur Renouvellement Position est non activé ET l'indicateur de renouvellement saisi est différent de l'indicateur de renouvellement avant saisie | P41: A_POS_INDREN [Saisi] = '0' ET A_POS_INDREN [Saisi] <> A_POS_INDREN [Valeur avant saisie] | Q41: Contractuel | R41: P0003 | S41: Général | T41: Passant | U41: 41722 | V41: 44677 | W41: MAD_I_012 ET MAD_I_013 ET MAD_I_014 ET MAD_I_094 ET MAD_D_019 ET MAD_D_816 ET MAD_D_014 ET POS_C_100 ET POS_C_004 ET POS_C_006 ET POS_C_007 ET POS_C_009 ET POS_C_010 ET POS_C_012 ET POS_C_022 ET POS_C_037 ET POS_C_106 ET POS_C_111 ET POS_C_431 ET POS_C_434 | X41: MAD_I_012 | Y41: =VLOOKUP(X41,'Axe 2 Règles de gestion'!$D$2:$F$271,3, FALSE) -> L'accord de l'agent est nécessaire. | Z41: MAD_I_013 | AA41: =VLOOKUP(Z41,'Axe 2 Règles de gestion'!$D$2:$F$271,3, FALSE) -> L'accord du ou des organismes d'accueil est nécessaire. | AB41: MAD_I_014 | AC41: =VLOOKUP(AB41,'Axe 2 Règles de gestion'!$D$2:$F$271,3, FALSE) -> Une convention entre l'organisme d'origine et l'organisme d'accueil doit être signée. | AD41: MAD_I_094 | AE41: =VLOOKUP(AD41,'Axe 2 Règles de gestion'!$D$2:$F$271,3, FALSE) -> La convention prévoit les modalités de remboursement, par l'organisme d'accueil, de la rémunération perçue par l'agent. | BB41: MAD_D_019 | BC41: =VLOOKUP(BB41,'Axe 2 Règles de gestion'!$D$2:$F$271,3, FALSE) -> La durée prévisionnelle est fixée à 3 ans maximum renouvelable pour chaque période. | BD41: MAD_D_816 | BE41: =VLOOKUP(BD41,'Axe 2 Règles de gestion'!$D$2:$F$271,3, FALSE) -> La durée réelle est fixée à 3 ans maximum renouvelable pour chaque période. | BF41: MAD_D_014 | BG41: =VLOOKUP(BF41,'Axe 2 Règles de gestion'!$D$2:$F$271,3, FALSE) -> Le type de contrat doit être un CDI. | BR41: POS_C_100 | BS41: =VLOOKUP(BR41,'Axe 2 Règles de gestion'!$D$2:$F$271,3, FALSE) -> Lors de la demande initiale, l'agent doit être en activité. | BT41: POS_C_004 | BU41: =VLOOKUP(BT41,'Axe 2 Règles de gestion'!$D$2:$F$271,3, FALSE) -> La date de début de position doit être antérieure ou égale à la date de fin prévisionnelle de position. | BV41: POS_C_006 | BW41: =VLOOKUP(BV41,'Axe 2 Règles de gestion'!$D$2:$F$271,3, FALSE) -> La date de fin réelle de la position doit être antérieure ou égale à la date de fin réelle ou prévisionnelle du lien juridique. | BX41: POS_C_007 | BY41: =VLOOKUP(BX41,'Axe 2 Règles de gestion'!$D$2:$F$271,3, FALSE) -> La date de fin réelle de la position doit être antérieure à la date limite de départ à la retraite. | BZ41: POS_C_009 | CA41: =VLOOKUP(BZ41,'Axe 2 Règles de gestion'!$D$2:$F$271,3, FALSE) -> La date de début de la position doit être postérieure ou égale à la date de début du lien juridique. | CB41: POS_C_010 | CC41: =VLOOKUP(CB41,'Axe 2 Règles de gestion'!$D$2:$F$271,3, FALSE) -> La date de début de position doit être antérieure ou égale à la date de fin réelle de position. | CD41: POS_C_012 | CE41: =VLOOKUP(CD41,'Axe 2 Règles de gestion'!$D$2:$F$271,3, FALSE) -> La date de fin prévisionnelle de la position doit être antérieure à la date limite de départ à la retraite. | CF41: POS_C_022 | CG41: =VLOOKUP(CF41,'Axe 2 Règles de gestion'!$D$2:$F$271,3, FALSE) -> La date de début de position est à J+1 de la date de fin de position de l'occurrence précédente. | CH41: POS_C_037 | CI41: =VLOOKUP(CH41,'Axe 2 Règles de gestion'!$D$2:$F$271,3, FALSE) -> Les champs "Type d'organisme d'accueil" et "Pays" de l'organisme d'accueil doivent être renseignés. | CJ41: POS_C_106 | CK41: =VLOOKUP(CJ41,'Axe 2 Règles de gestion'!$D$2:$F$271,3, FALSE) -> La date de fin prévisionnelle de la position doit être antérieure ou égale à la date de fin réelle ou prévisionnelle du lien juridique. | CL41: POS_C_111 | CM41: =VLOOKUP(CL41,'Axe 2 Règles de gestion'!$D$2:$F$271,3, FALSE) -> La date de fin ou la date de fin prévisionnelle doit être saisie. | CN41: POS_C_431 | CO41: =VLOOKUP(CN41,'Axe 2 Règles de gestion'!$D$2:$F$271,3, FALSE) -> Les champs "Ministère (ou institution de la République) d'accueil", "Corps d'accueil en détachement" et "Grade d'accueil en détachement" ou "Ministère (ou institution de la République) d'accueil", "Emploi fonctionnel d'accueil en détachement" et "Groupe dans un emploi fonctionnel d'accueil" sont renseignés si le "Type d'organisme d'accueil" est valorisé à FPE. | CP41: POS_C_434 | CQ41: =VLOOKUP(CP41,'Axe 2 Règles de gestion'!$D$2:$F$271,3, FALSE) -> Le champ "Organisme d'accueil" doit être alimenté si le type d'organisme d'accueil est égal à 'Autre organisme', 'Fonction publique d'un état de l'Union Européenne' ou 'Fonction publique Européenne'.
A42: 22.10.00 | B42: A | C42: 44832.365 | D42: D0004 | E42: Position | F42: S0017 | G42: Mise à disposition sortante | H42: E0203 | I42: MAD sortante avec remboursement auprès d'une autre administration ou d'un EPA de l'Etat | J42: Position administrative saisie égale à 'MAD sortante avec remboursement auprès d'une autre administration ou d'un EPA de l'Etat' | K42: A_POS_POSIAD [Saisi] = 'MAD51' | L42: T0596 | M42: MADS avec remboursement auprès d'une autre administration ou d'un EPA de l'Etat - Demande | N42: Création Modification | O42: Indicateur Renouvellement Position est non activé ET l'indicateur de renouvellement saisi est différent de l'indicateur de renouvellement avant saisie | P42: A_POS_INDREN [Saisi] = '0' ET A_POS_INDREN [Saisi] <> A_POS_INDREN [Valeur avant saisie] | Q42: Contractuel | R42: P0003 | S42: Général | T42: Passant | U42: 44678 | W42: MAD_I_021 ET MAD_I_012 ET MAD_I_013 ET MAD_I_014 ET MAD_I_094 ET MAD_D_019 ET MAD_D_816 ET MAD_D_014 ET POS_C_100 ET POS_C_004 ET POS_C_006 ET POS_C_007 ET POS_C_009 ET POS_C_010 ET POS_C_012 ET POS_C_022 ET POS_C_037 ET POS_C_106 ET POS_C_111 ET POS_C_431 ET POS_C_434 | X42: MAD_I_021 | Y42: =VLOOKUP(X42,'Axe 2 Règles de gestion'!$D$2:$F$271,3, FALSE) -> L'agent peut être mis à disposition d'un ou plusieurs organismes d'accueil. | Z42: MAD_I_012 | AA42: =VLOOKUP(Z42,'Axe 2 Règles de gestion'!$D$2:$F$271,3, FALSE) -> L'accord de l'agent est nécessaire. | AB42: MAD_I_013 | AC42: =VLOOKUP(AB42,'Axe 2 Règles de gestion'!$D$2:$F$271,3, FALSE) -> L'accord du ou des organismes d'accueil est nécessaire. | AD42: MAD_I_014 | AE42: =VLOOKUP(AD42,'Axe 2 Règles de gestion'!$D$2:$F$271,3, FALSE) -> Une convention entre l'organisme d'origine et l'organisme d'accueil doit être signée. | AF42: MAD_I_094 | AG42: =VLOOKUP(AF42,'Axe 2 Règles de gestion'!$D$2:$F$271,3, FALSE) -> La convention prévoit les modalités de remboursement, par l'organisme d'accueil, de la rémunération perçue par l'agent. | BB42: MAD_D_019 | BC42: =VLOOKUP(BB42,'Axe 2 Règles de gestion'!$D$2:$F$271,3, FALSE) -> La durée prévisionnelle est fixée à 3 ans maximum renouvelable pour chaque période. | BD42: MAD_D_816 | BE42: =VLOOKUP(BD42,'Axe 2 Règles de gestion'!$D$2:$F$271,3, FALSE) -> La durée réelle est fixée à 3 ans maximum renouvelable pour chaque période. | BF42: MAD_D_014 | BG42: =VLOOKUP(BF42,'Axe 2 Règles de gestion'!$D$2:$F$271,3, FALSE) -> Le type de contrat doit être un CDI. | BR42: POS_C_100 | BS42: =VLOOKUP(BR42,'Axe 2 Règles de gestion'!$D$2:$F$271,3, FALSE) -> Lors de la demande initiale, l'agent doit être en activité. | BT42: POS_C_004 | BU42: =VLOOKUP(BT42,'Axe 2 Règles de gestion'!$D$2:$F$271,3, FALSE) -> La date de début de position doit être antérieure ou égale à la date de fin prévisionnelle de position. | BV42: POS_C_006 | BW42: =VLOOKUP(BV42,'Axe 2 Règles de gestion'!$D$2:$F$271,3, FALSE) -> La date de fin réelle de la position doit être antérieure ou égale à la date de fin réelle ou prévisionnelle du lien juridique. | BX42: POS_C_007 | BY42: =VLOOKUP(BX42,'Axe 2 Règles de gestion'!$D$2:$F$271,3, FALSE) -> La date de fin réelle de la position doit être antérieure à la date limite de départ à la retraite. | BZ42: POS_C_009 | CA42: =VLOOKUP(BZ42,'Axe 2 Règles de gestion'!$D$2:$F$271,3, FALSE) -> La date de début de la position doit être postérieure ou égale à la date de début du lien juridique. | CB42: POS_C_010 | CC42: =VLOOKUP(CB42,'Axe 2 Règles de gestion'!$D$2:$F$271,3, FALSE) -> La date de début de position doit être antérieure ou égale à la date de fin réelle de position. | CD42: POS_C_012 | CE42: =VLOOKUP(CD42,'Axe 2 Règles de gestion'!$D$2:$F$271,3, FALSE) -> La date de fin prévisionnelle de la position doit être antérieure à la date limite de départ à la retraite. | CF42: POS_C_022 | CG42: =VLOOKUP(CF42,'Axe 2 Règles de gestion'!$D$2:$F$271,3, FALSE) -> La date de début de position est à J+1 de la date de fin de position de l'occurrence précédente. | CH42: POS_C_037 | CI42: =VLOOKUP(CH42,'Axe 2 Règles de gestion'!$D$2:$F$271,3, FALSE) -> Les champs "Type d'organisme d'accueil" et "Pays" de l'organisme d'accueil doivent être renseignés. | CJ42: POS_C_106 | CK42: =VLOOKUP(CJ42,'Axe 2 Règles de gestion'!$D$2:$F$271,3, FALSE) -> La date de fin prévisionnelle de la position doit être antérieure ou égale à la date de fin réelle ou prévisionnelle du lien juridique. | CL42: POS_C_111 | CM42: =VLOOKUP(CL42,'Axe 2 Règles de gestion'!$D$2:$F$271,3, FALSE) -> La date de fin ou la date de fin prévisionnelle doit être saisie. | CN42: POS_C_431 | CO42: =VLOOKUP(CN42,'Axe 2 Règles de gestion'!$D$2:$F$271,3, FALSE) -> Les champs "Ministère (ou institution de la République) d'accueil", "Corps d'accueil en détachement" et "Grade d'accueil en détachement" ou "Ministère (ou institution de la République) d'accueil", "Emploi fonctionnel d'accueil en détachement" et "Groupe dans un emploi fonctionnel d'accueil" sont renseignés si le "Type d'organisme d'accueil" est valorisé à FPE. | CP42: POS_C_434 | CQ42: =VLOOKUP(CP42,'Axe 2 Règles de gestion'!$D$2:$F$271,3, FALSE) -> Le champ "Organisme d'accueil" doit être alimenté si le type d'organisme d'accueil est égal à 'Autre organisme', 'Fonction publique d'un état de l'Union Européenne' ou 'Fonction publique Européenne'.
A43: 20.00.00 | B43: M | C43: 43152.5 | D43: D0004 | E43: Position | F43: S0017 | G43: Mise à disposition sortante | H43: E0203 | I43: MAD sortante avec remboursement auprès d'une autre administration ou d'un EPA de l'Etat | J43: Position administrative saisie égale à 'MAD sortante avec remboursement auprès d'une autre administration ou d'un EPA de l'Etat' | K43: A_POS_POSIAD [Saisi] = 'MAD51' | L43: T0597 | M43: MADS avec remboursement auprès d'une autre administration ou d'un EPA de l'Etat - Renouvellement | N43: Création Modification | O43: Indicateur Renouvellement Position est activé ET l'indicateur de renouvellement saisi est différent de l'indicateur de renouvellement avant saisie | P43: A_POS_INDREN [Saisi] = '1' ET A_POS_INDREN [Saisi] <> A_POS_INDREN [Valeur avant saisie] | Q43: Contractuel | R43: P0003 | S43: Général | T43: Passant | U43: 40725 | V43: 41721 | W43: MAD_D_019 ET MAD_D_816 ET MAD_D_014 ET MAD_D_039 ET MAD_D_817 ET POS_C_004 ET POS_C_006 ET POS_C_007 ET POS_C_009 ET POS_C_010 ET POS_C_012 ET POS_C_022 ET POS_C_037 ET POS_C_106 ET POS_C_111 ET POS_C_431 ET POS_C_434 | BB43: MAD_D_019 | BC43: =VLOOKUP(BB43,'Axe 2 Règles de gestion'!$D$2:$F$271,3, FALSE) -> La durée prévisionnelle est fixée à 3 ans maximum renouvelable pour chaque période. | BD43: MAD_D_816 | BE43: =VLOOKUP(BD43,'Axe 2 Règles de gestion'!$D$2:$F$271,3, FALSE) -> La durée réelle est fixée à 3 ans maximum renouvelable pour chaque période. | BF43: MAD_D_014 | BG43: =VLOOKUP(BF43,'Axe 2 Règles de gestion'!$D$2:$F$271,3, FALSE) -> Le type de contrat doit être un CDI. | BH43: MAD_D_039 | BI43: =VLOOKUP(BH43,'Axe 2 Règles de gestion'!$D$2:$F$271,3, FALSE) -> La durée totale prévisionnelle de la mise à disposition ne peut excéder 6 années consécutives. | BJ43: MAD_D_817 | BK43: =VLOOKUP(BJ43,'Axe 2 Règles de gestion'!$D$2:$F$271,3, FALSE) -> La durée totale réelle de la mise à disposition ne peut excéder 6 années consécutives. | BR43: POS_C_004 | BS43: =VLOOKUP(BR43,'Axe 2 Règles de gestion'!$D$2:$F$271,3, FALSE) -> La date de début de position doit être antérieure ou égale à la date de fin prévisionnelle de position. | BT43: POS_C_006 | BU43: =VLOOKUP(BT43,'Axe 2 Règles de gestion'!$D$2:$F$271,3, FALSE) -> La date de fin réelle de la position doit être antérieure ou égale à la date de fin réelle ou prévisionnelle du lien juridique. | BV43: POS_C_007 | BW43: =VLOOKUP(BV43,'Axe 2 Règles de gestion'!$D$2:$F$271,3, FALSE) -> La date de fin réelle de la position doit être antérieure à la date limite de départ à la retraite. | BX43: POS_C_009 | BY43: =VLOOKUP(BX43,'Axe 2 Règles de gestion'!$D$2:$F$271,3, FALSE) -> La date de début de la position doit être postérieure ou égale à la date de début du lien juridique. | BZ43: POS_C_010 | CA43: =VLOOKUP(BZ43,'Axe 2 Règles de gestion'!$D$2:$F$271,3, FALSE) -> La date de début de position doit être antérieure ou égale à la date de fin réelle de position. | CB43: POS_C_012 | CC43: =VLOOKUP(CB43,'Axe 2 Règles de gestion'!$D$2:$F$271,3, FALSE) -> La date de fin prévisionnelle de la position doit être antérieure à la date limite de départ à la retraite. | CD43: POS_C_022 | CE43: =VLOOKUP(CD43,'Axe 2 Règles de gestion'!$D$2:$F$271,3, FALSE) -> La date de début de position est à J+1 de la date de fin de position de l'occurrence précédente. | CF43: POS_C_037 | CG43: =VLOOKUP(CF43,'Axe 2 Règles de gestion'!$D$2:$F$271,3, FALSE) -> Les champs "Type d'organisme d'accueil" et "Pays" de l'organisme d'accueil doivent être renseignés. | CH43: POS_C_106 | CI43: =VLOOKUP(CH43,'Axe 2 Règles de gestion'!$D$2:$F$271,3, FALSE) -> La date de fin prévisionnelle de la position doit être antérieure ou égale à la date de fin réelle ou prévisionnelle du lien juridique. | CJ43: POS_C_111 | CK43: =VLOOKUP(CJ43,'Axe 2 Règles de gestion'!$D$2:$F$271,3, FALSE) -> La date de fin ou la date de fin prévisionnelle doit être saisie. | CL43: POS_C_431 | CM43: =VLOOKUP(CL43,'Axe 2 Règles de gestion'!$D$2:$F$271,3, FALSE) -> Les champs "Ministère (ou institution de la République) d'accueil", "Corps d'accueil en détachement" et "Grade d'accueil en détachement" ou "Ministère (ou institution de la République) d'accueil", "Emploi fonctionnel d'accueil en détachement" et "Groupe dans un emploi fonctionnel d'accueil" sont renseignés si le "Type d'organisme d'accueil" est valorisé à FPE. | CN43: POS_C_434 | CO43: =VLOOKUP(CN43,'Axe 2 Règles de gestion'!$D$2:$F$271,3, FALSE) -> Le champ "Organisme d'accueil" doit être alimenté si le type d'organisme d'accueil est égal à 'Autre organisme', 'Fonction publique d'un état de l'Union Européenne' ou 'Fonction publique Européenne'.
A44: 20.00.00 | B44: M | C44: 43152.5 | D44: D0004 | E44: Position | F44: S0017 | G44: Mise à disposition sortante | H44: E0203 | I44: MAD sortante avec remboursement auprès d'une autre administration ou d'un EPA de l'Etat | J44: Position administrative saisie égale à 'MAD sortante avec remboursement auprès d'une autre administration ou d'un EPA de l'Etat' | K44: A_POS_POSIAD [Saisi] = 'MAD51' | L44: T0597 | M44: MADS avec remboursement auprès d'une autre administration ou d'un EPA de l'Etat - Renouvellement | N44: Création Modification | O44: Indicateur Renouvellement Position est activé ET l'indicateur de renouvellement saisi est différent de l'indicateur de renouvellement avant saisie | P44: A_POS_INDREN [Saisi] = '1' ET A_POS_INDREN [Saisi] <> A_POS_INDREN [Valeur avant saisie] | Q44: Contractuel | R44: P0003 | S44: Général | T44: Passant | U44: 41722 | W44: MAD_D_019 ET MAD_D_816 ET MAD_D_221 ET MAD_D_818 ET MAD_D_014 ET POS_C_004 ET POS_C_006 ET POS_C_007 ET POS_C_009 ET POS_C_010 ET POS_C_012 ET POS_C_022 ET POS_C_037 ET POS_C_106 ET POS_C_111 ET POS_C_431 ET POS_C_434 | BB44: MAD_D_019 | BC44: =VLOOKUP(BB44,'Axe 2 Règles de gestion'!$D$2:$F$271,3, FALSE) -> La durée prévisionnelle est fixée à 3 ans maximum renouvelable pour chaque période. | BD44: MAD_D_816 | BE44: =VLOOKUP(BD44,'Axe 2 Règles de gestion'!$D$2:$F$271,3, FALSE) -> La durée réelle est fixée à 3 ans maximum renouvelable pour chaque période. | BF44: MAD_D_221 | BG44: =VLOOKUP(BF44,'Axe 2 Règles de gestion'!$D$2:$F$271,3, FALSE) -> La durée totale prévisionnelle de la mise à disposition ne peut excéder 10 années consécutives. | BH44: MAD_D_818 | BI44: =VLOOKUP(BH44,'Axe 2 Règles de gestion'!$D$2:$F$271,3, FALSE) -> La durée totale réelle de la mise à disposition ne peut excéder 10 années consécutives. | BJ44: MAD_D_014 | BK44: =VLOOKUP(BJ44,'Axe 2 Règles de gestion'!$D$2:$F$271,3, FALSE) -> Le type de contrat doit être un CDI. | BR44: POS_C_004 | BS44: =VLOOKUP(BR44,'Axe 2 Règles de gestion'!$D$2:$F$271,3, FALSE) -> La date de début de position doit être antérieure ou égale à la date de fin prévisionnelle de position. | BT44: POS_C_006 | BU44: =VLOOKUP(BT44,'Axe 2 Règles de gestion'!$D$2:$F$271,3, FALSE) -> La date de fin réelle de la position doit être antérieure ou égale à la date de fin réelle ou prévisionnelle du lien juridique. | BV44: POS_C_007 | BW44: =VLOOKUP(BV44,'Axe 2 Règles de gestion'!$D$2:$F$271,3, FALSE) -> La date de fin réelle de la position doit être antérieure à la date limite de départ à la retraite. | BX44: POS_C_009 | BY44: =VLOOKUP(BX44,'Axe 2 Règles de gestion'!$D$2:$F$271,3, FALSE) -> La date de début de la position doit être postérieure ou égale à la date de début du lien juridique. | BZ44: POS_C_010 | CA44: =VLOOKUP(BZ44,'Axe 2 Règles de gestion'!$D$2:$F$271,3, FALSE) -> La date de début de position doit être antérieure ou égale à la date de fin réelle de position. | CB44: POS_C_012 | CC44: =VLOOKUP(CB44,'Axe 2 Règles de gestion'!$D$2:$F$271,3, FALSE) -> La date de fin prévisionnelle de la position doit être antérieure à la date limite de départ à la retraite. | CD44: POS_C_022 | CE44: =VLOOKUP(CD44,'Axe 2 Règles de gestion'!$D$2:$F$271,3, FALSE) -> La date de début de position est à J+1 de la date de fin de position de l'occurrence précédente. | CF44: POS_C_037 | CG44: =VLOOKUP(CF44,'Axe 2 Règles de gestion'!$D$2:$F$271,3, FALSE) -> Les champs "Type d'organisme d'accueil" et "Pays" de l'organisme d'accueil doivent être renseignés. | CH44: POS_C_106 | CI44: =VLOOKUP(CH44,'Axe 2 Règles de gestion'!$D$2:$F$271,3, FALSE) -> La date de fin prévisionnelle de la position doit être antérieure ou égale à la date de fin réelle ou prévisionnelle du lien juridique. | CJ44: POS_C_111 | CK44: =VLOOKUP(CJ44,'Axe 2 Règles de gestion'!$D$2:$F$271,3, FALSE) -> La date de fin ou la date de fin prévisionnelle doit être saisie. | CL44: POS_C_431 | CM44: =VLOOKUP(CL44,'Axe 2 Règles de gestion'!$D$2:$F$271,3, FALSE) -> Les champs "Ministère (ou institution de la République) d'accueil", "Corps d'accueil en détachement" et "Grade d'accueil en détachement" ou "Ministère (ou institution de la République) d'accueil", "Emploi fonctionnel d'accueil en détachement" et "Groupe dans un emploi fonctionnel d'accueil" sont renseignés si le "Type d'organisme d'accueil" est valorisé à FPE. | CN44: POS_C_434 | CO44: =VLOOKUP(CN44,'Axe 2 Règles de gestion'!$D$2:$F$271,3, FALSE) -> Le champ "Organisme d'accueil" doit être alimenté si le type d'organisme d'accueil est égal à 'Autre organisme', 'Fonction publique d'un état de l'Union Européenne' ou 'Fonction publique Européenne'. | CU44: Finalisé
A45: 20.00.00 | B45: M | C45: 43152.5 | D45: D0004 | E45: Position | F45: S0017 | G45: Mise à disposition sortante | H45: E0203 | I45: MAD sortante avec remboursement auprès d'une autre administration ou d'un EPA de l'Etat | J45: Position administrative saisie égale à 'MAD sortante avec remboursement auprès d'une autre administration ou d'un EPA de l'Etat' | K45: A_POS_POSIAD [Saisi] = 'MAD51' | L45: T0598 | M45: MADS avec remboursement auprès d'une autre administration ou d'un EPA de l'Etat - Fin | N45: Modification | O45: L'indicateur de renouvellement saisi est égal à l'indicateur de renouvellement avant saisie | P45: A_POS_INDREN [Saisi] = A_POS_INDREN [Valeur avant saisie] | Q45: Contractuel | R45: P0003 | S45: Général | T45: Passant | U45: 40725 | V45: 41721 | W45: MAD_D_019 ET MAD_D_816 ET MAD_D_014 ET MAD_D_039 ET MAD_D_817 ET POS_C_004 ET POS_C_006 ET POS_C_007 ET POS_C_010 ET POS_C_012 ET POS_C_037 ET POS_C_106 ET POS_C_111 ET POS_C_431 ET POS_C_434 | BB45: MAD_D_019 | BC45: =VLOOKUP(BB45,'Axe 2 Règles de gestion'!$D$2:$F$271,3, FALSE) -> La durée prévisionnelle est fixée à 3 ans maximum renouvelable pour chaque période. | BD45: MAD_D_816 | BE45: =VLOOKUP(BD45,'Axe 2 Règles de gestion'!$D$2:$F$271,3, FALSE) -> La durée réelle est fixée à 3 ans maximum renouvelable pour chaque période. | BF45: MAD_D_014 | BG45: =VLOOKUP(BF45,'Axe 2 Règles de gestion'!$D$2:$F$271,3, FALSE) -> Le type de contrat doit être un CDI. | BH45: MAD_D_039 | BI45: =VLOOKUP(BH45,'Axe 2 Règles de gestion'!$D$2:$F$271,3, FALSE) -> La durée totale prévisionnelle de la mise à disposition ne peut excéder 6 années consécutives. | BJ45: MAD_D_817 | BK45: =VLOOKUP(BJ45,'Axe 2 Règles de gestion'!$D$2:$F$271,3, FALSE) -> La durée totale réelle de la mise à disposition ne peut excéder 6 années consécutives. | BR45: POS_C_004 | BS45: =VLOOKUP(BR45,'Axe 2 Règles de gestion'!$D$2:$F$271,3, FALSE) -> La date de début de position doit être antérieure ou égale à la date de fin prévisionnelle de position. | BT45: POS_C_006 | BU45: =VLOOKUP(BT45,'Axe 2 Règles de gestion'!$D$2:$F$271,3, FALSE) -> La date de fin réelle de la position doit être antérieure ou égale à la date de fin réelle ou prévisionnelle du lien juridique. | BV45: POS_C_007 | BW45: =VLOOKUP(BV45,'Axe 2 Règles de gestion'!$D$2:$F$271,3, FALSE) -> La date de fin réelle de la position doit être antérieure à la date limite de départ à la retraite. | BX45: POS_C_010 | BY45: =VLOOKUP(BX45,'Axe 2 Règles de gestion'!$D$2:$F$271,3, FALSE) -> La date de début de position doit être antérieure ou égale à la date de fin réelle de position. | BZ45: POS_C_012 | CA45: =VLOOKUP(BZ45,'Axe 2 Règles de gestion'!$D$2:$F$271,3, FALSE) -> La date de fin prévisionnelle de la position doit être antérieure à la date limite de départ à la retraite. | CB45: POS_C_037 | CC45: =VLOOKUP(CB45,'Axe 2 Règles de gestion'!$D$2:$F$271,3, FALSE) -> Les champs "Type d'organisme d'accueil" et "Pays" de l'organisme d'accueil doivent être renseignés. | CD45: POS_C_106 | CE45: =VLOOKUP(CD45,'Axe 2 Règles de gestion'!$D$2:$F$271,3, FALSE) -> La date de fin prévisionnelle de la position doit être antérieure ou égale à la date de fin réelle ou prévisionnelle du lien juridique. | CF45: POS_C_111 | CG45: =VLOOKUP(CF45,'Axe 2 Règles de gestion'!$D$2:$F$271,3, FALSE) -> La date de fin ou la date de fin prévisionnelle doit être saisie. | CH45: POS_C_431 | CI45: =VLOOKUP(CH45,'Axe 2 Règles de gestion'!$D$2:$F$271,3, FALSE) -> Les champs "Ministère (ou institution de la République) d'accueil", "Corps d'accueil en détachement" et "Grade d'accueil en détachement" ou "Ministère (ou institution de la République) d'accueil", "Emploi fonctionnel d'accueil en détachement" et "Groupe dans un emploi fonctionnel d'accueil" sont renseignés si le "Type d'organisme d'accueil" est valorisé à FPE. | CJ45: POS_C_434 | CK45: =VLOOKUP(CJ45,'Axe 2 Règles de gestion'!$D$2:$F$271,3, FALSE) -> Le champ "Organisme d'accueil" doit être alimenté si le type d'organisme d'accueil est égal à 'Autre organisme', 'Fonction publique d'un état de l'Union Européenne' ou 'Fonction publique Européenne'.
A46: 20.00.00 | B46: M | C46: 43152.5 | D46: D0004 | E46: Position | F46: S0017 | G46: Mise à disposition sortante | H46: E0203 | I46: MAD sortante avec remboursement auprès d'une autre administration ou d'un EPA de l'Etat | J46: Position administrative saisie égale à 'MAD sortante avec remboursement auprès d'une autre administration ou d'un EPA de l'Etat' | K46: A_POS_POSIAD [Saisi] = 'MAD51' | L46: T0598 | M46: MADS avec remboursement auprès d'une autre administration ou d'un EPA de l'Etat - Fin | N46: Modification | O46: L'indicateur de renouvellement saisi est égal à l'indicateur de renouvellement avant saisie | P46: A_POS_INDREN [Saisi] = A_POS_INDREN [Valeur avant saisie] | Q46: Contractuel | R46: P0003 | S46: Général | T46: Passant | U46: 41722 | W46: MAD_I_037 ET MAD_I_038 ET MAD_I_039 ET MAD_I_040 ET MAD_D_019 ET MAD_D_816 ET MAD_D_221 ET MAD_D_818 ET MAD_D_014 ET POS_C_004 ET POS_C_006 ET POS_C_007 ET POS_C_010 ET POS_C_012 ET POS_C_037 ET POS_C_106 ET POS_C_111 ET POS_C_431 ET POS_C_434 | X46: MAD_I_037 | Y46: =VLOOKUP(X46,'Axe 2 Règles de gestion'!$D$2:$F$271,3, FALSE) -> La mise à disposition peut prendre fin de manière anticipée à l'initiative de l'agent, de l'administration d'origine ou de l'organisme d'accueil. | Z46: MAD_I_038 | AA46: =VLOOKUP(Z46,'Axe 2 Règles de gestion'!$D$2:$F$271,3, FALSE) -> Si un préavis est prévu dans la convention, il doit être respecté. | AB46: MAD_I_039 | AC46: =VLOOKUP(AB46,'Axe 2 Règles de gestion'!$D$2:$F$271,3, FALSE) -> En cas de faute disciplinaire, la mise à disposition peut prendre fin sans préavis par accord entre l'administration d'origine et l'organisme d'accueil. | AD46: MAD_I_040 | AE46: =VLOOKUP(AD46,'Axe 2 Règles de gestion'!$D$2:$F$271,3, FALSE) -> L'agent est réemployé pour exercer les fonctions précédemment exercées, ou à défaut sur un poste équivalent de son administration d'origine. | BB46: MAD_D_019 | BC46: =VLOOKUP(BB46,'Axe 2 Règles de gestion'!$D$2:$F$271,3, FALSE) -> La durée prévisionnelle est fixée à 3 ans maximum renouvelable pour chaque période. | BD46: MAD_D_816 | BE46: =VLOOKUP(BD46,'Axe 2 Règles de gestion'!$D$2:$F$271,3, FALSE) -> La durée réelle est fixée à 3 ans maximum renouvelable pour chaque période. | BF46: MAD_D_221 | BG46: =VLOOKUP(BF46,'Axe 2 Règles de gestion'!$D$2:$F$271,3, FALSE) -> La durée totale prévisionnelle de la mise à disposition ne peut excéder 10 années consécutives. | BH46: MAD_D_818 | BI46: =VLOOKUP(BH46,'Axe 2 Règles de gestion'!$D$2:$F$271,3, FALSE) -> La durée totale réelle de la mise à disposition ne peut excéder 10 années consécutives. | BJ46: MAD_D_014 | BK46: =VLOOKUP(BJ46,'Axe 2 Règles de gestion'!$D$2:$F$271,3, FALSE) -> Le type de contrat doit être un CDI. | BR46: POS_C_004 | BS46: =VLOOKUP(BR46,'Axe 2 Règles de gestion'!$D$2:$F$271,3, FALSE) -> La date de début de position doit être antérieure ou égale à la date de fin prévisionnelle de position. | BT46: POS_C_006 | BU46: =VLOOKUP(BT46,'Axe 2 Règles de gestion'!$D$2:$F$271,3, FALSE) -> La date de fin réelle de la position doit être antérieure ou égale à la date de fin réelle ou prévisionnelle du lien juridique. | BV46: POS_C_007 | BW46: =VLOOKUP(BV46,'Axe 2 Règles de gestion'!$D$2:$F$271,3, FALSE) -> La date de fin réelle de la position doit être antérieure à la date limite de départ à la retraite. | BX46: POS_C_010 | BY46: =VLOOKUP(BX46,'Axe 2 Règles de gestion'!$D$2:$F$271,3, FALSE) -> La date de début de position doit être antérieure ou égale à la date de fin réelle de position. | BZ46: POS_C_012 | CA46: =VLOOKUP(BZ46,'Axe 2 Règles de gestion'!$D$2:$F$271,3, FALSE) -> La date de fin prévisionnelle de la position doit être antérieure à la date limite de départ à la retraite. | CB46: POS_C_037 | CC46: =VLOOKUP(CB46,'Axe 2 Règles de gestion'!$D$2:$F$271,3, FALSE) -> Les champs "Type d'organisme d'accueil" et "Pays" de l'organisme d'accueil doivent être renseignés. | CD46: POS_C_106 | CE46: =VLOOKUP(CD46,'Axe 2 Règles de gestion'!$D$2:$F$271,3, FALSE) -> La date de fin prévisionnelle de la position doit être antérieure ou égale à la date de fin réelle ou prévisionnelle du lien juridique. | CF46: POS_C_111 | CG46: =VLOOKUP(CF46,'Axe 2 Règles de gestion'!$D$2:$F$271,3, FALSE) -> La date de fin ou la date de fin prévisionnelle doit être saisie. | CH46: POS_C_431 | CI46: =VLOOKUP(CH46,'Axe 2 Règles de gestion'!$D$2:$F$271,3, FALSE) -> Les champs "Ministère (ou institution de la République) d'accueil", "Corps d'accueil en détachement" et "Grade d'accueil en détachement" ou "Ministère (ou institution de la République) d'accueil", "Emploi fonctionnel d'accueil en détachement" et "Groupe dans un emploi fonctionnel d'accueil" sont renseignés si le "Type d'organisme d'accueil" est valorisé à FPE. | CJ46: POS_C_434 | CK46: =VLOOKUP(CJ46,'Axe 2 Règles de gestion'!$D$2:$F$271,3, FALSE) -> Le champ "Organisme d'accueil" doit être alimenté si le type d'organisme d'accueil est égal à 'Autre organisme', 'Fonction publique d'un état de l'Union Européenne' ou 'Fonction publique Européenne'.
A47: 17.10.00 | B47: A | C47: 43152.5 | D47: D0004 | E47: Position | F47: S0017 | G47: Mise à disposition sortante | H47: E0203 | I47: MAD sortante avec remboursement auprès d'une autre administration ou d'un EPA de l'Etat | J47: Position administrative saisie égale à 'MAD sortante avec remboursement auprès d'une autre administration ou d'un EPA de l'Etat' | K47: A_POS_POSIAD [Saisi] = 'MAD51' | L47: T0596 | M47: MADS avec remboursement auprès d'une autre administration ou d'un EPA de l'Etat - Demande | N47: Création Modification | O47: Indicateur Renouvellement Position est non activé ET l'indicateur de renouvellement saisi est différent de l'indicateur de renouvellement avant saisie | P47: A_POS_INDREN [Saisi] = '0' ET A_POS_INDREN [Saisi] <> A_POS_INDREN [Valeur avant saisie] | Q47: Stagiaire ou auditeur ou élève | R47: P0004 | S47: Général | T47: Exclu | U47: 40725
A48: 17.10.00 | B48: A | C48: 43152.5 | D48: D0004 | E48: Position | F48: S0017 | G48: Mise à disposition sortante | H48: E0203 | I48: MAD sortante avec remboursement auprès d'une autre administration ou d'un EPA de l'Etat | J48: Position administrative saisie égale à 'MAD sortante avec remboursement auprès d'une autre administration ou d'un EPA de l'Etat' | K48: A_POS_POSIAD [Saisi] = 'MAD51' | L48: T0597 | M48: MADS avec remboursement auprès d'une autre administration ou d'un EPA de l'Etat - Renouvellement | N48: Création Modification | O48: Indicateur Renouvellement Position est activé ET l'indicateur de renouvellement saisi est différent de l'indicateur de renouvellement avant saisie | P48: A_POS_INDREN [Saisi] = '1' ET A_POS_INDREN [Saisi] <> A_POS_INDREN [Valeur avant saisie] | Q48: Stagiaire ou auditeur ou élève | R48: P0004 | S48: Général | T48: Exclu | U48: 40725
A49: 17.10.00 | B49: A | C49: 43152.5 | D49: D0004 | E49: Position | F49: S0017 | G49: Mise à disposition sortante | H49: E0203 | I49: MAD sortante avec remboursement auprès d'une autre administration ou d'un EPA de l'Etat | J49: Position administrative saisie égale à 'MAD sortante avec remboursement auprès d'une autre administration ou d'un EPA de l'Etat' | K49: A_POS_POSIAD [Saisi] = 'MAD51' | L49: T0598 | M49: MADS avec remboursement auprès d'une autre administration ou d'un EPA de l'Etat - Fin | N49: Modification | O49: L'indicateur de renouvellement saisi est égal à l'indicateur de renouvellement avant saisie | P49: A_POS_INDREN [Saisi] = A_POS_INDREN [Valeur avant saisie] | Q49: Stagiaire ou auditeur ou élève | R49: P0004 | S49: Général | T49: Exclu | U49: 40725
A50: 17.10.00 | B50: A | C50: 43189.5 | D50: D0004 | E50: Position | F50: S0017 | G50: Mise à disposition sortante | H50: E0203 | I50: MAD sortante avec remboursement auprès d'une autre administration ou d'un EPA de l'Etat | J50: Position administrative saisie égale à 'MAD sortante avec remboursement auprès d'une autre administration ou d'un EPA de l'Etat' | K50: A_POS_POSIAD [Saisi] = 'MAD51' | L50: T0596 | M50: MADS avec remboursement auprès d'une autre administration ou d'un EPA de l'Etat - Demande | N50: Création Modification | O50: Indicateur Renouvellement Position est non activé ET l'indicateur de renouvellement saisi est différent de l'indicateur de renouvellement avant saisie | P50: A_POS_INDREN [Saisi] = '0' ET A_POS_INDREN [Saisi] <> A_POS_INDREN [Valeur avant saisie] | Q50: Ouvrier d'état | R50: P0005 | S50: Général | T50: Exclu | U50: 40725
A51: 17.10.00 | B51: A | C51: 43189.5 | D51: D0004 | E51: Position | F51: S0017 | G51: Mise à disposition sortante | H51: E0203 | I51: MAD sortante avec remboursement auprès d'une autre administration ou d'un EPA de l'Etat | J51: Position administrative saisie égale à 'MAD sortante avec remboursement auprès d'une autre administration ou d'un EPA de l'Etat' | K51: A_POS_POSIAD [Saisi] = 'MAD51' | L51: T0597 | M51: MADS avec remboursement auprès d'une autre administration ou d'un EPA de l'Etat - Renouvellement | N51: Création Modification | O51: Indicateur Renouvellement Position est activé ET l'indicateur de renouvellement saisi est différent de l'indicateur de renouvellement avant saisie | P51: A_POS_INDREN [Saisi] = '1' ET A_POS_INDREN [Saisi] <> A_POS_INDREN [Valeur avant saisie] | Q51: Ouvrier d'état | R51: P0005 | S51: Général | T51: Exclu | U51: 40725
A52: 17.10.00 | B52: A | C52: 43189.5 | D52: D0004 | E52: Position | F52: S0017 | G52: Mise à disposition sortante | H52: E0203 | I52: MAD sortante avec remboursement auprès d'une autre administration ou d'un EPA de l'Etat | J52: Position administrative saisie égale à 'MAD sortante avec remboursement auprès d'une autre administration ou d'un EPA de l'Etat' | K52: A_POS_POSIAD [Saisi] = 'MAD51' | L52: T0598 | M52: MADS avec remboursement auprès d'une autre administration ou d'un EPA de l'Etat - Fin | N52: Modification | O52: L'indicateur de renouvellement saisi est égal à l'indicateur de renouvellement avant saisie | P52: A_POS_INDREN [Saisi] = A_POS_INDREN [Valeur avant saisie] | Q52: Ouvrier d'état | R52: P0005 | S52: Général | T52: Exclu | U52: 40725
A53: 20.00.00 | B53: M | C53: 43152.5 | D53: D0004 | E53: Position | F53: S0017 | G53: Mise à disposition sortante | H53: E0203 | I53: MAD sortante avec remboursement auprès d'une autre administration ou d'un EPA de l'Etat | J53: Position administrative saisie égale à 'MAD sortante avec remboursement auprès d'une autre administration ou d'un EPA de l'Etat' | K53: A_POS_POSIAD [Saisi] = 'MAD51' | L53: T0596 | M53: MADS avec remboursement auprès d'une autre administration ou d'un EPA de l'Etat - Demande | N53: Création Modification | O53: Indicateur Renouvellement Position est non activé ET l'indicateur de renouvellement saisi est différent de l'indicateur de renouvellement avant saisie | P53: A_POS_INDREN [Saisi] = '0' ET A_POS_INDREN [Saisi] <> A_POS_INDREN [Valeur avant saisie] | Q53: Magistrat de l'ordre judiciaire | R53: P0007 | S53: Particulier | T53: Passant | U53: 40725 | W53: MAD_I_048 ET MAD_I_049 ET MAD_I_050 ET MAD_I_051 ET MAD_I_052 ET MAD_I_053 ET MAD_I_054 ET MAD_I_080 ET MAD_I_081 ET MAD_D_145 ET MAD_D_445 ET MAD_D_137 ET POS_C_004 ET POS_C_005 ET POS_C_007 ET POS_C_010 ET POS_C_012 ET POS_C_022 ET POS_C_037 ET POS_C_111 ET POS_C_431 ET POS_C_434 | X53: MAD_I_048 | Y53: =VLOOKUP(X53,'Axe 2 Règles de gestion'!$D$2:$F$271,3, FALSE) -> La mise à disposition auprès d'un cabinet ministériel n'est possible qu'après 4 ans de services effectifs. | Z53: MAD_I_049 | AA53: =VLOOKUP(Z53,'Axe 2 Règles de gestion'!$D$2:$F$271,3, FALSE) -> L'accord de l'agent est nécessaire. | AB53: MAD_I_050 | AC53: =VLOOKUP(AB53,'Axe 2 Règles de gestion'!$D$2:$F$271,3, FALSE) -> Une convention entre l'organisme d'origine et l'organisme d'accueil doit être signée. | AD53: MAD_I_051 | AE53: =VLOOKUP(AD53,'Axe 2 Règles de gestion'!$D$2:$F$271,3, FALSE) -> En cas de pluralité d'organismes d'accueil, autant de conventions sont nécessaires. | AF53: MAD_I_052 | AG53: =VLOOKUP(AF53,'Axe 2 Règles de gestion'!$D$2:$F$271,3, FALSE) -> La convention ou les conventions doivent être transmises à l'agent avant signature. | AH53: MAD_I_053 | AI53: =VLOOKUP(AH53,'Axe 2 Règles de gestion'!$D$2:$F$271,3, FALSE) -> Tout avenant implique la même procédure notamment l'accord de l'agent et du (ou des) organisme(s) d'accueil, les arrêtés ou les décisions. | AJ53: MAD_I_054 | AK53: =VLOOKUP(AJ53,'Axe 2 Règles de gestion'!$D$2:$F$271,3, FALSE) -> La mise à disposition peut prendre fin avant le terme prévu à la demande du magistrat, ou de l'administration d'origine, ou de l'organisme d'accueil. | AL53: MAD_I_080 | AM53: =VLOOKUP(AL53,'Axe 2 Règles de gestion'!$D$2:$F$271,3, FALSE) -> L'organisme d'accueil rembourse à l'administration d'origine la rémunération de l'agent ainsi que les cotisations et contributions afférentes. | AN53: MAD_I_081 | AO53: =VLOOKUP(AN53,'Axe 2 Règles de gestion'!$D$2:$F$271,3, FALSE) -> En cas de pluralité d'organismes d'accueil, le remboursement de chacun se fait au prorata de la quotité de travail. | BB53: MAD_D_145 | BC53: =VLOOKUP(BB53,'Axe 2 Règles de gestion'!$D$2:$F$271,3, FALSE) -> La durée prévisionnelle est fixée à 3 ans maximum renouvelable pour chaque période. | BD53: MAD_D_445 | BE53: =VLOOKUP(BD53,'Axe 2 Règles de gestion'!$D$2:$F$271,3, FALSE) -> La durée réelle est fixée à 3 ans maximum renouvelable pour chaque période. | BF53: MAD_D_137 | BG53: =VLOOKUP(BF53,'Axe 2 Règles de gestion'!$D$2:$F$271,3, FALSE) -> L'agent doit être en activité. | BR53: POS_C_004 | BS53: =VLOOKUP(BR53,'Axe 2 Règles de gestion'!$D$2:$F$271,3, FALSE) -> La date de début de position doit être antérieure ou égale à la date de fin prévisionnelle de position. | BT53: POS_C_005 | BU53: =VLOOKUP(BT53,'Axe 2 Règles de gestion'!$D$2:$F$271,3, FALSE) -> La date de début de la position doit être postérieure ou égale à la date d'entrée dans la FPE ou dans la carrière militaire. | BV53: POS_C_007 | BW53: =VLOOKUP(BV53,'Axe 2 Règles de gestion'!$D$2:$F$271,3, FALSE) -> La date de fin réelle de la position doit être antérieure à la date limite de départ à la retraite. | BX53: POS_C_010 | BY53: =VLOOKUP(BX53,'Axe 2 Règles de gestion'!$D$2:$F$271,3, FALSE) -> La date de début de position doit être antérieure ou égale à la date de fin réelle de position. | BZ53: POS_C_012 | CA53: =VLOOKUP(BZ53,'Axe 2 Règles de gestion'!$D$2:$F$271,3, FALSE) -> La date de fin prévisionnelle de la position doit être antérieure à la date limite de départ à la retraite. | CB53: POS_C_022 | CC53: =VLOOKUP(CB53,'Axe 2 Règles de gestion'!$D$2:$F$271,3, FALSE) -> La date de début de position est à J+1 de la date de fin de position de l'occurrence précédente. | CD53: POS_C_037 | CE53: =VLOOKUP(CD53,'Axe 2 Règles de gestion'!$D$2:$F$271,3, FALSE) -> Les champs "Type d'organisme d'accueil" et "Pays" de l'organisme d'accueil doivent être renseignés. | CF53: POS_C_111 | CG53: =VLOOKUP(CF53,'Axe 2 Règles de gestion'!$D$2:$F$271,3, FALSE) -> La date de fin ou la date de fin prévisionnelle doit être saisie. | CH53: POS_C_431 | CI53: =VLOOKUP(CH53,'Axe 2 Règles de gestion'!$D$2:$F$271,3, FALSE) -> Les champs "Ministère (ou institution de la République) d'accueil", "Corps d'accueil en détachement" et "Grade d'accueil en détachement" ou "Ministère (ou institution de la République) d'accueil", "Emploi fonctionnel d'accueil en détachement" et "Groupe dans un emploi fonctionnel d'accueil" sont renseignés si le "Type d'organisme d'accueil" est valorisé à FPE. | CJ53: POS_C_434 | CK53: =VLOOKUP(CJ53,'Axe 2 Règles de gestion'!$D$2:$F$271,3, FALSE) -> Le champ "Organisme d'accueil" doit être alimenté si le type d'organisme d'accueil est égal à 'Autre organisme', 'Fonction publique d'un état de l'Union Européenne' ou 'Fonction publique Européenne'.
A54: 20.00.00 | B54: M | C54: 43152.5 | D54: D0004 | E54: Position | F54: S0017 | G54: Mise à disposition sortante | H54: E0203 | I54: MAD sortante avec remboursement auprès d'une autre administration ou d'un EPA de l'Etat | J54: Position administrative saisie égale à 'MAD sortante avec remboursement auprès d'une autre administration ou d'un EPA de l'Etat' | K54: A_POS_POSIAD [Saisi] = 'MAD51' | L54: T0597 | M54: MADS avec remboursement auprès d'une autre administration ou d'un EPA de l'Etat - Renouvellement | N54: Création Modification | O54: Indicateur Renouvellement Position est activé ET l'indicateur de renouvellement saisi est différent de l'indicateur de renouvellement avant saisie | P54: A_POS_INDREN [Saisi] = '1' ET A_POS_INDREN [Saisi] <> A_POS_INDREN [Valeur avant saisie] | Q54: Magistrat de l'ordre judiciaire | R54: P0007 | S54: Particulier | T54: Passant | U54: 40725 | W54: MAD_I_049 ET MAD_I_050 ET MAD_D_145 ET MAD_D_445 ET POS_C_004 ET POS_C_005 ET POS_C_007 ET POS_C_010 ET POS_C_012 ET POS_C_022 ET POS_C_037 ET POS_C_111 ET POS_C_431 ET POS_C_434 | X54: MAD_I_049 | Y54: =VLOOKUP(X54,'Axe 2 Règles de gestion'!$D$2:$F$271,3, FALSE) -> L'accord de l'agent est nécessaire. | Z54: MAD_I_050 | AA54: =VLOOKUP(Z54,'Axe 2 Règles de gestion'!$D$2:$F$271,3, FALSE) -> Une convention entre l'organisme d'origine et l'organisme d'accueil doit être signée. | BB54: MAD_D_145 | BC54: =VLOOKUP(BB54,'Axe 2 Règles de gestion'!$D$2:$F$271,3, FALSE) -> La durée prévisionnelle est fixée à 3 ans maximum renouvelable pour chaque période. | BD54: MAD_D_445 | BE54: =VLOOKUP(BD54,'Axe 2 Règles de gestion'!$D$2:$F$271,3, FALSE) -> La durée réelle est fixée à 3 ans maximum renouvelable pour chaque période. | BR54: POS_C_004 | BS54: =VLOOKUP(BR54,'Axe 2 Règles de gestion'!$D$2:$F$271,3, FALSE) -> La date de début de position doit être antérieure ou égale à la date de fin prévisionnelle de position. | BT54: POS_C_005 | BU54: =VLOOKUP(BT54,'Axe 2 Règles de gestion'!$D$2:$F$271,3, FALSE) -> La date de début de la position doit être postérieure ou égale à la date d'entrée dans la FPE ou dans la carrière militaire. | BV54: POS_C_007 | BW54: =VLOOKUP(BV54,'Axe 2 Règles de gestion'!$D$2:$F$271,3, FALSE) -> La date de fin réelle de la position doit être antérieure à la date limite de départ à la retraite. | BX54: POS_C_010 | BY54: =VLOOKUP(BX54,'Axe 2 Règles de gestion'!$D$2:$F$271,3, FALSE) -> La date de début de position doit être antérieure ou égale à la date de fin réelle de position. | BZ54: POS_C_012 | CA54: =VLOOKUP(BZ54,'Axe 2 Règles de gestion'!$D$2:$F$271,3, FALSE) -> La date de fin prévisionnelle de la position doit être antérieure à la date limite de départ à la retraite. | CB54: POS_C_022 | CC54: =VLOOKUP(CB54,'Axe 2 Règles de gestion'!$D$2:$F$271,3, FALSE) -> La date de début de position est à J+1 de la date de fin de position de l'occurrence précédente. | CD54: POS_C_037 | CE54: =VLOOKUP(CD54,'Axe 2 Règles de gestion'!$D$2:$F$271,3, FALSE) -> Les champs "Type d'organisme d'accueil" et "Pays" de l'organisme d'accueil doivent être renseignés. | CF54: POS_C_111 | CG54: =VLOOKUP(CF54,'Axe 2 Règles de gestion'!$D$2:$F$271,3, FALSE) -> La date de fin ou la date de fin prévisionnelle doit être saisie. | CH54: POS_C_431 | CI54: =VLOOKUP(CH54,'Axe 2 Règles de gestion'!$D$2:$F$271,3, FALSE) -> Les champs "Ministère (ou institution de la République) d'accueil", "Corps d'accueil en détachement" et "Grade d'accueil en détachement" ou "Ministère (ou institution de la République) d'accueil", "Emploi fonctionnel d'accueil en détachement" et "Groupe dans un emploi fonctionnel d'accueil" sont renseignés si le "Type d'organisme d'accueil" est valorisé à FPE. | CJ54: POS_C_434 | CK54: =VLOOKUP(CJ54,'Axe 2 Règles de gestion'!$D$2:$F$271,3, FALSE) -> Le champ "Organisme d'accueil" doit être alimenté si le type d'organisme d'accueil est égal à 'Autre organisme', 'Fonction publique d'un état de l'Union Européenne' ou 'Fonction publique Européenne'.
A55: 20.00.00 | B55: M | C55: 43152.5 | D55: D0004 | E55: Position | F55: S0017 | G55: Mise à disposition sortante | H55: E0203 | I55: MAD sortante avec remboursement auprès d'une autre administration ou d'un EPA de l'Etat | J55: Position administrative saisie égale à 'MAD sortante avec remboursement auprès d'une autre administration ou d'un EPA de l'Etat' | K55: A_POS_POSIAD [Saisi] = 'MAD51' | L55: T0598 | M55: MADS avec remboursement auprès d'une autre administration ou d'un EPA de l'Etat - Fin | N55: Modification | O55: L'indicateur de renouvellement saisi est égal à l'indicateur de renouvellement avant saisie | P55: A_POS_INDREN [Saisi] = A_POS_INDREN [Valeur avant saisie] | Q55: Magistrat de l'ordre judiciaire | R55: P0007 | S55: Particulier | T55: Passant | U55: 40725 | W55: MAD_I_054 ET MAD_I_055 ET MAD_I_056 ET MAD_I_057 ET MAD_I_059 ET MAD_D_145 ET MAD_D_445 ET POS_C_004 ET POS_C_007 ET POS_C_010 ET POS_C_012 ET POS_C_037 ET POS_C_111 ET POS_C_431 ET POS_C_434 | X55: MAD_I_054 | Y55: =VLOOKUP(X55,'Axe 2 Règles de gestion'!$D$2:$F$271,3, FALSE) -> La mise à disposition peut prendre fin avant le terme prévu à la demande du magistrat, ou de l'administration d'origine, ou de l'organisme d'accueil. | Z55: MAD_I_055 | AA55: =VLOOKUP(Z55,'Axe 2 Règles de gestion'!$D$2:$F$271,3, FALSE) -> Il peut être mis fin à la mise à disposition avant le terme fixé, sous réserve du respect des règles de préavis éventuellement prévues dans la convention. | AB55: MAD_I_056 | AC55: =VLOOKUP(AB55,'Axe 2 Règles de gestion'!$D$2:$F$271,3, FALSE) -> En cas de faute disciplinaire, la mise à disposition prend fin sans préavis par accord entre l'administration d'origine et l'organisme d'accueil. | AD55: MAD_I_057 | AE55: =VLOOKUP(AD55,'Axe 2 Règles de gestion'!$D$2:$F$271,3, FALSE) -> L'agent est affecté soit aux mêmes fonctions dans son service d'origine soit dans l'un des emplois que son grade lui donne vocation à occuper. | AF55: MAD_I_059 | AG55: =VLOOKUP(AF55,'Axe 2 Règles de gestion'!$D$2:$F$271,3, FALSE) -> L'agent mis à disposition qui accepte la proposition d'intégration émise par son administration d'accueil est intégré dans un corps comparable à son corps d'origine. | BB55: MAD_D_145 | BC55: =VLOOKUP(BB55,'Axe 2 Règles de gestion'!$D$2:$F$271,3, FALSE) -> La durée prévisionnelle est fixée à 3 ans maximum renouvelable pour chaque période. | BD55: MAD_D_445 | BE55: =VLOOKUP(BD55,'Axe 2 Règles de gestion'!$D$2:$F$271,3, FALSE) -> La durée réelle est fixée à 3 ans maximum renouvelable pour chaque période. | BR55: POS_C_004 | BS55: =VLOOKUP(BR55,'Axe 2 Règles de gestion'!$D$2:$F$271,3, FALSE) -> La date de début de position doit être antérieure ou égale à la date de fin prévisionnelle de position. | BT55: POS_C_007 | BU55: =VLOOKUP(BT55,'Axe 2 Règles de gestion'!$D$2:$F$271,3, FALSE) -> La date de fin réelle de la position doit être antérieure à la date limite de départ à la retraite. | BV55: POS_C_010 | BW55: =VLOOKUP(BV55,'Axe 2 Règles de gestion'!$D$2:$F$271,3, FALSE) -> La date de début de position doit être antérieure ou égale à la date de fin réelle de position. | BX55: POS_C_012 | BY55: =VLOOKUP(BX55,'Axe 2 Règles de gestion'!$D$2:$F$271,3, FALSE) -> La date de fin prévisionnelle de la position doit être antérieure à la date limite de départ à la retraite. | BZ55: POS_C_037 | CA55: =VLOOKUP(BZ55,'Axe 2 Règles de gestion'!$D$2:$F$271,3, FALSE) -> Les champs "Type d'organisme d'accueil" et "Pays" de l'organisme d'accueil doivent être renseignés. | CB55: POS_C_111 | CC55: =VLOOKUP(CB55,'Axe 2 Règles de gestion'!$D$2:$F$271,3, FALSE) -> La date de fin ou la date de fin prévisionnelle doit être saisie. | CD55: POS_C_431 | CE55: =VLOOKUP(CD55,'Axe 2 Règles de gestion'!$D$2:$F$271,3, FALSE) -> Les champs "Ministère (ou institution de la République) d'accueil", "Corps d'accueil en détachement" et "Grade d'accueil en détachement" ou "Ministère (ou institution de la République) d'accueil", "Emploi fonctionnel d'accueil en détachement" et "Groupe dans un emploi fonctionnel d'accueil" sont renseignés si le "Type d'organisme d'accueil" est valorisé à FPE. | CF55: POS_C_434 | CG55: =VLOOKUP(CF55,'Axe 2 Règles de gestion'!$D$2:$F$271,3, FALSE) -> Le champ "Organisme d'accueil" doit être alimenté si le type d'organisme d'accueil est égal à 'Autre organisme', 'Fonction publique d'un état de l'Union Européenne' ou 'Fonction publique Européenne'.
A56: 17.10.00 | B56: A | C56: 43152.5 | D56: D0004 | E56: Position | F56: S0017 | G56: Mise à disposition sortante | H56: E0203 | I56: MAD sortante avec remboursement auprès d'une autre administration ou d'un EPA de l'Etat | J56: Position administrative saisie égale à 'MAD sortante avec remboursement auprès d'une autre administration ou d'un EPA de l'Etat' | K56: A_POS_POSIAD [Saisi] = 'MAD51' | L56: T0596 | M56: MADS avec remboursement auprès d'une autre administration ou d'un EPA de l'Etat - Demande | N56: Création Modification | O56: Indicateur Renouvellement Position est non activé ET l'indicateur de renouvellement saisi est différent de l'indicateur de renouvellement avant saisie | P56: A_POS_INDREN [Saisi] = '0' ET A_POS_INDREN [Saisi] <> A_POS_INDREN [Valeur avant saisie] | Q56: Personnel civil payé à l'acte ou à la tâche | R56: P0054 | S56: Particulier | T56: Exclu | U56: 40725
A57: 17.10.00 | B57: A | C57: 43152.5 | D57: D0004 | E57: Position | F57: S0017 | G57: Mise à disposition sortante | H57: E0203 | I57: MAD sortante avec remboursement auprès d'une autre administration ou d'un EPA de l'Etat | J57: Position administrative saisie égale à 'MAD sortante avec remboursement auprès d'une autre administration ou d'un EPA de l'Etat' | K57: A_POS_POSIAD [Saisi] = 'MAD51' | L57: T0597 | M57: MADS avec remboursement auprès d'une autre administration ou d'un EPA de l'Etat - Renouvellement | N57: Création Modification | O57: Indicateur Renouvellement Position est activé ET l'indicateur de renouvellement saisi est différent de l'indicateur de renouvellement avant saisie | P57: A_POS_INDREN [Saisi] = '1' ET A_POS_INDREN [Saisi] <> A_POS_INDREN [Valeur avant saisie] | Q57: Personnel civil payé à l'acte ou à la tâche | R57: P0054 | S57: Particulier | T57: Exclu | U57: 40725
A58: 17.10.00 | B58: A | C58: 43152.5 | D58: D0004 | E58: Position | F58: S0017 | G58: Mise à disposition sortante | H58: E0203 | I58: MAD sortante avec remboursement auprès d'une autre administration ou d'un EPA de l'Etat | J58: Position administrative saisie égale à 'MAD sortante avec remboursement auprès d'une autre administration ou d'un EPA de l'Etat' | K58: A_POS_POSIAD [Saisi] = 'MAD51' | L58: T0598 | M58: MADS avec remboursement auprès d'une autre administration ou d'un EPA de l'Etat - Fin | N58: Modification | O58: L'indicateur de renouvellement saisi est égal à l'indicateur de renouvellement avant saisie | P58: A_POS_INDREN [Saisi] = A_POS_INDREN [Valeur avant saisie] | Q58: Personnel civil payé à l'acte ou à la tâche | R58: P0054 | S58: Particulier | T58: Exclu | U58: 40725
A59: 20.00.00 | B59: M | C59: 43189.5 | D59: D0004 | E59: Position | F59: S0017 | G59: Mise à disposition sortante | H59: E0203 | I59: MAD sortante avec remboursement auprès d'une autre administration ou d'un EPA de l'Etat | J59: Position administrative saisie égale à 'MAD sortante avec remboursement auprès d'une autre administration ou d'un EPA de l'Etat' | K59: A_POS_POSIAD [Saisi] = 'MAD51' | L59: T0596 | M59: MADS avec remboursement auprès d'une autre administration ou d'un EPA de l'Etat - Demande | N59: Création Modification | O59: Indicateur Renouvellement Position est non activé ET l'indicateur de renouvellement saisi est différent de l'indicateur de renouvellement avant saisie | P59: A_POS_INDREN [Saisi] = '0' ET A_POS_INDREN [Saisi] <> A_POS_INDREN [Valeur avant saisie] | Q59: Ouvrier de la défense réglementé affilié | R59: P0093 | S59: Particulier | T59: Passant | U59: 40725 | W59: MAD_I_060 ET MAD_I_062 ET MAD_I_061 ET MAD_I_097 ET MAD_D_061 ET MAD_D_070 ET POS_C_009 ET POS_C_004 ET POS_C_010 ET POS_C_007 ET POS_C_012 ET POS_C_106 ET POS_C_006 ET POS_C_431 ET POS_C_434 ET POS_C_022 ET POS_C_111 ET POS_C_037 ET POS_C_100 | X59: MAD_I_060 | Y59: =VLOOKUP(X59,'Axe 2 Règles de gestion'!$D$2:$F$271,3, FALSE) -> L'agent doit effectuer une demande. | Z59: MAD_I_062 | AA59: =VLOOKUP(Z59,'Axe 2 Règles de gestion'!$D$2:$F$271,3, FALSE) -> La mise à disposition n'intervient qu'après signature d'une convention passée entre l'administration gestionnaire et l'organisme d'accueil. | AB59: MAD_I_061 | AC59: =VLOOKUP(AB59,'Axe 2 Règles de gestion'!$D$2:$F$271,3, FALSE) -> La mise à disposition est prononcée par décision du ministère de la Défense. | AD59: MAD_I_097 | AE59: =VLOOKUP(AD59,'Axe 2 Règles de gestion'!$D$2:$F$271,3, FALSE) -> L'organisme d'accueil restitue au ministère de la défense, selon la procédure du rétablissement de crédits (ou par remboursement des organismes publics d'accueil), le montant des dépenses et charges sociales correspondant à l'emploi occupé par l'agent. | BB59: MAD_D_061 | BC59: =VLOOKUP(BB59,'Axe 2 Règles de gestion'!$D$2:$F$271,3, FALSE) -> La durée prévisionnelle est fixée à 5 ans renouvelable pour chaque période. | BD59: MAD_D_070 | BE59: =VLOOKUP(BD59,'Axe 2 Règles de gestion'!$D$2:$F$271,3, FALSE) -> La durée réelle est fixée à 5 ans renouvelable pour chaque période. | BR59: POS_C_009 | BS59: =VLOOKUP(BR59,'Axe 2 Règles de gestion'!$D$2:$F$271,3, FALSE) -> La date de début de la position doit être postérieure ou égale à la date de début du lien juridique. | BT59: POS_C_004 | BU59: =VLOOKUP(BT59,'Axe 2 Règles de gestion'!$D$2:$F$271,3, FALSE) -> La date de début de position doit être antérieure ou égale à la date de fin prévisionnelle de position. | BV59: POS_C_010 | BW59: =VLOOKUP(BV59,'Axe 2 Règles de gestion'!$D$2:$F$271,3, FALSE) -> La date de début de position doit être antérieure ou égale à la date de fin réelle de position. | BX59: POS_C_007 | BY59: =VLOOKUP(BX59,'Axe 2 Règles de gestion'!$D$2:$F$271,3, FALSE) -> La date de fin réelle de la position doit être antérieure à la date limite de départ à la retraite. | BZ59: POS_C_012 | CA59: =VLOOKUP(BZ59,'Axe 2 Règles de gestion'!$D$2:$F$271,3, FALSE) -> La date de fin prévisionnelle de la position doit être antérieure à la date limite de départ à la retraite. | CB59: POS_C_106 | CC59: =VLOOKUP(CB59,'Axe 2 Règles de gestion'!$D$2:$F$271,3, FALSE) -> La date de fin prévisionnelle de la position doit être antérieure ou égale à la date de fin réelle ou prévisionnelle du lien juridique. | CD59: POS_C_006 | CE59: =VLOOKUP(CD59,'Axe 2 Règles de gestion'!$D$2:$F$271,3, FALSE) -> La date de fin réelle de la position doit être antérieure ou égale à la date de fin réelle ou prévisionnelle du lien juridique. | CF59: POS_C_431 | CG59: =VLOOKUP(CF59,'Axe 2 Règles de gestion'!$D$2:$F$271,3, FALSE) -> Les champs "Ministère (ou institution de la République) d'accueil", "Corps d'accueil en détachement" et "Grade d'accueil en détachement" ou "Ministère (ou institution de la République) d'accueil", "Emploi fonctionnel d'accueil en détachement" et "Groupe dans un emploi fonctionnel d'accueil" sont renseignés si le "Type d'organisme d'accueil" est valorisé à FPE. | CH59: POS_C_434 | CI59: =VLOOKUP(CH59,'Axe 2 Règles de gestion'!$D$2:$F$271,3, FALSE) -> Le champ "Organisme d'accueil" doit être alimenté si le type d'organisme d'accueil est égal à 'Autre organisme', 'Fonction publique d'un état de l'Union Européenne' ou 'Fonction publique Européenne'. | CJ59: POS_C_022 | CK59: =VLOOKUP(CJ59,'Axe 2 Règles de gestion'!$D$2:$F$271,3, FALSE) -> La date de début de position est à J+1 de la date de fin de position de l'occurrence précédente. | CL59: POS_C_111 | CM59: =VLOOKUP(CL59,'Axe 2 Règles de gestion'!$D$2:$F$271,3, FALSE) -> La date de fin ou la date de fin prévisionnelle doit être saisie. | CN59: POS_C_037 | CO59: =VLOOKUP(CN59,'Axe 2 Règles de gestion'!$D$2:$F$271,3, FALSE) -> Les champs "Type d'organisme d'accueil" et "Pays" de l'organisme d'accueil doivent être renseignés. | CP59: POS_C_100 | CQ59: =VLOOKUP(CP59,'Axe 2 Règles de gestion'!$D$2:$F$271,3, FALSE) -> Lors de la demande initiale, l'agent doit être en activité.
A60: 20.00.00 | B60: M | C60: 43189.5 | D60: D0004 | E60: Position | F60: S0017 | G60: Mise à disposition sortante | H60: E0203 | I60: MAD sortante avec remboursement auprès d'une autre administration ou d'un EPA de l'Etat | J60: Position administrative saisie égale à 'MAD sortante avec remboursement auprès d'une autre administration ou d'un EPA de l'Etat' | K60: A_POS_POSIAD [Saisi] = 'MAD51' | L60: T0597 | M60: MADS avec remboursement auprès d'une autre administration ou d'un EPA de l'Etat - Renouvellement | N60: Création Modification | O60: Indicateur Renouvellement Position est activé ET l'indicateur de renouvellement saisi est différent de l'indicateur de renouvellement avant saisie | P60: A_POS_INDREN [Saisi] = '1' ET A_POS_INDREN [Saisi] <> A_POS_INDREN [Valeur avant saisie] | Q60: Ouvrier de la défense réglementé affilié | R60: P0093 | S60: Particulier | T60: Passant | U60: 40725 | W60: MAD_I_096 ET MAD_I_062 ET MAD_D_061 ET MAD_D_070 ET POS_C_009 ET POS_C_004 ET POS_C_010 ET POS_C_007 ET POS_C_012 ET POS_C_106 ET POS_C_006 ET POS_C_431 ET POS_C_434 ET POS_C_022 ET POS_C_111 ET POS_C_037 | X60: MAD_I_096 | Y60: =VLOOKUP(X60,'Axe 2 Règles de gestion'!$D$2:$F$271,3, FALSE) -> L'agent demande le renouvellement.de sa mise à disposition. | Z60: MAD_I_062 | AA60: =VLOOKUP(Z60,'Axe 2 Règles de gestion'!$D$2:$F$271,3, FALSE) -> La mise à disposition n'intervient qu'après signature d'une convention passée entre l'administration gestionnaire et l'organisme d'accueil. | BB60: MAD_D_061 | BC60: =VLOOKUP(BB60,'Axe 2 Règles de gestion'!$D$2:$F$271,3, FALSE) -> La durée prévisionnelle est fixée à 5 ans renouvelable pour chaque période. | BD60: MAD_D_070 | BE60: =VLOOKUP(BD60,'Axe 2 Règles de gestion'!$D$2:$F$271,3, FALSE) -> La durée réelle est fixée à 5 ans renouvelable pour chaque période. | BR60: POS_C_009 | BS60: =VLOOKUP(BR60,'Axe 2 Règles de gestion'!$D$2:$F$271,3, FALSE) -> La date de début de la position doit être postérieure ou égale à la date de début du lien juridique. | BT60: POS_C_004 | BU60: =VLOOKUP(BT60,'Axe 2 Règles de gestion'!$D$2:$F$271,3, FALSE) -> La date de début de position doit être antérieure ou égale à la date de fin prévisionnelle de position. | BV60: POS_C_010 | BW60: =VLOOKUP(BV60,'Axe 2 Règles de gestion'!$D$2:$F$271,3, FALSE) -> La date de début de position doit être antérieure ou égale à la date de fin réelle de position. | BX60: POS_C_007 | BY60: =VLOOKUP(BX60,'Axe 2 Règles de gestion'!$D$2:$F$271,3, FALSE) -> La date de fin réelle de la position doit être antérieure à la date limite de départ à la retraite. | BZ60: POS_C_012 | CA60: =VLOOKUP(BZ60,'Axe 2 Règles de gestion'!$D$2:$F$271,3, FALSE) -> La date de fin prévisionnelle de la position doit être antérieure à la date limite de départ à la retraite. | CB60: POS_C_106 | CC60: =VLOOKUP(CB60,'Axe 2 Règles de gestion'!$D$2:$F$271,3, FALSE) -> La date de fin prévisionnelle de la position doit être antérieure ou égale à la date de fin réelle ou prévisionnelle du lien juridique. | CD60: POS_C_006 | CE60: =VLOOKUP(CD60,'Axe 2 Règles de gestion'!$D$2:$F$271,3, FALSE) -> La date de fin réelle de la position doit être antérieure ou égale à la date de fin réelle ou prévisionnelle du lien juridique. | CF60: POS_C_431 | CG60: =VLOOKUP(CF60,'Axe 2 Règles de gestion'!$D$2:$F$271,3, FALSE) -> Les champs "Ministère (ou institution de la République) d'accueil", "Corps d'accueil en détachement" et "Grade d'accueil en détachement" ou "Ministère (ou institution de la République) d'accueil", "Emploi fonctionnel d'accueil en détachement" et "Groupe dans un emploi fonctionnel d'accueil" sont renseignés si le "Type d'organisme d'accueil" est valorisé à FPE. | CH60: POS_C_434 | CI60: =VLOOKUP(CH60,'Axe 2 Règles de gestion'!$D$2:$F$271,3, FALSE) -> Le champ "Organisme d'accueil" doit être alimenté si le type d'organisme d'accueil est égal à 'Autre organisme', 'Fonction publique d'un état de l'Union Européenne' ou 'Fonction publique Européenne'. | CJ60: POS_C_022 | CK60: =VLOOKUP(CJ60,'Axe 2 Règles de gestion'!$D$2:$F$271,3, FALSE) -> La date de début de position est à J+1 de la date de fin de position de l'occurrence précédente. | CL60: POS_C_111 | CM60: =VLOOKUP(CL60,'Axe 2 Règles de gestion'!$D$2:$F$271,3, FALSE) -> La date de fin ou la date de fin prévisionnelle doit être saisie. | CN60: POS_C_037 | CO60: =VLOOKUP(CN60,'Axe 2 Règles de gestion'!$D$2:$F$271,3, FALSE) -> Les champs "Type d'organisme d'accueil" et "Pays" de l'organisme d'accueil doivent être renseignés.
