Workbook
Name date_DIADC: 'Mode opératoire'!#REF!
Name notice_DIADC: 'Mode opératoire'!#REF!
Name notice_ENCHN: 'Mode opératoire'!$B$1:$B$4
Name notice_ICA: 'Mode opératoire'!#REF!

Sheet Mode opératoire
B1: MODE OPERATOIRE
B2: La transaction s'effectue au niveau de la sous rubrique "Position statutaire/situation administrative" Parmi les non titulaires ne sont pas traités pour le moment : - Les enseignants contractuels ou agréés d'établissement privé sous contrat d'association ou sous contrat simple à titre définitif - MEN - Les enseignants contractuels ou agréés d'établissement privé sous contrat d'association ou sous contrat simple à titre provisoire - MEN - Les maitres délégués établissement privé sous contrat d'association - MEN

Sheet Axe 1 Enchainement des RG
A1: Version | B1: Type de mise à jour | C1: Date de mise à jour | D1: Identifiant Domaine | E1: Libellé du Domaine | F1: Identifiant Sous-domaine | G1: Libellé du Sous-domaine | H1: Identifiant Evénement | I1: Libellé de l'évènement | J1: Libellé condition déclenchement Evènement | K1: Condition déclenchement Evènement | L1: Identifiant type d'évènement | M1: Libellé type d'évènement | N1: Type de mise à jour | O1: Libellé condition déclenchement Type Evènement | P1: Condition déclenchement Type Evènement | Q1: Libellé Population | R1: Codification Population | S1: Typologie de population | T1: Général / Particulier | U1: Passant / Exclu | V1: Date de début | W1: Date de fin | X1: Règles mobilisées | Y1: Identifiant Règle de contrôle intellectuel 1 | Z1: Libellé Règle de contrôle intellectuel 1 | AA1: Identifiant Règle de contrôle intellectuel 2 | AB1: Libellé Règle de contrôle intellectuel 2 | AC1: Identifiant Règle de contrôle intellectuel 3 | AD1: Libellé Règle de contrôle intellectuel 3 | AE1: Identifiant Règle de contrôle intellectuel 4 | AF1: Libellé Règle de contrôle intellectuel 4 | AG1: Identifiant Règle de contrôle intellectuel 5 | AH1: Libellé Règle de contrôle intellectuel 5 | AI1: Identifiant Règle de contrôle intellectuel 6 | AJ1: Libellé Règle de contrôle intellectuel 6 | AK1: Identifiant Règle de contrôle intellectuel 7 | AL1: Libellé Règle de contrôle intellectuel 7 | AM1: Identifiant Règle de contrôle intellectuel 8 | AN1: Libellé Règle de contrôle intellectuel 8 | AO1: Identifiant Règle de contrôle intellectuel 9 | AP1: Libellé Règle de contrôle intellectuel 9 | AQ1: Identifiant Règle de contrôle intellectuel 10 | AR1: Libellé Règle de contrôle intellectuel 10 | AS1: Identifiant Règle de contrôle intellectuel 11 | AT1: Libellé Règle de contrôle intellectuel 11 | AU1: Identifiant Règle de contrôle intellectuel 12 | AV1: Libellé Règle de contrôle intellectuel 12 | AW1: Identifiant Règle de contrôle intellectuel 13 | AX1: Libellé Règle de contrôle intellectuel 13 | AY1: Identifiant Règle de condition 1 | AZ1: Libellé Règle de condition 1 | BA1: Identifiant Règle de condition 2 | BB1: Libellé Règle de condition 2 | BC1: Identifiant Règle de condition 3 | BD1: Libellé Règle de condition 3 | BE1: Identifiant Règle de condition 4 | BF1: Libellé Règle de condition 4 | BG1: Identifiant Règle de condition 5 | BH1: Libellé Règle de condition 5 | BI1: Identifiant Règle de condition 6 | BJ1: Libellé Règle de condition 6 | BK1: Identifiant Règle de condition 7 | BL1: Libellé Règle de condition 7 | BM1: Identifiant Règle de condition 8 | BN1: Libellé Règle de condition 8 | BO1: Identifiant Règle de condition 9 | BP1: Libellé Règle de condition 9 | BQ1: Identifiant Règle de condition 10 | BR1: Libellé Règle de condition 10 | BS1: Identifiant Règle de condition 11 | BT1: Libellé Règle de condition 11 | BU1: Identifiant Règle de condition 12 | BV1: Libellé Règle de condition 12 | BW1: Identifiant Règle de condition 13 | BX1: Libellé Règle de condition 13 | BY1: Identifiant Règle de contrôle 1 | BZ1: Libellé Règle de contrôle 1 | CA1: Identifiant Règle de contrôle 2 | CB1: Libellé Règle de contrôle 2 | CC1: Identifiant Règle de contrôle 3 | CD1: Libellé Règle de contrôle 3 | CE1: Identifiant Règle de contrôle 4 | CF1: Libellé Règle de contrôle 4 | CG1: Identifiant Règle de contrôle 5 | CH1: Libellé Règle de contrôle 5 | CI1: Identifiant Règle de contrôle 6 | CJ1: Libellé Règle de contrôle 6 | CK1: Identifiant Règle de contrôle 7 | CL1: Libellé Règle de contrôle 7 | CM1: Identifiant Règle de contrôle 8 | CN1: Libellé Règle de contrôle 8 | CO1: Identifiant Règle de contrôle 9 | CP1: Libellé Règle de contrôle 9 | CQ1: Identifiant Règle de contrôle 10 | CR1: Libellé Règle de contrôle 10 | CS1: Identifiant Règle de contrôle 11 | CT1: Libellé Règle de contrôle 11 | CU1: Identifiant Règle de contrôle 12 | CV1: Libellé Règle de contrôle 12 | CW1: Identifiant Règle de contrôle 13 | CX1: Libellé Règle de contrôle 13 | CY1: Identifiant Règle de contrôle 14 | CZ1: Libellé Règle de contrôle 14 | DA1: Identifiant Règle de contrôle 15 | DB1: Libellé Règle de contrôle 15 | DC1: Identifiant Règle de contrôle 16 | DD1: Libellé Règle de contrôle 16 | DE1: Identifiant Règle de contrôle 17 | DF1: Libellé Règle de contrôle 17 | DG1: Identifiant Règle de contrôle 18 | DH1: Libellé Règle de contrôle 18 | DI1: FIME | DJ1: Statut de travail
A2: 17.10.00 | B2: A | C2: 43152.5 | D2: D0004 | E2: Position | F2: S0031 | G2: Congé parental | H2: E0333 | I2: Congé parental après congé de maternité | J2: Position saisie égale à 'Congé parental après congé de maternité' | K2: A_POS_POSIAD [Saisi] = 'CGP01' | L2: T0964 | M2: Congé parental après congé de maternité - Demande | N2: Création Modification | O2: Indicateur de renouvellement saisi = Non ET (Indicateur de renouvellement saisi différent d'Indicateur de renouvellement avant saisi OU Lien vers enfant saisi différent du Lien vers enfant avant saisi) ET Position saisie de l'occurrence précédente est différente d'une position de 'Congé parental' | P2: A_POS_INDREN [Saisi] = '0' ET (A_POS_INDREN [Saisi] <> A_POS_INDREN [Valeur avant saisie] OU A_POS_LVEPAC [Saisi] <> A_POS_LVEPAC [Valeur avant saisie]) ET (A_POS_POSIAD [Occurrence précédente] = POSITION_SITUATION.R_FOR_IDEN05 ET POSITION_SITUATION.R_REL_PSSAG2 <> 'CGP') | Q2: Titulaire ou magistrat | R2: P0001 | S2: T | T2: Général | U2: Passant | V2: 40725 | W2: 41182 | X2: CPR_D_007 ET CPR_D_702 ET CPR_D_002 ET CPR_D_003 ET CPR_D_025 ET CPR_D_700 ET POS_C_100 ET POS_C_004 ET POS_C_005 ET POS_C_007 ET POS_C_010 ET POS_C_012 ET POS_C_022 ET POS_C_050 ET POS_C_051 ET POS_C_055 ET POS_C_056 ET POS_C_057 ET POS_C_111 | AY2: CPR_D_007 | AZ2: =VLOOKUP(AY2,'Axe 2 Règles de gestion'!$D$2:$F$506,3, FALSE) -> Le congé parental est accordé par périodes de 6 mois maximum renouvelables (date de fin prévisionnelle du congé parental). | BA2: CPR_D_702 | BB2: =VLOOKUP(BA2,'Axe 2 Règles de gestion'!$D$2:$F$506,3, FALSE) -> Le congé parental est accordé par périodes de 6 mois maximum renouvelables (date de fin réelle du congé parental). | BC2: CPR_D_002 | BD2: =VLOOKUP(BC2,'Axe 2 Règles de gestion'!$D$2:$F$506,3, FALSE) -> L'agent doit avoir la qualité de mère ou de père. | BE2: CPR_D_003 | BF2: =VLOOKUP(BE2,'Axe 2 Règles de gestion'!$D$2:$F$506,3, FALSE) -> L'enfant né au foyer doit être âgé de 3 ans au plus (date de fin prévisionnelle du congé parental). | BG2: CPR_D_025 | BH2: =VLOOKUP(BG2,'Axe 2 Règles de gestion'!$D$2:$F$506,3, FALSE) -> Le congé parental est accordé de droit à la mère après un congé maternité. | BI2: CPR_D_700 | BJ2: =VLOOKUP(BI2,'Axe 2 Règles de gestion'!$D$2:$F$506,3, FALSE) -> L'enfant né au foyer doit être âgé de 3 ans au plus (date de fin réelle du congé parental). | BY2: POS_C_100 | BZ2: =VLOOKUP(BY2,'Axe 2 Règles de gestion'!$D$2:$F$506,3, FALSE) -> Lors de la demande initiale, l'agent doit être en activité. | CA2: POS_C_004 | CB2: =VLOOKUP(CA2,'Axe 2 Règles de gestion'!$D$2:$F$506,3, FALSE) -> La date de début de position doit être antérieure ou égale à la date de fin prévisionnelle de position. | CC2: POS_C_005 | CD2: =VLOOKUP(CC2,'Axe 2 Règles de gestion'!$D$2:$F$506,3, FALSE) -> La date de début de la position doit être postérieure ou égale à la date d'entrée dans la FPE ou dans la carrière militaire. | CE2: POS_C_007 | CF2: =VLOOKUP(CE2,'Axe 2 Règles de gestion'!$D$2:$F$506,3, FALSE) -> La date de fin réelle de la position doit être antérieure à la date limite de départ à la retraite. | CG2: POS_C_010 | CH2: =VLOOKUP(CG2,'Axe 2 Règles de gestion'!$D$2:$F$506,3, FALSE) -> La date de début de position doit être antérieure ou égale à la date de fin réelle de position. | CI2: POS_C_012 | CJ2: =VLOOKUP(CI2,'Axe 2 Règles de gestion'!$D$2:$F$506,3, FALSE) -> La date de fin prévisionnelle de la position doit être antérieure à la date limite de départ à la retraite. | CK2: POS_C_022 | CL2: =VLOOKUP(CK2,'Axe 2 Règles de gestion'!$D$2:$F$506,3, FALSE) -> La date de début de position est à J+1 de la date de fin de position de l'occurrence précédente. | CM2: POS_C_050 | CN2: =VLOOKUP(CM2,'Axe 2 Règles de gestion'!$D$2:$F$506,3, FALSE) -> Le lien vers l'enfant doit être renseigné. | CO2: POS_C_051 | CP2: =VLOOKUP(CO2,'Axe 2 Règles de gestion'!$D$2:$F$506,3, FALSE) -> La date de naissance de l'enfant doit être renseignée. | CQ2: POS_C_055 | CR2: =VLOOKUP(CQ2,'Axe 2 Règles de gestion'!$D$2:$F$506,3, FALSE) -> La date de fin réelle de la position doit être antérieure ou égale à la date de décès de l'enfant. | CS2: POS_C_056 | CT2: =VLOOKUP(CS2,'Axe 2 Règles de gestion'!$D$2:$F$506,3, FALSE) -> La date de fin prévisionnelle de la position doit être antérieure ou égale à la date de décès de l'enfant. | CU2: POS_C_057 | CV2: =VLOOKUP(CU2,'Axe 2 Règles de gestion'!$D$2:$F$506,3, FALSE) -> L'agent ne doit pas être en position de détachement entrant sur l'occurrence précédente. | CW2: POS_C_111 | CX2: =VLOOKUP(CW2,'Axe 2 Règles de gestion'!$D$2:$F$506,3, FALSE) -> La date de fin ou la date de fin prévisionnelle doit être saisie.
A3: 25.10.00 | B3: M | C3: 45989.673 | D3: D0004 | E3: Position | F3: S0031 | G3: Congé parental | H3: E0333 | I3: Congé parental après congé de maternité | J3: Position saisie égale à 'Congé parental après congé de maternité' | K3: A_POS_POSIAD [Saisi] = 'CGP01' | L3: T0964 | M3: Congé parental après congé de maternité - Demande | N3: Création Modification | O3: Indicateur de renouvellement saisi = Non ET (Indicateur de renouvellement saisi différent d'Indicateur de renouvellement avant saisi OU Lien vers enfant saisi différent du Lien vers enfant avant saisi) ET Position saisie de l'occurrence précédente est différente d'une position de 'Congé parental' | P3: A_POS_INDREN [Saisi] = '0' ET (A_POS_INDREN [Saisi] <> A_POS_INDREN [Valeur avant saisie] OU A_POS_LVEPAC [Saisi] <> A_POS_LVEPAC [Valeur avant saisie]) ET (A_POS_POSIAD [Occurrence précédente] = POSITION_SITUATION.R_FOR_IDEN05 ET POSITION_SITUATION.R_REL_PSSAG2 <> 'CGP') | Q3: Titulaire ou magistrat | R3: P0001 | S3: T | T3: Général | U3: Exclu | V3: 41183 | W3: 46110
A4: 17.10.00 | B4: A | C4: 43152.5 | D4: D0004 | E4: Position | F4: S0031 | G4: Congé parental | H4: E0333 | I4: Congé parental après congé de maternité | J4: Position saisie égale à 'Congé parental après congé de maternité' | K4: A_POS_POSIAD [Saisi] = 'CGP01' | L4: T0965 | M4: Congé parental après congé de maternité - Renouvellement | N4: Création Modification | O4: Indicateur de renouvellement saisi = Oui ET (Indicateur de renouvellement saisi différent d'Indicateur de renouvellement avant saisi OU Lien vers enfant saisi différent du Lien vers enfant avant saisi) | P4: A_POS_INDREN [Saisi] = '1' ET (A_POS_INDREN [Saisi] <> A_POS_INDREN [Valeur avant saisie] OU A_POS_LVEPAC [Saisi] <> A_POS_LVEPAC [Valeur avant saisie]) | Q4: Titulaire ou magistrat | R4: P0001 | S4: T | T4: Général | U4: Passant | V4: 40725 | W4: 41362 | X4: CPR_D_007 ET CPR_D_702 ET CPR_D_002 ET CPR_D_003 ET CPR_D_700 ET POS_C_004 ET POS_C_005 ET POS_C_007 ET POS_C_010 ET POS_C_012 ET POS_C_022 ET POS_C_050 ET POS_C_051 ET POS_C_055 ET POS_C_056 ET POS_C_111 | AY4: CPR_D_007 | AZ4: =VLOOKUP(AY4,'Axe 2 Règles de gestion'!$D$2:$F$506,3, FALSE) -> Le congé parental est accordé par périodes de 6 mois maximum renouvelables (date de fin prévisionnelle du congé parental). | BA4: CPR_D_702 | BB4: =VLOOKUP(BA4,'Axe 2 Règles de gestion'!$D$2:$F$506,3, FALSE) -> Le congé parental est accordé par périodes de 6 mois maximum renouvelables (date de fin réelle du congé parental). | BC4: CPR_D_002 | BD4: =VLOOKUP(BC4,'Axe 2 Règles de gestion'!$D$2:$F$506,3, FALSE) -> L'agent doit avoir la qualité de mère ou de père. | BE4: CPR_D_003 | BF4: =VLOOKUP(BE4,'Axe 2 Règles de gestion'!$D$2:$F$506,3, FALSE) -> L'enfant né au foyer doit être âgé de 3 ans au plus (date de fin prévisionnelle du congé parental). | BG4: CPR_D_700 | BH4: =VLOOKUP(BG4,'Axe 2 Règles de gestion'!$D$2:$F$506,3, FALSE) -> L'enfant né au foyer doit être âgé de 3 ans au plus (date de fin réelle du congé parental). | BY4: POS_C_004 | BZ4: =VLOOKUP(BY4,'Axe 2 Règles de gestion'!$D$2:$F$506,3, FALSE) -> La date de début de position doit être antérieure ou égale à la date de fin prévisionnelle de position. | CA4: POS_C_005 | CB4: =VLOOKUP(CA4,'Axe 2 Règles de gestion'!$D$2:$F$506,3, FALSE) -> La date de début de la position doit être postérieure ou égale à la date d'entrée dans la FPE ou dans la carrière militaire. | CC4: POS_C_007 | CD4: =VLOOKUP(CC4,'Axe 2 Règles de gestion'!$D$2:$F$506,3, FALSE) -> La date de fin réelle de la position doit être antérieure à la date limite de départ à la retraite. | CE4: POS_C_010 | CF4: =VLOOKUP(CE4,'Axe 2 Règles de gestion'!$D$2:$F$506,3, FALSE) -> La date de début de position doit être antérieure ou égale à la date de fin réelle de position. | CG4: POS_C_012 | CH4: =VLOOKUP(CG4,'Axe 2 Règles de gestion'!$D$2:$F$506,3, FALSE) -> La date de fin prévisionnelle de la position doit être antérieure à la date limite de départ à la retraite. | CI4: POS_C_022 | CJ4: =VLOOKUP(CI4,'Axe 2 Règles de gestion'!$D$2:$F$506,3, FALSE) -> La date de début de position est à J+1 de la date de fin de position de l'occurrence précédente. | CK4: POS_C_050 | CL4: =VLOOKUP(CK4,'Axe 2 Règles de gestion'!$D$2:$F$506,3, FALSE) -> Le lien vers l'enfant doit être renseigné. | CM4: POS_C_051 | CN4: =VLOOKUP(CM4,'Axe 2 Règles de gestion'!$D$2:$F$506,3, FALSE) -> La date de naissance de l'enfant doit être renseignée. | CO4: POS_C_055 | CP4: =VLOOKUP(CO4,'Axe 2 Règles de gestion'!$D$2:$F$506,3, FALSE) -> La date de fin réelle de la position doit être antérieure ou égale à la date de décès de l'enfant. | CQ4: POS_C_056 | CR4: =VLOOKUP(CQ4,'Axe 2 Règles de gestion'!$D$2:$F$506,3, FALSE) -> La date de fin prévisionnelle de la position doit être antérieure ou égale à la date de décès de l'enfant. | CS4: POS_C_111 | CT4: =VLOOKUP(CS4,'Axe 2 Règles de gestion'!$D$2:$F$506,3, FALSE) -> La date de fin ou la date de fin prévisionnelle doit être saisie.
A5: 25.10.00 | B5: M | C5: 45989.676 | D5: D0004 | E5: Position | F5: S0031 | G5: Congé parental | H5: E0333 | I5: Congé parental après congé de maternité | J5: Position saisie égale à 'Congé parental après congé de maternité' | K5: A_POS_POSIAD [Saisi] = 'CGP01' | L5: T0965 | M5: Congé parental après congé de maternité - Renouvellement | N5: Création Modification | O5: Indicateur de renouvellement saisi = Oui ET (Indicateur de renouvellement saisi différent d'Indicateur de renouvellement avant saisi OU Lien vers enfant saisi différent du Lien vers enfant avant saisi) | P5: A_POS_INDREN [Saisi] = '1' ET (A_POS_INDREN [Saisi] <> A_POS_INDREN [Valeur avant saisie] OU A_POS_LVEPAC [Saisi] <> A_POS_LVEPAC [Valeur avant saisie]) | Q5: Titulaire ou magistrat | R5: P0001 | S5: T | T5: Général | U5: Exclu | V5: 41363 | W5: 46110
A6: 17.10.00 | B6: A | C6: 43152.5 | D6: D0004 | E6: Position | F6: S0031 | G6: Congé parental | H6: E0333 | I6: Congé parental après congé de maternité | J6: Position saisie égale à 'Congé parental après congé de maternité' | K6: A_POS_POSIAD [Saisi] = 'CGP01' | L6: T0967 | M6: Congé parental après congé de maternité - Réintégration | N6: Modification | O6: Indicateur de renouvellement saisi identique à Indicateur de renouvellement avant saisi ET Lien vers enfant saisi identique au Lien vers enfant avant saisi | P6: A_POS_INDREN [Saisi] = A_POS_INDREN [Valeur avant saisie] ET A_POS_LVEPAC [Saisi] = A_POS_LVEPAC [Valeur avant saisie]) | Q6: Titulaire ou magistrat | R6: P0001 | S6: T | T6: Général | U6: Passant | V6: 40725 | W6: 41362 | X6: CPR_D_007 ET CPR_D_702 ET CPR_D_003 ET CPR_D_700 ET POS_C_004 ET POS_C_007 ET POS_C_010 ET POS_C_012 ET POS_C_050 ET POS_C_051 ET POS_C_055 ET POS_C_056 ET POS_C_111 | AY6: CPR_D_007 | AZ6: =VLOOKUP(AY6,'Axe 2 Règles de gestion'!$D$2:$F$506,3, FALSE) -> Le congé parental est accordé par périodes de 6 mois maximum renouvelables (date de fin prévisionnelle du congé parental). | BA6: CPR_D_702 | BB6: =VLOOKUP(BA6,'Axe 2 Règles de gestion'!$D$2:$F$506,3, FALSE) -> Le congé parental est accordé par périodes de 6 mois maximum renouvelables (date de fin réelle du congé parental). | BC6: CPR_D_003 | BD6: =VLOOKUP(BC6,'Axe 2 Règles de gestion'!$D$2:$F$506,3, FALSE) -> L'enfant né au foyer doit être âgé de 3 ans au plus (date de fin prévisionnelle du congé parental). | BE6: CPR_D_700 | BF6: =VLOOKUP(BE6,'Axe 2 Règles de gestion'!$D$2:$F$506,3, FALSE) -> L'enfant né au foyer doit être âgé de 3 ans au plus (date de fin réelle du congé parental). | BY6: POS_C_004 | BZ6: =VLOOKUP(BY6,'Axe 2 Règles de gestion'!$D$2:$F$506,3, FALSE) -> La date de début de position doit être antérieure ou égale à la date de fin prévisionnelle de position. | CA6: POS_C_007 | CB6: =VLOOKUP(CA6,'Axe 2 Règles de gestion'!$D$2:$F$506,3, FALSE) -> La date de fin réelle de la position doit être antérieure à la date limite de départ à la retraite. | CC6: POS_C_010 | CD6: =VLOOKUP(CC6,'Axe 2 Règles de gestion'!$D$2:$F$506,3, FALSE) -> La date de début de position doit être antérieure ou égale à la date de fin réelle de position. | CE6: POS_C_012 | CF6: =VLOOKUP(CE6,'Axe 2 Règles de gestion'!$D$2:$F$506,3, FALSE) -> La date de fin prévisionnelle de la position doit être antérieure à la date limite de départ à la retraite. | CG6: POS_C_050 | CH6: =VLOOKUP(CG6,'Axe 2 Règles de gestion'!$D$2:$F$506,3, FALSE) -> Le lien vers l'enfant doit être renseigné. | CI6: POS_C_051 | CJ6: =VLOOKUP(CI6,'Axe 2 Règles de gestion'!$D$2:$F$506,3, FALSE) -> La date de naissance de l'enfant doit être renseignée. | CK6: POS_C_055 | CL6: =VLOOKUP(CK6,'Axe 2 Règles de gestion'!$D$2:$F$506,3, FALSE) -> La date de fin réelle de la position doit être antérieure ou égale à la date de décès de l'enfant. | CM6: POS_C_056 | CN6: =VLOOKUP(CM6,'Axe 2 Règles de gestion'!$D$2:$F$506,3, FALSE) -> La date de fin prévisionnelle de la position doit être antérieure ou égale à la date de décès de l'enfant. | CO6: POS_C_111 | CP6: =VLOOKUP(CO6,'Axe 2 Règles de gestion'!$D$2:$F$506,3, FALSE) -> La date de fin ou la date de fin prévisionnelle doit être saisie.
A7: 25.10.00 | B7: M | C7: 45989.707 | D7: D0004 | E7: Position | F7: S0031 | G7: Congé parental | H7: E0333 | I7: Congé parental après congé de maternité | J7: Position saisie égale à 'Congé parental après congé de maternité' | K7: A_POS_POSIAD [Saisi] = 'CGP01' | L7: T0967 | M7: Congé parental après congé de maternité - Réintégration | N7: Modification | O7: Indicateur de renouvellement saisi identique à Indicateur de renouvellement avant saisi ET Lien vers enfant saisi identique au Lien vers enfant avant saisi | P7: A_POS_INDREN [Saisi] = A_POS_INDREN [Valeur avant saisie] ET A_POS_LVEPAC [Saisi] = A_POS_LVEPAC [Valeur avant saisie]) | Q7: Titulaire ou magistrat | R7: P0001 | S7: T | T7: Général | U7: Exclu | V7: 41363 | W7: 46110
A8: 17.10.00 | B8: A | C8: 43152.5 | D8: D0004 | E8: Position | F8: S0031 | G8: Congé parental | H8: E0333 | I8: Congé parental après congé de maternité | J8: Position saisie égale à 'Congé parental après congé de maternité' | K8: A_POS_POSIAD [Saisi] = 'CGP01' | L8: T1578 | M8: Congé parental après Congé de maternité - Demande pendant un Congé parental | N8: Création Modification | O8: Indicateur de renouvellement saisi = Non ET (Indicateur de renouvellement saisi différent d'Indicateur de renouvellement avant saisi OU Lien vers enfant saisi différent du Lien vers enfant avant saisi) ET Position saisie de l'occurrence précédente est une position de 'Congé parental' | P8: A_POS_INDREN [Saisi] = '0' ET (A_POS_INDREN [Saisi] <> A_POS_INDREN [Valeur avant saisie] OU A_POS_LVEPAC [Saisi] <> A_POS_LVEPAC [Valeur avant saisie]) ET (A_POS_POSIAD [Occurrence précédente] = POSITION_SITUATION.R_FOR_IDEN05 ET POSITION_SITUATION.R_REL_PSSAG2 = 'CGP') | Q8: Titulaire ou magistrat | R8: P0001 | S8: T | T8: Général | U8: Passant | V8: 40725 | W8: 41182 | X8: CPR_D_007 ET CPR_D_702 ET CPR_D_657 ET CPR_D_002 ET CPR_D_025 ET CPR_D_066 ET CPR_D_714 ET POS_C_004 ET POS_C_005 ET POS_C_007 ET POS_C_010 ET POS_C_012 ET POS_C_022 ET POS_C_050 ET POS_C_051 ET POS_C_055 ET POS_C_056 ET POS_C_111 | AY8: CPR_D_007 | AZ8: =VLOOKUP(AY8,'Axe 2 Règles de gestion'!$D$2:$F$506,3, FALSE) -> Le congé parental est accordé par périodes de 6 mois maximum renouvelables (date de fin prévisionnelle du congé parental). | BA8: CPR_D_702 | BB8: =VLOOKUP(BA8,'Axe 2 Règles de gestion'!$D$2:$F$506,3, FALSE) -> Le congé parental est accordé par périodes de 6 mois maximum renouvelables (date de fin réelle du congé parental). | BC8: CPR_D_657 | BD8: =VLOOKUP(BC8,'Axe 2 Règles de gestion'!$D$2:$F$506,3, FALSE) -> Si une nouvelle naissance ou adoption intervient alors que l'agent est déjà en position de congé parental, celui-ci a droit, du chef de son nouvel enfant, à un nouveau congé parental. | BE8: CPR_D_002 | BF8: =VLOOKUP(BE8,'Axe 2 Règles de gestion'!$D$2:$F$506,3, FALSE) -> L'agent doit avoir la qualité de mère ou de père. | BG8: CPR_D_025 | BH8: =VLOOKUP(BG8,'Axe 2 Règles de gestion'!$D$2:$F$506,3, FALSE) -> Le congé parental est accordé de droit à la mère après un congé maternité. | BI8: CPR_D_066 | BJ8: =VLOOKUP(BI8,'Axe 2 Règles de gestion'!$D$2:$F$506,3, FALSE) -> L'enfant né au foyer doit être âgé de 3 ans au plus (date de fin prévisionnelle du congé parental). | BK8: CPR_D_714 | BL8: =VLOOKUP(BK8,'Axe 2 Règles de gestion'!$D$2:$F$506,3, FALSE) -> L'enfant né au foyer doit être âgé de 3 ans au plus (date de fin réelle du congé parental). | BY8: POS_C_004 | BZ8: =VLOOKUP(BY8,'Axe 2 Règles de gestion'!$D$2:$F$506,3, FALSE) -> La date de début de position doit être antérieure ou égale à la date de fin prévisionnelle de position. | CA8: POS_C_005 | CB8: =VLOOKUP(CA8,'Axe 2 Règles de gestion'!$D$2:$F$506,3, FALSE) -> La date de début de la position doit être postérieure ou égale à la date d'entrée dans la FPE ou dans la carrière militaire. | CC8: POS_C_007 | CD8: =VLOOKUP(CC8,'Axe 2 Règles de gestion'!$D$2:$F$506,3, FALSE) -> La date de fin réelle de la position doit être antérieure à la date limite de départ à la retraite. | CE8: POS_C_010 | CF8: =VLOOKUP(CE8,'Axe 2 Règles de gestion'!$D$2:$F$506,3, FALSE) -> La date de début de position doit être antérieure ou égale à la date de fin réelle de position. | CG8: POS_C_012 | CH8: =VLOOKUP(CG8,'Axe 2 Règles de gestion'!$D$2:$F$506,3, FALSE) -> La date de fin prévisionnelle de la position doit être antérieure à la date limite de départ à la retraite. | CI8: POS_C_022 | CJ8: =VLOOKUP(CI8,'Axe 2 Règles de gestion'!$D$2:$F$506,3, FALSE) -> La date de début de position est à J+1 de la date de fin de position de l'occurrence précédente. | CK8: POS_C_050 | CL8: =VLOOKUP(CK8,'Axe 2 Règles de gestion'!$D$2:$F$506,3, FALSE) -> Le lien vers l'enfant doit être renseigné. | CM8: POS_C_051 | CN8: =VLOOKUP(CM8,'Axe 2 Règles de gestion'!$D$2:$F$506,3, FALSE) -> La date de naissance de l'enfant doit être renseignée. | CO8: POS_C_055 | CP8: =VLOOKUP(CO8,'Axe 2 Règles de gestion'!$D$2:$F$506,3, FALSE) -> La date de fin réelle de la position doit être antérieure ou égale à la date de décès de l'enfant. | CQ8: POS_C_056 | CR8: =VLOOKUP(CQ8,'Axe 2 Règles de gestion'!$D$2:$F$506,3, FALSE) -> La date de fin prévisionnelle de la position doit être antérieure ou égale à la date de décès de l'enfant. | CS8: POS_C_111 | CT8: =VLOOKUP(CS8,'Axe 2 Règles de gestion'!$D$2:$F$506,3, FALSE) -> La date de fin ou la date de fin prévisionnelle doit être saisie.
A9: 25.10.00 | B9: M | C9: 45992.61 | D9: D0004 | E9: Position | F9: S0031 | G9: Congé parental | H9: E0333 | I9: Congé parental après congé de maternité | J9: Position saisie égale à 'Congé parental après congé de maternité' | K9: A_POS_POSIAD [Saisi] = 'CGP01' | L9: T1578 | M9: Congé parental après Congé de maternité - Demande pendant un Congé parental | N9: Création Modification | O9: Indicateur de renouvellement saisi = Non ET (Indicateur de renouvellement saisi différent d'Indicateur de renouvellement avant saisi OU Lien vers enfant saisi différent du Lien vers enfant avant saisi) ET Position saisie de l'occurrence précédente est une position de 'Congé parental' | P9: A_POS_INDREN [Saisi] = '0' ET (A_POS_INDREN [Saisi] <> A_POS_INDREN [Valeur avant saisie] OU A_POS_LVEPAC [Saisi] <> A_POS_LVEPAC [Valeur avant saisie]) ET (A_POS_POSIAD [Occurrence précédente] = POSITION_SITUATION.R_FOR_IDEN05 ET POSITION_SITUATION.R_REL_PSSAG2 = 'CGP') | Q9: Titulaire ou magistrat | R9: P0001 | S9: T | T9: Général | U9: Exclu | V9: 41183 | W9: 46110
A10: 25.10.00 | B10: M | C10: 45989.674 | D10: D0004 | E10: Position | F10: S0031 | G10: Congé parental | H10: E0333 | I10: Congé parental après congé de maternité | J10: Position saisie égale à 'Congé parental après congé de maternité' | K10: A_POS_POSIAD [Saisi] = 'CGP01' | L10: T0964 | M10: Congé parental après congé de maternité - Demande | N10: Création Modification | O10: Indicateur de renouvellement saisi = Non ET (Indicateur de renouvellement saisi différent d'Indicateur de renouvellement avant saisi OU Lien vers enfant saisi différent du Lien vers enfant avant saisi) ET Position saisie de l'occurrence précédente est différente d'une position de 'Congé parental' | P10: A_POS_INDREN [Saisi] = '0' ET (A_POS_INDREN [Saisi] <> A_POS_INDREN [Valeur avant saisie] OU A_POS_LVEPAC [Saisi] <> A_POS_LVEPAC [Valeur avant saisie]) ET (A_POS_POSIAD [Occurrence précédente] = POSITION_SITUATION.R_FOR_IDEN05 ET POSITION_SITUATION.R_REL_PSSAG2 <> 'CGP') | Q10: Militaire | R10: P0002 | S10: M | T10: Général | U10: Exclu | V10: 40725 | W10: 46110
A11: 25.10.00 | B11: M | C11: 45989.675 | D11: D0004 | E11: Position | F11: S0031 | G11: Congé parental | H11: E0333 | I11: Congé parental après congé de maternité | J11: Position saisie égale à 'Congé parental après congé de maternité' | K11: A_POS_POSIAD [Saisi] = 'CGP01' | L11: T0965 | M11: Congé parental après congé de maternité - Renouvellement | N11: Création Modification | O11: Indicateur de renouvellement saisi = Oui ET (Indicateur de renouvellement saisi différent d'Indicateur de renouvellement avant saisi OU Lien vers enfant saisi différent du Lien vers enfant avant saisi) | P11: A_POS_INDREN [Saisi] = '1' ET (A_POS_INDREN [Saisi] <> A_POS_INDREN [Valeur avant saisie] OU A_POS_LVEPAC [Saisi] <> A_POS_LVEPAC [Valeur avant saisie]) | Q11: Militaire | R11: P0002 | S11: M | T11: Général | U11: Exclu | V11: 40725 | W11: 46110
A12: 25.10.00 | B12: M | C12: 45989.677 | D12: D0004 | E12: Position | F12: S0031 | G12: Congé parental | H12: E0333 | I12: Congé parental après congé de maternité | J12: Position saisie égale à 'Congé parental après congé de maternité' | K12: A_POS_POSIAD [Saisi] = 'CGP01' | L12: T0967 | M12: Congé parental après congé de maternité - Réintégration | N12: Modification | O12: Indicateur de renouvellement saisi identique à Indicateur de renouvellement avant saisi ET Lien vers enfant saisi identique au Lien vers enfant avant saisi | P12: A_POS_INDREN [Saisi] = A_POS_INDREN [Valeur avant saisie] ET A_POS_LVEPAC [Saisi] = A_POS_LVEPAC [Valeur avant saisie]) | Q12: Militaire | R12: P0002 | S12: M | T12: Général | U12: Exclu | V12: 40725 | W12: 46110
A13: 25.10.00 | B13: M | C13: 45992.61 | D13: D0004 | E13: Position | F13: S0031 | G13: Congé parental | H13: E0333 | I13: Congé parental après congé de maternité | J13: Position saisie égale à 'Congé parental après congé de maternité' | K13: A_POS_POSIAD [Saisi] = 'CGP01' | L13: T1578 | M13: Congé parental après Congé de maternité - Demande pendant un Congé parental | N13: Création Modification | O13: Indicateur de renouvellement saisi = Non ET (Indicateur de renouvellement saisi différent d'Indicateur de renouvellement avant saisi OU Lien vers enfant saisi différent du Lien vers enfant avant saisi) ET Position saisie de l'occurrence précédente est une position de 'Congé parental' | P13: A_POS_INDREN [Saisi] = '0' ET (A_POS_INDREN [Saisi] <> A_POS_INDREN [Valeur avant saisie] OU A_POS_LVEPAC [Saisi] <> A_POS_LVEPAC [Valeur avant saisie]) ET (A_POS_POSIAD [Occurrence précédente] = POSITION_SITUATION.R_FOR_IDEN05 ET POSITION_SITUATION.R_REL_PSSAG2 = 'CGP') | Q13: Militaire | R13: P0002 | S13: M | T13: Général | U13: Exclu | V13: 40725 | W13: 46110
A14: 17.10.00 | B14: A | C14: 43152.5 | D14: D0004 | E14: Position | F14: S0031 | G14: Congé parental | H14: E0333 | I14: Congé parental après congé de maternité | J14: Position saisie égale à 'Congé parental après congé de maternité' | K14: A_POS_POSIAD [Saisi] = 'CGP01' | L14: T0964 | M14: Congé parental après congé de maternité - Demande | N14: Création Modification | O14: Indicateur de renouvellement saisi = Non ET (Indicateur de renouvellement saisi différent d'Indicateur de renouvellement avant saisi OU Lien vers enfant saisi différent du Lien vers enfant avant saisi) ET Position saisie de l'occurrence précédente est différente d'une position de 'Congé parental' | P14: A_POS_INDREN [Saisi] = '0' ET (A_POS_INDREN [Saisi] <> A_POS_INDREN [Valeur avant saisie] OU A_POS_LVEPAC [Saisi] <> A_POS_LVEPAC [Valeur avant saisie]) ET (A_POS_POSIAD [Occurrence précédente] = POSITION_SITUATION.R_FOR_IDEN05 ET POSITION_SITUATION.R_REL_PSSAG2 <> 'CGP') | Q14: Contractuel | R14: P0003 | S14: N | T14: Général | U14: Passant | V14: 40725 | W14: 41182 | X14: CPR_D_024 ET CPR_D_744 ET CPR_D_020 ET CPR_D_743 ET CPR_D_018 ET CPR_D_017 ET CPR_D_043 ET POS_C_100 ET POS_C_004 ET POS_C_006 ET POS_C_007 ET POS_C_009 ET POS_C_010 ET POS_C_012 ET POS_C_022 ET POS_C_050 ET POS_C_051 ET POS_C_055 ET POS_C_056 ET POS_C_057 ET POS_C_106 ET POS_C_111 | AY14: CPR_D_024 | AZ14: =VLOOKUP(AY14,'Axe 2 Règles de gestion'!$D$2:$F$506,3, FALSE) -> Le congé parental est accordé par périodes de 6 mois maximum renouvelables (date de fin prévisionnelle du congé parental). | BA14: CPR_D_744 | BB14: =VLOOKUP(BA14,'Axe 2 Règles de gestion'!$D$2:$F$506,3, FALSE) -> Le congé parental est accordé par périodes de 6 mois maximum renouvelables (date de fin réelle du congé parental). | BC14: CPR_D_020 | BD14: =VLOOKUP(BC14,'Axe 2 Règles de gestion'!$D$2:$F$506,3, FALSE) -> L'enfant né au foyer doit être âgé de 3 ans au plus (date de fin prévisionnelle du congé parental). | BE14: CPR_D_743 | BF14: =VLOOKUP(BE14,'Axe 2 Règles de gestion'!$D$2:$F$506,3, FALSE) -> L'enfant né au foyer doit être âgé de 3 ans au plus (date de fin réelle du congé parental). | BG14: CPR_D_018 | BH14: =VLOOKUP(BG14,'Axe 2 Règles de gestion'!$D$2:$F$506,3, FALSE) -> L'agent doit justifier d'une ancienneté minimale d'un an à la date de la naissance. | BI14: CPR_D_017 | BJ14: =VLOOKUP(BI14,'Axe 2 Règles de gestion'!$D$2:$F$506,3, FALSE) -> L'agent doit avoir la qualité de mère ou de père. | BK14: CPR_D_043 | BL14: =VLOOKUP(BK14,'Axe 2 Règles de gestion'!$D$2:$F$506,3, FALSE) -> Le congé parental est accordé de droit à la mère après un congé maternité. | BY14: POS_C_100 | BZ14: =VLOOKUP(BY14,'Axe 2 Règles de gestion'!$D$2:$F$506,3, FALSE) -> Lors de la demande initiale, l'agent doit être en activité. | CA14: POS_C_004 | CB14: =VLOOKUP(CA14,'Axe 2 Règles de gestion'!$D$2:$F$506,3, FALSE) -> La date de début de position doit être antérieure ou égale à la date de fin prévisionnelle de position. | CC14: POS_C_006 | CD14: =VLOOKUP(CC14,'Axe 2 Règles de gestion'!$D$2:$F$506,3, FALSE) -> La date de fin réelle de la position doit être antérieure ou égale à la date de fin réelle ou prévisionnelle du lien juridique. | CE14: POS_C_007 | CF14: =VLOOKUP(CE14,'Axe 2 Règles de gestion'!$D$2:$F$506,3, FALSE) -> La date de fin réelle de la position doit être antérieure à la date limite de départ à la retraite. | CG14: POS_C_009 | CH14: =VLOOKUP(CG14,'Axe 2 Règles de gestion'!$D$2:$F$506,3, FALSE) -> La date de début de la position doit être postérieure ou égale à la date de début du lien juridique. | CI14: POS_C_010 | CJ14: =VLOOKUP(CI14,'Axe 2 Règles de gestion'!$D$2:$F$506,3, FALSE) -> La date de début de position doit être antérieure ou égale à la date de fin réelle de position. | CK14: POS_C_012 | CL14: =VLOOKUP(CK14,'Axe 2 Règles de gestion'!$D$2:$F$506,3, FALSE) -> La date de fin prévisionnelle de la position doit être antérieure à la date limite de départ à la retraite. | CM14: POS_C_022 | CN14: =VLOOKUP(CM14,'Axe 2 Règles de gestion'!$D$2:$F$506,3, FALSE) -> La date de début de position est à J+1 de la date de fin de position de l'occurrence précédente. | CO14: POS_C_050 | CP14: =VLOOKUP(CO14,'Axe 2 Règles de gestion'!$D$2:$F$506,3, FALSE) -> Le lien vers l'enfant doit être renseigné. | CQ14: POS_C_051 | CR14: =VLOOKUP(CQ14,'Axe 2 Règles de gestion'!$D$2:$F$506,3, FALSE) -> La date de naissance de l'enfant doit être renseignée. | CS14: POS_C_055 | CT14: =VLOOKUP(CS14,'Axe 2 Règles de gestion'!$D$2:$F$506,3, FALSE) -> La date de fin réelle de la position doit être antérieure ou égale à la date de décès de l'enfant. | CU14: POS_C_056 | CV14: =VLOOKUP(CU14,'Axe 2 Règles de gestion'!$D$2:$F$506,3, FALSE) -> La date de fin prévisionnelle de la position doit être antérieure ou égale à la date de décès de l'enfant. | CW14: POS_C_057 | CX14: =VLOOKUP(CW14,'Axe 2 Règles de gestion'!$D$2:$F$506,3, FALSE) -> L'agent ne doit pas être en position de détachement entrant sur l'occurrence précédente. | CY14: POS_C_106 | CZ14: =VLOOKUP(CY14,'Axe 2 Règles de gestion'!$D$2:$F$506,3, FALSE) -> La date de fin prévisionnelle de la position doit être antérieure ou égale à la date de fin réelle ou prévisionnelle du lien juridique. | DA14: POS_C_111 | DB14: =VLOOKUP(DA14,'Axe 2 Règles de gestion'!$D$2:$F$506,3, FALSE) -> La date de fin ou la date de fin prévisionnelle doit être saisie.
A15: 25.10.00 | B15: M | C15: 45989.669 | D15: D0004 | E15: Position | F15: S0031 | G15: Congé parental | H15: E0333 | I15: Congé parental après congé de maternité | J15: Position saisie égale à 'Congé parental après congé de maternité' | K15: A_POS_POSIAD [Saisi] = 'CGP01' | L15: T0964 | M15: Congé parental après congé de maternité - Demande | N15: Création Modification | O15: Indicateur de renouvellement saisi = Non ET (Indicateur de renouvellement saisi différent d'Indicateur de renouvellement avant saisi OU Lien vers enfant saisi différent du Lien vers enfant avant saisi) ET Position saisie de l'occurrence précédente est différente d'une position de 'Congé parental' | P15: A_POS_INDREN [Saisi] = '0' ET (A_POS_INDREN [Saisi] <> A_POS_INDREN [Valeur avant saisie] OU A_POS_LVEPAC [Saisi] <> A_POS_LVEPAC [Valeur avant saisie]) ET (A_POS_POSIAD [Occurrence précédente] = POSITION_SITUATION.R_FOR_IDEN05 ET POSITION_SITUATION.R_REL_PSSAG2 <> 'CGP') | Q15: Contractuel | R15: P0003 | S15: N | T15: Général | U15: Exclu | V15: 41183 | W15: 46110
A16: 17.10.00 | B16: A | C16: 43152.5 | D16: D0004 | E16: Position | F16: S0031 | G16: Congé parental | H16: E0333 | I16: Congé parental après congé de maternité | J16: Position saisie égale à 'Congé parental après congé de maternité' | K16: A_POS_POSIAD [Saisi] = 'CGP01' | L16: T0965 | M16: Congé parental après congé de maternité - Renouvellement | N16: Création Modification | O16: Indicateur de renouvellement saisi = Oui ET (Indicateur de renouvellement saisi différent d'Indicateur de renouvellement avant saisi OU Lien vers enfant saisi différent du Lien vers enfant avant saisi) | P16: A_POS_INDREN [Saisi] = '1' ET (A_POS_INDREN [Saisi] <> A_POS_INDREN [Valeur avant saisie] OU A_POS_LVEPAC [Saisi] <> A_POS_LVEPAC [Valeur avant saisie]) | Q16: Contractuel | R16: P0003 | S16: N | T16: Général | U16: Passant | V16: 40725 | W16: 41362 | X16: CPR_D_024 ET CPR_D_744 ET CPR_D_020 ET CPR_D_743 ET CPR_D_018 ET CPR_D_017 ET POS_C_004 ET POS_C_006 ET POS_C_007 ET POS_C_009 ET POS_C_010 ET POS_C_012 ET POS_C_022 ET POS_C_050 ET POS_C_051 ET POS_C_055 ET POS_C_056 ET POS_C_106 ET POS_C_111 | AY16: CPR_D_024 | AZ16: =VLOOKUP(AY16,'Axe 2 Règles de gestion'!$D$2:$F$506,3, FALSE) -> Le congé parental est accordé par périodes de 6 mois maximum renouvelables (date de fin prévisionnelle du congé parental). | BA16: CPR_D_744 | BB16: =VLOOKUP(BA16,'Axe 2 Règles de gestion'!$D$2:$F$506,3, FALSE) -> Le congé parental est accordé par périodes de 6 mois maximum renouvelables (date de fin réelle du congé parental). | BC16: CPR_D_020 | BD16: =VLOOKUP(BC16,'Axe 2 Règles de gestion'!$D$2:$F$506,3, FALSE) -> L'enfant né au foyer doit être âgé de 3 ans au plus (date de fin prévisionnelle du congé parental). | BE16: CPR_D_743 | BF16: =VLOOKUP(BE16,'Axe 2 Règles de gestion'!$D$2:$F$506,3, FALSE) -> L'enfant né au foyer doit être âgé de 3 ans au plus (date de fin réelle du congé parental). | BG16: CPR_D_018 | BH16: =VLOOKUP(BG16,'Axe 2 Règles de gestion'!$D$2:$F$506,3, FALSE) -> L'agent doit justifier d'une ancienneté minimale d'un an à la date de la naissance. | BI16: CPR_D_017 | BJ16: =VLOOKUP(BI16,'Axe 2 Règles de gestion'!$D$2:$F$506,3, FALSE) -> L'agent doit avoir la qualité de mère ou de père. | BY16: POS_C_004 | BZ16: =VLOOKUP(BY16,'Axe 2 Règles de gestion'!$D$2:$F$506,3, FALSE) -> La date de début de position doit être antérieure ou égale à la date de fin prévisionnelle de position. | CA16: POS_C_006 | CB16: =VLOOKUP(CA16,'Axe 2 Règles de gestion'!$D$2:$F$506,3, FALSE) -> La date de fin réelle de la position doit être antérieure ou égale à la date de fin réelle ou prévisionnelle du lien juridique. | CC16: POS_C_007 | CD16: =VLOOKUP(CC16,'Axe 2 Règles de gestion'!$D$2:$F$506,3, FALSE) -> La date de fin réelle de la position doit être antérieure à la date limite de départ à la retraite. | CE16: POS_C_009 | CF16: =VLOOKUP(CE16,'Axe 2 Règles de gestion'!$D$2:$F$506,3, FALSE) -> La date de début de la position doit être postérieure ou égale à la date de début du lien juridique. | CG16: POS_C_010 | CH16: =VLOOKUP(CG16,'Axe 2 Règles de gestion'!$D$2:$F$506,3, FALSE) -> La date de début de position doit être antérieure ou égale à la date de fin réelle de position. | CI16: POS_C_012 | CJ16: =VLOOKUP(CI16,'Axe 2 Règles de gestion'!$D$2:$F$506,3, FALSE) -> La date de fin prévisionnelle de la position doit être antérieure à la date limite de départ à la retraite. | CK16: POS_C_022 | CL16: =VLOOKUP(CK16,'Axe 2 Règles de gestion'!$D$2:$F$506,3, FALSE) -> La date de début de position est à J+1 de la date de fin de position de l'occurrence précédente. | CM16: POS_C_050 | CN16: =VLOOKUP(CM16,'Axe 2 Règles de gestion'!$D$2:$F$506,3, FALSE) -> Le lien vers l'enfant doit être renseigné. | CO16: POS_C_051 | CP16: =VLOOKUP(CO16,'Axe 2 Règles de gestion'!$D$2:$F$506,3, FALSE) -> La date de naissance de l'enfant doit être renseignée. | CQ16: POS_C_055 | CR16: =VLOOKUP(CQ16,'Axe 2 Règles de gestion'!$D$2:$F$506,3, FALSE) -> La date de fin réelle de la position doit être antérieure ou égale à la date de décès de l'enfant. | CS16: POS_C_056 | CT16: =VLOOKUP(CS16,'Axe 2 Règles de gestion'!$D$2:$F$506,3, FALSE) -> La date de fin prévisionnelle de la position doit être antérieure ou égale à la date de décès de l'enfant. | CU16: POS_C_106 | CV16: =VLOOKUP(CU16,'Axe 2 Règles de gestion'!$D$2:$F$506,3, FALSE) -> La date de fin prévisionnelle de la position doit être antérieure ou égale à la date de fin réelle ou prévisionnelle du lien juridique. | CW16: POS_C_111 | CX16: =VLOOKUP(CW16,'Axe 2 Règles de gestion'!$D$2:$F$506,3, FALSE) -> La date de fin ou la date de fin prévisionnelle doit être saisie.
A17: 25.10.00 | B17: M | C17: 45989.675 | D17: D0004 | E17: Position | F17: S0031 | G17: Congé parental | H17: E0333 | I17: Congé parental après congé de maternité | J17: Position saisie égale à 'Congé parental après congé de maternité' | K17: A_POS_POSIAD [Saisi] = 'CGP01' | L17: T0965 | M17: Congé parental après congé de maternité - Renouvellement | N17: Création Modification | O17: Indicateur de renouvellement saisi = Oui ET (Indicateur de renouvellement saisi différent d'Indicateur de renouvellement avant saisi OU Lien vers enfant saisi différent du Lien vers enfant avant saisi) | P17: A_POS_INDREN [Saisi] = '1' ET (A_POS_INDREN [Saisi] <> A_POS_INDREN [Valeur avant saisie] OU A_POS_LVEPAC [Saisi] <> A_POS_LVEPAC [Valeur avant saisie]) | Q17: Contractuel | R17: P0003 | S17: N | T17: Général | U17: Exclu | V17: 41363 | W17: 46110
A18: 17.10.00 | B18: A | C18: 43152.5 | D18: D0004 | E18: Position | F18: S0031 | G18: Congé parental | H18: E0333 | I18: Congé parental après congé de maternité | J18: Position saisie égale à 'Congé parental après congé de maternité' | K18: A_POS_POSIAD [Saisi] = 'CGP01' | L18: T0967 | M18: Congé parental après congé de maternité - Réintégration | N18: Modification | O18: Indicateur de renouvellement saisi identique à Indicateur de renouvellement avant saisi ET Lien vers enfant saisi identique au Lien vers enfant avant saisi | P18: A_POS_INDREN [Saisi] = A_POS_INDREN [Valeur avant saisie] ET A_POS_LVEPAC [Saisi] = A_POS_LVEPAC [Valeur avant saisie]) | Q18: Contractuel | R18: P0003 | S18: N | T18: Général | U18: Passant | V18: 40725 | W18: 41362 | X18: CPR_D_024 ET CPR_D_744 ET CPR_D_020 ET CPR_D_743 ET CPR_D_018 ET POS_C_004 ET POS_C_006 ET POS_C_007 ET POS_C_010 ET POS_C_012 ET POS_C_050 ET POS_C_051 ET POS_C_055 ET POS_C_056 ET POS_C_106 ET POS_C_111 | AY18: CPR_D_024 | AZ18: =VLOOKUP(AY18,'Axe 2 Règles de gestion'!$D$2:$F$506,3, FALSE) -> Le congé parental est accordé par périodes de 6 mois maximum renouvelables (date de fin prévisionnelle du congé parental). | BA18: CPR_D_744 | BB18: =VLOOKUP(BA18,'Axe 2 Règles de gestion'!$D$2:$F$506,3, FALSE) -> Le congé parental est accordé par périodes de 6 mois maximum renouvelables (date de fin réelle du congé parental). | BC18: CPR_D_020 | BD18: =VLOOKUP(BC18,'Axe 2 Règles de gestion'!$D$2:$F$506,3, FALSE) -> L'enfant né au foyer doit être âgé de 3 ans au plus (date de fin prévisionnelle du congé parental). | BE18: CPR_D_743 | BF18: =VLOOKUP(BE18,'Axe 2 Règles de gestion'!$D$2:$F$506,3, FALSE) -> L'enfant né au foyer doit être âgé de 3 ans au plus (date de fin réelle du congé parental). | BG18: CPR_D_018 | BH18: =VLOOKUP(BG18,'Axe 2 Règles de gestion'!$D$2:$F$506,3, FALSE) -> L'agent doit justifier d'une ancienneté minimale d'un an à la date de la naissance. | BY18: POS_C_004 | BZ18: =VLOOKUP(BY18,'Axe 2 Règles de gestion'!$D$2:$F$506,3, FALSE) -> La date de début de position doit être antérieure ou égale à la date de fin prévisionnelle de position. | CA18: POS_C_006 | CB18: =VLOOKUP(CA18,'Axe 2 Règles de gestion'!$D$2:$F$506,3, FALSE) -> La date de fin réelle de la position doit être antérieure ou égale à la date de fin réelle ou prévisionnelle du lien juridique. | CC18: POS_C_007 | CD18: =VLOOKUP(CC18,'Axe 2 Règles de gestion'!$D$2:$F$506,3, FALSE) -> La date de fin réelle de la position doit être antérieure à la date limite de départ à la retraite. | CE18: POS_C_010 | CF18: =VLOOKUP(CE18,'Axe 2 Règles de gestion'!$D$2:$F$506,3, FALSE) -> La date de début de position doit être antérieure ou égale à la date de fin réelle de position. | CG18: POS_C_012 | CH18: =VLOOKUP(CG18,'Axe 2 Règles de gestion'!$D$2:$F$506,3, FALSE) -> La date de fin prévisionnelle de la position doit être antérieure à la date limite de départ à la retraite. | CI18: POS_C_050 | CJ18: =VLOOKUP(CI18,'Axe 2 Règles de gestion'!$D$2:$F$506,3, FALSE) -> Le lien vers l'enfant doit être renseigné. | CK18: POS_C_051 | CL18: =VLOOKUP(CK18,'Axe 2 Règles de gestion'!$D$2:$F$506,3, FALSE) -> La date de naissance de l'enfant doit être renseignée. | CM18: POS_C_055 | CN18: =VLOOKUP(CM18,'Axe 2 Règles de gestion'!$D$2:$F$506,3, FALSE) -> La date de fin réelle de la position doit être antérieure ou égale à la date de décès de l'enfant. | CO18: POS_C_056 | CP18: =VLOOKUP(CO18,'Axe 2 Règles de gestion'!$D$2:$F$506,3, FALSE) -> La date de fin prévisionnelle de la position doit être antérieure ou égale à la date de décès de l'enfant. | CQ18: POS_C_106 | CR18: =VLOOKUP(CQ18,'Axe 2 Règles de gestion'!$D$2:$F$506,3, FALSE) -> La date de fin prévisionnelle de la position doit être antérieure ou égale à la date de fin réelle ou prévisionnelle du lien juridique. | CS18: POS_C_111 | CT18: =VLOOKUP(CS18,'Axe 2 Règles de gestion'!$D$2:$F$506,3, FALSE) -> La date de fin ou la date de fin prévisionnelle doit être saisie.
A19: 25.10.00 | B19: M | C19: 45989.706 | D19: D0004 | E19: Position | F19: S0031 | G19: Congé parental | H19: E0333 | I19: Congé parental après congé de maternité | J19: Position saisie égale à 'Congé parental après congé de maternité' | K19: A_POS_POSIAD [Saisi] = 'CGP01' | L19: T0967 | M19: Congé parental après congé de maternité - Réintégration | N19: Modification | O19: Indicateur de renouvellement saisi identique à Indicateur de renouvellement avant saisi ET Lien vers enfant saisi identique au Lien vers enfant avant saisi | P19: A_POS_INDREN [Saisi] = A_POS_INDREN [Valeur avant saisie] ET A_POS_LVEPAC [Saisi] = A_POS_LVEPAC [Valeur avant saisie]) | Q19: Contractuel | R19: P0003 | S19: N | T19: Général | U19: Exclu | V19: 41363 | W19: 46110
A20: 17.10.00 | B20: A | C20: 43152.5 | D20: D0004 | E20: Position | F20: S0031 | G20: Congé parental | H20: E0333 | I20: Congé parental après congé de maternité | J20: Position saisie égale à 'Congé parental après congé de maternité' | K20: A_POS_POSIAD [Saisi] = 'CGP01' | L20: T1578 | M20: Congé parental après Congé de maternité - Demande pendant un Congé parental | N20: Création Modification | O20: Indicateur de renouvellement saisi = Non ET (Indicateur de renouvellement saisi différent d'Indicateur de renouvellement avant saisi OU Lien vers enfant saisi différent du Lien vers enfant avant saisi) ET Position saisie de l'occurrence précédente est une position de 'Congé parental' | P20: A_POS_INDREN [Saisi] = '0' ET (A_POS_INDREN [Saisi] <> A_POS_INDREN [Valeur avant saisie] OU A_POS_LVEPAC [Saisi] <> A_POS_LVEPAC [Valeur avant saisie]) ET (A_POS_POSIAD [Occurrence précédente] = POSITION_SITUATION.R_FOR_IDEN05 ET POSITION_SITUATION.R_REL_PSSAG2 = 'CGP') | Q20: Contractuel | R20: P0003 | S20: N | T20: Général | U20: Passant | V20: 40725 | W20: 41182 | X20: CPR_D_024 ET CPR_D_744 ET CPR_D_658 ET CPR_D_074 ET CPR_D_747 ET CPR_D_018 ET CPR_D_017 ET CPR_D_043 ET POS_C_004 ET POS_C_006 ET POS_C_007 ET POS_C_009 ET POS_C_010 ET POS_C_012 ET POS_C_022 ET POS_C_050 ET POS_C_051 ET POS_C_055 ET POS_C_056 ET POS_C_106 ET POS_C_111 | AY20: CPR_D_024 | AZ20: =VLOOKUP(AY20,'Axe 2 Règles de gestion'!$D$2:$F$506,3, FALSE) -> Le congé parental est accordé par périodes de 6 mois maximum renouvelables (date de fin prévisionnelle du congé parental). | BA20: CPR_D_744 | BB20: =VLOOKUP(BA20,'Axe 2 Règles de gestion'!$D$2:$F$506,3, FALSE) -> Le congé parental est accordé par périodes de 6 mois maximum renouvelables (date de fin réelle du congé parental). | BC20: CPR_D_658 | BD20: =VLOOKUP(BC20,'Axe 2 Règles de gestion'!$D$2:$F$506,3, FALSE) -> Si une nouvelle naissance ou adoption intervient alors que l'agent est déjà en position de congé parental, celui-ci a droit, du chef de son nouvel enfant, à un nouveau congé parental. | BE20: CPR_D_074 | BF20: =VLOOKUP(BE20,'Axe 2 Règles de gestion'!$D$2:$F$506,3, FALSE) -> L'enfant né au foyer doit être âgé de 3 ans au plus (date de fin prévisionnelle du congé parental). | BG20: CPR_D_747 | BH20: =VLOOKUP(BG20,'Axe 2 Règles de gestion'!$D$2:$F$506,3, FALSE) -> L'enfant né au foyer doit être âgé de 3 ans au plus (date de fin réelle du congé parental). | BI20: CPR_D_018 | BJ20: =VLOOKUP(BI20,'Axe 2 Règles de gestion'!$D$2:$F$506,3, FALSE) -> L'agent doit justifier d'une ancienneté minimale d'un an à la date de la naissance. | BK20: CPR_D_017 | BL20: =VLOOKUP(BK20,'Axe 2 Règles de gestion'!$D$2:$F$506,3, FALSE) -> L'agent doit avoir la qualité de mère ou de père. | BM20: CPR_D_043 | BN20: =VLOOKUP(BM20,'Axe 2 Règles de gestion'!$D$2:$F$506,3, FALSE) -> Le congé parental est accordé de droit à la mère après un congé maternité. | BY20: POS_C_004 | BZ20: =VLOOKUP(BY20,'Axe 2 Règles de gestion'!$D$2:$F$506,3, FALSE) -> La date de début de position doit être antérieure ou égale à la date de fin prévisionnelle de position. | CA20: POS_C_006 | CB20: =VLOOKUP(CA20,'Axe 2 Règles de gestion'!$D$2:$F$506,3, FALSE) -> La date de fin réelle de la position doit être antérieure ou égale à la date de fin réelle ou prévisionnelle du lien juridique. | CC20: POS_C_007 | CD20: =VLOOKUP(CC20,'Axe 2 Règles de gestion'!$D$2:$F$506,3, FALSE) -> La date de fin réelle de la position doit être antérieure à la date limite de départ à la retraite. | CE20: POS_C_009 | CF20: =VLOOKUP(CE20,'Axe 2 Règles de gestion'!$D$2:$F$506,3, FALSE) -> La date de début de la position doit être postérieure ou égale à la date de début du lien juridique. | CG20: POS_C_010 | CH20: =VLOOKUP(CG20,'Axe 2 Règles de gestion'!$D$2:$F$506,3, FALSE) -> La date de début de position doit être antérieure ou égale à la date de fin réelle de position. | CI20: POS_C_012 | CJ20: =VLOOKUP(CI20,'Axe 2 Règles de gestion'!$D$2:$F$506,3, FALSE) -> La date de fin prévisionnelle de la position doit être antérieure à la date limite de départ à la retraite. | CK20: POS_C_022 | CL20: =VLOOKUP(CK20,'Axe 2 Règles de gestion'!$D$2:$F$506,3, FALSE) -> La date de début de position est à J+1 de la date de fin de position de l'occurrence précédente. | CM20: POS_C_050 | CN20: =VLOOKUP(CM20,'Axe 2 Règles de gestion'!$D$2:$F$506,3, FALSE) -> Le lien vers l'enfant doit être renseigné. | CO20: POS_C_051 | CP20: =VLOOKUP(CO20,'Axe 2 Règles de gestion'!$D$2:$F$506,3, FALSE) -> La date de naissance de l'enfant doit être renseignée. | CQ20: POS_C_055 | CR20: =VLOOKUP(CQ20,'Axe 2 Règles de gestion'!$D$2:$F$506,3, FALSE) -> La date de fin réelle de la position doit être antérieure ou égale à la date de décès de l'enfant. | CS20: POS_C_056 | CT20: =VLOOKUP(CS20,'Axe 2 Règles de gestion'!$D$2:$F$506,3, FALSE) -> La date de fin prévisionnelle de la position doit être antérieure ou égale à la date de décès de l'enfant. | CU20: POS_C_106 | CV20: =VLOOKUP(CU20,'Axe 2 Règles de gestion'!$D$2:$F$506,3, FALSE) -> La date de fin prévisionnelle de la position doit être antérieure ou égale à la date de fin réelle ou prévisionnelle du lien juridique. | CW20: POS_C_111 | CX20: =VLOOKUP(CW20,'Axe 2 Règles de gestion'!$D$2:$F$506,3, FALSE) -> La date de fin ou la date de fin prévisionnelle doit être saisie.
A21: 25.10.00 | B21: M | C21: 45992.61 | D21: D0004 | E21: Position | F21: S0031 | G21: Congé parental | H21: E0333 | I21: Congé parental après congé de maternité | J21: Position saisie égale à 'Congé parental après congé de maternité' | K21: A_POS_POSIAD [Saisi] = 'CGP01' | L21: T1578 | M21: Congé parental après Congé de maternité - Demande pendant un Congé parental | N21: Création Modification | O21: Indicateur de renouvellement saisi = Non ET (Indicateur de renouvellement saisi différent d'Indicateur de renouvellement avant saisi OU Lien vers enfant saisi différent du Lien vers enfant avant saisi) ET Position saisie de l'occurrence précédente est une position de 'Congé parental' | P21: A_POS_INDREN [Saisi] = '0' ET (A_POS_INDREN [Saisi] <> A_POS_INDREN [Valeur avant saisie] OU A_POS_LVEPAC [Saisi] <> A_POS_LVEPAC [Valeur avant saisie]) ET (A_POS_POSIAD [Occurrence précédente] = POSITION_SITUATION.R_FOR_IDEN05 ET POSITION_SITUATION.R_REL_PSSAG2 = 'CGP') | Q21: Contractuel | R21: P0003 | S21: N | T21: Général | U21: Exclu | V21: 41183 | W21: 46110
A22: 17.10.00 | B22: A | C22: 43152.5 | D22: D0004 | E22: Position | F22: S0031 | G22: Congé parental | H22: E0333 | I22: Congé parental après congé de maternité | J22: Position saisie égale à 'Congé parental après congé de maternité' | K22: A_POS_POSIAD [Saisi] = 'CGP01' | L22: T0964 | M22: Congé parental après congé de maternité - Demande | N22: Création Modification | O22: Indicateur de renouvellement saisi = Non ET (Indicateur de renouvellement saisi différent d'Indicateur de renouvellement avant saisi OU Lien vers enfant saisi différent du Lien vers enfant avant saisi) ET Position saisie de l'occurrence précédente est différente d'une position de 'Congé parental' | P22: A_POS_INDREN [Saisi] = '0' ET (A_POS_INDREN [Saisi] <> A_POS_INDREN [Valeur avant saisie] OU A_POS_LVEPAC [Saisi] <> A_POS_LVEPAC [Valeur avant saisie]) ET (A_POS_POSIAD [Occurrence précédente] = POSITION_SITUATION.R_FOR_IDEN05 ET POSITION_SITUATION.R_REL_PSSAG2 <> 'CGP') | Q22: Stagiaire ou auditeur ou élève | R22: P0004 | S22: S | T22: Général | U22: Passant | V22: 40725 | W22: 41182 | X22: CPR_D_014 ET CPR_D_705 ET CPR_D_009 ET CPR_D_010 ET CPR_D_034 ET CPR_D_703 ET POS_C_100 ET POS_C_004 ET POS_C_005 ET POS_C_007 ET POS_C_010 ET POS_C_012 ET POS_C_022 ET POS_C_050 ET POS_C_051 ET POS_C_055 ET POS_C_056 ET POS_C_057 ET POS_C_111 | AY22: CPR_D_014 | AZ22: =VLOOKUP(AY22,'Axe 2 Règles de gestion'!$D$2:$F$506,3, FALSE) -> Le congé parental est accordé par périodes de 6 mois maximum renouvelables (date de fin prévisionnelle du congé parental). | BA22: CPR_D_705 | BB22: =VLOOKUP(BA22,'Axe 2 Règles de gestion'!$D$2:$F$506,3, FALSE) -> Le congé parental est accordé par périodes de 6 mois maximum renouvelables (date de fin réelle du congé parental). | BC22: CPR_D_009 | BD22: =VLOOKUP(BC22,'Axe 2 Règles de gestion'!$D$2:$F$506,3, FALSE) -> L'agent doit avoir la qualité de mère ou de père. | BE22: CPR_D_010 | BF22: =VLOOKUP(BE22,'Axe 2 Règles de gestion'!$D$2:$F$506,3, FALSE) -> L'enfant né au foyer doit être âgé de 3 ans au plus (date de fin prévisionnelle du congé parental). | BG22: CPR_D_034 | BH22: =VLOOKUP(BG22,'Axe 2 Règles de gestion'!$D$2:$F$506,3, FALSE) -> Le congé parental est accordé de droit à la mère après un congé maternité. | BI22: CPR_D_703 | BJ22: =VLOOKUP(BI22,'Axe 2 Règles de gestion'!$D$2:$F$506,3, FALSE) -> L'enfant né au foyer doit être âgé de 3 ans au plus (date de fin réelle du congé parental). | BY22: POS_C_100 | BZ22: =VLOOKUP(BY22,'Axe 2 Règles de gestion'!$D$2:$F$506,3, FALSE) -> Lors de la demande initiale, l'agent doit être en activité. | CA22: POS_C_004 | CB22: =VLOOKUP(CA22,'Axe 2 Règles de gestion'!$D$2:$F$506,3, FALSE) -> La date de début de position doit être antérieure ou égale à la date de fin prévisionnelle de position. | CC22: POS_C_005 | CD22: =VLOOKUP(CC22,'Axe 2 Règles de gestion'!$D$2:$F$506,3, FALSE) -> La date de début de la position doit être postérieure ou égale à la date d'entrée dans la FPE ou dans la carrière militaire. | CE22: POS_C_007 | CF22: =VLOOKUP(CE22,'Axe 2 Règles de gestion'!$D$2:$F$506,3, FALSE) -> La date de fin réelle de la position doit être antérieure à la date limite de départ à la retraite. | CG22: POS_C_010 | CH22: =VLOOKUP(CG22,'Axe 2 Règles de gestion'!$D$2:$F$506,3, FALSE) -> La date de début de position doit être antérieure ou égale à la date de fin réelle de position. | CI22: POS_C_012 | CJ22: =VLOOKUP(CI22,'Axe 2 Règles de gestion'!$D$2:$F$506,3, FALSE) -> La date de fin prévisionnelle de la position doit être antérieure à la date limite de départ à la retraite. | CK22: POS_C_022 | CL22: =VLOOKUP(CK22,'Axe 2 Règles de gestion'!$D$2:$F$506,3, FALSE) -> La date de début de position est à J+1 de la date de fin de position de l'occurrence précédente. | CM22: POS_C_050 | CN22: =VLOOKUP(CM22,'Axe 2 Règles de gestion'!$D$2:$F$506,3, FALSE) -> Le lien vers l'enfant doit être renseigné. | CO22: POS_C_051 | CP22: =VLOOKUP(CO22,'Axe 2 Règles de gestion'!$D$2:$F$506,3, FALSE) -> La date de naissance de l'enfant doit être renseignée. | CQ22: POS_C_055 | CR22: =VLOOKUP(CQ22,'Axe 2 Règles de gestion'!$D$2:$F$506,3, FALSE) -> La date de fin réelle de la position doit être antérieure ou égale à la date de décès de l'enfant. | CS22: POS_C_056 | CT22: =VLOOKUP(CS22,'Axe 2 Règles de gestion'!$D$2:$F$506,3, FALSE) -> La date de fin prévisionnelle de la position doit être antérieure ou égale à la date de décès de l'enfant. | CU22: POS_C_057 | CV22: =VLOOKUP(CU22,'Axe 2 Règles de gestion'!$D$2:$F$506,3, FALSE) -> L'agent ne doit pas être en position de détachement entrant sur l'occurrence précédente. | CW22: POS_C_111 | CX22: =VLOOKUP(CW22,'Axe 2 Règles de gestion'!$D$2:$F$506,3, FALSE) -> La date de fin ou la date de fin prévisionnelle doit être saisie.
A23: 25.10.00 | B23: M | C23: 45989.672 | D23: D0004 | E23: Position | F23: S0031 | G23: Congé parental | H23: E0333 | I23: Congé parental après congé de maternité | J23: Position saisie égale à 'Congé parental après congé de maternité' | K23: A_POS_POSIAD [Saisi] = 'CGP01' | L23: T0964 | M23: Congé parental après congé de maternité - Demande | N23: Création Modification | O23: Indicateur de renouvellement saisi = Non ET (Indicateur de renouvellement saisi différent d'Indicateur de renouvellement avant saisi OU Lien vers enfant saisi différent du Lien vers enfant avant saisi) ET Position saisie de l'occurrence précédente est différente d'une position de 'Congé parental' | P23: A_POS_INDREN [Saisi] = '0' ET (A_POS_INDREN [Saisi] <> A_POS_INDREN [Valeur avant saisie] OU A_POS_LVEPAC [Saisi] <> A_POS_LVEPAC [Valeur avant saisie]) ET (A_POS_POSIAD [Occurrence précédente] = POSITION_SITUATION.R_FOR_IDEN05 ET POSITION_SITUATION.R_REL_PSSAG2 <> 'CGP') | Q23: Stagiaire ou auditeur ou élève | R23: P0004 | S23: S | T23: Général | U23: Exclu | V23: 41183 | W23: 46110
A24: 17.10.00 | B24: A | C24: 43152.5 | D24: D0004 | E24: Position | F24: S0031 | G24: Congé parental | H24: E0333 | I24: Congé parental après congé de maternité | J24: Position saisie égale à 'Congé parental après congé de maternité' | K24: A_POS_POSIAD [Saisi] = 'CGP01' | L24: T0965 | M24: Congé parental après congé de maternité - Renouvellement | N24: Création Modification | O24: Indicateur de renouvellement saisi = Oui ET (Indicateur de renouvellement saisi différent d'Indicateur de renouvellement avant saisi OU Lien vers enfant saisi différent du Lien vers enfant avant saisi) | P24: A_POS_INDREN [Saisi] = '1' ET (A_POS_INDREN [Saisi] <> A_POS_INDREN [Valeur avant saisie] OU A_POS_LVEPAC [Saisi] <> A_POS_LVEPAC [Valeur avant saisie]) | Q24: Stagiaire ou auditeur ou élève | R24: P0004 | S24: S | T24: Général | U24: Passant | V24: 40725 | W24: 41362 | X24: CPR_D_014 ET CPR_D_705 ET CPR_D_009 ET CPR_D_010 ET CPR_D_703 ET POS_C_004 ET POS_C_005 ET POS_C_007 ET POS_C_010 ET POS_C_012 ET POS_C_022 ET POS_C_050 ET POS_C_051 ET POS_C_055 ET POS_C_056 ET POS_C_111 | AY24: CPR_D_014 | AZ24: =VLOOKUP(AY24,'Axe 2 Règles de gestion'!$D$2:$F$506,3, FALSE) -> Le congé parental est accordé par périodes de 6 mois maximum renouvelables (date de fin prévisionnelle du congé parental). | BA24: CPR_D_705 | BB24: =VLOOKUP(BA24,'Axe 2 Règles de gestion'!$D$2:$F$506,3, FALSE) -> Le congé parental est accordé par périodes de 6 mois maximum renouvelables (date de fin réelle du congé parental). | BC24: CPR_D_009 | BD24: =VLOOKUP(BC24,'Axe 2 Règles de gestion'!$D$2:$F$506,3, FALSE) -> L'agent doit avoir la qualité de mère ou de père. | BE24: CPR_D_010 | BF24: =VLOOKUP(BE24,'Axe 2 Règles de gestion'!$D$2:$F$506,3, FALSE) -> L'enfant né au foyer doit être âgé de 3 ans au plus (date de fin prévisionnelle du congé parental). | BG24: CPR_D_703 | BH24: =VLOOKUP(BG24,'Axe 2 Règles de gestion'!$D$2:$F$506,3, FALSE) -> L'enfant né au foyer doit être âgé de 3 ans au plus (date de fin réelle du congé parental). | BY24: POS_C_004 | BZ24: =VLOOKUP(BY24,'Axe 2 Règles de gestion'!$D$2:$F$506,3, FALSE) -> La date de début de position doit être antérieure ou égale à la date de fin prévisionnelle de position. | CA24: POS_C_005 | CB24: =VLOOKUP(CA24,'Axe 2 Règles de gestion'!$D$2:$F$506,3, FALSE) -> La date de début de la position doit être postérieure ou égale à la date d'entrée dans la FPE ou dans la carrière militaire. | CC24: POS_C_007 | CD24: =VLOOKUP(CC24,'Axe 2 Règles de gestion'!$D$2:$F$506,3, FALSE) -> La date de fin réelle de la position doit être antérieure à la date limite de départ à la retraite. | CE24: POS_C_010 | CF24: =VLOOKUP(CE24,'Axe 2 Règles de gestion'!$D$2:$F$506,3, FALSE) -> La date de début de position doit être antérieure ou égale à la date de fin réelle de position. | CG24: POS_C_012 | CH24: =VLOOKUP(CG24,'Axe 2 Règles de gestion'!$D$2:$F$506,3, FALSE) -> La date de fin prévisionnelle de la position doit être antérieure à la date limite de départ à la retraite. | CI24: POS_C_022 | CJ24: =VLOOKUP(CI24,'Axe 2 Règles de gestion'!$D$2:$F$506,3, FALSE) -> La date de début de position est à J+1 de la date de fin de position de l'occurrence précédente. | CK24: POS_C_050 | CL24: =VLOOKUP(CK24,'Axe 2 Règles de gestion'!$D$2:$F$506,3, FALSE) -> Le lien vers l'enfant doit être renseigné. | CM24: POS_C_051 | CN24: =VLOOKUP(CM24,'Axe 2 Règles de gestion'!$D$2:$F$506,3, FALSE) -> La date de naissance de l'enfant doit être renseignée. | CO24: POS_C_055 | CP24: =VLOOKUP(CO24,'Axe 2 Règles de gestion'!$D$2:$F$506,3, FALSE) -> La date de fin réelle de la position doit être antérieure ou égale à la date de décès de l'enfant. | CQ24: POS_C_056 | CR24: =VLOOKUP(CQ24,'Axe 2 Règles de gestion'!$D$2:$F$506,3, FALSE) -> La date de fin prévisionnelle de la position doit être antérieure ou égale à la date de décès de l'enfant. | CS24: POS_C_111 | CT24: =VLOOKUP(CS24,'Axe 2 Règles de gestion'!$D$2:$F$506,3, FALSE) -> La date de fin ou la date de fin prévisionnelle doit être saisie.
A25: 25.10.00 | B25: M | C25: 45989.676 | D25: D0004 | E25: Position | F25: S0031 | G25: Congé parental | H25: E0333 | I25: Congé parental après congé de maternité | J25: Position saisie égale à 'Congé parental après congé de maternité' | K25: A_POS_POSIAD [Saisi] = 'CGP01' | L25: T0965 | M25: Congé parental après congé de maternité - Renouvellement | N25: Création Modification | O25: Indicateur de renouvellement saisi = Oui ET (Indicateur de renouvellement saisi différent d'Indicateur de renouvellement avant saisi OU Lien vers enfant saisi différent du Lien vers enfant avant saisi) | P25: A_POS_INDREN [Saisi] = '1' ET (A_POS_INDREN [Saisi] <> A_POS_INDREN [Valeur avant saisie] OU A_POS_LVEPAC [Saisi] <> A_POS_LVEPAC [Valeur avant saisie]) | Q25: Stagiaire ou auditeur ou élève | R25: P0004 | S25: S | T25: Général | U25: Exclu | V25: 41363 | W25: 46110
A26: 17.10.00 | B26: A | C26: 43152.5 | D26: D0004 | E26: Position | F26: S0031 | G26: Congé parental | H26: E0333 | I26: Congé parental après congé de maternité | J26: Position saisie égale à 'Congé parental après congé de maternité' | K26: A_POS_POSIAD [Saisi] = 'CGP01' | L26: T0967 | M26: Congé parental après congé de maternité - Réintégration | N26: Modification | O26: Indicateur de renouvellement saisi identique à Indicateur de renouvellement avant saisi ET Lien vers enfant saisi identique au Lien vers enfant avant saisi | P26: A_POS_INDREN [Saisi] = A_POS_INDREN [Valeur avant saisie] ET A_POS_LVEPAC [Saisi] = A_POS_LVEPAC [Valeur avant saisie]) | Q26: Stagiaire ou auditeur ou élève | R26: P0004 | S26: S | T26: Général | U26: Passant | V26: 40725 | W26: 41362 | X26: CPR_D_014 ET CPR_D_705 ET CPR_D_010 ET CPR_D_703 ET POS_C_004 ET POS_C_007 ET POS_C_010 ET POS_C_012 ET POS_C_050 ET POS_C_051 ET POS_C_055 ET POS_C_056 ET POS_C_111 | AY26: CPR_D_014 | AZ26: =VLOOKUP(AY26,'Axe 2 Règles de gestion'!$D$2:$F$506,3, FALSE) -> Le congé parental est accordé par périodes de 6 mois maximum renouvelables (date de fin prévisionnelle du congé parental). | BA26: CPR_D_705 | BB26: =VLOOKUP(BA26,'Axe 2 Règles de gestion'!$D$2:$F$506,3, FALSE) -> Le congé parental est accordé par périodes de 6 mois maximum renouvelables (date de fin réelle du congé parental). | BC26: CPR_D_010 | BD26: =VLOOKUP(BC26,'Axe 2 Règles de gestion'!$D$2:$F$506,3, FALSE) -> L'enfant né au foyer doit être âgé de 3 ans au plus (date de fin prévisionnelle du congé parental). | BE26: CPR_D_703 | BF26: =VLOOKUP(BE26,'Axe 2 Règles de gestion'!$D$2:$F$506,3, FALSE) -> L'enfant né au foyer doit être âgé de 3 ans au plus (date de fin réelle du congé parental). | BY26: POS_C_004 | BZ26: =VLOOKUP(BY26,'Axe 2 Règles de gestion'!$D$2:$F$506,3, FALSE) -> La date de début de position doit être antérieure ou égale à la date de fin prévisionnelle de position. | CA26: POS_C_007 | CB26: =VLOOKUP(CA26,'Axe 2 Règles de gestion'!$D$2:$F$506,3, FALSE) -> La date de fin réelle de la position doit être antérieure à la date limite de départ à la retraite. | CC26: POS_C_010 | CD26: =VLOOKUP(CC26,'Axe 2 Règles de gestion'!$D$2:$F$506,3, FALSE) -> La date de début de position doit être antérieure ou égale à la date de fin réelle de position. | CE26: POS_C_012 | CF26: =VLOOKUP(CE26,'Axe 2 Règles de gestion'!$D$2:$F$506,3, FALSE) -> La date de fin prévisionnelle de la position doit être antérieure à la date limite de départ à la retraite. | CG26: POS_C_050 | CH26: =VLOOKUP(CG26,'Axe 2 Règles de gestion'!$D$2:$F$506,3, FALSE) -> Le lien vers l'enfant doit être renseigné. | CI26: POS_C_051 | CJ26: =VLOOKUP(CI26,'Axe 2 Règles de gestion'!$D$2:$F$506,3, FALSE) -> La date de naissance de l'enfant doit être renseignée. | CK26: POS_C_055 | CL26: =VLOOKUP(CK26,'Axe 2 Règles de gestion'!$D$2:$F$506,3, FALSE) -> La date de fin réelle de la position doit être antérieure ou égale à la date de décès de l'enfant. | CM26: POS_C_056 | CN26: =VLOOKUP(CM26,'Axe 2 Règles de gestion'!$D$2:$F$506,3, FALSE) -> La date de fin prévisionnelle de la position doit être antérieure ou égale à la date de décès de l'enfant. | CO26: POS_C_111 | CP26: =VLOOKUP(CO26,'Axe 2 Règles de gestion'!$D$2:$F$506,3, FALSE) -> La date de fin ou la date de fin prévisionnelle doit être saisie.
A27: 25.10.00 | B27: M | C27: 45989.706 | D27: D0004 | E27: Position | F27: S0031 | G27: Congé parental | H27: E0333 | I27: Congé parental après congé de maternité | J27: Position saisie égale à 'Congé parental après congé de maternité' | K27: A_POS_POSIAD [Saisi] = 'CGP01' | L27: T0967 | M27: Congé parental après congé de maternité - Réintégration | N27: Modification | O27: Indicateur de renouvellement saisi identique à Indicateur de renouvellement avant saisi ET Lien vers enfant saisi identique au Lien vers enfant avant saisi | P27: A_POS_INDREN [Saisi] = A_POS_INDREN [Valeur avant saisie] ET A_POS_LVEPAC [Saisi] = A_POS_LVEPAC [Valeur avant saisie]) | Q27: Stagiaire ou auditeur ou élève | R27: P0004 | S27: S | T27: Général | U27: Exclu | V27: 41363 | W27: 46110
A28: 17.10.00 | B28: A | C28: 43152.5 | D28: D0004 | E28: Position | F28: S0031 | G28: Congé parental | H28: E0333 | I28: Congé parental après congé de maternité | J28: Position saisie égale à 'Congé parental après congé de maternité' | K28: A_POS_POSIAD [Saisi] = 'CGP01' | L28: T1578 | M28: Congé parental après Congé de maternité - Demande pendant un Congé parental | N28: Création Modification | O28: Indicateur de renouvellement saisi = Non ET (Indicateur de renouvellement saisi différent d'Indicateur de renouvellement avant saisi OU Lien vers enfant saisi différent du Lien vers enfant avant saisi) ET Position saisie de l'occurrence précédente est une position de 'Congé parental' | P28: A_POS_INDREN [Saisi] = '0' ET (A_POS_INDREN [Saisi] <> A_POS_INDREN [Valeur avant saisie] OU A_POS_LVEPAC [Saisi] <> A_POS_LVEPAC [Valeur avant saisie]) ET (A_POS_POSIAD [Occurrence précédente] = POSITION_SITUATION.R_FOR_IDEN05 ET POSITION_SITUATION.R_REL_PSSAG2 = 'CGP') | Q28: Stagiaire ou auditeur ou élève | R28: P0004 | S28: S | T28: Général | U28: Passant | V28: 40725 | W28: 41182 | X28: CPR_D_014 ET CPR_D_705 ET CPR_D_660 ET CPR_D_009 ET CPR_D_034 ET CPR_D_070 ET CPR_D_740 ET POS_C_004 ET POS_C_005 ET POS_C_007 ET POS_C_010 ET POS_C_012 ET POS_C_022 ET POS_C_050 ET POS_C_051 ET POS_C_055 ET POS_C_056 ET POS_C_111 | AY28: CPR_D_014 | AZ28: =VLOOKUP(AY28,'Axe 2 Règles de gestion'!$D$2:$F$506,3, FALSE) -> Le congé parental est accordé par périodes de 6 mois maximum renouvelables (date de fin prévisionnelle du congé parental). | BA28: CPR_D_705 | BB28: =VLOOKUP(BA28,'Axe 2 Règles de gestion'!$D$2:$F$506,3, FALSE) -> Le congé parental est accordé par périodes de 6 mois maximum renouvelables (date de fin réelle du congé parental). | BC28: CPR_D_660 | BD28: =VLOOKUP(BC28,'Axe 2 Règles de gestion'!$D$2:$F$506,3, FALSE) -> Si une nouvelle naissance ou adoption intervient alors que l'agent est déjà en position de congé parental, celui-ci a droit, du chef de son nouvel enfant, à un nouveau congé parental. | BE28: CPR_D_009 | BF28: =VLOOKUP(BE28,'Axe 2 Règles de gestion'!$D$2:$F$506,3, FALSE) -> L'agent doit avoir la qualité de mère ou de père. | BG28: CPR_D_034 | BH28: =VLOOKUP(BG28,'Axe 2 Règles de gestion'!$D$2:$F$506,3, FALSE) -> Le congé parental est accordé de droit à la mère après un congé maternité. | BI28: CPR_D_070 | BJ28: =VLOOKUP(BI28,'Axe 2 Règles de gestion'!$D$2:$F$506,3, FALSE) -> L'enfant né au foyer doit être âgé de 3 ans au plus (date de fin prévisionnelle du congé parental). | BK28: CPR_D_740 | BL28: =VLOOKUP(BK28,'Axe 2 Règles de gestion'!$D$2:$F$506,3, FALSE) -> L'enfant né au foyer doit être âgé de 3 ans au plus (date de fin réelle du congé parental). | BY28: POS_C_004 | BZ28: =VLOOKUP(BY28,'Axe 2 Règles de gestion'!$D$2:$F$506,3, FALSE) -> La date de début de position doit être antérieure ou égale à la date de fin prévisionnelle de position. | CA28: POS_C_005 | CB28: =VLOOKUP(CA28,'Axe 2 Règles de gestion'!$D$2:$F$506,3, FALSE) -> La date de début de la position doit être postérieure ou égale à la date d'entrée dans la FPE ou dans la carrière militaire. | CC28: POS_C_007 | CD28: =VLOOKUP(CC28,'Axe 2 Règles de gestion'!$D$2:$F$506,3, FALSE) -> La date de fin réelle de la position doit être antérieure à la date limite de départ à la retraite. | CE28: POS_C_010 | CF28: =VLOOKUP(CE28,'Axe 2 Règles de gestion'!$D$2:$F$506,3, FALSE) -> La date de début de position doit être antérieure ou égale à la date de fin réelle de position. | CG28: POS_C_012 | CH28: =VLOOKUP(CG28,'Axe 2 Règles de gestion'!$D$2:$F$506,3, FALSE) -> La date de fin prévisionnelle de la position doit être antérieure à la date limite de départ à la retraite. | CI28: POS_C_022 | CJ28: =VLOOKUP(CI28,'Axe 2 Règles de gestion'!$D$2:$F$506,3, FALSE) -> La date de début de position est à J+1 de la date de fin de position de l'occurrence précédente. | CK28: POS_C_050 | CL28: =VLOOKUP(CK28,'Axe 2 Règles de gestion'!$D$2:$F$506,3, FALSE) -> Le lien vers l'enfant doit être renseigné. | CM28: POS_C_051 | CN28: =VLOOKUP(CM28,'Axe 2 Règles de gestion'!$D$2:$F$506,3, FALSE) -> La date de naissance de l'enfant doit être renseignée. | CO28: POS_C_055 | CP28: =VLOOKUP(CO28,'Axe 2 Règles de gestion'!$D$2:$F$506,3, FALSE) -> La date de fin réelle de la position doit être antérieure ou égale à la date de décès de l'enfant. | CQ28: POS_C_056 | CR28: =VLOOKUP(CQ28,'Axe 2 Règles de gestion'!$D$2:$F$506,3, FALSE) -> La date de fin prévisionnelle de la position doit être antérieure ou égale à la date de décès de l'enfant. | CS28: POS_C_111 | CT28: =VLOOKUP(CS28,'Axe 2 Règles de gestion'!$D$2:$F$506,3, FALSE) -> La date de fin ou la date de fin prévisionnelle doit être saisie.
A29: 25.10.00 | B29: M | C29: 45992.61 | D29: D0004 | E29: Position | F29: S0031 | G29: Congé parental | H29: E0333 | I29: Congé parental après congé de maternité | J29: Position saisie égale à 'Congé parental après congé de maternité' | K29: A_POS_POSIAD [Saisi] = 'CGP01' | L29: T1578 | M29: Congé parental après Congé de maternité - Demande pendant un Congé parental | N29: Création Modification | O29: Indicateur de renouvellement saisi = Non ET (Indicateur de renouvellement saisi différent d'Indicateur de renouvellement avant saisi OU Lien vers enfant saisi différent du Lien vers enfant avant saisi) ET Position saisie de l'occurrence précédente est une position de 'Congé parental' | P29: A_POS_INDREN [Saisi] = '0' ET (A_POS_INDREN [Saisi] <> A_POS_INDREN [Valeur avant saisie] OU A_POS_LVEPAC [Saisi] <> A_POS_LVEPAC [Valeur avant saisie]) ET (A_POS_POSIAD [Occurrence précédente] = POSITION_SITUATION.R_FOR_IDEN05 ET POSITION_SITUATION.R_REL_PSSAG2 = 'CGP') | Q29: Stagiaire ou auditeur ou élève | R29: P0004 | S29: S | T29: Général | U29: Exclu | V29: 41183 | W29: 46110
A30: 25.10.00 | B30: M | C30: 45989.671 | D30: D0004 | E30: Position | F30: S0031 | G30: Congé parental | H30: E0333 | I30: Congé parental après congé de maternité | J30: Position saisie égale à 'Congé parental après congé de maternité' | K30: A_POS_POSIAD [Saisi] = 'CGP01' | L30: T0964 | M30: Congé parental après congé de maternité - Demande | N30: Création Modification | O30: Indicateur de renouvellement saisi = Non ET (Indicateur de renouvellement saisi différent d'Indicateur de renouvellement avant saisi OU Lien vers enfant saisi différent du Lien vers enfant avant saisi) ET Position saisie de l'occurrence précédente est différente d'une position de 'Congé parental' | P30: A_POS_INDREN [Saisi] = '0' ET (A_POS_INDREN [Saisi] <> A_POS_INDREN [Valeur avant saisie] OU A_POS_LVEPAC [Saisi] <> A_POS_LVEPAC [Valeur avant saisie]) ET (A_POS_POSIAD [Occurrence précédente] = POSITION_SITUATION.R_FOR_IDEN05 ET POSITION_SITUATION.R_REL_PSSAG2 <> 'CGP') | Q30: Ouvrier d'état | R30: P0005 | S30: O | T30: Général | U30: Passant | V30: 40725 | W30: 46110 | X30: CPR_I_050 ET CPR_I_053 ET CPR_D_186 ET CPR_D_187 ET CPR_D_189 ET CPR_D_184 ET CPR_D_183 ET CPR_D_182 ET POS_C_100 ET POS_C_004 ET POS_C_006 ET POS_C_007 ET POS_C_009 ET POS_C_010 ET POS_C_012 ET POS_C_022 ET POS_C_050 ET POS_C_051 ET POS_C_055 ET POS_C_056 ET POS_C_106 ET POS_C_111 ET POS_C_120 ET POS_C_121 | Y30: CPR_I_050 | Z30: =VLOOKUP(Y30,'Axe 2 Règles de gestion'!$D$2:$F$506,3, FALSE) -> La demande de l'agent doit être formulée au moins 1 mois avant le début du congé parental. | AA30: CPR_I_053 | AB30: =VLOOKUP(AA30,'Axe 2 Règles de gestion'!$D$2:$F$506,3, FALSE) -> L'enfant né au foyer doit être âgé de 3 ans au plus sauf en cas de naissances multiples le congé parental suite à une naissance peut être accordé jusqu'à l'entrée en maternelle. | AY30: CPR_D_186 | AZ30: =VLOOKUP(AY30,'Axe 2 Règles de gestion'!$D$2:$F$506,3, FALSE) -> Le congé parental est accordé par périodes de 6 mois maximum renouvelables (date de fin prévisionnelle du congé parental). | BA30: CPR_D_187 | BB30: =VLOOKUP(BA30,'Axe 2 Règles de gestion'!$D$2:$F$506,3, FALSE) -> Le congé parental est accordé par périodes de 6 mois maximum renouvelables (date de fin réelle du congé parental). | BC30: CPR_D_189 | BD30: =VLOOKUP(BC30,'Axe 2 Règles de gestion'!$D$2:$F$506,3, FALSE) -> Le congé parental est accordé de droit à la mère après un congé maternité. | BE30: CPR_D_184 | BF30: =VLOOKUP(BE30,'Axe 2 Règles de gestion'!$D$2:$F$506,3, FALSE) -> L'enfant né au foyer doit être âgé de 3 ans au plus (date de fin prévisionnelle du congé parental). | BG30: CPR_D_183 | BH30: =VLOOKUP(BG30,'Axe 2 Règles de gestion'!$D$2:$F$506,3, FALSE) -> L'enfant né au foyer doit être âgé de 3 ans au plus (date de fin réelle du congé parental). | BI30: CPR_D_182 | BJ30: =VLOOKUP(BI30,'Axe 2 Règles de gestion'!$D$2:$F$506,3, FALSE) -> L'agent doit avoir la qualité de mère ou de père. | BY30: POS_C_100 | BZ30: =VLOOKUP(BY30,'Axe 2 Règles de gestion'!$D$2:$F$506,3, FALSE) -> Lors de la demande initiale, l'agent doit être en activité. | CA30: POS_C_004 | CB30: =VLOOKUP(CA30,'Axe 2 Règles de gestion'!$D$2:$F$506,3, FALSE) -> La date de début de position doit être antérieure ou égale à la date de fin prévisionnelle de position. | CC30: POS_C_006 | CD30: =VLOOKUP(CC30,'Axe 2 Règles de gestion'!$D$2:$F$506,3, FALSE) -> La date de fin réelle de la position doit être antérieure ou égale à la date de fin réelle ou prévisionnelle du lien juridique. | CE30: POS_C_007 | CF30: =VLOOKUP(CE30,'Axe 2 Règles de gestion'!$D$2:$F$506,3, FALSE) -> La date de fin réelle de la position doit être antérieure à la date limite de départ à la retraite. | CG30: POS_C_009 | CH30: =VLOOKUP(CG30,'Axe 2 Règles de gestion'!$D$2:$F$506,3, FALSE) -> La date de début de la position doit être postérieure ou égale à la date de début du lien juridique. | CI30: POS_C_010 | CJ30: =VLOOKUP(CI30,'Axe 2 Règles de gestion'!$D$2:$F$506,3, FALSE) -> La date de début de position doit être antérieure ou égale à la date de fin réelle de position. | CK30: POS_C_012 | CL30: =VLOOKUP(CK30,'Axe 2 Règles de gestion'!$D$2:$F$506,3, FALSE) -> La date de fin prévisionnelle de la position doit être antérieure à la date limite de départ à la retraite. | CM30: POS_C_022 | CN30: =VLOOKUP(CM30,'Axe 2 Règles de gestion'!$D$2:$F$506,3, FALSE) -> La date de début de position est à J+1 de la date de fin de position de l'occurrence précédente. | CO30: POS_C_050 | CP30: =VLOOKUP(CO30,'Axe 2 Règles de gestion'!$D$2:$F$506,3, FALSE) -> Le lien vers l'enfant doit être renseigné. | CQ30: POS_C_051 | CR30: =VLOOKUP(CQ30,'Axe 2 Règles de gestion'!$D$2:$F$506,3, FALSE) -> La date de naissance de l'enfant doit être renseignée. | CS30: POS_C_055 | CT30: =VLOOKUP(CS30,'Axe 2 Règles de gestion'!$D$2:$F$506,3, FALSE) -> La date de fin réelle de la position doit être antérieure ou égale à la date de décès de l'enfant. | CU30: POS_C_056 | CV30: =VLOOKUP(CU30,'Axe 2 Règles de gestion'!$D$2:$F$506,3, FALSE) -> La date de fin prévisionnelle de la position doit être antérieure ou égale à la date de décès de l'enfant. | CW30: POS_C_106 | CX30: =VLOOKUP(CW30,'Axe 2 Règles de gestion'!$D$2:$F$506,3, FALSE) -> La date de fin prévisionnelle de la position doit être antérieure ou égale à la date de fin réelle ou prévisionnelle du lien juridique. | CY30: POS_C_111 | CZ30: =VLOOKUP(CY30,'Axe 2 Règles de gestion'!$D$2:$F$506,3, FALSE) -> La date de fin ou la date de fin prévisionnelle doit être saisie. | DA30: POS_C_120 | DB30: =VLOOKUP(DA30,'Axe 2 Règles de gestion'!$D$2:$F$506,3, FALSE) -> La saisie d'une occurrence de congés/absences est interdite (date de fin réelle) | DC30: POS_C_121 | DD30: =VLOOKUP(DC30,'Axe 2 Règles de gestion'!$D$2:$F$506,3, FALSE) -> La saisie d'une occurrence de congés/absences est interdite (date de fin prévisionnelle)
A31: 25.10.00 | B31: M | C31: 45989.676 | D31: D0004 | E31: Position | F31: S0031 | G31: Congé parental | H31: E0333 | I31: Congé parental après congé de maternité | J31: Position saisie égale à 'Congé parental après congé de maternité' | K31: A_POS_POSIAD [Saisi] = 'CGP01' | L31: T0965 | M31: Congé parental après congé de maternité - Renouvellement | N31: Création Modification | O31: Indicateur de renouvellement saisi = Oui ET (Indicateur de renouvellement saisi différent d'Indicateur de renouvellement avant saisi OU Lien vers enfant saisi différent du Lien vers enfant avant saisi) | P31: A_POS_INDREN [Saisi] = '1' ET (A_POS_INDREN [Saisi] <> A_POS_INDREN [Valeur avant saisie] OU A_POS_LVEPAC [Saisi] <> A_POS_LVEPAC [Valeur avant saisie]) | Q31: Ouvrier d'état | R31: P0005 | S31: O | T31: Général | U31: Passant | V31: 40725 | W31: 46110 | X31: CPR_I_051 ET CPR_I_053 ET CPR_D_186 ET CPR_D_187 ET CPR_D_184 ET CPR_D_183 ET CPR_D_182 ET POS_C_004 ET POS_C_006 ET POS_C_007 ET POS_C_009 ET POS_C_010 ET POS_C_012 ET POS_C_022 ET POS_C_050 ET POS_C_051 ET POS_C_055 ET POS_C_056 ET POS_C_106 ET POS_C_111 ET POS_C_120 ET POS_C_121 | Y31: CPR_I_051 | Z31: =VLOOKUP(Y31,'Axe 2 Règles de gestion'!$D$2:$F$506,3, FALSE) -> La demande de renouvellement du congé doit être formulée au moins 2 mois avant l'expiration de la période en cours. | AA31: CPR_I_053 | AB31: =VLOOKUP(AA31,'Axe 2 Règles de gestion'!$D$2:$F$506,3, FALSE) -> L'enfant né au foyer doit être âgé de 3 ans au plus sauf en cas de naissances multiples le congé parental suite à une naissance peut être accordé jusqu'à l'entrée en maternelle. | AY31: CPR_D_186 | AZ31: =VLOOKUP(AY31,'Axe 2 Règles de gestion'!$D$2:$F$506,3, FALSE) -> Le congé parental est accordé par périodes de 6 mois maximum renouvelables (date de fin prévisionnelle du congé parental). | BA31: CPR_D_187 | BB31: =VLOOKUP(BA31,'Axe 2 Règles de gestion'!$D$2:$F$506,3, FALSE) -> Le congé parental est accordé par périodes de 6 mois maximum renouvelables (date de fin réelle du congé parental). | BC31: CPR_D_184 | BD31: =VLOOKUP(BC31,'Axe 2 Règles de gestion'!$D$2:$F$506,3, FALSE) -> L'enfant né au foyer doit être âgé de 3 ans au plus (date de fin prévisionnelle du congé parental). | BE31: CPR_D_183 | BF31: =VLOOKUP(BE31,'Axe 2 Règles de gestion'!$D$2:$F$506,3, FALSE) -> L'enfant né au foyer doit être âgé de 3 ans au plus (date de fin réelle du congé parental). | BG31: CPR_D_182 | BH31: =VLOOKUP(BG31,'Axe 2 Règles de gestion'!$D$2:$F$506,3, FALSE) -> L'agent doit avoir la qualité de mère ou de père. | BY31: POS_C_004 | BZ31: =VLOOKUP(BY31,'Axe 2 Règles de gestion'!$D$2:$F$506,3, FALSE) -> La date de début de position doit être antérieure ou égale à la date de fin prévisionnelle de position. | CA31: POS_C_006 | CB31: =VLOOKUP(CA31,'Axe 2 Règles de gestion'!$D$2:$F$506,3, FALSE) -> La date de fin réelle de la position doit être antérieure ou égale à la date de fin réelle ou prévisionnelle du lien juridique. | CC31: POS_C_007 | CD31: =VLOOKUP(CC31,'Axe 2 Règles de gestion'!$D$2:$F$506,3, FALSE) -> La date de fin réelle de la position doit être antérieure à la date limite de départ à la retraite. | CE31: POS_C_009 | CF31: =VLOOKUP(CE31,'Axe 2 Règles de gestion'!$D$2:$F$506,3, FALSE) -> La date de début de la position doit être postérieure ou égale à la date de début du lien juridique. | CG31: POS_C_010 | CH31: =VLOOKUP(CG31,'Axe 2 Règles de gestion'!$D$2:$F$506,3, FALSE) -> La date de début de position doit être antérieure ou égale à la date de fin réelle de position. | CI31: POS_C_012 | CJ31: =VLOOKUP(CI31,'Axe 2 Règles de gestion'!$D$2:$F$506,3, FALSE) -> La date de fin prévisionnelle de la position doit être antérieure à la date limite de départ à la retraite. | CK31: POS_C_022 | CL31: =VLOOKUP(CK31,'Axe 2 Règles de gestion'!$D$2:$F$506,3, FALSE) -> La date de début de position est à J+1 de la date de fin de position de l'occurrence précédente. | CM31: POS_C_050 | CN31: =VLOOKUP(CM31,'Axe 2 Règles de gestion'!$D$2:$F$506,3, FALSE) -> Le lien vers l'enfant doit être renseigné. | CO31: POS_C_051 | CP31: =VLOOKUP(CO31,'Axe 2 Règles de gestion'!$D$2:$F$506,3, FALSE) -> La date de naissance de l'enfant doit être renseignée. | CQ31: POS_C_055 | CR31: =VLOOKUP(CQ31,'Axe 2 Règles de gestion'!$D$2:$F$506,3, FALSE) -> La date de fin réelle de la position doit être antérieure ou égale à la date de décès de l'enfant. | CS31: POS_C_056 | CT31: =VLOOKUP(CS31,'Axe 2 Règles de gestion'!$D$2:$F$506,3, FALSE) -> La date de fin prévisionnelle de la position doit être antérieure ou égale à la date de décès de l'enfant. | CU31: POS_C_106 | CV31: =VLOOKUP(CU31,'Axe 2 Règles de gestion'!$D$2:$F$506,3, FALSE) -> La date de fin prévisionnelle de la position doit être antérieure ou égale à la date de fin réelle ou prévisionnelle du lien juridique. | CW31: POS_C_111 | CX31: =VLOOKUP(CW31,'Axe 2 Règles de gestion'!$D$2:$F$506,3, FALSE) -> La date de fin ou la date de fin prévisionnelle doit être saisie. | CY31: POS_C_120 | CZ31: =VLOOKUP(CY31,'Axe 2 Règles de gestion'!$D$2:$F$506,3, FALSE) -> La saisie d'une occurrence de congés/absences est interdite (date de fin réelle) | DA31: POS_C_121 | DB31: =VLOOKUP(DA31,'Axe 2 Règles de gestion'!$D$2:$F$506,3, FALSE) -> La saisie d'une occurrence de congés/absences est interdite (date de fin prévisionnelle)
A32: 25.10.00 | B32: M | C32: 45989.706 | D32: D0004 | E32: Position | F32: S0031 | G32: Congé parental | H32: E0333 | I32: Congé parental après congé de maternité | J32: Position saisie égale à 'Congé parental après congé de maternité' | K32: A_POS_POSIAD [Saisi] = 'CGP01' | L32: T0967 | M32: Congé parental après congé de maternité - Réintégration | N32: Modification | O32: Indicateur de renouvellement saisi identique à Indicateur de renouvellement avant saisi ET Lien vers enfant saisi identique au Lien vers enfant avant saisi | P32: A_POS_INDREN [Saisi] = A_POS_INDREN [Valeur avant saisie] ET A_POS_LVEPAC [Saisi] = A_POS_LVEPAC [Valeur avant saisie]) | Q32: Ouvrier d'état | R32: P0005 | S32: O | T32: Général | U32: Passant | V32: 40725 | W32: 46110 | X32: CPR_I_053 ET CPR_I_054 ET CPR_I_061 ET CPR_I_055 ET CPR_I_107 ET CPR_I_056 ET CPR_D_186 ET CPR_D_187 ET CPR_D_184 ET CPR_D_183 ET POS_C_004 ET POS_C_006 ET POS_C_007 ET POS_C_010 ET POS_C_012 ET POS_C_050 ET POS_C_051 ET POS_C_055 ET POS_C_056 ET POS_C_106 ET POS_C_111 ET POS_C_120 ET POS_C_121 | Y32: CPR_I_053 | Z32: =VLOOKUP(Y32,'Axe 2 Règles de gestion'!$D$2:$F$506,3, FALSE) -> L'enfant né au foyer doit être âgé de 3 ans au plus sauf en cas de naissances multiples le congé parental suite à une naissance peut être accordé jusqu'à l'entrée en maternelle. | AA32: CPR_I_054 | AB32: =VLOOKUP(AA32,'Axe 2 Règles de gestion'!$D$2:$F$506,3, FALSE) -> En cas de défaut de demande de renouvellement dans les 2 mois au moins avant l'expiration de la période de congé, le bénéfice du congé parental cesse de plein droit, l'agent est réintégré. | AC32: CPR_I_061 | AD32: =VLOOKUP(AC32,'Axe 2 Règles de gestion'!$D$2:$F$506,3, FALSE) -> Si le contrôle pour s'assurer que l'activité du bénéficiaire du congé est réellement consacrée à élever l'enfant révèle que le congé n'est pas utilisé dans ce but, il peut y être mis fin après que l'intéressé ait été invité à présenter ses observations. | AE32: CPR_I_055 | AF32: =VLOOKUP(AE32,'Axe 2 Règles de gestion'!$D$2:$F$506,3, FALSE) -> L'agent peut demander que la durée du congé soit écourtée en cas de nouvelle naissance ou pour motif grave, notamment en cas de diminution des revenus du ménage. | AG32: CPR_I_107 | AH32: =VLOOKUP(AG32,'Axe 2 Règles de gestion'!$D$2:$F$506,3, FALSE) -> Le congé parental cesse de plein droit en cas de retrait de l'enfant placé en vue de son adoption. | AI32: CPR_I_056 | AJ32: =VLOOKUP(AI32,'Axe 2 Règles de gestion'!$D$2:$F$506,3, FALSE) -> L'agent peut demander à être réintégré dans un établissement le plus proche de son domicile. | AY32: CPR_D_186 | AZ32: =VLOOKUP(AY32,'Axe 2 Règles de gestion'!$D$2:$F$506,3, FALSE) -> Le congé parental est accordé par périodes de 6 mois maximum renouvelables (date de fin prévisionnelle du congé parental). | BA32: CPR_D_187 | BB32: =VLOOKUP(BA32,'Axe 2 Règles de gestion'!$D$2:$F$506,3, FALSE) -> Le congé parental est accordé par périodes de 6 mois maximum renouvelables (date de fin réelle du congé parental). | BC32: CPR_D_184 | BD32: =VLOOKUP(BC32,'Axe 2 Règles de gestion'!$D$2:$F$506,3, FALSE) -> L'enfant né au foyer doit être âgé de 3 ans au plus (date de fin prévisionnelle du congé parental). | BE32: CPR_D_183 | BF32: =VLOOKUP(BE32,'Axe 2 Règles de gestion'!$D$2:$F$506,3, FALSE) -> L'enfant né au foyer doit être âgé de 3 ans au plus (date de fin réelle du congé parental). | BY32: POS_C_004 | BZ32: =VLOOKUP(BY32,'Axe 2 Règles de gestion'!$D$2:$F$506,3, FALSE) -> La date de début de position doit être antérieure ou égale à la date de fin prévisionnelle de position. | CA32: POS_C_006 | CB32: =VLOOKUP(CA32,'Axe 2 Règles de gestion'!$D$2:$F$506,3, FALSE) -> La date de fin réelle de la position doit être antérieure ou égale à la date de fin réelle ou prévisionnelle du lien juridique. | CC32: POS_C_007 | CD32: =VLOOKUP(CC32,'Axe 2 Règles de gestion'!$D$2:$F$506,3, FALSE) -> La date de fin réelle de la position doit être antérieure à la date limite de départ à la retraite. | CE32: POS_C_010 | CF32: =VLOOKUP(CE32,'Axe 2 Règles de gestion'!$D$2:$F$506,3, FALSE) -> La date de début de position doit être antérieure ou égale à la date de fin réelle de position. | CG32: POS_C_012 | CH32: =VLOOKUP(CG32,'Axe 2 Règles de gestion'!$D$2:$F$506,3, FALSE) -> La date de fin prévisionnelle de la position doit être antérieure à la date limite de départ à la retraite. | CI32: POS_C_050 | CJ32: =VLOOKUP(CI32,'Axe 2 Règles de gestion'!$D$2:$F$506,3, FALSE) -> Le lien vers l'enfant doit être renseigné. | CK32: POS_C_051 | CL32: =VLOOKUP(CK32,'Axe 2 Règles de gestion'!$D$2:$F$506,3, FALSE) -> La date de naissance de l'enfant doit être renseignée. | CM32: POS_C_055 | CN32: =VLOOKUP(CM32,'Axe 2 Règles de gestion'!$D$2:$F$506,3, FALSE) -> La date de fin réelle de la position doit être antérieure ou égale à la date de décès de l'enfant. | CO32: POS_C_056 | CP32: =VLOOKUP(CO32,'Axe 2 Règles de gestion'!$D$2:$F$506,3, FALSE) -> La date de fin prévisionnelle de la position doit être antérieure ou égale à la date de décès de l'enfant. | CQ32: POS_C_106 | CR32: =VLOOKUP(CQ32,'Axe 2 Règles de gestion'!$D$2:$F$506,3, FALSE) -> La date de fin prévisionnelle de la position doit être antérieure ou égale à la date de fin réelle ou prévisionnelle du lien juridique. | CS32: POS_C_111 | CT32: =VLOOKUP(CS32,'Axe 2 Règles de gestion'!$D$2:$F$506,3, FALSE) -> La date de fin ou la date de fin prévisionnelle doit être saisie. | CU32: POS_C_120 | CV32: =VLOOKUP(CU32,'Axe 2 Règles de gestion'!$D$2:$F$506,3, FALSE) -> La saisie d'une occurrence de congés/absences est interdite (date de fin réelle) | CW32: POS_C_121 | CX32: =VLOOKUP(CW32,'Axe 2 Règles de gestion'!$D$2:$F$506,3, FALSE) -> La saisie d'une occurrence de congés/absences est interdite (date de fin prévisionnelle)
A33: 25.10.00 | B33: M | C33: 45992.61 | D33: D0004 | E33: Position | F33: S0031 | G33: Congé parental | H33: E0333 | I33: Congé parental après congé de maternité | J33: Position saisie égale à 'Congé parental après congé de maternité' | K33: A_POS_POSIAD [Saisi] = 'CGP01' | L33: T1578 | M33: Congé parental après Congé de maternité - Demande pendant un Congé parental | N33: Création Modification | O33: Indicateur de renouvellement saisi = Non ET (Indicateur de renouvellement saisi différent d'Indicateur de renouvellement avant saisi OU Lien vers enfant saisi différent du Lien vers enfant avant saisi) ET Position saisie de l'occurrence précédente est une position de 'Congé parental' | P33: A_POS_INDREN [Saisi] = '0' ET (A_POS_INDREN [Saisi] <> A_POS_INDREN [Valeur avant saisie] OU A_POS_LVEPAC [Saisi] <> A_POS_LVEPAC [Valeur avant saisie]) ET (A_POS_POSIAD [Occurrence précédente] = POSITION_SITUATION.R_FOR_IDEN05 ET POSITION_SITUATION.R_REL_PSSAG2 = 'CGP') | Q33: Ouvrier d'état | R33: P0005 | S33: O | T33: Général | U33: Passant | V33: 40725 | W33: 46110 | X33: CPR_I_052 ET CPR_I_053 ET CPR_D_186 ET CPR_D_187 ET CPR_D_188 ET CPR_D_210 ET CPR_D_209 ET CPR_D_182 ET POS_C_004 ET POS_C_006 ET POS_C_007 ET POS_C_009 ET POS_C_010 ET POS_C_012 ET POS_C_022 ET POS_C_050 ET POS_C_051 ET POS_C_055 ET POS_C_056 ET POS_C_106 ET POS_C_111 ET POS_C_120 ET POS_C_121 | Y33: CPR_I_052 | Z33: =VLOOKUP(Y33,'Axe 2 Règles de gestion'!$D$2:$F$506,3, FALSE) -> La demande de l'agent doit être formulée au moins 1 mois avant la date présumée de la naissance ou de l'arrivée de l'enfant. | AA33: CPR_I_053 | AB33: =VLOOKUP(AA33,'Axe 2 Règles de gestion'!$D$2:$F$506,3, FALSE) -> L'enfant né au foyer doit être âgé de 3 ans au plus sauf en cas de naissances multiples le congé parental suite à une naissance peut être accordé jusqu'à l'entrée en maternelle. | AY33: CPR_D_186 | AZ33: =VLOOKUP(AY33,'Axe 2 Règles de gestion'!$D$2:$F$506,3, FALSE) -> Le congé parental est accordé par périodes de 6 mois maximum renouvelables (date de fin prévisionnelle du congé parental). | BA33: CPR_D_187 | BB33: =VLOOKUP(BA33,'Axe 2 Règles de gestion'!$D$2:$F$506,3, FALSE) -> Le congé parental est accordé par périodes de 6 mois maximum renouvelables (date de fin réelle du congé parental). | BC33: CPR_D_188 | BD33: =VLOOKUP(BC33,'Axe 2 Règles de gestion'!$D$2:$F$506,3, FALSE) -> Si une nouvelle naissance ou adoption intervient alors que l'agent est déjà en position de congé parental, celui-ci a droit, du chef de son nouvel enfant, à un nouveau congé parental. | BE33: CPR_D_210 | BF33: =VLOOKUP(BE33,'Axe 2 Règles de gestion'!$D$2:$F$506,3, FALSE) -> L'enfant né au foyer doit être âgé de 3 ans au plus (date de fin prévisionnelle du congé parental). | BG33: CPR_D_209 | BH33: =VLOOKUP(BG33,'Axe 2 Règles de gestion'!$D$2:$F$506,3, FALSE) -> L'enfant né au foyer doit être âgé de 3 ans au plus (date de fin réelle du congé parental). | BI33: CPR_D_182 | BJ33: =VLOOKUP(BI33,'Axe 2 Règles de gestion'!$D$2:$F$506,3, FALSE) -> L'agent doit avoir la qualité de mère ou de père. | BY33: POS_C_004 | BZ33: =VLOOKUP(BY33,'Axe 2 Règles de gestion'!$D$2:$F$506,3, FALSE) -> La date de début de position doit être antérieure ou égale à la date de fin prévisionnelle de position. | CA33: POS_C_006 | CB33: =VLOOKUP(CA33,'Axe 2 Règles de gestion'!$D$2:$F$506,3, FALSE) -> La date de fin réelle de la position doit être antérieure ou égale à la date de fin réelle ou prévisionnelle du lien juridique. | CC33: POS_C_007 | CD33: =VLOOKUP(CC33,'Axe 2 Règles de gestion'!$D$2:$F$506,3, FALSE) -> La date de fin réelle de la position doit être antérieure à la date limite de départ à la retraite. | CE33: POS_C_009 | CF33: =VLOOKUP(CE33,'Axe 2 Règles de gestion'!$D$2:$F$506,3, FALSE) -> La date de début de la position doit être postérieure ou égale à la date de début du lien juridique. | CG33: POS_C_010 | CH33: =VLOOKUP(CG33,'Axe 2 Règles de gestion'!$D$2:$F$506,3, FALSE) -> La date de début de position doit être antérieure ou égale à la date de fin réelle de position. | CI33: POS_C_012 | CJ33: =VLOOKUP(CI33,'Axe 2 Règles de gestion'!$D$2:$F$506,3, FALSE) -> La date de fin prévisionnelle de la position doit être antérieure à la date limite de départ à la retraite. | CK33: POS_C_022 | CL33: =VLOOKUP(CK33,'Axe 2 Règles de gestion'!$D$2:$F$506,3, FALSE) -> La date de début de position est à J+1 de la date de fin de position de l'occurrence précédente. | CM33: POS_C_050 | CN33: =VLOOKUP(CM33,'Axe 2 Règles de gestion'!$D$2:$F$506,3, FALSE) -> Le lien vers l'enfant doit être renseigné. | CO33: POS_C_051 | CP33: =VLOOKUP(CO33,'Axe 2 Règles de gestion'!$D$2:$F$506,3, FALSE) -> La date de naissance de l'enfant doit être renseignée. | CQ33: POS_C_055 | CR33: =VLOOKUP(CQ33,'Axe 2 Règles de gestion'!$D$2:$F$506,3, FALSE) -> La date de fin réelle de la position doit être antérieure ou égale à la date de décès de l'enfant. | CS33: POS_C_056 | CT33: =VLOOKUP(CS33,'Axe 2 Règles de gestion'!$D$2:$F$506,3, FALSE) -> La date de fin prévisionnelle de la position doit être antérieure ou égale à la date de décès de l'enfant. | CU33: POS_C_106 | CV33: =VLOOKUP(CU33,'Axe 2 Règles de gestion'!$D$2:$F$506,3, FALSE) -> La date de fin prévisionnelle de la position doit être antérieure ou égale à la date de fin réelle ou prévisionnelle du lien juridique. | CW33: POS_C_111 | CX33: =VLOOKUP(CW33,'Axe 2 Règles de gestion'!$D$2:$F$506,3, FALSE) -> La date de fin ou la date de fin prévisionnelle doit être saisie. | CY33: POS_C_120 | CZ33: =VLOOKUP(CY33,'Axe 2 Règles de gestion'!$D$2:$F$506,3, FALSE) -> La saisie d'une occurrence de congés/absences est interdite (date de fin réelle) | DA33: POS_C_121 | DB33: =VLOOKUP(DA33,'Axe 2 Règles de gestion'!$D$2:$F$506,3, FALSE) -> La saisie d'une occurrence de congés/absences est interdite (date de fin prévisionnelle)
A34: 17.10.00 | B34: A | C34: 43152.5 | D34: D0004 | E34: Position | F34: S0031 | G34: Congé parental | H34: E0333 | I34: Congé parental après congé de maternité | J34: Position saisie égale à 'Congé parental après congé de maternité' | K34: A_POS_POSIAD [Saisi] = 'CGP01' | L34: T0964 | M34: Congé parental après congé de maternité - Demande | N34: Création Modification | O34: Indicateur de renouvellement saisi = Non ET (Indicateur de renouvellement saisi différent d'Indicateur de renouvellement avant saisi OU Lien vers enfant saisi différent du Lien vers enfant avant saisi) ET Position saisie de l'occurrence précédente est différente d'une position de 'Congé parental' | P34: A_POS_INDREN [Saisi] = '0' ET (A_POS_INDREN [Saisi] <> A_POS_INDREN [Valeur avant saisie] OU A_POS_LVEPAC [Saisi] <> A_POS_LVEPAC [Valeur avant saisie]) ET (A_POS_POSIAD [Occurrence précédente] = POSITION_SITUATION.R_FOR_IDEN05 ET POSITION_SITUATION.R_REL_PSSAG2 <> 'CGP') | Q34: Magistrat de l'ordre judiciaire | R34: P0007 | S34: T | T34: Particulier | U34: Passant | V34: 40725 | W34: 41182 | X34: CPR_D_492 ET CPR_D_720 ET CPR_D_487 ET CPR_D_488 ET CPR_D_500 ET CPR_D_718 ET POS_C_100 ET POS_C_004 ET POS_C_005 ET POS_C_007 ET POS_C_010 ET POS_C_012 ET POS_C_022 ET POS_C_050 ET POS_C_051 ET POS_C_055 ET POS_C_056 ET POS_C_057 ET POS_C_111 | AY34: CPR_D_492 | AZ34: =VLOOKUP(AY34,'Axe 2 Règles de gestion'!$D$2:$F$506,3, FALSE) -> Le congé parental est accordé par périodes de 6 mois maximum renouvelables (date de fin prévisionnelle du congé parental). | BA34: CPR_D_720 | BB34: =VLOOKUP(BA34,'Axe 2 Règles de gestion'!$D$2:$F$506,3, FALSE) -> Le congé parental est accordé par périodes de 6 mois maximum renouvelables (date de fin réelle du congé parental). | BC34: CPR_D_487 | BD34: =VLOOKUP(BC34,'Axe 2 Règles de gestion'!$D$2:$F$506,3, FALSE) -> L'agent doit avoir la qualité de mère ou de père. | BE34: CPR_D_488 | BF34: =VLOOKUP(BE34,'Axe 2 Règles de gestion'!$D$2:$F$506,3, FALSE) -> L'enfant né au foyer doit être âgé de 3 ans au plus (date de fin prévisionnelle du congé parental). | BG34: CPR_D_500 | BH34: =VLOOKUP(BG34,'Axe 2 Règles de gestion'!$D$2:$F$506,3, FALSE) -> Le congé parental est accordé de droit à la mère après un congé maternité. | BI34: CPR_D_718 | BJ34: =VLOOKUP(BI34,'Axe 2 Règles de gestion'!$D$2:$F$506,3, FALSE) -> L'enfant né au foyer doit être âgé de 3 ans au plus (date de fin réelle du congé parental). | BY34: POS_C_100 | BZ34: =VLOOKUP(BY34,'Axe 2 Règles de gestion'!$D$2:$F$506,3, FALSE) -> Lors de la demande initiale, l'agent doit être en activité. | CA34: POS_C_004 | CB34: =VLOOKUP(CA34,'Axe 2 Règles de gestion'!$D$2:$F$506,3, FALSE) -> La date de début de position doit être antérieure ou égale à la date de fin prévisionnelle de position. | CC34: POS_C_005 | CD34: =VLOOKUP(CC34,'Axe 2 Règles de gestion'!$D$2:$F$506,3, FALSE) -> La date de début de la position doit être postérieure ou égale à la date d'entrée dans la FPE ou dans la carrière militaire. | CE34: POS_C_007 | CF34: =VLOOKUP(CE34,'Axe 2 Règles de gestion'!$D$2:$F$506,3, FALSE) -> La date de fin réelle de la position doit être antérieure à la date limite de départ à la retraite. | CG34: POS_C_010 | CH34: =VLOOKUP(CG34,'Axe 2 Règles de gestion'!$D$2:$F$506,3, FALSE) -> La date de début de position doit être antérieure ou égale à la date de fin réelle de position. | CI34: POS_C_012 | CJ34: =VLOOKUP(CI34,'Axe 2 Règles de gestion'!$D$2:$F$506,3, FALSE) -> La date de fin prévisionnelle de la position doit être antérieure à la date limite de départ à la retraite. | CK34: POS_C_022 | CL34: =VLOOKUP(CK34,'Axe 2 Règles de gestion'!$D$2:$F$506,3, FALSE) -> La date de début de position est à J+1 de la date de fin de position de l'occurrence précédente. | CM34: POS_C_050 | CN34: =VLOOKUP(CM34,'Axe 2 Règles de gestion'!$D$2:$F$506,3, FALSE) -> Le lien vers l'enfant doit être renseigné. | CO34: POS_C_051 | CP34: =VLOOKUP(CO34,'Axe 2 Règles de gestion'!$D$2:$F$506,3, FALSE) -> La date de naissance de l'enfant doit être renseignée. | CQ34: POS_C_055 | CR34: =VLOOKUP(CQ34,'Axe 2 Règles de gestion'!$D$2:$F$506,3, FALSE) -> La date de fin réelle de la position doit être antérieure ou égale à la date de décès de l'enfant. | CS34: POS_C_056 | CT34: =VLOOKUP(CS34,'Axe 2 Règles de gestion'!$D$2:$F$506,3, FALSE) -> La date de fin prévisionnelle de la position doit être antérieure ou égale à la date de décès de l'enfant. | CU34: POS_C_057 | CV34: =VLOOKUP(CU34,'Axe 2 Règles de gestion'!$D$2:$F$506,3, FALSE) -> L'agent ne doit pas être en position de détachement entrant sur l'occurrence précédente. | CW34: POS_C_111 | CX34: =VLOOKUP(CW34,'Axe 2 Règles de gestion'!$D$2:$F$506,3, FALSE) -> La date de fin ou la date de fin prévisionnelle doit être saisie.
A35: 17.10.00 | B35: A | C35: 43152.5 | D35: D0004 | E35: Position | F35: S0031 | G35: Congé parental | H35: E0333 | I35: Congé parental après congé de maternité | J35: Position saisie égale à 'Congé parental après congé de maternité' | K35: A_POS_POSIAD [Saisi] = 'CGP01' | L35: T0965 | M35: Congé parental après congé de maternité - Renouvellement | N35: Création Modification | O35: Indicateur de renouvellement saisi = Oui ET (Indicateur de renouvellement saisi différent d'Indicateur de renouvellement avant saisi OU Lien vers enfant saisi différent du Lien vers enfant avant saisi) | P35: A_POS_INDREN [Saisi] = '1' ET (A_POS_INDREN [Saisi] <> A_POS_INDREN [Valeur avant saisie] OU A_POS_LVEPAC [Saisi] <> A_POS_LVEPAC [Valeur avant saisie]) | Q35: Magistrat de l'ordre judiciaire | R35: P0007 | S35: T | T35: Particulier | U35: Passant | V35: 40725 | W35: 41362 | X35: CPR_D_492 ET CPR_D_720 ET CPR_D_487 ET CPR_D_488 ET CPR_D_718 ET POS_C_004 ET POS_C_005 ET POS_C_007 ET POS_C_010 ET POS_C_012 ET POS_C_022 ET POS_C_050 ET POS_C_051 ET POS_C_055 ET POS_C_056 ET POS_C_111 | AY35: CPR_D_492 | AZ35: =VLOOKUP(AY35,'Axe 2 Règles de gestion'!$D$2:$F$506,3, FALSE) -> Le congé parental est accordé par périodes de 6 mois maximum renouvelables (date de fin prévisionnelle du congé parental). | BA35: CPR_D_720 | BB35: =VLOOKUP(BA35,'Axe 2 Règles de gestion'!$D$2:$F$506,3, FALSE) -> Le congé parental est accordé par périodes de 6 mois maximum renouvelables (date de fin réelle du congé parental). | BC35: CPR_D_487 | BD35: =VLOOKUP(BC35,'Axe 2 Règles de gestion'!$D$2:$F$506,3, FALSE) -> L'agent doit avoir la qualité de mère ou de père. | BE35: CPR_D_488 | BF35: =VLOOKUP(BE35,'Axe 2 Règles de gestion'!$D$2:$F$506,3, FALSE) -> L'enfant né au foyer doit être âgé de 3 ans au plus (date de fin prévisionnelle du congé parental). | BG35: CPR_D_718 | BH35: =VLOOKUP(BG35,'Axe 2 Règles de gestion'!$D$2:$F$506,3, FALSE) -> L'enfant né au foyer doit être âgé de 3 ans au plus (date de fin réelle du congé parental). | BY35: POS_C_004 | BZ35: =VLOOKUP(BY35,'Axe 2 Règles de gestion'!$D$2:$F$506,3, FALSE) -> La date de début de position doit être antérieure ou égale à la date de fin prévisionnelle de position. | CA35: POS_C_005 | CB35: =VLOOKUP(CA35,'Axe 2 Règles de gestion'!$D$2:$F$506,3, FALSE) -> La date de début de la position doit être postérieure ou égale à la date d'entrée dans la FPE ou dans la carrière militaire. | CC35: POS_C_007 | CD35: =VLOOKUP(CC35,'Axe 2 Règles de gestion'!$D$2:$F$506,3, FALSE) -> La date de fin réelle de la position doit être antérieure à la date limite de départ à la retraite. | CE35: POS_C_010 | CF35: =VLOOKUP(CE35,'Axe 2 Règles de gestion'!$D$2:$F$506,3, FALSE) -> La date de début de position doit être antérieure ou égale à la date de fin réelle de position. | CG35: POS_C_012 | CH35: =VLOOKUP(CG35,'Axe 2 Règles de gestion'!$D$2:$F$506,3, FALSE) -> La date de fin prévisionnelle de la position doit être antérieure à la date limite de départ à la retraite. | CI35: POS_C_022 | CJ35: =VLOOKUP(CI35,'Axe 2 Règles de gestion'!$D$2:$F$506,3, FALSE) -> La date de début de position est à J+1 de la date de fin de position de l'occurrence précédente. | CK35: POS_C_050 | CL35: =VLOOKUP(CK35,'Axe 2 Règles de gestion'!$D$2:$F$506,3, FALSE) -> Le lien vers l'enfant doit être renseigné. | CM35: POS_C_051 | CN35: =VLOOKUP(CM35,'Axe 2 Règles de gestion'!$D$2:$F$506,3, FALSE) -> La date de naissance de l'enfant doit être renseignée. | CO35: POS_C_055 | CP35: =VLOOKUP(CO35,'Axe 2 Règles de gestion'!$D$2:$F$506,3, FALSE) -> La date de fin réelle de la position doit être antérieure ou égale à la date de décès de l'enfant. | CQ35: POS_C_056 | CR35: =VLOOKUP(CQ35,'Axe 2 Règles de gestion'!$D$2:$F$506,3, FALSE) -> La date de fin prévisionnelle de la position doit être antérieure ou égale à la date de décès de l'enfant. | CS35: POS_C_111 | CT35: =VLOOKUP(CS35,'Axe 2 Règles de gestion'!$D$2:$F$506,3, FALSE) -> La date de fin ou la date de fin prévisionnelle doit être saisie.
A36: 17.10.00 | B36: A | C36: 43152.5 | D36: D0004 | E36: Position | F36: S0031 | G36: Congé parental | H36: E0333 | I36: Congé parental après congé de maternité | J36: Position saisie égale à 'Congé parental après congé de maternité' | K36: A_POS_POSIAD [Saisi] = 'CGP01' | L36: T0967 | M36: Congé parental après congé de maternité - Réintégration | N36: Modification | O36: Indicateur de renouvellement saisi identique à Indicateur de renouvellement avant saisi ET Lien vers enfant saisi identique au Lien vers enfant avant saisi | P36: A_POS_INDREN [Saisi] = A_POS_INDREN [Valeur avant saisie] ET A_POS_LVEPAC [Saisi] = A_POS_LVEPAC [Valeur avant saisie]) | Q36: Magistrat de l'ordre judiciaire | R36: P0007 | S36: T | T36: Particulier | U36: Passant | V36: 40725 | W36: 41362 | X36: CPR_D_492 ET CPR_D_720 ET CPR_D_488 ET CPR_D_718 ET POS_C_004 ET POS_C_007 ET POS_C_010 ET POS_C_012 ET POS_C_050 ET POS_C_051 ET POS_C_055 ET POS_C_056 ET POS_C_111 | AY36: CPR_D_492 | AZ36: =VLOOKUP(AY36,'Axe 2 Règles de gestion'!$D$2:$F$506,3, FALSE) -> Le congé parental est accordé par périodes de 6 mois maximum renouvelables (date de fin prévisionnelle du congé parental). | BA36: CPR_D_720 | BB36: =VLOOKUP(BA36,'Axe 2 Règles de gestion'!$D$2:$F$506,3, FALSE) -> Le congé parental est accordé par périodes de 6 mois maximum renouvelables (date de fin réelle du congé parental). | BC36: CPR_D_488 | BD36: =VLOOKUP(BC36,'Axe 2 Règles de gestion'!$D$2:$F$506,3, FALSE) -> L'enfant né au foyer doit être âgé de 3 ans au plus (date de fin prévisionnelle du congé parental). | BE36: CPR_D_718 | BF36: =VLOOKUP(BE36,'Axe 2 Règles de gestion'!$D$2:$F$506,3, FALSE) -> L'enfant né au foyer doit être âgé de 3 ans au plus (date de fin réelle du congé parental). | BY36: POS_C_004 | BZ36: =VLOOKUP(BY36,'Axe 2 Règles de gestion'!$D$2:$F$506,3, FALSE) -> La date de début de position doit être antérieure ou égale à la date de fin prévisionnelle de position. | CA36: POS_C_007 | CB36: =VLOOKUP(CA36,'Axe 2 Règles de gestion'!$D$2:$F$506,3, FALSE) -> La date de fin réelle de la position doit être antérieure à la date limite de départ à la retraite. | CC36: POS_C_010 | CD36: =VLOOKUP(CC36,'Axe 2 Règles de gestion'!$D$2:$F$506,3, FALSE) -> La date de début de position doit être antérieure ou égale à la date de fin réelle de position. | CE36: POS_C_012 | CF36: =VLOOKUP(CE36,'Axe 2 Règles de gestion'!$D$2:$F$506,3, FALSE) -> La date de fin prévisionnelle de la position doit être antérieure à la date limite de départ à la retraite. | CG36: POS_C_050 | CH36: =VLOOKUP(CG36,'Axe 2 Règles de gestion'!$D$2:$F$506,3, FALSE) -> Le lien vers l'enfant doit être renseigné. | CI36: POS_C_051 | CJ36: =VLOOKUP(CI36,'Axe 2 Règles de gestion'!$D$2:$F$506,3, FALSE) -> La date de naissance de l'enfant doit être renseignée. | CK36: POS_C_055 | CL36: =VLOOKUP(CK36,'Axe 2 Règles de gestion'!$D$2:$F$506,3, FALSE) -> La date de fin réelle de la position doit être antérieure ou égale à la date de décès de l'enfant. | CM36: POS_C_056 | CN36: =VLOOKUP(CM36,'Axe 2 Règles de gestion'!$D$2:$F$506,3, FALSE) -> La date de fin prévisionnelle de la position doit être antérieure ou égale à la date de décès de l'enfant. | CO36: POS_C_111 | CP36: =VLOOKUP(CO36,'Axe 2 Règles de gestion'!$D$2:$F$506,3, FALSE) -> La date de fin ou la date de fin prévisionnelle doit être saisie.
A37: 17.10.00 | B37: A | C37: 43152.5 | D37: D0004 | E37: Position | F37: S0031 | G37: Congé parental | H37: E0333 | I37: Congé parental après congé de maternité | J37: Position saisie égale à 'Congé parental après congé de maternité' | K37: A_POS_POSIAD [Saisi] = 'CGP01' | L37: T1578 | M37: Congé parental après Congé de maternité - Demande pendant un Congé parental | N37: Création Modification | O37: Indicateur de renouvellement saisi = Non ET (Indicateur de renouvellement saisi différent d'Indicateur de renouvellement avant saisi OU Lien vers enfant saisi différent du Lien vers enfant avant saisi) ET Position saisie de l'occurrence précédente est une position de 'Congé parental' | P37: A_POS_INDREN [Saisi] = '0' ET (A_POS_INDREN [Saisi] <> A_POS_INDREN [Valeur avant saisie] OU A_POS_LVEPAC [Saisi] <> A_POS_LVEPAC [Valeur avant saisie]) ET (A_POS_POSIAD [Occurrence précédente] = POSITION_SITUATION.R_FOR_IDEN05 ET POSITION_SITUATION.R_REL_PSSAG2 = 'CGP') | Q37: Magistrat de l'ordre judiciaire | R37: P0007 | S37: T | T37: Particulier | U37: Passant | V37: 40725 | W37: 41182 | X37: CPR_D_492 ET CPR_D_720 ET CPR_D_649 ET CPR_D_487 ET CPR_D_500 ET CPR_D_527 ET CPR_D_732 ET POS_C_004 ET POS_C_005 ET POS_C_007 ET POS_C_010 ET POS_C_012 ET POS_C_022 ET POS_C_050 ET POS_C_051 ET POS_C_055 ET POS_C_056 ET POS_C_111 | AY37: CPR_D_492 | AZ37: =VLOOKUP(AY37,'Axe 2 Règles de gestion'!$D$2:$F$506,3, FALSE) -> Le congé parental est accordé par périodes de 6 mois maximum renouvelables (date de fin prévisionnelle du congé parental). | BA37: CPR_D_720 | BB37: =VLOOKUP(BA37,'Axe 2 Règles de gestion'!$D$2:$F$506,3, FALSE) -> Le congé parental est accordé par périodes de 6 mois maximum renouvelables (date de fin réelle du congé parental). | BC37: CPR_D_649 | BD37: =VLOOKUP(BC37,'Axe 2 Règles de gestion'!$D$2:$F$506,3, FALSE) -> Si une nouvelle naissance ou adoption intervient alors que l'agent est déjà en position de congé parental, celui-ci a droit, du chef de son nouvel enfant, à un nouveau congé parental. | BE37: CPR_D_487 | BF37: =VLOOKUP(BE37,'Axe 2 Règles de gestion'!$D$2:$F$506,3, FALSE) -> L'agent doit avoir la qualité de mère ou de père. | BG37: CPR_D_500 | BH37: =VLOOKUP(BG37,'Axe 2 Règles de gestion'!$D$2:$F$506,3, FALSE) -> Le congé parental est accordé de droit à la mère après un congé maternité. | BI37: CPR_D_527 | BJ37: =VLOOKUP(BI37,'Axe 2 Règles de gestion'!$D$2:$F$506,3, FALSE) -> L'enfant né au foyer doit être âgé de 3 ans au plus (date de fin prévisionnelle du congé parental). | BK37: CPR_D_732 | BL37: =VLOOKUP(BK37,'Axe 2 Règles de gestion'!$D$2:$F$506,3, FALSE) -> L'enfant né au foyer doit être âgé de 3 ans au plus (date de fin réelle du congé parental). | BY37: POS_C_004 | BZ37: =VLOOKUP(BY37,'Axe 2 Règles de gestion'!$D$2:$F$506,3, FALSE) -> La date de début de position doit être antérieure ou égale à la date de fin prévisionnelle de position. | CA37: POS_C_005 | CB37: =VLOOKUP(CA37,'Axe 2 Règles de gestion'!$D$2:$F$506,3, FALSE) -> La date de début de la position doit être postérieure ou égale à la date d'entrée dans la FPE ou dans la carrière militaire. | CC37: POS_C_007 | CD37: =VLOOKUP(CC37,'Axe 2 Règles de gestion'!$D$2:$F$506,3, FALSE) -> La date de fin réelle de la position doit être antérieure à la date limite de départ à la retraite. | CE37: POS_C_010 | CF37: =VLOOKUP(CE37,'Axe 2 Règles de gestion'!$D$2:$F$506,3, FALSE) -> La date de début de position doit être antérieure ou égale à la date de fin réelle de position. | CG37: POS_C_012 | CH37: =VLOOKUP(CG37,'Axe 2 Règles de gestion'!$D$2:$F$506,3, FALSE) -> La date de fin prévisionnelle de la position doit être antérieure à la date limite de départ à la retraite. | CI37: POS_C_022 | CJ37: =VLOOKUP(CI37,'Axe 2 Règles de gestion'!$D$2:$F$506,3, FALSE) -> La date de début de position est à J+1 de la date de fin de position de l'occurrence précédente. | CK37: POS_C_050 | CL37: =VLOOKUP(CK37,'Axe 2 Règles de gestion'!$D$2:$F$506,3, FALSE) -> Le lien vers l'enfant doit être renseigné. | CM37: POS_C_051 | CN37: =VLOOKUP(CM37,'Axe 2 Règles de gestion'!$D$2:$F$506,3, FALSE) -> La date de naissance de l'enfant doit être renseignée. | CO37: POS_C_055 | CP37: =VLOOKUP(CO37,'Axe 2 Règles de gestion'!$D$2:$F$506,3, FALSE) -> La date de fin réelle de la position doit être antérieure ou égale à la date de décès de l'enfant. | CQ37: POS_C_056 | CR37: =VLOOKUP(CQ37,'Axe 2 Règles de gestion'!$D$2:$F$506,3, FALSE) -> La date de fin prévisionnelle de la position doit être antérieure ou égale à la date de décès de l'enfant. | CS37: POS_C_111 | CT37: =VLOOKUP(CS37,'Axe 2 Règles de gestion'!$D$2:$F$506,3, FALSE) -> La date de fin ou la date de fin prévisionnelle doit être saisie.
A38: 17.10.00 | B38: A | C38: 43152.5 | D38: D0004 | E38: Position | F38: S0031 | G38: Congé parental | H38: E0333 | I38: Congé parental après congé de maternité | J38: Position saisie égale à 'Congé parental après congé de maternité' | K38: A_POS_POSIAD [Saisi] = 'CGP01' | L38: T0964 | M38: Congé parental après congé de maternité - Demande | N38: Création Modification | O38: Indicateur de renouvellement saisi = Non ET (Indicateur de renouvellement saisi différent d'Indicateur de renouvellement avant saisi OU Lien vers enfant saisi différent du Lien vers enfant avant saisi) ET Position saisie de l'occurrence précédente est différente d'une position de 'Congé parental' | P38: A_POS_INDREN [Saisi] = '0' ET (A_POS_INDREN [Saisi] <> A_POS_INDREN [Valeur avant saisie] OU A_POS_LVEPAC [Saisi] <> A_POS_LVEPAC [Valeur avant saisie]) ET (A_POS_POSIAD [Occurrence précédente] = POSITION_SITUATION.R_FOR_IDEN05 ET POSITION_SITUATION.R_REL_PSSAG2 <> 'CGP') | Q38: Auditeur de justice | R38: P0009 | S38: S | T38: Particulier | U38: Passant | V38: 40725 | W38: 41182 | X38: CPR_D_499 ET CPR_D_723 ET CPR_D_494 ET CPR_D_495 ET CPR_D_509 ET CPR_D_721 ET POS_C_100 ET POS_C_004 ET POS_C_005 ET POS_C_007 ET POS_C_010 ET POS_C_012 ET POS_C_022 ET POS_C_050 ET POS_C_051 ET POS_C_055 ET POS_C_056 ET POS_C_057 ET POS_C_111 | AY38: CPR_D_499 | AZ38: =VLOOKUP(AY38,'Axe 2 Règles de gestion'!$D$2:$F$506,3, FALSE) -> Le congé parental est accordé par périodes de 6 mois maximum renouvelables (date de fin prévisionnelle du congé parental). | BA38: CPR_D_723 | BB38: =VLOOKUP(BA38,'Axe 2 Règles de gestion'!$D$2:$F$506,3, FALSE) -> Le congé parental est accordé par périodes de 6 mois maximum renouvelables (date de fin réelle du congé parental). | BC38: CPR_D_494 | BD38: =VLOOKUP(BC38,'Axe 2 Règles de gestion'!$D$2:$F$506,3, FALSE) -> L'agent doit avoir la qualité de mère ou de père. | BE38: CPR_D_495 | BF38: =VLOOKUP(BE38,'Axe 2 Règles de gestion'!$D$2:$F$506,3, FALSE) -> L'enfant né au foyer doit être âgé de 3 ans au plus (date de fin prévisionnelle du congé parental). | BG38: CPR_D_509 | BH38: =VLOOKUP(BG38,'Axe 2 Règles de gestion'!$D$2:$F$506,3, FALSE) -> Le congé parental est accordé de droit à la mère après un congé maternité. | BI38: CPR_D_721 | BJ38: =VLOOKUP(BI38,'Axe 2 Règles de gestion'!$D$2:$F$506,3, FALSE) -> L'enfant né au foyer doit être âgé de 3 ans au plus (date de fin réelle du congé parental). | BY38: POS_C_100 | BZ38: =VLOOKUP(BY38,'Axe 2 Règles de gestion'!$D$2:$F$506,3, FALSE) -> Lors de la demande initiale, l'agent doit être en activité. | CA38: POS_C_004 | CB38: =VLOOKUP(CA38,'Axe 2 Règles de gestion'!$D$2:$F$506,3, FALSE) -> La date de début de position doit être antérieure ou égale à la date de fin prévisionnelle de position. | CC38: POS_C_005 | CD38: =VLOOKUP(CC38,'Axe 2 Règles de gestion'!$D$2:$F$506,3, FALSE) -> La date de début de la position doit être postérieure ou égale à la date d'entrée dans la FPE ou dans la carrière militaire. | CE38: POS_C_007 | CF38: =VLOOKUP(CE38,'Axe 2 Règles de gestion'!$D$2:$F$506,3, FALSE) -> La date de fin réelle de la position doit être antérieure à la date limite de départ à la retraite. | CG38: POS_C_010 | CH38: =VLOOKUP(CG38,'Axe 2 Règles de gestion'!$D$2:$F$506,3, FALSE) -> La date de début de position doit être antérieure ou égale à la date de fin réelle de position. | CI38: POS_C_012 | CJ38: =VLOOKUP(CI38,'Axe 2 Règles de gestion'!$D$2:$F$506,3, FALSE) -> La date de fin prévisionnelle de la position doit être antérieure à la date limite de départ à la retraite. | CK38: POS_C_022 | CL38: =VLOOKUP(CK38,'Axe 2 Règles de gestion'!$D$2:$F$506,3, FALSE) -> La date de début de position est à J+1 de la date de fin de position de l'occurrence précédente. | CM38: POS_C_050 | CN38: =VLOOKUP(CM38,'Axe 2 Règles de gestion'!$D$2:$F$506,3, FALSE) -> Le lien vers l'enfant doit être renseigné. | CO38: POS_C_051 | CP38: =VLOOKUP(CO38,'Axe 2 Règles de gestion'!$D$2:$F$506,3, FALSE) -> La date de naissance de l'enfant doit être renseignée. | CQ38: POS_C_055 | CR38: =VLOOKUP(CQ38,'Axe 2 Règles de gestion'!$D$2:$F$506,3, FALSE) -> La date de fin réelle de la position doit être antérieure ou égale à la date de décès de l'enfant. | CS38: POS_C_056 | CT38: =VLOOKUP(CS38,'Axe 2 Règles de gestion'!$D$2:$F$506,3, FALSE) -> La date de fin prévisionnelle de la position doit être antérieure ou égale à la date de décès de l'enfant. | CU38: POS_C_057 | CV38: =VLOOKUP(CU38,'Axe 2 Règles de gestion'!$D$2:$F$506,3, FALSE) -> L'agent ne doit pas être en position de détachement entrant sur l'occurrence précédente. | CW38: POS_C_111 | CX38: =VLOOKUP(CW38,'Axe 2 Règles de gestion'!$D$2:$F$506,3, FALSE) -> La date de fin ou la date de fin prévisionnelle doit être saisie.
A39: 17.10.00 | B39: A | C39: 43152.5 | D39: D0004 | E39: Position | F39: S0031 | G39: Congé parental | H39: E0333 | I39: Congé parental après congé de maternité | J39: Position saisie égale à 'Congé parental après congé de maternité' | K39: A_POS_POSIAD [Saisi] = 'CGP01' | L39: T0965 | M39: Congé parental après congé de maternité - Renouvellement | N39: Création Modification | O39: Indicateur de renouvellement saisi = Oui ET (Indicateur de renouvellement saisi différent d'Indicateur de renouvellement avant saisi OU Lien vers enfant saisi différent du Lien vers enfant avant saisi) | P39: A_POS_INDREN [Saisi] = '1' ET (A_POS_INDREN [Saisi] <> A_POS_INDREN [Valeur avant saisie] OU A_POS_LVEPAC [Saisi] <> A_POS_LVEPAC [Valeur avant saisie]) | Q39: Auditeur de justice | R39: P0009 | S39: S | T39: Particulier | U39: Passant | V39: 40725 | W39: 41362 | X39: CPR_D_499 ET CPR_D_723 ET CPR_D_494 ET CPR_D_495 ET CPR_D_721 ET POS_C_004 ET POS_C_005 ET POS_C_007 ET POS_C_010 ET POS_C_012 ET POS_C_022 ET POS_C_050 ET POS_C_051 ET POS_C_055 ET POS_C_056 ET POS_C_111 | AY39: CPR_D_499 | AZ39: =VLOOKUP(AY39,'Axe 2 Règles de gestion'!$D$2:$F$506,3, FALSE) -> Le congé parental est accordé par périodes de 6 mois maximum renouvelables (date de fin prévisionnelle du congé parental). | BA39: CPR_D_723 | BB39: =VLOOKUP(BA39,'Axe 2 Règles de gestion'!$D$2:$F$506,3, FALSE) -> Le congé parental est accordé par périodes de 6 mois maximum renouvelables (date de fin réelle du congé parental). | BC39: CPR_D_494 | BD39: =VLOOKUP(BC39,'Axe 2 Règles de gestion'!$D$2:$F$506,3, FALSE) -> L'agent doit avoir la qualité de mère ou de père. | BE39: CPR_D_495 | BF39: =VLOOKUP(BE39,'Axe 2 Règles de gestion'!$D$2:$F$506,3, FALSE) -> L'enfant né au foyer doit être âgé de 3 ans au plus (date de fin prévisionnelle du congé parental). | BG39: CPR_D_721 | BH39: =VLOOKUP(BG39,'Axe 2 Règles de gestion'!$D$2:$F$506,3, FALSE) -> L'enfant né au foyer doit être âgé de 3 ans au plus (date de fin réelle du congé parental). | BY39: POS_C_004 | BZ39: =VLOOKUP(BY39,'Axe 2 Règles de gestion'!$D$2:$F$506,3, FALSE) -> La date de début de position doit être antérieure ou égale à la date de fin prévisionnelle de position. | CA39: POS_C_005 | CB39: =VLOOKUP(CA39,'Axe 2 Règles de gestion'!$D$2:$F$506,3, FALSE) -> La date de début de la position doit être postérieure ou égale à la date d'entrée dans la FPE ou dans la carrière militaire. | CC39: POS_C_007 | CD39: =VLOOKUP(CC39,'Axe 2 Règles de gestion'!$D$2:$F$506,3, FALSE) -> La date de fin réelle de la position doit être antérieure à la date limite de départ à la retraite. | CE39: POS_C_010 | CF39: =VLOOKUP(CE39,'Axe 2 Règles de gestion'!$D$2:$F$506,3, FALSE) -> La date de début de position doit être antérieure ou égale à la date de fin réelle de position. | CG39: POS_C_012 | CH39: =VLOOKUP(CG39,'Axe 2 Règles de gestion'!$D$2:$F$506,3, FALSE) -> La date de fin prévisionnelle de la position doit être antérieure à la date limite de départ à la retraite. | CI39: POS_C_022 | CJ39: =VLOOKUP(CI39,'Axe 2 Règles de gestion'!$D$2:$F$506,3, FALSE) -> La date de début de position est à J+1 de la date de fin de position de l'occurrence précédente. | CK39: POS_C_050 | CL39: =VLOOKUP(CK39,'Axe 2 Règles de gestion'!$D$2:$F$506,3, FALSE) -> Le lien vers l'enfant doit être renseigné. | CM39: POS_C_051 | CN39: =VLOOKUP(CM39,'Axe 2 Règles de gestion'!$D$2:$F$506,3, FALSE) -> La date de naissance de l'enfant doit être renseignée. | CO39: POS_C_055 | CP39: =VLOOKUP(CO39,'Axe 2 Règles de gestion'!$D$2:$F$506,3, FALSE) -> La date de fin réelle de la position doit être antérieure ou égale à la date de décès de l'enfant. | CQ39: POS_C_056 | CR39: =VLOOKUP(CQ39,'Axe 2 Règles de gestion'!$D$2:$F$506,3, FALSE) -> La date de fin prévisionnelle de la position doit être antérieure ou égale à la date de décès de l'enfant. | CS39: POS_C_111 | CT39: =VLOOKUP(CS39,'Axe 2 Règles de gestion'!$D$2:$F$506,3, FALSE) -> La date de fin ou la date de fin prévisionnelle doit être saisie.
A40: 17.10.00 | B40: A | C40: 43152.5 | D40: D0004 | E40: Position | F40: S0031 | G40: Congé parental | H40: E0333 | I40: Congé parental après congé de maternité | J40: Position saisie égale à 'Congé parental après congé de maternité' | K40: A_POS_POSIAD [Saisi] = 'CGP01' | L40: T0967 | M40: Congé parental après congé de maternité - Réintégration | N40: Modification | O40: Indicateur de renouvellement saisi identique à Indicateur de renouvellement avant saisi ET Lien vers enfant saisi identique au Lien vers enfant avant saisi | P40: A_POS_INDREN [Saisi] = A_POS_INDREN [Valeur avant saisie] ET A_POS_LVEPAC [Saisi] = A_POS_LVEPAC [Valeur avant saisie]) | Q40: Auditeur de justice | R40: P0009 | S40: S | T40: Particulier | U40: Passant | V40: 40725 | W40: 41362 | X40: CPR_D_499 ET CPR_D_723 ET CPR_D_495 ET CPR_D_721 ET POS_C_004 ET POS_C_007 ET POS_C_010 ET POS_C_012 ET POS_C_050 ET POS_C_051 ET POS_C_055 ET POS_C_056 ET POS_C_111 | AY40: CPR_D_499 | AZ40: =VLOOKUP(AY40,'Axe 2 Règles de gestion'!$D$2:$F$506,3, FALSE) -> Le congé parental est accordé par périodes de 6 mois maximum renouvelables (date de fin prévisionnelle du congé parental). | BA40: CPR_D_723 | BB40: =VLOOKUP(BA40,'Axe 2 Règles de gestion'!$D$2:$F$506,3, FALSE) -> Le congé parental est accordé par périodes de 6 mois maximum renouvelables (date de fin réelle du congé parental). | BC40: CPR_D_495 | BD40: =VLOOKUP(BC40,'Axe 2 Règles de gestion'!$D$2:$F$506,3, FALSE) -> L'enfant né au foyer doit être âgé de 3 ans au plus (date de fin prévisionnelle du congé parental). | BE40: CPR_D_721 | BF40: =VLOOKUP(BE40,'Axe 2 Règles de gestion'!$D$2:$F$506,3, FALSE) -> L'enfant né au foyer doit être âgé de 3 ans au plus (date de fin réelle du congé parental). | BY40: POS_C_004 | BZ40: =VLOOKUP(BY40,'Axe 2 Règles de gestion'!$D$2:$F$506,3, FALSE) -> La date de début de position doit être antérieure ou égale à la date de fin prévisionnelle de position. | CA40: POS_C_007 | CB40: =VLOOKUP(CA40,'Axe 2 Règles de gestion'!$D$2:$F$506,3, FALSE) -> La date de fin réelle de la position doit être antérieure à la date limite de départ à la retraite. | CC40: POS_C_010 | CD40: =VLOOKUP(CC40,'Axe 2 Règles de gestion'!$D$2:$F$506,3, FALSE) -> La date de début de position doit être antérieure ou égale à la date de fin réelle de position. | CE40: POS_C_012 | CF40: =VLOOKUP(CE40,'Axe 2 Règles de gestion'!$D$2:$F$506,3, FALSE) -> La date de fin prévisionnelle de la position doit être antérieure à la date limite de départ à la retraite. | CG40: POS_C_050 | CH40: =VLOOKUP(CG40,'Axe 2 Règles de gestion'!$D$2:$F$506,3, FALSE) -> Le lien vers l'enfant doit être renseigné. | CI40: POS_C_051 | CJ40: =VLOOKUP(CI40,'Axe 2 Règles de gestion'!$D$2:$F$506,3, FALSE) -> La date de naissance de l'enfant doit être renseignée. | CK40: POS_C_055 | CL40: =VLOOKUP(CK40,'Axe 2 Règles de gestion'!$D$2:$F$506,3, FALSE) -> La date de fin réelle de la position doit être antérieure ou égale à la date de décès de l'enfant. | CM40: POS_C_056 | CN40: =VLOOKUP(CM40,'Axe 2 Règles de gestion'!$D$2:$F$506,3, FALSE) -> La date de fin prévisionnelle de la position doit être antérieure ou égale à la date de décès de l'enfant. | CO40: POS_C_111 | CP40: =VLOOKUP(CO40,'Axe 2 Règles de gestion'!$D$2:$F$506,3, FALSE) -> La date de fin ou la date de fin prévisionnelle doit être saisie.
A41: 17.10.00 | B41: A | C41: 43152.5 | D41: D0004 | E41: Position | F41: S0031 | G41: Congé parental | H41: E0333 | I41: Congé parental après congé de maternité | J41: Position saisie égale à 'Congé parental après congé de maternité' | K41: A_POS_POSIAD [Saisi] = 'CGP01' | L41: T1578 | M41: Congé parental après Congé de maternité - Demande pendant un Congé parental | N41: Création Modification | O41: Indicateur de renouvellement saisi = Non ET (Indicateur de renouvellement saisi différent d'Indicateur de renouvellement avant saisi OU Lien vers enfant saisi différent du Lien vers enfant avant saisi) ET Position saisie de l'occurrence précédente est une position de 'Congé parental' | P41: A_POS_INDREN [Saisi] = '0' ET (A_POS_INDREN [Saisi] <> A_POS_INDREN [Valeur avant saisie] OU A_POS_LVEPAC [Saisi] <> A_POS_LVEPAC [Valeur avant saisie]) ET (A_POS_POSIAD [Occurrence précédente] = POSITION_SITUATION.R_FOR_IDEN05 ET POSITION_SITUATION.R_REL_PSSAG2 = 'CGP') | Q41: Auditeur de justice | R41: P0009 | S41: S | T41: Particulier | U41: Passant | V41: 40725 | W41: 41182 | X41: CPR_D_499 ET CPR_D_723 ET CPR_D_650 ET CPR_D_494 ET CPR_D_509 ET CPR_D_531 ET CPR_D_735 ET POS_C_004 ET POS_C_005 ET POS_C_007 ET POS_C_010 ET POS_C_012 ET POS_C_022 ET POS_C_050 ET POS_C_051 ET POS_C_055 ET POS_C_056 ET POS_C_111 | AY41: CPR_D_499 | AZ41: =VLOOKUP(AY41,'Axe 2 Règles de gestion'!$D$2:$F$506,3, FALSE) -> Le congé parental est accordé par périodes de 6 mois maximum renouvelables (date de fin prévisionnelle du congé parental). | BA41: CPR_D_723 | BB41: =VLOOKUP(BA41,'Axe 2 Règles de gestion'!$D$2:$F$506,3, FALSE) -> Le congé parental est accordé par périodes de 6 mois maximum renouvelables (date de fin réelle du congé parental). | BC41: CPR_D_650 | BD41: =VLOOKUP(BC41,'Axe 2 Règles de gestion'!$D$2:$F$506,3, FALSE) -> Si une nouvelle naissance ou adoption intervient alors que l'agent est déjà en position de congé parental, celui-ci a droit, du chef de son nouvel enfant, à un nouveau congé parental. | BE41: CPR_D_494 | BF41: =VLOOKUP(BE41,'Axe 2 Règles de gestion'!$D$2:$F$506,3, FALSE) -> L'agent doit avoir la qualité de mère ou de père. | BG41: CPR_D_509 | BH41: =VLOOKUP(BG41,'Axe 2 Règles de gestion'!$D$2:$F$506,3, FALSE) -> Le congé parental est accordé de droit à la mère après un congé maternité. | BI41: CPR_D_531 | BJ41: =VLOOKUP(BI41,'Axe 2 Règles de gestion'!$D$2:$F$506,3, FALSE) -> L'enfant né au foyer doit être âgé de 3 ans au plus (date de fin prévisionnelle du congé parental). | BK41: CPR_D_735 | BL41: =VLOOKUP(BK41,'Axe 2 Règles de gestion'!$D$2:$F$506,3, FALSE) -> L'enfant né au foyer doit être âgé de 3 ans au plus (date de fin réelle du congé parental). | BY41: POS_C_004 | BZ41: =VLOOKUP(BY41,'Axe 2 Règles de gestion'!$D$2:$F$506,3, FALSE) -> La date de début de position doit être antérieure ou égale à la date de fin prévisionnelle de position. | CA41: POS_C_005 | CB41: =VLOOKUP(CA41,'Axe 2 Règles de gestion'!$D$2:$F$506,3, FALSE) -> La date de début de la position doit être postérieure ou égale à la date d'entrée dans la FPE ou dans la carrière militaire. | CC41: POS_C_007 | CD41: =VLOOKUP(CC41,'Axe 2 Règles de gestion'!$D$2:$F$506,3, FALSE) -> La date de fin réelle de la position doit être antérieure à la date limite de départ à la retraite. | CE41: POS_C_010 | CF41: =VLOOKUP(CE41,'Axe 2 Règles de gestion'!$D$2:$F$506,3, FALSE) -> La date de début de position doit être antérieure ou égale à la date de fin réelle de position. | CG41: POS_C_012 | CH41: =VLOOKUP(CG41,'Axe 2 Règles de gestion'!$D$2:$F$506,3, FALSE) -> La date de fin prévisionnelle de la position doit être antérieure à la date limite de départ à la retraite. | CI41: POS_C_022 | CJ41: =VLOOKUP(CI41,'Axe 2 Règles de gestion'!$D$2:$F$506,3, FALSE) -> La date de début de position est à J+1 de la date de fin de position de l'occurrence précédente. | CK41: POS_C_050 | CL41: =VLOOKUP(CK41,'Axe 2 Règles de gestion'!$D$2:$F$506,3, FALSE) -> Le lien vers l'enfant doit être renseigné. | CM41: POS_C_051 | CN41: =VLOOKUP(CM41,'Axe 2 Règles de gestion'!$D$2:$F$506,3, FALSE) -> La date de naissance de l'enfant doit être renseignée. | CO41: POS_C_055 | CP41: =VLOOKUP(CO41,'Axe 2 Règles de gestion'!$D$2:$F$506,3, FALSE) -> La date de fin réelle de la position doit être antérieure ou égale à la date de décès de l'enfant. | CQ41: POS_C_056 | CR41: =VLOOKUP(CQ41,'Axe 2 Règles de gestion'!$D$2:$F$506,3, FALSE) -> La date de fin prévisionnelle de la position doit être antérieure ou égale à la date de décès de l'enfant. | CS41: POS_C_111 | CT41: =VLOOKUP(CS41,'Axe 2 Règles de gestion'!$D$2:$F$506,3, FALSE) -> La date de fin ou la date de fin prévisionnelle doit être saisie.
A42: 17.10.00 | B42: A | C42: 43152.5 | D42: D0004 | E42: Position | F42: S0031 | G42: Congé parental | H42: E0333 | I42: Congé parental après congé de maternité | J42: Position saisie égale à 'Congé parental après congé de maternité' | K42: A_POS_POSIAD [Saisi] = 'CGP01' | L42: T0964 | M42: Congé parental après congé de maternité - Demande | N42: Création Modification | O42: Indicateur de renouvellement saisi = Non ET (Indicateur de renouvellement saisi différent d'Indicateur de renouvellement avant saisi OU Lien vers enfant saisi différent du Lien vers enfant avant saisi) ET Position saisie de l'occurrence précédente est différente d'une position de 'Congé parental' | P42: A_POS_INDREN [Saisi] = '0' ET (A_POS_INDREN [Saisi] <> A_POS_INDREN [Valeur avant saisie] OU A_POS_LVEPAC [Saisi] <> A_POS_LVEPAC [Valeur avant saisie]) ET (A_POS_POSIAD [Occurrence précédente] = POSITION_SITUATION.R_FOR_IDEN05 ET POSITION_SITUATION.R_REL_PSSAG2 <> 'CGP') | Q42: Conseiller ou avocat général à la Cour de cassation en service extraordinaire | R42: P0046 | S42: N | T42: Particulier | U42: Passant | V42: 40725 | W42: 41182 | X42: CPR_D_492 ET CPR_D_720 ET CPR_D_487 ET CPR_D_488 ET CPR_D_500 ET CPR_D_718 ET POS_C_100 ET POS_C_004 ET POS_C_006 ET POS_C_007 ET POS_C_009 ET POS_C_010 ET POS_C_012 ET POS_C_022 ET POS_C_050 ET POS_C_051 ET POS_C_055 ET POS_C_056 ET POS_C_057 ET POS_C_106 ET POS_C_111 | AY42: CPR_D_492 | AZ42: =VLOOKUP(AY42,'Axe 2 Règles de gestion'!$D$2:$F$506,3, FALSE) -> Le congé parental est accordé par périodes de 6 mois maximum renouvelables (date de fin prévisionnelle du congé parental). | BA42: CPR_D_720 | BB42: =VLOOKUP(BA42,'Axe 2 Règles de gestion'!$D$2:$F$506,3, FALSE) -> Le congé parental est accordé par périodes de 6 mois maximum renouvelables (date de fin réelle du congé parental). | BC42: CPR_D_487 | BD42: =VLOOKUP(BC42,'Axe 2 Règles de gestion'!$D$2:$F$506,3, FALSE) -> L'agent doit avoir la qualité de mère ou de père. | BE42: CPR_D_488 | BF42: =VLOOKUP(BE42,'Axe 2 Règles de gestion'!$D$2:$F$506,3, FALSE) -> L'enfant né au foyer doit être âgé de 3 ans au plus (date de fin prévisionnelle du congé parental). | BG42: CPR_D_500 | BH42: =VLOOKUP(BG42,'Axe 2 Règles de gestion'!$D$2:$F$506,3, FALSE) -> Le congé parental est accordé de droit à la mère après un congé maternité. | BI42: CPR_D_718 | BJ42: =VLOOKUP(BI42,'Axe 2 Règles de gestion'!$D$2:$F$506,3, FALSE) -> L'enfant né au foyer doit être âgé de 3 ans au plus (date de fin réelle du congé parental). | BY42: POS_C_100 | BZ42: =VLOOKUP(BY42,'Axe 2 Règles de gestion'!$D$2:$F$506,3, FALSE) -> Lors de la demande initiale, l'agent doit être en activité. | CA42: POS_C_004 | CB42: =VLOOKUP(CA42,'Axe 2 Règles de gestion'!$D$2:$F$506,3, FALSE) -> La date de début de position doit être antérieure ou égale à la date de fin prévisionnelle de position. | CC42: POS_C_006 | CD42: =VLOOKUP(CC42,'Axe 2 Règles de gestion'!$D$2:$F$506,3, FALSE) -> La date de fin réelle de la position doit être antérieure ou égale à la date de fin réelle ou prévisionnelle du lien juridique. | CE42: POS_C_007 | CF42: =VLOOKUP(CE42,'Axe 2 Règles de gestion'!$D$2:$F$506,3, FALSE) -> La date de fin réelle de la position doit être antérieure à la date limite de départ à la retraite. | CG42: POS_C_009 | CH42: =VLOOKUP(CG42,'Axe 2 Règles de gestion'!$D$2:$F$506,3, FALSE) -> La date de début de la position doit être postérieure ou égale à la date de début du lien juridique. | CI42: POS_C_010 | CJ42: =VLOOKUP(CI42,'Axe 2 Règles de gestion'!$D$2:$F$506,3, FALSE) -> La date de début de position doit être antérieure ou égale à la date de fin réelle de position. | CK42: POS_C_012 | CL42: =VLOOKUP(CK42,'Axe 2 Règles de gestion'!$D$2:$F$506,3, FALSE) -> La date de fin prévisionnelle de la position doit être antérieure à la date limite de départ à la retraite. | CM42: POS_C_022 | CN42: =VLOOKUP(CM42,'Axe 2 Règles de gestion'!$D$2:$F$506,3, FALSE) -> La date de début de position est à J+1 de la date de fin de position de l'occurrence précédente. | CO42: POS_C_050 | CP42: =VLOOKUP(CO42,'Axe 2 Règles de gestion'!$D$2:$F$506,3, FALSE) -> Le lien vers l'enfant doit être renseigné. | CQ42: POS_C_051 | CR42: =VLOOKUP(CQ42,'Axe 2 Règles de gestion'!$D$2:$F$506,3, FALSE) -> La date de naissance de l'enfant doit être renseignée. | CS42: POS_C_055 | CT42: =VLOOKUP(CS42,'Axe 2 Règles de gestion'!$D$2:$F$506,3, FALSE) -> La date de fin réelle de la position doit être antérieure ou égale à la date de décès de l'enfant. | CU42: POS_C_056 | CV42: =VLOOKUP(CU42,'Axe 2 Règles de gestion'!$D$2:$F$506,3, FALSE) -> La date de fin prévisionnelle de la position doit être antérieure ou égale à la date de décès de l'enfant. | CW42: POS_C_057 | CX42: =VLOOKUP(CW42,'Axe 2 Règles de gestion'!$D$2:$F$506,3, FALSE) -> L'agent ne doit pas être en position de détachement entrant sur l'occurrence précédente. | CY42: POS_C_106 | CZ42: =VLOOKUP(CY42,'Axe 2 Règles de gestion'!$D$2:$F$506,3, FALSE) -> La date de fin prévisionnelle de la position doit être antérieure ou égale à la date de fin réelle ou prévisionnelle du lien juridique. | DA42: POS_C_111 | DB42: =VLOOKUP(DA42,'Axe 2 Règles de gestion'!$D$2:$F$506,3, FALSE) -> La date de fin ou la date de fin prévisionnelle doit être saisie.
A43: 17.10.00 | B43: A | C43: 43152.5 | D43: D0004 | E43: Position | F43: S0031 | G43: Congé parental | H43: E0333 | I43: Congé parental après congé de maternité | J43: Position saisie égale à 'Congé parental après congé de maternité' | K43: A_POS_POSIAD [Saisi] = 'CGP01' | L43: T0965 | M43: Congé parental après congé de maternité - Renouvellement | N43: Création Modification | O43: Indicateur de renouvellement saisi = Oui ET (Indicateur de renouvellement saisi différent d'Indicateur de renouvellement avant saisi OU Lien vers enfant saisi différent du Lien vers enfant avant saisi) | P43: A_POS_INDREN [Saisi] = '1' ET (A_POS_INDREN [Saisi] <> A_POS_INDREN [Valeur avant saisie] OU A_POS_LVEPAC [Saisi] <> A_POS_LVEPAC [Valeur avant saisie]) | Q43: Conseiller ou avocat général à la Cour de cassation en service extraordinaire | R43: P0046 | S43: N | T43: Particulier | U43: Passant | V43: 40725 | W43: 41362 | X43: CPR_D_492 ET CPR_D_720 ET CPR_D_487 ET CPR_D_488 ET CPR_D_718 ET POS_C_004 ET POS_C_006 ET POS_C_007 ET POS_C_009 ET POS_C_010 ET POS_C_012 ET POS_C_022 ET POS_C_050 ET POS_C_051 ET POS_C_055 ET POS_C_056 ET POS_C_106 ET POS_C_111 | AY43: CPR_D_492 | AZ43: =VLOOKUP(AY43,'Axe 2 Règles de gestion'!$D$2:$F$506,3, FALSE) -> Le congé parental est accordé par périodes de 6 mois maximum renouvelables (date de fin prévisionnelle du congé parental). | BA43: CPR_D_720 | BB43: =VLOOKUP(BA43,'Axe 2 Règles de gestion'!$D$2:$F$506,3, FALSE) -> Le congé parental est accordé par périodes de 6 mois maximum renouvelables (date de fin réelle du congé parental). | BC43: CPR_D_487 | BD43: =VLOOKUP(BC43,'Axe 2 Règles de gestion'!$D$2:$F$506,3, FALSE) -> L'agent doit avoir la qualité de mère ou de père. | BE43: CPR_D_488 | BF43: =VLOOKUP(BE43,'Axe 2 Règles de gestion'!$D$2:$F$506,3, FALSE) -> L'enfant né au foyer doit être âgé de 3 ans au plus (date de fin prévisionnelle du congé parental). | BG43: CPR_D_718 | BH43: =VLOOKUP(BG43,'Axe 2 Règles de gestion'!$D$2:$F$506,3, FALSE) -> L'enfant né au foyer doit être âgé de 3 ans au plus (date de fin réelle du congé parental). | BY43: POS_C_004 | BZ43: =VLOOKUP(BY43,'Axe 2 Règles de gestion'!$D$2:$F$506,3, FALSE) -> La date de début de position doit être antérieure ou égale à la date de fin prévisionnelle de position. | CA43: POS_C_006 | CB43: =VLOOKUP(CA43,'Axe 2 Règles de gestion'!$D$2:$F$506,3, FALSE) -> La date de fin réelle de la position doit être antérieure ou égale à la date de fin réelle ou prévisionnelle du lien juridique. | CC43: POS_C_007 | CD43: =VLOOKUP(CC43,'Axe 2 Règles de gestion'!$D$2:$F$506,3, FALSE) -> La date de fin réelle de la position doit être antérieure à la date limite de départ à la retraite. | CE43: POS_C_009 | CF43: =VLOOKUP(CE43,'Axe 2 Règles de gestion'!$D$2:$F$506,3, FALSE) -> La date de début de la position doit être postérieure ou égale à la date de début du lien juridique. | CG43: POS_C_010 | CH43: =VLOOKUP(CG43,'Axe 2 Règles de gestion'!$D$2:$F$506,3, FALSE) -> La date de début de position doit être antérieure ou égale à la date de fin réelle de position. | CI43: POS_C_012 | CJ43: =VLOOKUP(CI43,'Axe 2 Règles de gestion'!$D$2:$F$506,3, FALSE) -> La date de fin prévisionnelle de la position doit être antérieure à la date limite de départ à la retraite. | CK43: POS_C_022 | CL43: =VLOOKUP(CK43,'Axe 2 Règles de gestion'!$D$2:$F$506,3, FALSE) -> La date de début de position est à J+1 de la date de fin de position de l'occurrence précédente. | CM43: POS_C_050 | CN43: =VLOOKUP(CM43,'Axe 2 Règles de gestion'!$D$2:$F$506,3, FALSE) -> Le lien vers l'enfant doit être renseigné. | CO43: POS_C_051 | CP43: =VLOOKUP(CO43,'Axe 2 Règles de gestion'!$D$2:$F$506,3, FALSE) -> La date de naissance de l'enfant doit être renseignée. | CQ43: POS_C_055 | CR43: =VLOOKUP(CQ43,'Axe 2 Règles de gestion'!$D$2:$F$506,3, FALSE) -> La date de fin réelle de la position doit être antérieure ou égale à la date de décès de l'enfant. | CS43: POS_C_056 | CT43: =VLOOKUP(CS43,'Axe 2 Règles de gestion'!$D$2:$F$506,3, FALSE) -> La date de fin prévisionnelle de la position doit être antérieure ou égale à la date de décès de l'enfant. | CU43: POS_C_106 | CV43: =VLOOKUP(CU43,'Axe 2 Règles de gestion'!$D$2:$F$506,3, FALSE) -> La date de fin prévisionnelle de la position doit être antérieure ou égale à la date de fin réelle ou prévisionnelle du lien juridique. | CW43: POS_C_111 | CX43: =VLOOKUP(CW43,'Axe 2 Règles de gestion'!$D$2:$F$506,3, FALSE) -> La date de fin ou la date de fin prévisionnelle doit être saisie.
A44: 17.10.00 | B44: A | C44: 43152.5 | D44: D0004 | E44: Position | F44: S0031 | G44: Congé parental | H44: E0333 | I44: Congé parental après congé de maternité | J44: Position saisie égale à 'Congé parental après congé de maternité' | K44: A_POS_POSIAD [Saisi] = 'CGP01' | L44: T0967 | M44: Congé parental après congé de maternité - Réintégration | N44: Modification | O44: Indicateur de renouvellement saisi identique à Indicateur de renouvellement avant saisi ET Lien vers enfant saisi identique au Lien vers enfant avant saisi | P44: A_POS_INDREN [Saisi] = A_POS_INDREN [Valeur avant saisie] ET A_POS_LVEPAC [Saisi] = A_POS_LVEPAC [Valeur avant saisie]) | Q44: Conseiller ou avocat général à la Cour de cassation en service extraordinaire | R44: P0046 | S44: N | T44: Particulier | U44: Passant | V44: 40725 | W44: 41362 | X44: CPR_D_492 ET CPR_D_720 ET CPR_D_488 ET CPR_D_718 ET POS_C_004 ET POS_C_006 ET POS_C_007 ET POS_C_010 ET POS_C_012 ET POS_C_050 ET POS_C_051 ET POS_C_055 ET POS_C_056 ET POS_C_106 ET POS_C_111 | AY44: CPR_D_492 | AZ44: =VLOOKUP(AY44,'Axe 2 Règles de gestion'!$D$2:$F$506,3, FALSE) -> Le congé parental est accordé par périodes de 6 mois maximum renouvelables (date de fin prévisionnelle du congé parental). | BA44: CPR_D_720 | BB44: =VLOOKUP(BA44,'Axe 2 Règles de gestion'!$D$2:$F$506,3, FALSE) -> Le congé parental est accordé par périodes de 6 mois maximum renouvelables (date de fin réelle du congé parental). | BC44: CPR_D_488 | BD44: =VLOOKUP(BC44,'Axe 2 Règles de gestion'!$D$2:$F$506,3, FALSE) -> L'enfant né au foyer doit être âgé de 3 ans au plus (date de fin prévisionnelle du congé parental). | BE44: CPR_D_718 | BF44: =VLOOKUP(BE44,'Axe 2 Règles de gestion'!$D$2:$F$506,3, FALSE) -> L'enfant né au foyer doit être âgé de 3 ans au plus (date de fin réelle du congé parental). | BY44: POS_C_004 | BZ44: =VLOOKUP(BY44,'Axe 2 Règles de gestion'!$D$2:$F$506,3, FALSE) -> La date de début de position doit être antérieure ou égale à la date de fin prévisionnelle de position. | CA44: POS_C_006 | CB44: =VLOOKUP(CA44,'Axe 2 Règles de gestion'!$D$2:$F$506,3, FALSE) -> La date de fin réelle de la position doit être antérieure ou égale à la date de fin réelle ou prévisionnelle du lien juridique. | CC44: POS_C_007 | CD44: =VLOOKUP(CC44,'Axe 2 Règles de gestion'!$D$2:$F$506,3, FALSE) -> La date de fin réelle de la position doit être antérieure à la date limite de départ à la retraite. | CE44: POS_C_010 | CF44: =VLOOKUP(CE44,'Axe 2 Règles de gestion'!$D$2:$F$506,3, FALSE) -> La date de début de position doit être antérieure ou égale à la date de fin réelle de position. | CG44: POS_C_012 | CH44: =VLOOKUP(CG44,'Axe 2 Règles de gestion'!$D$2:$F$506,3, FALSE) -> La date de fin prévisionnelle de la position doit être antérieure à la date limite de départ à la retraite. | CI44: POS_C_050 | CJ44: =VLOOKUP(CI44,'Axe 2 Règles de gestion'!$D$2:$F$506,3, FALSE) -> Le lien vers l'enfant doit être renseigné. | CK44: POS_C_051 | CL44: =VLOOKUP(CK44,'Axe 2 Règles de gestion'!$D$2:$F$506,3, FALSE) -> La date de naissance de l'enfant doit être renseignée. | CM44: POS_C_055 | CN44: =VLOOKUP(CM44,'Axe 2 Règles de gestion'!$D$2:$F$506,3, FALSE) -> La date de fin réelle de la position doit être antérieure ou égale à la date de décès de l'enfant. | CO44: POS_C_056 | CP44: =VLOOKUP(CO44,'Axe 2 Règles de gestion'!$D$2:$F$506,3, FALSE) -> La date de fin prévisionnelle de la position doit être antérieure ou égale à la date de décès de l'enfant. | CQ44: POS_C_106 | CR44: =VLOOKUP(CQ44,'Axe 2 Règles de gestion'!$D$2:$F$506,3, FALSE) -> La date de fin prévisionnelle de la position doit être antérieure ou égale à la date de fin réelle ou prévisionnelle du lien juridique. | CS44: POS_C_111 | CT44: =VLOOKUP(CS44,'Axe 2 Règles de gestion'!$D$2:$F$506,3, FALSE) -> La date de fin ou la date de fin prévisionnelle doit être saisie.
A45: 17.10.00 | B45: A | C45: 43152.5 | D45: D0004 | E45: Position | F45: S0031 | G45: Congé parental | H45: E0333 | I45: Congé parental après congé de maternité | J45: Position saisie égale à 'Congé parental après congé de maternité' | K45: A_POS_POSIAD [Saisi] = 'CGP01' | L45: T1578 | M45: Congé parental après Congé de maternité - Demande pendant un Congé parental | N45: Création Modification | O45: Indicateur de renouvellement saisi = Non ET (Indicateur de renouvellement saisi différent d'Indicateur de renouvellement avant saisi OU Lien vers enfant saisi différent du Lien vers enfant avant saisi) ET Position saisie de l'occurrence précédente est une position de 'Congé parental' | P45: A_POS_INDREN [Saisi] = '0' ET (A_POS_INDREN [Saisi] <> A_POS_INDREN [Valeur avant saisie] OU A_POS_LVEPAC [Saisi] <> A_POS_LVEPAC [Valeur avant saisie]) ET (A_POS_POSIAD [Occurrence précédente] = POSITION_SITUATION.R_FOR_IDEN05 ET POSITION_SITUATION.R_REL_PSSAG2 = 'CGP') | Q45: Conseiller ou avocat général à la Cour de cassation en service extraordinaire | R45: P0046 | S45: N | T45: Particulier | U45: Passant | V45: 40725 | W45: 41182 | X45: CPR_D_492 ET CPR_D_720 ET CPR_D_649 ET CPR_D_487 ET CPR_D_500 ET CPR_D_527 ET CPR_D_732 ET POS_C_004 ET POS_C_006 ET POS_C_007 ET POS_C_009 ET POS_C_010 ET POS_C_012 ET POS_C_022 ET POS_C_050 ET POS_C_051 ET POS_C_055 ET POS_C_056 ET POS_C_106 ET POS_C_111 | AY45: CPR_D_492 | AZ45: =VLOOKUP(AY45,'Axe 2 Règles de gestion'!$D$2:$F$506,3, FALSE) -> Le congé parental est accordé par périodes de 6 mois maximum renouvelables (date de fin prévisionnelle du congé parental). | BA45: CPR_D_720 | BB45: =VLOOKUP(BA45,'Axe 2 Règles de gestion'!$D$2:$F$506,3, FALSE) -> Le congé parental est accordé par périodes de 6 mois maximum renouvelables (date de fin réelle du congé parental). | BC45: CPR_D_649 | BD45: =VLOOKUP(BC45,'Axe 2 Règles de gestion'!$D$2:$F$506,3, FALSE) -> Si une nouvelle naissance ou adoption intervient alors que l'agent est déjà en position de congé parental, celui-ci a droit, du chef de son nouvel enfant, à un nouveau congé parental. | BE45: CPR_D_487 | BF45: =VLOOKUP(BE45,'Axe 2 Règles de gestion'!$D$2:$F$506,3, FALSE) -> L'agent doit avoir la qualité de mère ou de père. | BG45: CPR_D_500 | BH45: =VLOOKUP(BG45,'Axe 2 Règles de gestion'!$D$2:$F$506,3, FALSE) -> Le congé parental est accordé de droit à la mère après un congé maternité. | BI45: CPR_D_527 | BJ45: =VLOOKUP(BI45,'Axe 2 Règles de gestion'!$D$2:$F$506,3, FALSE) -> L'enfant né au foyer doit être âgé de 3 ans au plus (date de fin prévisionnelle du congé parental). | BK45: CPR_D_732 | BL45: =VLOOKUP(BK45,'Axe 2 Règles de gestion'!$D$2:$F$506,3, FALSE) -> L'enfant né au foyer doit être âgé de 3 ans au plus (date de fin réelle du congé parental). | BY45: POS_C_004 | BZ45: =VLOOKUP(BY45,'Axe 2 Règles de gestion'!$D$2:$F$506,3, FALSE) -> La date de début de position doit être antérieure ou égale à la date de fin prévisionnelle de position. | CA45: POS_C_006 | CB45: =VLOOKUP(CA45,'Axe 2 Règles de gestion'!$D$2:$F$506,3, FALSE) -> La date de fin réelle de la position doit être antérieure ou égale à la date de fin réelle ou prévisionnelle du lien juridique. | CC45: POS_C_007 | CD45: =VLOOKUP(CC45,'Axe 2 Règles de gestion'!$D$2:$F$506,3, FALSE) -> La date de fin réelle de la position doit être antérieure à la date limite de départ à la retraite. | CE45: POS_C_009 | CF45: =VLOOKUP(CE45,'Axe 2 Règles de gestion'!$D$2:$F$506,3, FALSE) -> La date de début de la position doit être postérieure ou égale à la date de début du lien juridique. | CG45: POS_C_010 | CH45: =VLOOKUP(CG45,'Axe 2 Règles de gestion'!$D$2:$F$506,3, FALSE) -> La date de début de position doit être antérieure ou égale à la date de fin réelle de position. | CI45: POS_C_012 | CJ45: =VLOOKUP(CI45,'Axe 2 Règles de gestion'!$D$2:$F$506,3, FALSE) -> La date de fin prévisionnelle de la position doit être antérieure à la date limite de départ à la retraite. | CK45: POS_C_022 | CL45: =VLOOKUP(CK45,'Axe 2 Règles de gestion'!$D$2:$F$506,3, FALSE) -> La date de début de position est à J+1 de la date de fin de position de l'occurrence précédente. | CM45: POS_C_050 | CN45: =VLOOKUP(CM45,'Axe 2 Règles de gestion'!$D$2:$F$506,3, FALSE) -> Le lien vers l'enfant doit être renseigné. | CO45: POS_C_051 | CP45: =VLOOKUP(CO45,'Axe 2 Règles de gestion'!$D$2:$F$506,3, FALSE) -> La date de naissance de l'enfant doit être renseignée. | CQ45: POS_C_055 | CR45: =VLOOKUP(CQ45,'Axe 2 Règles de gestion'!$D$2:$F$506,3, FALSE) -> La date de fin réelle de la position doit être antérieure ou égale à la date de décès de l'enfant. | CS45: POS_C_056 | CT45: =VLOOKUP(CS45,'Axe 2 Règles de gestion'!$D$2:$F$506,3, FALSE) -> La date de fin prévisionnelle de la position doit être antérieure ou égale à la date de décès de l'enfant. | CU45: POS_C_106 | CV45: =VLOOKUP(CU45,'Axe 2 Règles de gestion'!$D$2:$F$506,3, FALSE) -> La date de fin prévisionnelle de la position doit être antérieure ou égale à la date de fin réelle ou prévisionnelle du lien juridique. | CW45: POS_C_111 | CX45: =VLOOKUP(CW45,'Axe 2 Règles de gestion'!$D$2:$F$506,3, FALSE) -> La date de fin ou la date de fin prévisionnelle doit être saisie.
A46: 22.10.00 | B46: M | C46: 44840.512 | D46: D0004 | E46: Position | F46: S0031 | G46: Congé parental | H46: E0333 | I46: Congé parental après congé de maternité | J46: Position saisie égale à 'Congé parental après congé de maternité' | K46: A_POS_POSIAD [Saisi] = 'CGP01' | L46: T0964 | M46: Congé parental après congé de maternité - Demande | N46: Création Modification | O46: Indicateur de renouvellement saisi = Non ET (Indicateur de renouvellement saisi différent d'Indicateur de renouvellement avant saisi OU Lien vers enfant saisi différent du Lien vers enfant avant saisi) ET Position saisie de l'occurrence précédente est différente d'une position de 'Congé parental' | P46: A_POS_INDREN [Saisi] = '0' ET (A_POS_INDREN [Saisi] <> A_POS_INDREN [Valeur avant saisie] OU A_POS_LVEPAC [Saisi] <> A_POS_LVEPAC [Valeur avant saisie]) ET (A_POS_POSIAD [Occurrence précédente] = POSITION_SITUATION.R_FOR_IDEN05 ET POSITION_SITUATION.R_REL_PSSAG2 <> 'CGP') | Q46: Personnel civil payé à l'acte ou à la tâche | R46: P0054 | S46: N | T46: Particulier | U46: Exclu | V46: 40725 | W46: 41182
A47: 22.10.00 | B47: M | C47: 44840.512 | D47: D0004 | E47: Position | F47: S0031 | G47: Congé parental | H47: E0333 | I47: Congé parental après congé de maternité | J47: Position saisie égale à 'Congé parental après congé de maternité' | K47: A_POS_POSIAD [Saisi] = 'CGP01' | L47: T0965 | M47: Congé parental après congé de maternité - Renouvellement | N47: Création Modification | O47: Indicateur de renouvellement saisi = Oui ET (Indicateur de renouvellement saisi différent d'Indicateur de renouvellement avant saisi OU Lien vers enfant saisi différent du Lien vers enfant avant saisi) | P47: A_POS_INDREN [Saisi] = '1' ET (A_POS_INDREN [Saisi] <> A_POS_INDREN [Valeur avant saisie] OU A_POS_LVEPAC [Saisi] <> A_POS_LVEPAC [Valeur avant saisie]) | Q47: Personnel civil payé à l'acte ou à la tâche | R47: P0054 | S47: N | T47: Particulier | U47: Exclu | V47: 40725 | W47: 41362
A48: 22.10.00 | B48: M | C48: 44840.512 | D48: D0004 | E48: Position | F48: S0031 | G48: Congé parental | H48: E0333 | I48: Congé parental après congé de maternité | J48: Position saisie égale à 'Congé parental après congé de maternité' | K48: A_POS_POSIAD [Saisi] = 'CGP01' | L48: T0967 | M48: Congé parental après congé de maternité - Réintégration | N48: Modification | O48: Indicateur de renouvellement saisi identique à Indicateur de renouvellement avant saisi ET Lien vers enfant saisi identique au Lien vers enfant avant saisi | P48: A_POS_INDREN [Saisi] = A_POS_INDREN [Valeur avant saisie] ET A_POS_LVEPAC [Saisi] = A_POS_LVEPAC [Valeur avant saisie]) | Q48: Personnel civil payé à l'acte ou à la tâche | R48: P0054 | S48: N | T48: Particulier | U48: Exclu | V48: 40725 | W48: 41362
A49: 22.10.00 | B49: M | C49: 44840.528 | D49: D0004 | E49: Position | F49: S0031 | G49: Congé parental | H49: E0333 | I49: Congé parental après congé de maternité | J49: Position saisie égale à 'Congé parental après congé de maternité' | K49: A_POS_POSIAD [Saisi] = 'CGP01' | L49: T1578 | M49: Congé parental après Congé de maternité - Demande pendant un Congé parental | N49: Création Modification | O49: Indicateur de renouvellement saisi = Non ET (Indicateur de renouvellement saisi différent d'Indicateur de renouvellement avant saisi OU Lien vers enfant saisi différent du Lien vers enfant avant saisi) ET Position saisie de l'occurrence précédente est une position de 'Congé parental' | P49: A_POS_INDREN [Saisi] = '0' ET (A_POS_INDREN [Saisi] <> A_POS_INDREN [Valeur avant saisie] OU A_POS_LVEPAC [Saisi] <> A_POS_LVEPAC [Valeur avant saisie]) ET (A_POS_POSIAD [Occurrence précédente] = POSITION_SITUATION.R_FOR_IDEN05 ET POSITION_SITUATION.R_REL_PSSAG2 = 'CGP') | Q49: Personnel civil payé à l'acte ou à la tâche | R49: P0054 | S49: N | T49: Particulier | U49: Exclu | V49: 40725 | W49: 41182
A50: 22.10.00 | B50: M | C50: 44840.512 | D50: D0004 | E50: Position | F50: S0031 | G50: Congé parental | H50: E0333 | I50: Congé parental après congé de maternité | J50: Position saisie égale à 'Congé parental après congé de maternité' | K50: A_POS_POSIAD [Saisi] = 'CGP01' | L50: T0964 | M50: Congé parental après congé de maternité - Demande | N50: Création Modification | O50: Indicateur de renouvellement saisi = Non ET (Indicateur de renouvellement saisi différent d'Indicateur de renouvellement avant saisi OU Lien vers enfant saisi différent du Lien vers enfant avant saisi) ET Position saisie de l'occurrence précédente est différente d'une position de 'Congé parental' | P50: A_POS_INDREN [Saisi] = '0' ET (A_POS_INDREN [Saisi] <> A_POS_INDREN [Valeur avant saisie] OU A_POS_LVEPAC [Saisi] <> A_POS_LVEPAC [Valeur avant saisie]) ET (A_POS_POSIAD [Occurrence précédente] = POSITION_SITUATION.R_FOR_IDEN05 ET POSITION_SITUATION.R_REL_PSSAG2 <> 'CGP') | Q50: Contractuel de droit privé | R50: P0072 | S50: N | T50: Particulier | U50: Exclu | V50: 40725 | W50: 41182
A51: 22.10.00 | B51: M | C51: 44840.512 | D51: D0004 | E51: Position | F51: S0031 | G51: Congé parental | H51: E0333 | I51: Congé parental après congé de maternité | J51: Position saisie égale à 'Congé parental après congé de maternité' | K51: A_POS_POSIAD [Saisi] = 'CGP01' | L51: T0965 | M51: Congé parental après congé de maternité - Renouvellement | N51: Création Modification | O51: Indicateur de renouvellement saisi = Oui ET (Indicateur de renouvellement saisi différent d'Indicateur de renouvellement avant saisi OU Lien vers enfant saisi différent du Lien vers enfant avant saisi) | P51: A_POS_INDREN [Saisi] = '1' ET (A_POS_INDREN [Saisi] <> A_POS_INDREN [Valeur avant saisie] OU A_POS_LVEPAC [Saisi] <> A_POS_LVEPAC [Valeur avant saisie]) | Q51: Contractuel de droit privé | R51: P0072 | S51: N | T51: Particulier | U51: Exclu | V51: 40725 | W51: 41362
A52: 22.10.00 | B52: M | C52: 44840.513 | D52: D0004 | E52: Position | F52: S0031 | G52: Congé parental | H52: E0333 | I52: Congé parental après congé de maternité | J52: Position saisie égale à 'Congé parental après congé de maternité' | K52: A_POS_POSIAD [Saisi] = 'CGP01' | L52: T0967 | M52: Congé parental après congé de maternité - Réintégration | N52: Modification | O52: Indicateur de renouvellement saisi identique à Indicateur de renouvellement avant saisi ET Lien vers enfant saisi identique au Lien vers enfant avant saisi | P52: A_POS_INDREN [Saisi] = A_POS_INDREN [Valeur avant saisie] ET A_POS_LVEPAC [Saisi] = A_POS_LVEPAC [Valeur avant saisie]) | Q52: Contractuel de droit privé | R52: P0072 | S52: N | T52: Particulier | U52: Exclu | V52: 40725 | W52: 41362
A53: 22.10.00 | B53: M | C53: 44840.529 | D53: D0004 | E53: Position | F53: S0031 | G53: Congé parental | H53: E0333 | I53: Congé parental après congé de maternité | J53: Position saisie égale à 'Congé parental après congé de maternité' | K53: A_POS_POSIAD [Saisi] = 'CGP01' | L53: T1578 | M53: Congé parental après Congé de maternité - Demande pendant un Congé parental | N53: Création Modification | O53: Indicateur de renouvellement saisi = Non ET (Indicateur de renouvellement saisi différent d'Indicateur de renouvellement avant saisi OU Lien vers enfant saisi différent du Lien vers enfant avant saisi) ET Position saisie de l'occurrence précédente est une position de 'Congé parental' | P53: A_POS_INDREN [Saisi] = '0' ET (A_POS_INDREN [Saisi] <> A_POS_INDREN [Valeur avant saisie] OU A_POS_LVEPAC [Saisi] <> A_POS_LVEPAC [Valeur avant saisie]) ET (A_POS_POSIAD [Occurrence précédente] = POSITION_SITUATION.R_FOR_IDEN05 ET POSITION_SITUATION.R_REL_PSSAG2 = 'CGP') | Q53: Contractuel de droit privé | R53: P0072 | S53: N | T53: Particulier | U53: Exclu | V53: 40725 | W53: 41182
A54: 17.10.00 | B54: A | C54: 43152.5 | D54: D0004 | E54: Position | F54: S0031 | G54: Congé parental | H54: E0333 | I54: Congé parental après congé de maternité | J54: Position saisie égale à 'Congé parental après congé de maternité' | K54: A_POS_POSIAD [Saisi] = 'CGP01' | L54: T0964 | M54: Congé parental après congé de maternité - Demande | N54: Création Modification | O54: Indicateur de renouvellement saisi = Non ET (Indicateur de renouvellement saisi différent d'Indicateur de renouvellement avant saisi OU Lien vers enfant saisi différent du Lien vers enfant avant saisi) ET Position saisie de l'occurrence précédente est différente d'une position de 'Congé parental' | P54: A_POS_INDREN [Saisi] = '0' ET (A_POS_INDREN [Saisi] <> A_POS_INDREN [Valeur avant saisie] OU A_POS_LVEPAC [Saisi] <> A_POS_LVEPAC [Valeur avant saisie]) ET (A_POS_POSIAD [Occurrence précédente] = POSITION_SITUATION.R_FOR_IDEN05 ET POSITION_SITUATION.R_REL_PSSAG2 <> 'CGP') | Q54: Enseignant contractuel de l'enseignement agricole privé sous contrat non définitif - Agriculture | R54: P0078 | S54: N | T54: Particulier | U54: Passant | V54: 40725 | W54: 41182 | X54: CPR_D_422 ET CPR_D_761 ET CPR_D_417 ET CPR_D_418 ET CPR_D_423 ET CPR_D_760 ET POS_C_100 ET POS_C_004 ET POS_C_006 ET POS_C_007 ET POS_C_009 ET POS_C_010 ET POS_C_012 ET POS_C_022 ET POS_C_050 ET POS_C_051 ET POS_C_055 ET POS_C_056 ET POS_C_057 ET POS_C_106 ET POS_C_111 | AY54: CPR_D_422 | AZ54: =VLOOKUP(AY54,'Axe 2 Règles de gestion'!$D$2:$F$506,3, FALSE) -> Le congé parental est accordé par périodes de 6 mois maximum renouvelables (date de fin prévisionnelle du congé parental). | BA54: CPR_D_761 | BB54: =VLOOKUP(BA54,'Axe 2 Règles de gestion'!$D$2:$F$506,3, FALSE) -> Le congé parental est accordé par périodes de 6 mois maximum renouvelables (date de fin réelle du congé parental). | BC54: CPR_D_417 | BD54: =VLOOKUP(BC54,'Axe 2 Règles de gestion'!$D$2:$F$506,3, FALSE) -> L'agent doit avoir la qualité de mère ou de père. | BE54: CPR_D_418 | BF54: =VLOOKUP(BE54,'Axe 2 Règles de gestion'!$D$2:$F$506,3, FALSE) -> L'enfant né au foyer doit être âgé de 3 ans au plus (date de fin prévisionnelle du congé parental). | BG54: CPR_D_423 | BH54: =VLOOKUP(BG54,'Axe 2 Règles de gestion'!$D$2:$F$506,3, FALSE) -> Le congé parental est accordé de droit à la mère après un congé maternité. | BI54: CPR_D_760 | BJ54: =VLOOKUP(BI54,'Axe 2 Règles de gestion'!$D$2:$F$506,3, FALSE) -> L'enfant né au foyer doit être âgé de 3 ans au plus (date de fin réelle du congé parental). | BY54: POS_C_100 | BZ54: =VLOOKUP(BY54,'Axe 2 Règles de gestion'!$D$2:$F$506,3, FALSE) -> Lors de la demande initiale, l'agent doit être en activité. | CA54: POS_C_004 | CB54: =VLOOKUP(CA54,'Axe 2 Règles de gestion'!$D$2:$F$506,3, FALSE) -> La date de début de position doit être antérieure ou égale à la date de fin prévisionnelle de position. | CC54: POS_C_006 | CD54: =VLOOKUP(CC54,'Axe 2 Règles de gestion'!$D$2:$F$506,3, FALSE) -> La date de fin réelle de la position doit être antérieure ou égale à la date de fin réelle ou prévisionnelle du lien juridique. | CE54: POS_C_007 | CF54: =VLOOKUP(CE54,'Axe 2 Règles de gestion'!$D$2:$F$506,3, FALSE) -> La date de fin réelle de la position doit être antérieure à la date limite de départ à la retraite. | CG54: POS_C_009 | CH54: =VLOOKUP(CG54,'Axe 2 Règles de gestion'!$D$2:$F$506,3, FALSE) -> La date de début de la position doit être postérieure ou égale à la date de début du lien juridique. | CI54: POS_C_010 | CJ54: =VLOOKUP(CI54,'Axe 2 Règles de gestion'!$D$2:$F$506,3, FALSE) -> La date de début de position doit être antérieure ou égale à la date de fin réelle de position. | CK54: POS_C_012 | CL54: =VLOOKUP(CK54,'Axe 2 Règles de gestion'!$D$2:$F$506,3, FALSE) -> La date de fin prévisionnelle de la position doit être antérieure à la date limite de départ à la retraite. | CM54: POS_C_022 | CN54: =VLOOKUP(CM54,'Axe 2 Règles de gestion'!$D$2:$F$506,3, FALSE) -> La date de début de position est à J+1 de la date de fin de position de l'occurrence précédente. | CO54: POS_C_050 | CP54: =VLOOKUP(CO54,'Axe 2 Règles de gestion'!$D$2:$F$506,3, FALSE) -> Le lien vers l'enfant doit être renseigné. | CQ54: POS_C_051 | CR54: =VLOOKUP(CQ54,'Axe 2 Règles de gestion'!$D$2:$F$506,3, FALSE) -> La date de naissance de l'enfant doit être renseignée. | CS54: POS_C_055 | CT54: =VLOOKUP(CS54,'Axe 2 Règles de gestion'!$D$2:$F$506,3, FALSE) -> La date de fin réelle de la position doit être antérieure ou égale à la date de décès de l'enfant. | CU54: POS_C_056 | CV54: =VLOOKUP(CU54,'Axe 2 Règles de gestion'!$D$2:$F$506,3, FALSE) -> La date de fin prévisionnelle de la position doit être antérieure ou égale à la date de décès de l'enfant. | CW54: POS_C_057 | CX54: =VLOOKUP(CW54,'Axe 2 Règles de gestion'!$D$2:$F$506,3, FALSE) -> L'agent ne doit pas être en position de détachement entrant sur l'occurrence précédente. | CY54: POS_C_106 | CZ54: =VLOOKUP(CY54,'Axe 2 Règles de gestion'!$D$2:$F$506,3, FALSE) -> La date de fin prévisionnelle de la position doit être antérieure ou égale à la date de fin réelle ou prévisionnelle du lien juridique. | DA54: POS_C_111 | DB54: =VLOOKUP(DA54,'Axe 2 Règles de gestion'!$D$2:$F$506,3, FALSE) -> La date de fin ou la date de fin prévisionnelle doit être saisie.
A55: 17.10.00 | B55: A | C55: 43152.5 | D55: D0004 | E55: Position | F55: S0031 | G55: Congé parental | H55: E0333 | I55: Congé parental après congé de maternité | J55: Position saisie égale à 'Congé parental après congé de maternité' | K55: A_POS_POSIAD [Saisi] = 'CGP01' | L55: T0965 | M55: Congé parental après congé de maternité - Renouvellement | N55: Création Modification | O55: Indicateur de renouvellement saisi = Oui ET (Indicateur de renouvellement saisi différent d'Indicateur de renouvellement avant saisi OU Lien vers enfant saisi différent du Lien vers enfant avant saisi) | P55: A_POS_INDREN [Saisi] = '1' ET (A_POS_INDREN [Saisi] <> A_POS_INDREN [Valeur avant saisie] OU A_POS_LVEPAC [Saisi] <> A_POS_LVEPAC [Valeur avant saisie]) | Q55: Enseignant contractuel de l'enseignement agricole privé sous contrat non définitif - Agriculture | R55: P0078 | S55: N | T55: Particulier | U55: Passant | V55: 40725 | W55: 41362 | X55: CPR_D_422 ET CPR_D_761 ET CPR_D_417 ET CPR_D_418 ET CPR_D_760 ET POS_C_004 ET POS_C_006 ET POS_C_007 ET POS_C_009 ET POS_C_010 ET POS_C_012 ET POS_C_022 ET POS_C_050 ET POS_C_051 ET POS_C_055 ET POS_C_056 ET POS_C_106 ET POS_C_111 | AY55: CPR_D_422 | AZ55: =VLOOKUP(AY55,'Axe 2 Règles de gestion'!$D$2:$F$506,3, FALSE) -> Le congé parental est accordé par périodes de 6 mois maximum renouvelables (date de fin prévisionnelle du congé parental). | BA55: CPR_D_761 | BB55: =VLOOKUP(BA55,'Axe 2 Règles de gestion'!$D$2:$F$506,3, FALSE) -> Le congé parental est accordé par périodes de 6 mois maximum renouvelables (date de fin réelle du congé parental). | BC55: CPR_D_417 | BD55: =VLOOKUP(BC55,'Axe 2 Règles de gestion'!$D$2:$F$506,3, FALSE) -> L'agent doit avoir la qualité de mère ou de père. | BE55: CPR_D_418 | BF55: =VLOOKUP(BE55,'Axe 2 Règles de gestion'!$D$2:$F$506,3, FALSE) -> L'enfant né au foyer doit être âgé de 3 ans au plus (date de fin prévisionnelle du congé parental). | BG55: CPR_D_760 | BH55: =VLOOKUP(BG55,'Axe 2 Règles de gestion'!$D$2:$F$506,3, FALSE) -> L'enfant né au foyer doit être âgé de 3 ans au plus (date de fin réelle du congé parental). | BY55: POS_C_004 | BZ55: =VLOOKUP(BY55,'Axe 2 Règles de gestion'!$D$2:$F$506,3, FALSE) -> La date de début de position doit être antérieure ou égale à la date de fin prévisionnelle de position. | CA55: POS_C_006 | CB55: =VLOOKUP(CA55,'Axe 2 Règles de gestion'!$D$2:$F$506,3, FALSE) -> La date de fin réelle de la position doit être antérieure ou égale à la date de fin réelle ou prévisionnelle du lien juridique. | CC55: POS_C_007 | CD55: =VLOOKUP(CC55,'Axe 2 Règles de gestion'!$D$2:$F$506,3, FALSE) -> La date de fin réelle de la position doit être antérieure à la date limite de départ à la retraite. | CE55: POS_C_009 | CF55: =VLOOKUP(CE55,'Axe 2 Règles de gestion'!$D$2:$F$506,3, FALSE) -> La date de début de la position doit être postérieure ou égale à la date de début du lien juridique. | CG55: POS_C_010 | CH55: =VLOOKUP(CG55,'Axe 2 Règles de gestion'!$D$2:$F$506,3, FALSE) -> La date de début de position doit être antérieure ou égale à la date de fin réelle de position. | CI55: POS_C_012 | CJ55: =VLOOKUP(CI55,'Axe 2 Règles de gestion'!$D$2:$F$506,3, FALSE) -> La date de fin prévisionnelle de la position doit être antérieure à la date limite de départ à la retraite. | CK55: POS_C_022 | CL55: =VLOOKUP(CK55,'Axe 2 Règles de gestion'!$D$2:$F$506,3, FALSE) -> La date de début de position est à J+1 de la date de fin de position de l'occurrence précédente. | CM55: POS_C_050 | CN55: =VLOOKUP(CM55,'Axe 2 Règles de gestion'!$D$2:$F$506,3, FALSE) -> Le lien vers l'enfant doit être renseigné. | CO55: POS_C_051 | CP55: =VLOOKUP(CO55,'Axe 2 Règles de gestion'!$D$2:$F$506,3, FALSE) -> La date de naissance de l'enfant doit être renseignée. | CQ55: POS_C_055 | CR55: =VLOOKUP(CQ55,'Axe 2 Règles de gestion'!$D$2:$F$506,3, FALSE) -> La date de fin réelle de la position doit être antérieure ou égale à la date de décès de l'enfant. | CS55: POS_C_056 | CT55: =VLOOKUP(CS55,'Axe 2 Règles de gestion'!$D$2:$F$506,3, FALSE) -> La date de fin prévisionnelle de la position doit être antérieure ou égale à la date de décès de l'enfant. | CU55: POS_C_106 | CV55: =VLOOKUP(CU55,'Axe 2 Règles de gestion'!$D$2:$F$506,3, FALSE) -> La date de fin prévisionnelle de la position doit être antérieure ou égale à la date de fin réelle ou prévisionnelle du lien juridique. | CW55: POS_C_111 | CX55: =VLOOKUP(CW55,'Axe 2 Règles de gestion'!$D$2:$F$506,3, FALSE) -> La date de fin ou la date de fin prévisionnelle doit être saisie.
A56: 17.10.00 | B56: A | C56: 43152.5 | D56: D0004 | E56: Position | F56: S0031 | G56: Congé parental | H56: E0333 | I56: Congé parental après congé de maternité | J56: Position saisie égale à 'Congé parental après congé de maternité' | K56: A_POS_POSIAD [Saisi] = 'CGP01' | L56: T0967 | M56: Congé parental après congé de maternité - Réintégration | N56: Modification | O56: Indicateur de renouvellement saisi identique à Indicateur de renouvellement avant saisi ET Lien vers enfant saisi identique au Lien vers enfant avant saisi | P56: A_POS_INDREN [Saisi] = A_POS_INDREN [Valeur avant saisie] ET A_POS_LVEPAC [Saisi] = A_POS_LVEPAC [Valeur avant saisie]) | Q56: Enseignant contractuel de l'enseignement agricole privé sous contrat non définitif - Agriculture | R56: P0078 | S56: N | T56: Particulier | U56: Passant | V56: 40725 | W56: 41362 | X56: CPR_D_422 ET CPR_D_761 ET CPR_D_418 ET CPR_D_760 ET POS_C_004 ET POS_C_006 ET POS_C_007 ET POS_C_010 ET POS_C_012 ET POS_C_050 ET POS_C_051 ET POS_C_055 ET POS_C_056 ET POS_C_106 ET POS_C_111 | AY56: CPR_D_422 | AZ56: =VLOOKUP(AY56,'Axe 2 Règles de gestion'!$D$2:$F$506,3, FALSE) -> Le congé parental est accordé par périodes de 6 mois maximum renouvelables (date de fin prévisionnelle du congé parental). | BA56: CPR_D_761 | BB56: =VLOOKUP(BA56,'Axe 2 Règles de gestion'!$D$2:$F$506,3, FALSE) -> Le congé parental est accordé par périodes de 6 mois maximum renouvelables (date de fin réelle du congé parental). | BC56: CPR_D_418 | BD56: =VLOOKUP(BC56,'Axe 2 Règles de gestion'!$D$2:$F$506,3, FALSE) -> L'enfant né au foyer doit être âgé de 3 ans au plus (date de fin prévisionnelle du congé parental). | BE56: CPR_D_760 | BF56: =VLOOKUP(BE56,'Axe 2 Règles de gestion'!$D$2:$F$506,3, FALSE) -> L'enfant né au foyer doit être âgé de 3 ans au plus (date de fin réelle du congé parental). | BY56: POS_C_004 | BZ56: =VLOOKUP(BY56,'Axe 2 Règles de gestion'!$D$2:$F$506,3, FALSE) -> La date de début de position doit être antérieure ou égale à la date de fin prévisionnelle de position. | CA56: POS_C_006 | CB56: =VLOOKUP(CA56,'Axe 2 Règles de gestion'!$D$2:$F$506,3, FALSE) -> La date de fin réelle de la position doit être antérieure ou égale à la date de fin réelle ou prévisionnelle du lien juridique. | CC56: POS_C_007 | CD56: =VLOOKUP(CC56,'Axe 2 Règles de gestion'!$D$2:$F$506,3, FALSE) -> La date de fin réelle de la position doit être antérieure à la date limite de départ à la retraite. | CE56: POS_C_010 | CF56: =VLOOKUP(CE56,'Axe 2 Règles de gestion'!$D$2:$F$506,3, FALSE) -> La date de début de position doit être antérieure ou égale à la date de fin réelle de position. | CG56: POS_C_012 | CH56: =VLOOKUP(CG56,'Axe 2 Règles de gestion'!$D$2:$F$506,3, FALSE) -> La date de fin prévisionnelle de la position doit être antérieure à la date limite de départ à la retraite. | CI56: POS_C_050 | CJ56: =VLOOKUP(CI56,'Axe 2 Règles de gestion'!$D$2:$F$506,3, FALSE) -> Le lien vers l'enfant doit être renseigné. | CK56: POS_C_051 | CL56: =VLOOKUP(CK56,'Axe 2 Règles de gestion'!$D$2:$F$506,3, FALSE) -> La date de naissance de l'enfant doit être renseignée. | CM56: POS_C_055 | CN56: =VLOOKUP(CM56,'Axe 2 Règles de gestion'!$D$2:$F$506,3, FALSE) -> La date de fin réelle de la position doit être antérieure ou égale à la date de décès de l'enfant. | CO56: POS_C_056 | CP56: =VLOOKUP(CO56,'Axe 2 Règles de gestion'!$D$2:$F$506,3, FALSE) -> La date de fin prévisionnelle de la position doit être antérieure ou égale à la date de décès de l'enfant. | CQ56: POS_C_106 | CR56: =VLOOKUP(CQ56,'Axe 2 Règles de gestion'!$D$2:$F$506,3, FALSE) -> La date de fin prévisionnelle de la position doit être antérieure ou égale à la date de fin réelle ou prévisionnelle du lien juridique. | CS56: POS_C_111 | CT56: =VLOOKUP(CS56,'Axe 2 Règles de gestion'!$D$2:$F$506,3, FALSE) -> La date de fin ou la date de fin prévisionnelle doit être saisie.
A57: 17.10.00 | B57: A | C57: 43152.5 | D57: D0004 | E57: Position | F57: S0031 | G57: Congé parental | H57: E0333 | I57: Congé parental après congé de maternité | J57: Position saisie égale à 'Congé parental après congé de maternité' | K57: A_POS_POSIAD [Saisi] = 'CGP01' | L57: T1578 | M57: Congé parental après Congé de maternité - Demande pendant un Congé parental | N57: Création Modification | O57: Indicateur de renouvellement saisi = Non ET (Indicateur de renouvellement saisi différent d'Indicateur de renouvellement avant saisi OU Lien vers enfant saisi différent du Lien vers enfant avant saisi) ET Position saisie de l'occurrence précédente est une position de 'Congé parental' | P57: A_POS_INDREN [Saisi] = '0' ET (A_POS_INDREN [Saisi] <> A_POS_INDREN [Valeur avant saisie] OU A_POS_LVEPAC [Saisi] <> A_POS_LVEPAC [Valeur avant saisie]) ET (A_POS_POSIAD [Occurrence précédente] = POSITION_SITUATION.R_FOR_IDEN05 ET POSITION_SITUATION.R_REL_PSSAG2 = 'CGP') | Q57: Enseignant contractuel de l'enseignement agricole privé sous contrat non définitif - Agriculture | R57: P0078 | S57: N | T57: Particulier | U57: Passant | V57: 40725 | W57: 41182 | X57: CPR_D_422 ET CPR_D_761 ET CPR_D_679 ET CPR_D_417 ET CPR_D_423 ET CPR_D_437 ET CPR_D_763 ET POS_C_004 ET POS_C_006 ET POS_C_007 ET POS_C_009 ET POS_C_010 ET POS_C_012 ET POS_C_022 ET POS_C_050 ET POS_C_051 ET POS_C_055 ET POS_C_056 ET POS_C_106 ET POS_C_111 | AY57: CPR_D_422 | AZ57: =VLOOKUP(AY57,'Axe 2 Règles de gestion'!$D$2:$F$506,3, FALSE) -> Le congé parental est accordé par périodes de 6 mois maximum renouvelables (date de fin prévisionnelle du congé parental). | BA57: CPR_D_761 | BB57: =VLOOKUP(BA57,'Axe 2 Règles de gestion'!$D$2:$F$506,3, FALSE) -> Le congé parental est accordé par périodes de 6 mois maximum renouvelables (date de fin réelle du congé parental). | BC57: CPR_D_679 | BD57: =VLOOKUP(BC57,'Axe 2 Règles de gestion'!$D$2:$F$506,3, FALSE) -> Si une nouvelle naissance ou adoption intervient alors que l'agent est déjà en position de congé parental, celui-ci a droit, du chef de son nouvel enfant, à un nouveau congé parental. | BE57: CPR_D_417 | BF57: =VLOOKUP(BE57,'Axe 2 Règles de gestion'!$D$2:$F$506,3, FALSE) -> L'agent doit avoir la qualité de mère ou de père. | BG57: CPR_D_423 | BH57: =VLOOKUP(BG57,'Axe 2 Règles de gestion'!$D$2:$F$506,3, FALSE) -> Le congé parental est accordé de droit à la mère après un congé maternité. | BI57: CPR_D_437 | BJ57: =VLOOKUP(BI57,'Axe 2 Règles de gestion'!$D$2:$F$506,3, FALSE) -> L'enfant né au foyer doit être âgé de 3 ans au plus (date de fin prévisionnelle du congé parental). | BK57: CPR_D_763 | BL57: =VLOOKUP(BK57,'Axe 2 Règles de gestion'!$D$2:$F$506,3, FALSE) -> L'enfant né au foyer doit être âgé de 3 ans au plus (date de fin réelle du congé parental). | BY57: POS_C_004 | BZ57: =VLOOKUP(BY57,'Axe 2 Règles de gestion'!$D$2:$F$506,3, FALSE) -> La date de début de position doit être antérieure ou égale à la date de fin prévisionnelle de position. | CA57: POS_C_006 | CB57: =VLOOKUP(CA57,'Axe 2 Règles de gestion'!$D$2:$F$506,3, FALSE) -> La date de fin réelle de la position doit être antérieure ou égale à la date de fin réelle ou prévisionnelle du lien juridique. | CC57: POS_C_007 | CD57: =VLOOKUP(CC57,'Axe 2 Règles de gestion'!$D$2:$F$506,3, FALSE) -> La date de fin réelle de la position doit être antérieure à la date limite de départ à la retraite. | CE57: POS_C_009 | CF57: =VLOOKUP(CE57,'Axe 2 Règles de gestion'!$D$2:$F$506,3, FALSE) -> La date de début de la position doit être postérieure ou égale à la date de début du lien juridique. | CG57: POS_C_010 | CH57: =VLOOKUP(CG57,'Axe 2 Règles de gestion'!$D$2:$F$506,3, FALSE) -> La date de début de position doit être antérieure ou égale à la date de fin réelle de position. | CI57: POS_C_012 | CJ57: =VLOOKUP(CI57,'Axe 2 Règles de gestion'!$D$2:$F$506,3, FALSE) -> La date de fin prévisionnelle de la position doit être antérieure à la date limite de départ à la retraite. | CK57: POS_C_022 | CL57: =VLOOKUP(CK57,'Axe 2 Règles de gestion'!$D$2:$F$506,3, FALSE) -> La date de début de position est à J+1 de la date de fin de position de l'occurrence précédente. | CM57: POS_C_050 | CN57: =VLOOKUP(CM57,'Axe 2 Règles de gestion'!$D$2:$F$506,3, FALSE) -> Le lien vers l'enfant doit être renseigné. | CO57: POS_C_051 | CP57: =VLOOKUP(CO57,'Axe 2 Règles de gestion'!$D$2:$F$506,3, FALSE) -> La date de naissance de l'enfant doit être renseignée. | CQ57: POS_C_055 | CR57: =VLOOKUP(CQ57,'Axe 2 Règles de gestion'!$D$2:$F$506,3, FALSE) -> La date de fin réelle de la position doit être antérieure ou égale à la date de décès de l'enfant. | CS57: POS_C_056 | CT57: =VLOOKUP(CS57,'Axe 2 Règles de gestion'!$D$2:$F$506,3, FALSE) -> La date de fin prévisionnelle de la position doit être antérieure ou égale à la date de décès de l'enfant. | CU57: POS_C_106 | CV57: =VLOOKUP(CU57,'Axe 2 Règles de gestion'!$D$2:$F$506,3, FALSE) -> La date de fin prévisionnelle de la position doit être antérieure ou égale à la date de fin réelle ou prévisionnelle du lien juridique. | CW57: POS_C_111 | CX57: =VLOOKUP(CW57,'Axe 2 Règles de gestion'!$D$2:$F$506,3, FALSE) -> La date de fin ou la date de fin prévisionnelle doit être saisie.
A58: 17.10.00 | B58: A | C58: 43152.5 | D58: D0004 | E58: Position | F58: S0031 | G58: Congé parental | H58: E0333 | I58: Congé parental après congé de maternité | J58: Position saisie égale à 'Congé parental après congé de maternité' | K58: A_POS_POSIAD [Saisi] = 'CGP01' | L58: T0964 | M58: Congé parental après congé de maternité - Demande | N58: Création Modification | O58: Indicateur de renouvellement saisi = Non ET (Indicateur de renouvellement saisi différent d'Indicateur de renouvellement avant saisi OU Lien vers enfant saisi différent du Lien vers enfant avant saisi) ET Position saisie de l'occurrence précédente est différente d'une position de 'Congé parental' | P58: A_POS_INDREN [Saisi] = '0' ET (A_POS_INDREN [Saisi] <> A_POS_INDREN [Valeur avant saisie] OU A_POS_LVEPAC [Saisi] <> A_POS_LVEPAC [Valeur avant saisie]) ET (A_POS_POSIAD [Occurrence précédente] = POSITION_SITUATION.R_FOR_IDEN05 ET POSITION_SITUATION.R_REL_PSSAG2 <> 'CGP') | Q58: Enseignant contractuel de l'enseignement agricole privé sous contrat définitif - Agriculture | R58: P0079 | S58: N | T58: Particulier | U58: Passant | V58: 40725 | W58: 41182 | X58: CPR_D_375 ET CPR_D_772 ET CPR_D_370 ET CPR_D_371 ET CPR_D_376 ET CPR_D_771 ET POS_C_100 ET POS_C_004 ET POS_C_006 ET POS_C_007 ET POS_C_009 ET POS_C_010 ET POS_C_012 ET POS_C_022 ET POS_C_050 ET POS_C_051 ET POS_C_055 ET POS_C_056 ET POS_C_057 ET POS_C_106 ET POS_C_111 | AY58: CPR_D_375 | AZ58: =VLOOKUP(AY58,'Axe 2 Règles de gestion'!$D$2:$F$506,3, FALSE) -> Le congé parental est accordé par périodes de 6 mois maximum renouvelables (date de fin prévisionnelle du congé parental). | BA58: CPR_D_772 | BB58: =VLOOKUP(BA58,'Axe 2 Règles de gestion'!$D$2:$F$506,3, FALSE) -> Le congé parental est accordé par périodes de 6 mois maximum renouvelables (date de fin réelle du congé parental). | BC58: CPR_D_370 | BD58: =VLOOKUP(BC58,'Axe 2 Règles de gestion'!$D$2:$F$506,3, FALSE) -> L'agent doit avoir la qualité de mère ou de père. | BE58: CPR_D_371 | BF58: =VLOOKUP(BE58,'Axe 2 Règles de gestion'!$D$2:$F$506,3, FALSE) -> L'enfant né au foyer doit être âgé de 3 ans au plus (date de fin prévisionnelle du congé parental). | BG58: CPR_D_376 | BH58: =VLOOKUP(BG58,'Axe 2 Règles de gestion'!$D$2:$F$506,3, FALSE) -> Le congé parental est accordé de droit à la mère après un congé maternité. | BI58: CPR_D_771 | BJ58: =VLOOKUP(BI58,'Axe 2 Règles de gestion'!$D$2:$F$506,3, FALSE) -> L'enfant né au foyer doit être âgé de 3 ans au plus (date de fin réelle du congé parental). | BY58: POS_C_100 | BZ58: =VLOOKUP(BY58,'Axe 2 Règles de gestion'!$D$2:$F$506,3, FALSE) -> Lors de la demande initiale, l'agent doit être en activité. | CA58: POS_C_004 | CB58: =VLOOKUP(CA58,'Axe 2 Règles de gestion'!$D$2:$F$506,3, FALSE) -> La date de début de position doit être antérieure ou égale à la date de fin prévisionnelle de position. | CC58: POS_C_006 | CD58: =VLOOKUP(CC58,'Axe 2 Règles de gestion'!$D$2:$F$506,3, FALSE) -> La date de fin réelle de la position doit être antérieure ou égale à la date de fin réelle ou prévisionnelle du lien juridique. | CE58: POS_C_007 | CF58: =VLOOKUP(CE58,'Axe 2 Règles de gestion'!$D$2:$F$506,3, FALSE) -> La date de fin réelle de la position doit être antérieure à la date limite de départ à la retraite. | CG58: POS_C_009 | CH58: =VLOOKUP(CG58,'Axe 2 Règles de gestion'!$D$2:$F$506,3, FALSE) -> La date de début de la position doit être postérieure ou égale à la date de début du lien juridique. | CI58: POS_C_010 | CJ58: =VLOOKUP(CI58,'Axe 2 Règles de gestion'!$D$2:$F$506,3, FALSE) -> La date de début de position doit être antérieure ou égale à la date de fin réelle de position. | CK58: POS_C_012 | CL58: =VLOOKUP(CK58,'Axe 2 Règles de gestion'!$D$2:$F$506,3, FALSE) -> La date de fin prévisionnelle de la position doit être antérieure à la date limite de départ à la retraite. | CM58: POS_C_022 | CN58: =VLOOKUP(CM58,'Axe 2 Règles de gestion'!$D$2:$F$506,3, FALSE) -> La date de début de position est à J+1 de la date de fin de position de l'occurrence précédente. | CO58: POS_C_050 | CP58: =VLOOKUP(CO58,'Axe 2 Règles de gestion'!$D$2:$F$506,3, FALSE) -> Le lien vers l'enfant doit être renseigné. | CQ58: POS_C_051 | CR58: =VLOOKUP(CQ58,'Axe 2 Règles de gestion'!$D$2:$F$506,3, FALSE) -> La date de naissance de l'enfant doit être renseignée. | CS58: POS_C_055 | CT58: =VLOOKUP(CS58,'Axe 2 Règles de gestion'!$D$2:$F$506,3, FALSE) -> La date de fin réelle de la position doit être antérieure ou égale à la date de décès de l'enfant. | CU58: POS_C_056 | CV58: =VLOOKUP(CU58,'Axe 2 Règles de gestion'!$D$2:$F$506,3, FALSE) -> La date de fin prévisionnelle de la position doit être antérieure ou égale à la date de décès de l'enfant. | CW58: POS_C_057 | CX58: =VLOOKUP(CW58,'Axe 2 Règles de gestion'!$D$2:$F$506,3, FALSE) -> L'agent ne doit pas être en position de détachement entrant sur l'occurrence précédente. | CY58: POS_C_106 | CZ58: =VLOOKUP(CY58,'Axe 2 Règles de gestion'!$D$2:$F$506,3, FALSE) -> La date de fin prévisionnelle de la position doit être antérieure ou égale à la date de fin réelle ou prévisionnelle du lien juridique. | DA58: POS_C_111 | DB58: =VLOOKUP(DA58,'Axe 2 Règles de gestion'!$D$2:$F$506,3, FALSE) -> La date de fin ou la date de fin prévisionnelle doit être saisie.
A59: 17.10.00 | B59: A | C59: 43152.5 | D59: D0004 | E59: Position | F59: S0031 | G59: Congé parental | H59: E0333 | I59: Congé parental après congé de maternité | J59: Position saisie égale à 'Congé parental après congé de maternité' | K59: A_POS_POSIAD [Saisi] = 'CGP01' | L59: T0965 | M59: Congé parental après congé de maternité - Renouvellement | N59: Création Modification | O59: Indicateur de renouvellement saisi = Oui ET (Indicateur de renouvellement saisi différent d'Indicateur de renouvellement avant saisi OU Lien vers enfant saisi différent du Lien vers enfant avant saisi) | P59: A_POS_INDREN [Saisi] = '1' ET (A_POS_INDREN [Saisi] <> A_POS_INDREN [Valeur avant saisie] OU A_POS_LVEPAC [Saisi] <> A_POS_LVEPAC [Valeur avant saisie]) | Q59: Enseignant contractuel de l'enseignement agricole privé sous contrat définitif - Agriculture | R59: P0079 | S59: N | T59: Particulier | U59: Passant | V59: 40725 | W59: 41362 | X59: CPR_D_375 ET CPR_D_772 ET CPR_D_370 ET CPR_D_371 ET CPR_D_771 ET POS_C_004 ET POS_C_006 ET POS_C_007 ET POS_C_009 ET POS_C_010 ET POS_C_012 ET POS_C_022 ET POS_C_050 ET POS_C_051 ET POS_C_055 ET POS_C_056 ET POS_C_106 ET POS_C_111 | AY59: CPR_D_375 | AZ59: =VLOOKUP(AY59,'Axe 2 Règles de gestion'!$D$2:$F$506,3, FALSE) -> Le congé parental est accordé par périodes de 6 mois maximum renouvelables (date de fin prévisionnelle du congé parental). | BA59: CPR_D_772 | BB59: =VLOOKUP(BA59,'Axe 2 Règles de gestion'!$D$2:$F$506,3, FALSE) -> Le congé parental est accordé par périodes de 6 mois maximum renouvelables (date de fin réelle du congé parental). | BC59: CPR_D_370 | BD59: =VLOOKUP(BC59,'Axe 2 Règles de gestion'!$D$2:$F$506,3, FALSE) -> L'agent doit avoir la qualité de mère ou de père. | BE59: CPR_D_371 | BF59: =VLOOKUP(BE59,'Axe 2 Règles de gestion'!$D$2:$F$506,3, FALSE) -> L'enfant né au foyer doit être âgé de 3 ans au plus (date de fin prévisionnelle du congé parental). | BG59: CPR_D_771 | BH59: =VLOOKUP(BG59,'Axe 2 Règles de gestion'!$D$2:$F$506,3, FALSE) -> L'enfant né au foyer doit être âgé de 3 ans au plus (date de fin réelle du congé parental). | BY59: POS_C_004 | BZ59: =VLOOKUP(BY59,'Axe 2 Règles de gestion'!$D$2:$F$506,3, FALSE) -> La date de début de position doit être antérieure ou égale à la date de fin prévisionnelle de position. | CA59: POS_C_006 | CB59: =VLOOKUP(CA59,'Axe 2 Règles de gestion'!$D$2:$F$506,3, FALSE) -> La date de fin réelle de la position doit être antérieure ou égale à la date de fin réelle ou prévisionnelle du lien juridique. | CC59: POS_C_007 | CD59: =VLOOKUP(CC59,'Axe 2 Règles de gestion'!$D$2:$F$506,3, FALSE) -> La date de fin réelle de la position doit être antérieure à la date limite de départ à la retraite. | CE59: POS_C_009 | CF59: =VLOOKUP(CE59,'Axe 2 Règles de gestion'!$D$2:$F$506,3, FALSE) -> La date de début de la position doit être postérieure ou égale à la date de début du lien juridique. | CG59: POS_C_010 | CH59: =VLOOKUP(CG59,'Axe 2 Règles de gestion'!$D$2:$F$506,3, FALSE) -> La date de début de position doit être antérieure ou égale à la date de fin réelle de position. | CI59: POS_C_012 | CJ59: =VLOOKUP(CI59,'Axe 2 Règles de gestion'!$D$2:$F$506,3, FALSE) -> La date de fin prévisionnelle de la position doit être antérieure à la date limite de départ à la retraite. | CK59: POS_C_022 | CL59: =VLOOKUP(CK59,'Axe 2 Règles de gestion'!$D$2:$F$506,3, FALSE) -> La date de début de position est à J+1 de la date de fin de position de l'occurrence précédente. | CM59: POS_C_050 | CN59: =VLOOKUP(CM59,'Axe 2 Règles de gestion'!$D$2:$F$506,3, FALSE) -> Le lien vers l'enfant doit être renseigné. | CO59: POS_C_051 | CP59: =VLOOKUP(CO59,'Axe 2 Règles de gestion'!$D$2:$F$506,3, FALSE) -> La date de naissance de l'enfant doit être renseignée. | CQ59: POS_C_055 | CR59: =VLOOKUP(CQ59,'Axe 2 Règles de gestion'!$D$2:$F$506,3, FALSE) -> La date de fin réelle de la position doit être antérieure ou égale à la date de décès de l'enfant. | CS59: POS_C_056 | CT59: =VLOOKUP(CS59,'Axe 2 Règles de gestion'!$D$2:$F$506,3, FALSE) -> La date de fin prévisionnelle de la position doit être antérieure ou égale à la date de décès de l'enfant. | CU59: POS_C_106 | CV59: =VLOOKUP(CU59,'Axe 2 Règles de gestion'!$D$2:$F$506,3, FALSE) -> La date de fin prévisionnelle de la position doit être antérieure ou égale à la date de fin réelle ou prévisionnelle du lien juridique. | CW59: POS_C_111 | CX59: =VLOOKUP(CW59,'Axe 2 Règles de gestion'!$D$2:$F$506,3, FALSE) -> La date de fin ou la date de fin prévisionnelle doit être saisie.
A60: 17.10.00 | B60: A | C60: 43152.5 | D60: D0004 | E60: Position | F60: S0031 | G60: Congé parental | H60: E0333 | I60: Congé parental après congé de maternité | J60: Position saisie égale à 'Congé parental après congé de maternité' | K60: A_POS_POSIAD [Saisi] = 'CGP01' | L60: T0967 | M60: Congé parental après congé de maternité - Réintégration | N60: Modification | O60: Indicateur de renouvellement saisi identique à Indicateur de renouvellement avant saisi ET Lien vers enfant saisi identique au Lien vers enfant avant saisi | P60: A_POS_INDREN [Saisi] = A_POS_INDREN [Valeur avant saisie] ET A_POS_LVEPAC [Saisi] = A_POS_LVEPAC [Valeur avant saisie]) | Q60: Enseignant contractuel de l'enseignement agricole privé sous contrat définitif - Agriculture | R60: P0079 | S60: N | T60: Particulier | U60: Passant | V60: 40725 | W60: 41362 | X60: CPR_D_375 ET CPR_D_772 ET CPR_D_371 ET CPR_D_771 ET POS_C_004 ET POS_C_006 ET POS_C_007 ET POS_C_010 ET POS_C_012 ET POS_C_050 ET POS_C_051 ET POS_C_055 ET POS_C_056 ET POS_C_106 ET POS_C_111 | AY60: CPR_D_375 | AZ60: =VLOOKUP(AY60,'Axe 2 Règles de gestion'!$D$2:$F$506,3, FALSE) -> Le congé parental est accordé par périodes de 6 mois maximum renouvelables (date de fin prévisionnelle du congé parental). | BA60: CPR_D_772 | BB60: =VLOOKUP(BA60,'Axe 2 Règles de gestion'!$D$2:$F$506,3, FALSE) -> Le congé parental est accordé par périodes de 6 mois maximum renouvelables (date de fin réelle du congé parental). | BC60: CPR_D_371 | BD60: =VLOOKUP(BC60,'Axe 2 Règles de gestion'!$D$2:$F$506,3, FALSE) -> L'enfant né au foyer doit être âgé de 3 ans au plus (date de fin prévisionnelle du congé parental). | BE60: CPR_D_771 | BF60: =VLOOKUP(BE60,'Axe 2 Règles de gestion'!$D$2:$F$506,3, FALSE) -> L'enfant né au foyer doit être âgé de 3 ans au plus (date de fin réelle du congé parental). | BY60: POS_C_004 | BZ60: =VLOOKUP(BY60,'Axe 2 Règles de gestion'!$D$2:$F$506,3, FALSE) -> La date de début de position doit être antérieure ou égale à la date de fin prévisionnelle de position. | CA60: POS_C_006 | CB60: =VLOOKUP(CA60,'Axe 2 Règles de gestion'!$D$2:$F$506,3, FALSE) -> La date de fin réelle de la position doit être antérieure ou égale à la date de fin réelle ou prévisionnelle du lien juridique. | CC60: POS_C_007 | CD60: =VLOOKUP(CC60,'Axe 2 Règles de gestion'!$D$2:$F$506,3, FALSE) -> La date de fin réelle de la position doit être antérieure à la date limite de départ à la retraite. | CE60: POS_C_010 | CF60: =VLOOKUP(CE60,'Axe 2 Règles de gestion'!$D$2:$F$506,3, FALSE) -> La date de début de position doit être antérieure ou égale à la date de fin réelle de position. | CG60: POS_C_012 | CH60: =VLOOKUP(CG60,'Axe 2 Règles de gestion'!$D$2:$F$506,3, FALSE) -> La date de fin prévisionnelle de la position doit être antérieure à la date limite de départ à la retraite. | CI60: POS_C_050 | CJ60: =VLOOKUP(CI60,'Axe 2 Règles de gestion'!$D$2:$F$506,3, FALSE) -> Le lien vers l'enfant doit être renseigné. | CK60: POS_C_051 | CL60: =VLOOKUP(CK60,'Axe 2 Règles de gestion'!$D$2:$F$506,3, FALSE) -> La date de naissance de l'enfant doit être renseignée. | CM60: POS_C_055 | CN60: =VLOOKUP(CM60,'Axe 2 Règles de gestion'!$D$2:$F$506,3, FALSE) -> La date de fin réelle de la position doit être antérieure ou égale à la date de décès de l'enfant. | CO60: POS_C_056 | CP60: =VLOOKUP(CO60,'Axe 2 Règles de gestion'!$D$2:$F$506,3, FALSE) -> La date de fin prévisionnelle de la position doit être antérieure ou égale à la date de décès de l'enfant. | CQ60: POS_C_106 | CR60: =VLOOKUP(CQ60,'Axe 2 Règles de gestion'!$D$2:$F$506,3, FALSE) -> La date de fin prévisionnelle de la position doit être antérieure ou égale à la date de fin réelle ou prévisionnelle du lien juridique. | CS60: POS_C_111 | CT60: =VLOOKUP(CS60,'Axe 2 Règles de gestion'!$D$2:$F$506,3, FALSE) -> La date de fin ou la date de fin prévisionnelle doit être saisie.
A61: 17.10.00 | B61: A | C61: 43152.5 | D61: D0004 | E61: Position | F61: S0031 | G61: Congé parental | H61: E0333 | I61: Congé parental après congé de maternité | J61: Position saisie égale à 'Congé parental après congé de maternité' | K61: A_POS_POSIAD [Saisi] = 'CGP01' | L61: T1578 | M61: Congé parental après Congé de maternité - Demande pendant un Congé parental | N61: Création Modification | O61: Indicateur de renouvellement saisi = Non ET (Indicateur de renouvellement saisi différent d'Indicateur de renouvellement avant saisi OU Lien vers enfant saisi différent du Lien vers enfant avant saisi) ET Position saisie de l'occurrence précédente est une position de 'Congé parental' | P61: A_POS_INDREN [Saisi] = '0' ET (A_POS_INDREN [Saisi] <> A_POS_INDREN [Valeur avant saisie] OU A_POS_LVEPAC [Saisi] <> A_POS_LVEPAC [Valeur avant saisie]) ET (A_POS_POSIAD [Occurrence précédente] = POSITION_SITUATION.R_FOR_IDEN05 ET POSITION_SITUATION.R_REL_PSSAG2 = 'CGP') | Q61: Enseignant contractuel de l'enseignement agricole privé sous contrat définitif - Agriculture | R61: P0079 | S61: N | T61: Particulier | U61: Passant | V61: 40725 | W61: 41182 | X61: CPR_D_375 ET CPR_D_772 ET CPR_D_677 ET CPR_D_370 ET CPR_D_376 ET CPR_D_390 ET CPR_D_781 ET POS_C_004 ET POS_C_006 ET POS_C_007 ET POS_C_009 ET POS_C_010 ET POS_C_012 ET POS_C_022 ET POS_C_050 ET POS_C_051 ET POS_C_055 ET POS_C_056 ET POS_C_106 ET POS_C_111 | AY61: CPR_D_375 | AZ61: =VLOOKUP(AY61,'Axe 2 Règles de gestion'!$D$2:$F$506,3, FALSE) -> Le congé parental est accordé par périodes de 6 mois maximum renouvelables (date de fin prévisionnelle du congé parental). | BA61: CPR_D_772 | BB61: =VLOOKUP(BA61,'Axe 2 Règles de gestion'!$D$2:$F$506,3, FALSE) -> Le congé parental est accordé par périodes de 6 mois maximum renouvelables (date de fin réelle du congé parental). | BC61: CPR_D_677 | BD61: =VLOOKUP(BC61,'Axe 2 Règles de gestion'!$D$2:$F$506,3, FALSE) -> Si une nouvelle naissance ou adoption intervient alors que l'agent est déjà en position de congé parental, celui-ci a droit, du chef de son nouvel enfant, à un nouveau congé parental. | BE61: CPR_D_370 | BF61: =VLOOKUP(BE61,'Axe 2 Règles de gestion'!$D$2:$F$506,3, FALSE) -> L'agent doit avoir la qualité de mère ou de père. | BG61: CPR_D_376 | BH61: =VLOOKUP(BG61,'Axe 2 Règles de gestion'!$D$2:$F$506,3, FALSE) -> Le congé parental est accordé de droit à la mère après un congé maternité. | BI61: CPR_D_390 | BJ61: =VLOOKUP(BI61,'Axe 2 Règles de gestion'!$D$2:$F$506,3, FALSE) -> L'enfant né au foyer doit être âgé de 3 ans au plus (date de fin prévisionnelle du congé parental). | BK61: CPR_D_781 | BL61: =VLOOKUP(BK61,'Axe 2 Règles de gestion'!$D$2:$F$506,3, FALSE) -> L'enfant né au foyer doit être âgé de 3 ans au plus (date de fin réelle du congé parental). | BY61: POS_C_004 | BZ61: =VLOOKUP(BY61,'Axe 2 Règles de gestion'!$D$2:$F$506,3, FALSE) -> La date de début de position doit être antérieure ou égale à la date de fin prévisionnelle de position. | CA61: POS_C_006 | CB61: =VLOOKUP(CA61,'Axe 2 Règles de gestion'!$D$2:$F$506,3, FALSE) -> La date de fin réelle de la position doit être antérieure ou égale à la date de fin réelle ou prévisionnelle du lien juridique. | CC61: POS_C_007 | CD61: =VLOOKUP(CC61,'Axe 2 Règles de gestion'!$D$2:$F$506,3, FALSE) -> La date de fin réelle de la position doit être antérieure à la date limite de départ à la retraite. | CE61: POS_C_009 | CF61: =VLOOKUP(CE61,'Axe 2 Règles de gestion'!$D$2:$F$506,3, FALSE) -> La date de début de la position doit être postérieure ou égale à la date de début du lien juridique. | CG61: POS_C_010 | CH61: =VLOOKUP(CG61,'Axe 2 Règles de gestion'!$D$2:$F$506,3, FALSE) -> La date de début de position doit être antérieure ou égale à la date de fin réelle de position. | CI61: POS_C_012 | CJ61: =VLOOKUP(CI61,'Axe 2 Règles de gestion'!$D$2:$F$506,3, FALSE) -> La date de fin prévisionnelle de la position doit être antérieure à la date limite de départ à la retraite. | CK61: POS_C_022 | CL61: =VLOOKUP(CK61,'Axe 2 Règles de gestion'!$D$2:$F$506,3, FALSE) -> La date de début de position est à J+1 de la date de fin de position de l'occurrence précédente. | CM61: POS_C_050 | CN61: =VLOOKUP(CM61,'Axe 2 Règles de gestion'!$D$2:$F$506,3, FALSE) -> Le lien vers l'enfant doit être renseigné. | CO61: POS_C_051 | CP61: =VLOOKUP(CO61,'Axe 2 Règles de gestion'!$D$2:$F$506,3, FALSE) -> La date de naissance de l'enfant doit être renseignée. | CQ61: POS_C_055 | CR61: =VLOOKUP(CQ61,'Axe 2 Règles de gestion'!$D$2:$F$506,3, FALSE) -> La date de fin réelle de la position doit être antérieure ou égale à la date de décès de l'enfant. | CS61: POS_C_056 | CT61: =VLOOKUP(CS61,'Axe 2 Règles de gestion'!$D$2:$F$506,3, FALSE) -> La date de fin prévisionnelle de la position doit être antérieure ou égale à la date de décès de l'enfant. | CU61: POS_C_106 | CV61: =VLOOKUP(CU61,'Axe 2 Règles de gestion'!$D$2:$F$506,3, FALSE) -> La date de fin prévisionnelle de la position doit être antérieure ou égale à la date de fin réelle ou prévisionnelle du lien juridique. | CW61: POS_C_111 | CX61: =VLOOKUP(CW61,'Axe 2 Règles de gestion'!$D$2:$F$506,3, FALSE) -> La date de fin ou la date de fin prévisionnelle doit être saisie.
A62: 25.10.00 | B62: M | C62: 45989.674 | D62: D0004 | E62: Position | F62: S0031 | G62: Congé parental | H62: E0333 | I62: Congé parental après congé de maternité | J62: Position saisie égale à 'Congé parental après congé de maternité' | K62: A_POS_POSIAD [Saisi] = 'CGP01' | L62: T0964 | M62: Congé parental après congé de maternité - Demande | N62: Création Modification | O62: Indicateur de renouvellement saisi = Non ET (Indicateur de renouvellement saisi différent d'Indicateur de renouvellement avant saisi OU Lien vers enfant saisi différent du Lien vers enfant avant saisi) ET Position saisie de l'occurrence précédente est différente d'une position de 'Congé parental' | P62: A_POS_INDREN [Saisi] = '0' ET (A_POS_INDREN [Saisi] <> A_POS_INDREN [Valeur avant saisie] OU A_POS_LVEPAC [Saisi] <> A_POS_LVEPAC [Valeur avant saisie]) ET (A_POS_POSIAD [Occurrence précédente] = POSITION_SITUATION.R_FOR_IDEN05 ET POSITION_SITUATION.R_REL_PSSAG2 <> 'CGP') | Q62: Ouvrier des parcs et ateliers confirmé non affilié ou stagiaire | R62: P0185 | S62: O | T62: Particulier | U62: Exclu | V62: 40725 | W62: 46110
A63: 25.10.00 | B63: M | C63: 45989.676 | D63: D0004 | E63: Position | F63: S0031 | G63: Congé parental | H63: E0333 | I63: Congé parental après congé de maternité | J63: Position saisie égale à 'Congé parental après congé de maternité' | K63: A_POS_POSIAD [Saisi] = 'CGP01' | L63: T0965 | M63: Congé parental après congé de maternité - Renouvellement | N63: Création Modification | O63: Indicateur de renouvellement saisi = Oui ET (Indicateur de renouvellement saisi différent d'Indicateur de renouvellement avant saisi OU Lien vers enfant saisi différent du Lien vers enfant avant saisi) | P63: A_POS_INDREN [Saisi] = '1' ET (A_POS_INDREN [Saisi] <> A_POS_INDREN [Valeur avant saisie] OU A_POS_LVEPAC [Saisi] <> A_POS_LVEPAC [Valeur avant saisie]) | Q63: Ouvrier des parcs et ateliers confirmé non affilié ou stagiaire | R63: P0185 | S63: O | T63: Particulier | U63: Exclu | V63: 40725 | W63: 46110
A64: 25.10.00 | B64: M | C64: 45989.707 | D64: D0004 | E64: Position | F64: S0031 | G64: Congé parental | H64: E0333 | I64: Congé parental après congé de maternité | J64: Position saisie égale à 'Congé parental après congé de maternité' | K64: A_POS_POSIAD [Saisi] = 'CGP01' | L64: T0967 | M64: Congé parental après congé de maternité - Réintégration | N64: Modification | O64: Indicateur de renouvellement saisi identique à Indicateur de renouvellement avant saisi ET Lien vers enfant saisi identique au Lien vers enfant avant saisi | P64: A_POS_INDREN [Saisi] = A_POS_INDREN [Valeur avant saisie] ET A_POS_LVEPAC [Saisi] = A_POS_LVEPAC [Valeur avant saisie]) | Q64: Ouvrier des parcs et ateliers confirmé non affilié ou stagiaire | R64: P0185 | S64: O | T64: Particulier | U64: Exclu | V64: 40725 | W64: 46110
A65: 25.10.00 | B65: M | C65: 45989.708 | D65: D0004 | E65: Position | F65: S0031 | G65: Congé parental | H65: E0333 | I65: Congé parental après congé de maternité | J65: Position saisie égale à 'Congé parental après congé de maternité' | K65: A_POS_POSIAD [Saisi] = 'CGP01' | L65: T1578 | M65: Congé parental après Congé de maternité - Demande pendant un Congé parental | N65: Création Modification | O65: Indicateur de renouvellement saisi = Non ET (Indicateur de renouvellement saisi différent d'Indicateur de renouvellement avant saisi OU Lien vers enfant saisi différent du Lien vers enfant avant saisi) ET Position saisie de l'occurrence précédente est une position de 'Congé parental' | P65: A_POS_INDREN [Saisi] = '0' ET (A_POS_INDREN [Saisi] <> A_POS_INDREN [Valeur avant saisie] OU A_POS_LVEPAC [Saisi] <> A_POS_LVEPAC [Valeur avant saisie]) ET (A_POS_POSIAD [Occurrence précédente] = POSITION_SITUATION.R_FOR_IDEN05 ET POSITION_SITUATION.R_REL_PSSAG2 = 'CGP') | Q65: Ouvrier des parcs et ateliers confirmé non affilié ou stagiaire | R65: P0185 | S65: O | T65: Particulier | U65: Exclu | V65: 40725 | W65: 46110
A66: 25.10.00 | B66: M | C66: 45989.674 | D66: D0004 | E66: Position | F66: S0031 | G66: Congé parental | H66: E0333 | I66: Congé parental après congé de maternité | J66: Position saisie égale à 'Congé parental après congé de maternité' | K66: A_POS_POSIAD [Saisi] = 'CGP01' | L66: T0964 | M66: Congé parental après congé de maternité - Demande | N66: Création Modification | O66: Indicateur de renouvellement saisi = Non ET (Indicateur de renouvellement saisi différent d'Indicateur de renouvellement avant saisi OU Lien vers enfant saisi différent du Lien vers enfant avant saisi) ET Position saisie de l'occurrence précédente est différente d'une position de 'Congé parental' | P66: A_POS_INDREN [Saisi] = '0' ET (A_POS_INDREN [Saisi] <> A_POS_INDREN [Valeur avant saisie] OU A_POS_LVEPAC [Saisi] <> A_POS_LVEPAC [Valeur avant saisie]) ET (A_POS_POSIAD [Occurrence précédente] = POSITION_SITUATION.R_FOR_IDEN05 ET POSITION_SITUATION.R_REL_PSSAG2 <> 'CGP') | Q66: Ouvrier du service des alcools confirmé non affilié | R66: P0221 | S66: O | T66: Particulier | U66: Exclu | V66: 40725 | W66: 46110
A67: 25.10.00 | B67: M | C67: 45989.677 | D67: D0004 | E67: Position | F67: S0031 | G67: Congé parental | H67: E0333 | I67: Congé parental après congé de maternité | J67: Position saisie égale à 'Congé parental après congé de maternité' | K67: A_POS_POSIAD [Saisi] = 'CGP01' | L67: T0965 | M67: Congé parental après congé de maternité - Renouvellement | N67: Création Modification | O67: Indicateur de renouvellement saisi = Oui ET (Indicateur de renouvellement saisi différent d'Indicateur de renouvellement avant saisi OU Lien vers enfant saisi différent du Lien vers enfant avant saisi) | P67: A_POS_INDREN [Saisi] = '1' ET (A_POS_INDREN [Saisi] <> A_POS_INDREN [Valeur avant saisie] OU A_POS_LVEPAC [Saisi] <> A_POS_LVEPAC [Valeur avant saisie]) | Q67: Ouvrier du service des alcools confirmé non affilié | R67: P0221 | S67: O | T67: Particulier | U67: Exclu | V67: 40725 | W67: 46110
