Workbook
Name date_DIADC: 'Mode opératoire'!#REF!
Name notice_DIADC: 'Mode opératoire'!#REF!
Name notice_ENCHN: 'Mode opératoire'!$B$1:$B$4
Name notice_ICA: 'Mode opératoire'!#REF!

Sheet Mode opératoire
B1: MODE OPERATOIRE
B2: La transaction s'effectue au niveau de la rubrique "Congés/absences", elle inclut l'ensemble des sous-rubriques listées ci-dessous : - Congés/absences - Complément pour congé / absence : impact rémunération - Compteurs des droits à congés - Compteurs de périodes de congés On notera que : La sous-rubrique "Complément pour congé / absence : impact rémunération" est réputée, suite au découpage des absences en tranche de rémunération, avoir des dates de début et de fin alignées sur les dates dedébut et de fin de la sous-rubrique "Congés/absences" (contrôle bloquant)

Sheet Axe 1 Enchainement des RG
A1: Version | B1: Type de mise à jour | C1: Date de mise à jour | D1: Identifiant Domaine | E1: Libellé du Domaine | F1: Identifiant Sous-domaine | G1: Libellé du Sous-domaine | H1: Identifiant Evénement | I1: Libellé de l'évènement | J1: Libellé condition déclenchement Evènement | K1: Condition déclenchement Evènement | L1: Identifiant type d'évènement | M1: Libellé type d'évènement | N1: Type de mise à jour | O1: Libellé condition déclenchement Type Evènement | P1: Condition déclenchement Type Evènement | Q1: Libellé Population | R1: Codification Population | S1: Typologie de population | T1: Général / Particulier | U1: Passant / Exclu | V1: Date de début | W1: Date de fin | X1: Règles mobilisées | Y1: Identifiant Règle de contrôle intellectuel 1 | Z1: Libellé Règle de contrôle intellectuel 1 | AA1: Identifiant Règle de contrôle intellectuel 2 | AB1: Libellé Règle de contrôle intellectuel 2 | AC1: Identifiant Règle de contrôle intellectuel 3 | AD1: Libellé Règle de contrôle intellectuel 3 | AE1: Identifiant Règle de contrôle intellectuel 4 | AF1: Libellé Règle de contrôle intellectuel 4 | AG1: Identifiant Règle de contrôle intellectuel 5 | AH1: Libellé Règle de contrôle intellectuel 5 | AI1: Identifiant Règle de contrôle intellectuel 6 | AJ1: Libellé Règle de contrôle intellectuel 6 | AK1: Identifiant Règle de contrôle intellectuel 7 | AL1: Libellé Règle de contrôle intellectuel 7 | AM1: Identifiant Règle de contrôle intellectuel 8 | AN1: Libellé Règle de contrôle intellectuel 8 | AO1: Identifiant Règle de contrôle intellectuel 9 | AP1: Libellé Règle de contrôle intellectuel 9 | AQ1: Identifiant Règle de condition 1 | AR1: Libellé Règle de condition 1 | AS1: Identifiant Règle de condition 2 | AT1: Libellé Règle de condition 2 | AU1: Identifiant Règle de condition 3 | AV1: Libellé Règle de condition 3 | AW1: Identifiant Règle de condition 4 | AX1: Libellé Règle de condition 4 | AY1: Identifiant Règle de condition 5 | AZ1: Libellé Règle de condition 5 | BA1: Identifiant Règle de condition 6 | BB1: Libellé Règle de condition 6 | BC1: Identifiant Règle de condition 7 | BD1: Libellé Règle de condition 7 | BE1: Identifiant Règle de condition 8 | BF1: Libellé Règle de condition 8 | BG1: Identifiant Règle de contrôle 1 | BH1: Libellé Règle de contrôle 1 | BI1: Identifiant Règle de contrôle 2 | BJ1: Libellé Règle de contrôle 2 | BK1: Identifiant Règle de contrôle 3 | BL1: Libellé Règle de contrôle 3 | BM1: Identifiant Règle de contrôle 4 | BN1: Libellé Règle de contrôle 4 | BO1: Identifiant Règle de contrôle 5 | BP1: Libellé Règle de contrôle 5 | BQ1: Identifiant Règle de contrôle 6 | BR1: Libellé Règle de contrôle 6 | BS1: Identifiant Règle de contrôle 7 | BT1: Libellé Règle de contrôle 7 | BU1: Identifiant Règle de contrôle 8 | BV1: Libellé Règle de contrôle 8 | BW1: Identifiant Règle de contrôle 9 | BX1: Libellé Règle de contrôle 9 | BY1: Identifiant Règle de contrôle 10 | BZ1: Libellé Règle de contrôle 10 | CA1: Identifiant Règle de contrôle 11 | CB1: Libellé Règle de contrôle 11 | CC1: Identifiant Règle de contrôle 12 | CD1: Libellé Règle de contrôle 12 | CE1: Identifiant Règle de contrôle 13 | CF1: Libellé Règle de contrôle 13 | CG1: Identifiant Règle de contrôle 14 | CH1: Libellé Règle de contrôle 14 | CI1: Identifiant Règle de contrôle 15 | CJ1: Libellé Règle de contrôle 15 | CK1: FIME | CL1: Statut de travail
A2: 17.10.00 | B2: A | C2: 43152.5 | D2: D0007 | E2: Congés/Absence | F2: S0046 | G2: Autorisations d'absence | H2: E0427 | I2: Autorisation d'absence pour formation professionnelle | J2: Type de congé/absence saisi égal 'Autorisation d'absence pour formation professionnelle' | K2: A_COA_TYCOAB [Saisi] = 'CA001' | L2: T1088 | M2: Autorisation d'absence pour formation professionnelle | N2: Création Modification | Q2: Titulaire ou magistrat | R2: P0001 | S2: T | T2: Général | U2: Passant | V2: 40725 | X2: ABS_C_010 ET ABS_C_001 ET ABS_C_003 ET ABS_C_004 ET ABS_C_007 ET ABS_C_008 ET ABS_C_009 ET ABS_C_019 ET ABS_C_020 ET ABS_C_026 | BG2: ABS_C_010 | BH2: =VLOOKUP(BG2,'Axe 2 Règles de gestion'!$D$2:$F$354,3, FALSE) -> L'agent doit être en activité. | BI2: ABS_C_001 | BJ2: =VLOOKUP(BI2,'Axe 2 Règles de gestion'!$D$2:$F$354,3, FALSE) -> La date de début du congé/absence doit être postérieure ou égale à la date de recrutement dans la FPE ou dans la carrière militaire. | BK2: ABS_C_003 | BL2: =VLOOKUP(BK2,'Axe 2 Règles de gestion'!$D$2:$F$354,3, FALSE) -> La date de début du congé/absence doit être antérieure ou égale à la date de fin réelle du congé/absence. | BM2: ABS_C_004 | BN2: =VLOOKUP(BM2,'Axe 2 Règles de gestion'!$D$2:$F$354,3, FALSE) -> La date de début du congé/absence doit être antérieure ou égale à la date de fin prévisionnelle du congé/absence. | BO2: ABS_C_007 | BP2: =VLOOKUP(BO2,'Axe 2 Règles de gestion'!$D$2:$F$354,3, FALSE) -> La date de fin réelle du congé/absence doit être antérieure à la date limite de départ à la retraite. | BQ2: ABS_C_008 | BR2: =VLOOKUP(BQ2,'Axe 2 Règles de gestion'!$D$2:$F$354,3, FALSE) -> La date de fin prévisionnelle du congé/absence doit être antérieure à la date limite de départ à la retraite. | BS2: ABS_C_009 | BT2: =VLOOKUP(BS2,'Axe 2 Règles de gestion'!$D$2:$F$354,3, FALSE) -> La date de fin réelle ou la date de fin prévisionnelle du congé/absence doit être saisie. | BU2: ABS_C_019 | BV2: =VLOOKUP(BU2,'Axe 2 Règles de gestion'!$D$2:$F$354,3, FALSE) -> Si l'absence ne commence pas par une demi-journée et si l'absence précédente ne finit pas par une demi journée, la date de début de l'absence saisie est postérieure à la date de fin réelle de l'absence précédente. | BW2: ABS_C_020 | BX2: =VLOOKUP(BW2,'Axe 2 Règles de gestion'!$D$2:$F$354,3, FALSE) -> Si l'absence ne commence pas par une demi-journée et si l'absence précédente ne finit pas par une demi journée, la date de début de l'absence saisie est postérieure à la date de fin prévisionnelle de l'absence précédente. | BY2: ABS_C_026 | BZ2: =VLOOKUP(BY2,'Axe 2 Règles de gestion'!$D$2:$F$354,3, FALSE) -> Dans le cas d'un congé autre que CLM, CLD, CGM et CITIS, l'indicateur de requalification doit être à non et les impacts spécifiques à la requalification ne doivent pas être mobilisés ou l'impact rémunération est vide.
A3: 17.10.00 | B3: A | C3: 43152.5 | D3: D0007 | E3: Congés/Absence | F3: S0046 | G3: Autorisations d'absence | H3: E0427 | I3: Autorisation d'absence pour formation professionnelle | J3: Type de congé/absence saisi égal 'Autorisation d'absence pour formation professionnelle' | K3: A_COA_TYCOAB [Saisi] = 'CA001' | L3: T1088 | M3: Autorisation d'absence pour formation professionnelle | N3: Création Modification | Q3: Contractuel | R3: P0003 | S3: N | T3: Général | U3: Passant | V3: 40725 | X3: ABS_C_010 ET ABS_C_003 ET ABS_C_004 ET ABS_C_009 ET ABS_C_019 ET ABS_C_020 ET ABS_C_026 ET ABS_C_002 ET ABS_C_005 ET ABS_C_006 ET ABS_C_007 ET ABS_C_008 | BG3: ABS_C_010 | BH3: =VLOOKUP(BG3,'Axe 2 Règles de gestion'!$D$2:$F$354,3, FALSE) -> L'agent doit être en activité. | BI3: ABS_C_003 | BJ3: =VLOOKUP(BI3,'Axe 2 Règles de gestion'!$D$2:$F$354,3, FALSE) -> La date de début du congé/absence doit être antérieure ou égale à la date de fin réelle du congé/absence. | BK3: ABS_C_004 | BL3: =VLOOKUP(BK3,'Axe 2 Règles de gestion'!$D$2:$F$354,3, FALSE) -> La date de début du congé/absence doit être antérieure ou égale à la date de fin prévisionnelle du congé/absence. | BM3: ABS_C_009 | BN3: =VLOOKUP(BM3,'Axe 2 Règles de gestion'!$D$2:$F$354,3, FALSE) -> La date de fin réelle ou la date de fin prévisionnelle du congé/absence doit être saisie. | BO3: ABS_C_019 | BP3: =VLOOKUP(BO3,'Axe 2 Règles de gestion'!$D$2:$F$354,3, FALSE) -> Si l'absence ne commence pas par une demi-journée et si l'absence précédente ne finit pas par une demi journée, la date de début de l'absence saisie est postérieure à la date de fin réelle de l'absence précédente. | BQ3: ABS_C_020 | BR3: =VLOOKUP(BQ3,'Axe 2 Règles de gestion'!$D$2:$F$354,3, FALSE) -> Si l'absence ne commence pas par une demi-journée et si l'absence précédente ne finit pas par une demi journée, la date de début de l'absence saisie est postérieure à la date de fin prévisionnelle de l'absence précédente. | BS3: ABS_C_026 | BT3: =VLOOKUP(BS3,'Axe 2 Règles de gestion'!$D$2:$F$354,3, FALSE) -> Dans le cas d'un congé autre que CLM, CLD, CGM et CITIS, l'indicateur de requalification doit être à non et les impacts spécifiques à la requalification ne doivent pas être mobilisés ou l'impact rémunération est vide. | BU3: ABS_C_002 | BV3: =VLOOKUP(BU3,'Axe 2 Règles de gestion'!$D$2:$F$354,3, FALSE) -> La date de début du congé/absence doit être postérieure ou égale à la date de début du lien juridique. | BW3: ABS_C_005 | BX3: =VLOOKUP(BW3,'Axe 2 Règles de gestion'!$D$2:$F$354,3, FALSE) -> La date de fin réelle du congé/absence doit être antérieure ou égale à la date limite de fin réelle ou prévisionnelle du lien juridique. | BY3: ABS_C_006 | BZ3: =VLOOKUP(BY3,'Axe 2 Règles de gestion'!$D$2:$F$354,3, FALSE) -> La date de fin prévisionnelle du congé/absence doit être antérieure ou égale à la date limite de fin réelle ou prévisionnelle du lien juridique. | CA3: ABS_C_007 | CB3: =VLOOKUP(CA3,'Axe 2 Règles de gestion'!$D$2:$F$354,3, FALSE) -> La date de fin réelle du congé/absence doit être antérieure à la date limite de départ à la retraite. | CC3: ABS_C_008 | CD3: =VLOOKUP(CC3,'Axe 2 Règles de gestion'!$D$2:$F$354,3, FALSE) -> La date de fin prévisionnelle du congé/absence doit être antérieure à la date limite de départ à la retraite.
A4: 17.10.00 | B4: A | C4: 43152.5 | D4: D0007 | E4: Congés/Absence | F4: S0046 | G4: Autorisations d'absence | H4: E0427 | I4: Autorisation d'absence pour formation professionnelle | J4: Type de congé/absence saisi égal 'Autorisation d'absence pour formation professionnelle' | K4: A_COA_TYCOAB [Saisi] = 'CA001' | L4: T1088 | M4: Autorisation d'absence pour formation professionnelle | N4: Création Modification | Q4: Stagiaire ou auditeur ou élève | R4: P0004 | S4: S | T4: Général | U4: Passant | V4: 40725 | X4: ABS_C_010 ET ABS_C_001 ET ABS_C_003 ET ABS_C_004 ET ABS_C_007 ET ABS_C_008 ET ABS_C_009 ET ABS_C_019 ET ABS_C_020 ET ABS_C_026 | BG4: ABS_C_010 | BH4: =VLOOKUP(BG4,'Axe 2 Règles de gestion'!$D$2:$F$354,3, FALSE) -> L'agent doit être en activité. | BI4: ABS_C_001 | BJ4: =VLOOKUP(BI4,'Axe 2 Règles de gestion'!$D$2:$F$354,3, FALSE) -> La date de début du congé/absence doit être postérieure ou égale à la date de recrutement dans la FPE ou dans la carrière militaire. | BK4: ABS_C_003 | BL4: =VLOOKUP(BK4,'Axe 2 Règles de gestion'!$D$2:$F$354,3, FALSE) -> La date de début du congé/absence doit être antérieure ou égale à la date de fin réelle du congé/absence. | BM4: ABS_C_004 | BN4: =VLOOKUP(BM4,'Axe 2 Règles de gestion'!$D$2:$F$354,3, FALSE) -> La date de début du congé/absence doit être antérieure ou égale à la date de fin prévisionnelle du congé/absence. | BO4: ABS_C_007 | BP4: =VLOOKUP(BO4,'Axe 2 Règles de gestion'!$D$2:$F$354,3, FALSE) -> La date de fin réelle du congé/absence doit être antérieure à la date limite de départ à la retraite. | BQ4: ABS_C_008 | BR4: =VLOOKUP(BQ4,'Axe 2 Règles de gestion'!$D$2:$F$354,3, FALSE) -> La date de fin prévisionnelle du congé/absence doit être antérieure à la date limite de départ à la retraite. | BS4: ABS_C_009 | BT4: =VLOOKUP(BS4,'Axe 2 Règles de gestion'!$D$2:$F$354,3, FALSE) -> La date de fin réelle ou la date de fin prévisionnelle du congé/absence doit être saisie. | BU4: ABS_C_019 | BV4: =VLOOKUP(BU4,'Axe 2 Règles de gestion'!$D$2:$F$354,3, FALSE) -> Si l'absence ne commence pas par une demi-journée et si l'absence précédente ne finit pas par une demi journée, la date de début de l'absence saisie est postérieure à la date de fin réelle de l'absence précédente. | BW4: ABS_C_020 | BX4: =VLOOKUP(BW4,'Axe 2 Règles de gestion'!$D$2:$F$354,3, FALSE) -> Si l'absence ne commence pas par une demi-journée et si l'absence précédente ne finit pas par une demi journée, la date de début de l'absence saisie est postérieure à la date de fin prévisionnelle de l'absence précédente. | BY4: ABS_C_026 | BZ4: =VLOOKUP(BY4,'Axe 2 Règles de gestion'!$D$2:$F$354,3, FALSE) -> Dans le cas d'un congé autre que CLM, CLD, CGM et CITIS, l'indicateur de requalification doit être à non et les impacts spécifiques à la requalification ne doivent pas être mobilisés ou l'impact rémunération est vide.
A5: 17.10.00 | B5: A | C5: 43189.5 | D5: D0007 | E5: Congés/Absence | F5: S0046 | G5: Autorisations d'absence | H5: E0427 | I5: Autorisation d'absence pour formation professionnelle | J5: Type de congé/absence saisi égal 'Autorisation d'absence pour formation professionnelle' | K5: A_COA_TYCOAB [Saisi] = 'CA001' | L5: T1088 | M5: Autorisation d'absence pour formation professionnelle | N5: Création Modification | Q5: Ouvrier d'état | R5: P0005 | S5: O | T5: Général | U5: Passant | V5: 40725 | X5: ABS_C_010 ET ABS_C_003 ET ABS_C_004 ET ABS_C_009 ET ABS_C_019 ET ABS_C_020 ET ABS_C_026 ET ABS_C_002 ET ABS_C_005 ET ABS_C_006 ET ABS_C_007 ET ABS_C_008 | BG5: ABS_C_010 | BH5: =VLOOKUP(BG5,'Axe 2 Règles de gestion'!$D$2:$F$354,3, FALSE) -> L'agent doit être en activité. | BI5: ABS_C_003 | BJ5: =VLOOKUP(BI5,'Axe 2 Règles de gestion'!$D$2:$F$354,3, FALSE) -> La date de début du congé/absence doit être antérieure ou égale à la date de fin réelle du congé/absence. | BK5: ABS_C_004 | BL5: =VLOOKUP(BK5,'Axe 2 Règles de gestion'!$D$2:$F$354,3, FALSE) -> La date de début du congé/absence doit être antérieure ou égale à la date de fin prévisionnelle du congé/absence. | BM5: ABS_C_009 | BN5: =VLOOKUP(BM5,'Axe 2 Règles de gestion'!$D$2:$F$354,3, FALSE) -> La date de fin réelle ou la date de fin prévisionnelle du congé/absence doit être saisie. | BO5: ABS_C_019 | BP5: =VLOOKUP(BO5,'Axe 2 Règles de gestion'!$D$2:$F$354,3, FALSE) -> Si l'absence ne commence pas par une demi-journée et si l'absence précédente ne finit pas par une demi journée, la date de début de l'absence saisie est postérieure à la date de fin réelle de l'absence précédente. | BQ5: ABS_C_020 | BR5: =VLOOKUP(BQ5,'Axe 2 Règles de gestion'!$D$2:$F$354,3, FALSE) -> Si l'absence ne commence pas par une demi-journée et si l'absence précédente ne finit pas par une demi journée, la date de début de l'absence saisie est postérieure à la date de fin prévisionnelle de l'absence précédente. | BS5: ABS_C_026 | BT5: =VLOOKUP(BS5,'Axe 2 Règles de gestion'!$D$2:$F$354,3, FALSE) -> Dans le cas d'un congé autre que CLM, CLD, CGM et CITIS, l'indicateur de requalification doit être à non et les impacts spécifiques à la requalification ne doivent pas être mobilisés ou l'impact rémunération est vide. | BU5: ABS_C_002 | BV5: =VLOOKUP(BU5,'Axe 2 Règles de gestion'!$D$2:$F$354,3, FALSE) -> La date de début du congé/absence doit être postérieure ou égale à la date de début du lien juridique. | BW5: ABS_C_005 | BX5: =VLOOKUP(BW5,'Axe 2 Règles de gestion'!$D$2:$F$354,3, FALSE) -> La date de fin réelle du congé/absence doit être antérieure ou égale à la date limite de fin réelle ou prévisionnelle du lien juridique. | BY5: ABS_C_006 | BZ5: =VLOOKUP(BY5,'Axe 2 Règles de gestion'!$D$2:$F$354,3, FALSE) -> La date de fin prévisionnelle du congé/absence doit être antérieure ou égale à la date limite de fin réelle ou prévisionnelle du lien juridique. | CA5: ABS_C_007 | CB5: =VLOOKUP(CA5,'Axe 2 Règles de gestion'!$D$2:$F$354,3, FALSE) -> La date de fin réelle du congé/absence doit être antérieure à la date limite de départ à la retraite. | CC5: ABS_C_008 | CD5: =VLOOKUP(CC5,'Axe 2 Règles de gestion'!$D$2:$F$354,3, FALSE) -> La date de fin prévisionnelle du congé/absence doit être antérieure à la date limite de départ à la retraite.
A6: 17.10.00 | B6: A | C6: 43152.5 | D6: D0007 | E6: Congés/Absence | F6: S0046 | G6: Autorisations d'absence | H6: E0427 | I6: Autorisation d'absence pour formation professionnelle | J6: Type de congé/absence saisi égal 'Autorisation d'absence pour formation professionnelle' | K6: A_COA_TYCOAB [Saisi] = 'CA001' | L6: T1088 | M6: Autorisation d'absence pour formation professionnelle | N6: Création Modification | Q6: Personnel civil payé à l'acte ou à la tâche | R6: P0054 | S6: N | T6: Particulier | U6: Exclu | V6: 40725
A7: 17.10.00 | B7: A | C7: 43152.5 | D7: D0007 | E7: Congés/Absence | F7: S0046 | G7: Autorisations d'absence | H7: E0427 | I7: Autorisation d'absence pour formation professionnelle | J7: Type de congé/absence saisi égal 'Autorisation d'absence pour formation professionnelle' | K7: A_COA_TYCOAB [Saisi] = 'CA001' | L7: T1088 | M7: Autorisation d'absence pour formation professionnelle | N7: Création Modification | Q7: Volontaire de service civique outre-mer | R7: P0179 | S7: N | T7: Particulier | U7: Exclu | V7: 40725
A8: 22.00.00 | B8: A | C8: 44714.667 | D8: D0007 | E8: Congés/Absence | F8: S0046 | G8: Autorisations d'absence | H8: E0427 | I8: Autorisation d'absence pour formation professionnelle | J8: Type de congé/absence saisi égal 'Autorisation d'absence pour formation professionnelle' | K8: A_COA_TYCOAB [Saisi] = 'CA001' | L8: T1088 | M8: Autorisation d'absence pour formation professionnelle | N8: Création Modification | Q8: Contractuel recruté sur contrat de mission scientifique | R8: P0266 | S8: N | T8: Particulier | U8: Passant | V8: 44507 | X8: ADI_I_202 ET ADI_I_200 ET ABS_C_010 ET ABS_C_003 ET ABS_C_004 ET ABS_C_009 ET ABS_C_019 ET ABS_C_020 ET ABS_C_026 ET ABS_C_002 ET ABS_C_005 ET ABS_C_006 ET ABS_C_007 ET ABS_C_008 | Y8: ADI_I_202 | Z8: =VLOOKUP(Y8,'Axe 2 Règles de gestion'!$D$2:$F$354,3, FALSE) -> L'agent bénéficie des dispositions applicables aux agents contractuels pour la formation professionnelle, sauf dispositions particulières. | AA8: ADI_I_200 | AB8: =VLOOKUP(AA8,'Axe 2 Règles de gestion'!$D$2:$F$354,3, FALSE) -> L'agent lié par un contrat de mission scientifique bénéficie de façon prioritaire de 20 jours de décharge de service dédiés à des actions de formation. | BG8: ABS_C_010 | BH8: =VLOOKUP(BG8,'Axe 2 Règles de gestion'!$D$2:$F$354,3, FALSE) -> L'agent doit être en activité. | BI8: ABS_C_003 | BJ8: =VLOOKUP(BI8,'Axe 2 Règles de gestion'!$D$2:$F$354,3, FALSE) -> La date de début du congé/absence doit être antérieure ou égale à la date de fin réelle du congé/absence. | BK8: ABS_C_004 | BL8: =VLOOKUP(BK8,'Axe 2 Règles de gestion'!$D$2:$F$354,3, FALSE) -> La date de début du congé/absence doit être antérieure ou égale à la date de fin prévisionnelle du congé/absence. | BM8: ABS_C_009 | BN8: =VLOOKUP(BM8,'Axe 2 Règles de gestion'!$D$2:$F$354,3, FALSE) -> La date de fin réelle ou la date de fin prévisionnelle du congé/absence doit être saisie. | BO8: ABS_C_019 | BP8: =VLOOKUP(BO8,'Axe 2 Règles de gestion'!$D$2:$F$354,3, FALSE) -> Si l'absence ne commence pas par une demi-journée et si l'absence précédente ne finit pas par une demi journée, la date de début de l'absence saisie est postérieure à la date de fin réelle de l'absence précédente. | BQ8: ABS_C_020 | BR8: =VLOOKUP(BQ8,'Axe 2 Règles de gestion'!$D$2:$F$354,3, FALSE) -> Si l'absence ne commence pas par une demi-journée et si l'absence précédente ne finit pas par une demi journée, la date de début de l'absence saisie est postérieure à la date de fin prévisionnelle de l'absence précédente. | BS8: ABS_C_026 | BT8: =VLOOKUP(BS8,'Axe 2 Règles de gestion'!$D$2:$F$354,3, FALSE) -> Dans le cas d'un congé autre que CLM, CLD, CGM et CITIS, l'indicateur de requalification doit être à non et les impacts spécifiques à la requalification ne doivent pas être mobilisés ou l'impact rémunération est vide. | BU8: ABS_C_002 | BV8: =VLOOKUP(BU8,'Axe 2 Règles de gestion'!$D$2:$F$354,3, FALSE) -> La date de début du congé/absence doit être postérieure ou égale à la date de début du lien juridique. | BW8: ABS_C_005 | BX8: =VLOOKUP(BW8,'Axe 2 Règles de gestion'!$D$2:$F$354,3, FALSE) -> La date de fin réelle du congé/absence doit être antérieure ou égale à la date limite de fin réelle ou prévisionnelle du lien juridique. | BY8: ABS_C_006 | BZ8: =VLOOKUP(BY8,'Axe 2 Règles de gestion'!$D$2:$F$354,3, FALSE) -> La date de fin prévisionnelle du congé/absence doit être antérieure ou égale à la date limite de fin réelle ou prévisionnelle du lien juridique. | CA8: ABS_C_007 | CB8: =VLOOKUP(CA8,'Axe 2 Règles de gestion'!$D$2:$F$354,3, FALSE) -> La date de fin réelle du congé/absence doit être antérieure à la date limite de départ à la retraite. | CC8: ABS_C_008 | CD8: =VLOOKUP(CC8,'Axe 2 Règles de gestion'!$D$2:$F$354,3, FALSE) -> La date de fin prévisionnelle du congé/absence doit être antérieure à la date limite de départ à la retraite.
A9: 22.00.00 | B9: A | C9: 44714.668 | D9: D0007 | E9: Congés/Absence | F9: S0046 | G9: Autorisations d'absence | H9: E0427 | I9: Autorisation d'absence pour formation professionnelle | J9: Type de congé/absence saisi égal 'Autorisation d'absence pour formation professionnelle' | K9: A_COA_TYCOAB [Saisi] = 'CA001' | L9: T1088 | M9: Autorisation d'absence pour formation professionnelle | N9: Création Modification | Q9: Contractuel recruté sur contrat post doctoral | R9: P0267 | S9: N | T9: Particulier | U9: Passant | V9: 44507 | X9: ADI_I_203 ET ADI_I_201 ET ABS_C_010 ET ABS_C_003 ET ABS_C_004 ET ABS_C_009 ET ABS_C_019 ET ABS_C_020 ET ABS_C_026 ET ABS_C_002 ET ABS_C_005 ET ABS_C_006 ET ABS_C_007 ET ABS_C_008 | Y9: ADI_I_203 | Z9: =VLOOKUP(Y9,'Axe 2 Règles de gestion'!$D$2:$F$354,3, FALSE) -> L'agent bénéficie des dispositions applicables aux agents contractuels pour la formation professionnelle, sauf dispositions particulières. | AA9: ADI_I_201 | AB9: =VLOOKUP(AA9,'Axe 2 Règles de gestion'!$D$2:$F$354,3, FALSE) -> L'agent lié par un contrat post doctoral bénéficie de façon prioritaire de 20 jours de décharge de service dédiés à des actions de formation. | BG9: ABS_C_010 | BH9: =VLOOKUP(BG9,'Axe 2 Règles de gestion'!$D$2:$F$354,3, FALSE) -> L'agent doit être en activité. | BI9: ABS_C_003 | BJ9: =VLOOKUP(BI9,'Axe 2 Règles de gestion'!$D$2:$F$354,3, FALSE) -> La date de début du congé/absence doit être antérieure ou égale à la date de fin réelle du congé/absence. | BK9: ABS_C_004 | BL9: =VLOOKUP(BK9,'Axe 2 Règles de gestion'!$D$2:$F$354,3, FALSE) -> La date de début du congé/absence doit être antérieure ou égale à la date de fin prévisionnelle du congé/absence. | BM9: ABS_C_009 | BN9: =VLOOKUP(BM9,'Axe 2 Règles de gestion'!$D$2:$F$354,3, FALSE) -> La date de fin réelle ou la date de fin prévisionnelle du congé/absence doit être saisie. | BO9: ABS_C_019 | BP9: =VLOOKUP(BO9,'Axe 2 Règles de gestion'!$D$2:$F$354,3, FALSE) -> Si l'absence ne commence pas par une demi-journée et si l'absence précédente ne finit pas par une demi journée, la date de début de l'absence saisie est postérieure à la date de fin réelle de l'absence précédente. | BQ9: ABS_C_020 | BR9: =VLOOKUP(BQ9,'Axe 2 Règles de gestion'!$D$2:$F$354,3, FALSE) -> Si l'absence ne commence pas par une demi-journée et si l'absence précédente ne finit pas par une demi journée, la date de début de l'absence saisie est postérieure à la date de fin prévisionnelle de l'absence précédente. | BS9: ABS_C_026 | BT9: =VLOOKUP(BS9,'Axe 2 Règles de gestion'!$D$2:$F$354,3, FALSE) -> Dans le cas d'un congé autre que CLM, CLD, CGM et CITIS, l'indicateur de requalification doit être à non et les impacts spécifiques à la requalification ne doivent pas être mobilisés ou l'impact rémunération est vide. | BU9: ABS_C_002 | BV9: =VLOOKUP(BU9,'Axe 2 Règles de gestion'!$D$2:$F$354,3, FALSE) -> La date de début du congé/absence doit être postérieure ou égale à la date de début du lien juridique. | BW9: ABS_C_005 | BX9: =VLOOKUP(BW9,'Axe 2 Règles de gestion'!$D$2:$F$354,3, FALSE) -> La date de fin réelle du congé/absence doit être antérieure ou égale à la date limite de fin réelle ou prévisionnelle du lien juridique. | BY9: ABS_C_006 | BZ9: =VLOOKUP(BY9,'Axe 2 Règles de gestion'!$D$2:$F$354,3, FALSE) -> La date de fin prévisionnelle du congé/absence doit être antérieure ou égale à la date limite de fin réelle ou prévisionnelle du lien juridique. | CA9: ABS_C_007 | CB9: =VLOOKUP(CA9,'Axe 2 Règles de gestion'!$D$2:$F$354,3, FALSE) -> La date de fin réelle du congé/absence doit être antérieure à la date limite de départ à la retraite. | CC9: ABS_C_008 | CD9: =VLOOKUP(CC9,'Axe 2 Règles de gestion'!$D$2:$F$354,3, FALSE) -> La date de fin prévisionnelle du congé/absence doit être antérieure à la date limite de départ à la retraite.
A10: 17.10.00 | B10: A | C10: 43152.5 | D10: D0007 | E10: Congés/Absence | F10: S0046 | G10: Autorisations d'absence | H10: E0428 | I10: Autorisations d'absences diverses | J10: Type de congé/absence saisi égal 'Autorisations d'absences diverses' | K10: A_COA_TYCOAB [Saisi] = 'CA009' | L10: T1089 | M10: Autorisations d'absences diverses | N10: Création Modification | Q10: Titulaire ou magistrat | R10: P0001 | S10: T | T10: Général | U10: Passant | V10: 40725 | X10: ABS_C_010 ET ABS_C_001 ET ABS_C_003 ET ABS_C_004 ET ABS_C_007 ET ABS_C_008 ET ABS_C_009 ET ABS_C_019 ET ABS_C_020 ET ABS_C_026 | BG10: ABS_C_010 | BH10: =VLOOKUP(BG10,'Axe 2 Règles de gestion'!$D$2:$F$354,3, FALSE) -> L'agent doit être en activité. | BI10: ABS_C_001 | BJ10: =VLOOKUP(BI10,'Axe 2 Règles de gestion'!$D$2:$F$354,3, FALSE) -> La date de début du congé/absence doit être postérieure ou égale à la date de recrutement dans la FPE ou dans la carrière militaire. | BK10: ABS_C_003 | BL10: =VLOOKUP(BK10,'Axe 2 Règles de gestion'!$D$2:$F$354,3, FALSE) -> La date de début du congé/absence doit être antérieure ou égale à la date de fin réelle du congé/absence. | BM10: ABS_C_004 | BN10: =VLOOKUP(BM10,'Axe 2 Règles de gestion'!$D$2:$F$354,3, FALSE) -> La date de début du congé/absence doit être antérieure ou égale à la date de fin prévisionnelle du congé/absence. | BO10: ABS_C_007 | BP10: =VLOOKUP(BO10,'Axe 2 Règles de gestion'!$D$2:$F$354,3, FALSE) -> La date de fin réelle du congé/absence doit être antérieure à la date limite de départ à la retraite. | BQ10: ABS_C_008 | BR10: =VLOOKUP(BQ10,'Axe 2 Règles de gestion'!$D$2:$F$354,3, FALSE) -> La date de fin prévisionnelle du congé/absence doit être antérieure à la date limite de départ à la retraite. | BS10: ABS_C_009 | BT10: =VLOOKUP(BS10,'Axe 2 Règles de gestion'!$D$2:$F$354,3, FALSE) -> La date de fin réelle ou la date de fin prévisionnelle du congé/absence doit être saisie. | BU10: ABS_C_019 | BV10: =VLOOKUP(BU10,'Axe 2 Règles de gestion'!$D$2:$F$354,3, FALSE) -> Si l'absence ne commence pas par une demi-journée et si l'absence précédente ne finit pas par une demi journée, la date de début de l'absence saisie est postérieure à la date de fin réelle de l'absence précédente. | BW10: ABS_C_020 | BX10: =VLOOKUP(BW10,'Axe 2 Règles de gestion'!$D$2:$F$354,3, FALSE) -> Si l'absence ne commence pas par une demi-journée et si l'absence précédente ne finit pas par une demi journée, la date de début de l'absence saisie est postérieure à la date de fin prévisionnelle de l'absence précédente. | BY10: ABS_C_026 | BZ10: =VLOOKUP(BY10,'Axe 2 Règles de gestion'!$D$2:$F$354,3, FALSE) -> Dans le cas d'un congé autre que CLM, CLD, CGM et CITIS, l'indicateur de requalification doit être à non et les impacts spécifiques à la requalification ne doivent pas être mobilisés ou l'impact rémunération est vide.
A11: 17.10.00 | B11: A | C11: 43152.5 | D11: D0007 | E11: Congés/Absence | F11: S0046 | G11: Autorisations d'absence | H11: E0428 | I11: Autorisations d'absences diverses | J11: Type de congé/absence saisi égal 'Autorisations d'absences diverses' | K11: A_COA_TYCOAB [Saisi] = 'CA009' | L11: T1089 | M11: Autorisations d'absences diverses | N11: Création Modification | Q11: Contractuel | R11: P0003 | S11: N | T11: Général | U11: Passant | V11: 40725 | X11: ABS_C_010 ET ABS_C_003 ET ABS_C_004 ET ABS_C_009 ET ABS_C_019 ET ABS_C_020 ET ABS_C_026 ET ABS_C_002 ET ABS_C_005 ET ABS_C_006 ET ABS_C_007 ET ABS_C_008 | BG11: ABS_C_010 | BH11: =VLOOKUP(BG11,'Axe 2 Règles de gestion'!$D$2:$F$354,3, FALSE) -> L'agent doit être en activité. | BI11: ABS_C_003 | BJ11: =VLOOKUP(BI11,'Axe 2 Règles de gestion'!$D$2:$F$354,3, FALSE) -> La date de début du congé/absence doit être antérieure ou égale à la date de fin réelle du congé/absence. | BK11: ABS_C_004 | BL11: =VLOOKUP(BK11,'Axe 2 Règles de gestion'!$D$2:$F$354,3, FALSE) -> La date de début du congé/absence doit être antérieure ou égale à la date de fin prévisionnelle du congé/absence. | BM11: ABS_C_009 | BN11: =VLOOKUP(BM11,'Axe 2 Règles de gestion'!$D$2:$F$354,3, FALSE) -> La date de fin réelle ou la date de fin prévisionnelle du congé/absence doit être saisie. | BO11: ABS_C_019 | BP11: =VLOOKUP(BO11,'Axe 2 Règles de gestion'!$D$2:$F$354,3, FALSE) -> Si l'absence ne commence pas par une demi-journée et si l'absence précédente ne finit pas par une demi journée, la date de début de l'absence saisie est postérieure à la date de fin réelle de l'absence précédente. | BQ11: ABS_C_020 | BR11: =VLOOKUP(BQ11,'Axe 2 Règles de gestion'!$D$2:$F$354,3, FALSE) -> Si l'absence ne commence pas par une demi-journée et si l'absence précédente ne finit pas par une demi journée, la date de début de l'absence saisie est postérieure à la date de fin prévisionnelle de l'absence précédente. | BS11: ABS_C_026 | BT11: =VLOOKUP(BS11,'Axe 2 Règles de gestion'!$D$2:$F$354,3, FALSE) -> Dans le cas d'un congé autre que CLM, CLD, CGM et CITIS, l'indicateur de requalification doit être à non et les impacts spécifiques à la requalification ne doivent pas être mobilisés ou l'impact rémunération est vide. | BU11: ABS_C_002 | BV11: =VLOOKUP(BU11,'Axe 2 Règles de gestion'!$D$2:$F$354,3, FALSE) -> La date de début du congé/absence doit être postérieure ou égale à la date de début du lien juridique. | BW11: ABS_C_005 | BX11: =VLOOKUP(BW11,'Axe 2 Règles de gestion'!$D$2:$F$354,3, FALSE) -> La date de fin réelle du congé/absence doit être antérieure ou égale à la date limite de fin réelle ou prévisionnelle du lien juridique. | BY11: ABS_C_006 | BZ11: =VLOOKUP(BY11,'Axe 2 Règles de gestion'!$D$2:$F$354,3, FALSE) -> La date de fin prévisionnelle du congé/absence doit être antérieure ou égale à la date limite de fin réelle ou prévisionnelle du lien juridique. | CA11: ABS_C_007 | CB11: =VLOOKUP(CA11,'Axe 2 Règles de gestion'!$D$2:$F$354,3, FALSE) -> La date de fin réelle du congé/absence doit être antérieure à la date limite de départ à la retraite. | CC11: ABS_C_008 | CD11: =VLOOKUP(CC11,'Axe 2 Règles de gestion'!$D$2:$F$354,3, FALSE) -> La date de fin prévisionnelle du congé/absence doit être antérieure à la date limite de départ à la retraite.
A12: 17.10.00 | B12: A | C12: 43152.5 | D12: D0007 | E12: Congés/Absence | F12: S0046 | G12: Autorisations d'absence | H12: E0428 | I12: Autorisations d'absences diverses | J12: Type de congé/absence saisi égal 'Autorisations d'absences diverses' | K12: A_COA_TYCOAB [Saisi] = 'CA009' | L12: T1089 | M12: Autorisations d'absences diverses | N12: Création Modification | Q12: Stagiaire ou auditeur ou élève | R12: P0004 | S12: S | T12: Général | U12: Passant | V12: 40725 | X12: ABS_C_010 ET ABS_C_001 ET ABS_C_003 ET ABS_C_004 ET ABS_C_007 ET ABS_C_008 ET ABS_C_009 ET ABS_C_019 ET ABS_C_020 ET ABS_C_026 | BG12: ABS_C_010 | BH12: =VLOOKUP(BG12,'Axe 2 Règles de gestion'!$D$2:$F$354,3, FALSE) -> L'agent doit être en activité. | BI12: ABS_C_001 | BJ12: =VLOOKUP(BI12,'Axe 2 Règles de gestion'!$D$2:$F$354,3, FALSE) -> La date de début du congé/absence doit être postérieure ou égale à la date de recrutement dans la FPE ou dans la carrière militaire. | BK12: ABS_C_003 | BL12: =VLOOKUP(BK12,'Axe 2 Règles de gestion'!$D$2:$F$354,3, FALSE) -> La date de début du congé/absence doit être antérieure ou égale à la date de fin réelle du congé/absence. | BM12: ABS_C_004 | BN12: =VLOOKUP(BM12,'Axe 2 Règles de gestion'!$D$2:$F$354,3, FALSE) -> La date de début du congé/absence doit être antérieure ou égale à la date de fin prévisionnelle du congé/absence. | BO12: ABS_C_007 | BP12: =VLOOKUP(BO12,'Axe 2 Règles de gestion'!$D$2:$F$354,3, FALSE) -> La date de fin réelle du congé/absence doit être antérieure à la date limite de départ à la retraite. | BQ12: ABS_C_008 | BR12: =VLOOKUP(BQ12,'Axe 2 Règles de gestion'!$D$2:$F$354,3, FALSE) -> La date de fin prévisionnelle du congé/absence doit être antérieure à la date limite de départ à la retraite. | BS12: ABS_C_009 | BT12: =VLOOKUP(BS12,'Axe 2 Règles de gestion'!$D$2:$F$354,3, FALSE) -> La date de fin réelle ou la date de fin prévisionnelle du congé/absence doit être saisie. | BU12: ABS_C_019 | BV12: =VLOOKUP(BU12,'Axe 2 Règles de gestion'!$D$2:$F$354,3, FALSE) -> Si l'absence ne commence pas par une demi-journée et si l'absence précédente ne finit pas par une demi journée, la date de début de l'absence saisie est postérieure à la date de fin réelle de l'absence précédente. | BW12: ABS_C_020 | BX12: =VLOOKUP(BW12,'Axe 2 Règles de gestion'!$D$2:$F$354,3, FALSE) -> Si l'absence ne commence pas par une demi-journée et si l'absence précédente ne finit pas par une demi journée, la date de début de l'absence saisie est postérieure à la date de fin prévisionnelle de l'absence précédente. | BY12: ABS_C_026 | BZ12: =VLOOKUP(BY12,'Axe 2 Règles de gestion'!$D$2:$F$354,3, FALSE) -> Dans le cas d'un congé autre que CLM, CLD, CGM et CITIS, l'indicateur de requalification doit être à non et les impacts spécifiques à la requalification ne doivent pas être mobilisés ou l'impact rémunération est vide.
A13: 17.10.00 | B13: A | C13: 43189.5 | D13: D0007 | E13: Congés/Absence | F13: S0046 | G13: Autorisations d'absence | H13: E0428 | I13: Autorisations d'absences diverses | J13: Type de congé/absence saisi égal 'Autorisations d'absences diverses' | K13: A_COA_TYCOAB [Saisi] = 'CA009' | L13: T1089 | M13: Autorisations d'absences diverses | N13: Création Modification | Q13: Ouvrier d'état | R13: P0005 | S13: O | T13: Général | U13: Passant | V13: 40725 | X13: ABS_C_010 ET ABS_C_003 ET ABS_C_004 ET ABS_C_009 ET ABS_C_019 ET ABS_C_020 ET ABS_C_026 ET ABS_C_002 ET ABS_C_005 ET ABS_C_006 ET ABS_C_007 ET ABS_C_008 | BG13: ABS_C_010 | BH13: =VLOOKUP(BG13,'Axe 2 Règles de gestion'!$D$2:$F$354,3, FALSE) -> L'agent doit être en activité. | BI13: ABS_C_003 | BJ13: =VLOOKUP(BI13,'Axe 2 Règles de gestion'!$D$2:$F$354,3, FALSE) -> La date de début du congé/absence doit être antérieure ou égale à la date de fin réelle du congé/absence. | BK13: ABS_C_004 | BL13: =VLOOKUP(BK13,'Axe 2 Règles de gestion'!$D$2:$F$354,3, FALSE) -> La date de début du congé/absence doit être antérieure ou égale à la date de fin prévisionnelle du congé/absence. | BM13: ABS_C_009 | BN13: =VLOOKUP(BM13,'Axe 2 Règles de gestion'!$D$2:$F$354,3, FALSE) -> La date de fin réelle ou la date de fin prévisionnelle du congé/absence doit être saisie. | BO13: ABS_C_019 | BP13: =VLOOKUP(BO13,'Axe 2 Règles de gestion'!$D$2:$F$354,3, FALSE) -> Si l'absence ne commence pas par une demi-journée et si l'absence précédente ne finit pas par une demi journée, la date de début de l'absence saisie est postérieure à la date de fin réelle de l'absence précédente. | BQ13: ABS_C_020 | BR13: =VLOOKUP(BQ13,'Axe 2 Règles de gestion'!$D$2:$F$354,3, FALSE) -> Si l'absence ne commence pas par une demi-journée et si l'absence précédente ne finit pas par une demi journée, la date de début de l'absence saisie est postérieure à la date de fin prévisionnelle de l'absence précédente. | BS13: ABS_C_026 | BT13: =VLOOKUP(BS13,'Axe 2 Règles de gestion'!$D$2:$F$354,3, FALSE) -> Dans le cas d'un congé autre que CLM, CLD, CGM et CITIS, l'indicateur de requalification doit être à non et les impacts spécifiques à la requalification ne doivent pas être mobilisés ou l'impact rémunération est vide. | BU13: ABS_C_002 | BV13: =VLOOKUP(BU13,'Axe 2 Règles de gestion'!$D$2:$F$354,3, FALSE) -> La date de début du congé/absence doit être postérieure ou égale à la date de début du lien juridique. | BW13: ABS_C_005 | BX13: =VLOOKUP(BW13,'Axe 2 Règles de gestion'!$D$2:$F$354,3, FALSE) -> La date de fin réelle du congé/absence doit être antérieure ou égale à la date limite de fin réelle ou prévisionnelle du lien juridique. | BY13: ABS_C_006 | BZ13: =VLOOKUP(BY13,'Axe 2 Règles de gestion'!$D$2:$F$354,3, FALSE) -> La date de fin prévisionnelle du congé/absence doit être antérieure ou égale à la date limite de fin réelle ou prévisionnelle du lien juridique. | CA13: ABS_C_007 | CB13: =VLOOKUP(CA13,'Axe 2 Règles de gestion'!$D$2:$F$354,3, FALSE) -> La date de fin réelle du congé/absence doit être antérieure à la date limite de départ à la retraite. | CC13: ABS_C_008 | CD13: =VLOOKUP(CC13,'Axe 2 Règles de gestion'!$D$2:$F$354,3, FALSE) -> La date de fin prévisionnelle du congé/absence doit être antérieure à la date limite de départ à la retraite.
A14: 17.10.00 | B14: A | C14: 43152.5 | D14: D0007 | E14: Congés/Absence | F14: S0046 | G14: Autorisations d'absence | H14: E0428 | I14: Autorisations d'absences diverses | J14: Type de congé/absence saisi égal 'Autorisations d'absences diverses' | K14: A_COA_TYCOAB [Saisi] = 'CA009' | L14: T1089 | M14: Autorisations d'absences diverses | N14: Création Modification | Q14: Personnel civil payé à l'acte ou à la tâche | R14: P0054 | S14: N | T14: Particulier | U14: Exclu | V14: 40725
A15: 17.10.00 | B15: A | C15: 43152.5 | D15: D0007 | E15: Congés/Absence | F15: S0046 | G15: Autorisations d'absence | H15: E0428 | I15: Autorisations d'absences diverses | J15: Type de congé/absence saisi égal 'Autorisations d'absences diverses' | K15: A_COA_TYCOAB [Saisi] = 'CA009' | L15: T1089 | M15: Autorisations d'absences diverses | N15: Création Modification | Q15: Volontaire de service civique outre-mer | R15: P0179 | S15: N | T15: Particulier | U15: Exclu | V15: 40725
A16: 22.10.00 | B16: M | C16: 44917.607 | D16: D0007 | E16: Congés/Absence | F16: S0046 | G16: Autorisations d'absence | H16: E0429 | I16: Autorisations d'absence avec rémunération pour mandat électif local | J16: Type de congé/absence saisi égal 'Autorisations d'absence avec rémunération pour mandat électif local' | K16: A_COA_TYCOAB [Saisi] = 'CA005' | L16: T1090 | M16: Autorisations d'absence avec rémunération pour mandat électif local | N16: Création Modification | Q16: Titulaire ou magistrat | R16: P0001 | S16: T | T16: Général | U16: Passant | V16: 40725 | W16: 43827 | X16: ABS_C_010 ET ABS_C_001 ET ABS_C_003 ET ABS_C_004 ET ABS_C_007 ET ABS_C_008 ET ABS_C_009 ET ABS_C_019 ET ABS_C_020 ET ABS_C_026 | BG16: ABS_C_010 | BH16: =VLOOKUP(BG16,'Axe 2 Règles de gestion'!$D$2:$F$354,3, FALSE) -> L'agent doit être en activité. | BI16: ABS_C_001 | BJ16: =VLOOKUP(BI16,'Axe 2 Règles de gestion'!$D$2:$F$354,3, FALSE) -> La date de début du congé/absence doit être postérieure ou égale à la date de recrutement dans la FPE ou dans la carrière militaire. | BK16: ABS_C_003 | BL16: =VLOOKUP(BK16,'Axe 2 Règles de gestion'!$D$2:$F$354,3, FALSE) -> La date de début du congé/absence doit être antérieure ou égale à la date de fin réelle du congé/absence. | BM16: ABS_C_004 | BN16: =VLOOKUP(BM16,'Axe 2 Règles de gestion'!$D$2:$F$354,3, FALSE) -> La date de début du congé/absence doit être antérieure ou égale à la date de fin prévisionnelle du congé/absence. | BO16: ABS_C_007 | BP16: =VLOOKUP(BO16,'Axe 2 Règles de gestion'!$D$2:$F$354,3, FALSE) -> La date de fin réelle du congé/absence doit être antérieure à la date limite de départ à la retraite. | BQ16: ABS_C_008 | BR16: =VLOOKUP(BQ16,'Axe 2 Règles de gestion'!$D$2:$F$354,3, FALSE) -> La date de fin prévisionnelle du congé/absence doit être antérieure à la date limite de départ à la retraite. | BS16: ABS_C_009 | BT16: =VLOOKUP(BS16,'Axe 2 Règles de gestion'!$D$2:$F$354,3, FALSE) -> La date de fin réelle ou la date de fin prévisionnelle du congé/absence doit être saisie. | BU16: ABS_C_019 | BV16: =VLOOKUP(BU16,'Axe 2 Règles de gestion'!$D$2:$F$354,3, FALSE) -> Si l'absence ne commence pas par une demi-journée et si l'absence précédente ne finit pas par une demi journée, la date de début de l'absence saisie est postérieure à la date de fin réelle de l'absence précédente. | BW16: ABS_C_020 | BX16: =VLOOKUP(BW16,'Axe 2 Règles de gestion'!$D$2:$F$354,3, FALSE) -> Si l'absence ne commence pas par une demi-journée et si l'absence précédente ne finit pas par une demi journée, la date de début de l'absence saisie est postérieure à la date de fin prévisionnelle de l'absence précédente. | BY16: ABS_C_026 | BZ16: =VLOOKUP(BY16,'Axe 2 Règles de gestion'!$D$2:$F$354,3, FALSE) -> Dans le cas d'un congé autre que CLM, CLD, CGM et CITIS, l'indicateur de requalification doit être à non et les impacts spécifiques à la requalification ne doivent pas être mobilisés ou l'impact rémunération est vide.
A17: 22.10.00 | B17: A | C17: 44917.607 | D17: D0007 | E17: Congés/Absence | F17: S0046 | G17: Autorisations d'absence | H17: E0429 | I17: Autorisations d'absence avec rémunération pour mandat électif local | J17: Type de congé/absence saisi égal 'Autorisations d'absence avec rémunération pour mandat électif local' | K17: A_COA_TYCOAB [Saisi] = 'CA005' | L17: T1090 | M17: Autorisations d'absence avec rémunération pour mandat électif local | N17: Création Modification | Q17: Titulaire ou magistrat | R17: P0001 | S17: T | T17: Général | U17: Passant | V17: 43828 | X17: ADI_I_116 ET ADI_I_117 ET ADI_I_118 ET ABS_C_010 ET ABS_C_001 ET ABS_C_003 ET ABS_C_004 ET ABS_C_007 ET ABS_C_008 ET ABS_C_009 ET ABS_C_019 ET ABS_C_020 ET ABS_C_026 | Y17: ADI_I_116 | Z17: =VLOOKUP(Y17,'Axe 2 Règles de gestion'!$D$2:$F$354,3, FALSE) -> L'agent doit être élu d'un conseil municipal, d'un conseil départemental ou d'un conseil régional. | AA17: ADI_I_117 | AB17: =VLOOKUP(AA17,'Axe 2 Règles de gestion'!$D$2:$F$354,3, FALSE) -> Des autorisations d'absence sont accordées à l'agent pour se rendre et participer aux séances plénières, aux réunions des commissions dont il est membre et aux réunions et assemblées des organismes où il représente la collectivité. | AC17: ADI_I_118 | AD17: =VLOOKUP(AC17,'Axe 2 Règles de gestion'!$D$2:$F$354,3, FALSE) -> L'agent doit informer l'administration de la date de la séance ou de la réunion dès qu'il en a connaissance. | BG17: ABS_C_010 | BH17: =VLOOKUP(BG17,'Axe 2 Règles de gestion'!$D$2:$F$354,3, FALSE) -> L'agent doit être en activité. | BI17: ABS_C_001 | BJ17: =VLOOKUP(BI17,'Axe 2 Règles de gestion'!$D$2:$F$354,3, FALSE) -> La date de début du congé/absence doit être postérieure ou égale à la date de recrutement dans la FPE ou dans la carrière militaire. | BK17: ABS_C_003 | BL17: =VLOOKUP(BK17,'Axe 2 Règles de gestion'!$D$2:$F$354,3, FALSE) -> La date de début du congé/absence doit être antérieure ou égale à la date de fin réelle du congé/absence. | BM17: ABS_C_004 | BN17: =VLOOKUP(BM17,'Axe 2 Règles de gestion'!$D$2:$F$354,3, FALSE) -> La date de début du congé/absence doit être antérieure ou égale à la date de fin prévisionnelle du congé/absence. | BO17: ABS_C_007 | BP17: =VLOOKUP(BO17,'Axe 2 Règles de gestion'!$D$2:$F$354,3, FALSE) -> La date de fin réelle du congé/absence doit être antérieure à la date limite de départ à la retraite. | BQ17: ABS_C_008 | BR17: =VLOOKUP(BQ17,'Axe 2 Règles de gestion'!$D$2:$F$354,3, FALSE) -> La date de fin prévisionnelle du congé/absence doit être antérieure à la date limite de départ à la retraite. | BS17: ABS_C_009 | BT17: =VLOOKUP(BS17,'Axe 2 Règles de gestion'!$D$2:$F$354,3, FALSE) -> La date de fin réelle ou la date de fin prévisionnelle du congé/absence doit être saisie. | BU17: ABS_C_019 | BV17: =VLOOKUP(BU17,'Axe 2 Règles de gestion'!$D$2:$F$354,3, FALSE) -> Si l'absence ne commence pas par une demi-journée et si l'absence précédente ne finit pas par une demi journée, la date de début de l'absence saisie est postérieure à la date de fin réelle de l'absence précédente. | BW17: ABS_C_020 | BX17: =VLOOKUP(BW17,'Axe 2 Règles de gestion'!$D$2:$F$354,3, FALSE) -> Si l'absence ne commence pas par une demi-journée et si l'absence précédente ne finit pas par une demi journée, la date de début de l'absence saisie est postérieure à la date de fin prévisionnelle de l'absence précédente. | BY17: ABS_C_026 | BZ17: =VLOOKUP(BY17,'Axe 2 Règles de gestion'!$D$2:$F$354,3, FALSE) -> Dans le cas d'un congé autre que CLM, CLD, CGM et CITIS, l'indicateur de requalification doit être à non et les impacts spécifiques à la requalification ne doivent pas être mobilisés ou l'impact rémunération est vide.
A18: 22.10.00 | B18: M | C18: 44917.603 | D18: D0007 | E18: Congés/Absence | F18: S0046 | G18: Autorisations d'absence | H18: E0429 | I18: Autorisations d'absence avec rémunération pour mandat électif local | J18: Type de congé/absence saisi égal 'Autorisations d'absence avec rémunération pour mandat électif local' | K18: A_COA_TYCOAB [Saisi] = 'CA005' | L18: T1090 | M18: Autorisations d'absence avec rémunération pour mandat électif local | N18: Création Modification | Q18: Contractuel | R18: P0003 | S18: N | T18: Général | U18: Passant | V18: 40725 | W18: 43827 | X18: ABS_C_010 ET ABS_C_003 ET ABS_C_004 ET ABS_C_009 ET ABS_C_019 ET ABS_C_020 ET ABS_C_026 ET ABS_C_002 ET ABS_C_005 ET ABS_C_006 ET ABS_C_007 ET ABS_C_008 | BG18: ABS_C_010 | BH18: =VLOOKUP(BG18,'Axe 2 Règles de gestion'!$D$2:$F$354,3, FALSE) -> L'agent doit être en activité. | BI18: ABS_C_003 | BJ18: =VLOOKUP(BI18,'Axe 2 Règles de gestion'!$D$2:$F$354,3, FALSE) -> La date de début du congé/absence doit être antérieure ou égale à la date de fin réelle du congé/absence. | BK18: ABS_C_004 | BL18: =VLOOKUP(BK18,'Axe 2 Règles de gestion'!$D$2:$F$354,3, FALSE) -> La date de début du congé/absence doit être antérieure ou égale à la date de fin prévisionnelle du congé/absence. | BM18: ABS_C_009 | BN18: =VLOOKUP(BM18,'Axe 2 Règles de gestion'!$D$2:$F$354,3, FALSE) -> La date de fin réelle ou la date de fin prévisionnelle du congé/absence doit être saisie. | BO18: ABS_C_019 | BP18: =VLOOKUP(BO18,'Axe 2 Règles de gestion'!$D$2:$F$354,3, FALSE) -> Si l'absence ne commence pas par une demi-journée et si l'absence précédente ne finit pas par une demi journée, la date de début de l'absence saisie est postérieure à la date de fin réelle de l'absence précédente. | BQ18: ABS_C_020 | BR18: =VLOOKUP(BQ18,'Axe 2 Règles de gestion'!$D$2:$F$354,3, FALSE) -> Si l'absence ne commence pas par une demi-journée et si l'absence précédente ne finit pas par une demi journée, la date de début de l'absence saisie est postérieure à la date de fin prévisionnelle de l'absence précédente. | BS18: ABS_C_026 | BT18: =VLOOKUP(BS18,'Axe 2 Règles de gestion'!$D$2:$F$354,3, FALSE) -> Dans le cas d'un congé autre que CLM, CLD, CGM et CITIS, l'indicateur de requalification doit être à non et les impacts spécifiques à la requalification ne doivent pas être mobilisés ou l'impact rémunération est vide. | BU18: ABS_C_002 | BV18: =VLOOKUP(BU18,'Axe 2 Règles de gestion'!$D$2:$F$354,3, FALSE) -> La date de début du congé/absence doit être postérieure ou égale à la date de début du lien juridique. | BW18: ABS_C_005 | BX18: =VLOOKUP(BW18,'Axe 2 Règles de gestion'!$D$2:$F$354,3, FALSE) -> La date de fin réelle du congé/absence doit être antérieure ou égale à la date limite de fin réelle ou prévisionnelle du lien juridique. | BY18: ABS_C_006 | BZ18: =VLOOKUP(BY18,'Axe 2 Règles de gestion'!$D$2:$F$354,3, FALSE) -> La date de fin prévisionnelle du congé/absence doit être antérieure ou égale à la date limite de fin réelle ou prévisionnelle du lien juridique. | CA18: ABS_C_007 | CB18: =VLOOKUP(CA18,'Axe 2 Règles de gestion'!$D$2:$F$354,3, FALSE) -> La date de fin réelle du congé/absence doit être antérieure à la date limite de départ à la retraite. | CC18: ABS_C_008 | CD18: =VLOOKUP(CC18,'Axe 2 Règles de gestion'!$D$2:$F$354,3, FALSE) -> La date de fin prévisionnelle du congé/absence doit être antérieure à la date limite de départ à la retraite.
A19: 22.10.00 | B19: A | C19: 44917.603 | D19: D0007 | E19: Congés/Absence | F19: S0046 | G19: Autorisations d'absence | H19: E0429 | I19: Autorisations d'absence avec rémunération pour mandat électif local | J19: Type de congé/absence saisi égal 'Autorisations d'absence avec rémunération pour mandat électif local' | K19: A_COA_TYCOAB [Saisi] = 'CA005' | L19: T1090 | M19: Autorisations d'absence avec rémunération pour mandat électif local | N19: Création Modification | Q19: Contractuel | R19: P0003 | S19: N | T19: Général | U19: Passant | V19: 43828 | X19: ADI_I_116 ET ADI_I_117 ET ADI_I_118 ET ABS_C_010 ET ABS_C_003 ET ABS_C_004 ET ABS_C_009 ET ABS_C_019 ET ABS_C_020 ET ABS_C_026 ET ABS_C_002 ET ABS_C_005 ET ABS_C_006 ET ABS_C_007 ET ABS_C_008 | Y19: ADI_I_116 | Z19: =VLOOKUP(Y19,'Axe 2 Règles de gestion'!$D$2:$F$354,3, FALSE) -> L'agent doit être élu d'un conseil municipal, d'un conseil départemental ou d'un conseil régional. | AA19: ADI_I_117 | AB19: =VLOOKUP(AA19,'Axe 2 Règles de gestion'!$D$2:$F$354,3, FALSE) -> Des autorisations d'absence sont accordées à l'agent pour se rendre et participer aux séances plénières, aux réunions des commissions dont il est membre et aux réunions et assemblées des organismes où il représente la collectivité. | AC19: ADI_I_118 | AD19: =VLOOKUP(AC19,'Axe 2 Règles de gestion'!$D$2:$F$354,3, FALSE) -> L'agent doit informer l'administration de la date de la séance ou de la réunion dès qu'il en a connaissance. | BG19: ABS_C_010 | BH19: =VLOOKUP(BG19,'Axe 2 Règles de gestion'!$D$2:$F$354,3, FALSE) -> L'agent doit être en activité. | BI19: ABS_C_003 | BJ19: =VLOOKUP(BI19,'Axe 2 Règles de gestion'!$D$2:$F$354,3, FALSE) -> La date de début du congé/absence doit être antérieure ou égale à la date de fin réelle du congé/absence. | BK19: ABS_C_004 | BL19: =VLOOKUP(BK19,'Axe 2 Règles de gestion'!$D$2:$F$354,3, FALSE) -> La date de début du congé/absence doit être antérieure ou égale à la date de fin prévisionnelle du congé/absence. | BM19: ABS_C_009 | BN19: =VLOOKUP(BM19,'Axe 2 Règles de gestion'!$D$2:$F$354,3, FALSE) -> La date de fin réelle ou la date de fin prévisionnelle du congé/absence doit être saisie. | BO19: ABS_C_019 | BP19: =VLOOKUP(BO19,'Axe 2 Règles de gestion'!$D$2:$F$354,3, FALSE) -> Si l'absence ne commence pas par une demi-journée et si l'absence précédente ne finit pas par une demi journée, la date de début de l'absence saisie est postérieure à la date de fin réelle de l'absence précédente. | BQ19: ABS_C_020 | BR19: =VLOOKUP(BQ19,'Axe 2 Règles de gestion'!$D$2:$F$354,3, FALSE) -> Si l'absence ne commence pas par une demi-journée et si l'absence précédente ne finit pas par une demi journée, la date de début de l'absence saisie est postérieure à la date de fin prévisionnelle de l'absence précédente. | BS19: ABS_C_026 | BT19: =VLOOKUP(BS19,'Axe 2 Règles de gestion'!$D$2:$F$354,3, FALSE) -> Dans le cas d'un congé autre que CLM, CLD, CGM et CITIS, l'indicateur de requalification doit être à non et les impacts spécifiques à la requalification ne doivent pas être mobilisés ou l'impact rémunération est vide. | BU19: ABS_C_002 | BV19: =VLOOKUP(BU19,'Axe 2 Règles de gestion'!$D$2:$F$354,3, FALSE) -> La date de début du congé/absence doit être postérieure ou égale à la date de début du lien juridique. | BW19: ABS_C_005 | BX19: =VLOOKUP(BW19,'Axe 2 Règles de gestion'!$D$2:$F$354,3, FALSE) -> La date de fin réelle du congé/absence doit être antérieure ou égale à la date limite de fin réelle ou prévisionnelle du lien juridique. | BY19: ABS_C_006 | BZ19: =VLOOKUP(BY19,'Axe 2 Règles de gestion'!$D$2:$F$354,3, FALSE) -> La date de fin prévisionnelle du congé/absence doit être antérieure ou égale à la date limite de fin réelle ou prévisionnelle du lien juridique. | CA19: ABS_C_007 | CB19: =VLOOKUP(CA19,'Axe 2 Règles de gestion'!$D$2:$F$354,3, FALSE) -> La date de fin réelle du congé/absence doit être antérieure à la date limite de départ à la retraite. | CC19: ABS_C_008 | CD19: =VLOOKUP(CC19,'Axe 2 Règles de gestion'!$D$2:$F$354,3, FALSE) -> La date de fin prévisionnelle du congé/absence doit être antérieure à la date limite de départ à la retraite.
A20: 22.10.00 | B20: M | C20: 44917.606 | D20: D0007 | E20: Congés/Absence | F20: S0046 | G20: Autorisations d'absence | H20: E0429 | I20: Autorisations d'absence avec rémunération pour mandat électif local | J20: Type de congé/absence saisi égal 'Autorisations d'absence avec rémunération pour mandat électif local' | K20: A_COA_TYCOAB [Saisi] = 'CA005' | L20: T1090 | M20: Autorisations d'absence avec rémunération pour mandat électif local | N20: Création Modification | Q20: Stagiaire ou auditeur ou élève | R20: P0004 | S20: S | T20: Général | U20: Passant | V20: 40725 | W20: 43827 | X20: ABS_C_010 ET ABS_C_001 ET ABS_C_003 ET ABS_C_004 ET ABS_C_007 ET ABS_C_008 ET ABS_C_009 ET ABS_C_019 ET ABS_C_020 ET ABS_C_026 | BG20: ABS_C_010 | BH20: =VLOOKUP(BG20,'Axe 2 Règles de gestion'!$D$2:$F$354,3, FALSE) -> L'agent doit être en activité. | BI20: ABS_C_001 | BJ20: =VLOOKUP(BI20,'Axe 2 Règles de gestion'!$D$2:$F$354,3, FALSE) -> La date de début du congé/absence doit être postérieure ou égale à la date de recrutement dans la FPE ou dans la carrière militaire. | BK20: ABS_C_003 | BL20: =VLOOKUP(BK20,'Axe 2 Règles de gestion'!$D$2:$F$354,3, FALSE) -> La date de début du congé/absence doit être antérieure ou égale à la date de fin réelle du congé/absence. | BM20: ABS_C_004 | BN20: =VLOOKUP(BM20,'Axe 2 Règles de gestion'!$D$2:$F$354,3, FALSE) -> La date de début du congé/absence doit être antérieure ou égale à la date de fin prévisionnelle du congé/absence. | BO20: ABS_C_007 | BP20: =VLOOKUP(BO20,'Axe 2 Règles de gestion'!$D$2:$F$354,3, FALSE) -> La date de fin réelle du congé/absence doit être antérieure à la date limite de départ à la retraite. | BQ20: ABS_C_008 | BR20: =VLOOKUP(BQ20,'Axe 2 Règles de gestion'!$D$2:$F$354,3, FALSE) -> La date de fin prévisionnelle du congé/absence doit être antérieure à la date limite de départ à la retraite. | BS20: ABS_C_009 | BT20: =VLOOKUP(BS20,'Axe 2 Règles de gestion'!$D$2:$F$354,3, FALSE) -> La date de fin réelle ou la date de fin prévisionnelle du congé/absence doit être saisie. | BU20: ABS_C_019 | BV20: =VLOOKUP(BU20,'Axe 2 Règles de gestion'!$D$2:$F$354,3, FALSE) -> Si l'absence ne commence pas par une demi-journée et si l'absence précédente ne finit pas par une demi journée, la date de début de l'absence saisie est postérieure à la date de fin réelle de l'absence précédente. | BW20: ABS_C_020 | BX20: =VLOOKUP(BW20,'Axe 2 Règles de gestion'!$D$2:$F$354,3, FALSE) -> Si l'absence ne commence pas par une demi-journée et si l'absence précédente ne finit pas par une demi journée, la date de début de l'absence saisie est postérieure à la date de fin prévisionnelle de l'absence précédente. | BY20: ABS_C_026 | BZ20: =VLOOKUP(BY20,'Axe 2 Règles de gestion'!$D$2:$F$354,3, FALSE) -> Dans le cas d'un congé autre que CLM, CLD, CGM et CITIS, l'indicateur de requalification doit être à non et les impacts spécifiques à la requalification ne doivent pas être mobilisés ou l'impact rémunération est vide.
A21: 22.10.00 | B21: A | C21: 44917.606 | D21: D0007 | E21: Congés/Absence | F21: S0046 | G21: Autorisations d'absence | H21: E0429 | I21: Autorisations d'absence avec rémunération pour mandat électif local | J21: Type de congé/absence saisi égal 'Autorisations d'absence avec rémunération pour mandat électif local' | K21: A_COA_TYCOAB [Saisi] = 'CA005' | L21: T1090 | M21: Autorisations d'absence avec rémunération pour mandat électif local | N21: Création Modification | Q21: Stagiaire ou auditeur ou élève | R21: P0004 | S21: S | T21: Général | U21: Passant | V21: 43828 | X21: ADI_I_116 ET ADI_I_117 ET ADI_I_118 ET ABS_C_010 ET ABS_C_001 ET ABS_C_003 ET ABS_C_004 ET ABS_C_007 ET ABS_C_008 ET ABS_C_009 ET ABS_C_019 ET ABS_C_020 ET ABS_C_026 | Y21: ADI_I_116 | Z21: =VLOOKUP(Y21,'Axe 2 Règles de gestion'!$D$2:$F$354,3, FALSE) -> L'agent doit être élu d'un conseil municipal, d'un conseil départemental ou d'un conseil régional. | AA21: ADI_I_117 | AB21: =VLOOKUP(AA21,'Axe 2 Règles de gestion'!$D$2:$F$354,3, FALSE) -> Des autorisations d'absence sont accordées à l'agent pour se rendre et participer aux séances plénières, aux réunions des commissions dont il est membre et aux réunions et assemblées des organismes où il représente la collectivité. | AC21: ADI_I_118 | AD21: =VLOOKUP(AC21,'Axe 2 Règles de gestion'!$D$2:$F$354,3, FALSE) -> L'agent doit informer l'administration de la date de la séance ou de la réunion dès qu'il en a connaissance. | BG21: ABS_C_010 | BH21: =VLOOKUP(BG21,'Axe 2 Règles de gestion'!$D$2:$F$354,3, FALSE) -> L'agent doit être en activité. | BI21: ABS_C_001 | BJ21: =VLOOKUP(BI21,'Axe 2 Règles de gestion'!$D$2:$F$354,3, FALSE) -> La date de début du congé/absence doit être postérieure ou égale à la date de recrutement dans la FPE ou dans la carrière militaire. | BK21: ABS_C_003 | BL21: =VLOOKUP(BK21,'Axe 2 Règles de gestion'!$D$2:$F$354,3, FALSE) -> La date de début du congé/absence doit être antérieure ou égale à la date de fin réelle du congé/absence. | BM21: ABS_C_004 | BN21: =VLOOKUP(BM21,'Axe 2 Règles de gestion'!$D$2:$F$354,3, FALSE) -> La date de début du congé/absence doit être antérieure ou égale à la date de fin prévisionnelle du congé/absence. | BO21: ABS_C_007 | BP21: =VLOOKUP(BO21,'Axe 2 Règles de gestion'!$D$2:$F$354,3, FALSE) -> La date de fin réelle du congé/absence doit être antérieure à la date limite de départ à la retraite. | BQ21: ABS_C_008 | BR21: =VLOOKUP(BQ21,'Axe 2 Règles de gestion'!$D$2:$F$354,3, FALSE) -> La date de fin prévisionnelle du congé/absence doit être antérieure à la date limite de départ à la retraite. | BS21: ABS_C_009 | BT21: =VLOOKUP(BS21,'Axe 2 Règles de gestion'!$D$2:$F$354,3, FALSE) -> La date de fin réelle ou la date de fin prévisionnelle du congé/absence doit être saisie. | BU21: ABS_C_019 | BV21: =VLOOKUP(BU21,'Axe 2 Règles de gestion'!$D$2:$F$354,3, FALSE) -> Si l'absence ne commence pas par une demi-journée et si l'absence précédente ne finit pas par une demi journée, la date de début de l'absence saisie est postérieure à la date de fin réelle de l'absence précédente. | BW21: ABS_C_020 | BX21: =VLOOKUP(BW21,'Axe 2 Règles de gestion'!$D$2:$F$354,3, FALSE) -> Si l'absence ne commence pas par une demi-journée et si l'absence précédente ne finit pas par une demi journée, la date de début de l'absence saisie est postérieure à la date de fin prévisionnelle de l'absence précédente. | BY21: ABS_C_026 | BZ21: =VLOOKUP(BY21,'Axe 2 Règles de gestion'!$D$2:$F$354,3, FALSE) -> Dans le cas d'un congé autre que CLM, CLD, CGM et CITIS, l'indicateur de requalification doit être à non et les impacts spécifiques à la requalification ne doivent pas être mobilisés ou l'impact rémunération est vide.
A22: 22.10.00 | B22: M | C22: 44917.605 | D22: D0007 | E22: Congés/Absence | F22: S0046 | G22: Autorisations d'absence | H22: E0429 | I22: Autorisations d'absence avec rémunération pour mandat électif local | J22: Type de congé/absence saisi égal 'Autorisations d'absence avec rémunération pour mandat électif local' | K22: A_COA_TYCOAB [Saisi] = 'CA005' | L22: T1090 | M22: Autorisations d'absence avec rémunération pour mandat électif local | N22: Création Modification | Q22: Ouvrier d'état | R22: P0005 | S22: O | T22: Général | U22: Passant | V22: 40725 | W22: 43827 | X22: ABS_C_010 ET ABS_C_003 ET ABS_C_004 ET ABS_C_009 ET ABS_C_019 ET ABS_C_020 ET ABS_C_026 ET ABS_C_002 ET ABS_C_005 ET ABS_C_006 ET ABS_C_007 ET ABS_C_008 | BG22: ABS_C_010 | BH22: =VLOOKUP(BG22,'Axe 2 Règles de gestion'!$D$2:$F$354,3, FALSE) -> L'agent doit être en activité. | BI22: ABS_C_003 | BJ22: =VLOOKUP(BI22,'Axe 2 Règles de gestion'!$D$2:$F$354,3, FALSE) -> La date de début du congé/absence doit être antérieure ou égale à la date de fin réelle du congé/absence. | BK22: ABS_C_004 | BL22: =VLOOKUP(BK22,'Axe 2 Règles de gestion'!$D$2:$F$354,3, FALSE) -> La date de début du congé/absence doit être antérieure ou égale à la date de fin prévisionnelle du congé/absence. | BM22: ABS_C_009 | BN22: =VLOOKUP(BM22,'Axe 2 Règles de gestion'!$D$2:$F$354,3, FALSE) -> La date de fin réelle ou la date de fin prévisionnelle du congé/absence doit être saisie. | BO22: ABS_C_019 | BP22: =VLOOKUP(BO22,'Axe 2 Règles de gestion'!$D$2:$F$354,3, FALSE) -> Si l'absence ne commence pas par une demi-journée et si l'absence précédente ne finit pas par une demi journée, la date de début de l'absence saisie est postérieure à la date de fin réelle de l'absence précédente. | BQ22: ABS_C_020 | BR22: =VLOOKUP(BQ22,'Axe 2 Règles de gestion'!$D$2:$F$354,3, FALSE) -> Si l'absence ne commence pas par une demi-journée et si l'absence précédente ne finit pas par une demi journée, la date de début de l'absence saisie est postérieure à la date de fin prévisionnelle de l'absence précédente. | BS22: ABS_C_026 | BT22: =VLOOKUP(BS22,'Axe 2 Règles de gestion'!$D$2:$F$354,3, FALSE) -> Dans le cas d'un congé autre que CLM, CLD, CGM et CITIS, l'indicateur de requalification doit être à non et les impacts spécifiques à la requalification ne doivent pas être mobilisés ou l'impact rémunération est vide. | BU22: ABS_C_002 | BV22: =VLOOKUP(BU22,'Axe 2 Règles de gestion'!$D$2:$F$354,3, FALSE) -> La date de début du congé/absence doit être postérieure ou égale à la date de début du lien juridique. | BW22: ABS_C_005 | BX22: =VLOOKUP(BW22,'Axe 2 Règles de gestion'!$D$2:$F$354,3, FALSE) -> La date de fin réelle du congé/absence doit être antérieure ou égale à la date limite de fin réelle ou prévisionnelle du lien juridique. | BY22: ABS_C_006 | BZ22: =VLOOKUP(BY22,'Axe 2 Règles de gestion'!$D$2:$F$354,3, FALSE) -> La date de fin prévisionnelle du congé/absence doit être antérieure ou égale à la date limite de fin réelle ou prévisionnelle du lien juridique. | CA22: ABS_C_007 | CB22: =VLOOKUP(CA22,'Axe 2 Règles de gestion'!$D$2:$F$354,3, FALSE) -> La date de fin réelle du congé/absence doit être antérieure à la date limite de départ à la retraite. | CC22: ABS_C_008 | CD22: =VLOOKUP(CC22,'Axe 2 Règles de gestion'!$D$2:$F$354,3, FALSE) -> La date de fin prévisionnelle du congé/absence doit être antérieure à la date limite de départ à la retraite.
A23: 22.10.00 | B23: A | C23: 44917.605 | D23: D0007 | E23: Congés/Absence | F23: S0046 | G23: Autorisations d'absence | H23: E0429 | I23: Autorisations d'absence avec rémunération pour mandat électif local | J23: Type de congé/absence saisi égal 'Autorisations d'absence avec rémunération pour mandat électif local' | K23: A_COA_TYCOAB [Saisi] = 'CA005' | L23: T1090 | M23: Autorisations d'absence avec rémunération pour mandat électif local | N23: Création Modification | Q23: Ouvrier d'état | R23: P0005 | S23: O | T23: Général | U23: Passant | V23: 43828 | X23: ADI_I_116 ET ADI_I_117 ET ADI_I_118 ET ABS_C_010 ET ABS_C_003 ET ABS_C_004 ET ABS_C_009 ET ABS_C_019 ET ABS_C_020 ET ABS_C_026 ET ABS_C_002 ET ABS_C_005 ET ABS_C_006 ET ABS_C_007 ET ABS_C_008 | Y23: ADI_I_116 | Z23: =VLOOKUP(Y23,'Axe 2 Règles de gestion'!$D$2:$F$354,3, FALSE) -> L'agent doit être élu d'un conseil municipal, d'un conseil départemental ou d'un conseil régional. | AA23: ADI_I_117 | AB23: =VLOOKUP(AA23,'Axe 2 Règles de gestion'!$D$2:$F$354,3, FALSE) -> Des autorisations d'absence sont accordées à l'agent pour se rendre et participer aux séances plénières, aux réunions des commissions dont il est membre et aux réunions et assemblées des organismes où il représente la collectivité. | AC23: ADI_I_118 | AD23: =VLOOKUP(AC23,'Axe 2 Règles de gestion'!$D$2:$F$354,3, FALSE) -> L'agent doit informer l'administration de la date de la séance ou de la réunion dès qu'il en a connaissance. | BG23: ABS_C_010 | BH23: =VLOOKUP(BG23,'Axe 2 Règles de gestion'!$D$2:$F$354,3, FALSE) -> L'agent doit être en activité. | BI23: ABS_C_003 | BJ23: =VLOOKUP(BI23,'Axe 2 Règles de gestion'!$D$2:$F$354,3, FALSE) -> La date de début du congé/absence doit être antérieure ou égale à la date de fin réelle du congé/absence. | BK23: ABS_C_004 | BL23: =VLOOKUP(BK23,'Axe 2 Règles de gestion'!$D$2:$F$354,3, FALSE) -> La date de début du congé/absence doit être antérieure ou égale à la date de fin prévisionnelle du congé/absence. | BM23: ABS_C_009 | BN23: =VLOOKUP(BM23,'Axe 2 Règles de gestion'!$D$2:$F$354,3, FALSE) -> La date de fin réelle ou la date de fin prévisionnelle du congé/absence doit être saisie. | BO23: ABS_C_019 | BP23: =VLOOKUP(BO23,'Axe 2 Règles de gestion'!$D$2:$F$354,3, FALSE) -> Si l'absence ne commence pas par une demi-journée et si l'absence précédente ne finit pas par une demi journée, la date de début de l'absence saisie est postérieure à la date de fin réelle de l'absence précédente. | BQ23: ABS_C_020 | BR23: =VLOOKUP(BQ23,'Axe 2 Règles de gestion'!$D$2:$F$354,3, FALSE) -> Si l'absence ne commence pas par une demi-journée et si l'absence précédente ne finit pas par une demi journée, la date de début de l'absence saisie est postérieure à la date de fin prévisionnelle de l'absence précédente. | BS23: ABS_C_026 | BT23: =VLOOKUP(BS23,'Axe 2 Règles de gestion'!$D$2:$F$354,3, FALSE) -> Dans le cas d'un congé autre que CLM, CLD, CGM et CITIS, l'indicateur de requalification doit être à non et les impacts spécifiques à la requalification ne doivent pas être mobilisés ou l'impact rémunération est vide. | BU23: ABS_C_002 | BV23: =VLOOKUP(BU23,'Axe 2 Règles de gestion'!$D$2:$F$354,3, FALSE) -> La date de début du congé/absence doit être postérieure ou égale à la date de début du lien juridique. | BW23: ABS_C_005 | BX23: =VLOOKUP(BW23,'Axe 2 Règles de gestion'!$D$2:$F$354,3, FALSE) -> La date de fin réelle du congé/absence doit être antérieure ou égale à la date limite de fin réelle ou prévisionnelle du lien juridique. | BY23: ABS_C_006 | BZ23: =VLOOKUP(BY23,'Axe 2 Règles de gestion'!$D$2:$F$354,3, FALSE) -> La date de fin prévisionnelle du congé/absence doit être antérieure ou égale à la date limite de fin réelle ou prévisionnelle du lien juridique. | CA23: ABS_C_007 | CB23: =VLOOKUP(CA23,'Axe 2 Règles de gestion'!$D$2:$F$354,3, FALSE) -> La date de fin réelle du congé/absence doit être antérieure à la date limite de départ à la retraite. | CC23: ABS_C_008 | CD23: =VLOOKUP(CC23,'Axe 2 Règles de gestion'!$D$2:$F$354,3, FALSE) -> La date de fin prévisionnelle du congé/absence doit être antérieure à la date limite de départ à la retraite.
A24: 17.10.00 | B24: A | C24: 43152.5 | D24: D0007 | E24: Congés/Absence | F24: S0046 | G24: Autorisations d'absence | H24: E0429 | I24: Autorisations d'absence avec rémunération pour mandat électif local | J24: Type de congé/absence saisi égal 'Autorisations d'absence avec rémunération pour mandat électif local' | K24: A_COA_TYCOAB [Saisi] = 'CA005' | L24: T1090 | M24: Autorisations d'absence avec rémunération pour mandat électif local | N24: Création Modification | Q24: Personnel civil payé à l'acte ou à la tâche | R24: P0054 | S24: N | T24: Particulier | U24: Exclu | V24: 40725
A25: 17.10.00 | B25: A | C25: 43152.5 | D25: D0007 | E25: Congés/Absence | F25: S0046 | G25: Autorisations d'absence | H25: E0429 | I25: Autorisations d'absence avec rémunération pour mandat électif local | J25: Type de congé/absence saisi égal 'Autorisations d'absence avec rémunération pour mandat électif local' | K25: A_COA_TYCOAB [Saisi] = 'CA005' | L25: T1090 | M25: Autorisations d'absence avec rémunération pour mandat électif local | N25: Création Modification | Q25: Volontaire International | R25: P0178 | S25: N | T25: Particulier | U25: Exclu | V25: 40725
A26: 17.10.00 | B26: A | C26: 43152.5 | D26: D0007 | E26: Congés/Absence | F26: S0046 | G26: Autorisations d'absence | H26: E0429 | I26: Autorisations d'absence avec rémunération pour mandat électif local | J26: Type de congé/absence saisi égal 'Autorisations d'absence avec rémunération pour mandat électif local' | K26: A_COA_TYCOAB [Saisi] = 'CA005' | L26: T1090 | M26: Autorisations d'absence avec rémunération pour mandat électif local | N26: Création Modification | Q26: Volontaire de service civique outre-mer | R26: P0179 | S26: N | T26: Particulier | U26: Exclu | V26: 40725
A27: 22.10.00 | B27: A | C27: 44917.61 | D27: D0007 | E27: Congés/Absence | F27: S0046 | G27: Autorisations d'absence | H27: E0429 | I27: Autorisations d'absence avec rémunération pour mandat électif local | J27: Type de congé/absence saisi égal 'Autorisations d'absence avec rémunération pour mandat électif local' | K27: A_COA_TYCOAB [Saisi] = 'CA005' | L27: T1090 | M27: Autorisations d'absence avec rémunération pour mandat électif local | N27: Création Modification | Q27: Ouvrier de la défense ou assimilé | R27: P0197 | S27: O | T27: Particulier | U27: Passant | V27: 40725 | X27: ADI_I_102 ET ADI_I_103 ET ADI_I_088 ET ADI_I_097 ET ABS_C_010 ET ABS_C_003 ET ABS_C_004 ET ABS_C_009 ET ABS_C_019 ET ABS_C_020 ET ABS_C_026 ET ABS_C_002 ET ABS_C_005 ET ABS_C_006 ET ABS_C_007 ET ABS_C_008 | Y27: ADI_I_102 | Z27: =VLOOKUP(Y27,'Axe 2 Règles de gestion'!$D$2:$F$354,3, FALSE) -> L'agent doit être élu d'un conseil municipal, d'un conseil départemental ou d'un conseil régional. | AA27: ADI_I_103 | AB27: =VLOOKUP(AA27,'Axe 2 Règles de gestion'!$D$2:$F$354,3, FALSE) -> Des autorisations d'absence sont accordées à l'agent pour se rendre et participer aux séances plénières, aux réunions des commissions dont il est membre et aux réunions et assemblées des organismes où il représente la collectivité. | AC27: ADI_I_088 | AD27: =VLOOKUP(AC27,'Axe 2 Règles de gestion'!$D$2:$F$354,3, FALSE) -> L'agent doit informer l'administration de la date de la séance ou de la réunion dès qu'il en a connaissance. | AE27: ADI_I_097 | AF27: =VLOOKUP(AE27,'Axe 2 Règles de gestion'!$D$2:$F$354,3, FALSE) -> La durée de l'autorisation d'absence est augmentée de 48 heures de délai de route maximum aller-retour si le déplacement dépasse 200 kms aller. | BG27: ABS_C_010 | BH27: =VLOOKUP(BG27,'Axe 2 Règles de gestion'!$D$2:$F$354,3, FALSE) -> L'agent doit être en activité. | BI27: ABS_C_003 | BJ27: =VLOOKUP(BI27,'Axe 2 Règles de gestion'!$D$2:$F$354,3, FALSE) -> La date de début du congé/absence doit être antérieure ou égale à la date de fin réelle du congé/absence. | BK27: ABS_C_004 | BL27: =VLOOKUP(BK27,'Axe 2 Règles de gestion'!$D$2:$F$354,3, FALSE) -> La date de début du congé/absence doit être antérieure ou égale à la date de fin prévisionnelle du congé/absence. | BM27: ABS_C_009 | BN27: =VLOOKUP(BM27,'Axe 2 Règles de gestion'!$D$2:$F$354,3, FALSE) -> La date de fin réelle ou la date de fin prévisionnelle du congé/absence doit être saisie. | BO27: ABS_C_019 | BP27: =VLOOKUP(BO27,'Axe 2 Règles de gestion'!$D$2:$F$354,3, FALSE) -> Si l'absence ne commence pas par une demi-journée et si l'absence précédente ne finit pas par une demi journée, la date de début de l'absence saisie est postérieure à la date de fin réelle de l'absence précédente. | BQ27: ABS_C_020 | BR27: =VLOOKUP(BQ27,'Axe 2 Règles de gestion'!$D$2:$F$354,3, FALSE) -> Si l'absence ne commence pas par une demi-journée et si l'absence précédente ne finit pas par une demi journée, la date de début de l'absence saisie est postérieure à la date de fin prévisionnelle de l'absence précédente. | BS27: ABS_C_026 | BT27: =VLOOKUP(BS27,'Axe 2 Règles de gestion'!$D$2:$F$354,3, FALSE) -> Dans le cas d'un congé autre que CLM, CLD, CGM et CITIS, l'indicateur de requalification doit être à non et les impacts spécifiques à la requalification ne doivent pas être mobilisés ou l'impact rémunération est vide. | BU27: ABS_C_002 | BV27: =VLOOKUP(BU27,'Axe 2 Règles de gestion'!$D$2:$F$354,3, FALSE) -> La date de début du congé/absence doit être postérieure ou égale à la date de début du lien juridique. | BW27: ABS_C_005 | BX27: =VLOOKUP(BW27,'Axe 2 Règles de gestion'!$D$2:$F$354,3, FALSE) -> La date de fin réelle du congé/absence doit être antérieure ou égale à la date limite de fin réelle ou prévisionnelle du lien juridique. | BY27: ABS_C_006 | BZ27: =VLOOKUP(BY27,'Axe 2 Règles de gestion'!$D$2:$F$354,3, FALSE) -> La date de fin prévisionnelle du congé/absence doit être antérieure ou égale à la date limite de fin réelle ou prévisionnelle du lien juridique. | CA27: ABS_C_007 | CB27: =VLOOKUP(CA27,'Axe 2 Règles de gestion'!$D$2:$F$354,3, FALSE) -> La date de fin réelle du congé/absence doit être antérieure à la date limite de départ à la retraite. | CC27: ABS_C_008 | CD27: =VLOOKUP(CC27,'Axe 2 Règles de gestion'!$D$2:$F$354,3, FALSE) -> La date de fin prévisionnelle du congé/absence doit être antérieure à la date limite de départ à la retraite.
A28: 22.10.00 | B28: M | C28: 44917.615 | D28: D0007 | E28: Congés/Absence | F28: S0046 | G28: Autorisations d'absence | H28: E0430 | I28: Autorisation d'absence pour candidature à une élection politique | J28: Type de congé/absence saisi égal 'Autorisation d'absence pour candidature à une élection politique' | K28: A_COA_TYCOAB [Saisi] = 'CA006' | L28: T1091 | M28: Autorisation d'absence pour candidature à une élection politique | N28: Création Modification | Q28: Titulaire ou magistrat | R28: P0001 | S28: T | T28: Général | U28: Passant | V28: 40725 | W28: 43827 | X28: ABS_C_010 ET ABS_C_001 ET ABS_C_003 ET ABS_C_004 ET ABS_C_007 ET ABS_C_008 ET ABS_C_009 ET ABS_C_019 ET ABS_C_020 ET ABS_C_026 | BG28: ABS_C_010 | BH28: =VLOOKUP(BG28,'Axe 2 Règles de gestion'!$D$2:$F$354,3, FALSE) -> L'agent doit être en activité. | BI28: ABS_C_001 | BJ28: =VLOOKUP(BI28,'Axe 2 Règles de gestion'!$D$2:$F$354,3, FALSE) -> La date de début du congé/absence doit être postérieure ou égale à la date de recrutement dans la FPE ou dans la carrière militaire. | BK28: ABS_C_003 | BL28: =VLOOKUP(BK28,'Axe 2 Règles de gestion'!$D$2:$F$354,3, FALSE) -> La date de début du congé/absence doit être antérieure ou égale à la date de fin réelle du congé/absence. | BM28: ABS_C_004 | BN28: =VLOOKUP(BM28,'Axe 2 Règles de gestion'!$D$2:$F$354,3, FALSE) -> La date de début du congé/absence doit être antérieure ou égale à la date de fin prévisionnelle du congé/absence. | BO28: ABS_C_007 | BP28: =VLOOKUP(BO28,'Axe 2 Règles de gestion'!$D$2:$F$354,3, FALSE) -> La date de fin réelle du congé/absence doit être antérieure à la date limite de départ à la retraite. | BQ28: ABS_C_008 | BR28: =VLOOKUP(BQ28,'Axe 2 Règles de gestion'!$D$2:$F$354,3, FALSE) -> La date de fin prévisionnelle du congé/absence doit être antérieure à la date limite de départ à la retraite. | BS28: ABS_C_009 | BT28: =VLOOKUP(BS28,'Axe 2 Règles de gestion'!$D$2:$F$354,3, FALSE) -> La date de fin réelle ou la date de fin prévisionnelle du congé/absence doit être saisie. | BU28: ABS_C_019 | BV28: =VLOOKUP(BU28,'Axe 2 Règles de gestion'!$D$2:$F$354,3, FALSE) -> Si l'absence ne commence pas par une demi-journée et si l'absence précédente ne finit pas par une demi journée, la date de début de l'absence saisie est postérieure à la date de fin réelle de l'absence précédente. | BW28: ABS_C_020 | BX28: =VLOOKUP(BW28,'Axe 2 Règles de gestion'!$D$2:$F$354,3, FALSE) -> Si l'absence ne commence pas par une demi-journée et si l'absence précédente ne finit pas par une demi journée, la date de début de l'absence saisie est postérieure à la date de fin prévisionnelle de l'absence précédente. | BY28: ABS_C_026 | BZ28: =VLOOKUP(BY28,'Axe 2 Règles de gestion'!$D$2:$F$354,3, FALSE) -> Dans le cas d'un congé autre que CLM, CLD, CGM et CITIS, l'indicateur de requalification doit être à non et les impacts spécifiques à la requalification ne doivent pas être mobilisés ou l'impact rémunération est vide.
A29: 22.10.00 | B29: A | C29: 44917.615 | D29: D0007 | E29: Congés/Absence | F29: S0046 | G29: Autorisations d'absence | H29: E0430 | I29: Autorisation d'absence pour candidature à une élection politique | J29: Type de congé/absence saisi égal 'Autorisation d'absence pour candidature à une élection politique' | K29: A_COA_TYCOAB [Saisi] = 'CA006' | L29: T1091 | M29: Autorisation d'absence pour candidature à une élection politique | N29: Création Modification | Q29: Titulaire ou magistrat | R29: P0001 | S29: T | T29: Général | U29: Passant | V29: 43828 | X29: ADI_I_120 ET ADI_I_121 ET ADI_I_122 ET ADI_D_606 ET ADI_D_607 ET ADI_D_608 ET ADI_D_609 ET ABS_C_010 ET ABS_C_001 ET ABS_C_003 ET ABS_C_004 ET ABS_C_007 ET ABS_C_008 ET ABS_C_009 ET ABS_C_019 ET ABS_C_020 ET ABS_C_026 | Y29: ADI_I_120 | Z29: =VLOOKUP(Y29,'Axe 2 Règles de gestion'!$D$2:$F$354,3, FALSE) -> L'agent, candidat à l'Assemblée nationale ou au Sénat, dispose du temps nécessaire pour participer à la campagne électorale dans la limite de 20 jours ouvrables. | AA29: ADI_I_121 | AB29: =VLOOKUP(AA29,'Axe 2 Règles de gestion'!$D$2:$F$354,3, FALSE) -> Le même droit est accordé, sur demande, dans la limite de 10 jours ouvrables à l'agent, candidat au Parlement européen, au conseil municipal, au conseil départemental ou régional, à l'Assemblée de Corse, au conseil de la métropole de Lyon. | AC29: ADI_I_122 | AD29: =VLOOKUP(AC29,'Axe 2 Règles de gestion'!$D$2:$F$354,3, FALSE) -> L'agent doit avertir l'administration 24 heures au moins avant le début de chaque absence qui doit être au moins d'une 1/2 journée entière. | AQ29: ADI_D_606 | AR29: =VLOOKUP(AQ29,'Axe 2 Règles de gestion'!$D$2:$F$354,3, FALSE) -> La durée prévisionnelle du congé accordé à l'agent, candidat à l'Assemblée nationale ou au Sénat, pour participer à la campagne électorale est limitée à 20 jours ouvrables. | AS29: ADI_D_607 | AT29: =VLOOKUP(AS29,'Axe 2 Règles de gestion'!$D$2:$F$354,3, FALSE) -> La durée réelle du congé accordé à l'agent, candidat à l'Assemblée nationale ou au Sénat, pour participer à la campagne électorale est limitée à 20 jours ouvrables. | AU29: ADI_D_608 | AV29: =VLOOKUP(AU29,'Axe 2 Règles de gestion'!$D$2:$F$354,3, FALSE) -> La durée prévisionnelle du congé accordé à l'agent, candidat au Parlement européen, au conseil municipal, au conseil départemental ou régional, à l'Assemblée de Corse, au conseil de la métropole de Lyon est limitée à 10 jours ouvrables. | AW29: ADI_D_609 | AX29: =VLOOKUP(AW29,'Axe 2 Règles de gestion'!$D$2:$F$354,3, FALSE) -> La durée réelle du congé accordé à l'agent, candidat au Parlement européen, au conseil municipal, au conseil départemental ou régional, à l'Assemblée de Corse, au conseil de la métropole de Lyon est limitée à 10 jours ouvrables. | BG29: ABS_C_010 | BH29: =VLOOKUP(BG29,'Axe 2 Règles de gestion'!$D$2:$F$354,3, FALSE) -> L'agent doit être en activité. | BI29: ABS_C_001 | BJ29: =VLOOKUP(BI29,'Axe 2 Règles de gestion'!$D$2:$F$354,3, FALSE) -> La date de début du congé/absence doit être postérieure ou égale à la date de recrutement dans la FPE ou dans la carrière militaire. | BK29: ABS_C_003 | BL29: =VLOOKUP(BK29,'Axe 2 Règles de gestion'!$D$2:$F$354,3, FALSE) -> La date de début du congé/absence doit être antérieure ou égale à la date de fin réelle du congé/absence. | BM29: ABS_C_004 | BN29: =VLOOKUP(BM29,'Axe 2 Règles de gestion'!$D$2:$F$354,3, FALSE) -> La date de début du congé/absence doit être antérieure ou égale à la date de fin prévisionnelle du congé/absence. | BO29: ABS_C_007 | BP29: =VLOOKUP(BO29,'Axe 2 Règles de gestion'!$D$2:$F$354,3, FALSE) -> La date de fin réelle du congé/absence doit être antérieure à la date limite de départ à la retraite. | BQ29: ABS_C_008 | BR29: =VLOOKUP(BQ29,'Axe 2 Règles de gestion'!$D$2:$F$354,3, FALSE) -> La date de fin prévisionnelle du congé/absence doit être antérieure à la date limite de départ à la retraite. | BS29: ABS_C_009 | BT29: =VLOOKUP(BS29,'Axe 2 Règles de gestion'!$D$2:$F$354,3, FALSE) -> La date de fin réelle ou la date de fin prévisionnelle du congé/absence doit être saisie. | BU29: ABS_C_019 | BV29: =VLOOKUP(BU29,'Axe 2 Règles de gestion'!$D$2:$F$354,3, FALSE) -> Si l'absence ne commence pas par une demi-journée et si l'absence précédente ne finit pas par une demi journée, la date de début de l'absence saisie est postérieure à la date de fin réelle de l'absence précédente. | BW29: ABS_C_020 | BX29: =VLOOKUP(BW29,'Axe 2 Règles de gestion'!$D$2:$F$354,3, FALSE) -> Si l'absence ne commence pas par une demi-journée et si l'absence précédente ne finit pas par une demi journée, la date de début de l'absence saisie est postérieure à la date de fin prévisionnelle de l'absence précédente. | BY29: ABS_C_026 | BZ29: =VLOOKUP(BY29,'Axe 2 Règles de gestion'!$D$2:$F$354,3, FALSE) -> Dans le cas d'un congé autre que CLM, CLD, CGM et CITIS, l'indicateur de requalification doit être à non et les impacts spécifiques à la requalification ne doivent pas être mobilisés ou l'impact rémunération est vide.
A30: 22.10.00 | B30: M | C30: 44917.616 | D30: D0007 | E30: Congés/Absence | F30: S0046 | G30: Autorisations d'absence | H30: E0430 | I30: Autorisation d'absence pour candidature à une élection politique | J30: Type de congé/absence saisi égal 'Autorisation d'absence pour candidature à une élection politique' | K30: A_COA_TYCOAB [Saisi] = 'CA006' | L30: T1091 | M30: Autorisation d'absence pour candidature à une élection politique | N30: Création Modification | Q30: Contractuel | R30: P0003 | S30: N | T30: Général | U30: Passant | V30: 40725 | W30: 43827 | X30: ABS_C_010 ET ABS_C_003 ET ABS_C_004 ET ABS_C_009 ET ABS_C_019 ET ABS_C_020 ET ABS_C_026 ET ABS_C_002 ET ABS_C_005 ET ABS_C_006 ET ABS_C_007 ET ABS_C_008 | BG30: ABS_C_010 | BH30: =VLOOKUP(BG30,'Axe 2 Règles de gestion'!$D$2:$F$354,3, FALSE) -> L'agent doit être en activité. | BI30: ABS_C_003 | BJ30: =VLOOKUP(BI30,'Axe 2 Règles de gestion'!$D$2:$F$354,3, FALSE) -> La date de début du congé/absence doit être antérieure ou égale à la date de fin réelle du congé/absence. | BK30: ABS_C_004 | BL30: =VLOOKUP(BK30,'Axe 2 Règles de gestion'!$D$2:$F$354,3, FALSE) -> La date de début du congé/absence doit être antérieure ou égale à la date de fin prévisionnelle du congé/absence. | BM30: ABS_C_009 | BN30: =VLOOKUP(BM30,'Axe 2 Règles de gestion'!$D$2:$F$354,3, FALSE) -> La date de fin réelle ou la date de fin prévisionnelle du congé/absence doit être saisie. | BO30: ABS_C_019 | BP30: =VLOOKUP(BO30,'Axe 2 Règles de gestion'!$D$2:$F$354,3, FALSE) -> Si l'absence ne commence pas par une demi-journée et si l'absence précédente ne finit pas par une demi journée, la date de début de l'absence saisie est postérieure à la date de fin réelle de l'absence précédente. | BQ30: ABS_C_020 | BR30: =VLOOKUP(BQ30,'Axe 2 Règles de gestion'!$D$2:$F$354,3, FALSE) -> Si l'absence ne commence pas par une demi-journée et si l'absence précédente ne finit pas par une demi journée, la date de début de l'absence saisie est postérieure à la date de fin prévisionnelle de l'absence précédente. | BS30: ABS_C_026 | BT30: =VLOOKUP(BS30,'Axe 2 Règles de gestion'!$D$2:$F$354,3, FALSE) -> Dans le cas d'un congé autre que CLM, CLD, CGM et CITIS, l'indicateur de requalification doit être à non et les impacts spécifiques à la requalification ne doivent pas être mobilisés ou l'impact rémunération est vide. | BU30: ABS_C_002 | BV30: =VLOOKUP(BU30,'Axe 2 Règles de gestion'!$D$2:$F$354,3, FALSE) -> La date de début du congé/absence doit être postérieure ou égale à la date de début du lien juridique. | BW30: ABS_C_005 | BX30: =VLOOKUP(BW30,'Axe 2 Règles de gestion'!$D$2:$F$354,3, FALSE) -> La date de fin réelle du congé/absence doit être antérieure ou égale à la date limite de fin réelle ou prévisionnelle du lien juridique. | BY30: ABS_C_006 | BZ30: =VLOOKUP(BY30,'Axe 2 Règles de gestion'!$D$2:$F$354,3, FALSE) -> La date de fin prévisionnelle du congé/absence doit être antérieure ou égale à la date limite de fin réelle ou prévisionnelle du lien juridique. | CA30: ABS_C_007 | CB30: =VLOOKUP(CA30,'Axe 2 Règles de gestion'!$D$2:$F$354,3, FALSE) -> La date de fin réelle du congé/absence doit être antérieure à la date limite de départ à la retraite. | CC30: ABS_C_008 | CD30: =VLOOKUP(CC30,'Axe 2 Règles de gestion'!$D$2:$F$354,3, FALSE) -> La date de fin prévisionnelle du congé/absence doit être antérieure à la date limite de départ à la retraite.
A31: 22.10.00 | B31: A | C31: 44917.616 | D31: D0007 | E31: Congés/Absence | F31: S0046 | G31: Autorisations d'absence | H31: E0430 | I31: Autorisation d'absence pour candidature à une élection politique | J31: Type de congé/absence saisi égal 'Autorisation d'absence pour candidature à une élection politique' | K31: A_COA_TYCOAB [Saisi] = 'CA006' | L31: T1091 | M31: Autorisation d'absence pour candidature à une élection politique | N31: Création Modification | Q31: Contractuel | R31: P0003 | S31: N | T31: Général | U31: Passant | V31: 43828 | X31: ADI_I_120 ET ADI_I_121 ET ADI_I_122 ET ADI_D_606 ET ADI_D_607 ET ADI_D_608 ET ADI_D_609 ET ABS_C_010 ET ABS_C_003 ET ABS_C_004 ET ABS_C_009 ET ABS_C_019 ET ABS_C_020 ET ABS_C_026 ET ABS_C_002 ET ABS_C_005 ET ABS_C_006 ET ABS_C_007 ET ABS_C_008 | Y31: ADI_I_120 | Z31: =VLOOKUP(Y31,'Axe 2 Règles de gestion'!$D$2:$F$354,3, FALSE) -> L'agent, candidat à l'Assemblée nationale ou au Sénat, dispose du temps nécessaire pour participer à la campagne électorale dans la limite de 20 jours ouvrables. | AA31: ADI_I_121 | AB31: =VLOOKUP(AA31,'Axe 2 Règles de gestion'!$D$2:$F$354,3, FALSE) -> Le même droit est accordé, sur demande, dans la limite de 10 jours ouvrables à l'agent, candidat au Parlement européen, au conseil municipal, au conseil départemental ou régional, à l'Assemblée de Corse, au conseil de la métropole de Lyon. | AC31: ADI_I_122 | AD31: =VLOOKUP(AC31,'Axe 2 Règles de gestion'!$D$2:$F$354,3, FALSE) -> L'agent doit avertir l'administration 24 heures au moins avant le début de chaque absence qui doit être au moins d'une 1/2 journée entière. | AQ31: ADI_D_606 | AR31: =VLOOKUP(AQ31,'Axe 2 Règles de gestion'!$D$2:$F$354,3, FALSE) -> La durée prévisionnelle du congé accordé à l'agent, candidat à l'Assemblée nationale ou au Sénat, pour participer à la campagne électorale est limitée à 20 jours ouvrables. | AS31: ADI_D_607 | AT31: =VLOOKUP(AS31,'Axe 2 Règles de gestion'!$D$2:$F$354,3, FALSE) -> La durée réelle du congé accordé à l'agent, candidat à l'Assemblée nationale ou au Sénat, pour participer à la campagne électorale est limitée à 20 jours ouvrables. | AU31: ADI_D_608 | AV31: =VLOOKUP(AU31,'Axe 2 Règles de gestion'!$D$2:$F$354,3, FALSE) -> La durée prévisionnelle du congé accordé à l'agent, candidat au Parlement européen, au conseil municipal, au conseil départemental ou régional, à l'Assemblée de Corse, au conseil de la métropole de Lyon est limitée à 10 jours ouvrables. | AW31: ADI_D_609 | AX31: =VLOOKUP(AW31,'Axe 2 Règles de gestion'!$D$2:$F$354,3, FALSE) -> La durée réelle du congé accordé à l'agent, candidat au Parlement européen, au conseil municipal, au conseil départemental ou régional, à l'Assemblée de Corse, au conseil de la métropole de Lyon est limitée à 10 jours ouvrables. | BG31: ABS_C_010 | BH31: =VLOOKUP(BG31,'Axe 2 Règles de gestion'!$D$2:$F$354,3, FALSE) -> L'agent doit être en activité. | BI31: ABS_C_003 | BJ31: =VLOOKUP(BI31,'Axe 2 Règles de gestion'!$D$2:$F$354,3, FALSE) -> La date de début du congé/absence doit être antérieure ou égale à la date de fin réelle du congé/absence. | BK31: ABS_C_004 | BL31: =VLOOKUP(BK31,'Axe 2 Règles de gestion'!$D$2:$F$354,3, FALSE) -> La date de début du congé/absence doit être antérieure ou égale à la date de fin prévisionnelle du congé/absence. | BM31: ABS_C_009 | BN31: =VLOOKUP(BM31,'Axe 2 Règles de gestion'!$D$2:$F$354,3, FALSE) -> La date de fin réelle ou la date de fin prévisionnelle du congé/absence doit être saisie. | BO31: ABS_C_019 | BP31: =VLOOKUP(BO31,'Axe 2 Règles de gestion'!$D$2:$F$354,3, FALSE) -> Si l'absence ne commence pas par une demi-journée et si l'absence précédente ne finit pas par une demi journée, la date de début de l'absence saisie est postérieure à la date de fin réelle de l'absence précédente. | BQ31: ABS_C_020 | BR31: =VLOOKUP(BQ31,'Axe 2 Règles de gestion'!$D$2:$F$354,3, FALSE) -> Si l'absence ne commence pas par une demi-journée et si l'absence précédente ne finit pas par une demi journée, la date de début de l'absence saisie est postérieure à la date de fin prévisionnelle de l'absence précédente. | BS31: ABS_C_026 | BT31: =VLOOKUP(BS31,'Axe 2 Règles de gestion'!$D$2:$F$354,3, FALSE) -> Dans le cas d'un congé autre que CLM, CLD, CGM et CITIS, l'indicateur de requalification doit être à non et les impacts spécifiques à la requalification ne doivent pas être mobilisés ou l'impact rémunération est vide. | BU31: ABS_C_002 | BV31: =VLOOKUP(BU31,'Axe 2 Règles de gestion'!$D$2:$F$354,3, FALSE) -> La date de début du congé/absence doit être postérieure ou égale à la date de début du lien juridique. | BW31: ABS_C_005 | BX31: =VLOOKUP(BW31,'Axe 2 Règles de gestion'!$D$2:$F$354,3, FALSE) -> La date de fin réelle du congé/absence doit être antérieure ou égale à la date limite de fin réelle ou prévisionnelle du lien juridique. | BY31: ABS_C_006 | BZ31: =VLOOKUP(BY31,'Axe 2 Règles de gestion'!$D$2:$F$354,3, FALSE) -> La date de fin prévisionnelle du congé/absence doit être antérieure ou égale à la date limite de fin réelle ou prévisionnelle du lien juridique. | CA31: ABS_C_007 | CB31: =VLOOKUP(CA31,'Axe 2 Règles de gestion'!$D$2:$F$354,3, FALSE) -> La date de fin réelle du congé/absence doit être antérieure à la date limite de départ à la retraite. | CC31: ABS_C_008 | CD31: =VLOOKUP(CC31,'Axe 2 Règles de gestion'!$D$2:$F$354,3, FALSE) -> La date de fin prévisionnelle du congé/absence doit être antérieure à la date limite de départ à la retraite.
A32: 22.10.00 | B32: M | C32: 44917.617 | D32: D0007 | E32: Congés/Absence | F32: S0046 | G32: Autorisations d'absence | H32: E0430 | I32: Autorisation d'absence pour candidature à une élection politique | J32: Type de congé/absence saisi égal 'Autorisation d'absence pour candidature à une élection politique' | K32: A_COA_TYCOAB [Saisi] = 'CA006' | L32: T1091 | M32: Autorisation d'absence pour candidature à une élection politique | N32: Création Modification | Q32: Stagiaire ou auditeur ou élève | R32: P0004 | S32: S | T32: Général | U32: Passant | V32: 40725 | W32: 43827 | X32: ABS_C_010 ET ABS_C_001 ET ABS_C_003 ET ABS_C_004 ET ABS_C_007 ET ABS_C_008 ET ABS_C_009 ET ABS_C_019 ET ABS_C_020 ET ABS_C_026 | BG32: ABS_C_010 | BH32: =VLOOKUP(BG32,'Axe 2 Règles de gestion'!$D$2:$F$354,3, FALSE) -> L'agent doit être en activité. | BI32: ABS_C_001 | BJ32: =VLOOKUP(BI32,'Axe 2 Règles de gestion'!$D$2:$F$354,3, FALSE) -> La date de début du congé/absence doit être postérieure ou égale à la date de recrutement dans la FPE ou dans la carrière militaire. | BK32: ABS_C_003 | BL32: =VLOOKUP(BK32,'Axe 2 Règles de gestion'!$D$2:$F$354,3, FALSE) -> La date de début du congé/absence doit être antérieure ou égale à la date de fin réelle du congé/absence. | BM32: ABS_C_004 | BN32: =VLOOKUP(BM32,'Axe 2 Règles de gestion'!$D$2:$F$354,3, FALSE) -> La date de début du congé/absence doit être antérieure ou égale à la date de fin prévisionnelle du congé/absence. | BO32: ABS_C_007 | BP32: =VLOOKUP(BO32,'Axe 2 Règles de gestion'!$D$2:$F$354,3, FALSE) -> La date de fin réelle du congé/absence doit être antérieure à la date limite de départ à la retraite. | BQ32: ABS_C_008 | BR32: =VLOOKUP(BQ32,'Axe 2 Règles de gestion'!$D$2:$F$354,3, FALSE) -> La date de fin prévisionnelle du congé/absence doit être antérieure à la date limite de départ à la retraite. | BS32: ABS_C_009 | BT32: =VLOOKUP(BS32,'Axe 2 Règles de gestion'!$D$2:$F$354,3, FALSE) -> La date de fin réelle ou la date de fin prévisionnelle du congé/absence doit être saisie. | BU32: ABS_C_019 | BV32: =VLOOKUP(BU32,'Axe 2 Règles de gestion'!$D$2:$F$354,3, FALSE) -> Si l'absence ne commence pas par une demi-journée et si l'absence précédente ne finit pas par une demi journée, la date de début de l'absence saisie est postérieure à la date de fin réelle de l'absence précédente. | BW32: ABS_C_020 | BX32: =VLOOKUP(BW32,'Axe 2 Règles de gestion'!$D$2:$F$354,3, FALSE) -> Si l'absence ne commence pas par une demi-journée et si l'absence précédente ne finit pas par une demi journée, la date de début de l'absence saisie est postérieure à la date de fin prévisionnelle de l'absence précédente. | BY32: ABS_C_026 | BZ32: =VLOOKUP(BY32,'Axe 2 Règles de gestion'!$D$2:$F$354,3, FALSE) -> Dans le cas d'un congé autre que CLM, CLD, CGM et CITIS, l'indicateur de requalification doit être à non et les impacts spécifiques à la requalification ne doivent pas être mobilisés ou l'impact rémunération est vide.
A33: 22.10.00 | B33: A | C33: 44917.617 | D33: D0007 | E33: Congés/Absence | F33: S0046 | G33: Autorisations d'absence | H33: E0430 | I33: Autorisation d'absence pour candidature à une élection politique | J33: Type de congé/absence saisi égal 'Autorisation d'absence pour candidature à une élection politique' | K33: A_COA_TYCOAB [Saisi] = 'CA006' | L33: T1091 | M33: Autorisation d'absence pour candidature à une élection politique | N33: Création Modification | Q33: Stagiaire ou auditeur ou élève | R33: P0004 | S33: S | T33: Général | U33: Passant | V33: 43828 | X33: ADI_I_120 ET ADI_I_121 ET ADI_I_122 ET ADI_D_606 ET ADI_D_607 ET ADI_D_608 ET ADI_D_609 ET ABS_C_010 ET ABS_C_001 ET ABS_C_003 ET ABS_C_004 ET ABS_C_007 ET ABS_C_008 ET ABS_C_009 ET ABS_C_019 ET ABS_C_020 ET ABS_C_026 | Y33: ADI_I_120 | Z33: =VLOOKUP(Y33,'Axe 2 Règles de gestion'!$D$2:$F$354,3, FALSE) -> L'agent, candidat à l'Assemblée nationale ou au Sénat, dispose du temps nécessaire pour participer à la campagne électorale dans la limite de 20 jours ouvrables. | AA33: ADI_I_121 | AB33: =VLOOKUP(AA33,'Axe 2 Règles de gestion'!$D$2:$F$354,3, FALSE) -> Le même droit est accordé, sur demande, dans la limite de 10 jours ouvrables à l'agent, candidat au Parlement européen, au conseil municipal, au conseil départemental ou régional, à l'Assemblée de Corse, au conseil de la métropole de Lyon. | AC33: ADI_I_122 | AD33: =VLOOKUP(AC33,'Axe 2 Règles de gestion'!$D$2:$F$354,3, FALSE) -> L'agent doit avertir l'administration 24 heures au moins avant le début de chaque absence qui doit être au moins d'une 1/2 journée entière. | AQ33: ADI_D_606 | AR33: =VLOOKUP(AQ33,'Axe 2 Règles de gestion'!$D$2:$F$354,3, FALSE) -> La durée prévisionnelle du congé accordé à l'agent, candidat à l'Assemblée nationale ou au Sénat, pour participer à la campagne électorale est limitée à 20 jours ouvrables. | AS33: ADI_D_607 | AT33: =VLOOKUP(AS33,'Axe 2 Règles de gestion'!$D$2:$F$354,3, FALSE) -> La durée réelle du congé accordé à l'agent, candidat à l'Assemblée nationale ou au Sénat, pour participer à la campagne électorale est limitée à 20 jours ouvrables. | AU33: ADI_D_608 | AV33: =VLOOKUP(AU33,'Axe 2 Règles de gestion'!$D$2:$F$354,3, FALSE) -> La durée prévisionnelle du congé accordé à l'agent, candidat au Parlement européen, au conseil municipal, au conseil départemental ou régional, à l'Assemblée de Corse, au conseil de la métropole de Lyon est limitée à 10 jours ouvrables. | AW33: ADI_D_609 | AX33: =VLOOKUP(AW33,'Axe 2 Règles de gestion'!$D$2:$F$354,3, FALSE) -> La durée réelle du congé accordé à l'agent, candidat au Parlement européen, au conseil municipal, au conseil départemental ou régional, à l'Assemblée de Corse, au conseil de la métropole de Lyon est limitée à 10 jours ouvrables. | BG33: ABS_C_010 | BH33: =VLOOKUP(BG33,'Axe 2 Règles de gestion'!$D$2:$F$354,3, FALSE) -> L'agent doit être en activité. | BI33: ABS_C_001 | BJ33: =VLOOKUP(BI33,'Axe 2 Règles de gestion'!$D$2:$F$354,3, FALSE) -> La date de début du congé/absence doit être postérieure ou égale à la date de recrutement dans la FPE ou dans la carrière militaire. | BK33: ABS_C_003 | BL33: =VLOOKUP(BK33,'Axe 2 Règles de gestion'!$D$2:$F$354,3, FALSE) -> La date de début du congé/absence doit être antérieure ou égale à la date de fin réelle du congé/absence. | BM33: ABS_C_004 | BN33: =VLOOKUP(BM33,'Axe 2 Règles de gestion'!$D$2:$F$354,3, FALSE) -> La date de début du congé/absence doit être antérieure ou égale à la date de fin prévisionnelle du congé/absence. | BO33: ABS_C_007 | BP33: =VLOOKUP(BO33,'Axe 2 Règles de gestion'!$D$2:$F$354,3, FALSE) -> La date de fin réelle du congé/absence doit être antérieure à la date limite de départ à la retraite. | BQ33: ABS_C_008 | BR33: =VLOOKUP(BQ33,'Axe 2 Règles de gestion'!$D$2:$F$354,3, FALSE) -> La date de fin prévisionnelle du congé/absence doit être antérieure à la date limite de départ à la retraite. | BS33: ABS_C_009 | BT33: =VLOOKUP(BS33,'Axe 2 Règles de gestion'!$D$2:$F$354,3, FALSE) -> La date de fin réelle ou la date de fin prévisionnelle du congé/absence doit être saisie. | BU33: ABS_C_019 | BV33: =VLOOKUP(BU33,'Axe 2 Règles de gestion'!$D$2:$F$354,3, FALSE) -> Si l'absence ne commence pas par une demi-journée et si l'absence précédente ne finit pas par une demi journée, la date de début de l'absence saisie est postérieure à la date de fin réelle de l'absence précédente. | BW33: ABS_C_020 | BX33: =VLOOKUP(BW33,'Axe 2 Règles de gestion'!$D$2:$F$354,3, FALSE) -> Si l'absence ne commence pas par une demi-journée et si l'absence précédente ne finit pas par une demi journée, la date de début de l'absence saisie est postérieure à la date de fin prévisionnelle de l'absence précédente. | BY33: ABS_C_026 | BZ33: =VLOOKUP(BY33,'Axe 2 Règles de gestion'!$D$2:$F$354,3, FALSE) -> Dans le cas d'un congé autre que CLM, CLD, CGM et CITIS, l'indicateur de requalification doit être à non et les impacts spécifiques à la requalification ne doivent pas être mobilisés ou l'impact rémunération est vide.
A34: 22.10.00 | B34: M | C34: 44917.617 | D34: D0007 | E34: Congés/Absence | F34: S0046 | G34: Autorisations d'absence | H34: E0430 | I34: Autorisation d'absence pour candidature à une élection politique | J34: Type de congé/absence saisi égal 'Autorisation d'absence pour candidature à une élection politique' | K34: A_COA_TYCOAB [Saisi] = 'CA006' | L34: T1091 | M34: Autorisation d'absence pour candidature à une élection politique | N34: Création Modification | Q34: Ouvrier d'état | R34: P0005 | S34: O | T34: Général | U34: Passant | V34: 40725 | W34: 43827 | X34: ABS_C_010 ET ABS_C_003 ET ABS_C_004 ET ABS_C_009 ET ABS_C_019 ET ABS_C_020 ET ABS_C_026 ET ABS_C_002 ET ABS_C_005 ET ABS_C_006 ET ABS_C_007 ET ABS_C_008 | BG34: ABS_C_010 | BH34: =VLOOKUP(BG34,'Axe 2 Règles de gestion'!$D$2:$F$354,3, FALSE) -> L'agent doit être en activité. | BI34: ABS_C_003 | BJ34: =VLOOKUP(BI34,'Axe 2 Règles de gestion'!$D$2:$F$354,3, FALSE) -> La date de début du congé/absence doit être antérieure ou égale à la date de fin réelle du congé/absence. | BK34: ABS_C_004 | BL34: =VLOOKUP(BK34,'Axe 2 Règles de gestion'!$D$2:$F$354,3, FALSE) -> La date de début du congé/absence doit être antérieure ou égale à la date de fin prévisionnelle du congé/absence. | BM34: ABS_C_009 | BN34: =VLOOKUP(BM34,'Axe 2 Règles de gestion'!$D$2:$F$354,3, FALSE) -> La date de fin réelle ou la date de fin prévisionnelle du congé/absence doit être saisie. | BO34: ABS_C_019 | BP34: =VLOOKUP(BO34,'Axe 2 Règles de gestion'!$D$2:$F$354,3, FALSE) -> Si l'absence ne commence pas par une demi-journée et si l'absence précédente ne finit pas par une demi journée, la date de début de l'absence saisie est postérieure à la date de fin réelle de l'absence précédente. | BQ34: ABS_C_020 | BR34: =VLOOKUP(BQ34,'Axe 2 Règles de gestion'!$D$2:$F$354,3, FALSE) -> Si l'absence ne commence pas par une demi-journée et si l'absence précédente ne finit pas par une demi journée, la date de début de l'absence saisie est postérieure à la date de fin prévisionnelle de l'absence précédente. | BS34: ABS_C_026 | BT34: =VLOOKUP(BS34,'Axe 2 Règles de gestion'!$D$2:$F$354,3, FALSE) -> Dans le cas d'un congé autre que CLM, CLD, CGM et CITIS, l'indicateur de requalification doit être à non et les impacts spécifiques à la requalification ne doivent pas être mobilisés ou l'impact rémunération est vide. | BU34: ABS_C_002 | BV34: =VLOOKUP(BU34,'Axe 2 Règles de gestion'!$D$2:$F$354,3, FALSE) -> La date de début du congé/absence doit être postérieure ou égale à la date de début du lien juridique. | BW34: ABS_C_005 | BX34: =VLOOKUP(BW34,'Axe 2 Règles de gestion'!$D$2:$F$354,3, FALSE) -> La date de fin réelle du congé/absence doit être antérieure ou égale à la date limite de fin réelle ou prévisionnelle du lien juridique. | BY34: ABS_C_006 | BZ34: =VLOOKUP(BY34,'Axe 2 Règles de gestion'!$D$2:$F$354,3, FALSE) -> La date de fin prévisionnelle du congé/absence doit être antérieure ou égale à la date limite de fin réelle ou prévisionnelle du lien juridique. | CA34: ABS_C_007 | CB34: =VLOOKUP(CA34,'Axe 2 Règles de gestion'!$D$2:$F$354,3, FALSE) -> La date de fin réelle du congé/absence doit être antérieure à la date limite de départ à la retraite. | CC34: ABS_C_008 | CD34: =VLOOKUP(CC34,'Axe 2 Règles de gestion'!$D$2:$F$354,3, FALSE) -> La date de fin prévisionnelle du congé/absence doit être antérieure à la date limite de départ à la retraite.
A35: 22.10.00 | B35: A | C35: 44917.617 | D35: D0007 | E35: Congés/Absence | F35: S0046 | G35: Autorisations d'absence | H35: E0430 | I35: Autorisation d'absence pour candidature à une élection politique | J35: Type de congé/absence saisi égal 'Autorisation d'absence pour candidature à une élection politique' | K35: A_COA_TYCOAB [Saisi] = 'CA006' | L35: T1091 | M35: Autorisation d'absence pour candidature à une élection politique | N35: Création Modification | Q35: Ouvrier d'état | R35: P0005 | S35: O | T35: Général | U35: Passant | V35: 43828 | X35: ADI_I_120 ET ADI_I_121 ET ADI_I_122 ET ADI_D_606 ET ADI_D_607 ET ADI_D_608 ET ADI_D_609 ET ABS_C_010 ET ABS_C_003 ET ABS_C_004 ET ABS_C_009 ET ABS_C_019 ET ABS_C_020 ET ABS_C_026 ET ABS_C_002 ET ABS_C_005 ET ABS_C_006 ET ABS_C_007 ET ABS_C_008 | Y35: ADI_I_120 | Z35: =VLOOKUP(Y35,'Axe 2 Règles de gestion'!$D$2:$F$354,3, FALSE) -> L'agent, candidat à l'Assemblée nationale ou au Sénat, dispose du temps nécessaire pour participer à la campagne électorale dans la limite de 20 jours ouvrables. | AA35: ADI_I_121 | AB35: =VLOOKUP(AA35,'Axe 2 Règles de gestion'!$D$2:$F$354,3, FALSE) -> Le même droit est accordé, sur demande, dans la limite de 10 jours ouvrables à l'agent, candidat au Parlement européen, au conseil municipal, au conseil départemental ou régional, à l'Assemblée de Corse, au conseil de la métropole de Lyon. | AC35: ADI_I_122 | AD35: =VLOOKUP(AC35,'Axe 2 Règles de gestion'!$D$2:$F$354,3, FALSE) -> L'agent doit avertir l'administration 24 heures au moins avant le début de chaque absence qui doit être au moins d'une 1/2 journée entière. | AQ35: ADI_D_606 | AR35: =VLOOKUP(AQ35,'Axe 2 Règles de gestion'!$D$2:$F$354,3, FALSE) -> La durée prévisionnelle du congé accordé à l'agent, candidat à l'Assemblée nationale ou au Sénat, pour participer à la campagne électorale est limitée à 20 jours ouvrables. | AS35: ADI_D_607 | AT35: =VLOOKUP(AS35,'Axe 2 Règles de gestion'!$D$2:$F$354,3, FALSE) -> La durée réelle du congé accordé à l'agent, candidat à l'Assemblée nationale ou au Sénat, pour participer à la campagne électorale est limitée à 20 jours ouvrables. | AU35: ADI_D_608 | AV35: =VLOOKUP(AU35,'Axe 2 Règles de gestion'!$D$2:$F$354,3, FALSE) -> La durée prévisionnelle du congé accordé à l'agent, candidat au Parlement européen, au conseil municipal, au conseil départemental ou régional, à l'Assemblée de Corse, au conseil de la métropole de Lyon est limitée à 10 jours ouvrables. | AW35: ADI_D_609 | AX35: =VLOOKUP(AW35,'Axe 2 Règles de gestion'!$D$2:$F$354,3, FALSE) -> La durée réelle du congé accordé à l'agent, candidat au Parlement européen, au conseil municipal, au conseil départemental ou régional, à l'Assemblée de Corse, au conseil de la métropole de Lyon est limitée à 10 jours ouvrables. | BG35: ABS_C_010 | BH35: =VLOOKUP(BG35,'Axe 2 Règles de gestion'!$D$2:$F$354,3, FALSE) -> L'agent doit être en activité. | BI35: ABS_C_003 | BJ35: =VLOOKUP(BI35,'Axe 2 Règles de gestion'!$D$2:$F$354,3, FALSE) -> La date de début du congé/absence doit être antérieure ou égale à la date de fin réelle du congé/absence. | BK35: ABS_C_004 | BL35: =VLOOKUP(BK35,'Axe 2 Règles de gestion'!$D$2:$F$354,3, FALSE) -> La date de début du congé/absence doit être antérieure ou égale à la date de fin prévisionnelle du congé/absence. | BM35: ABS_C_009 | BN35: =VLOOKUP(BM35,'Axe 2 Règles de gestion'!$D$2:$F$354,3, FALSE) -> La date de fin réelle ou la date de fin prévisionnelle du congé/absence doit être saisie. | BO35: ABS_C_019 | BP35: =VLOOKUP(BO35,'Axe 2 Règles de gestion'!$D$2:$F$354,3, FALSE) -> Si l'absence ne commence pas par une demi-journée et si l'absence précédente ne finit pas par une demi journée, la date de début de l'absence saisie est postérieure à la date de fin réelle de l'absence précédente. | BQ35: ABS_C_020 | BR35: =VLOOKUP(BQ35,'Axe 2 Règles de gestion'!$D$2:$F$354,3, FALSE) -> Si l'absence ne commence pas par une demi-journée et si l'absence précédente ne finit pas par une demi journée, la date de début de l'absence saisie est postérieure à la date de fin prévisionnelle de l'absence précédente. | BS35: ABS_C_026 | BT35: =VLOOKUP(BS35,'Axe 2 Règles de gestion'!$D$2:$F$354,3, FALSE) -> Dans le cas d'un congé autre que CLM, CLD, CGM et CITIS, l'indicateur de requalification doit être à non et les impacts spécifiques à la requalification ne doivent pas être mobilisés ou l'impact rémunération est vide. | BU35: ABS_C_002 | BV35: =VLOOKUP(BU35,'Axe 2 Règles de gestion'!$D$2:$F$354,3, FALSE) -> La date de début du congé/absence doit être postérieure ou égale à la date de début du lien juridique. | BW35: ABS_C_005 | BX35: =VLOOKUP(BW35,'Axe 2 Règles de gestion'!$D$2:$F$354,3, FALSE) -> La date de fin réelle du congé/absence doit être antérieure ou égale à la date limite de fin réelle ou prévisionnelle du lien juridique. | BY35: ABS_C_006 | BZ35: =VLOOKUP(BY35,'Axe 2 Règles de gestion'!$D$2:$F$354,3, FALSE) -> La date de fin prévisionnelle du congé/absence doit être antérieure ou égale à la date limite de fin réelle ou prévisionnelle du lien juridique. | CA35: ABS_C_007 | CB35: =VLOOKUP(CA35,'Axe 2 Règles de gestion'!$D$2:$F$354,3, FALSE) -> La date de fin réelle du congé/absence doit être antérieure à la date limite de départ à la retraite. | CC35: ABS_C_008 | CD35: =VLOOKUP(CC35,'Axe 2 Règles de gestion'!$D$2:$F$354,3, FALSE) -> La date de fin prévisionnelle du congé/absence doit être antérieure à la date limite de départ à la retraite.
A36: 17.10.00 | B36: A | C36: 43152.5 | D36: D0007 | E36: Congés/Absence | F36: S0046 | G36: Autorisations d'absence | H36: E0430 | I36: Autorisation d'absence pour candidature à une élection politique | J36: Type de congé/absence saisi égal 'Autorisation d'absence pour candidature à une élection politique' | K36: A_COA_TYCOAB [Saisi] = 'CA006' | L36: T1091 | M36: Autorisation d'absence pour candidature à une élection politique | N36: Création Modification | Q36: Personnel civil payé à l'acte ou à la tâche | R36: P0054 | S36: N | T36: Particulier | U36: Exclu | V36: 40725
A37: 17.10.00 | B37: A | C37: 43152.5 | D37: D0007 | E37: Congés/Absence | F37: S0046 | G37: Autorisations d'absence | H37: E0430 | I37: Autorisation d'absence pour candidature à une élection politique | J37: Type de congé/absence saisi égal 'Autorisation d'absence pour candidature à une élection politique' | K37: A_COA_TYCOAB [Saisi] = 'CA006' | L37: T1091 | M37: Autorisation d'absence pour candidature à une élection politique | N37: Création Modification | Q37: Volontaire International | R37: P0178 | S37: N | T37: Particulier | U37: Exclu | V37: 40725
A38: 17.10.00 | B38: A | C38: 43152.5 | D38: D0007 | E38: Congés/Absence | F38: S0046 | G38: Autorisations d'absence | H38: E0430 | I38: Autorisation d'absence pour candidature à une élection politique | J38: Type de congé/absence saisi égal 'Autorisation d'absence pour candidature à une élection politique' | K38: A_COA_TYCOAB [Saisi] = 'CA006' | L38: T1091 | M38: Autorisation d'absence pour candidature à une élection politique | N38: Création Modification | Q38: Volontaire de service civique outre-mer | R38: P0179 | S38: N | T38: Particulier | U38: Exclu | V38: 40725
A39: 22.10.00 | B39: M | C39: 44929.465 | D39: D0007 | E39: Congés/Absence | F39: S0046 | G39: Autorisations d'absence | H39: E0431 | I39: Autorisation d'absence au profit des administrateurs de mutuelle | J39: Type de congé/absence saisi égal 'Autorisation d'absence au profit des administrateurs de mutuelle' | K39: A_COA_TYCOAB [Saisi] = 'CA011' | L39: T1092 | M39: Autorisation d'absence au profit des administrateurs de mutuelle | N39: Création Modification | Q39: Titulaire ou magistrat | R39: P0001 | S39: T | T39: Général | U39: Passant | V39: 40725 | X39: ADI_I_123 ET ADI_I_124 ET ADI_I_125 ET ABS_C_010 ET ABS_C_001 ET ABS_C_003 ET ABS_C_004 ET ABS_C_007 ET ABS_C_008 ET ABS_C_009 ET ABS_C_019 ET ABS_C_020 ET ABS_C_026 | Y39: ADI_I_123 | Z39: =VLOOKUP(Y39,'Axe 2 Règles de gestion'!$D$2:$F$354,3, FALSE) -> L'agent doit être membre d'un conseil d'administration d'une mutuelle, union ou fédération. | AA39: ADI_I_124 | AB39: =VLOOKUP(AA39,'Axe 2 Règles de gestion'!$D$2:$F$354,3, FALSE) -> Des autorisations d'absence sont accordées à l'agent pour se rendre et participer aux séances du conseil ou des commissions. | AC39: ADI_I_125 | AD39: =VLOOKUP(AC39,'Axe 2 Règles de gestion'!$D$2:$F$354,3, FALSE) -> L'agent doit informer l'administration de la séance dès qu'il en a connaissance. | BG39: ABS_C_010 | BH39: =VLOOKUP(BG39,'Axe 2 Règles de gestion'!$D$2:$F$354,3, FALSE) -> L'agent doit être en activité. | BI39: ABS_C_001 | BJ39: =VLOOKUP(BI39,'Axe 2 Règles de gestion'!$D$2:$F$354,3, FALSE) -> La date de début du congé/absence doit être postérieure ou égale à la date de recrutement dans la FPE ou dans la carrière militaire. | BK39: ABS_C_003 | BL39: =VLOOKUP(BK39,'Axe 2 Règles de gestion'!$D$2:$F$354,3, FALSE) -> La date de début du congé/absence doit être antérieure ou égale à la date de fin réelle du congé/absence. | BM39: ABS_C_004 | BN39: =VLOOKUP(BM39,'Axe 2 Règles de gestion'!$D$2:$F$354,3, FALSE) -> La date de début du congé/absence doit être antérieure ou égale à la date de fin prévisionnelle du congé/absence. | BO39: ABS_C_007 | BP39: =VLOOKUP(BO39,'Axe 2 Règles de gestion'!$D$2:$F$354,3, FALSE) -> La date de fin réelle du congé/absence doit être antérieure à la date limite de départ à la retraite. | BQ39: ABS_C_008 | BR39: =VLOOKUP(BQ39,'Axe 2 Règles de gestion'!$D$2:$F$354,3, FALSE) -> La date de fin prévisionnelle du congé/absence doit être antérieure à la date limite de départ à la retraite. | BS39: ABS_C_009 | BT39: =VLOOKUP(BS39,'Axe 2 Règles de gestion'!$D$2:$F$354,3, FALSE) -> La date de fin réelle ou la date de fin prévisionnelle du congé/absence doit être saisie. | BU39: ABS_C_019 | BV39: =VLOOKUP(BU39,'Axe 2 Règles de gestion'!$D$2:$F$354,3, FALSE) -> Si l'absence ne commence pas par une demi-journée et si l'absence précédente ne finit pas par une demi journée, la date de début de l'absence saisie est postérieure à la date de fin réelle de l'absence précédente. | BW39: ABS_C_020 | BX39: =VLOOKUP(BW39,'Axe 2 Règles de gestion'!$D$2:$F$354,3, FALSE) -> Si l'absence ne commence pas par une demi-journée et si l'absence précédente ne finit pas par une demi journée, la date de début de l'absence saisie est postérieure à la date de fin prévisionnelle de l'absence précédente. | BY39: ABS_C_026 | BZ39: =VLOOKUP(BY39,'Axe 2 Règles de gestion'!$D$2:$F$354,3, FALSE) -> Dans le cas d'un congé autre que CLM, CLD, CGM et CITIS, l'indicateur de requalification doit être à non et les impacts spécifiques à la requalification ne doivent pas être mobilisés ou l'impact rémunération est vide.
A40: 22.10.00 | B40: M | C40: 44929.464 | D40: D0007 | E40: Congés/Absence | F40: S0046 | G40: Autorisations d'absence | H40: E0431 | I40: Autorisation d'absence au profit des administrateurs de mutuelle | J40: Type de congé/absence saisi égal 'Autorisation d'absence au profit des administrateurs de mutuelle' | K40: A_COA_TYCOAB [Saisi] = 'CA011' | L40: T1092 | M40: Autorisation d'absence au profit des administrateurs de mutuelle | N40: Création Modification | Q40: Contractuel | R40: P0003 | S40: N | T40: Général | U40: Passant | V40: 40725 | X40: ADI_I_123 ET ADI_I_124 ET ADI_I_125 ET ABS_C_010 ET ABS_C_003 ET ABS_C_004 ET ABS_C_009 ET ABS_C_019 ET ABS_C_020 ET ABS_C_026 ET ABS_C_002 ET ABS_C_005 ET ABS_C_006 ET ABS_C_007 ET ABS_C_008 | Y40: ADI_I_123 | Z40: =VLOOKUP(Y40,'Axe 2 Règles de gestion'!$D$2:$F$354,3, FALSE) -> L'agent doit être membre d'un conseil d'administration d'une mutuelle, union ou fédération. | AA40: ADI_I_124 | AB40: =VLOOKUP(AA40,'Axe 2 Règles de gestion'!$D$2:$F$354,3, FALSE) -> Des autorisations d'absence sont accordées à l'agent pour se rendre et participer aux séances du conseil ou des commissions. | AC40: ADI_I_125 | AD40: =VLOOKUP(AC40,'Axe 2 Règles de gestion'!$D$2:$F$354,3, FALSE) -> L'agent doit informer l'administration de la séance dès qu'il en a connaissance. | BG40: ABS_C_010 | BH40: =VLOOKUP(BG40,'Axe 2 Règles de gestion'!$D$2:$F$354,3, FALSE) -> L'agent doit être en activité. | BI40: ABS_C_003 | BJ40: =VLOOKUP(BI40,'Axe 2 Règles de gestion'!$D$2:$F$354,3, FALSE) -> La date de début du congé/absence doit être antérieure ou égale à la date de fin réelle du congé/absence. | BK40: ABS_C_004 | BL40: =VLOOKUP(BK40,'Axe 2 Règles de gestion'!$D$2:$F$354,3, FALSE) -> La date de début du congé/absence doit être antérieure ou égale à la date de fin prévisionnelle du congé/absence. | BM40: ABS_C_009 | BN40: =VLOOKUP(BM40,'Axe 2 Règles de gestion'!$D$2:$F$354,3, FALSE) -> La date de fin réelle ou la date de fin prévisionnelle du congé/absence doit être saisie. | BO40: ABS_C_019 | BP40: =VLOOKUP(BO40,'Axe 2 Règles de gestion'!$D$2:$F$354,3, FALSE) -> Si l'absence ne commence pas par une demi-journée et si l'absence précédente ne finit pas par une demi journée, la date de début de l'absence saisie est postérieure à la date de fin réelle de l'absence précédente. | BQ40: ABS_C_020 | BR40: =VLOOKUP(BQ40,'Axe 2 Règles de gestion'!$D$2:$F$354,3, FALSE) -> Si l'absence ne commence pas par une demi-journée et si l'absence précédente ne finit pas par une demi journée, la date de début de l'absence saisie est postérieure à la date de fin prévisionnelle de l'absence précédente. | BS40: ABS_C_026 | BT40: =VLOOKUP(BS40,'Axe 2 Règles de gestion'!$D$2:$F$354,3, FALSE) -> Dans le cas d'un congé autre que CLM, CLD, CGM et CITIS, l'indicateur de requalification doit être à non et les impacts spécifiques à la requalification ne doivent pas être mobilisés ou l'impact rémunération est vide. | BU40: ABS_C_002 | BV40: =VLOOKUP(BU40,'Axe 2 Règles de gestion'!$D$2:$F$354,3, FALSE) -> La date de début du congé/absence doit être postérieure ou égale à la date de début du lien juridique. | BW40: ABS_C_005 | BX40: =VLOOKUP(BW40,'Axe 2 Règles de gestion'!$D$2:$F$354,3, FALSE) -> La date de fin réelle du congé/absence doit être antérieure ou égale à la date limite de fin réelle ou prévisionnelle du lien juridique. | BY40: ABS_C_006 | BZ40: =VLOOKUP(BY40,'Axe 2 Règles de gestion'!$D$2:$F$354,3, FALSE) -> La date de fin prévisionnelle du congé/absence doit être antérieure ou égale à la date limite de fin réelle ou prévisionnelle du lien juridique. | CA40: ABS_C_007 | CB40: =VLOOKUP(CA40,'Axe 2 Règles de gestion'!$D$2:$F$354,3, FALSE) -> La date de fin réelle du congé/absence doit être antérieure à la date limite de départ à la retraite. | CC40: ABS_C_008 | CD40: =VLOOKUP(CC40,'Axe 2 Règles de gestion'!$D$2:$F$354,3, FALSE) -> La date de fin prévisionnelle du congé/absence doit être antérieure à la date limite de départ à la retraite.
A41: 22.10.00 | B41: M | C41: 44929.465 | D41: D0007 | E41: Congés/Absence | F41: S0046 | G41: Autorisations d'absence | H41: E0431 | I41: Autorisation d'absence au profit des administrateurs de mutuelle | J41: Type de congé/absence saisi égal 'Autorisation d'absence au profit des administrateurs de mutuelle' | K41: A_COA_TYCOAB [Saisi] = 'CA011' | L41: T1092 | M41: Autorisation d'absence au profit des administrateurs de mutuelle | N41: Création Modification | Q41: Stagiaire ou auditeur ou élève | R41: P0004 | S41: S | T41: Général | U41: Passant | V41: 40725 | X41: ADI_I_123 ET ADI_I_124 ET ADI_I_125 ET ABS_C_010 ET ABS_C_001 ET ABS_C_003 ET ABS_C_004 ET ABS_C_007 ET ABS_C_008 ET ABS_C_009 ET ABS_C_019 ET ABS_C_020 ET ABS_C_026 | Y41: ADI_I_123 | Z41: =VLOOKUP(Y41,'Axe 2 Règles de gestion'!$D$2:$F$354,3, FALSE) -> L'agent doit être membre d'un conseil d'administration d'une mutuelle, union ou fédération. | AA41: ADI_I_124 | AB41: =VLOOKUP(AA41,'Axe 2 Règles de gestion'!$D$2:$F$354,3, FALSE) -> Des autorisations d'absence sont accordées à l'agent pour se rendre et participer aux séances du conseil ou des commissions. | AC41: ADI_I_125 | AD41: =VLOOKUP(AC41,'Axe 2 Règles de gestion'!$D$2:$F$354,3, FALSE) -> L'agent doit informer l'administration de la séance dès qu'il en a connaissance. | BG41: ABS_C_010 | BH41: =VLOOKUP(BG41,'Axe 2 Règles de gestion'!$D$2:$F$354,3, FALSE) -> L'agent doit être en activité. | BI41: ABS_C_001 | BJ41: =VLOOKUP(BI41,'Axe 2 Règles de gestion'!$D$2:$F$354,3, FALSE) -> La date de début du congé/absence doit être postérieure ou égale à la date de recrutement dans la FPE ou dans la carrière militaire. | BK41: ABS_C_003 | BL41: =VLOOKUP(BK41,'Axe 2 Règles de gestion'!$D$2:$F$354,3, FALSE) -> La date de début du congé/absence doit être antérieure ou égale à la date de fin réelle du congé/absence. | BM41: ABS_C_004 | BN41: =VLOOKUP(BM41,'Axe 2 Règles de gestion'!$D$2:$F$354,3, FALSE) -> La date de début du congé/absence doit être antérieure ou égale à la date de fin prévisionnelle du congé/absence. | BO41: ABS_C_007 | BP41: =VLOOKUP(BO41,'Axe 2 Règles de gestion'!$D$2:$F$354,3, FALSE) -> La date de fin réelle du congé/absence doit être antérieure à la date limite de départ à la retraite. | BQ41: ABS_C_008 | BR41: =VLOOKUP(BQ41,'Axe 2 Règles de gestion'!$D$2:$F$354,3, FALSE) -> La date de fin prévisionnelle du congé/absence doit être antérieure à la date limite de départ à la retraite. | BS41: ABS_C_009 | BT41: =VLOOKUP(BS41,'Axe 2 Règles de gestion'!$D$2:$F$354,3, FALSE) -> La date de fin réelle ou la date de fin prévisionnelle du congé/absence doit être saisie. | BU41: ABS_C_019 | BV41: =VLOOKUP(BU41,'Axe 2 Règles de gestion'!$D$2:$F$354,3, FALSE) -> Si l'absence ne commence pas par une demi-journée et si l'absence précédente ne finit pas par une demi journée, la date de début de l'absence saisie est postérieure à la date de fin réelle de l'absence précédente. | BW41: ABS_C_020 | BX41: =VLOOKUP(BW41,'Axe 2 Règles de gestion'!$D$2:$F$354,3, FALSE) -> Si l'absence ne commence pas par une demi-journée et si l'absence précédente ne finit pas par une demi journée, la date de début de l'absence saisie est postérieure à la date de fin prévisionnelle de l'absence précédente. | BY41: ABS_C_026 | BZ41: =VLOOKUP(BY41,'Axe 2 Règles de gestion'!$D$2:$F$354,3, FALSE) -> Dans le cas d'un congé autre que CLM, CLD, CGM et CITIS, l'indicateur de requalification doit être à non et les impacts spécifiques à la requalification ne doivent pas être mobilisés ou l'impact rémunération est vide.
A42: 22.10.00 | B42: M | C42: 44929.465 | D42: D0007 | E42: Congés/Absence | F42: S0046 | G42: Autorisations d'absence | H42: E0431 | I42: Autorisation d'absence au profit des administrateurs de mutuelle | J42: Type de congé/absence saisi égal 'Autorisation d'absence au profit des administrateurs de mutuelle' | K42: A_COA_TYCOAB [Saisi] = 'CA011' | L42: T1092 | M42: Autorisation d'absence au profit des administrateurs de mutuelle | N42: Création Modification | Q42: Ouvrier d'état | R42: P0005 | S42: O | T42: Général | U42: Passant | V42: 40725 | X42: ADI_I_123 ET ADI_I_124 ET ADI_I_125 ET ABS_C_010 ET ABS_C_003 ET ABS_C_004 ET ABS_C_009 ET ABS_C_019 ET ABS_C_020 ET ABS_C_026 ET ABS_C_002 ET ABS_C_005 ET ABS_C_006 ET ABS_C_007 ET ABS_C_008 | Y42: ADI_I_123 | Z42: =VLOOKUP(Y42,'Axe 2 Règles de gestion'!$D$2:$F$354,3, FALSE) -> L'agent doit être membre d'un conseil d'administration d'une mutuelle, union ou fédération. | AA42: ADI_I_124 | AB42: =VLOOKUP(AA42,'Axe 2 Règles de gestion'!$D$2:$F$354,3, FALSE) -> Des autorisations d'absence sont accordées à l'agent pour se rendre et participer aux séances du conseil ou des commissions. | AC42: ADI_I_125 | AD42: =VLOOKUP(AC42,'Axe 2 Règles de gestion'!$D$2:$F$354,3, FALSE) -> L'agent doit informer l'administration de la séance dès qu'il en a connaissance. | BG42: ABS_C_010 | BH42: =VLOOKUP(BG42,'Axe 2 Règles de gestion'!$D$2:$F$354,3, FALSE) -> L'agent doit être en activité. | BI42: ABS_C_003 | BJ42: =VLOOKUP(BI42,'Axe 2 Règles de gestion'!$D$2:$F$354,3, FALSE) -> La date de début du congé/absence doit être antérieure ou égale à la date de fin réelle du congé/absence. | BK42: ABS_C_004 | BL42: =VLOOKUP(BK42,'Axe 2 Règles de gestion'!$D$2:$F$354,3, FALSE) -> La date de début du congé/absence doit être antérieure ou égale à la date de fin prévisionnelle du congé/absence. | BM42: ABS_C_009 | BN42: =VLOOKUP(BM42,'Axe 2 Règles de gestion'!$D$2:$F$354,3, FALSE) -> La date de fin réelle ou la date de fin prévisionnelle du congé/absence doit être saisie. | BO42: ABS_C_019 | BP42: =VLOOKUP(BO42,'Axe 2 Règles de gestion'!$D$2:$F$354,3, FALSE) -> Si l'absence ne commence pas par une demi-journée et si l'absence précédente ne finit pas par une demi journée, la date de début de l'absence saisie est postérieure à la date de fin réelle de l'absence précédente. | BQ42: ABS_C_020 | BR42: =VLOOKUP(BQ42,'Axe 2 Règles de gestion'!$D$2:$F$354,3, FALSE) -> Si l'absence ne commence pas par une demi-journée et si l'absence précédente ne finit pas par une demi journée, la date de début de l'absence saisie est postérieure à la date de fin prévisionnelle de l'absence précédente. | BS42: ABS_C_026 | BT42: =VLOOKUP(BS42,'Axe 2 Règles de gestion'!$D$2:$F$354,3, FALSE) -> Dans le cas d'un congé autre que CLM, CLD, CGM et CITIS, l'indicateur de requalification doit être à non et les impacts spécifiques à la requalification ne doivent pas être mobilisés ou l'impact rémunération est vide. | BU42: ABS_C_002 | BV42: =VLOOKUP(BU42,'Axe 2 Règles de gestion'!$D$2:$F$354,3, FALSE) -> La date de début du congé/absence doit être postérieure ou égale à la date de début du lien juridique. | BW42: ABS_C_005 | BX42: =VLOOKUP(BW42,'Axe 2 Règles de gestion'!$D$2:$F$354,3, FALSE) -> La date de fin réelle du congé/absence doit être antérieure ou égale à la date limite de fin réelle ou prévisionnelle du lien juridique. | BY42: ABS_C_006 | BZ42: =VLOOKUP(BY42,'Axe 2 Règles de gestion'!$D$2:$F$354,3, FALSE) -> La date de fin prévisionnelle du congé/absence doit être antérieure ou égale à la date limite de fin réelle ou prévisionnelle du lien juridique. | CA42: ABS_C_007 | CB42: =VLOOKUP(CA42,'Axe 2 Règles de gestion'!$D$2:$F$354,3, FALSE) -> La date de fin réelle du congé/absence doit être antérieure à la date limite de départ à la retraite. | CC42: ABS_C_008 | CD42: =VLOOKUP(CC42,'Axe 2 Règles de gestion'!$D$2:$F$354,3, FALSE) -> La date de fin prévisionnelle du congé/absence doit être antérieure à la date limite de départ à la retraite.
A43: 17.10.00 | B43: A | C43: 43152.5 | D43: D0007 | E43: Congés/Absence | F43: S0046 | G43: Autorisations d'absence | H43: E0431 | I43: Autorisation d'absence au profit des administrateurs de mutuelle | J43: Type de congé/absence saisi égal 'Autorisation d'absence au profit des administrateurs de mutuelle' | K43: A_COA_TYCOAB [Saisi] = 'CA011' | L43: T1092 | M43: Autorisation d'absence au profit des administrateurs de mutuelle | N43: Création Modification | Q43: Personnel civil payé à l'acte ou à la tâche | R43: P0054 | S43: N | T43: Particulier | U43: Exclu | V43: 40725
A44: 17.10.00 | B44: A | C44: 43152.5 | D44: D0007 | E44: Congés/Absence | F44: S0046 | G44: Autorisations d'absence | H44: E0431 | I44: Autorisation d'absence au profit des administrateurs de mutuelle | J44: Type de congé/absence saisi égal 'Autorisation d'absence au profit des administrateurs de mutuelle' | K44: A_COA_TYCOAB [Saisi] = 'CA011' | L44: T1092 | M44: Autorisation d'absence au profit des administrateurs de mutuelle | N44: Création Modification | Q44: Contractuel de droit privé | R44: P0072 | S44: N | T44: Particulier | U44: Exclu | V44: 40725
A45: 17.10.00 | B45: A | C45: 43152.5 | D45: D0007 | E45: Congés/Absence | F45: S0046 | G45: Autorisations d'absence | H45: E0431 | I45: Autorisation d'absence au profit des administrateurs de mutuelle | J45: Type de congé/absence saisi égal 'Autorisation d'absence au profit des administrateurs de mutuelle' | K45: A_COA_TYCOAB [Saisi] = 'CA011' | L45: T1092 | M45: Autorisation d'absence au profit des administrateurs de mutuelle | N45: Création Modification | Q45: Volontaire International | R45: P0178 | S45: N | T45: Particulier | U45: Exclu | V45: 40725
A46: 17.10.00 | B46: A | C46: 43152.5 | D46: D0007 | E46: Congés/Absence | F46: S0046 | G46: Autorisations d'absence | H46: E0431 | I46: Autorisation d'absence au profit des administrateurs de mutuelle | J46: Type de congé/absence saisi égal 'Autorisation d'absence au profit des administrateurs de mutuelle' | K46: A_COA_TYCOAB [Saisi] = 'CA011' | L46: T1092 | M46: Autorisation d'absence au profit des administrateurs de mutuelle | N46: Création Modification | Q46: Volontaire de service civique outre-mer | R46: P0179 | S46: N | T46: Particulier | U46: Exclu | V46: 40725
A47: 22.10.00 | B47: M | C47: 44917.636 | D47: D0007 | E47: Congés/Absence | F47: S0046 | G47: Autorisations d'absence | H47: E0432 | I47: Autorisation d'absence pour fêtes et cérémonies religieuses | J47: Type de congé/absence saisi égal 'Autorisation d'absence pour fêtes et cérémonies religieuses' | K47: A_COA_TYCOAB [Saisi] = 'CA012' | L47: T1093 | M47: Autorisation d'absence pour fêtes et cérémonies religieuses | N47: Création Modification | Q47: Titulaire ou magistrat | R47: P0001 | S47: T | T47: Général | U47: Passant | V47: 40725 | W47: 40949 | X47: ABS_C_010 ET ABS_C_001 ET ABS_C_003 ET ABS_C_004 ET ABS_C_007 ET ABS_C_008 ET ABS_C_009 ET ABS_C_019 ET ABS_C_020 ET ABS_C_026 | BG47: ABS_C_010 | BH47: =VLOOKUP(BG47,'Axe 2 Règles de gestion'!$D$2:$F$354,3, FALSE) -> L'agent doit être en activité. | BI47: ABS_C_001 | BJ47: =VLOOKUP(BI47,'Axe 2 Règles de gestion'!$D$2:$F$354,3, FALSE) -> La date de début du congé/absence doit être postérieure ou égale à la date de recrutement dans la FPE ou dans la carrière militaire. | BK47: ABS_C_003 | BL47: =VLOOKUP(BK47,'Axe 2 Règles de gestion'!$D$2:$F$354,3, FALSE) -> La date de début du congé/absence doit être antérieure ou égale à la date de fin réelle du congé/absence. | BM47: ABS_C_004 | BN47: =VLOOKUP(BM47,'Axe 2 Règles de gestion'!$D$2:$F$354,3, FALSE) -> La date de début du congé/absence doit être antérieure ou égale à la date de fin prévisionnelle du congé/absence. | BO47: ABS_C_007 | BP47: =VLOOKUP(BO47,'Axe 2 Règles de gestion'!$D$2:$F$354,3, FALSE) -> La date de fin réelle du congé/absence doit être antérieure à la date limite de départ à la retraite. | BQ47: ABS_C_008 | BR47: =VLOOKUP(BQ47,'Axe 2 Règles de gestion'!$D$2:$F$354,3, FALSE) -> La date de fin prévisionnelle du congé/absence doit être antérieure à la date limite de départ à la retraite. | BS47: ABS_C_009 | BT47: =VLOOKUP(BS47,'Axe 2 Règles de gestion'!$D$2:$F$354,3, FALSE) -> La date de fin réelle ou la date de fin prévisionnelle du congé/absence doit être saisie. | BU47: ABS_C_019 | BV47: =VLOOKUP(BU47,'Axe 2 Règles de gestion'!$D$2:$F$354,3, FALSE) -> Si l'absence ne commence pas par une demi-journée et si l'absence précédente ne finit pas par une demi journée, la date de début de l'absence saisie est postérieure à la date de fin réelle de l'absence précédente. | BW47: ABS_C_020 | BX47: =VLOOKUP(BW47,'Axe 2 Règles de gestion'!$D$2:$F$354,3, FALSE) -> Si l'absence ne commence pas par une demi-journée et si l'absence précédente ne finit pas par une demi journée, la date de début de l'absence saisie est postérieure à la date de fin prévisionnelle de l'absence précédente. | BY47: ABS_C_026 | BZ47: =VLOOKUP(BY47,'Axe 2 Règles de gestion'!$D$2:$F$354,3, FALSE) -> Dans le cas d'un congé autre que CLM, CLD, CGM et CITIS, l'indicateur de requalification doit être à non et les impacts spécifiques à la requalification ne doivent pas être mobilisés ou l'impact rémunération est vide.
A48: 22.10.00 | B48: A | C48: 44917.636 | D48: D0007 | E48: Congés/Absence | F48: S0046 | G48: Autorisations d'absence | H48: E0432 | I48: Autorisation d'absence pour fêtes et cérémonies religieuses | J48: Type de congé/absence saisi égal 'Autorisation d'absence pour fêtes et cérémonies religieuses' | K48: A_COA_TYCOAB [Saisi] = 'CA012' | L48: T1093 | M48: Autorisation d'absence pour fêtes et cérémonies religieuses | N48: Création Modification | Q48: Titulaire ou magistrat | R48: P0001 | S48: T | T48: Général | U48: Passant | V48: 40950 | X48: ADI_I_114 ET ADI_I_115 ET ABS_C_010 ET ABS_C_001 ET ABS_C_003 ET ABS_C_004 ET ABS_C_007 ET ABS_C_008 ET ABS_C_009 ET ABS_C_019 ET ABS_C_020 ET ABS_C_026 | Y48: ADI_I_114 | Z48: =VLOOKUP(Y48,'Axe 2 Règles de gestion'!$D$2:$F$354,3, FALSE) -> L'agent doit effectuer une demande. | AA48: ADI_I_115 | AB48: =VLOOKUP(AA48,'Axe 2 Règles de gestion'!$D$2:$F$354,3, FALSE) -> L'autorisation d'absence doit être compatible avec le fonctionnement normal du service. | BG48: ABS_C_010 | BH48: =VLOOKUP(BG48,'Axe 2 Règles de gestion'!$D$2:$F$354,3, FALSE) -> L'agent doit être en activité. | BI48: ABS_C_001 | BJ48: =VLOOKUP(BI48,'Axe 2 Règles de gestion'!$D$2:$F$354,3, FALSE) -> La date de début du congé/absence doit être postérieure ou égale à la date de recrutement dans la FPE ou dans la carrière militaire. | BK48: ABS_C_003 | BL48: =VLOOKUP(BK48,'Axe 2 Règles de gestion'!$D$2:$F$354,3, FALSE) -> La date de début du congé/absence doit être antérieure ou égale à la date de fin réelle du congé/absence. | BM48: ABS_C_004 | BN48: =VLOOKUP(BM48,'Axe 2 Règles de gestion'!$D$2:$F$354,3, FALSE) -> La date de début du congé/absence doit être antérieure ou égale à la date de fin prévisionnelle du congé/absence. | BO48: ABS_C_007 | BP48: =VLOOKUP(BO48,'Axe 2 Règles de gestion'!$D$2:$F$354,3, FALSE) -> La date de fin réelle du congé/absence doit être antérieure à la date limite de départ à la retraite. | BQ48: ABS_C_008 | BR48: =VLOOKUP(BQ48,'Axe 2 Règles de gestion'!$D$2:$F$354,3, FALSE) -> La date de fin prévisionnelle du congé/absence doit être antérieure à la date limite de départ à la retraite. | BS48: ABS_C_009 | BT48: =VLOOKUP(BS48,'Axe 2 Règles de gestion'!$D$2:$F$354,3, FALSE) -> La date de fin réelle ou la date de fin prévisionnelle du congé/absence doit être saisie. | BU48: ABS_C_019 | BV48: =VLOOKUP(BU48,'Axe 2 Règles de gestion'!$D$2:$F$354,3, FALSE) -> Si l'absence ne commence pas par une demi-journée et si l'absence précédente ne finit pas par une demi journée, la date de début de l'absence saisie est postérieure à la date de fin réelle de l'absence précédente. | BW48: ABS_C_020 | BX48: =VLOOKUP(BW48,'Axe 2 Règles de gestion'!$D$2:$F$354,3, FALSE) -> Si l'absence ne commence pas par une demi-journée et si l'absence précédente ne finit pas par une demi journée, la date de début de l'absence saisie est postérieure à la date de fin prévisionnelle de l'absence précédente. | BY48: ABS_C_026 | BZ48: =VLOOKUP(BY48,'Axe 2 Règles de gestion'!$D$2:$F$354,3, FALSE) -> Dans le cas d'un congé autre que CLM, CLD, CGM et CITIS, l'indicateur de requalification doit être à non et les impacts spécifiques à la requalification ne doivent pas être mobilisés ou l'impact rémunération est vide.
A49: 22.10.00 | B49: M | C49: 44917.644 | D49: D0007 | E49: Congés/Absence | F49: S0046 | G49: Autorisations d'absence | H49: E0432 | I49: Autorisation d'absence pour fêtes et cérémonies religieuses | J49: Type de congé/absence saisi égal 'Autorisation d'absence pour fêtes et cérémonies religieuses' | K49: A_COA_TYCOAB [Saisi] = 'CA012' | L49: T1093 | M49: Autorisation d'absence pour fêtes et cérémonies religieuses | N49: Création Modification | Q49: Contractuel | R49: P0003 | S49: N | T49: Général | U49: Passant | V49: 40725 | W49: 40949 | X49: ABS_C_010 ET ABS_C_003 ET ABS_C_004 ET ABS_C_009 ET ABS_C_019 ET ABS_C_020 ET ABS_C_026 ET ABS_C_002 ET ABS_C_005 ET ABS_C_006 ET ABS_C_007 ET ABS_C_008 | BG49: ABS_C_010 | BH49: =VLOOKUP(BG49,'Axe 2 Règles de gestion'!$D$2:$F$354,3, FALSE) -> L'agent doit être en activité. | BI49: ABS_C_003 | BJ49: =VLOOKUP(BI49,'Axe 2 Règles de gestion'!$D$2:$F$354,3, FALSE) -> La date de début du congé/absence doit être antérieure ou égale à la date de fin réelle du congé/absence. | BK49: ABS_C_004 | BL49: =VLOOKUP(BK49,'Axe 2 Règles de gestion'!$D$2:$F$354,3, FALSE) -> La date de début du congé/absence doit être antérieure ou égale à la date de fin prévisionnelle du congé/absence. | BM49: ABS_C_009 | BN49: =VLOOKUP(BM49,'Axe 2 Règles de gestion'!$D$2:$F$354,3, FALSE) -> La date de fin réelle ou la date de fin prévisionnelle du congé/absence doit être saisie. | BO49: ABS_C_019 | BP49: =VLOOKUP(BO49,'Axe 2 Règles de gestion'!$D$2:$F$354,3, FALSE) -> Si l'absence ne commence pas par une demi-journée et si l'absence précédente ne finit pas par une demi journée, la date de début de l'absence saisie est postérieure à la date de fin réelle de l'absence précédente. | BQ49: ABS_C_020 | BR49: =VLOOKUP(BQ49,'Axe 2 Règles de gestion'!$D$2:$F$354,3, FALSE) -> Si l'absence ne commence pas par une demi-journée et si l'absence précédente ne finit pas par une demi journée, la date de début de l'absence saisie est postérieure à la date de fin prévisionnelle de l'absence précédente. | BS49: ABS_C_026 | BT49: =VLOOKUP(BS49,'Axe 2 Règles de gestion'!$D$2:$F$354,3, FALSE) -> Dans le cas d'un congé autre que CLM, CLD, CGM et CITIS, l'indicateur de requalification doit être à non et les impacts spécifiques à la requalification ne doivent pas être mobilisés ou l'impact rémunération est vide. | BU49: ABS_C_002 | BV49: =VLOOKUP(BU49,'Axe 2 Règles de gestion'!$D$2:$F$354,3, FALSE) -> La date de début du congé/absence doit être postérieure ou égale à la date de début du lien juridique. | BW49: ABS_C_005 | BX49: =VLOOKUP(BW49,'Axe 2 Règles de gestion'!$D$2:$F$354,3, FALSE) -> La date de fin réelle du congé/absence doit être antérieure ou égale à la date limite de fin réelle ou prévisionnelle du lien juridique. | BY49: ABS_C_006 | BZ49: =VLOOKUP(BY49,'Axe 2 Règles de gestion'!$D$2:$F$354,3, FALSE) -> La date de fin prévisionnelle du congé/absence doit être antérieure ou égale à la date limite de fin réelle ou prévisionnelle du lien juridique. | CA49: ABS_C_007 | CB49: =VLOOKUP(CA49,'Axe 2 Règles de gestion'!$D$2:$F$354,3, FALSE) -> La date de fin réelle du congé/absence doit être antérieure à la date limite de départ à la retraite. | CC49: ABS_C_008 | CD49: =VLOOKUP(CC49,'Axe 2 Règles de gestion'!$D$2:$F$354,3, FALSE) -> La date de fin prévisionnelle du congé/absence doit être antérieure à la date limite de départ à la retraite.
A50: 22.10.00 | B50: A | C50: 44917.644 | D50: D0007 | E50: Congés/Absence | F50: S0046 | G50: Autorisations d'absence | H50: E0432 | I50: Autorisation d'absence pour fêtes et cérémonies religieuses | J50: Type de congé/absence saisi égal 'Autorisation d'absence pour fêtes et cérémonies religieuses' | K50: A_COA_TYCOAB [Saisi] = 'CA012' | L50: T1093 | M50: Autorisation d'absence pour fêtes et cérémonies religieuses | N50: Création Modification | Q50: Contractuel | R50: P0003 | S50: N | T50: Général | U50: Passant | V50: 40950 | X50: ADI_I_114 ET ADI_I_115 ET ABS_C_010 ET ABS_C_003 ET ABS_C_004 ET ABS_C_009 ET ABS_C_019 ET ABS_C_020 ET ABS_C_026 ET ABS_C_002 ET ABS_C_005 ET ABS_C_006 ET ABS_C_007 ET ABS_C_008 | Y50: ADI_I_114 | Z50: =VLOOKUP(Y50,'Axe 2 Règles de gestion'!$D$2:$F$354,3, FALSE) -> L'agent doit effectuer une demande. | AA50: ADI_I_115 | AB50: =VLOOKUP(AA50,'Axe 2 Règles de gestion'!$D$2:$F$354,3, FALSE) -> L'autorisation d'absence doit être compatible avec le fonctionnement normal du service. | BG50: ABS_C_010 | BH50: =VLOOKUP(BG50,'Axe 2 Règles de gestion'!$D$2:$F$354,3, FALSE) -> L'agent doit être en activité. | BI50: ABS_C_003 | BJ50: =VLOOKUP(BI50,'Axe 2 Règles de gestion'!$D$2:$F$354,3, FALSE) -> La date de début du congé/absence doit être antérieure ou égale à la date de fin réelle du congé/absence. | BK50: ABS_C_004 | BL50: =VLOOKUP(BK50,'Axe 2 Règles de gestion'!$D$2:$F$354,3, FALSE) -> La date de début du congé/absence doit être antérieure ou égale à la date de fin prévisionnelle du congé/absence. | BM50: ABS_C_009 | BN50: =VLOOKUP(BM50,'Axe 2 Règles de gestion'!$D$2:$F$354,3, FALSE) -> La date de fin réelle ou la date de fin prévisionnelle du congé/absence doit être saisie. | BO50: ABS_C_019 | BP50: =VLOOKUP(BO50,'Axe 2 Règles de gestion'!$D$2:$F$354,3, FALSE) -> Si l'absence ne commence pas par une demi-journée et si l'absence précédente ne finit pas par une demi journée, la date de début de l'absence saisie est postérieure à la date de fin réelle de l'absence précédente. | BQ50: ABS_C_020 | BR50: =VLOOKUP(BQ50,'Axe 2 Règles de gestion'!$D$2:$F$354,3, FALSE) -> Si l'absence ne commence pas par une demi-journée et si l'absence précédente ne finit pas par une demi journée, la date de début de l'absence saisie est postérieure à la date de fin prévisionnelle de l'absence précédente. | BS50: ABS_C_026 | BT50: =VLOOKUP(BS50,'Axe 2 Règles de gestion'!$D$2:$F$354,3, FALSE) -> Dans le cas d'un congé autre que CLM, CLD, CGM et CITIS, l'indicateur de requalification doit être à non et les impacts spécifiques à la requalification ne doivent pas être mobilisés ou l'impact rémunération est vide. | BU50: ABS_C_002 | BV50: =VLOOKUP(BU50,'Axe 2 Règles de gestion'!$D$2:$F$354,3, FALSE) -> La date de début du congé/absence doit être postérieure ou égale à la date de début du lien juridique. | BW50: ABS_C_005 | BX50: =VLOOKUP(BW50,'Axe 2 Règles de gestion'!$D$2:$F$354,3, FALSE) -> La date de fin réelle du congé/absence doit être antérieure ou égale à la date limite de fin réelle ou prévisionnelle du lien juridique. | BY50: ABS_C_006 | BZ50: =VLOOKUP(BY50,'Axe 2 Règles de gestion'!$D$2:$F$354,3, FALSE) -> La date de fin prévisionnelle du congé/absence doit être antérieure ou égale à la date limite de fin réelle ou prévisionnelle du lien juridique. | CA50: ABS_C_007 | CB50: =VLOOKUP(CA50,'Axe 2 Règles de gestion'!$D$2:$F$354,3, FALSE) -> La date de fin réelle du congé/absence doit être antérieure à la date limite de départ à la retraite. | CC50: ABS_C_008 | CD50: =VLOOKUP(CC50,'Axe 2 Règles de gestion'!$D$2:$F$354,3, FALSE) -> La date de fin prévisionnelle du congé/absence doit être antérieure à la date limite de départ à la retraite.
A51: 22.10.00 | B51: M | C51: 44917.642 | D51: D0007 | E51: Congés/Absence | F51: S0046 | G51: Autorisations d'absence | H51: E0432 | I51: Autorisation d'absence pour fêtes et cérémonies religieuses | J51: Type de congé/absence saisi égal 'Autorisation d'absence pour fêtes et cérémonies religieuses' | K51: A_COA_TYCOAB [Saisi] = 'CA012' | L51: T1093 | M51: Autorisation d'absence pour fêtes et cérémonies religieuses | N51: Création Modification | Q51: Stagiaire ou auditeur ou élève | R51: P0004 | S51: S | T51: Général | U51: Passant | V51: 40725 | W51: 40949 | X51: ABS_C_010 ET ABS_C_001 ET ABS_C_003 ET ABS_C_004 ET ABS_C_007 ET ABS_C_008 ET ABS_C_009 ET ABS_C_019 ET ABS_C_020 ET ABS_C_026 | BG51: ABS_C_010 | BH51: =VLOOKUP(BG51,'Axe 2 Règles de gestion'!$D$2:$F$354,3, FALSE) -> L'agent doit être en activité. | BI51: ABS_C_001 | BJ51: =VLOOKUP(BI51,'Axe 2 Règles de gestion'!$D$2:$F$354,3, FALSE) -> La date de début du congé/absence doit être postérieure ou égale à la date de recrutement dans la FPE ou dans la carrière militaire. | BK51: ABS_C_003 | BL51: =VLOOKUP(BK51,'Axe 2 Règles de gestion'!$D$2:$F$354,3, FALSE) -> La date de début du congé/absence doit être antérieure ou égale à la date de fin réelle du congé/absence. | BM51: ABS_C_004 | BN51: =VLOOKUP(BM51,'Axe 2 Règles de gestion'!$D$2:$F$354,3, FALSE) -> La date de début du congé/absence doit être antérieure ou égale à la date de fin prévisionnelle du congé/absence. | BO51: ABS_C_007 | BP51: =VLOOKUP(BO51,'Axe 2 Règles de gestion'!$D$2:$F$354,3, FALSE) -> La date de fin réelle du congé/absence doit être antérieure à la date limite de départ à la retraite. | BQ51: ABS_C_008 | BR51: =VLOOKUP(BQ51,'Axe 2 Règles de gestion'!$D$2:$F$354,3, FALSE) -> La date de fin prévisionnelle du congé/absence doit être antérieure à la date limite de départ à la retraite. | BS51: ABS_C_009 | BT51: =VLOOKUP(BS51,'Axe 2 Règles de gestion'!$D$2:$F$354,3, FALSE) -> La date de fin réelle ou la date de fin prévisionnelle du congé/absence doit être saisie. | BU51: ABS_C_019 | BV51: =VLOOKUP(BU51,'Axe 2 Règles de gestion'!$D$2:$F$354,3, FALSE) -> Si l'absence ne commence pas par une demi-journée et si l'absence précédente ne finit pas par une demi journée, la date de début de l'absence saisie est postérieure à la date de fin réelle de l'absence précédente. | BW51: ABS_C_020 | BX51: =VLOOKUP(BW51,'Axe 2 Règles de gestion'!$D$2:$F$354,3, FALSE) -> Si l'absence ne commence pas par une demi-journée et si l'absence précédente ne finit pas par une demi journée, la date de début de l'absence saisie est postérieure à la date de fin prévisionnelle de l'absence précédente. | BY51: ABS_C_026 | BZ51: =VLOOKUP(BY51,'Axe 2 Règles de gestion'!$D$2:$F$354,3, FALSE) -> Dans le cas d'un congé autre que CLM, CLD, CGM et CITIS, l'indicateur de requalification doit être à non et les impacts spécifiques à la requalification ne doivent pas être mobilisés ou l'impact rémunération est vide.
A52: 22.10.00 | B52: A | C52: 44917.642 | D52: D0007 | E52: Congés/Absence | F52: S0046 | G52: Autorisations d'absence | H52: E0432 | I52: Autorisation d'absence pour fêtes et cérémonies religieuses | J52: Type de congé/absence saisi égal 'Autorisation d'absence pour fêtes et cérémonies religieuses' | K52: A_COA_TYCOAB [Saisi] = 'CA012' | L52: T1093 | M52: Autorisation d'absence pour fêtes et cérémonies religieuses | N52: Création Modification | Q52: Stagiaire ou auditeur ou élève | R52: P0004 | S52: S | T52: Général | U52: Passant | V52: 40950 | X52: ADI_I_114 ET ADI_I_115 ET ABS_C_010 ET ABS_C_001 ET ABS_C_003 ET ABS_C_004 ET ABS_C_007 ET ABS_C_008 ET ABS_C_009 ET ABS_C_019 ET ABS_C_020 ET ABS_C_026 | Y52: ADI_I_114 | Z52: =VLOOKUP(Y52,'Axe 2 Règles de gestion'!$D$2:$F$354,3, FALSE) -> L'agent doit effectuer une demande. | AA52: ADI_I_115 | AB52: =VLOOKUP(AA52,'Axe 2 Règles de gestion'!$D$2:$F$354,3, FALSE) -> L'autorisation d'absence doit être compatible avec le fonctionnement normal du service. | BG52: ABS_C_010 | BH52: =VLOOKUP(BG52,'Axe 2 Règles de gestion'!$D$2:$F$354,3, FALSE) -> L'agent doit être en activité. | BI52: ABS_C_001 | BJ52: =VLOOKUP(BI52,'Axe 2 Règles de gestion'!$D$2:$F$354,3, FALSE) -> La date de début du congé/absence doit être postérieure ou égale à la date de recrutement dans la FPE ou dans la carrière militaire. | BK52: ABS_C_003 | BL52: =VLOOKUP(BK52,'Axe 2 Règles de gestion'!$D$2:$F$354,3, FALSE) -> La date de début du congé/absence doit être antérieure ou égale à la date de fin réelle du congé/absence. | BM52: ABS_C_004 | BN52: =VLOOKUP(BM52,'Axe 2 Règles de gestion'!$D$2:$F$354,3, FALSE) -> La date de début du congé/absence doit être antérieure ou égale à la date de fin prévisionnelle du congé/absence. | BO52: ABS_C_007 | BP52: =VLOOKUP(BO52,'Axe 2 Règles de gestion'!$D$2:$F$354,3, FALSE) -> La date de fin réelle du congé/absence doit être antérieure à la date limite de départ à la retraite. | BQ52: ABS_C_008 | BR52: =VLOOKUP(BQ52,'Axe 2 Règles de gestion'!$D$2:$F$354,3, FALSE) -> La date de fin prévisionnelle du congé/absence doit être antérieure à la date limite de départ à la retraite. | BS52: ABS_C_009 | BT52: =VLOOKUP(BS52,'Axe 2 Règles de gestion'!$D$2:$F$354,3, FALSE) -> La date de fin réelle ou la date de fin prévisionnelle du congé/absence doit être saisie. | BU52: ABS_C_019 | BV52: =VLOOKUP(BU52,'Axe 2 Règles de gestion'!$D$2:$F$354,3, FALSE) -> Si l'absence ne commence pas par une demi-journée et si l'absence précédente ne finit pas par une demi journée, la date de début de l'absence saisie est postérieure à la date de fin réelle de l'absence précédente. | BW52: ABS_C_020 | BX52: =VLOOKUP(BW52,'Axe 2 Règles de gestion'!$D$2:$F$354,3, FALSE) -> Si l'absence ne commence pas par une demi-journée et si l'absence précédente ne finit pas par une demi journée, la date de début de l'absence saisie est postérieure à la date de fin prévisionnelle de l'absence précédente. | BY52: ABS_C_026 | BZ52: =VLOOKUP(BY52,'Axe 2 Règles de gestion'!$D$2:$F$354,3, FALSE) -> Dans le cas d'un congé autre que CLM, CLD, CGM et CITIS, l'indicateur de requalification doit être à non et les impacts spécifiques à la requalification ne doivent pas être mobilisés ou l'impact rémunération est vide.
A53: 22.10.00 | B53: M | C53: 44917.644 | D53: D0007 | E53: Congés/Absence | F53: S0046 | G53: Autorisations d'absence | H53: E0432 | I53: Autorisation d'absence pour fêtes et cérémonies religieuses | J53: Type de congé/absence saisi égal 'Autorisation d'absence pour fêtes et cérémonies religieuses' | K53: A_COA_TYCOAB [Saisi] = 'CA012' | L53: T1093 | M53: Autorisation d'absence pour fêtes et cérémonies religieuses | N53: Création Modification | Q53: Ouvrier d'état | R53: P0005 | S53: O | T53: Général | U53: Passant | V53: 40725 | W53: 40949 | X53: ABS_C_010 ET ABS_C_003 ET ABS_C_004 ET ABS_C_009 ET ABS_C_019 ET ABS_C_020 ET ABS_C_026 ET ABS_C_002 ET ABS_C_005 ET ABS_C_006 ET ABS_C_007 ET ABS_C_008 | BG53: ABS_C_010 | BH53: =VLOOKUP(BG53,'Axe 2 Règles de gestion'!$D$2:$F$354,3, FALSE) -> L'agent doit être en activité. | BI53: ABS_C_003 | BJ53: =VLOOKUP(BI53,'Axe 2 Règles de gestion'!$D$2:$F$354,3, FALSE) -> La date de début du congé/absence doit être antérieure ou égale à la date de fin réelle du congé/absence. | BK53: ABS_C_004 | BL53: =VLOOKUP(BK53,'Axe 2 Règles de gestion'!$D$2:$F$354,3, FALSE) -> La date de début du congé/absence doit être antérieure ou égale à la date de fin prévisionnelle du congé/absence. | BM53: ABS_C_009 | BN53: =VLOOKUP(BM53,'Axe 2 Règles de gestion'!$D$2:$F$354,3, FALSE) -> La date de fin réelle ou la date de fin prévisionnelle du congé/absence doit être saisie. | BO53: ABS_C_019 | BP53: =VLOOKUP(BO53,'Axe 2 Règles de gestion'!$D$2:$F$354,3, FALSE) -> Si l'absence ne commence pas par une demi-journée et si l'absence précédente ne finit pas par une demi journée, la date de début de l'absence saisie est postérieure à la date de fin réelle de l'absence précédente. | BQ53: ABS_C_020 | BR53: =VLOOKUP(BQ53,'Axe 2 Règles de gestion'!$D$2:$F$354,3, FALSE) -> Si l'absence ne commence pas par une demi-journée et si l'absence précédente ne finit pas par une demi journée, la date de début de l'absence saisie est postérieure à la date de fin prévisionnelle de l'absence précédente. | BS53: ABS_C_026 | BT53: =VLOOKUP(BS53,'Axe 2 Règles de gestion'!$D$2:$F$354,3, FALSE) -> Dans le cas d'un congé autre que CLM, CLD, CGM et CITIS, l'indicateur de requalification doit être à non et les impacts spécifiques à la requalification ne doivent pas être mobilisés ou l'impact rémunération est vide. | BU53: ABS_C_002 | BV53: =VLOOKUP(BU53,'Axe 2 Règles de gestion'!$D$2:$F$354,3, FALSE) -> La date de début du congé/absence doit être postérieure ou égale à la date de début du lien juridique. | BW53: ABS_C_005 | BX53: =VLOOKUP(BW53,'Axe 2 Règles de gestion'!$D$2:$F$354,3, FALSE) -> La date de fin réelle du congé/absence doit être antérieure ou égale à la date limite de fin réelle ou prévisionnelle du lien juridique. | BY53: ABS_C_006 | BZ53: =VLOOKUP(BY53,'Axe 2 Règles de gestion'!$D$2:$F$354,3, FALSE) -> La date de fin prévisionnelle du congé/absence doit être antérieure ou égale à la date limite de fin réelle ou prévisionnelle du lien juridique. | CA53: ABS_C_007 | CB53: =VLOOKUP(CA53,'Axe 2 Règles de gestion'!$D$2:$F$354,3, FALSE) -> La date de fin réelle du congé/absence doit être antérieure à la date limite de départ à la retraite. | CC53: ABS_C_008 | CD53: =VLOOKUP(CC53,'Axe 2 Règles de gestion'!$D$2:$F$354,3, FALSE) -> La date de fin prévisionnelle du congé/absence doit être antérieure à la date limite de départ à la retraite.
A54: 22.10.00 | B54: A | C54: 44917.644 | D54: D0007 | E54: Congés/Absence | F54: S0046 | G54: Autorisations d'absence | H54: E0432 | I54: Autorisation d'absence pour fêtes et cérémonies religieuses | J54: Type de congé/absence saisi égal 'Autorisation d'absence pour fêtes et cérémonies religieuses' | K54: A_COA_TYCOAB [Saisi] = 'CA012' | L54: T1093 | M54: Autorisation d'absence pour fêtes et cérémonies religieuses | N54: Création Modification | Q54: Ouvrier d'état | R54: P0005 | S54: O | T54: Général | U54: Passant | V54: 40950 | X54: ADI_I_114 ET ADI_I_115 ET ABS_C_010 ET ABS_C_003 ET ABS_C_004 ET ABS_C_009 ET ABS_C_019 ET ABS_C_020 ET ABS_C_026 ET ABS_C_002 ET ABS_C_005 ET ABS_C_006 ET ABS_C_007 ET ABS_C_008 | Y54: ADI_I_114 | Z54: =VLOOKUP(Y54,'Axe 2 Règles de gestion'!$D$2:$F$354,3, FALSE) -> L'agent doit effectuer une demande. | AA54: ADI_I_115 | AB54: =VLOOKUP(AA54,'Axe 2 Règles de gestion'!$D$2:$F$354,3, FALSE) -> L'autorisation d'absence doit être compatible avec le fonctionnement normal du service. | BG54: ABS_C_010 | BH54: =VLOOKUP(BG54,'Axe 2 Règles de gestion'!$D$2:$F$354,3, FALSE) -> L'agent doit être en activité. | BI54: ABS_C_003 | BJ54: =VLOOKUP(BI54,'Axe 2 Règles de gestion'!$D$2:$F$354,3, FALSE) -> La date de début du congé/absence doit être antérieure ou égale à la date de fin réelle du congé/absence. | BK54: ABS_C_004 | BL54: =VLOOKUP(BK54,'Axe 2 Règles de gestion'!$D$2:$F$354,3, FALSE) -> La date de début du congé/absence doit être antérieure ou égale à la date de fin prévisionnelle du congé/absence. | BM54: ABS_C_009 | BN54: =VLOOKUP(BM54,'Axe 2 Règles de gestion'!$D$2:$F$354,3, FALSE) -> La date de fin réelle ou la date de fin prévisionnelle du congé/absence doit être saisie. | BO54: ABS_C_019 | BP54: =VLOOKUP(BO54,'Axe 2 Règles de gestion'!$D$2:$F$354,3, FALSE) -> Si l'absence ne commence pas par une demi-journée et si l'absence précédente ne finit pas par une demi journée, la date de début de l'absence saisie est postérieure à la date de fin réelle de l'absence précédente. | BQ54: ABS_C_020 | BR54: =VLOOKUP(BQ54,'Axe 2 Règles de gestion'!$D$2:$F$354,3, FALSE) -> Si l'absence ne commence pas par une demi-journée et si l'absence précédente ne finit pas par une demi journée, la date de début de l'absence saisie est postérieure à la date de fin prévisionnelle de l'absence précédente. | BS54: ABS_C_026 | BT54: =VLOOKUP(BS54,'Axe 2 Règles de gestion'!$D$2:$F$354,3, FALSE) -> Dans le cas d'un congé autre que CLM, CLD, CGM et CITIS, l'indicateur de requalification doit être à non et les impacts spécifiques à la requalification ne doivent pas être mobilisés ou l'impact rémunération est vide. | BU54: ABS_C_002 | BV54: =VLOOKUP(BU54,'Axe 2 Règles de gestion'!$D$2:$F$354,3, FALSE) -> La date de début du congé/absence doit être postérieure ou égale à la date de début du lien juridique. | BW54: ABS_C_005 | BX54: =VLOOKUP(BW54,'Axe 2 Règles de gestion'!$D$2:$F$354,3, FALSE) -> La date de fin réelle du congé/absence doit être antérieure ou égale à la date limite de fin réelle ou prévisionnelle du lien juridique. | BY54: ABS_C_006 | BZ54: =VLOOKUP(BY54,'Axe 2 Règles de gestion'!$D$2:$F$354,3, FALSE) -> La date de fin prévisionnelle du congé/absence doit être antérieure ou égale à la date limite de fin réelle ou prévisionnelle du lien juridique. | CA54: ABS_C_007 | CB54: =VLOOKUP(CA54,'Axe 2 Règles de gestion'!$D$2:$F$354,3, FALSE) -> La date de fin réelle du congé/absence doit être antérieure à la date limite de départ à la retraite. | CC54: ABS_C_008 | CD54: =VLOOKUP(CC54,'Axe 2 Règles de gestion'!$D$2:$F$354,3, FALSE) -> La date de fin prévisionnelle du congé/absence doit être antérieure à la date limite de départ à la retraite.
A55: 17.10.00 | B55: A | C55: 43152.5 | D55: D0007 | E55: Congés/Absence | F55: S0046 | G55: Autorisations d'absence | H55: E0432 | I55: Autorisation d'absence pour fêtes et cérémonies religieuses | J55: Type de congé/absence saisi égal 'Autorisation d'absence pour fêtes et cérémonies religieuses' | K55: A_COA_TYCOAB [Saisi] = 'CA012' | L55: T1093 | M55: Autorisation d'absence pour fêtes et cérémonies religieuses | N55: Création Modification | Q55: Personnel civil payé à l'acte ou à la tâche | R55: P0054 | S55: N | T55: Particulier | U55: Exclu | V55: 40725
A56: 17.10.00 | B56: A | C56: 43152.5 | D56: D0007 | E56: Congés/Absence | F56: S0046 | G56: Autorisations d'absence | H56: E0432 | I56: Autorisation d'absence pour fêtes et cérémonies religieuses | J56: Type de congé/absence saisi égal 'Autorisation d'absence pour fêtes et cérémonies religieuses' | K56: A_COA_TYCOAB [Saisi] = 'CA012' | L56: T1093 | M56: Autorisation d'absence pour fêtes et cérémonies religieuses | N56: Création Modification | Q56: Volontaire International | R56: P0178 | S56: N | T56: Particulier | U56: Exclu | V56: 40725
A57: 17.10.00 | B57: A | C57: 43152.5 | D57: D0007 | E57: Congés/Absence | F57: S0046 | G57: Autorisations d'absence | H57: E0432 | I57: Autorisation d'absence pour fêtes et cérémonies religieuses | J57: Type de congé/absence saisi égal 'Autorisation d'absence pour fêtes et cérémonies religieuses' | K57: A_COA_TYCOAB [Saisi] = 'CA012' | L57: T1093 | M57: Autorisation d'absence pour fêtes et cérémonies religieuses | N57: Création Modification | Q57: Volontaire de service civique outre-mer | R57: P0179 | S57: N | T57: Particulier | U57: Exclu | V57: 40725
A58: 17.10.00 | B58: A | C58: 43189.5 | D58: D0007 | E58: Congés/Absence | F58: S0046 | G58: Autorisations d'absence | H58: E0432 | I58: Autorisation d'absence pour fêtes et cérémonies religieuses | J58: Type de congé/absence saisi égal 'Autorisation d'absence pour fêtes et cérémonies religieuses' | K58: A_COA_TYCOAB [Saisi] = 'CA012' | L58: T1093 | M58: Autorisation d'absence pour fêtes et cérémonies religieuses | N58: Création Modification | Q58: Ouvrier de la défense ou assimilé | R58: P0197 | S58: O | T58: Particulier | U58: Exclu | V58: 40725
A59: 22.10.00 | B59: M | C59: 44917.669 | D59: D0007 | E59: Congés/Absence | F59: S0046 | G59: Autorisations d'absence | H59: E0433 | I59: Autorisation d'absence au profit des membres des associations agrées en matière de sécurité civile | J59: Type de congé/absence saisi égal 'Autorisation d'absence au profit des membres des associations agrées en matière de sécurité civile' | K59: A_COA_TYCOAB [Saisi] = 'CA013' | L59: T1094 | M59: Autorisation d'absence au profit des membres des associations agrées en matière de sécurité civile | N59: Création Modification | Q59: Titulaire ou magistrat | R59: P0001 | S59: T | T59: Général | U59: Passant | V59: 40725 | W59: 44620 | X59: ABS_C_010 ET ABS_C_001 ET ABS_C_003 ET ABS_C_004 ET ABS_C_007 ET ABS_C_008 ET ABS_C_009 ET ABS_C_019 ET ABS_C_020 ET ABS_C_026 | BG59: ABS_C_010 | BH59: =VLOOKUP(BG59,'Axe 2 Règles de gestion'!$D$2:$F$354,3, FALSE) -> L'agent doit être en activité. | BI59: ABS_C_001 | BJ59: =VLOOKUP(BI59,'Axe 2 Règles de gestion'!$D$2:$F$354,3, FALSE) -> La date de début du congé/absence doit être postérieure ou égale à la date de recrutement dans la FPE ou dans la carrière militaire. | BK59: ABS_C_003 | BL59: =VLOOKUP(BK59,'Axe 2 Règles de gestion'!$D$2:$F$354,3, FALSE) -> La date de début du congé/absence doit être antérieure ou égale à la date de fin réelle du congé/absence. | BM59: ABS_C_004 | BN59: =VLOOKUP(BM59,'Axe 2 Règles de gestion'!$D$2:$F$354,3, FALSE) -> La date de début du congé/absence doit être antérieure ou égale à la date de fin prévisionnelle du congé/absence. | BO59: ABS_C_007 | BP59: =VLOOKUP(BO59,'Axe 2 Règles de gestion'!$D$2:$F$354,3, FALSE) -> La date de fin réelle du congé/absence doit être antérieure à la date limite de départ à la retraite. | BQ59: ABS_C_008 | BR59: =VLOOKUP(BQ59,'Axe 2 Règles de gestion'!$D$2:$F$354,3, FALSE) -> La date de fin prévisionnelle du congé/absence doit être antérieure à la date limite de départ à la retraite. | BS59: ABS_C_009 | BT59: =VLOOKUP(BS59,'Axe 2 Règles de gestion'!$D$2:$F$354,3, FALSE) -> La date de fin réelle ou la date de fin prévisionnelle du congé/absence doit être saisie. | BU59: ABS_C_019 | BV59: =VLOOKUP(BU59,'Axe 2 Règles de gestion'!$D$2:$F$354,3, FALSE) -> Si l'absence ne commence pas par une demi-journée et si l'absence précédente ne finit pas par une demi journée, la date de début de l'absence saisie est postérieure à la date de fin réelle de l'absence précédente. | BW59: ABS_C_020 | BX59: =VLOOKUP(BW59,'Axe 2 Règles de gestion'!$D$2:$F$354,3, FALSE) -> Si l'absence ne commence pas par une demi-journée et si l'absence précédente ne finit pas par une demi journée, la date de début de l'absence saisie est postérieure à la date de fin prévisionnelle de l'absence précédente. | BY59: ABS_C_026 | BZ59: =VLOOKUP(BY59,'Axe 2 Règles de gestion'!$D$2:$F$354,3, FALSE) -> Dans le cas d'un congé autre que CLM, CLD, CGM et CITIS, l'indicateur de requalification doit être à non et les impacts spécifiques à la requalification ne doivent pas être mobilisés ou l'impact rémunération est vide.
A60: 22.10.00 | B60: A | C60: 44917.669 | D60: D0007 | E60: Congés/Absence | F60: S0046 | G60: Autorisations d'absence | H60: E0433 | I60: Autorisation d'absence au profit des membres des associations agrées en matière de sécurité civile | J60: Type de congé/absence saisi égal 'Autorisation d'absence au profit des membres des associations agrées en matière de sécurité civile' | K60: A_COA_TYCOAB [Saisi] = 'CA013' | L60: T1094 | M60: Autorisation d'absence au profit des membres des associations agrées en matière de sécurité civile | N60: Création Modification | Q60: Titulaire ou magistrat | R60: P0001 | S60: T | T60: Général | U60: Passant | V60: 44621 | X60: ADI_I_126 ET ADI_I_127 ET ADI_I_089 ET ABS_C_010 ET ABS_C_001 ET ABS_C_003 ET ABS_C_004 ET ABS_C_007 ET ABS_C_008 ET ABS_C_009 ET ABS_C_019 ET ABS_C_020 ET ABS_C_026 | Y60: ADI_I_126 | Z60: =VLOOKUP(Y60,'Axe 2 Règles de gestion'!$D$2:$F$354,3, FALSE) -> L'agent est membre d'une association agréée en matière de sécurité civile. | AA60: ADI_I_127 | AB60: =VLOOKUP(AA60,'Axe 2 Règles de gestion'!$D$2:$F$354,3, FALSE) -> L'agent doit obtenir l'accord de sa hiérarchie pour s'absenter s'il est sollicité en cas de mise en oeuvre du plan Orsec, ou par l'autorité de police compétente en cas d'accident, sinistre ou catastrophe. | AC60: ADI_I_089 | AD60: =VLOOKUP(AC60,'Axe 2 Règles de gestion'!$D$2:$F$354,3, FALSE) -> L'administration ne peut s'opposer à l'absence, sous réserve de nécessité de service. | BG60: ABS_C_010 | BH60: =VLOOKUP(BG60,'Axe 2 Règles de gestion'!$D$2:$F$354,3, FALSE) -> L'agent doit être en activité. | BI60: ABS_C_001 | BJ60: =VLOOKUP(BI60,'Axe 2 Règles de gestion'!$D$2:$F$354,3, FALSE) -> La date de début du congé/absence doit être postérieure ou égale à la date de recrutement dans la FPE ou dans la carrière militaire. | BK60: ABS_C_003 | BL60: =VLOOKUP(BK60,'Axe 2 Règles de gestion'!$D$2:$F$354,3, FALSE) -> La date de début du congé/absence doit être antérieure ou égale à la date de fin réelle du congé/absence. | BM60: ABS_C_004 | BN60: =VLOOKUP(BM60,'Axe 2 Règles de gestion'!$D$2:$F$354,3, FALSE) -> La date de début du congé/absence doit être antérieure ou égale à la date de fin prévisionnelle du congé/absence. | BO60: ABS_C_007 | BP60: =VLOOKUP(BO60,'Axe 2 Règles de gestion'!$D$2:$F$354,3, FALSE) -> La date de fin réelle du congé/absence doit être antérieure à la date limite de départ à la retraite. | BQ60: ABS_C_008 | BR60: =VLOOKUP(BQ60,'Axe 2 Règles de gestion'!$D$2:$F$354,3, FALSE) -> La date de fin prévisionnelle du congé/absence doit être antérieure à la date limite de départ à la retraite. | BS60: ABS_C_009 | BT60: =VLOOKUP(BS60,'Axe 2 Règles de gestion'!$D$2:$F$354,3, FALSE) -> La date de fin réelle ou la date de fin prévisionnelle du congé/absence doit être saisie. | BU60: ABS_C_019 | BV60: =VLOOKUP(BU60,'Axe 2 Règles de gestion'!$D$2:$F$354,3, FALSE) -> Si l'absence ne commence pas par une demi-journée et si l'absence précédente ne finit pas par une demi journée, la date de début de l'absence saisie est postérieure à la date de fin réelle de l'absence précédente. | BW60: ABS_C_020 | BX60: =VLOOKUP(BW60,'Axe 2 Règles de gestion'!$D$2:$F$354,3, FALSE) -> Si l'absence ne commence pas par une demi-journée et si l'absence précédente ne finit pas par une demi journée, la date de début de l'absence saisie est postérieure à la date de fin prévisionnelle de l'absence précédente. | BY60: ABS_C_026 | BZ60: =VLOOKUP(BY60,'Axe 2 Règles de gestion'!$D$2:$F$354,3, FALSE) -> Dans le cas d'un congé autre que CLM, CLD, CGM et CITIS, l'indicateur de requalification doit être à non et les impacts spécifiques à la requalification ne doivent pas être mobilisés ou l'impact rémunération est vide.
A61: 22.10.00 | B61: M | C61: 44917.669 | D61: D0007 | E61: Congés/Absence | F61: S0046 | G61: Autorisations d'absence | H61: E0433 | I61: Autorisation d'absence au profit des membres des associations agrées en matière de sécurité civile | J61: Type de congé/absence saisi égal 'Autorisation d'absence au profit des membres des associations agrées en matière de sécurité civile' | K61: A_COA_TYCOAB [Saisi] = 'CA013' | L61: T1094 | M61: Autorisation d'absence au profit des membres des associations agrées en matière de sécurité civile | N61: Création Modification | Q61: Contractuel | R61: P0003 | S61: N | T61: Général | U61: Passant | V61: 40725 | W61: 44620 | X61: ABS_C_010 ET ABS_C_003 ET ABS_C_004 ET ABS_C_009 ET ABS_C_019 ET ABS_C_020 ET ABS_C_026 ET ABS_C_002 ET ABS_C_005 ET ABS_C_006 ET ABS_C_007 ET ABS_C_008 | BG61: ABS_C_010 | BH61: =VLOOKUP(BG61,'Axe 2 Règles de gestion'!$D$2:$F$354,3, FALSE) -> L'agent doit être en activité. | BI61: ABS_C_003 | BJ61: =VLOOKUP(BI61,'Axe 2 Règles de gestion'!$D$2:$F$354,3, FALSE) -> La date de début du congé/absence doit être antérieure ou égale à la date de fin réelle du congé/absence. | BK61: ABS_C_004 | BL61: =VLOOKUP(BK61,'Axe 2 Règles de gestion'!$D$2:$F$354,3, FALSE) -> La date de début du congé/absence doit être antérieure ou égale à la date de fin prévisionnelle du congé/absence. | BM61: ABS_C_009 | BN61: =VLOOKUP(BM61,'Axe 2 Règles de gestion'!$D$2:$F$354,3, FALSE) -> La date de fin réelle ou la date de fin prévisionnelle du congé/absence doit être saisie. | BO61: ABS_C_019 | BP61: =VLOOKUP(BO61,'Axe 2 Règles de gestion'!$D$2:$F$354,3, FALSE) -> Si l'absence ne commence pas par une demi-journée et si l'absence précédente ne finit pas par une demi journée, la date de début de l'absence saisie est postérieure à la date de fin réelle de l'absence précédente. | BQ61: ABS_C_020 | BR61: =VLOOKUP(BQ61,'Axe 2 Règles de gestion'!$D$2:$F$354,3, FALSE) -> Si l'absence ne commence pas par une demi-journée et si l'absence précédente ne finit pas par une demi journée, la date de début de l'absence saisie est postérieure à la date de fin prévisionnelle de l'absence précédente. | BS61: ABS_C_026 | BT61: =VLOOKUP(BS61,'Axe 2 Règles de gestion'!$D$2:$F$354,3, FALSE) -> Dans le cas d'un congé autre que CLM, CLD, CGM et CITIS, l'indicateur de requalification doit être à non et les impacts spécifiques à la requalification ne doivent pas être mobilisés ou l'impact rémunération est vide. | BU61: ABS_C_002 | BV61: =VLOOKUP(BU61,'Axe 2 Règles de gestion'!$D$2:$F$354,3, FALSE) -> La date de début du congé/absence doit être postérieure ou égale à la date de début du lien juridique. | BW61: ABS_C_005 | BX61: =VLOOKUP(BW61,'Axe 2 Règles de gestion'!$D$2:$F$354,3, FALSE) -> La date de fin réelle du congé/absence doit être antérieure ou égale à la date limite de fin réelle ou prévisionnelle du lien juridique. | BY61: ABS_C_006 | BZ61: =VLOOKUP(BY61,'Axe 2 Règles de gestion'!$D$2:$F$354,3, FALSE) -> La date de fin prévisionnelle du congé/absence doit être antérieure ou égale à la date limite de fin réelle ou prévisionnelle du lien juridique. | CA61: ABS_C_007 | CB61: =VLOOKUP(CA61,'Axe 2 Règles de gestion'!$D$2:$F$354,3, FALSE) -> La date de fin réelle du congé/absence doit être antérieure à la date limite de départ à la retraite. | CC61: ABS_C_008 | CD61: =VLOOKUP(CC61,'Axe 2 Règles de gestion'!$D$2:$F$354,3, FALSE) -> La date de fin prévisionnelle du congé/absence doit être antérieure à la date limite de départ à la retraite.
A62: 22.10.00 | B62: A | C62: 44917.669 | D62: D0007 | E62: Congés/Absence | F62: S0046 | G62: Autorisations d'absence | H62: E0433 | I62: Autorisation d'absence au profit des membres des associations agrées en matière de sécurité civile | J62: Type de congé/absence saisi égal 'Autorisation d'absence au profit des membres des associations agrées en matière de sécurité civile' | K62: A_COA_TYCOAB [Saisi] = 'CA013' | L62: T1094 | M62: Autorisation d'absence au profit des membres des associations agrées en matière de sécurité civile | N62: Création Modification | Q62: Contractuel | R62: P0003 | S62: N | T62: Général | U62: Passant | V62: 44621 | X62: ADI_I_126 ET ADI_I_127 ET ADI_I_089 ET ABS_C_010 ET ABS_C_003 ET ABS_C_004 ET ABS_C_009 ET ABS_C_019 ET ABS_C_020 ET ABS_C_026 ET ABS_C_002 ET ABS_C_005 ET ABS_C_006 ET ABS_C_007 ET ABS_C_008 | Y62: ADI_I_126 | Z62: =VLOOKUP(Y62,'Axe 2 Règles de gestion'!$D$2:$F$354,3, FALSE) -> L'agent est membre d'une association agréée en matière de sécurité civile. | AA62: ADI_I_127 | AB62: =VLOOKUP(AA62,'Axe 2 Règles de gestion'!$D$2:$F$354,3, FALSE) -> L'agent doit obtenir l'accord de sa hiérarchie pour s'absenter s'il est sollicité en cas de mise en oeuvre du plan Orsec, ou par l'autorité de police compétente en cas d'accident, sinistre ou catastrophe. | AC62: ADI_I_089 | AD62: =VLOOKUP(AC62,'Axe 2 Règles de gestion'!$D$2:$F$354,3, FALSE) -> L'administration ne peut s'opposer à l'absence, sous réserve de nécessité de service. | BG62: ABS_C_010 | BH62: =VLOOKUP(BG62,'Axe 2 Règles de gestion'!$D$2:$F$354,3, FALSE) -> L'agent doit être en activité. | BI62: ABS_C_003 | BJ62: =VLOOKUP(BI62,'Axe 2 Règles de gestion'!$D$2:$F$354,3, FALSE) -> La date de début du congé/absence doit être antérieure ou égale à la date de fin réelle du congé/absence. | BK62: ABS_C_004 | BL62: =VLOOKUP(BK62,'Axe 2 Règles de gestion'!$D$2:$F$354,3, FALSE) -> La date de début du congé/absence doit être antérieure ou égale à la date de fin prévisionnelle du congé/absence. | BM62: ABS_C_009 | BN62: =VLOOKUP(BM62,'Axe 2 Règles de gestion'!$D$2:$F$354,3, FALSE) -> La date de fin réelle ou la date de fin prévisionnelle du congé/absence doit être saisie. | BO62: ABS_C_019 | BP62: =VLOOKUP(BO62,'Axe 2 Règles de gestion'!$D$2:$F$354,3, FALSE) -> Si l'absence ne commence pas par une demi-journée et si l'absence précédente ne finit pas par une demi journée, la date de début de l'absence saisie est postérieure à la date de fin réelle de l'absence précédente. | BQ62: ABS_C_020 | BR62: =VLOOKUP(BQ62,'Axe 2 Règles de gestion'!$D$2:$F$354,3, FALSE) -> Si l'absence ne commence pas par une demi-journée et si l'absence précédente ne finit pas par une demi journée, la date de début de l'absence saisie est postérieure à la date de fin prévisionnelle de l'absence précédente. | BS62: ABS_C_026 | BT62: =VLOOKUP(BS62,'Axe 2 Règles de gestion'!$D$2:$F$354,3, FALSE) -> Dans le cas d'un congé autre que CLM, CLD, CGM et CITIS, l'indicateur de requalification doit être à non et les impacts spécifiques à la requalification ne doivent pas être mobilisés ou l'impact rémunération est vide. | BU62: ABS_C_002 | BV62: =VLOOKUP(BU62,'Axe 2 Règles de gestion'!$D$2:$F$354,3, FALSE) -> La date de début du congé/absence doit être postérieure ou égale à la date de début du lien juridique. | BW62: ABS_C_005 | BX62: =VLOOKUP(BW62,'Axe 2 Règles de gestion'!$D$2:$F$354,3, FALSE) -> La date de fin réelle du congé/absence doit être antérieure ou égale à la date limite de fin réelle ou prévisionnelle du lien juridique. | BY62: ABS_C_006 | BZ62: =VLOOKUP(BY62,'Axe 2 Règles de gestion'!$D$2:$F$354,3, FALSE) -> La date de fin prévisionnelle du congé/absence doit être antérieure ou égale à la date limite de fin réelle ou prévisionnelle du lien juridique. | CA62: ABS_C_007 | CB62: =VLOOKUP(CA62,'Axe 2 Règles de gestion'!$D$2:$F$354,3, FALSE) -> La date de fin réelle du congé/absence doit être antérieure à la date limite de départ à la retraite. | CC62: ABS_C_008 | CD62: =VLOOKUP(CC62,'Axe 2 Règles de gestion'!$D$2:$F$354,3, FALSE) -> La date de fin prévisionnelle du congé/absence doit être antérieure à la date limite de départ à la retraite.
A63: 22.10.00 | B63: M | C63: 44917.672 | D63: D0007 | E63: Congés/Absence | F63: S0046 | G63: Autorisations d'absence | H63: E0433 | I63: Autorisation d'absence au profit des membres des associations agrées en matière de sécurité civile | J63: Type de congé/absence saisi égal 'Autorisation d'absence au profit des membres des associations agrées en matière de sécurité civile' | K63: A_COA_TYCOAB [Saisi] = 'CA013' | L63: T1094 | M63: Autorisation d'absence au profit des membres des associations agrées en matière de sécurité civile | N63: Création Modification | Q63: Stagiaire ou auditeur ou élève | R63: P0004 | S63: S | T63: Général | U63: Passant | V63: 40725 | W63: 44620 | X63: ABS_C_010 ET ABS_C_001 ET ABS_C_003 ET ABS_C_004 ET ABS_C_007 ET ABS_C_008 ET ABS_C_009 ET ABS_C_019 ET ABS_C_020 ET ABS_C_026 | BG63: ABS_C_010 | BH63: =VLOOKUP(BG63,'Axe 2 Règles de gestion'!$D$2:$F$354,3, FALSE) -> L'agent doit être en activité. | BI63: ABS_C_001 | BJ63: =VLOOKUP(BI63,'Axe 2 Règles de gestion'!$D$2:$F$354,3, FALSE) -> La date de début du congé/absence doit être postérieure ou égale à la date de recrutement dans la FPE ou dans la carrière militaire. | BK63: ABS_C_003 | BL63: =VLOOKUP(BK63,'Axe 2 Règles de gestion'!$D$2:$F$354,3, FALSE) -> La date de début du congé/absence doit être antérieure ou égale à la date de fin réelle du congé/absence. | BM63: ABS_C_004 | BN63: =VLOOKUP(BM63,'Axe 2 Règles de gestion'!$D$2:$F$354,3, FALSE) -> La date de début du congé/absence doit être antérieure ou égale à la date de fin prévisionnelle du congé/absence. | BO63: ABS_C_007 | BP63: =VLOOKUP(BO63,'Axe 2 Règles de gestion'!$D$2:$F$354,3, FALSE) -> La date de fin réelle du congé/absence doit être antérieure à la date limite de départ à la retraite. | BQ63: ABS_C_008 | BR63: =VLOOKUP(BQ63,'Axe 2 Règles de gestion'!$D$2:$F$354,3, FALSE) -> La date de fin prévisionnelle du congé/absence doit être antérieure à la date limite de départ à la retraite. | BS63: ABS_C_009 | BT63: =VLOOKUP(BS63,'Axe 2 Règles de gestion'!$D$2:$F$354,3, FALSE) -> La date de fin réelle ou la date de fin prévisionnelle du congé/absence doit être saisie. | BU63: ABS_C_019 | BV63: =VLOOKUP(BU63,'Axe 2 Règles de gestion'!$D$2:$F$354,3, FALSE) -> Si l'absence ne commence pas par une demi-journée et si l'absence précédente ne finit pas par une demi journée, la date de début de l'absence saisie est postérieure à la date de fin réelle de l'absence précédente. | BW63: ABS_C_020 | BX63: =VLOOKUP(BW63,'Axe 2 Règles de gestion'!$D$2:$F$354,3, FALSE) -> Si l'absence ne commence pas par une demi-journée et si l'absence précédente ne finit pas par une demi journée, la date de début de l'absence saisie est postérieure à la date de fin prévisionnelle de l'absence précédente. | BY63: ABS_C_026 | BZ63: =VLOOKUP(BY63,'Axe 2 Règles de gestion'!$D$2:$F$354,3, FALSE) -> Dans le cas d'un congé autre que CLM, CLD, CGM et CITIS, l'indicateur de requalification doit être à non et les impacts spécifiques à la requalification ne doivent pas être mobilisés ou l'impact rémunération est vide.
A64: 22.10.00 | B64: M | C64: 44932.7 | D64: D0007 | E64: Congés/Absence | F64: S0046 | G64: Autorisations d'absence | H64: E0433 | I64: Autorisation d'absence au profit des membres des associations agrées en matière de sécurité civile | J64: Type de congé/absence saisi égal 'Autorisation d'absence au profit des membres des associations agrées en matière de sécurité civile' | K64: A_COA_TYCOAB [Saisi] = 'CA013' | L64: T1094 | M64: Autorisation d'absence au profit des membres des associations agrées en matière de sécurité civile | N64: Création Modification | Q64: Stagiaire ou auditeur ou élève | R64: P0004 | S64: S | T64: Général | U64: Passant | V64: 44621 | X64: ADI_I_157 ET ADI_I_126 ET ADI_I_127 ET ADI_I_089 ET ABS_C_010 ET ABS_C_001 ET ABS_C_003 ET ABS_C_004 ET ABS_C_007 ET ABS_C_008 ET ABS_C_009 ET ABS_C_019 ET ABS_C_020 ET ABS_C_026 | Y64: ADI_I_157 | Z64: =VLOOKUP(Y64,'Axe 2 Règles de gestion'!$D$2:$F$354,3, FALSE) -> L'agent bénéficie des dispositions applicables aux agents titulaires pour cette absence dans la mesure où elles sont compatibles avec leur situation particulière. | AA64: ADI_I_126 | AB64: =VLOOKUP(AA64,'Axe 2 Règles de gestion'!$D$2:$F$354,3, FALSE) -> L'agent est membre d'une association agréée en matière de sécurité civile. | AC64: ADI_I_127 | AD64: =VLOOKUP(AC64,'Axe 2 Règles de gestion'!$D$2:$F$354,3, FALSE) -> L'agent doit obtenir l'accord de sa hiérarchie pour s'absenter s'il est sollicité en cas de mise en oeuvre du plan Orsec, ou par l'autorité de police compétente en cas d'accident, sinistre ou catastrophe. | AE64: ADI_I_089 | AF64: =VLOOKUP(AE64,'Axe 2 Règles de gestion'!$D$2:$F$354,3, FALSE) -> L'administration ne peut s'opposer à l'absence, sous réserve de nécessité de service. | BG64: ABS_C_010 | BH64: =VLOOKUP(BG64,'Axe 2 Règles de gestion'!$D$2:$F$354,3, FALSE) -> L'agent doit être en activité. | BI64: ABS_C_001 | BJ64: =VLOOKUP(BI64,'Axe 2 Règles de gestion'!$D$2:$F$354,3, FALSE) -> La date de début du congé/absence doit être postérieure ou égale à la date de recrutement dans la FPE ou dans la carrière militaire. | BK64: ABS_C_003 | BL64: =VLOOKUP(BK64,'Axe 2 Règles de gestion'!$D$2:$F$354,3, FALSE) -> La date de début du congé/absence doit être antérieure ou égale à la date de fin réelle du congé/absence. | BM64: ABS_C_004 | BN64: =VLOOKUP(BM64,'Axe 2 Règles de gestion'!$D$2:$F$354,3, FALSE) -> La date de début du congé/absence doit être antérieure ou égale à la date de fin prévisionnelle du congé/absence. | BO64: ABS_C_007 | BP64: =VLOOKUP(BO64,'Axe 2 Règles de gestion'!$D$2:$F$354,3, FALSE) -> La date de fin réelle du congé/absence doit être antérieure à la date limite de départ à la retraite. | BQ64: ABS_C_008 | BR64: =VLOOKUP(BQ64,'Axe 2 Règles de gestion'!$D$2:$F$354,3, FALSE) -> La date de fin prévisionnelle du congé/absence doit être antérieure à la date limite de départ à la retraite. | BS64: ABS_C_009 | BT64: =VLOOKUP(BS64,'Axe 2 Règles de gestion'!$D$2:$F$354,3, FALSE) -> La date de fin réelle ou la date de fin prévisionnelle du congé/absence doit être saisie. | BU64: ABS_C_019 | BV64: =VLOOKUP(BU64,'Axe 2 Règles de gestion'!$D$2:$F$354,3, FALSE) -> Si l'absence ne commence pas par une demi-journée et si l'absence précédente ne finit pas par une demi journée, la date de début de l'absence saisie est postérieure à la date de fin réelle de l'absence précédente. | BW64: ABS_C_020 | BX64: =VLOOKUP(BW64,'Axe 2 Règles de gestion'!$D$2:$F$354,3, FALSE) -> Si l'absence ne commence pas par une demi-journée et si l'absence précédente ne finit pas par une demi journée, la date de début de l'absence saisie est postérieure à la date de fin prévisionnelle de l'absence précédente. | BY64: ABS_C_026 | BZ64: =VLOOKUP(BY64,'Axe 2 Règles de gestion'!$D$2:$F$354,3, FALSE) -> Dans le cas d'un congé autre que CLM, CLD, CGM et CITIS, l'indicateur de requalification doit être à non et les impacts spécifiques à la requalification ne doivent pas être mobilisés ou l'impact rémunération est vide.
A65: 17.10.00 | B65: A | C65: 44917.673 | D65: D0007 | E65: Congés/Absence | F65: S0046 | G65: Autorisations d'absence | H65: E0433 | I65: Autorisation d'absence au profit des membres des associations agrées en matière de sécurité civile | J65: Type de congé/absence saisi égal 'Autorisation d'absence au profit des membres des associations agrées en matière de sécurité civile' | K65: A_COA_TYCOAB [Saisi] = 'CA013' | L65: T1094 | M65: Autorisation d'absence au profit des membres des associations agrées en matière de sécurité civile | N65: Création Modification | Q65: Ouvrier d'état | R65: P0005 | S65: O | T65: Général | U65: Exclu | V65: 40725
A66: 17.10.00 | B66: A | C66: 43152.5 | D66: D0007 | E66: Congés/Absence | F66: S0046 | G66: Autorisations d'absence | H66: E0433 | I66: Autorisation d'absence au profit des membres des associations agrées en matière de sécurité civile | J66: Type de congé/absence saisi égal 'Autorisation d'absence au profit des membres des associations agrées en matière de sécurité civile' | K66: A_COA_TYCOAB [Saisi] = 'CA013' | L66: T1094 | M66: Autorisation d'absence au profit des membres des associations agrées en matière de sécurité civile | N66: Création Modification | Q66: Professeur ou maître de conférences des univ-praticien hospitalier titulaire (centres de soins, d'ens. et de rech. dentaire, discipline pharma) | R66: P0029 | S66: T | T66: Particulier | U66: Exclu | V66: 40725
A67: 17.10.00 | B67: A | C67: 43152.5 | D67: D0007 | E67: Congés/Absence | F67: S0046 | G67: Autorisations d'absence | H67: E0433 | I67: Autorisation d'absence au profit des membres des associations agrées en matière de sécurité civile | J67: Type de congé/absence saisi égal 'Autorisation d'absence au profit des membres des associations agrées en matière de sécurité civile' | K67: A_COA_TYCOAB [Saisi] = 'CA013' | L67: T1094 | M67: Autorisation d'absence au profit des membres des associations agrées en matière de sécurité civile | N67: Création Modification | Q67: Maître de conférences des univ-praticien hospitalier, des centres de soins, d'ens. et de recherche dentaire, des disciplines pharmaceutiques stagiaire | R67: P0040 | S67: S | T67: Particulier | U67: Exclu | V67: 40725
A68: 17.10.00 | B68: A | C68: 43152.5 | D68: D0007 | E68: Congés/Absence | F68: S0046 | G68: Autorisations d'absence | H68: E0433 | I68: Autorisation d'absence au profit des membres des associations agrées en matière de sécurité civile | J68: Type de congé/absence saisi égal 'Autorisation d'absence au profit des membres des associations agrées en matière de sécurité civile' | K68: A_COA_TYCOAB [Saisi] = 'CA013' | L68: T1094 | M68: Autorisation d'absence au profit des membres des associations agrées en matière de sécurité civile | N68: Création Modification | Q68: Personnel civil payé à l'acte ou à la tâche | R68: P0054 | S68: N | T68: Particulier | U68: Exclu | V68: 40725
A69: 17.10.00 | B69: A | C69: 43152.5 | D69: D0007 | E69: Congés/Absence | F69: S0046 | G69: Autorisations d'absence | H69: E0433 | I69: Autorisation d'absence au profit des membres des associations agrées en matière de sécurité civile | J69: Type de congé/absence saisi égal 'Autorisation d'absence au profit des membres des associations agrées en matière de sécurité civile' | K69: A_COA_TYCOAB [Saisi] = 'CA013' | L69: T1094 | M69: Autorisation d'absence au profit des membres des associations agrées en matière de sécurité civile | N69: Création Modification | Q69: Contractuel de droit privé | R69: P0072 | S69: N | T69: Particulier | U69: Exclu | V69: 40725
A70: 17.10.00 | B70: A | C70: 43152.5 | D70: D0007 | E70: Congés/Absence | F70: S0046 | G70: Autorisations d'absence | H70: E0433 | I70: Autorisation d'absence au profit des membres des associations agrées en matière de sécurité civile | J70: Type de congé/absence saisi égal 'Autorisation d'absence au profit des membres des associations agrées en matière de sécurité civile' | K70: A_COA_TYCOAB [Saisi] = 'CA013' | L70: T1094 | M70: Autorisation d'absence au profit des membres des associations agrées en matière de sécurité civile | N70: Création Modification | Q70: Volontaire International | R70: P0178 | S70: N | T70: Particulier | U70: Exclu | V70: 40725
A71: 17.10.00 | B71: A | C71: 43152.5 | D71: D0007 | E71: Congés/Absence | F71: S0046 | G71: Autorisations d'absence | H71: E0433 | I71: Autorisation d'absence au profit des membres des associations agrées en matière de sécurité civile | J71: Type de congé/absence saisi égal 'Autorisation d'absence au profit des membres des associations agrées en matière de sécurité civile' | K71: A_COA_TYCOAB [Saisi] = 'CA013' | L71: T1094 | M71: Autorisation d'absence au profit des membres des associations agrées en matière de sécurité civile | N71: Création Modification | Q71: Volontaire de service civique outre-mer | R71: P0179 | S71: N | T71: Particulier | U71: Exclu | V71: 40725
A72: 22.10.00 | B72: M | C72: 44917.702 | D72: D0007 | E72: Congés/Absence | F72: S0046 | G72: Autorisations d'absence | H72: E0433 | I72: Autorisation d'absence au profit des membres des associations agrées en matière de sécurité civile | J72: Type de congé/absence saisi égal 'Autorisation d'absence au profit des membres des associations agrées en matière de sécurité civile' | K72: A_COA_TYCOAB [Saisi] = 'CA013' | L72: T1094 | M72: Autorisation d'absence au profit des membres des associations agrées en matière de sécurité civile | N72: Création Modification | Q72: Ouvrier de la défense ou assimilé | R72: P0197 | S72: O | T72: Particulier | U72: Passant | V72: 40725 | X72: ADI_I_085 ET ADI_I_095 ET ADI_I_113 ET ADI_I_119 ET ADI_I_097 ET ABS_C_010 ET ABS_C_003 ET ABS_C_004 ET ABS_C_009 ET ABS_C_019 ET ABS_C_020 ET ABS_C_026 ET ABS_C_002 ET ABS_C_005 ET ABS_C_006 ET ABS_C_007 ET ABS_C_008 | Y72: ADI_I_085 | Z72: =VLOOKUP(Y72,'Axe 2 Règles de gestion'!$D$2:$F$354,3, FALSE) -> L'agent est membre d'une association agréée en matière de sécurité civile. | AA72: ADI_I_095 | AB72: =VLOOKUP(AA72,'Axe 2 Règles de gestion'!$D$2:$F$354,3, FALSE) -> L'agent doit fournir un justificatif certifiant qu'il a effectivement aidé à combattre le sinistre. | AC72: ADI_I_113 | AD72: =VLOOKUP(AC72,'Axe 2 Règles de gestion'!$D$2:$F$354,3, FALSE) -> L'agent doit obtenir l'accord de sa hiérarchie pour s'absenter s'il est sollicité en cas de mise en oeuvre du plan Orsec, ou par l'autorité de police compétente en cas d'accident, sinistre ou catastrophe. | AE72: ADI_I_119 | AF72: =VLOOKUP(AE72,'Axe 2 Règles de gestion'!$D$2:$F$354,3, FALSE) -> L'administration ne peut s'opposer à l'absence, sous réserve de nécessité de service. | AG72: ADI_I_097 | AH72: =VLOOKUP(AG72,'Axe 2 Règles de gestion'!$D$2:$F$354,3, FALSE) -> La durée de l'autorisation d'absence est augmentée de 48 heures de délai de route maximum aller-retour si le déplacement dépasse 200 kms aller. | BG72: ABS_C_010 | BH72: =VLOOKUP(BG72,'Axe 2 Règles de gestion'!$D$2:$F$354,3, FALSE) -> L'agent doit être en activité. | BI72: ABS_C_003 | BJ72: =VLOOKUP(BI72,'Axe 2 Règles de gestion'!$D$2:$F$354,3, FALSE) -> La date de début du congé/absence doit être antérieure ou égale à la date de fin réelle du congé/absence. | BK72: ABS_C_004 | BL72: =VLOOKUP(BK72,'Axe 2 Règles de gestion'!$D$2:$F$354,3, FALSE) -> La date de début du congé/absence doit être antérieure ou égale à la date de fin prévisionnelle du congé/absence. | BM72: ABS_C_009 | BN72: =VLOOKUP(BM72,'Axe 2 Règles de gestion'!$D$2:$F$354,3, FALSE) -> La date de fin réelle ou la date de fin prévisionnelle du congé/absence doit être saisie. | BO72: ABS_C_019 | BP72: =VLOOKUP(BO72,'Axe 2 Règles de gestion'!$D$2:$F$354,3, FALSE) -> Si l'absence ne commence pas par une demi-journée et si l'absence précédente ne finit pas par une demi journée, la date de début de l'absence saisie est postérieure à la date de fin réelle de l'absence précédente. | BQ72: ABS_C_020 | BR72: =VLOOKUP(BQ72,'Axe 2 Règles de gestion'!$D$2:$F$354,3, FALSE) -> Si l'absence ne commence pas par une demi-journée et si l'absence précédente ne finit pas par une demi journée, la date de début de l'absence saisie est postérieure à la date de fin prévisionnelle de l'absence précédente. | BS72: ABS_C_026 | BT72: =VLOOKUP(BS72,'Axe 2 Règles de gestion'!$D$2:$F$354,3, FALSE) -> Dans le cas d'un congé autre que CLM, CLD, CGM et CITIS, l'indicateur de requalification doit être à non et les impacts spécifiques à la requalification ne doivent pas être mobilisés ou l'impact rémunération est vide. | BU72: ABS_C_002 | BV72: =VLOOKUP(BU72,'Axe 2 Règles de gestion'!$D$2:$F$354,3, FALSE) -> La date de début du congé/absence doit être postérieure ou égale à la date de début du lien juridique. | BW72: ABS_C_005 | BX72: =VLOOKUP(BW72,'Axe 2 Règles de gestion'!$D$2:$F$354,3, FALSE) -> La date de fin réelle du congé/absence doit être antérieure ou égale à la date limite de fin réelle ou prévisionnelle du lien juridique. | BY72: ABS_C_006 | BZ72: =VLOOKUP(BY72,'Axe 2 Règles de gestion'!$D$2:$F$354,3, FALSE) -> La date de fin prévisionnelle du congé/absence doit être antérieure ou égale à la date limite de fin réelle ou prévisionnelle du lien juridique. | CA72: ABS_C_007 | CB72: =VLOOKUP(CA72,'Axe 2 Règles de gestion'!$D$2:$F$354,3, FALSE) -> La date de fin réelle du congé/absence doit être antérieure à la date limite de départ à la retraite. | CC72: ABS_C_008 | CD72: =VLOOKUP(CC72,'Axe 2 Règles de gestion'!$D$2:$F$354,3, FALSE) -> La date de fin prévisionnelle du congé/absence doit être antérieure à la date limite de départ à la retraite.
A73: 22.10.00 | B73: M | C73: 44925.581 | D73: D0007 | E73: Congés/Absence | F73: S0046 | G73: Autorisations d'absence | H73: E0434 | I73: Autorisation d'absence pour garde d'enfant | J73: Type de congé/absence saisi égal 'Autorisation d'absence pour garde d'enfant' | K73: A_COA_TYCOAB [Saisi] = 'CA014' | L73: T1095 | M73: Autorisation d'absence pour garde d'enfant | N73: Création Modification | Q73: Titulaire ou magistrat | R73: P0001 | S73: T | T73: Général | U73: Passant | V73: 40725 | X73: ADI_I_072 ET ADI_I_067 ET ADI_I_065 ET ADI_I_071 ET ADI_I_066 ET ADI_I_109 ET ADI_I_110 ET ADI_I_111 ET ADI_I_112 ET ADI_D_008 ET ADI_D_402 ET ADI_D_403 ET ABS_C_010 ET ABS_C_001 ET ABS_C_003 ET ABS_C_004 ET ABS_C_007 ET ABS_C_008 ET ABS_C_009 ET ABS_C_019 ET ABS_C_020 ET ABS_C_026 ET ABS_C_038 ET ABS_C_039 | Y73: ADI_I_072 | Z73: =VLOOKUP(Y73,'Axe 2 Règles de gestion'!$D$2:$F$354,3, FALSE) -> L'agent doit être le père ou la mère de l'enfant ou en avoir la charge. | AA73: ADI_I_067 | AB73: =VLOOKUP(AA73,'Axe 2 Règles de gestion'!$D$2:$F$354,3, FALSE) -> L'autorisation d'absence est accordée sous réserve des nécessités de service. | AC73: ADI_I_065 | AD73: =VLOOKUP(AC73,'Axe 2 Règles de gestion'!$D$2:$F$354,3, FALSE) -> L'agent doit fournir un certificat médical ou toute autre pièce justifiant la présence du parent auprès de l'enfant. | AE73: ADI_I_071 | AF73: =VLOOKUP(AE73,'Axe 2 Règles de gestion'!$D$2:$F$354,3, FALSE) -> Le nombre de jours d'autorisation d'absence est accordé par famille, quel que soit le nombre d'enfants. | AG73: ADI_I_066 | AH73: =VLOOKUP(AG73,'Axe 2 Règles de gestion'!$D$2:$F$354,3, FALSE) -> Le décompte des jours est fait par année civile ou par année scolaire pour les agents travaillant selon le cycle scolaire. Aucun report n'est possible d'une année sur l'autre. | AI73: ADI_I_109 | AJ73: =VLOOKUP(AI73,'Axe 2 Règles de gestion'!$D$2:$F$354,3, FALSE) -> La durée totale de l'autorisation d'absence ne pourra dépasser les obligations hebdomadaires de service plus 1 jour, pour un agent à temps plein. | AK73: ADI_I_110 | AL73: =VLOOKUP(AK73,'Axe 2 Règles de gestion'!$D$2:$F$354,3, FALSE) -> Pour un agent à temps partiel, la durée est celle accordée à un agent à temps plein, à laquelle on applique la quotité de travail de l'agent concerné. | AM73: ADI_I_111 | AN73: =VLOOKUP(AM73,'Axe 2 Règles de gestion'!$D$2:$F$354,3, FALSE) -> Les durées totales précédentes sont portées à 2 fois les obligations de service plus 2 jours si l'agent justifie qu'il assume seul la garde de l'enfant ou que son conjoint est en recherche d'emploi ou ne bénéficie d'aucune autorisation d'absence. | AO73: ADI_I_112 | AP73: =VLOOKUP(AO73,'Axe 2 Règles de gestion'!$D$2:$F$354,3, FALSE) -> Si les deux parents sont agents de l'Etat, les autorisations d'absence peuvent être réparties entre eux à leur convenance. | AQ73: ADI_D_008 | AR73: =VLOOKUP(AQ73,'Axe 2 Règles de gestion'!$D$2:$F$354,3, FALSE) -> L'enfant doit avoir moins de 16 ans (date de fin réelle). Aucune limite d'âge ne s'applique si l'enfant est handicapé. | AS73: ADI_D_402 | AT73: =VLOOKUP(AS73,'Axe 2 Règles de gestion'!$D$2:$F$354,3, FALSE) -> L'enfant doit avoir moins de 16 ans (date de fin prévisionnelle). Aucune limite d'âge ne s'applique si l'enfant est handicapé. | AU73: ADI_D_403 | AV73: =VLOOKUP(AU73,'Axe 2 Règles de gestion'!$D$2:$F$354,3, FALSE) -> L'agent doit avoir un enfant lié à cette absence. | BG73: ABS_C_010 | BH73: =VLOOKUP(BG73,'Axe 2 Règles de gestion'!$D$2:$F$354,3, FALSE) -> L'agent doit être en activité. | BI73: ABS_C_001 | BJ73: =VLOOKUP(BI73,'Axe 2 Règles de gestion'!$D$2:$F$354,3, FALSE) -> La date de début du congé/absence doit être postérieure ou égale à la date de recrutement dans la FPE ou dans la carrière militaire. | BK73: ABS_C_003 | BL73: =VLOOKUP(BK73,'Axe 2 Règles de gestion'!$D$2:$F$354,3, FALSE) -> La date de début du congé/absence doit être antérieure ou égale à la date de fin réelle du congé/absence. | BM73: ABS_C_004 | BN73: =VLOOKUP(BM73,'Axe 2 Règles de gestion'!$D$2:$F$354,3, FALSE) -> La date de début du congé/absence doit être antérieure ou égale à la date de fin prévisionnelle du congé/absence. | BO73: ABS_C_007 | BP73: =VLOOKUP(BO73,'Axe 2 Règles de gestion'!$D$2:$F$354,3, FALSE) -> La date de fin réelle du congé/absence doit être antérieure à la date limite de départ à la retraite. | BQ73: ABS_C_008 | BR73: =VLOOKUP(BQ73,'Axe 2 Règles de gestion'!$D$2:$F$354,3, FALSE) -> La date de fin prévisionnelle du congé/absence doit être antérieure à la date limite de départ à la retraite. | BS73: ABS_C_009 | BT73: =VLOOKUP(BS73,'Axe 2 Règles de gestion'!$D$2:$F$354,3, FALSE) -> La date de fin réelle ou la date de fin prévisionnelle du congé/absence doit être saisie. | BU73: ABS_C_019 | BV73: =VLOOKUP(BU73,'Axe 2 Règles de gestion'!$D$2:$F$354,3, FALSE) -> Si l'absence ne commence pas par une demi-journée et si l'absence précédente ne finit pas par une demi journée, la date de début de l'absence saisie est postérieure à la date de fin réelle de l'absence précédente. | BW73: ABS_C_020 | BX73: =VLOOKUP(BW73,'Axe 2 Règles de gestion'!$D$2:$F$354,3, FALSE) -> Si l'absence ne commence pas par une demi-journée et si l'absence précédente ne finit pas par une demi journée, la date de début de l'absence saisie est postérieure à la date de fin prévisionnelle de l'absence précédente. | BY73: ABS_C_026 | BZ73: =VLOOKUP(BY73,'Axe 2 Règles de gestion'!$D$2:$F$354,3, FALSE) -> Dans le cas d'un congé autre que CLM, CLD, CGM et CITIS, l'indicateur de requalification doit être à non et les impacts spécifiques à la requalification ne doivent pas être mobilisés ou l'impact rémunération est vide. | CA73: ABS_C_038 | CB73: =VLOOKUP(CA73,'Axe 2 Règles de gestion'!$D$2:$F$354,3, FALSE) -> Le congé prend fin à la date de décès de l'enfant (date de fin réelle). | CC73: ABS_C_039 | CD73: =VLOOKUP(CC73,'Axe 2 Règles de gestion'!$D$2:$F$354,3, FALSE) -> Le congé prend fin à la date de décès de l'enfant (date de fin prévisionnelle).
A74: 22.10.00 | B74: M | C74: 44925.58 | D74: D0007 | E74: Congés/Absence | F74: S0046 | G74: Autorisations d'absence | H74: E0434 | I74: Autorisation d'absence pour garde d'enfant | J74: Type de congé/absence saisi égal 'Autorisation d'absence pour garde d'enfant' | K74: A_COA_TYCOAB [Saisi] = 'CA014' | L74: T1095 | M74: Autorisation d'absence pour garde d'enfant | N74: Création Modification | Q74: Contractuel | R74: P0003 | S74: N | T74: Général | U74: Passant | V74: 40725 | X74: ADI_I_072 ET ADI_I_067 ET ADI_I_065 ET ADI_I_071 ET ADI_I_066 ET ADI_I_109 ET ADI_I_110 ET ADI_I_111 ET ADI_I_112 ET ADI_D_008 ET ADI_D_402 ET ADI_D_403 ET ABS_C_010 ET ABS_C_003 ET ABS_C_004 ET ABS_C_009 ET ABS_C_019 ET ABS_C_020 ET ABS_C_026 ET ABS_C_002 ET ABS_C_005 ET ABS_C_006 ET ABS_C_007 ET ABS_C_008 ET ABS_C_038 ET ABS_C_039 | Y74: ADI_I_072 | Z74: =VLOOKUP(Y74,'Axe 2 Règles de gestion'!$D$2:$F$354,3, FALSE) -> L'agent doit être le père ou la mère de l'enfant ou en avoir la charge. | AA74: ADI_I_067 | AB74: =VLOOKUP(AA74,'Axe 2 Règles de gestion'!$D$2:$F$354,3, FALSE) -> L'autorisation d'absence est accordée sous réserve des nécessités de service. | AC74: ADI_I_065 | AD74: =VLOOKUP(AC74,'Axe 2 Règles de gestion'!$D$2:$F$354,3, FALSE) -> L'agent doit fournir un certificat médical ou toute autre pièce justifiant la présence du parent auprès de l'enfant. | AE74: ADI_I_071 | AF74: =VLOOKUP(AE74,'Axe 2 Règles de gestion'!$D$2:$F$354,3, FALSE) -> Le nombre de jours d'autorisation d'absence est accordé par famille, quel que soit le nombre d'enfants. | AG74: ADI_I_066 | AH74: =VLOOKUP(AG74,'Axe 2 Règles de gestion'!$D$2:$F$354,3, FALSE) -> Le décompte des jours est fait par année civile ou par année scolaire pour les agents travaillant selon le cycle scolaire. Aucun report n'est possible d'une année sur l'autre. | AI74: ADI_I_109 | AJ74: =VLOOKUP(AI74,'Axe 2 Règles de gestion'!$D$2:$F$354,3, FALSE) -> La durée totale de l'autorisation d'absence ne pourra dépasser les obligations hebdomadaires de service plus 1 jour, pour un agent à temps plein. | AK74: ADI_I_110 | AL74: =VLOOKUP(AK74,'Axe 2 Règles de gestion'!$D$2:$F$354,3, FALSE) -> Pour un agent à temps partiel, la durée est celle accordée à un agent à temps plein, à laquelle on applique la quotité de travail de l'agent concerné. | AM74: ADI_I_111 | AN74: =VLOOKUP(AM74,'Axe 2 Règles de gestion'!$D$2:$F$354,3, FALSE) -> Les durées totales précédentes sont portées à 2 fois les obligations de service plus 2 jours si l'agent justifie qu'il assume seul la garde de l'enfant ou que son conjoint est en recherche d'emploi ou ne bénéficie d'aucune autorisation d'absence. | AO74: ADI_I_112 | AP74: =VLOOKUP(AO74,'Axe 2 Règles de gestion'!$D$2:$F$354,3, FALSE) -> Si les deux parents sont agents de l'Etat, les autorisations d'absence peuvent être réparties entre eux à leur convenance. | AQ74: ADI_D_008 | AR74: =VLOOKUP(AQ74,'Axe 2 Règles de gestion'!$D$2:$F$354,3, FALSE) -> L'enfant doit avoir moins de 16 ans (date de fin réelle). Aucune limite d'âge ne s'applique si l'enfant est handicapé. | AS74: ADI_D_402 | AT74: =VLOOKUP(AS74,'Axe 2 Règles de gestion'!$D$2:$F$354,3, FALSE) -> L'enfant doit avoir moins de 16 ans (date de fin prévisionnelle). Aucune limite d'âge ne s'applique si l'enfant est handicapé. | AU74: ADI_D_403 | AV74: =VLOOKUP(AU74,'Axe 2 Règles de gestion'!$D$2:$F$354,3, FALSE) -> L'agent doit avoir un enfant lié à cette absence. | BG74: ABS_C_010 | BH74: =VLOOKUP(BG74,'Axe 2 Règles de gestion'!$D$2:$F$354,3, FALSE) -> L'agent doit être en activité. | BI74: ABS_C_003 | BJ74: =VLOOKUP(BI74,'Axe 2 Règles de gestion'!$D$2:$F$354,3, FALSE) -> La date de début du congé/absence doit être antérieure ou égale à la date de fin réelle du congé/absence. | BK74: ABS_C_004 | BL74: =VLOOKUP(BK74,'Axe 2 Règles de gestion'!$D$2:$F$354,3, FALSE) -> La date de début du congé/absence doit être antérieure ou égale à la date de fin prévisionnelle du congé/absence. | BM74: ABS_C_009 | BN74: =VLOOKUP(BM74,'Axe 2 Règles de gestion'!$D$2:$F$354,3, FALSE) -> La date de fin réelle ou la date de fin prévisionnelle du congé/absence doit être saisie. | BO74: ABS_C_019 | BP74: =VLOOKUP(BO74,'Axe 2 Règles de gestion'!$D$2:$F$354,3, FALSE) -> Si l'absence ne commence pas par une demi-journée et si l'absence précédente ne finit pas par une demi journée, la date de début de l'absence saisie est postérieure à la date de fin réelle de l'absence précédente. | BQ74: ABS_C_020 | BR74: =VLOOKUP(BQ74,'Axe 2 Règles de gestion'!$D$2:$F$354,3, FALSE) -> Si l'absence ne commence pas par une demi-journée et si l'absence précédente ne finit pas par une demi journée, la date de début de l'absence saisie est postérieure à la date de fin prévisionnelle de l'absence précédente. | BS74: ABS_C_026 | BT74: =VLOOKUP(BS74,'Axe 2 Règles de gestion'!$D$2:$F$354,3, FALSE) -> Dans le cas d'un congé autre que CLM, CLD, CGM et CITIS, l'indicateur de requalification doit être à non et les impacts spécifiques à la requalification ne doivent pas être mobilisés ou l'impact rémunération est vide. | BU74: ABS_C_002 | BV74: =VLOOKUP(BU74,'Axe 2 Règles de gestion'!$D$2:$F$354,3, FALSE) -> La date de début du congé/absence doit être postérieure ou égale à la date de début du lien juridique. | BW74: ABS_C_005 | BX74: =VLOOKUP(BW74,'Axe 2 Règles de gestion'!$D$2:$F$354,3, FALSE) -> La date de fin réelle du congé/absence doit être antérieure ou égale à la date limite de fin réelle ou prévisionnelle du lien juridique. | BY74: ABS_C_006 | BZ74: =VLOOKUP(BY74,'Axe 2 Règles de gestion'!$D$2:$F$354,3, FALSE) -> La date de fin prévisionnelle du congé/absence doit être antérieure ou égale à la date limite de fin réelle ou prévisionnelle du lien juridique. | CA74: ABS_C_007 | CB74: =VLOOKUP(CA74,'Axe 2 Règles de gestion'!$D$2:$F$354,3, FALSE) -> La date de fin réelle du congé/absence doit être antérieure à la date limite de départ à la retraite. | CC74: ABS_C_008 | CD74: =VLOOKUP(CC74,'Axe 2 Règles de gestion'!$D$2:$F$354,3, FALSE) -> La date de fin prévisionnelle du congé/absence doit être antérieure à la date limite de départ à la retraite. | CE74: ABS_C_038 | CF74: =VLOOKUP(CE74,'Axe 2 Règles de gestion'!$D$2:$F$354,3, FALSE) -> Le congé prend fin à la date de décès de l'enfant (date de fin réelle). | CG74: ABS_C_039 | CH74: =VLOOKUP(CG74,'Axe 2 Règles de gestion'!$D$2:$F$354,3, FALSE) -> Le congé prend fin à la date de décès de l'enfant (date de fin prévisionnelle).
