Workbook

Sheet Mode opératoire
B1: MODE OPERATOIRE
B2: La transaction s'effectue au niveau de la rubrique "Congés/absences", elle inclut l'ensemble des sous-rubriques listées ci-dessous : - Congés/absences - Complément pour congé / absence : impact rémunération - Compteurs de périodes de congés On notera que : La sous-rubrique "Complément pour congé / absence : impact rémunération" est réputée, suite au découpage des absences en tranche de rémunération, avoir des dates de début et de fin alignées sur les dates de début et de fin de la sous-rubrique "Congés/absences" (contrôle bloquant) Parmi les non titulaires, les populations suivantes ne sont pas traitées pour le moment : - Les enseignants contractuels ou agréés d'établissement privé sous contrat d'association ou sous contrat simple à titre définitif ou à titre provisoire - MEN - Les maitres délégués d'établissement privé sous contrat d'association - MEN

Sheet Axe 1 Enchainement des RG
A1: Version | B1: Type de mise à jour | C1: Date de mise à jour | D1: Identifiant Domaine | E1: Libellé du Domaine | F1: Identifiant Sous-domaine | G1: Libellé du Sous-domaine | H1: Identifiant Evénement | I1: Libellé de l'évènement | J1: Libellé condition déclenchement Evènement | K1: Condition déclenchement Evènement | L1: Identifiant type d'évènement | M1: Libellé type d'évènement | N1: Type de mise à jour | O1: Libellé condition déclenchement Type Evènement | P1: Condition déclenchement Type Evènement | Q1: Libellé Population | R1: Codification Population | S1: Général / Particulier | T1: Passant / Exclu | U1: Date de début | V1: Date de fin | W1: Règles mobilisées | X1: Identifiant Règle de contrôle intellectuel 1 | Y1: Libellé Règle de contrôle intellectuel 1 | Z1: Identifiant Règle de contrôle intellectuel 2 | AA1: Libellé Règle de contrôle intellectuel 2 | AB1: Identifiant Règle de contrôle intellectuel 3 | AC1: Libellé Règle de contrôle intellectuel 3 | AD1: Identifiant Règle de contrôle intellectuel 4 | AE1: Libellé Règle de contrôle intellectuel 4 | AF1: Identifiant Règle de contrôle intellectuel 5 | AG1: Libellé Règle de contrôle intellectuel 5 | AH1: Identifiant Règle de contrôle intellectuel 6 | AI1: Libellé Règle de contrôle intellectuel 6 | AJ1: Identifiant Règle de contrôle intellectuel 7 | AK1: Libellé Règle de contrôle intellectuel 7 | AL1: Identifiant Règle de contrôle intellectuel 8 | AM1: Libellé Règle de contrôle intellectuel 8 | AN1: Identifiant Règle de contrôle intellectuel 9 | AO1: Libellé Règle de contrôle intellectuel 9 | AP1: Identifiant Règle de contrôle intellectuel 10 | AQ1: Libellé Règle de contrôle intellectuel 10 | AR1: Identifiant Règle de contrôle intellectuel 11 | AS1: Libellé Règle de contrôle intellectuel 11 | AT1: Identifiant Règle de condition 1 | AU1: Libellé Règle de condition 1 | AV1: Identifiant Règle de condition 2 | AW1: Libellé Règle de condition 2 | AX1: Identifiant Règle de condition 3 | AY1: Libellé Règle de condition 3 | AZ1: Identifiant Règle de condition 4 | BA1: Libellé Règle de condition 4 | BB1: Identifiant Règle de condition 5 | BC1: Libellé Règle de condition 5 | BD1: Identifiant Règle de condition 6 | BE1: Libellé Règle de condition 6 | BF1: Identifiant Règle de contrôle 1 | BG1: Libellé Règle de contrôle 1 | BH1: Identifiant Règle de contrôle 2 | BI1: Libellé Règle de contrôle 2 | BJ1: Identifiant Règle de contrôle 3 | BK1: Libellé Règle de contrôle 3 | BL1: Identifiant Règle de contrôle 4 | BM1: Libellé Règle de contrôle 4 | BN1: Identifiant Règle de contrôle 5 | BO1: Libellé Règle de contrôle 5 | BP1: Identifiant Règle de contrôle 6 | BQ1: Libellé Règle de contrôle 6 | BR1: Identifiant Règle de contrôle 7 | BS1: Libellé Règle de contrôle 7 | BT1: Identifiant Règle de contrôle 8 | BU1: Libellé Règle de contrôle 8 | BV1: Identifiant Règle de contrôle 9 | BW1: Libellé Règle de contrôle 9 | BX1: Identifiant Règle de contrôle 10 | BY1: Libellé Règle de contrôle 10 | BZ1: Identifiant Règle de contrôle 11 | CA1: Libellé Règle de contrôle 11 | CB1: Identifiant Règle de contrôle 12 | CC1: Libellé Règle de contrôle 12 | CD1: Identifiant Règle de contrôle 13 | CE1: Libellé Règle de contrôle 13 | CF1: Identifiant Règle de contrôle 14 | CG1: Libellé Règle de contrôle 14 | CH1: FIME | CI1: Statut de travail
A2: 21.00.00 | B2: M | C2: 44337.578 | D2: D0007 | E2: Congés/Absence | F2: S0072 | G2: Congé pour raisons de famille | H2: E0499 | I2: Congé d'accompagnement d'une personne en fin de vie | J2: Le Type de congé/absence est 'Congé d'accompagnement d'une personne en fin de vie' | K2: A_COA_TYCOAB [Saisi] = 'CG100' | L2: T1204 | M2: Congé d'accompagnement d'une personne en fin de vie - Demande | N2: Création | Q2: Titulaire ou magistrat | R2: P0001 | S2: Général | T2: Exclu | U2: 40725 | V2: 44561
A3: 21.00.00 | B3: M | C3: 44337.584 | D3: D0007 | E3: Congés/Absence | F3: S0072 | G3: Congé pour raisons de famille | H3: E0499 | I3: Congé d'accompagnement d'une personne en fin de vie | J3: Le Type de congé/absence est 'Congé d'accompagnement d'une personne en fin de vie' | K3: A_COA_TYCOAB [Saisi] = 'CG100' | L3: T1205 | M3: Congé d'accompagnement d'une personne en fin de vie - Fin | N3: Modification | Q3: Titulaire ou magistrat | R3: P0001 | S3: Général | T3: Exclu | U3: 40725 | V3: 44561
A4: 18.10.00 | B4: M | C4: 43152.5 | D4: D0007 | E4: Congés/Absence | F4: S0072 | G4: Congé pour raisons de famille | H4: E0499 | I4: Congé d'accompagnement d'une personne en fin de vie | J4: Le Type de congé/absence est 'Congé d'accompagnement d'une personne en fin de vie' | K4: A_COA_TYCOAB [Saisi] = 'CG100' | L4: T1204 | M4: Congé d'accompagnement d'une personne en fin de vie - Demande | N4: Création | Q4: Contractuel | R4: P0003 | S4: Général | T4: Passant | U4: 40725 | V4: 41294 | W4: CDI_D_236 ET CDI_D_240 ET CDI_D_600 ET ABS_C_002 ET ABS_C_003 ET ABS_C_004 ET ABS_C_005 ET ABS_C_006 ET ABS_C_007 ET ABS_C_008 ET ABS_C_009 ET ABS_C_019 ET ABS_C_020 ET ABS_C_026 | AT4: CDI_D_236 | AU4: =VLOOKUP(AT4,'Axe 2 Règles de gestion'!$D$2:$F$564,3, FALSE) -> L'agent doit être en activité. | AV4: CDI_D_240 | AW4: =VLOOKUP(AV4,'Axe 2 Règles de gestion'!$D$2:$F$564,3, FALSE) -> La durée réelle maximale du congé d'accompagnement d'une personne en fin de vie est de 3 mois par personne accompagnée. | AX4: CDI_D_600 | AY4: =VLOOKUP(AX4,'Axe 2 Règles de gestion'!$D$2:$F$564,3, FALSE) -> La durée prévisionnelle maximale du congé d'accompagnement d'une personne en fin de vie est de 3 mois par personne accompagnée. | BF4: ABS_C_002 | BG4: =VLOOKUP(BF4,'Axe 2 Règles de gestion'!$D$2:$F$564,3, FALSE) -> La date de début du congé/absence doit être postérieure ou égale à la date de début du lien juridique. | BH4: ABS_C_003 | BI4: =VLOOKUP(BH4,'Axe 2 Règles de gestion'!$D$2:$F$564,3, FALSE) -> La date de début du congé/absence doit être antérieure ou égale à la date de fin réelle du congé/absence. | BJ4: ABS_C_004 | BK4: =VLOOKUP(BJ4,'Axe 2 Règles de gestion'!$D$2:$F$564,3, FALSE) -> La date de début du congé/absence doit être antérieure ou égale à la date de fin prévisionnelle du congé/absence. | BL4: ABS_C_005 | BM4: =VLOOKUP(BL4,'Axe 2 Règles de gestion'!$D$2:$F$564,3, FALSE) -> La date de fin réelle du congé/absence doit être antérieure ou égale à la date limite de fin réelle ou prévisionnelle du lien juridique. | BN4: ABS_C_006 | BO4: =VLOOKUP(BN4,'Axe 2 Règles de gestion'!$D$2:$F$564,3, FALSE) -> La date de fin prévisionnelle du congé/absence doit être antérieure ou égale à la date limite de fin réelle ou prévisionnelle du lien juridique. | BP4: ABS_C_007 | BQ4: =VLOOKUP(BP4,'Axe 2 Règles de gestion'!$D$2:$F$564,3, FALSE) -> La date de fin réelle du congé/absence doit être antérieure à la date limite de départ à la retraite. | BR4: ABS_C_008 | BS4: =VLOOKUP(BR4,'Axe 2 Règles de gestion'!$D$2:$F$564,3, FALSE) -> La date de fin prévisionnelle du congé/absence doit être antérieure à la date limite de départ à la retraite. | BT4: ABS_C_009 | BU4: =VLOOKUP(BT4,'Axe 2 Règles de gestion'!$D$2:$F$564,3, FALSE) -> La date de fin réelle ou la date de fin prévisionnelle du congé/absence doit être saisie. | BV4: ABS_C_019 | BW4: =VLOOKUP(BV4,'Axe 2 Règles de gestion'!$D$2:$F$564,3, FALSE) -> Si l'absence ne commence pas par une demi-journée et si l'absence précédente ne finit pas par une demi journée, la date de début de l'absence saisie est postérieure à la date de fin réelle de l'absence précédente. | BX4: ABS_C_020 | BY4: =VLOOKUP(BX4,'Axe 2 Règles de gestion'!$D$2:$F$564,3, FALSE) -> Si l'absence ne commence pas par une demi-journée et si l'absence précédente ne finit pas par une demi journée, la date de début de l'absence saisie est postérieure à la date de fin prévisionnelle de l'absence précédente. | BZ4: ABS_C_026 | CA4: =VLOOKUP(BZ4,'Axe 2 Règles de gestion'!$D$2:$F$564,3, FALSE) -> Dans le cas d'un congé autre que CLM, CLD, CGM et CITIS, l'indicateur de requalification doit être à non et les impacts spécifiques à la requalification ne doivent pas être mobilisés ou l'impact rémunération est vide.
A5: 21.00.00 | B5: M | C5: 44337.58 | D5: D0007 | E5: Congés/Absence | F5: S0072 | G5: Congé pour raisons de famille | H5: E0499 | I5: Congé d'accompagnement d'une personne en fin de vie | J5: Le Type de congé/absence est 'Congé d'accompagnement d'une personne en fin de vie' | K5: A_COA_TYCOAB [Saisi] = 'CG100' | L5: T1204 | M5: Congé d'accompagnement d'une personne en fin de vie - Demande | N5: Création | Q5: Contractuel | R5: P0003 | S5: Général | T5: Exclu | U5: 41295 | V5: 44561
A6: 18.10.00 | B6: M | C6: 43152.5 | D6: D0007 | E6: Congés/Absence | F6: S0072 | G6: Congé pour raisons de famille | H6: E0499 | I6: Congé d'accompagnement d'une personne en fin de vie | J6: Le Type de congé/absence est 'Congé d'accompagnement d'une personne en fin de vie' | K6: A_COA_TYCOAB [Saisi] = 'CG100' | L6: T1205 | M6: Congé d'accompagnement d'une personne en fin de vie - Fin | N6: Modification | Q6: Contractuel | R6: P0003 | S6: Général | T6: Passant | U6: 40725 | V6: 41294 | W6: CDI_D_240 ET CDI_D_600 ET ABS_C_003 ET ABS_C_004 ET ABS_C_005 ET ABS_C_006 ET ABS_C_007 ET ABS_C_008 ET ABS_C_009 ET ABS_C_026 | AT6: CDI_D_240 | AU6: =VLOOKUP(AT6,'Axe 2 Règles de gestion'!$D$2:$F$564,3, FALSE) -> La durée réelle maximale du congé d'accompagnement d'une personne en fin de vie est de 3 mois par personne accompagnée. | AV6: CDI_D_600 | AW6: =VLOOKUP(AV6,'Axe 2 Règles de gestion'!$D$2:$F$564,3, FALSE) -> La durée prévisionnelle maximale du congé d'accompagnement d'une personne en fin de vie est de 3 mois par personne accompagnée. | BF6: ABS_C_003 | BG6: =VLOOKUP(BF6,'Axe 2 Règles de gestion'!$D$2:$F$564,3, FALSE) -> La date de début du congé/absence doit être antérieure ou égale à la date de fin réelle du congé/absence. | BH6: ABS_C_004 | BI6: =VLOOKUP(BH6,'Axe 2 Règles de gestion'!$D$2:$F$564,3, FALSE) -> La date de début du congé/absence doit être antérieure ou égale à la date de fin prévisionnelle du congé/absence. | BJ6: ABS_C_005 | BK6: =VLOOKUP(BJ6,'Axe 2 Règles de gestion'!$D$2:$F$564,3, FALSE) -> La date de fin réelle du congé/absence doit être antérieure ou égale à la date limite de fin réelle ou prévisionnelle du lien juridique. | BL6: ABS_C_006 | BM6: =VLOOKUP(BL6,'Axe 2 Règles de gestion'!$D$2:$F$564,3, FALSE) -> La date de fin prévisionnelle du congé/absence doit être antérieure ou égale à la date limite de fin réelle ou prévisionnelle du lien juridique. | BN6: ABS_C_007 | BO6: =VLOOKUP(BN6,'Axe 2 Règles de gestion'!$D$2:$F$564,3, FALSE) -> La date de fin réelle du congé/absence doit être antérieure à la date limite de départ à la retraite. | BP6: ABS_C_008 | BQ6: =VLOOKUP(BP6,'Axe 2 Règles de gestion'!$D$2:$F$564,3, FALSE) -> La date de fin prévisionnelle du congé/absence doit être antérieure à la date limite de départ à la retraite. | BR6: ABS_C_009 | BS6: =VLOOKUP(BR6,'Axe 2 Règles de gestion'!$D$2:$F$564,3, FALSE) -> La date de fin réelle ou la date de fin prévisionnelle du congé/absence doit être saisie. | BT6: ABS_C_026 | BU6: =VLOOKUP(BT6,'Axe 2 Règles de gestion'!$D$2:$F$564,3, FALSE) -> Dans le cas d'un congé autre que CLM, CLD, CGM et CITIS, l'indicateur de requalification doit être à non et les impacts spécifiques à la requalification ne doivent pas être mobilisés ou l'impact rémunération est vide.
A7: 21.00.00 | B7: M | C7: 44337.583 | D7: D0007 | E7: Congés/Absence | F7: S0072 | G7: Congé pour raisons de famille | H7: E0499 | I7: Congé d'accompagnement d'une personne en fin de vie | J7: Le Type de congé/absence est 'Congé d'accompagnement d'une personne en fin de vie' | K7: A_COA_TYCOAB [Saisi] = 'CG100' | L7: T1205 | M7: Congé d'accompagnement d'une personne en fin de vie - Fin | N7: Modification | Q7: Contractuel | R7: P0003 | S7: Général | T7: Exclu | U7: 41295 | V7: 44561
A8: 21.00.00 | B8: M | C8: 44337.579 | D8: D0007 | E8: Congés/Absence | F8: S0072 | G8: Congé pour raisons de famille | H8: E0499 | I8: Congé d'accompagnement d'une personne en fin de vie | J8: Le Type de congé/absence est 'Congé d'accompagnement d'une personne en fin de vie' | K8: A_COA_TYCOAB [Saisi] = 'CG100' | L8: T1204 | M8: Congé d'accompagnement d'une personne en fin de vie - Demande | N8: Création | Q8: Stagiaire ou auditeur ou élève | R8: P0004 | S8: Général | T8: Exclu | U8: 40725 | V8: 44561
A9: 21.00.00 | B9: M | C9: 44337.584 | D9: D0007 | E9: Congés/Absence | F9: S0072 | G9: Congé pour raisons de famille | H9: E0499 | I9: Congé d'accompagnement d'une personne en fin de vie | J9: Le Type de congé/absence est 'Congé d'accompagnement d'une personne en fin de vie' | K9: A_COA_TYCOAB [Saisi] = 'CG100' | L9: T1205 | M9: Congé d'accompagnement d'une personne en fin de vie - Fin | N9: Modification | Q9: Stagiaire ou auditeur ou élève | R9: P0004 | S9: Général | T9: Exclu | U9: 40725 | V9: 44561
A10: 21.00.00 | B10: M | C10: 44337.462 | D10: D0007 | E10: Congés/Absence | F10: S0072 | G10: Congé pour raisons de famille | H10: E0499 | I10: Congé d'accompagnement d'une personne en fin de vie | J10: Le Type de congé/absence est 'Congé d'accompagnement d'une personne en fin de vie' | K10: A_COA_TYCOAB [Saisi] = 'CG100' | L10: T1204 | M10: Congé d'accompagnement d'une personne en fin de vie - Demande | N10: Création | Q10: Ouvrier d'état | R10: P0005 | S10: Général | T10: Passant | U10: 40725 | V10: 44561 | W10: CDI_I_177 ET CDI_I_176 ET CDI_D_163 ET CDI_D_617 ET CDI_D_158 ET ABS_C_002 ET ABS_C_003 ET ABS_C_004 ET ABS_C_005 ET ABS_C_006 ET ABS_C_007 ET ABS_C_008 ET ABS_C_009 ET ABS_C_019 ET ABS_C_020 ET ABS_C_026 | X10: CDI_I_177 | Y10: =VLOOKUP(X10,'Axe 2 Règles de gestion'!$D$2:$F$564,3, FALSE) -> L'agent doit faire une demande écrite auprès de l'administration. | Z10: CDI_I_176 | AA10: =VLOOKUP(Z10,'Axe 2 Règles de gestion'!$D$2:$F$564,3, FALSE) -> Ce congé est de droit lorsqu'un ascendant, un descendant ou une personne partageant le domicile de l'agent fait l'objet de soins palliatifs. | AT10: CDI_D_163 | AU10: =VLOOKUP(AT10,'Axe 2 Règles de gestion'!$D$2:$F$564,3, FALSE) -> La durée réelle maximale du congé d'accompagnement d'une personne en fin de vie est de 3 mois par personne accompagnée. | AV10: CDI_D_617 | AW10: =VLOOKUP(AV10,'Axe 2 Règles de gestion'!$D$2:$F$564,3, FALSE) -> La durée prévisionnelle maximale du congé d'accompagnement d'une personne en fin de vie est de 3 mois par personne accompagnée. | AX10: CDI_D_158 | AY10: =VLOOKUP(AX10,'Axe 2 Règles de gestion'!$D$2:$F$564,3, FALSE) -> L'agent doit être en activité. | BF10: ABS_C_002 | BG10: =VLOOKUP(BF10,'Axe 2 Règles de gestion'!$D$2:$F$564,3, FALSE) -> La date de début du congé/absence doit être postérieure ou égale à la date de début du lien juridique. | BH10: ABS_C_003 | BI10: =VLOOKUP(BH10,'Axe 2 Règles de gestion'!$D$2:$F$564,3, FALSE) -> La date de début du congé/absence doit être antérieure ou égale à la date de fin réelle du congé/absence. | BJ10: ABS_C_004 | BK10: =VLOOKUP(BJ10,'Axe 2 Règles de gestion'!$D$2:$F$564,3, FALSE) -> La date de début du congé/absence doit être antérieure ou égale à la date de fin prévisionnelle du congé/absence. | BL10: ABS_C_005 | BM10: =VLOOKUP(BL10,'Axe 2 Règles de gestion'!$D$2:$F$564,3, FALSE) -> La date de fin réelle du congé/absence doit être antérieure ou égale à la date limite de fin réelle ou prévisionnelle du lien juridique. | BN10: ABS_C_006 | BO10: =VLOOKUP(BN10,'Axe 2 Règles de gestion'!$D$2:$F$564,3, FALSE) -> La date de fin prévisionnelle du congé/absence doit être antérieure ou égale à la date limite de fin réelle ou prévisionnelle du lien juridique. | BP10: ABS_C_007 | BQ10: =VLOOKUP(BP10,'Axe 2 Règles de gestion'!$D$2:$F$564,3, FALSE) -> La date de fin réelle du congé/absence doit être antérieure à la date limite de départ à la retraite. | BR10: ABS_C_008 | BS10: =VLOOKUP(BR10,'Axe 2 Règles de gestion'!$D$2:$F$564,3, FALSE) -> La date de fin prévisionnelle du congé/absence doit être antérieure à la date limite de départ à la retraite. | BT10: ABS_C_009 | BU10: =VLOOKUP(BT10,'Axe 2 Règles de gestion'!$D$2:$F$564,3, FALSE) -> La date de fin réelle ou la date de fin prévisionnelle du congé/absence doit être saisie. | BV10: ABS_C_019 | BW10: =VLOOKUP(BV10,'Axe 2 Règles de gestion'!$D$2:$F$564,3, FALSE) -> Si l'absence ne commence pas par une demi-journée et si l'absence précédente ne finit pas par une demi journée, la date de début de l'absence saisie est postérieure à la date de fin réelle de l'absence précédente. | BX10: ABS_C_020 | BY10: =VLOOKUP(BX10,'Axe 2 Règles de gestion'!$D$2:$F$564,3, FALSE) -> Si l'absence ne commence pas par une demi-journée et si l'absence précédente ne finit pas par une demi journée, la date de début de l'absence saisie est postérieure à la date de fin prévisionnelle de l'absence précédente. | BZ10: ABS_C_026 | CA10: =VLOOKUP(BZ10,'Axe 2 Règles de gestion'!$D$2:$F$564,3, FALSE) -> Dans le cas d'un congé autre que CLM, CLD, CGM et CITIS, l'indicateur de requalification doit être à non et les impacts spécifiques à la requalification ne doivent pas être mobilisés ou l'impact rémunération est vide.
A11: 21.00.00 | B11: M | C11: 44337.463 | D11: D0007 | E11: Congés/Absence | F11: S0072 | G11: Congé pour raisons de famille | H11: E0499 | I11: Congé d'accompagnement d'une personne en fin de vie | J11: Le Type de congé/absence est 'Congé d'accompagnement d'une personne en fin de vie' | K11: A_COA_TYCOAB [Saisi] = 'CG100' | L11: T1205 | M11: Congé d'accompagnement d'une personne en fin de vie - Fin | N11: Modification | Q11: Ouvrier d'état | R11: P0005 | S11: Général | T11: Passant | U11: 40725 | V11: 44561 | W11: CDI_I_178 ET CDI_D_163 ET CDI_D_617 ET ABS_C_003 ET ABS_C_004 ET ABS_C_005 ET ABS_C_006 ET ABS_C_007 ET ABS_C_008 ET ABS_C_009 ET ABS_C_026 | X11: CDI_I_178 | Y11: =VLOOKUP(X11,'Axe 2 Règles de gestion'!$D$2:$F$564,3, FALSE) -> Ce congé peut prendre fin soit à l'expiration de la période de 3 mois, soit dans les 3 jours qui suivent le décès de la personne accompagnée, soit à la demande de l'agent. | AT11: CDI_D_163 | AU11: =VLOOKUP(AT11,'Axe 2 Règles de gestion'!$D$2:$F$564,3, FALSE) -> La durée réelle maximale du congé d'accompagnement d'une personne en fin de vie est de 3 mois par personne accompagnée. | AV11: CDI_D_617 | AW11: =VLOOKUP(AV11,'Axe 2 Règles de gestion'!$D$2:$F$564,3, FALSE) -> La durée prévisionnelle maximale du congé d'accompagnement d'une personne en fin de vie est de 3 mois par personne accompagnée. | BF11: ABS_C_003 | BG11: =VLOOKUP(BF11,'Axe 2 Règles de gestion'!$D$2:$F$564,3, FALSE) -> La date de début du congé/absence doit être antérieure ou égale à la date de fin réelle du congé/absence. | BH11: ABS_C_004 | BI11: =VLOOKUP(BH11,'Axe 2 Règles de gestion'!$D$2:$F$564,3, FALSE) -> La date de début du congé/absence doit être antérieure ou égale à la date de fin prévisionnelle du congé/absence. | BJ11: ABS_C_005 | BK11: =VLOOKUP(BJ11,'Axe 2 Règles de gestion'!$D$2:$F$564,3, FALSE) -> La date de fin réelle du congé/absence doit être antérieure ou égale à la date limite de fin réelle ou prévisionnelle du lien juridique. | BL11: ABS_C_006 | BM11: =VLOOKUP(BL11,'Axe 2 Règles de gestion'!$D$2:$F$564,3, FALSE) -> La date de fin prévisionnelle du congé/absence doit être antérieure ou égale à la date limite de fin réelle ou prévisionnelle du lien juridique. | BN11: ABS_C_007 | BO11: =VLOOKUP(BN11,'Axe 2 Règles de gestion'!$D$2:$F$564,3, FALSE) -> La date de fin réelle du congé/absence doit être antérieure à la date limite de départ à la retraite. | BP11: ABS_C_008 | BQ11: =VLOOKUP(BP11,'Axe 2 Règles de gestion'!$D$2:$F$564,3, FALSE) -> La date de fin prévisionnelle du congé/absence doit être antérieure à la date limite de départ à la retraite. | BR11: ABS_C_009 | BS11: =VLOOKUP(BR11,'Axe 2 Règles de gestion'!$D$2:$F$564,3, FALSE) -> La date de fin réelle ou la date de fin prévisionnelle du congé/absence doit être saisie. | BT11: ABS_C_026 | BU11: =VLOOKUP(BT11,'Axe 2 Règles de gestion'!$D$2:$F$564,3, FALSE) -> Dans le cas d'un congé autre que CLM, CLD, CGM et CITIS, l'indicateur de requalification doit être à non et les impacts spécifiques à la requalification ne doivent pas être mobilisés ou l'impact rémunération est vide.
A12: 17.10.00 | B12: A | C12: 43152.5 | D12: D0007 | E12: Congés/Absence | F12: S0072 | G12: Congé pour raisons de famille | H12: E0499 | I12: Congé d'accompagnement d'une personne en fin de vie | J12: Le Type de congé/absence est 'Congé d'accompagnement d'une personne en fin de vie' | K12: A_COA_TYCOAB [Saisi] = 'CG100' | L12: T1204 | M12: Congé d'accompagnement d'une personne en fin de vie - Demande | N12: Création | Q12: Conseiller ou avocat général à la Cour de cassation en service extraordinaire | R12: P0046 | S12: Particulier | T12: Exclu | U12: 40725 | V12: 41294
A13: 17.10.00 | B13: A | C13: 43152.5 | D13: D0007 | E13: Congés/Absence | F13: S0072 | G13: Congé pour raisons de famille | H13: E0499 | I13: Congé d'accompagnement d'une personne en fin de vie | J13: Le Type de congé/absence est 'Congé d'accompagnement d'une personne en fin de vie' | K13: A_COA_TYCOAB [Saisi] = 'CG100' | L13: T1205 | M13: Congé d'accompagnement d'une personne en fin de vie - Fin | N13: Modification | Q13: Conseiller ou avocat général à la Cour de cassation en service extraordinaire | R13: P0046 | S13: Particulier | T13: Exclu | U13: 40725 | V13: 41294
A14: 17.10.00 | B14: A | C14: 43152.5 | D14: D0007 | E14: Congés/Absence | F14: S0072 | G14: Congé pour raisons de famille | H14: E0499 | I14: Congé d'accompagnement d'une personne en fin de vie | J14: Le Type de congé/absence est 'Congé d'accompagnement d'une personne en fin de vie' | K14: A_COA_TYCOAB [Saisi] = 'CG100' | L14: T1204 | M14: Congé d'accompagnement d'une personne en fin de vie - Demande | N14: Création | Q14: Personnel civil payé à l'acte ou à la tâche | R14: P0054 | S14: Particulier | T14: Exclu | U14: 40725 | V14: 41294
A15: 17.10.00 | B15: A | C15: 43152.5 | D15: D0007 | E15: Congés/Absence | F15: S0072 | G15: Congé pour raisons de famille | H15: E0499 | I15: Congé d'accompagnement d'une personne en fin de vie | J15: Le Type de congé/absence est 'Congé d'accompagnement d'une personne en fin de vie' | K15: A_COA_TYCOAB [Saisi] = 'CG100' | L15: T1205 | M15: Congé d'accompagnement d'une personne en fin de vie - Fin | N15: Modification | Q15: Personnel civil payé à l'acte ou à la tâche | R15: P0054 | S15: Particulier | T15: Exclu | U15: 40725 | V15: 41294
A16: 17.10.00 | B16: A | C16: 43152.5 | D16: D0007 | E16: Congés/Absence | F16: S0072 | G16: Congé pour raisons de famille | H16: E0499 | I16: Congé d'accompagnement d'une personne en fin de vie | J16: Le Type de congé/absence est 'Congé d'accompagnement d'une personne en fin de vie' | K16: A_COA_TYCOAB [Saisi] = 'CG100' | L16: T1204 | M16: Congé d'accompagnement d'une personne en fin de vie - Demande | N16: Création | Q16: Contractuel en service à l'étranger | R16: P0069 | S16: Particulier | T16: Exclu | U16: 40725 | V16: 41294
A17: 17.10.00 | B17: A | C17: 43152.5 | D17: D0007 | E17: Congés/Absence | F17: S0072 | G17: Congé pour raisons de famille | H17: E0499 | I17: Congé d'accompagnement d'une personne en fin de vie | J17: Le Type de congé/absence est 'Congé d'accompagnement d'une personne en fin de vie' | K17: A_COA_TYCOAB [Saisi] = 'CG100' | L17: T1205 | M17: Congé d'accompagnement d'une personne en fin de vie - Fin | N17: Modification | Q17: Contractuel en service à l'étranger | R17: P0069 | S17: Particulier | T17: Exclu | U17: 40725 | V17: 41294
A18: 17.10.00 | B18: A | C18: 43152.5 | D18: D0007 | E18: Congés/Absence | F18: S0072 | G18: Congé pour raisons de famille | H18: E0499 | I18: Congé d'accompagnement d'une personne en fin de vie | J18: Le Type de congé/absence est 'Congé d'accompagnement d'une personne en fin de vie' | K18: A_COA_TYCOAB [Saisi] = 'CG100' | L18: T1204 | M18: Congé d'accompagnement d'une personne en fin de vie - Demande | N18: Création | Q18: Contractuel de droit privé | R18: P0072 | S18: Particulier | T18: Exclu | U18: 40725 | V18: 41294
A19: 17.10.00 | B19: A | C19: 43152.5 | D19: D0007 | E19: Congés/Absence | F19: S0072 | G19: Congé pour raisons de famille | H19: E0499 | I19: Congé d'accompagnement d'une personne en fin de vie | J19: Le Type de congé/absence est 'Congé d'accompagnement d'une personne en fin de vie' | K19: A_COA_TYCOAB [Saisi] = 'CG100' | L19: T1205 | M19: Congé d'accompagnement d'une personne en fin de vie - Fin | N19: Modification | Q19: Contractuel de droit privé | R19: P0072 | S19: Particulier | T19: Exclu | U19: 40725 | V19: 41294
A20: 17.10.00 | B20: A | C20: 43152.5 | D20: D0007 | E20: Congés/Absence | F20: S0072 | G20: Congé pour raisons de famille | H20: E0499 | I20: Congé d'accompagnement d'une personne en fin de vie | J20: Le Type de congé/absence est 'Congé d'accompagnement d'une personne en fin de vie' | K20: A_COA_TYCOAB [Saisi] = 'CG100' | L20: T1204 | M20: Congé d'accompagnement d'une personne en fin de vie - Demande | N20: Création | Q20: Personnel hospitalo-universitaire | R20: P0091 | S20: Particulier | T20: Exclu | U20: 40725 | V20: 41294
A21: 17.10.00 | B21: A | C21: 43152.5 | D21: D0007 | E21: Congés/Absence | F21: S0072 | G21: Congé pour raisons de famille | H21: E0499 | I21: Congé d'accompagnement d'une personne en fin de vie | J21: Le Type de congé/absence est 'Congé d'accompagnement d'une personne en fin de vie' | K21: A_COA_TYCOAB [Saisi] = 'CG100' | L21: T1205 | M21: Congé d'accompagnement d'une personne en fin de vie - Fin | N21: Modification | Q21: Personnel hospitalo-universitaire | R21: P0091 | S21: Particulier | T21: Exclu | U21: 40725 | V21: 41294
A22: 21.00.00 | B22: M | C22: 44337.581 | D22: D0007 | E22: Congés/Absence | F22: S0072 | G22: Congé pour raisons de famille | H22: E0499 | I22: Congé d'accompagnement d'une personne en fin de vie | J22: Le Type de congé/absence est 'Congé d'accompagnement d'une personne en fin de vie' | K22: A_COA_TYCOAB [Saisi] = 'CG100' | L22: T1204 | M22: Congé d'accompagnement d'une personne en fin de vie - Demande | N22: Création | Q22: Ouvrier des parcs et ateliers confirmé non affilié ou stagiaire | R22: P0185 | S22: Particulier | T22: Exclu | U22: 40725 | V22: 44561
A23: 21.00.00 | B23: M | C23: 44337.583 | D23: D0007 | E23: Congés/Absence | F23: S0072 | G23: Congé pour raisons de famille | H23: E0499 | I23: Congé d'accompagnement d'une personne en fin de vie | J23: Le Type de congé/absence est 'Congé d'accompagnement d'une personne en fin de vie' | K23: A_COA_TYCOAB [Saisi] = 'CG100' | L23: T1205 | M23: Congé d'accompagnement d'une personne en fin de vie - Fin | N23: Modification | Q23: Ouvrier des parcs et ateliers confirmé non affilié ou stagiaire | R23: P0185 | S23: Particulier | T23: Exclu | U23: 40725 | V23: 44561
... A27: 21.00.00 | B27: M | C27: 44337.583 | D27: D0007 | E27: Congés/Absence | F27: S0072 | G27: Congé pour raisons de famille | H27: E0499 | I27: Congé d'accompagnement d'une personne en fin de vie | J27: Le Type de congé/absence est 'Congé d'accompagnement d'une personne en fin de vie' | K27: A_COA_TYCOAB [Saisi] = 'CG100' | L27: T1205 | M27: Congé d'accompagnement d'une personne en fin de vie - Fin | N27: Modification | Q27: Ouvrier du service des alcools confirmé non affilié | R27: P0221 | S27: Particulier | T27: Exclu | U27: 40725 | V27: 44561
A28: 21.10.00 | B28: M | C28: 44469.651 | D28: D0007 | E28: Congés/Absence | F28: S0072 | G28: Congé pour raisons de famille | H28: E0500 | I28: Congé de solidarité familiale | J28: Le Type de congé/absence est 'Congé de solidarité familiale' | K28: A_COA_TYCOAB [Saisi] = 'CG103' | L28: T1206 | M28: Congé de solidarité familiale - Demande | N28: Création Modification | O28: La valeur de l'Etat du congé est différente de 'Renouvellement' et la valeur de l'Etat du congé saisie est différente de celle avant saisie | P28: A_COA_ETCOMA [Saisi] <> 'EC02' ET A_COA_ETCOMA [Saisi] <> A_COA_ETCOMA [Valeur avant saisie] | Q28: Titulaire ou magistrat | R28: P0001 | S28: Général | T28: Passant | U28: 40725 | W28: CDI_I_001 ET CDI_I_002 ET CDI_I_003 ET CDI_I_004 ET CDI_D_121 ET CDI_D_521 ET CDI_D_122 ET CDI_D_123 ET CDI_D_601 ET CDI_D_117 ET ABS_C_001 ET ABS_C_003 ET ABS_C_004 ET ABS_C_007 ET ABS_C_008 ET ABS_C_009 ET ABS_C_019 ET ABS_C_020 ET ABS_C_023 ET ABS_C_026 ET ABS_C_065 | X28: CDI_I_001 | Y28: =VLOOKUP(X28,'Axe 2 Règles de gestion'!$D$2:$F$564,3, FALSE) -> Le congé est accordé si un ascendant, descendant, un frère ou une sœur, une personne partageant le même domicile ou l'ayant désigné comme sa personne de confiance souffre d'une pathologie mettant en jeu le pronostic vital ou en phase avancée ou terminale d'une affection grave et incurable, quelle qu'en soit la cause. | Z28: CDI_I_002 | AA28: =VLOOKUP(Z28,'Axe 2 Règles de gestion'!$D$2:$F$564,3, FALSE) -> L'agent doit faire la demande par écrit. Elle est accordée de droit. | AB28: CDI_I_003 | AC28: =VLOOKUP(AB28,'Axe 2 Règles de gestion'!$D$2:$F$564,3, FALSE) -> La demande doit être appuyée d'un certificat médical attestant que la personne accompagnée souffre d'une pathologie mettant en jeu le pronostic vital ou en phase avancée ou terminale d'une affection grave et incurable, quelle qu'en soit la cause. | AD28: CDI_I_004 | AE28: =VLOOKUP(AD28,'Axe 2 Règles de gestion'!$D$2:$F$564,3, FALSE) -> Le congé peut être fractionné ou pris de manière continue. | AT28: CDI_D_121 | AU28: =VLOOKUP(AT28,'Axe 2 Règles de gestion'!$D$2:$F$564,3, FALSE) -> Le congé de solidarité familiale, ou son renouvellement, est accordé pour une durée réelle maximale de trois mois. | AV28: CDI_D_521 | AW28: =VLOOKUP(AV28,'Axe 2 Règles de gestion'!$D$2:$F$564,3, FALSE) -> Le congé de solidarité familiale, ou son renouvellement, est accordé pour une durée prévisionnelle maximale de trois mois. | AX28: CDI_D_122 | AY28: =VLOOKUP(AX28,'Axe 2 Règles de gestion'!$D$2:$F$564,3, FALSE) -> Le congé de solidarité familiale peut être fractionné mais ne peut, renouvellement inclus, excéder les 6 mois. | AZ28: CDI_D_123 | BA28: =VLOOKUP(AZ28,'Axe 2 Règles de gestion'!$D$2:$F$564,3, FALSE) -> Le congé de solidarité familiale peut être fractionné mais chaque période doit être d'une durée réelle minimale de 7 jours consécutifs. | BB28: CDI_D_601 | BC28: =VLOOKUP(BB28,'Axe 2 Règles de gestion'!$D$2:$F$564,3, FALSE) -> Le congé de solidarité familiale peut être fractionné mais chaque période doit être d'une durée prévisionnelle minimale de 7 jours consécutifs. | BD28: CDI_D_117 | BE28: =VLOOKUP(BD28,'Axe 2 Règles de gestion'!$D$2:$F$564,3, FALSE) -> L'agent doit être en activité. | BF28: ABS_C_001 | BG28: =VLOOKUP(BF28,'Axe 2 Règles de gestion'!$D$2:$F$564,3, FALSE) -> La date de début du congé/absence doit être postérieure ou égale à la date de recrutement dans la FPE ou dans la carrière militaire. | BH28: ABS_C_003 | BI28: =VLOOKUP(BH28,'Axe 2 Règles de gestion'!$D$2:$F$564,3, FALSE) -> La date de début du congé/absence doit être antérieure ou égale à la date de fin réelle du congé/absence. | BJ28: ABS_C_004 | BK28: =VLOOKUP(BJ28,'Axe 2 Règles de gestion'!$D$2:$F$564,3, FALSE) -> La date de début du congé/absence doit être antérieure ou égale à la date de fin prévisionnelle du congé/absence. | BL28: ABS_C_007 | BM28: =VLOOKUP(BL28,'Axe 2 Règles de gestion'!$D$2:$F$564,3, FALSE) -> La date de fin réelle du congé/absence doit être antérieure à la date limite de départ à la retraite. | BN28: ABS_C_008 | BO28: =VLOOKUP(BN28,'Axe 2 Règles de gestion'!$D$2:$F$564,3, FALSE) -> La date de fin prévisionnelle du congé/absence doit être antérieure à la date limite de départ à la retraite. | BP28: ABS_C_009 | BQ28: =VLOOKUP(BP28,'Axe 2 Règles de gestion'!$D$2:$F$564,3, FALSE) -> La date de fin réelle ou la date de fin prévisionnelle du congé/absence doit être saisie. | BR28: ABS_C_019 | BS28: =VLOOKUP(BR28,'Axe 2 Règles de gestion'!$D$2:$F$564,3, FALSE) -> Si l'absence ne commence pas par une demi-journée et si l'absence précédente ne finit pas par une demi journée, la date de début de l'absence saisie est postérieure à la date de fin réelle de l'absence précédente. | BT28: ABS_C_020 | BU28: =VLOOKUP(BT28,'Axe 2 Règles de gestion'!$D$2:$F$564,3, FALSE) -> Si l'absence ne commence pas par une demi-journée et si l'absence précédente ne finit pas par une demi journée, la date de début de l'absence saisie est postérieure à la date de fin prévisionnelle de l'absence précédente. | BV28: ABS_C_023 | BW28: =VLOOKUP(BV28,'Axe 2 Règles de gestion'!$D$2:$F$564,3, FALSE) -> L'état du congé est renseigné. | BX28: ABS_C_026 | BY28: =VLOOKUP(BX28,'Axe 2 Règles de gestion'!$D$2:$F$564,3, FALSE) -> Dans le cas d'un congé autre que CLM, CLD, CGM et CITIS, l'indicateur de requalification doit être à non et les impacts spécifiques à la requalification ne doivent pas être mobilisés ou l'impact rémunération est vide. | BZ28: ABS_C_065 | CA28: =VLOOKUP(BZ28,'Axe 2 Règles de gestion'!$D$2:$F$564,3, FALSE) -> L'agent en congé de présence parentale / congé de proche aidant / congé de solidarité familiale ne peut se voir accorder de manière simultanée un temps partiel pour congé de présence parentale / pour congé de proche aidant / pour congé de solidarité familiale.
A29: 21.10.00 | B29: M | C29: 44469.651 | D29: D0007 | E29: Congés/Absence | F29: S0072 | G29: Congé pour raisons de famille | H29: E0500 | I29: Congé de solidarité familiale | J29: Le Type de congé/absence est 'Congé de solidarité familiale' | K29: A_COA_TYCOAB [Saisi] = 'CG103' | L29: T1207 | M29: Congé de solidarité familiale - Renouvellement | N29: Création Modification | O29: La valeur de l'Etat du congé est égale à 'Renouvellement' et la valeur de l'Etat du congé saisie est différente de celle avant saisie | P29: A_COA_ETCOMA [Saisi] = 'EC02' ET A_COA_ETCOMA [Saisi] <> A_COA_ETCOMA [Valeur avant saisie] | Q29: Titulaire ou magistrat | R29: P0001 | S29: Général | T29: Passant | U29: 40725 | W29: CDI_I_001 ET CDI_I_002 ET CDI_I_003 ET CDI_I_004 ET CDI_D_121 ET CDI_D_521 ET CDI_D_122 ET CDI_D_123 ET CDI_D_601 ET CDI_D_117 ET ABS_C_001 ET ABS_C_003 ET ABS_C_004 ET ABS_C_007 ET ABS_C_008 ET ABS_C_009 ET ABS_C_019 ET ABS_C_020 ET ABS_C_023 ET ABS_C_026 ET ABS_C_065 | X29: CDI_I_001 | Y29: =VLOOKUP(X29,'Axe 2 Règles de gestion'!$D$2:$F$564,3, FALSE) -> Le congé est accordé si un ascendant, descendant, un frère ou une sœur, une personne partageant le même domicile ou l'ayant désigné comme sa personne de confiance souffre d'une pathologie mettant en jeu le pronostic vital ou en phase avancée ou terminale d'une affection grave et incurable, quelle qu'en soit la cause. | Z29: CDI_I_002 | AA29: =VLOOKUP(Z29,'Axe 2 Règles de gestion'!$D$2:$F$564,3, FALSE) -> L'agent doit faire la demande par écrit. Elle est accordée de droit. | AB29: CDI_I_003 | AC29: =VLOOKUP(AB29,'Axe 2 Règles de gestion'!$D$2:$F$564,3, FALSE) -> La demande doit être appuyée d'un certificat médical attestant que la personne accompagnée souffre d'une pathologie mettant en jeu le pronostic vital ou en phase avancée ou terminale d'une affection grave et incurable, quelle qu'en soit la cause. | AD29: CDI_I_004 | AE29: =VLOOKUP(AD29,'Axe 2 Règles de gestion'!$D$2:$F$564,3, FALSE) -> Le congé peut être fractionné ou pris de manière continue. | AT29: CDI_D_121 | AU29: =VLOOKUP(AT29,'Axe 2 Règles de gestion'!$D$2:$F$564,3, FALSE) -> Le congé de solidarité familiale, ou son renouvellement, est accordé pour une durée réelle maximale de trois mois. | AV29: CDI_D_521 | AW29: =VLOOKUP(AV29,'Axe 2 Règles de gestion'!$D$2:$F$564,3, FALSE) -> Le congé de solidarité familiale, ou son renouvellement, est accordé pour une durée prévisionnelle maximale de trois mois. | AX29: CDI_D_122 | AY29: =VLOOKUP(AX29,'Axe 2 Règles de gestion'!$D$2:$F$564,3, FALSE) -> Le congé de solidarité familiale peut être fractionné mais ne peut, renouvellement inclus, excéder les 6 mois. | AZ29: CDI_D_123 | BA29: =VLOOKUP(AZ29,'Axe 2 Règles de gestion'!$D$2:$F$564,3, FALSE) -> Le congé de solidarité familiale peut être fractionné mais chaque période doit être d'une durée réelle minimale de 7 jours consécutifs. | BB29: CDI_D_601 | BC29: =VLOOKUP(BB29,'Axe 2 Règles de gestion'!$D$2:$F$564,3, FALSE) -> Le congé de solidarité familiale peut être fractionné mais chaque période doit être d'une durée prévisionnelle minimale de 7 jours consécutifs. | BD29: CDI_D_117 | BE29: =VLOOKUP(BD29,'Axe 2 Règles de gestion'!$D$2:$F$564,3, FALSE) -> L'agent doit être en activité. | BF29: ABS_C_001 | BG29: =VLOOKUP(BF29,'Axe 2 Règles de gestion'!$D$2:$F$564,3, FALSE) -> La date de début du congé/absence doit être postérieure ou égale à la date de recrutement dans la FPE ou dans la carrière militaire. | BH29: ABS_C_003 | BI29: =VLOOKUP(BH29,'Axe 2 Règles de gestion'!$D$2:$F$564,3, FALSE) -> La date de début du congé/absence doit être antérieure ou égale à la date de fin réelle du congé/absence. | BJ29: ABS_C_004 | BK29: =VLOOKUP(BJ29,'Axe 2 Règles de gestion'!$D$2:$F$564,3, FALSE) -> La date de début du congé/absence doit être antérieure ou égale à la date de fin prévisionnelle du congé/absence. | BL29: ABS_C_007 | BM29: =VLOOKUP(BL29,'Axe 2 Règles de gestion'!$D$2:$F$564,3, FALSE) -> La date de fin réelle du congé/absence doit être antérieure à la date limite de départ à la retraite. | BN29: ABS_C_008 | BO29: =VLOOKUP(BN29,'Axe 2 Règles de gestion'!$D$2:$F$564,3, FALSE) -> La date de fin prévisionnelle du congé/absence doit être antérieure à la date limite de départ à la retraite. | BP29: ABS_C_009 | BQ29: =VLOOKUP(BP29,'Axe 2 Règles de gestion'!$D$2:$F$564,3, FALSE) -> La date de fin réelle ou la date de fin prévisionnelle du congé/absence doit être saisie. | BR29: ABS_C_019 | BS29: =VLOOKUP(BR29,'Axe 2 Règles de gestion'!$D$2:$F$564,3, FALSE) -> Si l'absence ne commence pas par une demi-journée et si l'absence précédente ne finit pas par une demi journée, la date de début de l'absence saisie est postérieure à la date de fin réelle de l'absence précédente. | BT29: ABS_C_020 | BU29: =VLOOKUP(BT29,'Axe 2 Règles de gestion'!$D$2:$F$564,3, FALSE) -> Si l'absence ne commence pas par une demi-journée et si l'absence précédente ne finit pas par une demi journée, la date de début de l'absence saisie est postérieure à la date de fin prévisionnelle de l'absence précédente. | BV29: ABS_C_023 | BW29: =VLOOKUP(BV29,'Axe 2 Règles de gestion'!$D$2:$F$564,3, FALSE) -> L'état du congé est renseigné. | BX29: ABS_C_026 | BY29: =VLOOKUP(BX29,'Axe 2 Règles de gestion'!$D$2:$F$564,3, FALSE) -> Dans le cas d'un congé autre que CLM, CLD, CGM et CITIS, l'indicateur de requalification doit être à non et les impacts spécifiques à la requalification ne doivent pas être mobilisés ou l'impact rémunération est vide. | BZ29: ABS_C_065 | CA29: =VLOOKUP(BZ29,'Axe 2 Règles de gestion'!$D$2:$F$564,3, FALSE) -> L'agent en congé de présence parentale / congé de proche aidant / congé de solidarité familiale ne peut se voir accorder de manière simultanée un temps partiel pour congé de présence parentale / pour congé de proche aidant / pour congé de solidarité familiale.
A30: 20.10.00 | B30: M | C30: 44054.675 | D30: D0007 | E30: Congés/Absence | F30: S0072 | G30: Congé pour raisons de famille | H30: E0500 | I30: Congé de solidarité familiale | J30: Le Type de congé/absence est 'Congé de solidarité familiale' | K30: A_COA_TYCOAB [Saisi] = 'CG103' | L30: T1208 | M30: Congé de solidarité familiale - Fin | N30: Modification | O30: La valeur de l'Etat du congé saisie est égale à celle avant saisie | P30: A_COA_ETCOMA [Saisi] = A_COA_ETCOMA [Valeur avant saisie] | Q30: Titulaire ou magistrat | R30: P0001 | S30: Général | T30: Passant | U30: 40725 | V30: 43951 | W30: CDI_I_005 ET CDI_D_121 ET CDI_D_521 ET CDI_D_122 ET CDI_D_123 ET CDI_D_601 ET ABS_C_003 ET ABS_C_004 ET ABS_C_007 ET ABS_C_008 ET ABS_C_009 ET ABS_C_023 ET ABS_C_026 | X30: CDI_I_005 | Y30: =VLOOKUP(X30,'Axe 2 Règles de gestion'!$D$2:$F$564,3, FALSE) -> Le congé prend fin à l'issue de la période de 3 mois ou dans les 3 jours suivant le décès de la personnes accompagnée ou à la demande de l'agent. | AT30: CDI_D_121 | AU30: =VLOOKUP(AT30,'Axe 2 Règles de gestion'!$D$2:$F$564,3, FALSE) -> Le congé de solidarité familiale, ou son renouvellement, est accordé pour une durée réelle maximale de trois mois. | AV30: CDI_D_521 | AW30: =VLOOKUP(AV30,'Axe 2 Règles de gestion'!$D$2:$F$564,3, FALSE) -> Le congé de solidarité familiale, ou son renouvellement, est accordé pour une durée prévisionnelle maximale de trois mois. | AX30: CDI_D_122 | AY30: =VLOOKUP(AX30,'Axe 2 Règles de gestion'!$D$2:$F$564,3, FALSE) -> Le congé de solidarité familiale peut être fractionné mais ne peut, renouvellement inclus, excéder les 6 mois. | AZ30: CDI_D_123 | BA30: =VLOOKUP(AZ30,'Axe 2 Règles de gestion'!$D$2:$F$564,3, FALSE) -> Le congé de solidarité familiale peut être fractionné mais chaque période doit être d'une durée réelle minimale de 7 jours consécutifs. | BB30: CDI_D_601 | BC30: =VLOOKUP(BB30,'Axe 2 Règles de gestion'!$D$2:$F$564,3, FALSE) -> Le congé de solidarité familiale peut être fractionné mais chaque période doit être d'une durée prévisionnelle minimale de 7 jours consécutifs. | BF30: ABS_C_003 | BG30: =VLOOKUP(BF30,'Axe 2 Règles de gestion'!$D$2:$F$564,3, FALSE) -> La date de début du congé/absence doit être antérieure ou égale à la date de fin réelle du congé/absence. | BH30: ABS_C_004 | BI30: =VLOOKUP(BH30,'Axe 2 Règles de gestion'!$D$2:$F$564,3, FALSE) -> La date de début du congé/absence doit être antérieure ou égale à la date de fin prévisionnelle du congé/absence. | BJ30: ABS_C_007 | BK30: =VLOOKUP(BJ30,'Axe 2 Règles de gestion'!$D$2:$F$564,3, FALSE) -> La date de fin réelle du congé/absence doit être antérieure à la date limite de départ à la retraite. | BL30: ABS_C_008 | BM30: =VLOOKUP(BL30,'Axe 2 Règles de gestion'!$D$2:$F$564,3, FALSE) -> La date de fin prévisionnelle du congé/absence doit être antérieure à la date limite de départ à la retraite. | BN30: ABS_C_009 | BO30: =VLOOKUP(BN30,'Axe 2 Règles de gestion'!$D$2:$F$564,3, FALSE) -> La date de fin réelle ou la date de fin prévisionnelle du congé/absence doit être saisie. | BP30: ABS_C_023 | BQ30: =VLOOKUP(BP30,'Axe 2 Règles de gestion'!$D$2:$F$564,3, FALSE) -> L'état du congé est renseigné. | BR30: ABS_C_026 | BS30: =VLOOKUP(BR30,'Axe 2 Règles de gestion'!$D$2:$F$564,3, FALSE) -> Dans le cas d'un congé autre que CLM, CLD, CGM et CITIS, l'indicateur de requalification doit être à non et les impacts spécifiques à la requalification ne doivent pas être mobilisés ou l'impact rémunération est vide.
A31: 21.10.00 | B31: M | C31: 44469.652 | D31: D0007 | E31: Congés/Absence | F31: S0072 | G31: Congé pour raisons de famille | H31: E0500 | I31: Congé de solidarité familiale | J31: Le Type de congé/absence est 'Congé de solidarité familiale' | K31: A_COA_TYCOAB [Saisi] = 'CG103' | L31: T1208 | M31: Congé de solidarité familiale - Fin | N31: Modification | O31: La valeur de l'Etat du congé saisie est égale à celle avant saisie | P31: A_COA_ETCOMA [Saisi] = A_COA_ETCOMA [Valeur avant saisie] | Q31: Titulaire ou magistrat | R31: P0001 | S31: Général | T31: Passant | U31: 43952 | W31: CDI_I_005 ET CDI_I_192 ET CDI_D_121 ET CDI_D_521 ET CDI_D_122 ET CDI_D_123 ET CDI_D_601 ET ABS_C_003 ET ABS_C_004 ET ABS_C_007 ET ABS_C_008 ET ABS_C_009 ET ABS_C_023 ET ABS_C_026 ET ABS_C_065 | X31: CDI_I_005 | Y31: =VLOOKUP(X31,'Axe 2 Règles de gestion'!$D$2:$F$564,3, FALSE) -> Le congé prend fin à l'issue de la période de 3 mois ou dans les 3 jours suivant le décès de la personnes accompagnée ou à la demande de l'agent. | Z31: CDI_I_192 | AA31: =VLOOKUP(Z31,'Axe 2 Règles de gestion'!$D$2:$F$564,3, FALSE) -> A l'issue du congé, l'agent ne relevant pas des régimes d'obligations de service qui en fait la demande, bénéficie de plein droit des droits à congés accumulés sur son compte épargne-temps sans que les nécessités de service puissent être opposées. | AT31: CDI_D_121 | AU31: =VLOOKUP(AT31,'Axe 2 Règles de gestion'!$D$2:$F$564,3, FALSE) -> Le congé de solidarité familiale, ou son renouvellement, est accordé pour une durée réelle maximale de trois mois. | AV31: CDI_D_521 | AW31: =VLOOKUP(AV31,'Axe 2 Règles de gestion'!$D$2:$F$564,3, FALSE) -> Le congé de solidarité familiale, ou son renouvellement, est accordé pour une durée prévisionnelle maximale de trois mois. | AX31: CDI_D_122 | AY31: =VLOOKUP(AX31,'Axe 2 Règles de gestion'!$D$2:$F$564,3, FALSE) -> Le congé de solidarité familiale peut être fractionné mais ne peut, renouvellement inclus, excéder les 6 mois. | AZ31: CDI_D_123 | BA31: =VLOOKUP(AZ31,'Axe 2 Règles de gestion'!$D$2:$F$564,3, FALSE) -> Le congé de solidarité familiale peut être fractionné mais chaque période doit être d'une durée réelle minimale de 7 jours consécutifs. | BB31: CDI_D_601 | BC31: =VLOOKUP(BB31,'Axe 2 Règles de gestion'!$D$2:$F$564,3, FALSE) -> Le congé de solidarité familiale peut être fractionné mais chaque période doit être d'une durée prévisionnelle minimale de 7 jours consécutifs. | BF31: ABS_C_003 | BG31: =VLOOKUP(BF31,'Axe 2 Règles de gestion'!$D$2:$F$564,3, FALSE) -> La date de début du congé/absence doit être antérieure ou égale à la date de fin réelle du congé/absence. | BH31: ABS_C_004 | BI31: =VLOOKUP(BH31,'Axe 2 Règles de gestion'!$D$2:$F$564,3, FALSE) -> La date de début du congé/absence doit être antérieure ou égale à la date de fin prévisionnelle du congé/absence. | BJ31: ABS_C_007 | BK31: =VLOOKUP(BJ31,'Axe 2 Règles de gestion'!$D$2:$F$564,3, FALSE) -> La date de fin réelle du congé/absence doit être antérieure à la date limite de départ à la retraite. | BL31: ABS_C_008 | BM31: =VLOOKUP(BL31,'Axe 2 Règles de gestion'!$D$2:$F$564,3, FALSE) -> La date de fin prévisionnelle du congé/absence doit être antérieure à la date limite de départ à la retraite. | BN31: ABS_C_009 | BO31: =VLOOKUP(BN31,'Axe 2 Règles de gestion'!$D$2:$F$564,3, FALSE) -> La date de fin réelle ou la date de fin prévisionnelle du congé/absence doit être saisie. | BP31: ABS_C_023 | BQ31: =VLOOKUP(BP31,'Axe 2 Règles de gestion'!$D$2:$F$564,3, FALSE) -> L'état du congé est renseigné. | BR31: ABS_C_026 | BS31: =VLOOKUP(BR31,'Axe 2 Règles de gestion'!$D$2:$F$564,3, FALSE) -> Dans le cas d'un congé autre que CLM, CLD, CGM et CITIS, l'indicateur de requalification doit être à non et les impacts spécifiques à la requalification ne doivent pas être mobilisés ou l'impact rémunération est vide. | BT31: ABS_C_065 | BU31: =VLOOKUP(BT31,'Axe 2 Règles de gestion'!$D$2:$F$564,3, FALSE) -> L'agent en congé de présence parentale / congé de proche aidant / congé de solidarité familiale ne peut se voir accorder de manière simultanée un temps partiel pour congé de présence parentale / pour congé de proche aidant / pour congé de solidarité familiale.
A32: 17.10.00 | B32: A | C32: 43152.5 | D32: D0007 | E32: Congés/Absence | F32: S0072 | G32: Congé pour raisons de famille | H32: E0500 | I32: Congé de solidarité familiale | J32: Le Type de congé/absence est 'Congé de solidarité familiale' | K32: A_COA_TYCOAB [Saisi] = 'CG103' | L32: T1206 | M32: Congé de solidarité familiale - Demande | N32: Création Modification | O32: La valeur de l'Etat du congé est différente de 'Renouvellement' et la valeur de l'Etat du congé saisie est différente de celle avant saisie | P32: A_COA_ETCOMA [Saisi] <> 'EC02' ET A_COA_ETCOMA [Saisi] <> A_COA_ETCOMA [Valeur avant saisie] | Q32: Contractuel | R32: P0003 | S32: Général | T32: Exclu | U32: 40725 | V32: 41294
A33: 21.10.00 | B33: M | C33: 44469.65 | D33: D0007 | E33: Congés/Absence | F33: S0072 | G33: Congé pour raisons de famille | H33: E0500 | I33: Congé de solidarité familiale | J33: Le Type de congé/absence est 'Congé de solidarité familiale' | K33: A_COA_TYCOAB [Saisi] = 'CG103' | L33: T1206 | M33: Congé de solidarité familiale - Demande | N33: Création Modification | O33: La valeur de l'Etat du congé est différente de 'Renouvellement' et la valeur de l'Etat du congé saisie est différente de celle avant saisie | P33: A_COA_ETCOMA [Saisi] <> 'EC02' ET A_COA_ETCOMA [Saisi] <> A_COA_ETCOMA [Valeur avant saisie] | Q33: Contractuel | R33: P0003 | S33: Général | T33: Passant | U33: 41295 | W33: CDI_I_011 ET CDI_I_012 ET CDI_I_013 ET CDI_I_014 ET CDI_D_216 ET CDI_D_602 ET CDI_D_603 ET CDI_D_218 ET CDI_D_604 ET CDI_D_212 ET ABS_C_002 ET ABS_C_003 ET ABS_C_004 ET ABS_C_005 ET ABS_C_006 ET ABS_C_007 ET ABS_C_008 ET ABS_C_009 ET ABS_C_019 ET ABS_C_020 ET ABS_C_023 ET ABS_C_026 ET ABS_C_065 | X33: CDI_I_011 | Y33: =VLOOKUP(X33,'Axe 2 Règles de gestion'!$D$2:$F$564,3, FALSE) -> Le congé est accordé si un ascendant, descendant, un frère ou une sœur, une personne partageant le même domicile ou l'ayant désigné comme sa personne de confiance souffre d'une pathologie mettant en jeu le pronostic vital ou en phase avancée ou terminale d'une affection grave et incurable, quelle qu'en soit la cause. | Z33: CDI_I_012 | AA33: =VLOOKUP(Z33,'Axe 2 Règles de gestion'!$D$2:$F$564,3, FALSE) -> L'agent doit faire la demande par écrit. Elle est accordée de droit. | AB33: CDI_I_013 | AC33: =VLOOKUP(AB33,'Axe 2 Règles de gestion'!$D$2:$F$564,3, FALSE) -> La demande doit être appuyée d'un certificat médical attestant que la personne accompagnée souffre d'une pathologie mettant en jeu le pronostic vital ou en phase avancée ou terminale d'une affection grave et incurable, quelle qu'en soit la cause. | AD33: CDI_I_014 | AE33: =VLOOKUP(AD33,'Axe 2 Règles de gestion'!$D$2:$F$564,3, FALSE) -> Le congé peut être fractionné ou pris de manière continue. | AT33: CDI_D_216 | AU33: =VLOOKUP(AT33,'Axe 2 Règles de gestion'!$D$2:$F$564,3, FALSE) -> Le congé de solidarité familiale, ou son renouvellement, est accordé pour une durée réelle maximale de trois mois. | AV33: CDI_D_602 | AW33: =VLOOKUP(AV33,'Axe 2 Règles de gestion'!$D$2:$F$564,3, FALSE) -> Le congé de solidarité familiale, ou son renouvellement, est accordé pour une durée prévisionnelle maximale de trois mois. | AX33: CDI_D_603 | AY33: =VLOOKUP(AX33,'Axe 2 Règles de gestion'!$D$2:$F$564,3, FALSE) -> Le congé de solidarité familiale peut être fractionné mais ne peut, renouvellement inclus, excéder les 6 mois. | AZ33: CDI_D_218 | BA33: =VLOOKUP(AZ33,'Axe 2 Règles de gestion'!$D$2:$F$564,3, FALSE) -> Le congé de solidarité familiale peut être fractionné mais chaque période doit être d'une durée réelle minimale de 7 jours consécutifs. | BB33: CDI_D_604 | BC33: =VLOOKUP(BB33,'Axe 2 Règles de gestion'!$D$2:$F$564,3, FALSE) -> Le congé de solidarité familiale peut être fractionné mais chaque période doit être d'une durée prévisionnelle minimale de 7 jours consécutifs. | BD33: CDI_D_212 | BE33: =VLOOKUP(BD33,'Axe 2 Règles de gestion'!$D$2:$F$564,3, FALSE) -> L'agent doit être en activité. | BF33: ABS_C_002 | BG33: =VLOOKUP(BF33,'Axe 2 Règles de gestion'!$D$2:$F$564,3, FALSE) -> La date de début du congé/absence doit être postérieure ou égale à la date de début du lien juridique. | BH33: ABS_C_003 | BI33: =VLOOKUP(BH33,'Axe 2 Règles de gestion'!$D$2:$F$564,3, FALSE) -> La date de début du congé/absence doit être antérieure ou égale à la date de fin réelle du congé/absence. | BJ33: ABS_C_004 | BK33: =VLOOKUP(BJ33,'Axe 2 Règles de gestion'!$D$2:$F$564,3, FALSE) -> La date de début du congé/absence doit être antérieure ou égale à la date de fin prévisionnelle du congé/absence. | BL33: ABS_C_005 | BM33: =VLOOKUP(BL33,'Axe 2 Règles de gestion'!$D$2:$F$564,3, FALSE) -> La date de fin réelle du congé/absence doit être antérieure ou égale à la date limite de fin réelle ou prévisionnelle du lien juridique. | BN33: ABS_C_006 | BO33: =VLOOKUP(BN33,'Axe 2 Règles de gestion'!$D$2:$F$564,3, FALSE) -> La date de fin prévisionnelle du congé/absence doit être antérieure ou égale à la date limite de fin réelle ou prévisionnelle du lien juridique. | BP33: ABS_C_007 | BQ33: =VLOOKUP(BP33,'Axe 2 Règles de gestion'!$D$2:$F$564,3, FALSE) -> La date de fin réelle du congé/absence doit être antérieure à la date limite de départ à la retraite. | BR33: ABS_C_008 | BS33: =VLOOKUP(BR33,'Axe 2 Règles de gestion'!$D$2:$F$564,3, FALSE) -> La date de fin prévisionnelle du congé/absence doit être antérieure à la date limite de départ à la retraite. | BT33: ABS_C_009 | BU33: =VLOOKUP(BT33,'Axe 2 Règles de gestion'!$D$2:$F$564,3, FALSE) -> La date de fin réelle ou la date de fin prévisionnelle du congé/absence doit être saisie. | BV33: ABS_C_019 | BW33: =VLOOKUP(BV33,'Axe 2 Règles de gestion'!$D$2:$F$564,3, FALSE) -> Si l'absence ne commence pas par une demi-journée et si l'absence précédente ne finit pas par une demi journée, la date de début de l'absence saisie est postérieure à la date de fin réelle de l'absence précédente. | BX33: ABS_C_020 | BY33: =VLOOKUP(BX33,'Axe 2 Règles de gestion'!$D$2:$F$564,3, FALSE) -> Si l'absence ne commence pas par une demi-journée et si l'absence précédente ne finit pas par une demi journée, la date de début de l'absence saisie est postérieure à la date de fin prévisionnelle de l'absence précédente. | BZ33: ABS_C_023 | CA33: =VLOOKUP(BZ33,'Axe 2 Règles de gestion'!$D$2:$F$564,3, FALSE) -> L'état du congé est renseigné. | CB33: ABS_C_026 | CC33: =VLOOKUP(CB33,'Axe 2 Règles de gestion'!$D$2:$F$564,3, FALSE) -> Dans le cas d'un congé autre que CLM, CLD, CGM et CITIS, l'indicateur de requalification doit être à non et les impacts spécifiques à la requalification ne doivent pas être mobilisés ou l'impact rémunération est vide. | CD33: ABS_C_065 | CE33: =VLOOKUP(CD33,'Axe 2 Règles de gestion'!$D$2:$F$564,3, FALSE) -> L'agent en congé de présence parentale / congé de proche aidant / congé de solidarité familiale ne peut se voir accorder de manière simultanée un temps partiel pour congé de présence parentale / pour congé de proche aidant / pour congé de solidarité familiale.
A34: 17.10.00 | B34: A | C34: 43152.5 | D34: D0007 | E34: Congés/Absence | F34: S0072 | G34: Congé pour raisons de famille | H34: E0500 | I34: Congé de solidarité familiale | J34: Le Type de congé/absence est 'Congé de solidarité familiale' | K34: A_COA_TYCOAB [Saisi] = 'CG103' | L34: T1207 | M34: Congé de solidarité familiale - Renouvellement | N34: Création Modification | O34: La valeur de l'Etat du congé est égale à 'Renouvellement' et la valeur de l'Etat du congé saisie est différente de celle avant saisie | P34: A_COA_ETCOMA [Saisi] = 'EC02' ET A_COA_ETCOMA [Saisi] <> A_COA_ETCOMA [Valeur avant saisie] | Q34: Contractuel | R34: P0003 | S34: Général | T34: Exclu | U34: 40725 | V34: 41294
A35: 21.10.00 | B35: M | C35: 44469.65 | D35: D0007 | E35: Congés/Absence | F35: S0072 | G35: Congé pour raisons de famille | H35: E0500 | I35: Congé de solidarité familiale | J35: Le Type de congé/absence est 'Congé de solidarité familiale' | K35: A_COA_TYCOAB [Saisi] = 'CG103' | L35: T1207 | M35: Congé de solidarité familiale - Renouvellement | N35: Création Modification | O35: La valeur de l'Etat du congé est égale à 'Renouvellement' et la valeur de l'Etat du congé saisie est différente de celle avant saisie | P35: A_COA_ETCOMA [Saisi] = 'EC02' ET A_COA_ETCOMA [Saisi] <> A_COA_ETCOMA [Valeur avant saisie] | Q35: Contractuel | R35: P0003 | S35: Général | T35: Passant | U35: 41295 | W35: CDI_I_011 ET CDI_I_012 ET CDI_I_013 ET CDI_I_014 ET CDI_D_216 ET CDI_D_602 ET CDI_D_603 ET CDI_D_218 ET CDI_D_604 ET CDI_D_212 ET ABS_C_002 ET ABS_C_003 ET ABS_C_004 ET ABS_C_005 ET ABS_C_006 ET ABS_C_007 ET ABS_C_008 ET ABS_C_009 ET ABS_C_019 ET ABS_C_020 ET ABS_C_023 ET ABS_C_026 ET ABS_C_065 | X35: CDI_I_011 | Y35: =VLOOKUP(X35,'Axe 2 Règles de gestion'!$D$2:$F$564,3, FALSE) -> Le congé est accordé si un ascendant, descendant, un frère ou une sœur, une personne partageant le même domicile ou l'ayant désigné comme sa personne de confiance souffre d'une pathologie mettant en jeu le pronostic vital ou en phase avancée ou terminale d'une affection grave et incurable, quelle qu'en soit la cause. | Z35: CDI_I_012 | AA35: =VLOOKUP(Z35,'Axe 2 Règles de gestion'!$D$2:$F$564,3, FALSE) -> L'agent doit faire la demande par écrit. Elle est accordée de droit. | AB35: CDI_I_013 | AC35: =VLOOKUP(AB35,'Axe 2 Règles de gestion'!$D$2:$F$564,3, FALSE) -> La demande doit être appuyée d'un certificat médical attestant que la personne accompagnée souffre d'une pathologie mettant en jeu le pronostic vital ou en phase avancée ou terminale d'une affection grave et incurable, quelle qu'en soit la cause. | AD35: CDI_I_014 | AE35: =VLOOKUP(AD35,'Axe 2 Règles de gestion'!$D$2:$F$564,3, FALSE) -> Le congé peut être fractionné ou pris de manière continue. | AT35: CDI_D_216 | AU35: =VLOOKUP(AT35,'Axe 2 Règles de gestion'!$D$2:$F$564,3, FALSE) -> Le congé de solidarité familiale, ou son renouvellement, est accordé pour une durée réelle maximale de trois mois. | AV35: CDI_D_602 | AW35: =VLOOKUP(AV35,'Axe 2 Règles de gestion'!$D$2:$F$564,3, FALSE) -> Le congé de solidarité familiale, ou son renouvellement, est accordé pour une durée prévisionnelle maximale de trois mois. | AX35: CDI_D_603 | AY35: =VLOOKUP(AX35,'Axe 2 Règles de gestion'!$D$2:$F$564,3, FALSE) -> Le congé de solidarité familiale peut être fractionné mais ne peut, renouvellement inclus, excéder les 6 mois. | AZ35: CDI_D_218 | BA35: =VLOOKUP(AZ35,'Axe 2 Règles de gestion'!$D$2:$F$564,3, FALSE) -> Le congé de solidarité familiale peut être fractionné mais chaque période doit être d'une durée réelle minimale de 7 jours consécutifs. | BB35: CDI_D_604 | BC35: =VLOOKUP(BB35,'Axe 2 Règles de gestion'!$D$2:$F$564,3, FALSE) -> Le congé de solidarité familiale peut être fractionné mais chaque période doit être d'une durée prévisionnelle minimale de 7 jours consécutifs. | BD35: CDI_D_212 | BE35: =VLOOKUP(BD35,'Axe 2 Règles de gestion'!$D$2:$F$564,3, FALSE) -> L'agent doit être en activité. | BF35: ABS_C_002 | BG35: =VLOOKUP(BF35,'Axe 2 Règles de gestion'!$D$2:$F$564,3, FALSE) -> La date de début du congé/absence doit être postérieure ou égale à la date de début du lien juridique. | BH35: ABS_C_003 | BI35: =VLOOKUP(BH35,'Axe 2 Règles de gestion'!$D$2:$F$564,3, FALSE) -> La date de début du congé/absence doit être antérieure ou égale à la date de fin réelle du congé/absence. | BJ35: ABS_C_004 | BK35: =VLOOKUP(BJ35,'Axe 2 Règles de gestion'!$D$2:$F$564,3, FALSE) -> La date de début du congé/absence doit être antérieure ou égale à la date de fin prévisionnelle du congé/absence. | BL35: ABS_C_005 | BM35: =VLOOKUP(BL35,'Axe 2 Règles de gestion'!$D$2:$F$564,3, FALSE) -> La date de fin réelle du congé/absence doit être antérieure ou égale à la date limite de fin réelle ou prévisionnelle du lien juridique. | BN35: ABS_C_006 | BO35: =VLOOKUP(BN35,'Axe 2 Règles de gestion'!$D$2:$F$564,3, FALSE) -> La date de fin prévisionnelle du congé/absence doit être antérieure ou égale à la date limite de fin réelle ou prévisionnelle du lien juridique. | BP35: ABS_C_007 | BQ35: =VLOOKUP(BP35,'Axe 2 Règles de gestion'!$D$2:$F$564,3, FALSE) -> La date de fin réelle du congé/absence doit être antérieure à la date limite de départ à la retraite. | BR35: ABS_C_008 | BS35: =VLOOKUP(BR35,'Axe 2 Règles de gestion'!$D$2:$F$564,3, FALSE) -> La date de fin prévisionnelle du congé/absence doit être antérieure à la date limite de départ à la retraite. | BT35: ABS_C_009 | BU35: =VLOOKUP(BT35,'Axe 2 Règles de gestion'!$D$2:$F$564,3, FALSE) -> La date de fin réelle ou la date de fin prévisionnelle du congé/absence doit être saisie. | BV35: ABS_C_019 | BW35: =VLOOKUP(BV35,'Axe 2 Règles de gestion'!$D$2:$F$564,3, FALSE) -> Si l'absence ne commence pas par une demi-journée et si l'absence précédente ne finit pas par une demi journée, la date de début de l'absence saisie est postérieure à la date de fin réelle de l'absence précédente. | BX35: ABS_C_020 | BY35: =VLOOKUP(BX35,'Axe 2 Règles de gestion'!$D$2:$F$564,3, FALSE) -> Si l'absence ne commence pas par une demi-journée et si l'absence précédente ne finit pas par une demi journée, la date de début de l'absence saisie est postérieure à la date de fin prévisionnelle de l'absence précédente. | BZ35: ABS_C_023 | CA35: =VLOOKUP(BZ35,'Axe 2 Règles de gestion'!$D$2:$F$564,3, FALSE) -> L'état du congé est renseigné. | CB35: ABS_C_026 | CC35: =VLOOKUP(CB35,'Axe 2 Règles de gestion'!$D$2:$F$564,3, FALSE) -> Dans le cas d'un congé autre que CLM, CLD, CGM et CITIS, l'indicateur de requalification doit être à non et les impacts spécifiques à la requalification ne doivent pas être mobilisés ou l'impact rémunération est vide. | CD35: ABS_C_065 | CE35: =VLOOKUP(CD35,'Axe 2 Règles de gestion'!$D$2:$F$564,3, FALSE) -> L'agent en congé de présence parentale / congé de proche aidant / congé de solidarité familiale ne peut se voir accorder de manière simultanée un temps partiel pour congé de présence parentale / pour congé de proche aidant / pour congé de solidarité familiale.
A36: 17.10.00 | B36: A | C36: 43152.5 | D36: D0007 | E36: Congés/Absence | F36: S0072 | G36: Congé pour raisons de famille | H36: E0500 | I36: Congé de solidarité familiale | J36: Le Type de congé/absence est 'Congé de solidarité familiale' | K36: A_COA_TYCOAB [Saisi] = 'CG103' | L36: T1208 | M36: Congé de solidarité familiale - Fin | N36: Modification | O36: La valeur de l'Etat du congé saisie est égale à celle avant saisie | P36: A_COA_ETCOMA [Saisi] = A_COA_ETCOMA [Valeur avant saisie] | Q36: Contractuel | R36: P0003 | S36: Général | T36: Exclu | U36: 40725 | V36: 41294
A37: 20.10.00 | B37: M | C37: 44054.674 | D37: D0007 | E37: Congés/Absence | F37: S0072 | G37: Congé pour raisons de famille | H37: E0500 | I37: Congé de solidarité familiale | J37: Le Type de congé/absence est 'Congé de solidarité familiale' | K37: A_COA_TYCOAB [Saisi] = 'CG103' | L37: T1208 | M37: Congé de solidarité familiale - Fin | N37: Modification | O37: La valeur de l'Etat du congé saisie est égale à celle avant saisie | P37: A_COA_ETCOMA [Saisi] = A_COA_ETCOMA [Valeur avant saisie] | Q37: Contractuel | R37: P0003 | S37: Général | T37: Passant | U37: 41295 | V37: 43951 | W37: CDI_I_015 ET CDI_D_216 ET CDI_D_602 ET CDI_D_603 ET CDI_D_218 ET CDI_D_604 ET ABS_C_003 ET ABS_C_004 ET ABS_C_005 ET ABS_C_006 ET ABS_C_007 ET ABS_C_008 ET ABS_C_009 ET ABS_C_023 ET ABS_C_026 | X37: CDI_I_015 | Y37: =VLOOKUP(X37,'Axe 2 Règles de gestion'!$D$2:$F$564,3, FALSE) -> Le congé prend fin à l'issue de la période de 3 mois ou dans les 3 jours suivant le décès de la personne accompagnée ou à la demande de l'agent. | AT37: CDI_D_216 | AU37: =VLOOKUP(AT37,'Axe 2 Règles de gestion'!$D$2:$F$564,3, FALSE) -> Le congé de solidarité familiale, ou son renouvellement, est accordé pour une durée réelle maximale de trois mois. | AV37: CDI_D_602 | AW37: =VLOOKUP(AV37,'Axe 2 Règles de gestion'!$D$2:$F$564,3, FALSE) -> Le congé de solidarité familiale, ou son renouvellement, est accordé pour une durée prévisionnelle maximale de trois mois. | AX37: CDI_D_603 | AY37: =VLOOKUP(AX37,'Axe 2 Règles de gestion'!$D$2:$F$564,3, FALSE) -> Le congé de solidarité familiale peut être fractionné mais ne peut, renouvellement inclus, excéder les 6 mois. | AZ37: CDI_D_218 | BA37: =VLOOKUP(AZ37,'Axe 2 Règles de gestion'!$D$2:$F$564,3, FALSE) -> Le congé de solidarité familiale peut être fractionné mais chaque période doit être d'une durée réelle minimale de 7 jours consécutifs. | BB37: CDI_D_604 | BC37: =VLOOKUP(BB37,'Axe 2 Règles de gestion'!$D$2:$F$564,3, FALSE) -> Le congé de solidarité familiale peut être fractionné mais chaque période doit être d'une durée prévisionnelle minimale de 7 jours consécutifs. | BF37: ABS_C_003 | BG37: =VLOOKUP(BF37,'Axe 2 Règles de gestion'!$D$2:$F$564,3, FALSE) -> La date de début du congé/absence doit être antérieure ou égale à la date de fin réelle du congé/absence. | BH37: ABS_C_004 | BI37: =VLOOKUP(BH37,'Axe 2 Règles de gestion'!$D$2:$F$564,3, FALSE) -> La date de début du congé/absence doit être antérieure ou égale à la date de fin prévisionnelle du congé/absence. | BJ37: ABS_C_005 | BK37: =VLOOKUP(BJ37,'Axe 2 Règles de gestion'!$D$2:$F$564,3, FALSE) -> La date de fin réelle du congé/absence doit être antérieure ou égale à la date limite de fin réelle ou prévisionnelle du lien juridique. | BL37: ABS_C_006 | BM37: =VLOOKUP(BL37,'Axe 2 Règles de gestion'!$D$2:$F$564,3, FALSE) -> La date de fin prévisionnelle du congé/absence doit être antérieure ou égale à la date limite de fin réelle ou prévisionnelle du lien juridique. | BN37: ABS_C_007 | BO37: =VLOOKUP(BN37,'Axe 2 Règles de gestion'!$D$2:$F$564,3, FALSE) -> La date de fin réelle du congé/absence doit être antérieure à la date limite de départ à la retraite. | BP37: ABS_C_008 | BQ37: =VLOOKUP(BP37,'Axe 2 Règles de gestion'!$D$2:$F$564,3, FALSE) -> La date de fin prévisionnelle du congé/absence doit être antérieure à la date limite de départ à la retraite. | BR37: ABS_C_009 | BS37: =VLOOKUP(BR37,'Axe 2 Règles de gestion'!$D$2:$F$564,3, FALSE) -> La date de fin réelle ou la date de fin prévisionnelle du congé/absence doit être saisie. | BT37: ABS_C_023 | BU37: =VLOOKUP(BT37,'Axe 2 Règles de gestion'!$D$2:$F$564,3, FALSE) -> L'état du congé est renseigné. | BV37: ABS_C_026 | BW37: =VLOOKUP(BV37,'Axe 2 Règles de gestion'!$D$2:$F$564,3, FALSE) -> Dans le cas d'un congé autre que CLM, CLD, CGM et CITIS, l'indicateur de requalification doit être à non et les impacts spécifiques à la requalification ne doivent pas être mobilisés ou l'impact rémunération est vide.
A38: 22.10.00 | B38: M | C38: 44833.832 | D38: D0007 | E38: Congés/Absence | F38: S0072 | G38: Congé pour raisons de famille | H38: E0500 | I38: Congé de solidarité familiale | J38: Le Type de congé/absence est 'Congé de solidarité familiale' | K38: A_COA_TYCOAB [Saisi] = 'CG103' | L38: T1208 | M38: Congé de solidarité familiale - Fin | N38: Modification | O38: La valeur de l'Etat du congé saisie est égale à celle avant saisie | P38: A_COA_ETCOMA [Saisi] = A_COA_ETCOMA [Valeur avant saisie] | Q38: Contractuel | R38: P0003 | S38: Général | T38: Passant | U38: 43952 | V38: 44677 | W38: CDI_I_015 ET CDI_I_192 ET CDI_D_216 ET CDI_D_602 ET CDI_D_603 ET CDI_D_218 ET CDI_D_604 ET ABS_C_003 ET ABS_C_004 ET ABS_C_005 ET ABS_C_006 ET ABS_C_007 ET ABS_C_008 ET ABS_C_009 ET ABS_C_023 ET ABS_C_026 ET ABS_C_065 | X38: CDI_I_015 | Y38: =VLOOKUP(X38,'Axe 2 Règles de gestion'!$D$2:$F$564,3, FALSE) -> Le congé prend fin à l'issue de la période de 3 mois ou dans les 3 jours suivant le décès de la personne accompagnée ou à la demande de l'agent. | Z38: CDI_I_192 | AA38: =VLOOKUP(Z38,'Axe 2 Règles de gestion'!$D$2:$F$564,3, FALSE) -> A l'issue du congé, l'agent ne relevant pas des régimes d'obligations de service qui en fait la demande, bénéficie de plein droit des droits à congés accumulés sur son compte épargne-temps sans que les nécessités de service puissent être opposées. | AT38: CDI_D_216 | AU38: =VLOOKUP(AT38,'Axe 2 Règles de gestion'!$D$2:$F$564,3, FALSE) -> Le congé de solidarité familiale, ou son renouvellement, est accordé pour une durée réelle maximale de trois mois. | AV38: CDI_D_602 | AW38: =VLOOKUP(AV38,'Axe 2 Règles de gestion'!$D$2:$F$564,3, FALSE) -> Le congé de solidarité familiale, ou son renouvellement, est accordé pour une durée prévisionnelle maximale de trois mois. | AX38: CDI_D_603 | AY38: =VLOOKUP(AX38,'Axe 2 Règles de gestion'!$D$2:$F$564,3, FALSE) -> Le congé de solidarité familiale peut être fractionné mais ne peut, renouvellement inclus, excéder les 6 mois. | AZ38: CDI_D_218 | BA38: =VLOOKUP(AZ38,'Axe 2 Règles de gestion'!$D$2:$F$564,3, FALSE) -> Le congé de solidarité familiale peut être fractionné mais chaque période doit être d'une durée réelle minimale de 7 jours consécutifs. | BB38: CDI_D_604 | BC38: =VLOOKUP(BB38,'Axe 2 Règles de gestion'!$D$2:$F$564,3, FALSE) -> Le congé de solidarité familiale peut être fractionné mais chaque période doit être d'une durée prévisionnelle minimale de 7 jours consécutifs. | BF38: ABS_C_003 | BG38: =VLOOKUP(BF38,'Axe 2 Règles de gestion'!$D$2:$F$564,3, FALSE) -> La date de début du congé/absence doit être antérieure ou égale à la date de fin réelle du congé/absence. | BH38: ABS_C_004 | BI38: =VLOOKUP(BH38,'Axe 2 Règles de gestion'!$D$2:$F$564,3, FALSE) -> La date de début du congé/absence doit être antérieure ou égale à la date de fin prévisionnelle du congé/absence. | BJ38: ABS_C_005 | BK38: =VLOOKUP(BJ38,'Axe 2 Règles de gestion'!$D$2:$F$564,3, FALSE) -> La date de fin réelle du congé/absence doit être antérieure ou égale à la date limite de fin réelle ou prévisionnelle du lien juridique. | BL38: ABS_C_006 | BM38: =VLOOKUP(BL38,'Axe 2 Règles de gestion'!$D$2:$F$564,3, FALSE) -> La date de fin prévisionnelle du congé/absence doit être antérieure ou égale à la date limite de fin réelle ou prévisionnelle du lien juridique. | BN38: ABS_C_007 | BO38: =VLOOKUP(BN38,'Axe 2 Règles de gestion'!$D$2:$F$564,3, FALSE) -> La date de fin réelle du congé/absence doit être antérieure à la date limite de départ à la retraite. | BP38: ABS_C_008 | BQ38: =VLOOKUP(BP38,'Axe 2 Règles de gestion'!$D$2:$F$564,3, FALSE) -> La date de fin prévisionnelle du congé/absence doit être antérieure à la date limite de départ à la retraite. | BR38: ABS_C_009 | BS38: =VLOOKUP(BR38,'Axe 2 Règles de gestion'!$D$2:$F$564,3, FALSE) -> La date de fin réelle ou la date de fin prévisionnelle du congé/absence doit être saisie. | BT38: ABS_C_023 | BU38: =VLOOKUP(BT38,'Axe 2 Règles de gestion'!$D$2:$F$564,3, FALSE) -> L'état du congé est renseigné. | BV38: ABS_C_026 | BW38: =VLOOKUP(BV38,'Axe 2 Règles de gestion'!$D$2:$F$564,3, FALSE) -> Dans le cas d'un congé autre que CLM, CLD, CGM et CITIS, l'indicateur de requalification doit être à non et les impacts spécifiques à la requalification ne doivent pas être mobilisés ou l'impact rémunération est vide. | BX38: ABS_C_065 | BY38: =VLOOKUP(BX38,'Axe 2 Règles de gestion'!$D$2:$F$564,3, FALSE) -> L'agent en congé de présence parentale / congé de proche aidant / congé de solidarité familiale ne peut se voir accorder de manière simultanée un temps partiel pour congé de présence parentale / pour congé de proche aidant / pour congé de solidarité familiale.
A39: 22.10.00 | B39: A | C39: 44833.833 | D39: D0007 | E39: Congés/Absence | F39: S0072 | G39: Congé pour raisons de famille | H39: E0500 | I39: Congé de solidarité familiale | J39: Le Type de congé/absence est 'Congé de solidarité familiale' | K39: A_COA_TYCOAB [Saisi] = 'CG103' | L39: T1208 | M39: Congé de solidarité familiale - Fin | N39: Modification | O39: La valeur de l'Etat du congé saisie est égale à celle avant saisie | P39: A_COA_ETCOMA [Saisi] = A_COA_ETCOMA [Valeur avant saisie] | Q39: Contractuel | R39: P0003 | S39: Général | T39: Passant | U39: 44678 | W39: CDI_I_015 ET CDI_I_192 ET CDI_I_321 ET CDI_D_216 ET CDI_D_602 ET CDI_D_603 ET CDI_D_218 ET CDI_D_604 ET ABS_C_003 ET ABS_C_004 ET ABS_C_005 ET ABS_C_006 ET ABS_C_007 ET ABS_C_008 ET ABS_C_009 ET ABS_C_023 ET ABS_C_026 ET ABS_C_065 | X39: CDI_I_015 | Y39: =VLOOKUP(X39,'Axe 2 Règles de gestion'!$D$2:$F$564,3, FALSE) -> Le congé prend fin à l'issue de la période de 3 mois ou dans les 3 jours suivant le décès de la personne accompagnée ou à la demande de l'agent. | Z39: CDI_I_192 | AA39: =VLOOKUP(Z39,'Axe 2 Règles de gestion'!$D$2:$F$564,3, FALSE) -> A l'issue du congé, l'agent ne relevant pas des régimes d'obligations de service qui en fait la demande, bénéficie de plein droit des droits à congés accumulés sur son compte épargne-temps sans que les nécessités de service puissent être opposées. | AB39: CDI_I_321 | AC39: =VLOOKUP(AB39,'Axe 2 Règles de gestion'!$D$2:$F$564,3, FALSE) -> A l'issue du congé, l'agent qui remplit toujours les conditions requises est réemployé sur son emploi ou occupation précédente dans la mesure permise par le service. | AT39: CDI_D_216 | AU39: =VLOOKUP(AT39,'Axe 2 Règles de gestion'!$D$2:$F$564,3, FALSE) -> Le congé de solidarité familiale, ou son renouvellement, est accordé pour une durée réelle maximale de trois mois. | AV39: CDI_D_602 | AW39: =VLOOKUP(AV39,'Axe 2 Règles de gestion'!$D$2:$F$564,3, FALSE) -> Le congé de solidarité familiale, ou son renouvellement, est accordé pour une durée prévisionnelle maximale de trois mois. | AX39: CDI_D_603 | AY39: =VLOOKUP(AX39,'Axe 2 Règles de gestion'!$D$2:$F$564,3, FALSE) -> Le congé de solidarité familiale peut être fractionné mais ne peut, renouvellement inclus, excéder les 6 mois. | AZ39: CDI_D_218 | BA39: =VLOOKUP(AZ39,'Axe 2 Règles de gestion'!$D$2:$F$564,3, FALSE) -> Le congé de solidarité familiale peut être fractionné mais chaque période doit être d'une durée réelle minimale de 7 jours consécutifs. | BB39: CDI_D_604 | BC39: =VLOOKUP(BB39,'Axe 2 Règles de gestion'!$D$2:$F$564,3, FALSE) -> Le congé de solidarité familiale peut être fractionné mais chaque période doit être d'une durée prévisionnelle minimale de 7 jours consécutifs. | BF39: ABS_C_003 | BG39: =VLOOKUP(BF39,'Axe 2 Règles de gestion'!$D$2:$F$564,3, FALSE) -> La date de début du congé/absence doit être antérieure ou égale à la date de fin réelle du congé/absence. | BH39: ABS_C_004 | BI39: =VLOOKUP(BH39,'Axe 2 Règles de gestion'!$D$2:$F$564,3, FALSE) -> La date de début du congé/absence doit être antérieure ou égale à la date de fin prévisionnelle du congé/absence. | BJ39: ABS_C_005 | BK39: =VLOOKUP(BJ39,'Axe 2 Règles de gestion'!$D$2:$F$564,3, FALSE) -> La date de fin réelle du congé/absence doit être antérieure ou égale à la date limite de fin réelle ou prévisionnelle du lien juridique. | BL39: ABS_C_006 | BM39: =VLOOKUP(BL39,'Axe 2 Règles de gestion'!$D$2:$F$564,3, FALSE) -> La date de fin prévisionnelle du congé/absence doit être antérieure ou égale à la date limite de fin réelle ou prévisionnelle du lien juridique. | BN39: ABS_C_007 | BO39: =VLOOKUP(BN39,'Axe 2 Règles de gestion'!$D$2:$F$564,3, FALSE) -> La date de fin réelle du congé/absence doit être antérieure à la date limite de départ à la retraite. | BP39: ABS_C_008 | BQ39: =VLOOKUP(BP39,'Axe 2 Règles de gestion'!$D$2:$F$564,3, FALSE) -> La date de fin prévisionnelle du congé/absence doit être antérieure à la date limite de départ à la retraite. | BR39: ABS_C_009 | BS39: =VLOOKUP(BR39,'Axe 2 Règles de gestion'!$D$2:$F$564,3, FALSE) -> La date de fin réelle ou la date de fin prévisionnelle du congé/absence doit être saisie. | BT39: ABS_C_023 | BU39: =VLOOKUP(BT39,'Axe 2 Règles de gestion'!$D$2:$F$564,3, FALSE) -> L'état du congé est renseigné. | BV39: ABS_C_026 | BW39: =VLOOKUP(BV39,'Axe 2 Règles de gestion'!$D$2:$F$564,3, FALSE) -> Dans le cas d'un congé autre que CLM, CLD, CGM et CITIS, l'indicateur de requalification doit être à non et les impacts spécifiques à la requalification ne doivent pas être mobilisés ou l'impact rémunération est vide. | BX39: ABS_C_065 | BY39: =VLOOKUP(BX39,'Axe 2 Règles de gestion'!$D$2:$F$564,3, FALSE) -> L'agent en congé de présence parentale / congé de proche aidant / congé de solidarité familiale ne peut se voir accorder de manière simultanée un temps partiel pour congé de présence parentale / pour congé de proche aidant / pour congé de solidarité familiale.
A40: 25.10.00 | B40: M | C40: 45993.391 | D40: D0007 | E40: Congés/Absence | F40: S0072 | G40: Congé pour raisons de famille | H40: E0500 | I40: Congé de solidarité familiale | J40: Le Type de congé/absence est 'Congé de solidarité familiale' | K40: A_COA_TYCOAB [Saisi] = 'CG103' | L40: T1206 | M40: Congé de solidarité familiale - Demande | N40: Création Modification | O40: La valeur de l'Etat du congé est différente de 'Renouvellement' et la valeur de l'Etat du congé saisie est différente de celle avant saisie | P40: A_COA_ETCOMA [Saisi] <> 'EC02' ET A_COA_ETCOMA [Saisi] <> A_COA_ETCOMA [Valeur avant saisie] | Q40: Stagiaire ou auditeur ou élève | R40: P0004 | S40: Général | T40: Passant | U40: 40725 | W40: CDI_I_066 ET CDI_I_001 ET CDI_I_002 ET CDI_I_003 ET CDI_I_004 ET CDI_D_121 ET CDI_D_521 ET CDI_D_122 ET CDI_D_123 ET CDI_D_601 ET CDI_D_117 ET ABS_C_001 ET ABS_C_003 ET ABS_C_004 ET ABS_C_007 ET ABS_C_008 ET ABS_C_009 ET ABS_C_019 ET ABS_C_020 ET ABS_C_023 ET ABS_C_026 ET ABS_C_065 | X40: CDI_I_066 | Y40: =VLOOKUP(X40,'Axe 2 Règles de gestion'!$D$2:$F$564,3, FALSE) -> L'agent bénéficie des dispositions applicables aux agents titulaires pour le congé de solidarité familiale, sauf dispositions particulières. | Z40: CDI_I_001 | AA40: =VLOOKUP(Z40,'Axe 2 Règles de gestion'!$D$2:$F$564,3, FALSE) -> Le congé est accordé si un ascendant, descendant, un frère ou une sœur, une personne partageant le même domicile ou l'ayant désigné comme sa personne de confiance souffre d'une pathologie mettant en jeu le pronostic vital ou en phase avancée ou terminale d'une affection grave et incurable, quelle qu'en soit la cause. | AB40: CDI_I_002 | AC40: =VLOOKUP(AB40,'Axe 2 Règles de gestion'!$D$2:$F$564,3, FALSE) -> L'agent doit faire la demande par écrit. Elle est accordée de droit. | AD40: CDI_I_003 | AE40: =VLOOKUP(AD40,'Axe 2 Règles de gestion'!$D$2:$F$564,3, FALSE) -> La demande doit être appuyée d'un certificat médical attestant que la personne accompagnée souffre d'une pathologie mettant en jeu le pronostic vital ou en phase avancée ou terminale d'une affection grave et incurable, quelle qu'en soit la cause. | AF40: CDI_I_004 | AG40: =VLOOKUP(AF40,'Axe 2 Règles de gestion'!$D$2:$F$564,3, FALSE) -> Le congé peut être fractionné ou pris de manière continue. | AT40: CDI_D_121 | AU40: =VLOOKUP(AT40,'Axe 2 Règles de gestion'!$D$2:$F$564,3, FALSE) -> Le congé de solidarité familiale, ou son renouvellement, est accordé pour une durée réelle maximale de trois mois. | AV40: CDI_D_521 | AW40: =VLOOKUP(AV40,'Axe 2 Règles de gestion'!$D$2:$F$564,3, FALSE) -> Le congé de solidarité familiale, ou son renouvellement, est accordé pour une durée prévisionnelle maximale de trois mois. | AX40: CDI_D_122 | AY40: =VLOOKUP(AX40,'Axe 2 Règles de gestion'!$D$2:$F$564,3, FALSE) -> Le congé de solidarité familiale peut être fractionné mais ne peut, renouvellement inclus, excéder les 6 mois. | AZ40: CDI_D_123 | BA40: =VLOOKUP(AZ40,'Axe 2 Règles de gestion'!$D$2:$F$564,3, FALSE) -> Le congé de solidarité familiale peut être fractionné mais chaque période doit être d'une durée réelle minimale de 7 jours consécutifs. | BB40: CDI_D_601 | BC40: =VLOOKUP(BB40,'Axe 2 Règles de gestion'!$D$2:$F$564,3, FALSE) -> Le congé de solidarité familiale peut être fractionné mais chaque période doit être d'une durée prévisionnelle minimale de 7 jours consécutifs. | BD40: CDI_D_117 | BE40: =VLOOKUP(BD40,'Axe 2 Règles de gestion'!$D$2:$F$564,3, FALSE) -> L'agent doit être en activité. | BF40: ABS_C_001 | BG40: =VLOOKUP(BF40,'Axe 2 Règles de gestion'!$D$2:$F$564,3, FALSE) -> La date de début du congé/absence doit être postérieure ou égale à la date de recrutement dans la FPE ou dans la carrière militaire. | BH40: ABS_C_003 | BI40: =VLOOKUP(BH40,'Axe 2 Règles de gestion'!$D$2:$F$564,3, FALSE) -> La date de début du congé/absence doit être antérieure ou égale à la date de fin réelle du congé/absence. | BJ40: ABS_C_004 | BK40: =VLOOKUP(BJ40,'Axe 2 Règles de gestion'!$D$2:$F$564,3, FALSE) -> La date de début du congé/absence doit être antérieure ou égale à la date de fin prévisionnelle du congé/absence. | BL40: ABS_C_007 | BM40: =VLOOKUP(BL40,'Axe 2 Règles de gestion'!$D$2:$F$564,3, FALSE) -> La date de fin réelle du congé/absence doit être antérieure à la date limite de départ à la retraite. | BN40: ABS_C_008 | BO40: =VLOOKUP(BN40,'Axe 2 Règles de gestion'!$D$2:$F$564,3, FALSE) -> La date de fin prévisionnelle du congé/absence doit être antérieure à la date limite de départ à la retraite. | BP40: ABS_C_009 | BQ40: =VLOOKUP(BP40,'Axe 2 Règles de gestion'!$D$2:$F$564,3, FALSE) -> La date de fin réelle ou la date de fin prévisionnelle du congé/absence doit être saisie. | BR40: ABS_C_019 | BS40: =VLOOKUP(BR40,'Axe 2 Règles de gestion'!$D$2:$F$564,3, FALSE) -> Si l'absence ne commence pas par une demi-journée et si l'absence précédente ne finit pas par une demi journée, la date de début de l'absence saisie est postérieure à la date de fin réelle de l'absence précédente. | BT40: ABS_C_020 | BU40: =VLOOKUP(BT40,'Axe 2 Règles de gestion'!$D$2:$F$564,3, FALSE) -> Si l'absence ne commence pas par une demi-journée et si l'absence précédente ne finit pas par une demi journée, la date de début de l'absence saisie est postérieure à la date de fin prévisionnelle de l'absence précédente. | BV40: ABS_C_023 | BW40: =VLOOKUP(BV40,'Axe 2 Règles de gestion'!$D$2:$F$564,3, FALSE) -> L'état du congé est renseigné. | BX40: ABS_C_026 | BY40: =VLOOKUP(BX40,'Axe 2 Règles de gestion'!$D$2:$F$564,3, FALSE) -> Dans le cas d'un congé autre que CLM, CLD, CGM et CITIS, l'indicateur de requalification doit être à non et les impacts spécifiques à la requalification ne doivent pas être mobilisés ou l'impact rémunération est vide. | BZ40: ABS_C_065 | CA40: =VLOOKUP(BZ40,'Axe 2 Règles de gestion'!$D$2:$F$564,3, FALSE) -> L'agent en congé de présence parentale / congé de proche aidant / congé de solidarité familiale ne peut se voir accorder de manière simultanée un temps partiel pour congé de présence parentale / pour congé de proche aidant / pour congé de solidarité familiale. | CH40: 2025-118
A41: 25.10.00 | B41: M | C41: 45993.391 | D41: D0007 | E41: Congés/Absence | F41: S0072 | G41: Congé pour raisons de famille | H41: E0500 | I41: Congé de solidarité familiale | J41: Le Type de congé/absence est 'Congé de solidarité familiale' | K41: A_COA_TYCOAB [Saisi] = 'CG103' | L41: T1207 | M41: Congé de solidarité familiale - Renouvellement | N41: Création Modification | O41: La valeur de l'Etat du congé est égale à 'Renouvellement' et la valeur de l'Etat du congé saisie est différente de celle avant saisie | P41: A_COA_ETCOMA [Saisi] = 'EC02' ET A_COA_ETCOMA [Saisi] <> A_COA_ETCOMA [Valeur avant saisie] | Q41: Stagiaire ou auditeur ou élève | R41: P0004 | S41: Général | T41: Passant | U41: 40725 | W41: CDI_I_066 ET CDI_I_002 ET CDI_I_003 ET CDI_I_004 ET CDI_D_121 ET CDI_D_521 ET CDI_D_122 ET CDI_D_123 ET CDI_D_601 ET CDI_D_117 ET ABS_C_001 ET ABS_C_003 ET ABS_C_004 ET ABS_C_007 ET ABS_C_008 ET ABS_C_009 ET ABS_C_019 ET ABS_C_020 ET ABS_C_023 ET ABS_C_026 ET ABS_C_065 | X41: CDI_I_066 | Y41: =VLOOKUP(X41,'Axe 2 Règles de gestion'!$D$2:$F$564,3, FALSE) -> L'agent bénéficie des dispositions applicables aux agents titulaires pour le congé de solidarité familiale, sauf dispositions particulières. | Z41: CDI_I_002 | AA41: =VLOOKUP(Z41,'Axe 2 Règles de gestion'!$D$2:$F$564,3, FALSE) -> L'agent doit faire la demande par écrit. Elle est accordée de droit. | AB41: CDI_I_003 | AC41: =VLOOKUP(AB41,'Axe 2 Règles de gestion'!$D$2:$F$564,3, FALSE) -> La demande doit être appuyée d'un certificat médical attestant que la personne accompagnée souffre d'une pathologie mettant en jeu le pronostic vital ou en phase avancée ou terminale d'une affection grave et incurable, quelle qu'en soit la cause. | AD41: CDI_I_004 | AE41: =VLOOKUP(AD41,'Axe 2 Règles de gestion'!$D$2:$F$564,3, FALSE) -> Le congé peut être fractionné ou pris de manière continue. | AT41: CDI_D_121 | AU41: =VLOOKUP(AT41,'Axe 2 Règles de gestion'!$D$2:$F$564,3, FALSE) -> Le congé de solidarité familiale, ou son renouvellement, est accordé pour une durée réelle maximale de trois mois. | AV41: CDI_D_521 | AW41: =VLOOKUP(AV41,'Axe 2 Règles de gestion'!$D$2:$F$564,3, FALSE) -> Le congé de solidarité familiale, ou son renouvellement, est accordé pour une durée prévisionnelle maximale de trois mois. | AX41: CDI_D_122 | AY41: =VLOOKUP(AX41,'Axe 2 Règles de gestion'!$D$2:$F$564,3, FALSE) -> Le congé de solidarité familiale peut être fractionné mais ne peut, renouvellement inclus, excéder les 6 mois. | AZ41: CDI_D_123 | BA41: =VLOOKUP(AZ41,'Axe 2 Règles de gestion'!$D$2:$F$564,3, FALSE) -> Le congé de solidarité familiale peut être fractionné mais chaque période doit être d'une durée réelle minimale de 7 jours consécutifs. | BB41: CDI_D_601 | BC41: =VLOOKUP(BB41,'Axe 2 Règles de gestion'!$D$2:$F$564,3, FALSE) -> Le congé de solidarité familiale peut être fractionné mais chaque période doit être d'une durée prévisionnelle minimale de 7 jours consécutifs. | BD41: CDI_D_117 | BE41: =VLOOKUP(BD41,'Axe 2 Règles de gestion'!$D$2:$F$564,3, FALSE) -> L'agent doit être en activité. | BF41: ABS_C_001 | BG41: =VLOOKUP(BF41,'Axe 2 Règles de gestion'!$D$2:$F$564,3, FALSE) -> La date de début du congé/absence doit être postérieure ou égale à la date de recrutement dans la FPE ou dans la carrière militaire. | BH41: ABS_C_003 | BI41: =VLOOKUP(BH41,'Axe 2 Règles de gestion'!$D$2:$F$564,3, FALSE) -> La date de début du congé/absence doit être antérieure ou égale à la date de fin réelle du congé/absence. | BJ41: ABS_C_004 | BK41: =VLOOKUP(BJ41,'Axe 2 Règles de gestion'!$D$2:$F$564,3, FALSE) -> La date de début du congé/absence doit être antérieure ou égale à la date de fin prévisionnelle du congé/absence. | BL41: ABS_C_007 | BM41: =VLOOKUP(BL41,'Axe 2 Règles de gestion'!$D$2:$F$564,3, FALSE) -> La date de fin réelle du congé/absence doit être antérieure à la date limite de départ à la retraite. | BN41: ABS_C_008 | BO41: =VLOOKUP(BN41,'Axe 2 Règles de gestion'!$D$2:$F$564,3, FALSE) -> La date de fin prévisionnelle du congé/absence doit être antérieure à la date limite de départ à la retraite. | BP41: ABS_C_009 | BQ41: =VLOOKUP(BP41,'Axe 2 Règles de gestion'!$D$2:$F$564,3, FALSE) -> La date de fin réelle ou la date de fin prévisionnelle du congé/absence doit être saisie. | BR41: ABS_C_019 | BS41: =VLOOKUP(BR41,'Axe 2 Règles de gestion'!$D$2:$F$564,3, FALSE) -> Si l'absence ne commence pas par une demi-journée et si l'absence précédente ne finit pas par une demi journée, la date de début de l'absence saisie est postérieure à la date de fin réelle de l'absence précédente. | BT41: ABS_C_020 | BU41: =VLOOKUP(BT41,'Axe 2 Règles de gestion'!$D$2:$F$564,3, FALSE) -> Si l'absence ne commence pas par une demi-journée et si l'absence précédente ne finit pas par une demi journée, la date de début de l'absence saisie est postérieure à la date de fin prévisionnelle de l'absence précédente. | BV41: ABS_C_023 | BW41: =VLOOKUP(BV41,'Axe 2 Règles de gestion'!$D$2:$F$564,3, FALSE) -> L'état du congé est renseigné. | BX41: ABS_C_026 | BY41: =VLOOKUP(BX41,'Axe 2 Règles de gestion'!$D$2:$F$564,3, FALSE) -> Dans le cas d'un congé autre que CLM, CLD, CGM et CITIS, l'indicateur de requalification doit être à non et les impacts spécifiques à la requalification ne doivent pas être mobilisés ou l'impact rémunération est vide. | BZ41: ABS_C_065 | CA41: =VLOOKUP(BZ41,'Axe 2 Règles de gestion'!$D$2:$F$564,3, FALSE) -> L'agent en congé de présence parentale / congé de proche aidant / congé de solidarité familiale ne peut se voir accorder de manière simultanée un temps partiel pour congé de présence parentale / pour congé de proche aidant / pour congé de solidarité familiale. | CH41: 2025-118
A42: 25.10.00 | B42: M | C42: 45993.392 | D42: D0007 | E42: Congés/Absence | F42: S0072 | G42: Congé pour raisons de famille | H42: E0500 | I42: Congé de solidarité familiale | J42: Le Type de congé/absence est 'Congé de solidarité familiale' | K42: A_COA_TYCOAB [Saisi] = 'CG103' | L42: T1208 | M42: Congé de solidarité familiale - Fin | N42: Modification | O42: La valeur de l'Etat du congé saisie est égale à celle avant saisie | P42: A_COA_ETCOMA [Saisi] = A_COA_ETCOMA [Valeur avant saisie] | Q42: Stagiaire ou auditeur ou élève | R42: P0004 | S42: Général | T42: Passant | U42: 40725 | W42: CDI_I_066 ET CDI_I_005 ET CDI_D_121 ET CDI_D_521 ET CDI_D_122 ET CDI_D_123 ET CDI_D_601 ET ABS_C_003 ET ABS_C_004 ET ABS_C_007 ET ABS_C_008 ET ABS_C_009 ET ABS_C_023 ET ABS_C_026 ET ABS_C_065 | X42: CDI_I_066 | Y42: =VLOOKUP(X42,'Axe 2 Règles de gestion'!$D$2:$F$564,3, FALSE) -> L'agent bénéficie des dispositions applicables aux agents titulaires pour le congé de solidarité familiale, sauf dispositions particulières. | Z42: CDI_I_005 | AA42: =VLOOKUP(Z42,'Axe 2 Règles de gestion'!$D$2:$F$564,3, FALSE) -> Le congé prend fin à l'issue de la période de 3 mois ou dans les 3 jours suivant le décès de la personnes accompagnée ou à la demande de l'agent. | AT42: CDI_D_121 | AU42: =VLOOKUP(AT42,'Axe 2 Règles de gestion'!$D$2:$F$564,3, FALSE) -> Le congé de solidarité familiale, ou son renouvellement, est accordé pour une durée réelle maximale de trois mois. | AV42: CDI_D_521 | AW42: =VLOOKUP(AV42,'Axe 2 Règles de gestion'!$D$2:$F$564,3, FALSE) -> Le congé de solidarité familiale, ou son renouvellement, est accordé pour une durée prévisionnelle maximale de trois mois. | AX42: CDI_D_122 | AY42: =VLOOKUP(AX42,'Axe 2 Règles de gestion'!$D$2:$F$564,3, FALSE) -> Le congé de solidarité familiale peut être fractionné mais ne peut, renouvellement inclus, excéder les 6 mois. | AZ42: CDI_D_123 | BA42: =VLOOKUP(AZ42,'Axe 2 Règles de gestion'!$D$2:$F$564,3, FALSE) -> Le congé de solidarité familiale peut être fractionné mais chaque période doit être d'une durée réelle minimale de 7 jours consécutifs. | BB42: CDI_D_601 | BC42: =VLOOKUP(BB42,'Axe 2 Règles de gestion'!$D$2:$F$564,3, FALSE) -> Le congé de solidarité familiale peut être fractionné mais chaque période doit être d'une durée prévisionnelle minimale de 7 jours consécutifs. | BF42: ABS_C_003 | BG42: =VLOOKUP(BF42,'Axe 2 Règles de gestion'!$D$2:$F$564,3, FALSE) -> La date de début du congé/absence doit être antérieure ou égale à la date de fin réelle du congé/absence. | BH42: ABS_C_004 | BI42: =VLOOKUP(BH42,'Axe 2 Règles de gestion'!$D$2:$F$564,3, FALSE) -> La date de début du congé/absence doit être antérieure ou égale à la date de fin prévisionnelle du congé/absence. | BJ42: ABS_C_007 | BK42: =VLOOKUP(BJ42,'Axe 2 Règles de gestion'!$D$2:$F$564,3, FALSE) -> La date de fin réelle du congé/absence doit être antérieure à la date limite de départ à la retraite. | BL42: ABS_C_008 | BM42: =VLOOKUP(BL42,'Axe 2 Règles de gestion'!$D$2:$F$564,3, FALSE) -> La date de fin prévisionnelle du congé/absence doit être antérieure à la date limite de départ à la retraite. | BN42: ABS_C_009 | BO42: =VLOOKUP(BN42,'Axe 2 Règles de gestion'!$D$2:$F$564,3, FALSE) -> La date de fin réelle ou la date de fin prévisionnelle du congé/absence doit être saisie. | BP42: ABS_C_023 | BQ42: =VLOOKUP(BP42,'Axe 2 Règles de gestion'!$D$2:$F$564,3, FALSE) -> L'état du congé est renseigné. | BR42: ABS_C_026 | BS42: =VLOOKUP(BR42,'Axe 2 Règles de gestion'!$D$2:$F$564,3, FALSE) -> Dans le cas d'un congé autre que CLM, CLD, CGM et CITIS, l'indicateur de requalification doit être à non et les impacts spécifiques à la requalification ne doivent pas être mobilisés ou l'impact rémunération est vide. | BT42: ABS_C_065 | BU42: =VLOOKUP(BT42,'Axe 2 Règles de gestion'!$D$2:$F$564,3, FALSE) -> L'agent en congé de présence parentale / congé de proche aidant / congé de solidarité familiale ne peut se voir accorder de manière simultanée un temps partiel pour congé de présence parentale / pour congé de proche aidant / pour congé de solidarité familiale. | CH42: 2025-118
A43: 25.10.00 | B43: M | C43: 45937.706 | D43: D0007 | E43: Congés/Absence | F43: S0072 | G43: Congé pour raisons de famille | H43: E0500 | I43: Congé de solidarité familiale | J43: Le Type de congé/absence est 'Congé de solidarité familiale' | K43: A_COA_TYCOAB [Saisi] = 'CG103' | L43: T1206 | M43: Congé de solidarité familiale - Demande | N43: Création Modification | O43: La valeur de l'Etat du congé est différente de 'Renouvellement' et la valeur de l'Etat du congé saisie est différente de celle avant saisie | P43: A_COA_ETCOMA [Saisi] <> 'EC02' ET A_COA_ETCOMA [Saisi] <> A_COA_ETCOMA [Valeur avant saisie] | Q43: Ouvrier d'état | R43: P0005 | S43: Général | T43: Passant | U43: 40725 | V43: 45930 | W43: CDI_I_310 ET CDI_I_311 ET CDI_I_312 ET CDI_I_313 ET CDI_I_314 ET CDI_D_611 ET CDI_D_612 ET CDI_D_158 ET ABS_C_002 ET ABS_C_003 ET ABS_C_004 ET ABS_C_005 ET ABS_C_006 ET ABS_C_007 ET ABS_C_008 ET ABS_C_009 ET ABS_C_019 ET ABS_C_020 ET ABS_C_023 ET ABS_C_026 ET ABS_C_065 | X43: CDI_I_310 | Y43: =VLOOKUP(X43,'Axe 2 Règles de gestion'!$D$2:$F$564,3, FALSE) -> Le congé est accordé si une personne de la famille directe ou partageant le même domicile ou ayant désigné l'agent comme personne de confiance souffre d'une pathologie ou affection grave et incurable, quelle qu'en soit la cause. | Z43: CDI_I_311 | AA43: =VLOOKUP(Z43,'Axe 2 Règles de gestion'!$D$2:$F$564,3, FALSE) -> L'agent doit faire la demande par écrit. Elle est accordée de droit. | AB43: CDI_I_312 | AC43: =VLOOKUP(AB43,'Axe 2 Règles de gestion'!$D$2:$F$564,3, FALSE) -> La demande doit être appuyée d'un certificat médical attestant que la personne accompagnée souffre d'une pathologie mettant en jeu le pronostic vital ou en phase avancée ou terminale d'une affection grave et incurable, quelle qu'en soit la cause. | AD43: CDI_I_313 | AE43: =VLOOKUP(AD43,'Axe 2 Règles de gestion'!$D$2:$F$564,3, FALSE) -> Le congé peut être fractionné ou pris de manière continue. | AF43: CDI_I_314 | AG43: =VLOOKUP(AF43,'Axe 2 Règles de gestion'!$D$2:$F$564,3, FALSE) -> Le congé prend fin à l'issue de la période de 3 mois ou dans les 3 jours suivant le décès de la personnes accompagnée ou à la demande de l'agent. | AT43: CDI_D_611 | AU43: =VLOOKUP(AT43,'Axe 2 Règles de gestion'!$D$2:$F$564,3, FALSE) -> Le congé de solidarité familiale, ou son renouvellement, est accordé pour une durée prévisionnelle maximale de trois mois. | AV43: CDI_D_612 | AW43: =VLOOKUP(AV43,'Axe 2 Règles de gestion'!$D$2:$F$564,3, FALSE) -> Le congé de solidarité familiale peut être fractionné mais ne peut, renouvellement inclus, excéder les 6 mois. | AX43: CDI_D_158 | AY43: =VLOOKUP(AX43,'Axe 2 Règles de gestion'!$D$2:$F$564,3, FALSE) -> L'agent doit être en activité. | BF43: ABS_C_002 | BG43: =VLOOKUP(BF43,'Axe 2 Règles de gestion'!$D$2:$F$564,3, FALSE) -> La date de début du congé/absence doit être postérieure ou égale à la date de début du lien juridique. | BH43: ABS_C_003 | BI43: =VLOOKUP(BH43,'Axe 2 Règles de gestion'!$D$2:$F$564,3, FALSE) -> La date de début du congé/absence doit être antérieure ou égale à la date de fin réelle du congé/absence. | BJ43: ABS_C_004 | BK43: =VLOOKUP(BJ43,'Axe 2 Règles de gestion'!$D$2:$F$564,3, FALSE) -> La date de début du congé/absence doit être antérieure ou égale à la date de fin prévisionnelle du congé/absence. | BL43: ABS_C_005 | BM43: =VLOOKUP(BL43,'Axe 2 Règles de gestion'!$D$2:$F$564,3, FALSE) -> La date de fin réelle du congé/absence doit être antérieure ou égale à la date limite de fin réelle ou prévisionnelle du lien juridique. | BN43: ABS_C_006 | BO43: =VLOOKUP(BN43,'Axe 2 Règles de gestion'!$D$2:$F$564,3, FALSE) -> La date de fin prévisionnelle du congé/absence doit être antérieure ou égale à la date limite de fin réelle ou prévisionnelle du lien juridique. | BP43: ABS_C_007 | BQ43: =VLOOKUP(BP43,'Axe 2 Règles de gestion'!$D$2:$F$564,3, FALSE) -> La date de fin réelle du congé/absence doit être antérieure à la date limite de départ à la retraite. | BR43: ABS_C_008 | BS43: =VLOOKUP(BR43,'Axe 2 Règles de gestion'!$D$2:$F$564,3, FALSE) -> La date de fin prévisionnelle du congé/absence doit être antérieure à la date limite de départ à la retraite. | BT43: ABS_C_009 | BU43: =VLOOKUP(BT43,'Axe 2 Règles de gestion'!$D$2:$F$564,3, FALSE) -> La date de fin réelle ou la date de fin prévisionnelle du congé/absence doit être saisie. | BV43: ABS_C_019 | BW43: =VLOOKUP(BV43,'Axe 2 Règles de gestion'!$D$2:$F$564,3, FALSE) -> Si l'absence ne commence pas par une demi-journée et si l'absence précédente ne finit pas par une demi journée, la date de début de l'absence saisie est postérieure à la date de fin réelle de l'absence précédente. | BX43: ABS_C_020 | BY43: =VLOOKUP(BX43,'Axe 2 Règles de gestion'!$D$2:$F$564,3, FALSE) -> Si l'absence ne commence pas par une demi-journée et si l'absence précédente ne finit pas par une demi journée, la date de début de l'absence saisie est postérieure à la date de fin prévisionnelle de l'absence précédente. | BZ43: ABS_C_023 | CA43: =VLOOKUP(BZ43,'Axe 2 Règles de gestion'!$D$2:$F$564,3, FALSE) -> L'état du congé est renseigné. | CB43: ABS_C_026 | CC43: =VLOOKUP(CB43,'Axe 2 Règles de gestion'!$D$2:$F$564,3, FALSE) -> Dans le cas d'un congé autre que CLM, CLD, CGM et CITIS, l'indicateur de requalification doit être à non et les impacts spécifiques à la requalification ne doivent pas être mobilisés ou l'impact rémunération est vide. | CD43: ABS_C_065 | CE43: =VLOOKUP(CD43,'Axe 2 Règles de gestion'!$D$2:$F$564,3, FALSE) -> L'agent en congé de présence parentale / congé de proche aidant / congé de solidarité familiale ne peut se voir accorder de manière simultanée un temps partiel pour congé de présence parentale / pour congé de proche aidant / pour congé de solidarité familiale. | CH43: 2025-86
A44: 25.10.00 | B44: M | C44: 46041.647 | D44: D0007 | E44: Congés/Absence | F44: S0072 | G44: Congé pour raisons de famille | H44: E0500 | I44: Congé de solidarité familiale | J44: Le Type de congé/absence est 'Congé de solidarité familiale' | K44: A_COA_TYCOAB [Saisi] = 'CG103' | L44: T1206 | M44: Congé de solidarité familiale - Demande | N44: Création Modification | O44: La valeur de l'Etat du congé est différente de 'Renouvellement' et la valeur de l'Etat du congé saisie est différente de celle avant saisie | P44: A_COA_ETCOMA [Saisi] <> 'EC02' ET A_COA_ETCOMA [Saisi] <> A_COA_ETCOMA [Valeur avant saisie] | Q44: Ouvrier d'état | R44: P0005 | S44: Général | T44: Passant | U44: 45931 | W44: CDI_I_062 ET CDI_I_002 ET CDI_I_003 ET CDI_I_001 ET CDI_I_004 ET CDI_D_121 ET CDI_D_521 ET CDI_D_122 ET CDI_D_123 ET CDI_D_601 ET CDI_D_117 ET ABS_C_002 ET ABS_C_003 ET ABS_C_004 ET ABS_C_005 ET ABS_C_006 ET ABS_C_007 ET ABS_C_008 ET ABS_C_009 ET ABS_C_019 ET ABS_C_020 ET ABS_C_023 ET ABS_C_026 ET ABS_C_065 | X44: CDI_I_062 | Y44: =VLOOKUP(X44,'Axe 2 Règles de gestion'!$D$2:$F$564,3, FALSE) -> L'agent bénéficie des dispositions applicables aux agents titulaires pour le congé de solidarité familiale, sauf dispositions particulières. | Z44: CDI_I_002 | AA44: =VLOOKUP(Z44,'Axe 2 Règles de gestion'!$D$2:$F$564,3, FALSE) -> L'agent doit faire la demande par écrit. Elle est accordée de droit. | AB44: CDI_I_003 | AC44: =VLOOKUP(AB44,'Axe 2 Règles de gestion'!$D$2:$F$564,3, FALSE) -> La demande doit être appuyée d'un certificat médical attestant que la personne accompagnée souffre d'une pathologie mettant en jeu le pronostic vital ou en phase avancée ou terminale d'une affection grave et incurable, quelle qu'en soit la cause. | AD44: CDI_I_001 | AE44: =VLOOKUP(AD44,'Axe 2 Règles de gestion'!$D$2:$F$564,3, FALSE) -> Le congé est accordé si un ascendant, descendant, un frère ou une sœur, une personne partageant le même domicile ou l'ayant désigné comme sa personne de confiance souffre d'une pathologie mettant en jeu le pronostic vital ou en phase avancée ou terminale d'une affection grave et incurable, quelle qu'en soit la cause. | AF44: CDI_I_004 | AG44: =VLOOKUP(AF44,'Axe 2 Règles de gestion'!$D$2:$F$564,3, FALSE) -> Le congé peut être fractionné ou pris de manière continue. | AT44: CDI_D_121 | AU44: =VLOOKUP(AT44,'Axe 2 Règles de gestion'!$D$2:$F$564,3, FALSE) -> Le congé de solidarité familiale, ou son renouvellement, est accordé pour une durée réelle maximale de trois mois. | AV44: CDI_D_521 | AW44: =VLOOKUP(AV44,'Axe 2 Règles de gestion'!$D$2:$F$564,3, FALSE) -> Le congé de solidarité familiale, ou son renouvellement, est accordé pour une durée prévisionnelle maximale de trois mois. | AX44: CDI_D_122 | AY44: =VLOOKUP(AX44,'Axe 2 Règles de gestion'!$D$2:$F$564,3, FALSE) -> Le congé de solidarité familiale peut être fractionné mais ne peut, renouvellement inclus, excéder les 6 mois. | AZ44: CDI_D_123 | BA44: =VLOOKUP(AZ44,'Axe 2 Règles de gestion'!$D$2:$F$564,3, FALSE) -> Le congé de solidarité familiale peut être fractionné mais chaque période doit être d'une durée réelle minimale de 7 jours consécutifs. | BB44: CDI_D_601 | BC44: =VLOOKUP(BB44,'Axe 2 Règles de gestion'!$D$2:$F$564,3, FALSE) -> Le congé de solidarité familiale peut être fractionné mais chaque période doit être d'une durée prévisionnelle minimale de 7 jours consécutifs. | BD44: CDI_D_117 | BE44: =VLOOKUP(BD44,'Axe 2 Règles de gestion'!$D$2:$F$564,3, FALSE) -> L'agent doit être en activité. | BF44: ABS_C_002 | BG44: =VLOOKUP(BF44,'Axe 2 Règles de gestion'!$D$2:$F$564,3, FALSE) -> La date de début du congé/absence doit être postérieure ou égale à la date de début du lien juridique. | BH44: ABS_C_003 | BI44: =VLOOKUP(BH44,'Axe 2 Règles de gestion'!$D$2:$F$564,3, FALSE) -> La date de début du congé/absence doit être antérieure ou égale à la date de fin réelle du congé/absence. | BJ44: ABS_C_004 | BK44: =VLOOKUP(BJ44,'Axe 2 Règles de gestion'!$D$2:$F$564,3, FALSE) -> La date de début du congé/absence doit être antérieure ou égale à la date de fin prévisionnelle du congé/absence. | BL44: ABS_C_005 | BM44: =VLOOKUP(BL44,'Axe 2 Règles de gestion'!$D$2:$F$564,3, FALSE) -> La date de fin réelle du congé/absence doit être antérieure ou égale à la date limite de fin réelle ou prévisionnelle du lien juridique. | BN44: ABS_C_006 | BO44: =VLOOKUP(BN44,'Axe 2 Règles de gestion'!$D$2:$F$564,3, FALSE) -> La date de fin prévisionnelle du congé/absence doit être antérieure ou égale à la date limite de fin réelle ou prévisionnelle du lien juridique. | BP44: ABS_C_007 | BQ44: =VLOOKUP(BP44,'Axe 2 Règles de gestion'!$D$2:$F$564,3, FALSE) -> La date de fin réelle du congé/absence doit être antérieure à la date limite de départ à la retraite. | BR44: ABS_C_008 | BS44: =VLOOKUP(BR44,'Axe 2 Règles de gestion'!$D$2:$F$564,3, FALSE) -> La date de fin prévisionnelle du congé/absence doit être antérieure à la date limite de départ à la retraite. | BT44: ABS_C_009 | BU44: =VLOOKUP(BT44,'Axe 2 Règles de gestion'!$D$2:$F$564,3, FALSE) -> La date de fin réelle ou la date de fin prévisionnelle du congé/absence doit être saisie. | BV44: ABS_C_019 | BW44: =VLOOKUP(BV44,'Axe 2 Règles de gestion'!$D$2:$F$564,3, FALSE) -> Si l'absence ne commence pas par une demi-journée et si l'absence précédente ne finit pas par une demi journée, la date de début de l'absence saisie est postérieure à la date de fin réelle de l'absence précédente. | BX44: ABS_C_020 | BY44: =VLOOKUP(BX44,'Axe 2 Règles de gestion'!$D$2:$F$564,3, FALSE) -> Si l'absence ne commence pas par une demi-journée et si l'absence précédente ne finit pas par une demi journée, la date de début de l'absence saisie est postérieure à la date de fin prévisionnelle de l'absence précédente. | BZ44: ABS_C_023 | CA44: =VLOOKUP(BZ44,'Axe 2 Règles de gestion'!$D$2:$F$564,3, FALSE) -> L'état du congé est renseigné. | CB44: ABS_C_026 | CC44: =VLOOKUP(CB44,'Axe 2 Règles de gestion'!$D$2:$F$564,3, FALSE) -> Dans le cas d'un congé autre que CLM, CLD, CGM et CITIS, l'indicateur de requalification doit être à non et les impacts spécifiques à la requalification ne doivent pas être mobilisés ou l'impact rémunération est vide. | CD44: ABS_C_065 | CE44: =VLOOKUP(CD44,'Axe 2 Règles de gestion'!$D$2:$F$564,3, FALSE) -> L'agent en congé de présence parentale / congé de proche aidant / congé de solidarité familiale ne peut se voir accorder de manière simultanée un temps partiel pour congé de présence parentale / pour congé de proche aidant / pour congé de solidarité familiale. | CH44: 2025-86
A45: 25.10.00 | B45: M | C45: 45937.707 | D45: D0007 | E45: Congés/Absence | F45: S0072 | G45: Congé pour raisons de famille | H45: E0500 | I45: Congé de solidarité familiale | J45: Le Type de congé/absence est 'Congé de solidarité familiale' | K45: A_COA_TYCOAB [Saisi] = 'CG103' | L45: T1207 | M45: Congé de solidarité familiale - Renouvellement | N45: Création Modification | O45: La valeur de l'Etat du congé est égale à 'Renouvellement' et la valeur de l'Etat du congé saisie est différente de celle avant saisie | P45: A_COA_ETCOMA [Saisi] = 'EC02' ET A_COA_ETCOMA [Saisi] <> A_COA_ETCOMA [Valeur avant saisie] | Q45: Ouvrier d'état | R45: P0005 | S45: Général | T45: Passant | U45: 40725 | V45: 45930 | W45: CDI_I_310 ET CDI_I_311 ET CDI_I_312 ET CDI_I_313 ET CDI_I_314 ET CDI_D_611 ET CDI_D_612 ET CDI_D_158 ET ABS_C_002 ET ABS_C_003 ET ABS_C_004 ET ABS_C_005 ET ABS_C_006 ET ABS_C_007 ET ABS_C_008 ET ABS_C_009 ET ABS_C_019 ET ABS_C_020 ET ABS_C_023 ET ABS_C_026 ET ABS_C_065 | X45: CDI_I_310 | Y45: =VLOOKUP(X45,'Axe 2 Règles de gestion'!$D$2:$F$564,3, FALSE) -> Le congé est accordé si une personne de la famille directe ou partageant le même domicile ou ayant désigné l'agent comme personne de confiance souffre d'une pathologie ou affection grave et incurable, quelle qu'en soit la cause. | Z45: CDI_I_311 | AA45: =VLOOKUP(Z45,'Axe 2 Règles de gestion'!$D$2:$F$564,3, FALSE) -> L'agent doit faire la demande par écrit. Elle est accordée de droit. | AB45: CDI_I_312 | AC45: =VLOOKUP(AB45,'Axe 2 Règles de gestion'!$D$2:$F$564,3, FALSE) -> La demande doit être appuyée d'un certificat médical attestant que la personne accompagnée souffre d'une pathologie mettant en jeu le pronostic vital ou en phase avancée ou terminale d'une affection grave et incurable, quelle qu'en soit la cause. | AD45: CDI_I_313 | AE45: =VLOOKUP(AD45,'Axe 2 Règles de gestion'!$D$2:$F$564,3, FALSE) -> Le congé peut être fractionné ou pris de manière continue. | AF45: CDI_I_314 | AG45: =VLOOKUP(AF45,'Axe 2 Règles de gestion'!$D$2:$F$564,3, FALSE) -> Le congé prend fin à l'issue de la période de 3 mois ou dans les 3 jours suivant le décès de la personnes accompagnée ou à la demande de l'agent. | AT45: CDI_D_611 | AU45: =VLOOKUP(AT45,'Axe 2 Règles de gestion'!$D$2:$F$564,3, FALSE) -> Le congé de solidarité familiale, ou son renouvellement, est accordé pour une durée prévisionnelle maximale de trois mois. | AV45: CDI_D_612 | AW45: =VLOOKUP(AV45,'Axe 2 Règles de gestion'!$D$2:$F$564,3, FALSE) -> Le congé de solidarité familiale peut être fractionné mais ne peut, renouvellement inclus, excéder les 6 mois. | AX45: CDI_D_158 | AY45: =VLOOKUP(AX45,'Axe 2 Règles de gestion'!$D$2:$F$564,3, FALSE) -> L'agent doit être en activité. | BF45: ABS_C_002 | BG45: =VLOOKUP(BF45,'Axe 2 Règles de gestion'!$D$2:$F$564,3, FALSE) -> La date de début du congé/absence doit être postérieure ou égale à la date de début du lien juridique. | BH45: ABS_C_003 | BI45: =VLOOKUP(BH45,'Axe 2 Règles de gestion'!$D$2:$F$564,3, FALSE) -> La date de début du congé/absence doit être antérieure ou égale à la date de fin réelle du congé/absence. | BJ45: ABS_C_004 | BK45: =VLOOKUP(BJ45,'Axe 2 Règles de gestion'!$D$2:$F$564,3, FALSE) -> La date de début du congé/absence doit être antérieure ou égale à la date de fin prévisionnelle du congé/absence. | BL45: ABS_C_005 | BM45: =VLOOKUP(BL45,'Axe 2 Règles de gestion'!$D$2:$F$564,3, FALSE) -> La date de fin réelle du congé/absence doit être antérieure ou égale à la date limite de fin réelle ou prévisionnelle du lien juridique. | BN45: ABS_C_006 | BO45: =VLOOKUP(BN45,'Axe 2 Règles de gestion'!$D$2:$F$564,3, FALSE) -> La date de fin prévisionnelle du congé/absence doit être antérieure ou égale à la date limite de fin réelle ou prévisionnelle du lien juridique. | BP45: ABS_C_007 | BQ45: =VLOOKUP(BP45,'Axe 2 Règles de gestion'!$D$2:$F$564,3, FALSE) -> La date de fin réelle du congé/absence doit être antérieure à la date limite de départ à la retraite. | BR45: ABS_C_008 | BS45: =VLOOKUP(BR45,'Axe 2 Règles de gestion'!$D$2:$F$564,3, FALSE) -> La date de fin prévisionnelle du congé/absence doit être antérieure à la date limite de départ à la retraite. | BT45: ABS_C_009 | BU45: =VLOOKUP(BT45,'Axe 2 Règles de gestion'!$D$2:$F$564,3, FALSE) -> La date de fin réelle ou la date de fin prévisionnelle du congé/absence doit être saisie. | BV45: ABS_C_019 | BW45: =VLOOKUP(BV45,'Axe 2 Règles de gestion'!$D$2:$F$564,3, FALSE) -> Si l'absence ne commence pas par une demi-journée et si l'absence précédente ne finit pas par une demi journée, la date de début de l'absence saisie est postérieure à la date de fin réelle de l'absence précédente. | BX45: ABS_C_020 | BY45: =VLOOKUP(BX45,'Axe 2 Règles de gestion'!$D$2:$F$564,3, FALSE) -> Si l'absence ne commence pas par une demi-journée et si l'absence précédente ne finit pas par une demi journée, la date de début de l'absence saisie est postérieure à la date de fin prévisionnelle de l'absence précédente. | BZ45: ABS_C_023 | CA45: =VLOOKUP(BZ45,'Axe 2 Règles de gestion'!$D$2:$F$564,3, FALSE) -> L'état du congé est renseigné. | CB45: ABS_C_026 | CC45: =VLOOKUP(CB45,'Axe 2 Règles de gestion'!$D$2:$F$564,3, FALSE) -> Dans le cas d'un congé autre que CLM, CLD, CGM et CITIS, l'indicateur de requalification doit être à non et les impacts spécifiques à la requalification ne doivent pas être mobilisés ou l'impact rémunération est vide. | CD45: ABS_C_065 | CE45: =VLOOKUP(CD45,'Axe 2 Règles de gestion'!$D$2:$F$564,3, FALSE) -> L'agent en congé de présence parentale / congé de proche aidant / congé de solidarité familiale ne peut se voir accorder de manière simultanée un temps partiel pour congé de présence parentale / pour congé de proche aidant / pour congé de solidarité familiale. | CH45: 2025-86
A46: 25.10.00 | B46: M | C46: 46041.648 | D46: D0007 | E46: Congés/Absence | F46: S0072 | G46: Congé pour raisons de famille | H46: E0500 | I46: Congé de solidarité familiale | J46: Le Type de congé/absence est 'Congé de solidarité familiale' | K46: A_COA_TYCOAB [Saisi] = 'CG103' | L46: T1207 | M46: Congé de solidarité familiale - Renouvellement | N46: Création Modification | O46: La valeur de l'Etat du congé est égale à 'Renouvellement' et la valeur de l'Etat du congé saisie est différente de celle avant saisie | P46: A_COA_ETCOMA [Saisi] = 'EC02' ET A_COA_ETCOMA [Saisi] <> A_COA_ETCOMA [Valeur avant saisie] | Q46: Ouvrier d'état | R46: P0005 | S46: Général | T46: Passant | U46: 45931 | W46: CDI_I_062 ET CDI_I_002 ET CDI_I_003 ET CDI_I_001 ET CDI_I_064 ET CDI_D_121 ET CDI_D_521 ET CDI_D_122 ET CDI_D_123 ET CDI_D_601 ET CDI_D_117 ET ABS_C_002 ET ABS_C_003 ET ABS_C_004 ET ABS_C_005 ET ABS_C_006 ET ABS_C_007 ET ABS_C_008 ET ABS_C_009 ET ABS_C_019 ET ABS_C_020 ET ABS_C_023 ET ABS_C_026 ET ABS_C_065 | X46: CDI_I_062 | Y46: =VLOOKUP(X46,'Axe 2 Règles de gestion'!$D$2:$F$564,3, FALSE) -> L'agent bénéficie des dispositions applicables aux agents titulaires pour le congé de solidarité familiale, sauf dispositions particulières. | Z46: CDI_I_002 | AA46: =VLOOKUP(Z46,'Axe 2 Règles de gestion'!$D$2:$F$564,3, FALSE) -> L'agent doit faire la demande par écrit. Elle est accordée de droit. | AB46: CDI_I_003 | AC46: =VLOOKUP(AB46,'Axe 2 Règles de gestion'!$D$2:$F$564,3, FALSE) -> La demande doit être appuyée d'un certificat médical attestant que la personne accompagnée souffre d'une pathologie mettant en jeu le pronostic vital ou en phase avancée ou terminale d'une affection grave et incurable, quelle qu'en soit la cause. | AD46: CDI_I_001 | AE46: =VLOOKUP(AD46,'Axe 2 Règles de gestion'!$D$2:$F$564,3, FALSE) -> Le congé est accordé si un ascendant, descendant, un frère ou une sœur, une personne partageant le même domicile ou l'ayant désigné comme sa personne de confiance souffre d'une pathologie mettant en jeu le pronostic vital ou en phase avancée ou terminale d'une affection grave et incurable, quelle qu'en soit la cause. | AF46: CDI_I_064 | AG46: =VLOOKUP(AF46,'Axe 2 Règles de gestion'!$D$2:$F$564,3, FALSE) -> Si son ancien emploi ne peut lui être proposé, l'agent est affecté dans un emploi équivalent, le plus proche de son dernier lieu de travail. | AT46: CDI_D_121 | AU46: =VLOOKUP(AT46,'Axe 2 Règles de gestion'!$D$2:$F$564,3, FALSE) -> Le congé de solidarité familiale, ou son renouvellement, est accordé pour une durée réelle maximale de trois mois. | AV46: CDI_D_521 | AW46: =VLOOKUP(AV46,'Axe 2 Règles de gestion'!$D$2:$F$564,3, FALSE) -> Le congé de solidarité familiale, ou son renouvellement, est accordé pour une durée prévisionnelle maximale de trois mois. | AX46: CDI_D_122 | AY46: =VLOOKUP(AX46,'Axe 2 Règles de gestion'!$D$2:$F$564,3, FALSE) -> Le congé de solidarité familiale peut être fractionné mais ne peut, renouvellement inclus, excéder les 6 mois. | AZ46: CDI_D_123 | BA46: =VLOOKUP(AZ46,'Axe 2 Règles de gestion'!$D$2:$F$564,3, FALSE) -> Le congé de solidarité familiale peut être fractionné mais chaque période doit être d'une durée réelle minimale de 7 jours consécutifs. | BB46: CDI_D_601 | BC46: =VLOOKUP(BB46,'Axe 2 Règles de gestion'!$D$2:$F$564,3, FALSE) -> Le congé de solidarité familiale peut être fractionné mais chaque période doit être d'une durée prévisionnelle minimale de 7 jours consécutifs. | BD46: CDI_D_117 | BE46: =VLOOKUP(BD46,'Axe 2 Règles de gestion'!$D$2:$F$564,3, FALSE) -> L'agent doit être en activité. | BF46: ABS_C_002 | BG46: =VLOOKUP(BF46,'Axe 2 Règles de gestion'!$D$2:$F$564,3, FALSE) -> La date de début du congé/absence doit être postérieure ou égale à la date de début du lien juridique. | BH46: ABS_C_003 | BI46: =VLOOKUP(BH46,'Axe 2 Règles de gestion'!$D$2:$F$564,3, FALSE) -> La date de début du congé/absence doit être antérieure ou égale à la date de fin réelle du congé/absence. | BJ46: ABS_C_004 | BK46: =VLOOKUP(BJ46,'Axe 2 Règles de gestion'!$D$2:$F$564,3, FALSE) -> La date de début du congé/absence doit être antérieure ou égale à la date de fin prévisionnelle du congé/absence. | BL46: ABS_C_005 | BM46: =VLOOKUP(BL46,'Axe 2 Règles de gestion'!$D$2:$F$564,3, FALSE) -> La date de fin réelle du congé/absence doit être antérieure ou égale à la date limite de fin réelle ou prévisionnelle du lien juridique. | BN46: ABS_C_006 | BO46: =VLOOKUP(BN46,'Axe 2 Règles de gestion'!$D$2:$F$564,3, FALSE) -> La date de fin prévisionnelle du congé/absence doit être antérieure ou égale à la date limite de fin réelle ou prévisionnelle du lien juridique. | BP46: ABS_C_007 | BQ46: =VLOOKUP(BP46,'Axe 2 Règles de gestion'!$D$2:$F$564,3, FALSE) -> La date de fin réelle du congé/absence doit être antérieure à la date limite de départ à la retraite. | BR46: ABS_C_008 | BS46: =VLOOKUP(BR46,'Axe 2 Règles de gestion'!$D$2:$F$564,3, FALSE) -> La date de fin prévisionnelle du congé/absence doit être antérieure à la date limite de départ à la retraite. | BT46: ABS_C_009 | BU46: =VLOOKUP(BT46,'Axe 2 Règles de gestion'!$D$2:$F$564,3, FALSE) -> La date de fin réelle ou la date de fin prévisionnelle du congé/absence doit être saisie. | BV46: ABS_C_019 | BW46: =VLOOKUP(BV46,'Axe 2 Règles de gestion'!$D$2:$F$564,3, FALSE) -> Si l'absence ne commence pas par une demi-journée et si l'absence précédente ne finit pas par une demi journée, la date de début de l'absence saisie est postérieure à la date de fin réelle de l'absence précédente. | BX46: ABS_C_020 | BY46: =VLOOKUP(BX46,'Axe 2 Règles de gestion'!$D$2:$F$564,3, FALSE) -> Si l'absence ne commence pas par une demi-journée et si l'absence précédente ne finit pas par une demi journée, la date de début de l'absence saisie est postérieure à la date de fin prévisionnelle de l'absence précédente. | BZ46: ABS_C_023 | CA46: =VLOOKUP(BZ46,'Axe 2 Règles de gestion'!$D$2:$F$564,3, FALSE) -> L'état du congé est renseigné. | CB46: ABS_C_026 | CC46: =VLOOKUP(CB46,'Axe 2 Règles de gestion'!$D$2:$F$564,3, FALSE) -> Dans le cas d'un congé autre que CLM, CLD, CGM et CITIS, l'indicateur de requalification doit être à non et les impacts spécifiques à la requalification ne doivent pas être mobilisés ou l'impact rémunération est vide. | CD46: ABS_C_065 | CE46: =VLOOKUP(CD46,'Axe 2 Règles de gestion'!$D$2:$F$564,3, FALSE) -> L'agent en congé de présence parentale / congé de proche aidant / congé de solidarité familiale ne peut se voir accorder de manière simultanée un temps partiel pour congé de présence parentale / pour congé de proche aidant / pour congé de solidarité familiale. | CH46: 2025-86
A47: 25.10.00 | B47: M | C47: 45937.708 | D47: D0007 | E47: Congés/Absence | F47: S0072 | G47: Congé pour raisons de famille | H47: E0500 | I47: Congé de solidarité familiale | J47: Le Type de congé/absence est 'Congé de solidarité familiale' | K47: A_COA_TYCOAB [Saisi] = 'CG103' | L47: T1208 | M47: Congé de solidarité familiale - Fin | N47: Modification | O47: La valeur de l'Etat du congé saisie est égale à celle avant saisie | P47: A_COA_ETCOMA [Saisi] = A_COA_ETCOMA [Valeur avant saisie] | Q47: Ouvrier d'état | R47: P0005 | S47: Général | T47: Passant | U47: 40725 | V47: 45930 | W47: CDI_I_314 ET CDI_D_611 ET CDI_D_612 ET ABS_C_003 ET ABS_C_004 ET ABS_C_005 ET ABS_C_006 ET ABS_C_007 ET ABS_C_008 ET ABS_C_009 ET ABS_C_023 ET ABS_C_026 ET ABS_C_065 | X47: CDI_I_314 | Y47: =VLOOKUP(X47,'Axe 2 Règles de gestion'!$D$2:$F$564,3, FALSE) -> Le congé prend fin à l'issue de la période de 3 mois ou dans les 3 jours suivant le décès de la personnes accompagnée ou à la demande de l'agent. | AT47: CDI_D_611 | AU47: =VLOOKUP(AT47,'Axe 2 Règles de gestion'!$D$2:$F$564,3, FALSE) -> Le congé de solidarité familiale, ou son renouvellement, est accordé pour une durée prévisionnelle maximale de trois mois. | AV47: CDI_D_612 | AW47: =VLOOKUP(AV47,'Axe 2 Règles de gestion'!$D$2:$F$564,3, FALSE) -> Le congé de solidarité familiale peut être fractionné mais ne peut, renouvellement inclus, excéder les 6 mois. | BF47: ABS_C_003 | BG47: =VLOOKUP(BF47,'Axe 2 Règles de gestion'!$D$2:$F$564,3, FALSE) -> La date de début du congé/absence doit être antérieure ou égale à la date de fin réelle du congé/absence. | BH47: ABS_C_004 | BI47: =VLOOKUP(BH47,'Axe 2 Règles de gestion'!$D$2:$F$564,3, FALSE) -> La date de début du congé/absence doit être antérieure ou égale à la date de fin prévisionnelle du congé/absence. | BJ47: ABS_C_005 | BK47: =VLOOKUP(BJ47,'Axe 2 Règles de gestion'!$D$2:$F$564,3, FALSE) -> La date de fin réelle du congé/absence doit être antérieure ou égale à la date limite de fin réelle ou prévisionnelle du lien juridique. | BL47: ABS_C_006 | BM47: =VLOOKUP(BL47,'Axe 2 Règles de gestion'!$D$2:$F$564,3, FALSE) -> La date de fin prévisionnelle du congé/absence doit être antérieure ou égale à la date limite de fin réelle ou prévisionnelle du lien juridique. | BN47: ABS_C_007 | BO47: =VLOOKUP(BN47,'Axe 2 Règles de gestion'!$D$2:$F$564,3, FALSE) -> La date de fin réelle du congé/absence doit être antérieure à la date limite de départ à la retraite. | BP47: ABS_C_008 | BQ47: =VLOOKUP(BP47,'Axe 2 Règles de gestion'!$D$2:$F$564,3, FALSE) -> La date de fin prévisionnelle du congé/absence doit être antérieure à la date limite de départ à la retraite. | BR47: ABS_C_009 | BS47: =VLOOKUP(BR47,'Axe 2 Règles de gestion'!$D$2:$F$564,3, FALSE) -> La date de fin réelle ou la date de fin prévisionnelle du congé/absence doit être saisie. | BT47: ABS_C_023 | BU47: =VLOOKUP(BT47,'Axe 2 Règles de gestion'!$D$2:$F$564,3, FALSE) -> L'état du congé est renseigné. | BV47: ABS_C_026 | BW47: =VLOOKUP(BV47,'Axe 2 Règles de gestion'!$D$2:$F$564,3, FALSE) -> Dans le cas d'un congé autre que CLM, CLD, CGM et CITIS, l'indicateur de requalification doit être à non et les impacts spécifiques à la requalification ne doivent pas être mobilisés ou l'impact rémunération est vide. | BX47: ABS_C_065 | BY47: =VLOOKUP(BX47,'Axe 2 Règles de gestion'!$D$2:$F$564,3, FALSE) -> L'agent en congé de présence parentale / congé de proche aidant / congé de solidarité familiale ne peut se voir accorder de manière simultanée un temps partiel pour congé de présence parentale / pour congé de proche aidant / pour congé de solidarité familiale. | CH47: 2025-86
A48: 25.10.00 | B48: M | C48: 46041.648 | D48: D0007 | E48: Congés/Absence | F48: S0072 | G48: Congé pour raisons de famille | H48: E0500 | I48: Congé de solidarité familiale | J48: Le Type de congé/absence est 'Congé de solidarité familiale' | K48: A_COA_TYCOAB [Saisi] = 'CG103' | L48: T1208 | M48: Congé de solidarité familiale - Fin | N48: Modification | O48: La valeur de l'Etat du congé saisie est égale à celle avant saisie | P48: A_COA_ETCOMA [Saisi] = A_COA_ETCOMA [Valeur avant saisie] | Q48: Ouvrier d'état | R48: P0005 | S48: Général | T48: Passant | U48: 45931 | W48: CDI_I_062 ET CDI_I_064 ET CDI_I_065 ET CDI_I_005 ET CDI_D_121 ET CDI_D_521 ET CDI_D_122 ET CDI_D_123 ET CDI_D_601 ET ABS_C_003 ET ABS_C_004 ET ABS_C_005 ET ABS_C_006 ET ABS_C_007 ET ABS_C_008 ET ABS_C_009 ET ABS_C_023 ET ABS_C_026 ET ABS_C_065 | X48: CDI_I_062 | Y48: =VLOOKUP(X48,'Axe 2 Règles de gestion'!$D$2:$F$564,3, FALSE) -> L'agent bénéficie des dispositions applicables aux agents titulaires pour le congé de solidarité familiale, sauf dispositions particulières. | Z48: CDI_I_064 | AA48: =VLOOKUP(Z48,'Axe 2 Règles de gestion'!$D$2:$F$564,3, FALSE) -> Si son ancien emploi ne peut lui être proposé, l'agent est affecté dans un emploi équivalent, le plus proche de son dernier lieu de travail. | AB48: CDI_I_065 | AC48: =VLOOKUP(AB48,'Axe 2 Règles de gestion'!$D$2:$F$564,3, FALSE) -> Si l'agent effectue une demande, il peut également être affecté dans un emploi plus proche de son domicile. | AD48: CDI_I_005 | AE48: =VLOOKUP(AD48,'Axe 2 Règles de gestion'!$D$2:$F$564,3, FALSE) -> Le congé prend fin à l'issue de la période de 3 mois ou dans les 3 jours suivant le décès de la personnes accompagnée ou à la demande de l'agent. | AT48: CDI_D_121 | AU48: =VLOOKUP(AT48,'Axe 2 Règles de gestion'!$D$2:$F$564,3, FALSE) -> Le congé de solidarité familiale, ou son renouvellement, est accordé pour une durée réelle maximale de trois mois. | AV48: CDI_D_521 | AW48: =VLOOKUP(AV48,'Axe 2 Règles de gestion'!$D$2:$F$564,3, FALSE) -> Le congé de solidarité familiale, ou son renouvellement, est accordé pour une durée prévisionnelle maximale de trois mois. | AX48: CDI_D_122 | AY48: =VLOOKUP(AX48,'Axe 2 Règles de gestion'!$D$2:$F$564,3, FALSE) -> Le congé de solidarité familiale peut être fractionné mais ne peut, renouvellement inclus, excéder les 6 mois. | AZ48: CDI_D_123 | BA48: =VLOOKUP(AZ48,'Axe 2 Règles de gestion'!$D$2:$F$564,3, FALSE) -> Le congé de solidarité familiale peut être fractionné mais chaque période doit être d'une durée réelle minimale de 7 jours consécutifs. | BB48: CDI_D_601 | BC48: =VLOOKUP(BB48,'Axe 2 Règles de gestion'!$D$2:$F$564,3, FALSE) -> Le congé de solidarité familiale peut être fractionné mais chaque période doit être d'une durée prévisionnelle minimale de 7 jours consécutifs. | BF48: ABS_C_003 | BG48: =VLOOKUP(BF48,'Axe 2 Règles de gestion'!$D$2:$F$564,3, FALSE) -> La date de début du congé/absence doit être antérieure ou égale à la date de fin réelle du congé/absence. | BH48: ABS_C_004 | BI48: =VLOOKUP(BH48,'Axe 2 Règles de gestion'!$D$2:$F$564,3, FALSE) -> La date de début du congé/absence doit être antérieure ou égale à la date de fin prévisionnelle du congé/absence. | BJ48: ABS_C_005 | BK48: =VLOOKUP(BJ48,'Axe 2 Règles de gestion'!$D$2:$F$564,3, FALSE) -> La date de fin réelle du congé/absence doit être antérieure ou égale à la date limite de fin réelle ou prévisionnelle du lien juridique. | BL48: ABS_C_006 | BM48: =VLOOKUP(BL48,'Axe 2 Règles de gestion'!$D$2:$F$564,3, FALSE) -> La date de fin prévisionnelle du congé/absence doit être antérieure ou égale à la date limite de fin réelle ou prévisionnelle du lien juridique. | BN48: ABS_C_007 | BO48: =VLOOKUP(BN48,'Axe 2 Règles de gestion'!$D$2:$F$564,3, FALSE) -> La date de fin réelle du congé/absence doit être antérieure à la date limite de départ à la retraite. | BP48: ABS_C_008 | BQ48: =VLOOKUP(BP48,'Axe 2 Règles de gestion'!$D$2:$F$564,3, FALSE) -> La date de fin prévisionnelle du congé/absence doit être antérieure à la date limite de départ à la retraite. | BR48: ABS_C_009 | BS48: =VLOOKUP(BR48,'Axe 2 Règles de gestion'!$D$2:$F$564,3, FALSE) -> La date de fin réelle ou la date de fin prévisionnelle du congé/absence doit être saisie. | BT48: ABS_C_023 | BU48: =VLOOKUP(BT48,'Axe 2 Règles de gestion'!$D$2:$F$564,3, FALSE) -> L'état du congé est renseigné. | BV48: ABS_C_026 | BW48: =VLOOKUP(BV48,'Axe 2 Règles de gestion'!$D$2:$F$564,3, FALSE) -> Dans le cas d'un congé autre que CLM, CLD, CGM et CITIS, l'indicateur de requalification doit être à non et les impacts spécifiques à la requalification ne doivent pas être mobilisés ou l'impact rémunération est vide. | BX48: ABS_C_065 | BY48: =VLOOKUP(BX48,'Axe 2 Règles de gestion'!$D$2:$F$564,3, FALSE) -> L'agent en congé de présence parentale / congé de proche aidant / congé de solidarité familiale ne peut se voir accorder de manière simultanée un temps partiel pour congé de présence parentale / pour congé de proche aidant / pour congé de solidarité familiale. | CH48: 2025-86
A49: 21.10.00 | B49: M | C49: 44469.665 | D49: D0007 | E49: Congés/Absence | F49: S0072 | G49: Congé pour raisons de famille | H49: E0500 | I49: Congé de solidarité familiale | J49: Le Type de congé/absence est 'Congé de solidarité familiale' | K49: A_COA_TYCOAB [Saisi] = 'CG103' | L49: T1206 | M49: Congé de solidarité familiale - Demande | N49: Création Modification | O49: La valeur de l'Etat du congé est différente de 'Renouvellement' et la valeur de l'Etat du congé saisie est différente de celle avant saisie | P49: A_COA_ETCOMA [Saisi] <> 'EC02' ET A_COA_ETCOMA [Saisi] <> A_COA_ETCOMA [Valeur avant saisie] | Q49: Magistrat de l'ordre judiciaire | R49: P0007 | S49: Particulier | T49: Passant | U49: 40725 | W49: CDI_I_016 ET CDI_I_017 ET CDI_I_018 ET CDI_I_019 ET CDI_D_177 ET CDI_D_577 ET CDI_D_179 ET CDI_D_613 ET CDI_D_605 ET CDI_D_173 ET ABS_C_001 ET ABS_C_003 ET ABS_C_004 ET ABS_C_007 ET ABS_C_008 ET ABS_C_009 ET ABS_C_019 ET ABS_C_020 ET ABS_C_023 ET ABS_C_026 ET ABS_C_065 | X49: CDI_I_016 | Y49: =VLOOKUP(X49,'Axe 2 Règles de gestion'!$D$2:$F$564,3, FALSE) -> Le congé est accordé si un ascendant, descendant, un frère ou une sœur, une personne partageant le même domicile ou l'ayant désigné comme sa personne de confiance souffre d'une pathologie mettant en jeu le pronostic vital ou en phase avancée ou terminale d'une affection grave et incurable, quelle qu'en soit la cause. | Z49: CDI_I_017 | AA49: =VLOOKUP(Z49,'Axe 2 Règles de gestion'!$D$2:$F$564,3, FALSE) -> L'agent doit faire la demande par écrit. Elle est accordée de droit. | AB49: CDI_I_018 | AC49: =VLOOKUP(AB49,'Axe 2 Règles de gestion'!$D$2:$F$564,3, FALSE) -> La demande doit être appuyée d'un certificat médical attestant que la personne accompagnée souffre d'une pathologie mettant en jeu le pronostic vital ou en phase avancée ou terminale d'une affection grave et incurable, quelle qu'en soit la cause. | AD49: CDI_I_019 | AE49: =VLOOKUP(AD49,'Axe 2 Règles de gestion'!$D$2:$F$564,3, FALSE) -> Le congé peut être fractionné ou pris de manière continue. | AT49: CDI_D_177 | AU49: =VLOOKUP(AT49,'Axe 2 Règles de gestion'!$D$2:$F$564,3, FALSE) -> Le congé de solidarité familiale, ou son renouvellement, est accordé pour une durée réelle maximale de trois mois. | AV49: CDI_D_577 | AW49: =VLOOKUP(AV49,'Axe 2 Règles de gestion'!$D$2:$F$564,3, FALSE) -> Le congé de solidarité familiale, ou son renouvellement, est accordé pour une durée prévisionnelle maximale de trois mois. | AX49: CDI_D_179 | AY49: =VLOOKUP(AX49,'Axe 2 Règles de gestion'!$D$2:$F$564,3, FALSE) -> Le congé de solidarité familiale peut être fractionné mais ne peut, renouvellement inclus, excéder les 6 mois. | AZ49: CDI_D_613 | BA49: =VLOOKUP(AZ49,'Axe 2 Règles de gestion'!$D$2:$F$564,3, FALSE) -> Le congé de solidarité familiale peut être fractionné mais chaque période doit être d'une durée réelle minimale de 7 jours consécutifs. | BB49: CDI_D_605 | BC49: =VLOOKUP(BB49,'Axe 2 Règles de gestion'!$D$2:$F$564,3, FALSE) -> Le congé de solidarité familiale peut être fractionné mais chaque période doit être d'une durée prévisionnelle minimale de 7 jours consécutifs. | BD49: CDI_D_173 | BE49: =VLOOKUP(BD49,'Axe 2 Règles de gestion'!$D$2:$F$564,3, FALSE) -> L'agent doit être en activité. | BF49: ABS_C_001 | BG49: =VLOOKUP(BF49,'Axe 2 Règles de gestion'!$D$2:$F$564,3, FALSE) -> La date de début du congé/absence doit être postérieure ou égale à la date de recrutement dans la FPE ou dans la carrière militaire. | BH49: ABS_C_003 | BI49: =VLOOKUP(BH49,'Axe 2 Règles de gestion'!$D$2:$F$564,3, FALSE) -> La date de début du congé/absence doit être antérieure ou égale à la date de fin réelle du congé/absence. | BJ49: ABS_C_004 | BK49: =VLOOKUP(BJ49,'Axe 2 Règles de gestion'!$D$2:$F$564,3, FALSE) -> La date de début du congé/absence doit être antérieure ou égale à la date de fin prévisionnelle du congé/absence. | BL49: ABS_C_007 | BM49: =VLOOKUP(BL49,'Axe 2 Règles de gestion'!$D$2:$F$564,3, FALSE) -> La date de fin réelle du congé/absence doit être antérieure à la date limite de départ à la retraite. | BN49: ABS_C_008 | BO49: =VLOOKUP(BN49,'Axe 2 Règles de gestion'!$D$2:$F$564,3, FALSE) -> La date de fin prévisionnelle du congé/absence doit être antérieure à la date limite de départ à la retraite. | BP49: ABS_C_009 | BQ49: =VLOOKUP(BP49,'Axe 2 Règles de gestion'!$D$2:$F$564,3, FALSE) -> La date de fin réelle ou la date de fin prévisionnelle du congé/absence doit être saisie. | BR49: ABS_C_019 | BS49: =VLOOKUP(BR49,'Axe 2 Règles de gestion'!$D$2:$F$564,3, FALSE) -> Si l'absence ne commence pas par une demi-journée et si l'absence précédente ne finit pas par une demi journée, la date de début de l'absence saisie est postérieure à la date de fin réelle de l'absence précédente. | BT49: ABS_C_020 | BU49: =VLOOKUP(BT49,'Axe 2 Règles de gestion'!$D$2:$F$564,3, FALSE) -> Si l'absence ne commence pas par une demi-journée et si l'absence précédente ne finit pas par une demi journée, la date de début de l'absence saisie est postérieure à la date de fin prévisionnelle de l'absence précédente. | BV49: ABS_C_023 | BW49: =VLOOKUP(BV49,'Axe 2 Règles de gestion'!$D$2:$F$564,3, FALSE) -> L'état du congé est renseigné. | BX49: ABS_C_026 | BY49: =VLOOKUP(BX49,'Axe 2 Règles de gestion'!$D$2:$F$564,3, FALSE) -> Dans le cas d'un congé autre que CLM, CLD, CGM et CITIS, l'indicateur de requalification doit être à non et les impacts spécifiques à la requalification ne doivent pas être mobilisés ou l'impact rémunération est vide. | BZ49: ABS_C_065 | CA49: =VLOOKUP(BZ49,'Axe 2 Règles de gestion'!$D$2:$F$564,3, FALSE) -> L'agent en congé de présence parentale / congé de proche aidant / congé de solidarité familiale ne peut se voir accorder de manière simultanée un temps partiel pour congé de présence parentale / pour congé de proche aidant / pour congé de solidarité familiale.
A50: 21.10.00 | B50: M | C50: 44469.665 | D50: D0007 | E50: Congés/Absence | F50: S0072 | G50: Congé pour raisons de famille | H50: E0500 | I50: Congé de solidarité familiale | J50: Le Type de congé/absence est 'Congé de solidarité familiale' | K50: A_COA_TYCOAB [Saisi] = 'CG103' | L50: T1207 | M50: Congé de solidarité familiale - Renouvellement | N50: Création Modification | O50: La valeur de l'Etat du congé est égale à 'Renouvellement' et la valeur de l'Etat du congé saisie est différente de celle avant saisie | P50: A_COA_ETCOMA [Saisi] = 'EC02' ET A_COA_ETCOMA [Saisi] <> A_COA_ETCOMA [Valeur avant saisie] | Q50: Magistrat de l'ordre judiciaire | R50: P0007 | S50: Particulier | T50: Passant | U50: 40725 | W50: CDI_I_016 ET CDI_I_017 ET CDI_I_018 ET CDI_I_019 ET CDI_D_177 ET CDI_D_577 ET CDI_D_179 ET CDI_D_613 ET CDI_D_605 ET CDI_D_173 ET ABS_C_001 ET ABS_C_003 ET ABS_C_004 ET ABS_C_007 ET ABS_C_008 ET ABS_C_009 ET ABS_C_019 ET ABS_C_020 ET ABS_C_023 ET ABS_C_026 ET ABS_C_065 | X50: CDI_I_016 | Y50: =VLOOKUP(X50,'Axe 2 Règles de gestion'!$D$2:$F$564,3, FALSE) -> Le congé est accordé si un ascendant, descendant, un frère ou une sœur, une personne partageant le même domicile ou l'ayant désigné comme sa personne de confiance souffre d'une pathologie mettant en jeu le pronostic vital ou en phase avancée ou terminale d'une affection grave et incurable, quelle qu'en soit la cause. | Z50: CDI_I_017 | AA50: =VLOOKUP(Z50,'Axe 2 Règles de gestion'!$D$2:$F$564,3, FALSE) -> L'agent doit faire la demande par écrit. Elle est accordée de droit. | AB50: CDI_I_018 | AC50: =VLOOKUP(AB50,'Axe 2 Règles de gestion'!$D$2:$F$564,3, FALSE) -> La demande doit être appuyée d'un certificat médical attestant que la personne accompagnée souffre d'une pathologie mettant en jeu le pronostic vital ou en phase avancée ou terminale d'une affection grave et incurable, quelle qu'en soit la cause. | AD50: CDI_I_019 | AE50: =VLOOKUP(AD50,'Axe 2 Règles de gestion'!$D$2:$F$564,3, FALSE) -> Le congé peut être fractionné ou pris de manière continue. | AT50: CDI_D_177 | AU50: =VLOOKUP(AT50,'Axe 2 Règles de gestion'!$D$2:$F$564,3, FALSE) -> Le congé de solidarité familiale, ou son renouvellement, est accordé pour une durée réelle maximale de trois mois. | AV50: CDI_D_577 | AW50: =VLOOKUP(AV50,'Axe 2 Règles de gestion'!$D$2:$F$564,3, FALSE) -> Le congé de solidarité familiale, ou son renouvellement, est accordé pour une durée prévisionnelle maximale de trois mois. | AX50: CDI_D_179 | AY50: =VLOOKUP(AX50,'Axe 2 Règles de gestion'!$D$2:$F$564,3, FALSE) -> Le congé de solidarité familiale peut être fractionné mais ne peut, renouvellement inclus, excéder les 6 mois. | AZ50: CDI_D_613 | BA50: =VLOOKUP(AZ50,'Axe 2 Règles de gestion'!$D$2:$F$564,3, FALSE) -> Le congé de solidarité familiale peut être fractionné mais chaque période doit être d'une durée réelle minimale de 7 jours consécutifs. | BB50: CDI_D_605 | BC50: =VLOOKUP(BB50,'Axe 2 Règles de gestion'!$D$2:$F$564,3, FALSE) -> Le congé de solidarité familiale peut être fractionné mais chaque période doit être d'une durée prévisionnelle minimale de 7 jours consécutifs. | BD50: CDI_D_173 | BE50: =VLOOKUP(BD50,'Axe 2 Règles de gestion'!$D$2:$F$564,3, FALSE) -> L'agent doit être en activité. | BF50: ABS_C_001 | BG50: =VLOOKUP(BF50,'Axe 2 Règles de gestion'!$D$2:$F$564,3, FALSE) -> La date de début du congé/absence doit être postérieure ou égale à la date de recrutement dans la FPE ou dans la carrière militaire. | BH50: ABS_C_003 | BI50: =VLOOKUP(BH50,'Axe 2 Règles de gestion'!$D$2:$F$564,3, FALSE) -> La date de début du congé/absence doit être antérieure ou égale à la date de fin réelle du congé/absence. | BJ50: ABS_C_004 | BK50: =VLOOKUP(BJ50,'Axe 2 Règles de gestion'!$D$2:$F$564,3, FALSE) -> La date de début du congé/absence doit être antérieure ou égale à la date de fin prévisionnelle du congé/absence. | BL50: ABS_C_007 | BM50: =VLOOKUP(BL50,'Axe 2 Règles de gestion'!$D$2:$F$564,3, FALSE) -> La date de fin réelle du congé/absence doit être antérieure à la date limite de départ à la retraite. | BN50: ABS_C_008 | BO50: =VLOOKUP(BN50,'Axe 2 Règles de gestion'!$D$2:$F$564,3, FALSE) -> La date de fin prévisionnelle du congé/absence doit être antérieure à la date limite de départ à la retraite. | BP50: ABS_C_009 | BQ50: =VLOOKUP(BP50,'Axe 2 Règles de gestion'!$D$2:$F$564,3, FALSE) -> La date de fin réelle ou la date de fin prévisionnelle du congé/absence doit être saisie. | BR50: ABS_C_019 | BS50: =VLOOKUP(BR50,'Axe 2 Règles de gestion'!$D$2:$F$564,3, FALSE) -> Si l'absence ne commence pas par une demi-journée et si l'absence précédente ne finit pas par une demi journée, la date de début de l'absence saisie est postérieure à la date de fin réelle de l'absence précédente. | BT50: ABS_C_020 | BU50: =VLOOKUP(BT50,'Axe 2 Règles de gestion'!$D$2:$F$564,3, FALSE) -> Si l'absence ne commence pas par une demi-journée et si l'absence précédente ne finit pas par une demi journée, la date de début de l'absence saisie est postérieure à la date de fin prévisionnelle de l'absence précédente. | BV50: ABS_C_023 | BW50: =VLOOKUP(BV50,'Axe 2 Règles de gestion'!$D$2:$F$564,3, FALSE) -> L'état du congé est renseigné. | BX50: ABS_C_026 | BY50: =VLOOKUP(BX50,'Axe 2 Règles de gestion'!$D$2:$F$564,3, FALSE) -> Dans le cas d'un congé autre que CLM, CLD, CGM et CITIS, l'indicateur de requalification doit être à non et les impacts spécifiques à la requalification ne doivent pas être mobilisés ou l'impact rémunération est vide. | BZ50: ABS_C_065 | CA50: =VLOOKUP(BZ50,'Axe 2 Règles de gestion'!$D$2:$F$564,3, FALSE) -> L'agent en congé de présence parentale / congé de proche aidant / congé de solidarité familiale ne peut se voir accorder de manière simultanée un temps partiel pour congé de présence parentale / pour congé de proche aidant / pour congé de solidarité familiale.
A51: 21.10.00 | B51: M | C51: 44469.665 | D51: D0007 | E51: Congés/Absence | F51: S0072 | G51: Congé pour raisons de famille | H51: E0500 | I51: Congé de solidarité familiale | J51: Le Type de congé/absence est 'Congé de solidarité familiale' | K51: A_COA_TYCOAB [Saisi] = 'CG103' | L51: T1208 | M51: Congé de solidarité familiale - Fin | N51: Modification | O51: La valeur de l'Etat du congé saisie est égale à celle avant saisie | P51: A_COA_ETCOMA [Saisi] = A_COA_ETCOMA [Valeur avant saisie] | Q51: Magistrat de l'ordre judiciaire | R51: P0007 | S51: Particulier | T51: Passant | U51: 40725 | W51: CDI_I_020 ET CDI_D_177 ET CDI_D_577 ET CDI_D_179 ET CDI_D_613 ET CDI_D_605 ET ABS_C_003 ET ABS_C_004 ET ABS_C_007 ET ABS_C_008 ET ABS_C_009 ET ABS_C_023 ET ABS_C_026 ET ABS_C_065 | X51: CDI_I_020 | Y51: =VLOOKUP(X51,'Axe 2 Règles de gestion'!$D$2:$F$564,3, FALSE) -> Le congé prend fin à l'issue de la période de 3 mois ou dans les 3 jours suivant le décès de la personnes accompagnée ou à la demande de l'agent. | AT51: CDI_D_177 | AU51: =VLOOKUP(AT51,'Axe 2 Règles de gestion'!$D$2:$F$564,3, FALSE) -> Le congé de solidarité familiale, ou son renouvellement, est accordé pour une durée réelle maximale de trois mois. | AV51: CDI_D_577 | AW51: =VLOOKUP(AV51,'Axe 2 Règles de gestion'!$D$2:$F$564,3, FALSE) -> Le congé de solidarité familiale, ou son renouvellement, est accordé pour une durée prévisionnelle maximale de trois mois. | AX51: CDI_D_179 | AY51: =VLOOKUP(AX51,'Axe 2 Règles de gestion'!$D$2:$F$564,3, FALSE) -> Le congé de solidarité familiale peut être fractionné mais ne peut, renouvellement inclus, excéder les 6 mois. | AZ51: CDI_D_613 | BA51: =VLOOKUP(AZ51,'Axe 2 Règles de gestion'!$D$2:$F$564,3, FALSE) -> Le congé de solidarité familiale peut être fractionné mais chaque période doit être d'une durée réelle minimale de 7 jours consécutifs. | BB51: CDI_D_605 | BC51: =VLOOKUP(BB51,'Axe 2 Règles de gestion'!$D$2:$F$564,3, FALSE) -> Le congé de solidarité familiale peut être fractionné mais chaque période doit être d'une durée prévisionnelle minimale de 7 jours consécutifs. | BF51: ABS_C_003 | BG51: =VLOOKUP(BF51,'Axe 2 Règles de gestion'!$D$2:$F$564,3, FALSE) -> La date de début du congé/absence doit être antérieure ou égale à la date de fin réelle du congé/absence. | BH51: ABS_C_004 | BI51: =VLOOKUP(BH51,'Axe 2 Règles de gestion'!$D$2:$F$564,3, FALSE) -> La date de début du congé/absence doit être antérieure ou égale à la date de fin prévisionnelle du congé/absence. | BJ51: ABS_C_007 | BK51: =VLOOKUP(BJ51,'Axe 2 Règles de gestion'!$D$2:$F$564,3, FALSE) -> La date de fin réelle du congé/absence doit être antérieure à la date limite de départ à la retraite. | BL51: ABS_C_008 | BM51: =VLOOKUP(BL51,'Axe 2 Règles de gestion'!$D$2:$F$564,3, FALSE) -> La date de fin prévisionnelle du congé/absence doit être antérieure à la date limite de départ à la retraite. | BN51: ABS_C_009 | BO51: =VLOOKUP(BN51,'Axe 2 Règles de gestion'!$D$2:$F$564,3, FALSE) -> La date de fin réelle ou la date de fin prévisionnelle du congé/absence doit être saisie. | BP51: ABS_C_023 | BQ51: =VLOOKUP(BP51,'Axe 2 Règles de gestion'!$D$2:$F$564,3, FALSE) -> L'état du congé est renseigné. | BR51: ABS_C_026 | BS51: =VLOOKUP(BR51,'Axe 2 Règles de gestion'!$D$2:$F$564,3, FALSE) -> Dans le cas d'un congé autre que CLM, CLD, CGM et CITIS, l'indicateur de requalification doit être à non et les impacts spécifiques à la requalification ne doivent pas être mobilisés ou l'impact rémunération est vide. | BT51: ABS_C_065 | BU51: =VLOOKUP(BT51,'Axe 2 Règles de gestion'!$D$2:$F$564,3, FALSE) -> L'agent en congé de présence parentale / congé de proche aidant / congé de solidarité familiale ne peut se voir accorder de manière simultanée un temps partiel pour congé de présence parentale / pour congé de proche aidant / pour congé de solidarité familiale.
A52: 25.10.00 | B52: M | C52: 45993.392 | D52: D0007 | E52: Congés/Absence | F52: S0072 | G52: Congé pour raisons de famille | H52: E0500 | I52: Congé de solidarité familiale | J52: Le Type de congé/absence est 'Congé de solidarité familiale' | K52: A_COA_TYCOAB [Saisi] = 'CG103' | L52: T1206 | M52: Congé de solidarité familiale - Demande | N52: Création Modification | O52: La valeur de l'Etat du congé est différente de 'Renouvellement' et la valeur de l'Etat du congé saisie est différente de celle avant saisie | P52: A_COA_ETCOMA [Saisi] <> 'EC02' ET A_COA_ETCOMA [Saisi] <> A_COA_ETCOMA [Valeur avant saisie] | Q52: Auditeur de justice | R52: P0009 | S52: Particulier | T52: Passant | U52: 40725 | W52: CDI_I_101 ET CDI_I_001 ET CDI_I_002 ET CDI_I_003 ET CDI_I_004 ET CDI_D_121 ET CDI_D_521 ET CDI_D_122 ET CDI_D_123 ET CDI_D_601 ET CDI_D_117 ET ABS_C_001 ET ABS_C_003 ET ABS_C_004 ET ABS_C_007 ET ABS_C_008 ET ABS_C_009 ET ABS_C_019 ET ABS_C_020 ET ABS_C_023 ET ABS_C_026 ET ABS_C_065 | X52: CDI_I_101 | Y52: =VLOOKUP(X52,'Axe 2 Règles de gestion'!$D$2:$F$564,3, FALSE) -> L'agent bénéficie des dispositions applicables aux agents titulaires pour le congé de solidarité familiale, sauf dispositions particulières. | Z52: CDI_I_001 | AA52: =VLOOKUP(Z52,'Axe 2 Règles de gestion'!$D$2:$F$564,3, FALSE) -> Le congé est accordé si un ascendant, descendant, un frère ou une sœur, une personne partageant le même domicile ou l'ayant désigné comme sa personne de confiance souffre d'une pathologie mettant en jeu le pronostic vital ou en phase avancée ou terminale d'une affection grave et incurable, quelle qu'en soit la cause. | AB52: CDI_I_002 | AC52: =VLOOKUP(AB52,'Axe 2 Règles de gestion'!$D$2:$F$564,3, FALSE) -> L'agent doit faire la demande par écrit. Elle est accordée de droit. | AD52: CDI_I_003 | AE52: =VLOOKUP(AD52,'Axe 2 Règles de gestion'!$D$2:$F$564,3, FALSE) -> La demande doit être appuyée d'un certificat médical attestant que la personne accompagnée souffre d'une pathologie mettant en jeu le pronostic vital ou en phase avancée ou terminale d'une affection grave et incurable, quelle qu'en soit la cause. | AF52: CDI_I_004 | AG52: =VLOOKUP(AF52,'Axe 2 Règles de gestion'!$D$2:$F$564,3, FALSE) -> Le congé peut être fractionné ou pris de manière continue. | AT52: CDI_D_121 | AU52: =VLOOKUP(AT52,'Axe 2 Règles de gestion'!$D$2:$F$564,3, FALSE) -> Le congé de solidarité familiale, ou son renouvellement, est accordé pour une durée réelle maximale de trois mois. | AV52: CDI_D_521 | AW52: =VLOOKUP(AV52,'Axe 2 Règles de gestion'!$D$2:$F$564,3, FALSE) -> Le congé de solidarité familiale, ou son renouvellement, est accordé pour une durée prévisionnelle maximale de trois mois. | AX52: CDI_D_122 | AY52: =VLOOKUP(AX52,'Axe 2 Règles de gestion'!$D$2:$F$564,3, FALSE) -> Le congé de solidarité familiale peut être fractionné mais ne peut, renouvellement inclus, excéder les 6 mois. | AZ52: CDI_D_123 | BA52: =VLOOKUP(AZ52,'Axe 2 Règles de gestion'!$D$2:$F$564,3, FALSE) -> Le congé de solidarité familiale peut être fractionné mais chaque période doit être d'une durée réelle minimale de 7 jours consécutifs. | BB52: CDI_D_601 | BC52: =VLOOKUP(BB52,'Axe 2 Règles de gestion'!$D$2:$F$564,3, FALSE) -> Le congé de solidarité familiale peut être fractionné mais chaque période doit être d'une durée prévisionnelle minimale de 7 jours consécutifs. | BD52: CDI_D_117 | BE52: =VLOOKUP(BD52,'Axe 2 Règles de gestion'!$D$2:$F$564,3, FALSE) -> L'agent doit être en activité. | BF52: ABS_C_001 | BG52: =VLOOKUP(BF52,'Axe 2 Règles de gestion'!$D$2:$F$564,3, FALSE) -> La date de début du congé/absence doit être postérieure ou égale à la date de recrutement dans la FPE ou dans la carrière militaire. | BH52: ABS_C_003 | BI52: =VLOOKUP(BH52,'Axe 2 Règles de gestion'!$D$2:$F$564,3, FALSE) -> La date de début du congé/absence doit être antérieure ou égale à la date de fin réelle du congé/absence. | BJ52: ABS_C_004 | BK52: =VLOOKUP(BJ52,'Axe 2 Règles de gestion'!$D$2:$F$564,3, FALSE) -> La date de début du congé/absence doit être antérieure ou égale à la date de fin prévisionnelle du congé/absence. | BL52: ABS_C_007 | BM52: =VLOOKUP(BL52,'Axe 2 Règles de gestion'!$D$2:$F$564,3, FALSE) -> La date de fin réelle du congé/absence doit être antérieure à la date limite de départ à la retraite. | BN52: ABS_C_008 | BO52: =VLOOKUP(BN52,'Axe 2 Règles de gestion'!$D$2:$F$564,3, FALSE) -> La date de fin prévisionnelle du congé/absence doit être antérieure à la date limite de départ à la retraite. | BP52: ABS_C_009 | BQ52: =VLOOKUP(BP52,'Axe 2 Règles de gestion'!$D$2:$F$564,3, FALSE) -> La date de fin réelle ou la date de fin prévisionnelle du congé/absence doit être saisie. | BR52: ABS_C_019 | BS52: =VLOOKUP(BR52,'Axe 2 Règles de gestion'!$D$2:$F$564,3, FALSE) -> Si l'absence ne commence pas par une demi-journée et si l'absence précédente ne finit pas par une demi journée, la date de début de l'absence saisie est postérieure à la date de fin réelle de l'absence précédente. | BT52: ABS_C_020 | BU52: =VLOOKUP(BT52,'Axe 2 Règles de gestion'!$D$2:$F$564,3, FALSE) -> Si l'absence ne commence pas par une demi-journée et si l'absence précédente ne finit pas par une demi journée, la date de début de l'absence saisie est postérieure à la date de fin prévisionnelle de l'absence précédente. | BV52: ABS_C_023 | BW52: =VLOOKUP(BV52,'Axe 2 Règles de gestion'!$D$2:$F$564,3, FALSE) -> L'état du congé est renseigné. | BX52: ABS_C_026 | BY52: =VLOOKUP(BX52,'Axe 2 Règles de gestion'!$D$2:$F$564,3, FALSE) -> Dans le cas d'un congé autre que CLM, CLD, CGM et CITIS, l'indicateur de requalification doit être à non et les impacts spécifiques à la requalification ne doivent pas être mobilisés ou l'impact rémunération est vide. | BZ52: ABS_C_065 | CA52: =VLOOKUP(BZ52,'Axe 2 Règles de gestion'!$D$2:$F$564,3, FALSE) -> L'agent en congé de présence parentale / congé de proche aidant / congé de solidarité familiale ne peut se voir accorder de manière simultanée un temps partiel pour congé de présence parentale / pour congé de proche aidant / pour congé de solidarité familiale. | CH52: 2025-118
A53: 25.10.00 | B53: M | C53: 45993.393 | D53: D0007 | E53: Congés/Absence | F53: S0072 | G53: Congé pour raisons de famille | H53: E0500 | I53: Congé de solidarité familiale | J53: Le Type de congé/absence est 'Congé de solidarité familiale' | K53: A_COA_TYCOAB [Saisi] = 'CG103' | L53: T1207 | M53: Congé de solidarité familiale - Renouvellement | N53: Création Modification | O53: La valeur de l'Etat du congé est égale à 'Renouvellement' et la valeur de l'Etat du congé saisie est différente de celle avant saisie | P53: A_COA_ETCOMA [Saisi] = 'EC02' ET A_COA_ETCOMA [Saisi] <> A_COA_ETCOMA [Valeur avant saisie] | Q53: Auditeur de justice | R53: P0009 | S53: Particulier | T53: Passant | U53: 40725 | W53: CDI_I_101 ET CDI_I_002 ET CDI_I_003 ET CDI_I_004 ET CDI_D_121 ET CDI_D_521 ET CDI_D_122 ET CDI_D_123 ET CDI_D_601 ET CDI_D_117 ET ABS_C_001 ET ABS_C_003 ET ABS_C_004 ET ABS_C_007 ET ABS_C_008 ET ABS_C_009 ET ABS_C_019 ET ABS_C_020 ET ABS_C_023 ET ABS_C_026 ET ABS_C_065 | X53: CDI_I_101 | Y53: =VLOOKUP(X53,'Axe 2 Règles de gestion'!$D$2:$F$564,3, FALSE) -> L'agent bénéficie des dispositions applicables aux agents titulaires pour le congé de solidarité familiale, sauf dispositions particulières. | Z53: CDI_I_002 | AA53: =VLOOKUP(Z53,'Axe 2 Règles de gestion'!$D$2:$F$564,3, FALSE) -> L'agent doit faire la demande par écrit. Elle est accordée de droit. | AB53: CDI_I_003 | AC53: =VLOOKUP(AB53,'Axe 2 Règles de gestion'!$D$2:$F$564,3, FALSE) -> La demande doit être appuyée d'un certificat médical attestant que la personne accompagnée souffre d'une pathologie mettant en jeu le pronostic vital ou en phase avancée ou terminale d'une affection grave et incurable, quelle qu'en soit la cause. | AD53: CDI_I_004 | AE53: =VLOOKUP(AD53,'Axe 2 Règles de gestion'!$D$2:$F$564,3, FALSE) -> Le congé peut être fractionné ou pris de manière continue. | AT53: CDI_D_121 | AU53: =VLOOKUP(AT53,'Axe 2 Règles de gestion'!$D$2:$F$564,3, FALSE) -> Le congé de solidarité familiale, ou son renouvellement, est accordé pour une durée réelle maximale de trois mois. | AV53: CDI_D_521 | AW53: =VLOOKUP(AV53,'Axe 2 Règles de gestion'!$D$2:$F$564,3, FALSE) -> Le congé de solidarité familiale, ou son renouvellement, est accordé pour une durée prévisionnelle maximale de trois mois. | AX53: CDI_D_122 | AY53: =VLOOKUP(AX53,'Axe 2 Règles de gestion'!$D$2:$F$564,3, FALSE) -> Le congé de solidarité familiale peut être fractionné mais ne peut, renouvellement inclus, excéder les 6 mois. | AZ53: CDI_D_123 | BA53: =VLOOKUP(AZ53,'Axe 2 Règles de gestion'!$D$2:$F$564,3, FALSE) -> Le congé de solidarité familiale peut être fractionné mais chaque période doit être d'une durée réelle minimale de 7 jours consécutifs. | BB53: CDI_D_601 | BC53: =VLOOKUP(BB53,'Axe 2 Règles de gestion'!$D$2:$F$564,3, FALSE) -> Le congé de solidarité familiale peut être fractionné mais chaque période doit être d'une durée prévisionnelle minimale de 7 jours consécutifs. | BD53: CDI_D_117 | BE53: =VLOOKUP(BD53,'Axe 2 Règles de gestion'!$D$2:$F$564,3, FALSE) -> L'agent doit être en activité. | BF53: ABS_C_001 | BG53: =VLOOKUP(BF53,'Axe 2 Règles de gestion'!$D$2:$F$564,3, FALSE) -> La date de début du congé/absence doit être postérieure ou égale à la date de recrutement dans la FPE ou dans la carrière militaire. | BH53: ABS_C_003 | BI53: =VLOOKUP(BH53,'Axe 2 Règles de gestion'!$D$2:$F$564,3, FALSE) -> La date de début du congé/absence doit être antérieure ou égale à la date de fin réelle du congé/absence. | BJ53: ABS_C_004 | BK53: =VLOOKUP(BJ53,'Axe 2 Règles de gestion'!$D$2:$F$564,3, FALSE) -> La date de début du congé/absence doit être antérieure ou égale à la date de fin prévisionnelle du congé/absence. | BL53: ABS_C_007 | BM53: =VLOOKUP(BL53,'Axe 2 Règles de gestion'!$D$2:$F$564,3, FALSE) -> La date de fin réelle du congé/absence doit être antérieure à la date limite de départ à la retraite. | BN53: ABS_C_008 | BO53: =VLOOKUP(BN53,'Axe 2 Règles de gestion'!$D$2:$F$564,3, FALSE) -> La date de fin prévisionnelle du congé/absence doit être antérieure à la date limite de départ à la retraite. | BP53: ABS_C_009 | BQ53: =VLOOKUP(BP53,'Axe 2 Règles de gestion'!$D$2:$F$564,3, FALSE) -> La date de fin réelle ou la date de fin prévisionnelle du congé/absence doit être saisie. | BR53: ABS_C_019 | BS53: =VLOOKUP(BR53,'Axe 2 Règles de gestion'!$D$2:$F$564,3, FALSE) -> Si l'absence ne commence pas par une demi-journée et si l'absence précédente ne finit pas par une demi journée, la date de début de l'absence saisie est postérieure à la date de fin réelle de l'absence précédente. | BT53: ABS_C_020 | BU53: =VLOOKUP(BT53,'Axe 2 Règles de gestion'!$D$2:$F$564,3, FALSE) -> Si l'absence ne commence pas par une demi-journée et si l'absence précédente ne finit pas par une demi journée, la date de début de l'absence saisie est postérieure à la date de fin prévisionnelle de l'absence précédente. | BV53: ABS_C_023 | BW53: =VLOOKUP(BV53,'Axe 2 Règles de gestion'!$D$2:$F$564,3, FALSE) -> L'état du congé est renseigné. | BX53: ABS_C_026 | BY53: =VLOOKUP(BX53,'Axe 2 Règles de gestion'!$D$2:$F$564,3, FALSE) -> Dans le cas d'un congé autre que CLM, CLD, CGM et CITIS, l'indicateur de requalification doit être à non et les impacts spécifiques à la requalification ne doivent pas être mobilisés ou l'impact rémunération est vide. | BZ53: ABS_C_065 | CA53: =VLOOKUP(BZ53,'Axe 2 Règles de gestion'!$D$2:$F$564,3, FALSE) -> L'agent en congé de présence parentale / congé de proche aidant / congé de solidarité familiale ne peut se voir accorder de manière simultanée un temps partiel pour congé de présence parentale / pour congé de proche aidant / pour congé de solidarité familiale. | CH53: 2025-118
A54: 25.10.00 | B54: M | C54: 45993.393 | D54: D0007 | E54: Congés/Absence | F54: S0072 | G54: Congé pour raisons de famille | H54: E0500 | I54: Congé de solidarité familiale | J54: Le Type de congé/absence est 'Congé de solidarité familiale' | K54: A_COA_TYCOAB [Saisi] = 'CG103' | L54: T1208 | M54: Congé de solidarité familiale - Fin | N54: Modification | O54: La valeur de l'Etat du congé saisie est égale à celle avant saisie | P54: A_COA_ETCOMA [Saisi] = A_COA_ETCOMA [Valeur avant saisie] | Q54: Auditeur de justice | R54: P0009 | S54: Particulier | T54: Passant | U54: 40725 | W54: CDI_I_101 ET CDI_I_005 ET CDI_D_121 ET CDI_D_521 ET CDI_D_122 ET CDI_D_123 ET CDI_D_601 ET ABS_C_003 ET ABS_C_004 ET ABS_C_007 ET ABS_C_008 ET ABS_C_009 ET ABS_C_023 ET ABS_C_026 ET ABS_C_065 | X54: CDI_I_101 | Y54: =VLOOKUP(X54,'Axe 2 Règles de gestion'!$D$2:$F$564,3, FALSE) -> L'agent bénéficie des dispositions applicables aux agents titulaires pour le congé de solidarité familiale, sauf dispositions particulières. | Z54: CDI_I_005 | AA54: =VLOOKUP(Z54,'Axe 2 Règles de gestion'!$D$2:$F$564,3, FALSE) -> Le congé prend fin à l'issue de la période de 3 mois ou dans les 3 jours suivant le décès de la personnes accompagnée ou à la demande de l'agent. | AT54: CDI_D_121 | AU54: =VLOOKUP(AT54,'Axe 2 Règles de gestion'!$D$2:$F$564,3, FALSE) -> Le congé de solidarité familiale, ou son renouvellement, est accordé pour une durée réelle maximale de trois mois. | AV54: CDI_D_521 | AW54: =VLOOKUP(AV54,'Axe 2 Règles de gestion'!$D$2:$F$564,3, FALSE) -> Le congé de solidarité familiale, ou son renouvellement, est accordé pour une durée prévisionnelle maximale de trois mois. | AX54: CDI_D_122 | AY54: =VLOOKUP(AX54,'Axe 2 Règles de gestion'!$D$2:$F$564,3, FALSE) -> Le congé de solidarité familiale peut être fractionné mais ne peut, renouvellement inclus, excéder les 6 mois. | AZ54: CDI_D_123 | BA54: =VLOOKUP(AZ54,'Axe 2 Règles de gestion'!$D$2:$F$564,3, FALSE) -> Le congé de solidarité familiale peut être fractionné mais chaque période doit être d'une durée réelle minimale de 7 jours consécutifs. | BB54: CDI_D_601 | BC54: =VLOOKUP(BB54,'Axe 2 Règles de gestion'!$D$2:$F$564,3, FALSE) -> Le congé de solidarité familiale peut être fractionné mais chaque période doit être d'une durée prévisionnelle minimale de 7 jours consécutifs. | BF54: ABS_C_003 | BG54: =VLOOKUP(BF54,'Axe 2 Règles de gestion'!$D$2:$F$564,3, FALSE) -> La date de début du congé/absence doit être antérieure ou égale à la date de fin réelle du congé/absence. | BH54: ABS_C_004 | BI54: =VLOOKUP(BH54,'Axe 2 Règles de gestion'!$D$2:$F$564,3, FALSE) -> La date de début du congé/absence doit être antérieure ou égale à la date de fin prévisionnelle du congé/absence. | BJ54: ABS_C_007 | BK54: =VLOOKUP(BJ54,'Axe 2 Règles de gestion'!$D$2:$F$564,3, FALSE) -> La date de fin réelle du congé/absence doit être antérieure à la date limite de départ à la retraite. | BL54: ABS_C_008 | BM54: =VLOOKUP(BL54,'Axe 2 Règles de gestion'!$D$2:$F$564,3, FALSE) -> La date de fin prévisionnelle du congé/absence doit être antérieure à la date limite de départ à la retraite. | BN54: ABS_C_009 | BO54: =VLOOKUP(BN54,'Axe 2 Règles de gestion'!$D$2:$F$564,3, FALSE) -> La date de fin réelle ou la date de fin prévisionnelle du congé/absence doit être saisie. | BP54: ABS_C_023 | BQ54: =VLOOKUP(BP54,'Axe 2 Règles de gestion'!$D$2:$F$564,3, FALSE) -> L'état du congé est renseigné. | BR54: ABS_C_026 | BS54: =VLOOKUP(BR54,'Axe 2 Règles de gestion'!$D$2:$F$564,3, FALSE) -> Dans le cas d'un congé autre que CLM, CLD, CGM et CITIS, l'indicateur de requalification doit être à non et les impacts spécifiques à la requalification ne doivent pas être mobilisés ou l'impact rémunération est vide. | BT54: ABS_C_065 | BU54: =VLOOKUP(BT54,'Axe 2 Règles de gestion'!$D$2:$F$564,3, FALSE) -> L'agent en congé de présence parentale / congé de proche aidant / congé de solidarité familiale ne peut se voir accorder de manière simultanée un temps partiel pour congé de présence parentale / pour congé de proche aidant / pour congé de solidarité familiale. | CH54: 2025-118
A55: 21.10.00 | B55: M | C55: 44469.655 | D55: D0007 | E55: Congés/Absence | F55: S0072 | G55: Congé pour raisons de famille | H55: E0500 | I55: Congé de solidarité familiale | J55: Le Type de congé/absence est 'Congé de solidarité familiale' | K55: A_COA_TYCOAB [Saisi] = 'CG103' | L55: T1206 | M55: Congé de solidarité familiale - Demande | N55: Création Modification | O55: La valeur de l'Etat du congé est différente de 'Renouvellement' et la valeur de l'Etat du congé saisie est différente de celle avant saisie | P55: A_COA_ETCOMA [Saisi] <> 'EC02' ET A_COA_ETCOMA [Saisi] <> A_COA_ETCOMA [Valeur avant saisie] | Q55: Conseiller ou avocat général à la Cour de cassation en service extraordinaire | R55: P0046 | S55: Particulier | T55: Passant | U55: 40725 | W55: CDI_I_026 ET CDI_I_027 ET CDI_I_028 ET CDI_I_029 ET CDI_D_177 ET CDI_D_577 ET CDI_D_179 ET CDI_D_613 ET CDI_D_605 ET CDI_D_173 ET ABS_C_002 ET ABS_C_003 ET ABS_C_004 ET ABS_C_005 ET ABS_C_006 ET ABS_C_007 ET ABS_C_008 ET ABS_C_009 ET ABS_C_019 ET ABS_C_020 ET ABS_C_023 ET ABS_C_026 ET ABS_C_065 | X55: CDI_I_026 | Y55: =VLOOKUP(X55,'Axe 2 Règles de gestion'!$D$2:$F$564,3, FALSE) -> Le congé est accordé si un ascendant, descendant, un frère ou une sœur, une personne partageant le même domicile ou l'ayant désigné comme sa personne de confiance souffre d'une pathologie mettant en jeu le pronostic vital ou en phase avancée ou terminale d'une affection grave et incurable, quelle qu'en soit la cause. | Z55: CDI_I_027 | AA55: =VLOOKUP(Z55,'Axe 2 Règles de gestion'!$D$2:$F$564,3, FALSE) -> L'agent doit faire la demande par écrit. Elle est accordée de droit. | AB55: CDI_I_028 | AC55: =VLOOKUP(AB55,'Axe 2 Règles de gestion'!$D$2:$F$564,3, FALSE) -> La demande doit être appuyée d'un certificat médical attestant que la personne accompagnée souffre d'une pathologie mettant en jeu le pronostic vital ou en phase avancée ou terminale d'une affection grave et incurable, quelle qu'en soit la cause. | AD55: CDI_I_029 | AE55: =VLOOKUP(AD55,'Axe 2 Règles de gestion'!$D$2:$F$564,3, FALSE) -> Le congé peut être fractionné ou pris de manière continue. | AT55: CDI_D_177 | AU55: =VLOOKUP(AT55,'Axe 2 Règles de gestion'!$D$2:$F$564,3, FALSE) -> Le congé de solidarité familiale, ou son renouvellement, est accordé pour une durée réelle maximale de trois mois. | AV55: CDI_D_577 | AW55: =VLOOKUP(AV55,'Axe 2 Règles de gestion'!$D$2:$F$564,3, FALSE) -> Le congé de solidarité familiale, ou son renouvellement, est accordé pour une durée prévisionnelle maximale de trois mois. | AX55: CDI_D_179 | AY55: =VLOOKUP(AX55,'Axe 2 Règles de gestion'!$D$2:$F$564,3, FALSE) -> Le congé de solidarité familiale peut être fractionné mais ne peut, renouvellement inclus, excéder les 6 mois. | AZ55: CDI_D_613 | BA55: =VLOOKUP(AZ55,'Axe 2 Règles de gestion'!$D$2:$F$564,3, FALSE) -> Le congé de solidarité familiale peut être fractionné mais chaque période doit être d'une durée réelle minimale de 7 jours consécutifs. | BB55: CDI_D_605 | BC55: =VLOOKUP(BB55,'Axe 2 Règles de gestion'!$D$2:$F$564,3, FALSE) -> Le congé de solidarité familiale peut être fractionné mais chaque période doit être d'une durée prévisionnelle minimale de 7 jours consécutifs. | BD55: CDI_D_173 | BE55: =VLOOKUP(BD55,'Axe 2 Règles de gestion'!$D$2:$F$564,3, FALSE) -> L'agent doit être en activité. | BF55: ABS_C_002 | BG55: =VLOOKUP(BF55,'Axe 2 Règles de gestion'!$D$2:$F$564,3, FALSE) -> La date de début du congé/absence doit être postérieure ou égale à la date de début du lien juridique. | BH55: ABS_C_003 | BI55: =VLOOKUP(BH55,'Axe 2 Règles de gestion'!$D$2:$F$564,3, FALSE) -> La date de début du congé/absence doit être antérieure ou égale à la date de fin réelle du congé/absence. | BJ55: ABS_C_004 | BK55: =VLOOKUP(BJ55,'Axe 2 Règles de gestion'!$D$2:$F$564,3, FALSE) -> La date de début du congé/absence doit être antérieure ou égale à la date de fin prévisionnelle du congé/absence. | BL55: ABS_C_005 | BM55: =VLOOKUP(BL55,'Axe 2 Règles de gestion'!$D$2:$F$564,3, FALSE) -> La date de fin réelle du congé/absence doit être antérieure ou égale à la date limite de fin réelle ou prévisionnelle du lien juridique. | BN55: ABS_C_006 | BO55: =VLOOKUP(BN55,'Axe 2 Règles de gestion'!$D$2:$F$564,3, FALSE) -> La date de fin prévisionnelle du congé/absence doit être antérieure ou égale à la date limite de fin réelle ou prévisionnelle du lien juridique. | BP55: ABS_C_007 | BQ55: =VLOOKUP(BP55,'Axe 2 Règles de gestion'!$D$2:$F$564,3, FALSE) -> La date de fin réelle du congé/absence doit être antérieure à la date limite de départ à la retraite. | BR55: ABS_C_008 | BS55: =VLOOKUP(BR55,'Axe 2 Règles de gestion'!$D$2:$F$564,3, FALSE) -> La date de fin prévisionnelle du congé/absence doit être antérieure à la date limite de départ à la retraite. | BT55: ABS_C_009 | BU55: =VLOOKUP(BT55,'Axe 2 Règles de gestion'!$D$2:$F$564,3, FALSE) -> La date de fin réelle ou la date de fin prévisionnelle du congé/absence doit être saisie. | BV55: ABS_C_019 | BW55: =VLOOKUP(BV55,'Axe 2 Règles de gestion'!$D$2:$F$564,3, FALSE) -> Si l'absence ne commence pas par une demi-journée et si l'absence précédente ne finit pas par une demi journée, la date de début de l'absence saisie est postérieure à la date de fin réelle de l'absence précédente. | BX55: ABS_C_020 | BY55: =VLOOKUP(BX55,'Axe 2 Règles de gestion'!$D$2:$F$564,3, FALSE) -> Si l'absence ne commence pas par une demi-journée et si l'absence précédente ne finit pas par une demi journée, la date de début de l'absence saisie est postérieure à la date de fin prévisionnelle de l'absence précédente. | BZ55: ABS_C_023 | CA55: =VLOOKUP(BZ55,'Axe 2 Règles de gestion'!$D$2:$F$564,3, FALSE) -> L'état du congé est renseigné. | CB55: ABS_C_026 | CC55: =VLOOKUP(CB55,'Axe 2 Règles de gestion'!$D$2:$F$564,3, FALSE) -> Dans le cas d'un congé autre que CLM, CLD, CGM et CITIS, l'indicateur de requalification doit être à non et les impacts spécifiques à la requalification ne doivent pas être mobilisés ou l'impact rémunération est vide. | CD55: ABS_C_065 | CE55: =VLOOKUP(CD55,'Axe 2 Règles de gestion'!$D$2:$F$564,3, FALSE) -> L'agent en congé de présence parentale / congé de proche aidant / congé de solidarité familiale ne peut se voir accorder de manière simultanée un temps partiel pour congé de présence parentale / pour congé de proche aidant / pour congé de solidarité familiale.
A56: 21.10.00 | B56: M | C56: 44469.656 | D56: D0007 | E56: Congés/Absence | F56: S0072 | G56: Congé pour raisons de famille | H56: E0500 | I56: Congé de solidarité familiale | J56: Le Type de congé/absence est 'Congé de solidarité familiale' | K56: A_COA_TYCOAB [Saisi] = 'CG103' | L56: T1207 | M56: Congé de solidarité familiale - Renouvellement | N56: Création Modification | O56: La valeur de l'Etat du congé est égale à 'Renouvellement' et la valeur de l'Etat du congé saisie est différente de celle avant saisie | P56: A_COA_ETCOMA [Saisi] = 'EC02' ET A_COA_ETCOMA [Saisi] <> A_COA_ETCOMA [Valeur avant saisie] | Q56: Conseiller ou avocat général à la Cour de cassation en service extraordinaire | R56: P0046 | S56: Particulier | T56: Passant | U56: 40725 | W56: CDI_I_026 ET CDI_I_027 ET CDI_I_028 ET CDI_I_029 ET CDI_D_177 ET CDI_D_577 ET CDI_D_179 ET CDI_D_613 ET CDI_D_605 ET CDI_D_173 ET ABS_C_002 ET ABS_C_003 ET ABS_C_004 ET ABS_C_005 ET ABS_C_006 ET ABS_C_007 ET ABS_C_008 ET ABS_C_009 ET ABS_C_019 ET ABS_C_020 ET ABS_C_023 ET ABS_C_026 ET ABS_C_065 | X56: CDI_I_026 | Y56: =VLOOKUP(X56,'Axe 2 Règles de gestion'!$D$2:$F$564,3, FALSE) -> Le congé est accordé si un ascendant, descendant, un frère ou une sœur, une personne partageant le même domicile ou l'ayant désigné comme sa personne de confiance souffre d'une pathologie mettant en jeu le pronostic vital ou en phase avancée ou terminale d'une affection grave et incurable, quelle qu'en soit la cause. | Z56: CDI_I_027 | AA56: =VLOOKUP(Z56,'Axe 2 Règles de gestion'!$D$2:$F$564,3, FALSE) -> L'agent doit faire la demande par écrit. Elle est accordée de droit. | AB56: CDI_I_028 | AC56: =VLOOKUP(AB56,'Axe 2 Règles de gestion'!$D$2:$F$564,3, FALSE) -> La demande doit être appuyée d'un certificat médical attestant que la personne accompagnée souffre d'une pathologie mettant en jeu le pronostic vital ou en phase avancée ou terminale d'une affection grave et incurable, quelle qu'en soit la cause. | AD56: CDI_I_029 | AE56: =VLOOKUP(AD56,'Axe 2 Règles de gestion'!$D$2:$F$564,3, FALSE) -> Le congé peut être fractionné ou pris de manière continue. | AT56: CDI_D_177 | AU56: =VLOOKUP(AT56,'Axe 2 Règles de gestion'!$D$2:$F$564,3, FALSE) -> Le congé de solidarité familiale, ou son renouvellement, est accordé pour une durée réelle maximale de trois mois. | AV56: CDI_D_577 | AW56: =VLOOKUP(AV56,'Axe 2 Règles de gestion'!$D$2:$F$564,3, FALSE) -> Le congé de solidarité familiale, ou son renouvellement, est accordé pour une durée prévisionnelle maximale de trois mois. | AX56: CDI_D_179 | AY56: =VLOOKUP(AX56,'Axe 2 Règles de gestion'!$D$2:$F$564,3, FALSE) -> Le congé de solidarité familiale peut être fractionné mais ne peut, renouvellement inclus, excéder les 6 mois. | AZ56: CDI_D_613 | BA56: =VLOOKUP(AZ56,'Axe 2 Règles de gestion'!$D$2:$F$564,3, FALSE) -> Le congé de solidarité familiale peut être fractionné mais chaque période doit être d'une durée réelle minimale de 7 jours consécutifs. | BB56: CDI_D_605 | BC56: =VLOOKUP(BB56,'Axe 2 Règles de gestion'!$D$2:$F$564,3, FALSE) -> Le congé de solidarité familiale peut être fractionné mais chaque période doit être d'une durée prévisionnelle minimale de 7 jours consécutifs. | BD56: CDI_D_173 | BE56: =VLOOKUP(BD56,'Axe 2 Règles de gestion'!$D$2:$F$564,3, FALSE) -> L'agent doit être en activité. | BF56: ABS_C_002 | BG56: =VLOOKUP(BF56,'Axe 2 Règles de gestion'!$D$2:$F$564,3, FALSE) -> La date de début du congé/absence doit être postérieure ou égale à la date de début du lien juridique. | BH56: ABS_C_003 | BI56: =VLOOKUP(BH56,'Axe 2 Règles de gestion'!$D$2:$F$564,3, FALSE) -> La date de début du congé/absence doit être antérieure ou égale à la date de fin réelle du congé/absence. | BJ56: ABS_C_004 | BK56: =VLOOKUP(BJ56,'Axe 2 Règles de gestion'!$D$2:$F$564,3, FALSE) -> La date de début du congé/absence doit être antérieure ou égale à la date de fin prévisionnelle du congé/absence. | BL56: ABS_C_005 | BM56: =VLOOKUP(BL56,'Axe 2 Règles de gestion'!$D$2:$F$564,3, FALSE) -> La date de fin réelle du congé/absence doit être antérieure ou égale à la date limite de fin réelle ou prévisionnelle du lien juridique. | BN56: ABS_C_006 | BO56: =VLOOKUP(BN56,'Axe 2 Règles de gestion'!$D$2:$F$564,3, FALSE) -> La date de fin prévisionnelle du congé/absence doit être antérieure ou égale à la date limite de fin réelle ou prévisionnelle du lien juridique. | BP56: ABS_C_007 | BQ56: =VLOOKUP(BP56,'Axe 2 Règles de gestion'!$D$2:$F$564,3, FALSE) -> La date de fin réelle du congé/absence doit être antérieure à la date limite de départ à la retraite. | BR56: ABS_C_008 | BS56: =VLOOKUP(BR56,'Axe 2 Règles de gestion'!$D$2:$F$564,3, FALSE) -> La date de fin prévisionnelle du congé/absence doit être antérieure à la date limite de départ à la retraite. | BT56: ABS_C_009 | BU56: =VLOOKUP(BT56,'Axe 2 Règles de gestion'!$D$2:$F$564,3, FALSE) -> La date de fin réelle ou la date de fin prévisionnelle du congé/absence doit être saisie. | BV56: ABS_C_019 | BW56: =VLOOKUP(BV56,'Axe 2 Règles de gestion'!$D$2:$F$564,3, FALSE) -> Si l'absence ne commence pas par une demi-journée et si l'absence précédente ne finit pas par une demi journée, la date de début de l'absence saisie est postérieure à la date de fin réelle de l'absence précédente. | BX56: ABS_C_020 | BY56: =VLOOKUP(BX56,'Axe 2 Règles de gestion'!$D$2:$F$564,3, FALSE) -> Si l'absence ne commence pas par une demi-journée et si l'absence précédente ne finit pas par une demi journée, la date de début de l'absence saisie est postérieure à la date de fin prévisionnelle de l'absence précédente. | BZ56: ABS_C_023 | CA56: =VLOOKUP(BZ56,'Axe 2 Règles de gestion'!$D$2:$F$564,3, FALSE) -> L'état du congé est renseigné. | CB56: ABS_C_026 | CC56: =VLOOKUP(CB56,'Axe 2 Règles de gestion'!$D$2:$F$564,3, FALSE) -> Dans le cas d'un congé autre que CLM, CLD, CGM et CITIS, l'indicateur de requalification doit être à non et les impacts spécifiques à la requalification ne doivent pas être mobilisés ou l'impact rémunération est vide. | CD56: ABS_C_065 | CE56: =VLOOKUP(CD56,'Axe 2 Règles de gestion'!$D$2:$F$564,3, FALSE) -> L'agent en congé de présence parentale / congé de proche aidant / congé de solidarité familiale ne peut se voir accorder de manière simultanée un temps partiel pour congé de présence parentale / pour congé de proche aidant / pour congé de solidarité familiale.
A57: 21.10.00 | B57: M | C57: 44469.656 | D57: D0007 | E57: Congés/Absence | F57: S0072 | G57: Congé pour raisons de famille | H57: E0500 | I57: Congé de solidarité familiale | J57: Le Type de congé/absence est 'Congé de solidarité familiale' | K57: A_COA_TYCOAB [Saisi] = 'CG103' | L57: T1208 | M57: Congé de solidarité familiale - Fin | N57: Modification | O57: La valeur de l'Etat du congé saisie est égale à celle avant saisie | P57: A_COA_ETCOMA [Saisi] = A_COA_ETCOMA [Valeur avant saisie] | Q57: Conseiller ou avocat général à la Cour de cassation en service extraordinaire | R57: P0046 | S57: Particulier | T57: Passant | U57: 40725 | W57: CDI_I_030 ET CDI_D_177 ET CDI_D_577 ET CDI_D_179 ET CDI_D_613 ET CDI_D_605 ET ABS_C_003 ET ABS_C_004 ET ABS_C_005 ET ABS_C_006 ET ABS_C_007 ET ABS_C_008 ET ABS_C_009 ET ABS_C_023 ET ABS_C_026 ET ABS_C_065 | X57: CDI_I_030 | Y57: =VLOOKUP(X57,'Axe 2 Règles de gestion'!$D$2:$F$564,3, FALSE) -> Le congé prend fin à l'issue de la période de 3 mois ou dans les 3 jours suivant le décès de la personnes accompagnée ou à la demande de l'agent. | AT57: CDI_D_177 | AU57: =VLOOKUP(AT57,'Axe 2 Règles de gestion'!$D$2:$F$564,3, FALSE) -> Le congé de solidarité familiale, ou son renouvellement, est accordé pour une durée réelle maximale de trois mois. | AV57: CDI_D_577 | AW57: =VLOOKUP(AV57,'Axe 2 Règles de gestion'!$D$2:$F$564,3, FALSE) -> Le congé de solidarité familiale, ou son renouvellement, est accordé pour une durée prévisionnelle maximale de trois mois. | AX57: CDI_D_179 | AY57: =VLOOKUP(AX57,'Axe 2 Règles de gestion'!$D$2:$F$564,3, FALSE) -> Le congé de solidarité familiale peut être fractionné mais ne peut, renouvellement inclus, excéder les 6 mois. | AZ57: CDI_D_613 | BA57: =VLOOKUP(AZ57,'Axe 2 Règles de gestion'!$D$2:$F$564,3, FALSE) -> Le congé de solidarité familiale peut être fractionné mais chaque période doit être d'une durée réelle minimale de 7 jours consécutifs. | BB57: CDI_D_605 | BC57: =VLOOKUP(BB57,'Axe 2 Règles de gestion'!$D$2:$F$564,3, FALSE) -> Le congé de solidarité familiale peut être fractionné mais chaque période doit être d'une durée prévisionnelle minimale de 7 jours consécutifs. | BF57: ABS_C_003 | BG57: =VLOOKUP(BF57,'Axe 2 Règles de gestion'!$D$2:$F$564,3, FALSE) -> La date de début du congé/absence doit être antérieure ou égale à la date de fin réelle du congé/absence. | BH57: ABS_C_004 | BI57: =VLOOKUP(BH57,'Axe 2 Règles de gestion'!$D$2:$F$564,3, FALSE) -> La date de début du congé/absence doit être antérieure ou égale à la date de fin prévisionnelle du congé/absence. | BJ57: ABS_C_005 | BK57: =VLOOKUP(BJ57,'Axe 2 Règles de gestion'!$D$2:$F$564,3, FALSE) -> La date de fin réelle du congé/absence doit être antérieure ou égale à la date limite de fin réelle ou prévisionnelle du lien juridique. | BL57: ABS_C_006 | BM57: =VLOOKUP(BL57,'Axe 2 Règles de gestion'!$D$2:$F$564,3, FALSE) -> La date de fin prévisionnelle du congé/absence doit être antérieure ou égale à la date limite de fin réelle ou prévisionnelle du lien juridique. | BN57: ABS_C_007 | BO57: =VLOOKUP(BN57,'Axe 2 Règles de gestion'!$D$2:$F$564,3, FALSE) -> La date de fin réelle du congé/absence doit être antérieure à la date limite de départ à la retraite. | BP57: ABS_C_008 | BQ57: =VLOOKUP(BP57,'Axe 2 Règles de gestion'!$D$2:$F$564,3, FALSE) -> La date de fin prévisionnelle du congé/absence doit être antérieure à la date limite de départ à la retraite. | BR57: ABS_C_009 | BS57: =VLOOKUP(BR57,'Axe 2 Règles de gestion'!$D$2:$F$564,3, FALSE) -> La date de fin réelle ou la date de fin prévisionnelle du congé/absence doit être saisie. | BT57: ABS_C_023 | BU57: =VLOOKUP(BT57,'Axe 2 Règles de gestion'!$D$2:$F$564,3, FALSE) -> L'état du congé est renseigné. | BV57: ABS_C_026 | BW57: =VLOOKUP(BV57,'Axe 2 Règles de gestion'!$D$2:$F$564,3, FALSE) -> Dans le cas d'un congé autre que CLM, CLD, CGM et CITIS, l'indicateur de requalification doit être à non et les impacts spécifiques à la requalification ne doivent pas être mobilisés ou l'impact rémunération est vide. | BX57: ABS_C_065 | BY57: =VLOOKUP(BX57,'Axe 2 Règles de gestion'!$D$2:$F$564,3, FALSE) -> L'agent en congé de présence parentale / congé de proche aidant / congé de solidarité familiale ne peut se voir accorder de manière simultanée un temps partiel pour congé de présence parentale / pour congé de proche aidant / pour congé de solidarité familiale.
A58: 17.10.00 | B58: A | C58: 43152.5 | D58: D0007 | E58: Congés/Absence | F58: S0072 | G58: Congé pour raisons de famille | H58: E0500 | I58: Congé de solidarité familiale | J58: Le Type de congé/absence est 'Congé de solidarité familiale' | K58: A_COA_TYCOAB [Saisi] = 'CG103' | L58: T1206 | M58: Congé de solidarité familiale - Demande | N58: Création Modification | O58: La valeur de l'Etat du congé est différente de 'Renouvellement' et la valeur de l'Etat du congé saisie est différente de celle avant saisie | P58: A_COA_ETCOMA [Saisi] <> 'EC02' ET A_COA_ETCOMA [Saisi] <> A_COA_ETCOMA [Valeur avant saisie] | Q58: Personnel civil payé à l'acte ou à la tâche | R58: P0054 | S58: Particulier | T58: Exclu | U58: 41295
A59: 17.10.00 | B59: A | C59: 43152.5 | D59: D0007 | E59: Congés/Absence | F59: S0072 | G59: Congé pour raisons de famille | H59: E0500 | I59: Congé de solidarité familiale | J59: Le Type de congé/absence est 'Congé de solidarité familiale' | K59: A_COA_TYCOAB [Saisi] = 'CG103' | L59: T1207 | M59: Congé de solidarité familiale - Renouvellement | N59: Création Modification | O59: La valeur de l'Etat du congé est égale à 'Renouvellement' et la valeur de l'Etat du congé saisie est différente de celle avant saisie | P59: A_COA_ETCOMA [Saisi] = 'EC02' ET A_COA_ETCOMA [Saisi] <> A_COA_ETCOMA [Valeur avant saisie] | Q59: Personnel civil payé à l'acte ou à la tâche | R59: P0054 | S59: Particulier | T59: Exclu | U59: 41295
A60: 17.10.00 | B60: A | C60: 43152.5 | D60: D0007 | E60: Congés/Absence | F60: S0072 | G60: Congé pour raisons de famille | H60: E0500 | I60: Congé de solidarité familiale | J60: Le Type de congé/absence est 'Congé de solidarité familiale' | K60: A_COA_TYCOAB [Saisi] = 'CG103' | L60: T1208 | M60: Congé de solidarité familiale - Fin | N60: Modification | O60: La valeur de l'Etat du congé saisie est égale à celle avant saisie | P60: A_COA_ETCOMA [Saisi] = A_COA_ETCOMA [Valeur avant saisie] | Q60: Personnel civil payé à l'acte ou à la tâche | R60: P0054 | S60: Particulier | T60: Exclu | U60: 41295
A61: 17.10.00 | B61: A | C61: 43152.5 | D61: D0007 | E61: Congés/Absence | F61: S0072 | G61: Congé pour raisons de famille | H61: E0500 | I61: Congé de solidarité familiale | J61: Le Type de congé/absence est 'Congé de solidarité familiale' | K61: A_COA_TYCOAB [Saisi] = 'CG103' | L61: T1206 | M61: Congé de solidarité familiale - Demande | N61: Création Modification | O61: La valeur de l'Etat du congé est différente de 'Renouvellement' et la valeur de l'Etat du congé saisie est différente de celle avant saisie | P61: A_COA_ETCOMA [Saisi] <> 'EC02' ET A_COA_ETCOMA [Saisi] <> A_COA_ETCOMA [Valeur avant saisie] | Q61: Contractuel en service à l'étranger | R61: P0069 | S61: Particulier | T61: Exclu | U61: 41295
A62: 17.10.00 | B62: A | C62: 43152.5 | D62: D0007 | E62: Congés/Absence | F62: S0072 | G62: Congé pour raisons de famille | H62: E0500 | I62: Congé de solidarité familiale | J62: Le Type de congé/absence est 'Congé de solidarité familiale' | K62: A_COA_TYCOAB [Saisi] = 'CG103' | L62: T1207 | M62: Congé de solidarité familiale - Renouvellement | N62: Création Modification | O62: La valeur de l'Etat du congé est égale à 'Renouvellement' et la valeur de l'Etat du congé saisie est différente de celle avant saisie | P62: A_COA_ETCOMA [Saisi] = 'EC02' ET A_COA_ETCOMA [Saisi] <> A_COA_ETCOMA [Valeur avant saisie] | Q62: Contractuel en service à l'étranger | R62: P0069 | S62: Particulier | T62: Exclu | U62: 41295
A63: 17.10.00 | B63: A | C63: 43152.5 | D63: D0007 | E63: Congés/Absence | F63: S0072 | G63: Congé pour raisons de famille | H63: E0500 | I63: Congé de solidarité familiale | J63: Le Type de congé/absence est 'Congé de solidarité familiale' | K63: A_COA_TYCOAB [Saisi] = 'CG103' | L63: T1208 | M63: Congé de solidarité familiale - Fin | N63: Modification | O63: La valeur de l'Etat du congé saisie est égale à celle avant saisie | P63: A_COA_ETCOMA [Saisi] = A_COA_ETCOMA [Valeur avant saisie] | Q63: Contractuel en service à l'étranger | R63: P0069 | S63: Particulier | T63: Exclu | U63: 41295
A64: 21.10.00 | B64: M | C64: 44469.656 | D64: D0007 | E64: Congés/Absence | F64: S0072 | G64: Congé pour raisons de famille | H64: E0500 | I64: Congé de solidarité familiale | J64: Le Type de congé/absence est 'Congé de solidarité familiale' | K64: A_COA_TYCOAB [Saisi] = 'CG103' | L64: T1206 | M64: Congé de solidarité familiale - Demande | N64: Création Modification | O64: La valeur de l'Etat du congé est différente de 'Renouvellement' et la valeur de l'Etat du congé saisie est différente de celle avant saisie | P64: A_COA_ETCOMA [Saisi] <> 'EC02' ET A_COA_ETCOMA [Saisi] <> A_COA_ETCOMA [Valeur avant saisie] | Q64: Contractuel de droit privé | R64: P0072 | S64: Particulier | T64: Passant | U64: 40725 | W64: CDI_I_051 ET CDI_I_052 ET CDI_I_053 ET CDI_I_054 ET CDI_D_169 ET CDI_D_609 ET CDI_D_610 ET CDI_D_165 ET ABS_C_002 ET ABS_C_003 ET ABS_C_004 ET ABS_C_005 ET ABS_C_006 ET ABS_C_007 ET ABS_C_008 ET ABS_C_009 ET ABS_C_019 ET ABS_C_020 ET ABS_C_023 ET ABS_C_026 ET ABS_C_065 | X64: CDI_I_051 | Y64: =VLOOKUP(X64,'Axe 2 Règles de gestion'!$D$2:$F$564,3, FALSE) -> Le congé est accordé si un ascendant, descendant, un frère ou une sœur, une personne partageant le même domicile ou l'ayant désigné comme sa personne de confiance souffre d'une pathologie mettant en jeu le pronostic vital ou en phase avancée ou terminale d'une affection grave et incurable, quelle qu'en soit la cause. | Z64: CDI_I_052 | AA64: =VLOOKUP(Z64,'Axe 2 Règles de gestion'!$D$2:$F$564,3, FALSE) -> L'agent doit faire la demande par écrit. Elle est accordée de droit. | AB64: CDI_I_053 | AC64: =VLOOKUP(AB64,'Axe 2 Règles de gestion'!$D$2:$F$564,3, FALSE) -> La demande doit être appuyée d'un certificat médical attestant que la personne accompagnée souffre d'une pathologie mettant en jeu le pronostic vital ou en phase avancée ou terminale d'une affection grave et incurable, quelle qu'en soit la cause. | AD64: CDI_I_054 | AE64: =VLOOKUP(AD64,'Axe 2 Règles de gestion'!$D$2:$F$564,3, FALSE) -> Le congé peut être fractionné ou pris de manière continue. | AT64: CDI_D_169 | AU64: =VLOOKUP(AT64,'Axe 2 Règles de gestion'!$D$2:$F$564,3, FALSE) -> Le congé de solidarité familiale, ou son renouvellement, est accordé pour une durée réelle maximale de trois mois. | AV64: CDI_D_609 | AW64: =VLOOKUP(AV64,'Axe 2 Règles de gestion'!$D$2:$F$564,3, FALSE) -> Le congé de solidarité familiale, ou son renouvellement, est accordé pour une durée prévisionnelle maximale de trois mois. | AX64: CDI_D_610 | AY64: =VLOOKUP(AX64,'Axe 2 Règles de gestion'!$D$2:$F$564,3, FALSE) -> Le congé de solidarité familiale peut être fractionné mais ne peut, renouvellement inclus, excéder les 6 mois. | AZ64: CDI_D_165 | BA64: =VLOOKUP(AZ64,'Axe 2 Règles de gestion'!$D$2:$F$564,3, FALSE) -> L'agent doit être en activité. | BF64: ABS_C_002 | BG64: =VLOOKUP(BF64,'Axe 2 Règles de gestion'!$D$2:$F$564,3, FALSE) -> La date de début du congé/absence doit être postérieure ou égale à la date de début du lien juridique. | BH64: ABS_C_003 | BI64: =VLOOKUP(BH64,'Axe 2 Règles de gestion'!$D$2:$F$564,3, FALSE) -> La date de début du congé/absence doit être antérieure ou égale à la date de fin réelle du congé/absence. | BJ64: ABS_C_004 | BK64: =VLOOKUP(BJ64,'Axe 2 Règles de gestion'!$D$2:$F$564,3, FALSE) -> La date de début du congé/absence doit être antérieure ou égale à la date de fin prévisionnelle du congé/absence. | BL64: ABS_C_005 | BM64: =VLOOKUP(BL64,'Axe 2 Règles de gestion'!$D$2:$F$564,3, FALSE) -> La date de fin réelle du congé/absence doit être antérieure ou égale à la date limite de fin réelle ou prévisionnelle du lien juridique. | BN64: ABS_C_006 | BO64: =VLOOKUP(BN64,'Axe 2 Règles de gestion'!$D$2:$F$564,3, FALSE) -> La date de fin prévisionnelle du congé/absence doit être antérieure ou égale à la date limite de fin réelle ou prévisionnelle du lien juridique. | BP64: ABS_C_007 | BQ64: =VLOOKUP(BP64,'Axe 2 Règles de gestion'!$D$2:$F$564,3, FALSE) -> La date de fin réelle du congé/absence doit être antérieure à la date limite de départ à la retraite. | BR64: ABS_C_008 | BS64: =VLOOKUP(BR64,'Axe 2 Règles de gestion'!$D$2:$F$564,3, FALSE) -> La date de fin prévisionnelle du congé/absence doit être antérieure à la date limite de départ à la retraite. | BT64: ABS_C_009 | BU64: =VLOOKUP(BT64,'Axe 2 Règles de gestion'!$D$2:$F$564,3, FALSE) -> La date de fin réelle ou la date de fin prévisionnelle du congé/absence doit être saisie. | BV64: ABS_C_019 | BW64: =VLOOKUP(BV64,'Axe 2 Règles de gestion'!$D$2:$F$564,3, FALSE) -> Si l'absence ne commence pas par une demi-journée et si l'absence précédente ne finit pas par une demi journée, la date de début de l'absence saisie est postérieure à la date de fin réelle de l'absence précédente. | BX64: ABS_C_020 | BY64: =VLOOKUP(BX64,'Axe 2 Règles de gestion'!$D$2:$F$564,3, FALSE) -> Si l'absence ne commence pas par une demi-journée et si l'absence précédente ne finit pas par une demi journée, la date de début de l'absence saisie est postérieure à la date de fin prévisionnelle de l'absence précédente. | BZ64: ABS_C_023 | CA64: =VLOOKUP(BZ64,'Axe 2 Règles de gestion'!$D$2:$F$564,3, FALSE) -> L'état du congé est renseigné. | CB64: ABS_C_026 | CC64: =VLOOKUP(CB64,'Axe 2 Règles de gestion'!$D$2:$F$564,3, FALSE) -> Dans le cas d'un congé autre que CLM, CLD, CGM et CITIS, l'indicateur de requalification doit être à non et les impacts spécifiques à la requalification ne doivent pas être mobilisés ou l'impact rémunération est vide. | CD64: ABS_C_065 | CE64: =VLOOKUP(CD64,'Axe 2 Règles de gestion'!$D$2:$F$564,3, FALSE) -> L'agent en congé de présence parentale / congé de proche aidant / congé de solidarité familiale ne peut se voir accorder de manière simultanée un temps partiel pour congé de présence parentale / pour congé de proche aidant / pour congé de solidarité familiale.
A65: 21.10.00 | B65: M | C65: 44469.656 | D65: D0007 | E65: Congés/Absence | F65: S0072 | G65: Congé pour raisons de famille | H65: E0500 | I65: Congé de solidarité familiale | J65: Le Type de congé/absence est 'Congé de solidarité familiale' | K65: A_COA_TYCOAB [Saisi] = 'CG103' | L65: T1207 | M65: Congé de solidarité familiale - Renouvellement | N65: Création Modification | O65: La valeur de l'Etat du congé est égale à 'Renouvellement' et la valeur de l'Etat du congé saisie est différente de celle avant saisie | P65: A_COA_ETCOMA [Saisi] = 'EC02' ET A_COA_ETCOMA [Saisi] <> A_COA_ETCOMA [Valeur avant saisie] | Q65: Contractuel de droit privé | R65: P0072 | S65: Particulier | T65: Passant | U65: 40725 | W65: CDI_I_051 ET CDI_I_052 ET CDI_I_053 ET CDI_I_054 ET CDI_D_169 ET CDI_D_609 ET CDI_D_610 ET CDI_D_165 ET ABS_C_002 ET ABS_C_003 ET ABS_C_004 ET ABS_C_005 ET ABS_C_006 ET ABS_C_007 ET ABS_C_008 ET ABS_C_009 ET ABS_C_019 ET ABS_C_020 ET ABS_C_023 ET ABS_C_026 ET ABS_C_065 | X65: CDI_I_051 | Y65: =VLOOKUP(X65,'Axe 2 Règles de gestion'!$D$2:$F$564,3, FALSE) -> Le congé est accordé si un ascendant, descendant, un frère ou une sœur, une personne partageant le même domicile ou l'ayant désigné comme sa personne de confiance souffre d'une pathologie mettant en jeu le pronostic vital ou en phase avancée ou terminale d'une affection grave et incurable, quelle qu'en soit la cause. | Z65: CDI_I_052 | AA65: =VLOOKUP(Z65,'Axe 2 Règles de gestion'!$D$2:$F$564,3, FALSE) -> L'agent doit faire la demande par écrit. Elle est accordée de droit. | AB65: CDI_I_053 | AC65: =VLOOKUP(AB65,'Axe 2 Règles de gestion'!$D$2:$F$564,3, FALSE) -> La demande doit être appuyée d'un certificat médical attestant que la personne accompagnée souffre d'une pathologie mettant en jeu le pronostic vital ou en phase avancée ou terminale d'une affection grave et incurable, quelle qu'en soit la cause. | AD65: CDI_I_054 | AE65: =VLOOKUP(AD65,'Axe 2 Règles de gestion'!$D$2:$F$564,3, FALSE) -> Le congé peut être fractionné ou pris de manière continue. | AT65: CDI_D_169 | AU65: =VLOOKUP(AT65,'Axe 2 Règles de gestion'!$D$2:$F$564,3, FALSE) -> Le congé de solidarité familiale, ou son renouvellement, est accordé pour une durée réelle maximale de trois mois. | AV65: CDI_D_609 | AW65: =VLOOKUP(AV65,'Axe 2 Règles de gestion'!$D$2:$F$564,3, FALSE) -> Le congé de solidarité familiale, ou son renouvellement, est accordé pour une durée prévisionnelle maximale de trois mois. | AX65: CDI_D_610 | AY65: =VLOOKUP(AX65,'Axe 2 Règles de gestion'!$D$2:$F$564,3, FALSE) -> Le congé de solidarité familiale peut être fractionné mais ne peut, renouvellement inclus, excéder les 6 mois. | AZ65: CDI_D_165 | BA65: =VLOOKUP(AZ65,'Axe 2 Règles de gestion'!$D$2:$F$564,3, FALSE) -> L'agent doit être en activité. | BF65: ABS_C_002 | BG65: =VLOOKUP(BF65,'Axe 2 Règles de gestion'!$D$2:$F$564,3, FALSE) -> La date de début du congé/absence doit être postérieure ou égale à la date de début du lien juridique. | BH65: ABS_C_003 | BI65: =VLOOKUP(BH65,'Axe 2 Règles de gestion'!$D$2:$F$564,3, FALSE) -> La date de début du congé/absence doit être antérieure ou égale à la date de fin réelle du congé/absence. | BJ65: ABS_C_004 | BK65: =VLOOKUP(BJ65,'Axe 2 Règles de gestion'!$D$2:$F$564,3, FALSE) -> La date de début du congé/absence doit être antérieure ou égale à la date de fin prévisionnelle du congé/absence. | BL65: ABS_C_005 | BM65: =VLOOKUP(BL65,'Axe 2 Règles de gestion'!$D$2:$F$564,3, FALSE) -> La date de fin réelle du congé/absence doit être antérieure ou égale à la date limite de fin réelle ou prévisionnelle du lien juridique. | BN65: ABS_C_006 | BO65: =VLOOKUP(BN65,'Axe 2 Règles de gestion'!$D$2:$F$564,3, FALSE) -> La date de fin prévisionnelle du congé/absence doit être antérieure ou égale à la date limite de fin réelle ou prévisionnelle du lien juridique. | BP65: ABS_C_007 | BQ65: =VLOOKUP(BP65,'Axe 2 Règles de gestion'!$D$2:$F$564,3, FALSE) -> La date de fin réelle du congé/absence doit être antérieure à la date limite de départ à la retraite. | BR65: ABS_C_008 | BS65: =VLOOKUP(BR65,'Axe 2 Règles de gestion'!$D$2:$F$564,3, FALSE) -> La date de fin prévisionnelle du congé/absence doit être antérieure à la date limite de départ à la retraite. | BT65: ABS_C_009 | BU65: =VLOOKUP(BT65,'Axe 2 Règles de gestion'!$D$2:$F$564,3, FALSE) -> La date de fin réelle ou la date de fin prévisionnelle du congé/absence doit être saisie. | BV65: ABS_C_019 | BW65: =VLOOKUP(BV65,'Axe 2 Règles de gestion'!$D$2:$F$564,3, FALSE) -> Si l'absence ne commence pas par une demi-journée et si l'absence précédente ne finit pas par une demi journée, la date de début de l'absence saisie est postérieure à la date de fin réelle de l'absence précédente. | BX65: ABS_C_020 | BY65: =VLOOKUP(BX65,'Axe 2 Règles de gestion'!$D$2:$F$564,3, FALSE) -> Si l'absence ne commence pas par une demi-journée et si l'absence précédente ne finit pas par une demi journée, la date de début de l'absence saisie est postérieure à la date de fin prévisionnelle de l'absence précédente. | BZ65: ABS_C_023 | CA65: =VLOOKUP(BZ65,'Axe 2 Règles de gestion'!$D$2:$F$564,3, FALSE) -> L'état du congé est renseigné. | CB65: ABS_C_026 | CC65: =VLOOKUP(CB65,'Axe 2 Règles de gestion'!$D$2:$F$564,3, FALSE) -> Dans le cas d'un congé autre que CLM, CLD, CGM et CITIS, l'indicateur de requalification doit être à non et les impacts spécifiques à la requalification ne doivent pas être mobilisés ou l'impact rémunération est vide. | CD65: ABS_C_065 | CE65: =VLOOKUP(CD65,'Axe 2 Règles de gestion'!$D$2:$F$564,3, FALSE) -> L'agent en congé de présence parentale / congé de proche aidant / congé de solidarité familiale ne peut se voir accorder de manière simultanée un temps partiel pour congé de présence parentale / pour congé de proche aidant / pour congé de solidarité familiale.
A66: 21.10.00 | B66: M | C66: 44469.656 | D66: D0007 | E66: Congés/Absence | F66: S0072 | G66: Congé pour raisons de famille | H66: E0500 | I66: Congé de solidarité familiale | J66: Le Type de congé/absence est 'Congé de solidarité familiale' | K66: A_COA_TYCOAB [Saisi] = 'CG103' | L66: T1208 | M66: Congé de solidarité familiale - Fin | N66: Modification | O66: La valeur de l'Etat du congé saisie est égale à celle avant saisie | P66: A_COA_ETCOMA [Saisi] = A_COA_ETCOMA [Valeur avant saisie] | Q66: Contractuel de droit privé | R66: P0072 | S66: Particulier | T66: Passant | U66: 40725 | W66: CDI_I_055 ET CDI_D_169 ET CDI_D_609 ET CDI_D_610 ET ABS_C_003 ET ABS_C_004 ET ABS_C_005 ET ABS_C_006 ET ABS_C_007 ET ABS_C_008 ET ABS_C_009 ET ABS_C_023 ET ABS_C_026 ET ABS_C_065 | X66: CDI_I_055 | Y66: =VLOOKUP(X66,'Axe 2 Règles de gestion'!$D$2:$F$564,3, FALSE) -> Le congé prend fin à l'issue de la période de 3 mois ou dans les 3 jours suivant le décès de la personnes accompagnée ou à la demande de l'agent. | AT66: CDI_D_169 | AU66: =VLOOKUP(AT66,'Axe 2 Règles de gestion'!$D$2:$F$564,3, FALSE) -> Le congé de solidarité familiale, ou son renouvellement, est accordé pour une durée réelle maximale de trois mois. | AV66: CDI_D_609 | AW66: =VLOOKUP(AV66,'Axe 2 Règles de gestion'!$D$2:$F$564,3, FALSE) -> Le congé de solidarité familiale, ou son renouvellement, est accordé pour une durée prévisionnelle maximale de trois mois. | AX66: CDI_D_610 | AY66: =VLOOKUP(AX66,'Axe 2 Règles de gestion'!$D$2:$F$564,3, FALSE) -> Le congé de solidarité familiale peut être fractionné mais ne peut, renouvellement inclus, excéder les 6 mois. | BF66: ABS_C_003 | BG66: =VLOOKUP(BF66,'Axe 2 Règles de gestion'!$D$2:$F$564,3, FALSE) -> La date de début du congé/absence doit être antérieure ou égale à la date de fin réelle du congé/absence. | BH66: ABS_C_004 | BI66: =VLOOKUP(BH66,'Axe 2 Règles de gestion'!$D$2:$F$564,3, FALSE) -> La date de début du congé/absence doit être antérieure ou égale à la date de fin prévisionnelle du congé/absence. | BJ66: ABS_C_005 | BK66: =VLOOKUP(BJ66,'Axe 2 Règles de gestion'!$D$2:$F$564,3, FALSE) -> La date de fin réelle du congé/absence doit être antérieure ou égale à la date limite de fin réelle ou prévisionnelle du lien juridique. | BL66: ABS_C_006 | BM66: =VLOOKUP(BL66,'Axe 2 Règles de gestion'!$D$2:$F$564,3, FALSE) -> La date de fin prévisionnelle du congé/absence doit être antérieure ou égale à la date limite de fin réelle ou prévisionnelle du lien juridique. | BN66: ABS_C_007 | BO66: =VLOOKUP(BN66,'Axe 2 Règles de gestion'!$D$2:$F$564,3, FALSE) -> La date de fin réelle du congé/absence doit être antérieure à la date limite de départ à la retraite. | BP66: ABS_C_008 | BQ66: =VLOOKUP(BP66,'Axe 2 Règles de gestion'!$D$2:$F$564,3, FALSE) -> La date de fin prévisionnelle du congé/absence doit être antérieure à la date limite de départ à la retraite. | BR66: ABS_C_009 | BS66: =VLOOKUP(BR66,'Axe 2 Règles de gestion'!$D$2:$F$564,3, FALSE) -> La date de fin réelle ou la date de fin prévisionnelle du congé/absence doit être saisie. | BT66: ABS_C_023 | BU66: =VLOOKUP(BT66,'Axe 2 Règles de gestion'!$D$2:$F$564,3, FALSE) -> L'état du congé est renseigné. | BV66: ABS_C_026 | BW66: =VLOOKUP(BV66,'Axe 2 Règles de gestion'!$D$2:$F$564,3, FALSE) -> Dans le cas d'un congé autre que CLM, CLD, CGM et CITIS, l'indicateur de requalification doit être à non et les impacts spécifiques à la requalification ne doivent pas être mobilisés ou l'impact rémunération est vide. | BX66: ABS_C_065 | BY66: =VLOOKUP(BX66,'Axe 2 Règles de gestion'!$D$2:$F$564,3, FALSE) -> L'agent en congé de présence parentale / congé de proche aidant / congé de solidarité familiale ne peut se voir accorder de manière simultanée un temps partiel pour congé de présence parentale / pour congé de proche aidant / pour congé de solidarité familiale.
A67: 25.10.00 | B67: M | C67: 45993.394 | D67: D0007 | E67: Congés/Absence | F67: S0072 | G67: Congé pour raisons de famille | H67: E0500 | I67: Congé de solidarité familiale | J67: Le Type de congé/absence est 'Congé de solidarité familiale' | K67: A_COA_TYCOAB [Saisi] = 'CG103' | L67: T1206 | M67: Congé de solidarité familiale - Demande | N67: Création Modification | O67: La valeur de l'Etat du congé est différente de 'Renouvellement' et la valeur de l'Etat du congé saisie est différente de celle avant saisie | P67: A_COA_ETCOMA [Saisi] <> 'EC02' ET A_COA_ETCOMA [Saisi] <> A_COA_ETCOMA [Valeur avant saisie] | Q67: Enseignant contractuel de l'enseignement agricole privé sous contrat non définitif - Agriculture | R67: P0078 | S67: Particulier | T67: Passant | U67: 40725 | W67: CDI_I_102 ET CDI_I_001 ET CDI_I_002 ET CDI_I_003 ET CDI_I_004 ET CDI_D_121 ET CDI_D_521 ET CDI_D_122 ET CDI_D_123 ET CDI_D_601 ET CDI_D_117 ET ABS_C_002 ET ABS_C_003 ET ABS_C_004 ET ABS_C_005 ET ABS_C_006 ET ABS_C_007 ET ABS_C_008 ET ABS_C_009 ET ABS_C_019 ET ABS_C_020 ET ABS_C_023 ET ABS_C_026 ET ABS_C_065 | X67: CDI_I_102 | Y67: =VLOOKUP(X67,'Axe 2 Règles de gestion'!$D$2:$F$564,3, FALSE) -> L'agent bénéficie des dispositions applicables aux agents titulaires pour le congé de solidarité familiale, sauf dispositions particulières. | Z67: CDI_I_001 | AA67: =VLOOKUP(Z67,'Axe 2 Règles de gestion'!$D$2:$F$564,3, FALSE) -> Le congé est accordé si un ascendant, descendant, un frère ou une sœur, une personne partageant le même domicile ou l'ayant désigné comme sa personne de confiance souffre d'une pathologie mettant en jeu le pronostic vital ou en phase avancée ou terminale d'une affection grave et incurable, quelle qu'en soit la cause. | AB67: CDI_I_002 | AC67: =VLOOKUP(AB67,'Axe 2 Règles de gestion'!$D$2:$F$564,3, FALSE) -> L'agent doit faire la demande par écrit. Elle est accordée de droit. | AD67: CDI_I_003 | AE67: =VLOOKUP(AD67,'Axe 2 Règles de gestion'!$D$2:$F$564,3, FALSE) -> La demande doit être appuyée d'un certificat médical attestant que la personne accompagnée souffre d'une pathologie mettant en jeu le pronostic vital ou en phase avancée ou terminale d'une affection grave et incurable, quelle qu'en soit la cause. | AF67: CDI_I_004 | AG67: =VLOOKUP(AF67,'Axe 2 Règles de gestion'!$D$2:$F$564,3, FALSE) -> Le congé peut être fractionné ou pris de manière continue. | AT67: CDI_D_121 | AU67: =VLOOKUP(AT67,'Axe 2 Règles de gestion'!$D$2:$F$564,3, FALSE) -> Le congé de solidarité familiale, ou son renouvellement, est accordé pour une durée réelle maximale de trois mois. | AV67: CDI_D_521 | AW67: =VLOOKUP(AV67,'Axe 2 Règles de gestion'!$D$2:$F$564,3, FALSE) -> Le congé de solidarité familiale, ou son renouvellement, est accordé pour une durée prévisionnelle maximale de trois mois. | AX67: CDI_D_122 | AY67: =VLOOKUP(AX67,'Axe 2 Règles de gestion'!$D$2:$F$564,3, FALSE) -> Le congé de solidarité familiale peut être fractionné mais ne peut, renouvellement inclus, excéder les 6 mois. | AZ67: CDI_D_123 | BA67: =VLOOKUP(AZ67,'Axe 2 Règles de gestion'!$D$2:$F$564,3, FALSE) -> Le congé de solidarité familiale peut être fractionné mais chaque période doit être d'une durée réelle minimale de 7 jours consécutifs. | BB67: CDI_D_601 | BC67: =VLOOKUP(BB67,'Axe 2 Règles de gestion'!$D$2:$F$564,3, FALSE) -> Le congé de solidarité familiale peut être fractionné mais chaque période doit être d'une durée prévisionnelle minimale de 7 jours consécutifs. | BD67: CDI_D_117 | BE67: =VLOOKUP(BD67,'Axe 2 Règles de gestion'!$D$2:$F$564,3, FALSE) -> L'agent doit être en activité. | BF67: ABS_C_002 | BG67: =VLOOKUP(BF67,'Axe 2 Règles de gestion'!$D$2:$F$564,3, FALSE) -> La date de début du congé/absence doit être postérieure ou égale à la date de début du lien juridique. | BH67: ABS_C_003 | BI67: =VLOOKUP(BH67,'Axe 2 Règles de gestion'!$D$2:$F$564,3, FALSE) -> La date de début du congé/absence doit être antérieure ou égale à la date de fin réelle du congé/absence. | BJ67: ABS_C_004 | BK67: =VLOOKUP(BJ67,'Axe 2 Règles de gestion'!$D$2:$F$564,3, FALSE) -> La date de début du congé/absence doit être antérieure ou égale à la date de fin prévisionnelle du congé/absence. | BL67: ABS_C_005 | BM67: =VLOOKUP(BL67,'Axe 2 Règles de gestion'!$D$2:$F$564,3, FALSE) -> La date de fin réelle du congé/absence doit être antérieure ou égale à la date limite de fin réelle ou prévisionnelle du lien juridique. | BN67: ABS_C_006 | BO67: =VLOOKUP(BN67,'Axe 2 Règles de gestion'!$D$2:$F$564,3, FALSE) -> La date de fin prévisionnelle du congé/absence doit être antérieure ou égale à la date limite de fin réelle ou prévisionnelle du lien juridique. | BP67: ABS_C_007 | BQ67: =VLOOKUP(BP67,'Axe 2 Règles de gestion'!$D$2:$F$564,3, FALSE) -> La date de fin réelle du congé/absence doit être antérieure à la date limite de départ à la retraite. | BR67: ABS_C_008 | BS67: =VLOOKUP(BR67,'Axe 2 Règles de gestion'!$D$2:$F$564,3, FALSE) -> La date de fin prévisionnelle du congé/absence doit être antérieure à la date limite de départ à la retraite. | BT67: ABS_C_009 | BU67: =VLOOKUP(BT67,'Axe 2 Règles de gestion'!$D$2:$F$564,3, FALSE) -> La date de fin réelle ou la date de fin prévisionnelle du congé/absence doit être saisie. | BV67: ABS_C_019 | BW67: =VLOOKUP(BV67,'Axe 2 Règles de gestion'!$D$2:$F$564,3, FALSE) -> Si l'absence ne commence pas par une demi-journée et si l'absence précédente ne finit pas par une demi journée, la date de début de l'absence saisie est postérieure à la date de fin réelle de l'absence précédente. | BX67: ABS_C_020 | BY67: =VLOOKUP(BX67,'Axe 2 Règles de gestion'!$D$2:$F$564,3, FALSE) -> Si l'absence ne commence pas par une demi-journée et si l'absence précédente ne finit pas par une demi journée, la date de début de l'absence saisie est postérieure à la date de fin prévisionnelle de l'absence précédente. | BZ67: ABS_C_023 | CA67: =VLOOKUP(BZ67,'Axe 2 Règles de gestion'!$D$2:$F$564,3, FALSE) -> L'état du congé est renseigné. | CB67: ABS_C_026 | CC67: =VLOOKUP(CB67,'Axe 2 Règles de gestion'!$D$2:$F$564,3, FALSE) -> Dans le cas d'un congé autre que CLM, CLD, CGM et CITIS, l'indicateur de requalification doit être à non et les impacts spécifiques à la requalification ne doivent pas être mobilisés ou l'impact rémunération est vide. | CD67: ABS_C_065 | CE67: =VLOOKUP(CD67,'Axe 2 Règles de gestion'!$D$2:$F$564,3, FALSE) -> L'agent en congé de présence parentale / congé de proche aidant / congé de solidarité familiale ne peut se voir accorder de manière simultanée un temps partiel pour congé de présence parentale / pour congé de proche aidant / pour congé de solidarité familiale. | CH67: 2025-118
