Workbook

Sheet Mode opératoire
B1: MODE OPERATOIRE
B2: La transaction s'effectue pour l'évènement E0466 'Compte épargne temps' au niveau des sous rubriques : - Compte épargne temps global - Opérations CET La transaction s'effectue pour l'évènement E0468 'Compte épargne temps transitoire' au niveau dessous rubriques : - Compte épargne temps transitoire - Opérations CET La transaction s'effectue pour l'évènement E0469 'Compte épargne temps - Opérations d'inventaire' au niveau de la sous rubrique : - Jours demandés restant à payer

Sheet Axe 1 Enchainement des RG
A1: Version | B1: Type de mise à jour | C1: Date de mise à jour | D1: Identifiant Domaine | E1: Libellé du Domaine | F1: Identifiant Sous-domaine | G1: Libellé du Sous-domaine | H1: Identifiant Evénement | I1: Libellé de l'évènement | J1: Libellé condition déclenchement Evènement | K1: Condition déclenchement Evènement | L1: Identifiant type d'évènement | M1: Libellé type d'évènement | N1: Type de mise à jour | O1: Libellé condition déclenchement Type Evènement | P1: Condition déclenchement Type Evènement | Q1: Libellé Population | R1: Codification Population | S1: Général / Particulier | T1: Passant / Exclu | U1: Date de début | V1: Date de fin | W1: Règles mobilisées | X1: Identifiant Règle de contrôle intellectuel 1 | Y1: Libellé Règle de contrôle intellectuel 1 | Z1: Identifiant Règle de contrôle intellectuel 2 | AA1: Libellé Règle de contrôle intellectuel 2 | AB1: Identifiant Règle de contrôle intellectuel 3 | AC1: Libellé Règle de contrôle intellectuel 3 | AD1: Identifiant Règle de contrôle intellectuel 4 | AE1: Libellé Règle de contrôle intellectuel 4 | AF1: Identifiant Règle de contrôle intellectuel 5 | AG1: Libellé Règle de contrôle intellectuel 5 | AH1: Identifiant Règle de contrôle intellectuel 6 | AI1: Libellé Règle de contrôle intellectuel 6 | AJ1: Identifiant Règle de contrôle intellectuel 7 | AK1: Libellé Règle de contrôle intellectuel 7 | AL1: Identifiant Règle de condition 1 | AM1: Libellé Règle de condition 1 | AN1: Identifiant Règle de condition 2 | AO1: Libellé Règle de condition 2 | AP1: Identifiant Règle de condition 3 | AQ1: Libellé Règle de condition 3 | AR1: Identifiant Règle de condition 4 | AS1: Libellé Règle de condition 4 | AT1: Identifiant Règle de condition 5 | AU1: Libellé Règle de condition 5 | AV1: Identifiant Règle de condition 6 | AW1: Libellé Règle de condition 6 | AX1: Identifiant Règle de condition 7 | AY1: Libellé Règle de condition 7 | AZ1: Identifiant Règle de condition 8 | BA1: Libellé Règle de condition 8 | BB1: Identifiant Règle de contrôle 1 | BC1: Libellé Règle de contrôle 1 | BD1: Identifiant Règle de contrôle 2 | BE1: Libellé Règle de contrôle 2 | BF1: Identifiant Règle de contrôle 3 | BG1: Libellé Règle de contrôle 3 | BH1: Identifiant Règle de contrôle 4 | BI1: Libellé Règle de contrôle 4 | BJ1: Identifiant Règle de contrôle 5 | BK1: Libellé Règle de contrôle 5 | BL1: Identifiant Règle de contrôle 6 | BM1: Libellé Règle de contrôle 6 | BN1: Identifiant Règle de contrôle 7 | BO1: Libellé Règle de contrôle 7 | BP1: Identifiant Règle de contrôle 8 | BQ1: Libellé Règle de contrôle 8 | BR1: Identifiant Règle de contrôle 9 | BS1: Libellé Règle de contrôle 9 | BT1: Identifiant Règle de contrôle 10 | BU1: Libellé Règle de contrôle 10 | BV1: FIME | BW1: Statut de travail
A2: 24.10.00 | B2: M | C2: 45628.699 | D2: D0007 | E2: Congés/Absence | F2: S0049 | G2: Compte épargne temps | H2: E0466 | I2: Compte épargne temps | J2: La date d'observation saisie du CET est non vide | K2: A_CET_DAGCET [Saisi] <> Vide | L2: T1128 | M2: Compte épargne temps - Ouverture sans opération | N2: Création Modification | O2: La date de l'opération saisie est vide. | P2: A_CET_DOOCET [Saisi] = Vide | Q2: Titulaire ou magistrat | R2: P0001 | S2: Général | T2: Passant | U2: 40725 | V2: 40725 | W2: CET_I_002 ET CET_I_001 ET CET_I_004 ET CET_D_020 ET CET_D_059 ET CET_C_004 ET CET_C_010 ET CET_C_011 ET CET_C_017 ET CET_C_019 ET CET_C_031 | X2: CET_I_002 | Y2: =VLOOKUP(X2,'Axe 2 Règles de gestion'!$D$2:$F$84,3, FALSE) -> L'agent doit être employé de manière continue et avoir accompli au moins 1 an de service. | Z2: CET_I_001 | AA2: =VLOOKUP(Z2,'Axe 2 Règles de gestion'!$D$2:$F$84,3, FALSE) -> L'agent demande l'ouverture d'un compte épargne-temps auprès du service gestionnaire. | AB2: CET_I_004 | AC2: =VLOOKUP(AB2,'Axe 2 Règles de gestion'!$D$2:$F$84,3, FALSE) -> Un arrêté de la fonction publique, du budget et du ministre intéressé, pris après consultation du comité technique paritaire, détermine, dans le respect de l'intérêt du service, les règles de fonctionnement du compte épargne-temps. | AL2: CET_D_020 | AM2: =VLOOKUP(AL2,'Axe 2 Règles de gestion'!$D$2:$F$84,3, FALSE) -> L'agent ne doit pas être soumis à des obligations de service fixées par le statut particulier de son corps ou par un décret commun à plusieurs corps. | AN2: CET_D_059 | AO2: =VLOOKUP(AN2,'Axe 2 Règles de gestion'!$D$2:$F$84,3, FALSE) -> Le nombre de jours maximum du compteur global doit être inférieur ou égal à 60 jours à l'issue de l'exercice du droit d'option. | BB2: CET_C_004 | BC2: =VLOOKUP(BB2,'Axe 2 Règles de gestion'!$D$2:$F$84,3, FALSE) -> Le nombre de jours de l'opération doit être inférieur ou égal au nombre de jours du compteur global du CET. | BD2: CET_C_010 | BE2: =VLOOKUP(BD2,'Axe 2 Règles de gestion'!$D$2:$F$84,3, FALSE) -> La date de fermeture du CET doit être antérieure ou égale à la date limite de départ en retraite. | BF2: CET_C_011 | BG2: =VLOOKUP(BF2,'Axe 2 Règles de gestion'!$D$2:$F$84,3, FALSE) -> La date de fermeture du CET doit être antérieure ou égale à la date de fin réelle ou prévisionnelle du lien juridique. | BH2: CET_C_017 | BI2: =VLOOKUP(BH2,'Axe 2 Règles de gestion'!$D$2:$F$84,3, FALSE) -> La date d'ouverture du compte épargne temps global doit être postérieure ou égale à la date d'entrée dans le SIRH. | BJ2: CET_C_019 | BK2: =VLOOKUP(BJ2,'Axe 2 Règles de gestion'!$D$2:$F$84,3, FALSE) -> La date d'ouverture du CET doit être renseignée. | BL2: CET_C_031 | BM2: =VLOOKUP(BL2,'Axe 2 Règles de gestion'!$D$2:$F$84,3, FALSE) -> Les champs "Origine", "Nombre de jours de l'opération", "Nombre de jours pour valorisation financière" et "Nombre de jours pour cotisation RAFP" ne doivent pas être renseignés.
A3: 20.10.00 | B3: M | C3: 44053.458 | D3: D0007 | E3: Congés/Absence | F3: S0049 | G3: Compte épargne temps | H3: E0466 | I3: Compte épargne temps | J3: La date d'observation saisie du CET est non vide | K3: A_CET_DAGCET [Saisi] <> Vide | L3: T1129 | M3: Compte épargne temps - Ouverture et opération "Consommation" | N3: Création Modification | O3: La date de l'opération saisie est non vide et le sens de l'opération est "Consommé". | P3: A_CET_DOOCET [Saisi] <> Vide ET A_CET_SEOCET [Saisi] = 'C' | Q3: Titulaire ou magistrat | R3: P0001 | S3: Général | T3: Passant | U3: 40725 | V3: 43435 | W3: CET_I_002 ET CET_I_001 ET CET_I_004 ET CET_I_011 ET CET_I_012 ET CET_I_016 ET CET_D_020 ET CET_D_059 ET CET_D_055 ET CET_D_300 ET CET_C_004 ET CET_C_010 ET CET_C_011 ET CET_C_017 ET CET_C_019 ET CET_C_024 ET CET_C_027 | X3: CET_I_002 | Y3: =VLOOKUP(X3,'Axe 2 Règles de gestion'!$D$2:$F$84,3, FALSE) -> L'agent doit être employé de manière continue et avoir accompli au moins 1 an de service. | Z3: CET_I_001 | AA3: =VLOOKUP(Z3,'Axe 2 Règles de gestion'!$D$2:$F$84,3, FALSE) -> L'agent demande l'ouverture d'un compte épargne-temps auprès du service gestionnaire. | AB3: CET_I_004 | AC3: =VLOOKUP(AB3,'Axe 2 Règles de gestion'!$D$2:$F$84,3, FALSE) -> Un arrêté de la fonction publique, du budget et du ministre intéressé, pris après consultation du comité technique paritaire, détermine, dans le respect de l'intérêt du service, les règles de fonctionnement du compte épargne-temps. | AD3: CET_I_011 | AE3: =VLOOKUP(AD3,'Axe 2 Règles de gestion'!$D$2:$F$84,3, FALSE) -> L'agent exerce son droit d'option au plus tard le 31 janvier de l'année suivant la période de référence de l'épargne. | AF3: CET_I_012 | AG3: =VLOOKUP(AF3,'Axe 2 Règles de gestion'!$D$2:$F$84,3, FALSE) -> L'agent indique au service gestionnaire son choix entre maintien sur le compte en vue de congés, indemnisation et épargne-retraite, surtout s'il souhaite conserver ces jours sur son compte épargne-temps. | AH3: CET_I_016 | AI3: =VLOOKUP(AH3,'Axe 2 Règles de gestion'!$D$2:$F$84,3, FALSE) -> En l'absence d'exercice d'une option par l'agent, les jours au-delà de 15 sont automatiquement placés au titre du régime de retraite additionnelle de la fonction publique. | AL3: CET_D_020 | AM3: =VLOOKUP(AL3,'Axe 2 Règles de gestion'!$D$2:$F$84,3, FALSE) -> L'agent ne doit pas être soumis à des obligations de service fixées par le statut particulier de son corps ou par un décret commun à plusieurs corps. | AN3: CET_D_059 | AO3: =VLOOKUP(AN3,'Axe 2 Règles de gestion'!$D$2:$F$84,3, FALSE) -> Le nombre de jours maximum du compteur global doit être inférieur ou égal à 60 jours à l'issue de l'exercice du droit d'option. | AP3: CET_D_055 | AQ3: =VLOOKUP(AP3,'Axe 2 Règles de gestion'!$D$2:$F$84,3, FALSE) -> La différence entre le nombre de jours du compteur global du CET et le nombre de jours pour valorisation financière doit être strictement supérieure à 20 jours. | AR3: CET_D_300 | AS3: =VLOOKUP(AR3,'Axe 2 Règles de gestion'!$D$2:$F$84,3, FALSE) -> La différence entre le nombre de jours du compteur global du CET et le nombre de jours pour cotisation RAFP doit être strictement supérieure à 20 jours. | BB3: CET_C_004 | BC3: =VLOOKUP(BB3,'Axe 2 Règles de gestion'!$D$2:$F$84,3, FALSE) -> Le nombre de jours de l'opération doit être inférieur ou égal au nombre de jours du compteur global du CET. | BD3: CET_C_010 | BE3: =VLOOKUP(BD3,'Axe 2 Règles de gestion'!$D$2:$F$84,3, FALSE) -> La date de fermeture du CET doit être antérieure ou égale à la date limite de départ en retraite. | BF3: CET_C_011 | BG3: =VLOOKUP(BF3,'Axe 2 Règles de gestion'!$D$2:$F$84,3, FALSE) -> La date de fermeture du CET doit être antérieure ou égale à la date de fin réelle ou prévisionnelle du lien juridique. | BH3: CET_C_017 | BI3: =VLOOKUP(BH3,'Axe 2 Règles de gestion'!$D$2:$F$84,3, FALSE) -> La date d'ouverture du compte épargne temps global doit être postérieure ou égale à la date d'entrée dans le SIRH. | BJ3: CET_C_019 | BK3: =VLOOKUP(BJ3,'Axe 2 Règles de gestion'!$D$2:$F$84,3, FALSE) -> La date d'ouverture du CET doit être renseignée. | BL3: CET_C_024 | BM3: =VLOOKUP(BL3,'Axe 2 Règles de gestion'!$D$2:$F$84,3, FALSE) -> Lorsque le sens de l'opération est à "consommé", le compteur global saisi est égal au compteur global de l'occurrence précédente duquel sont soustraits les jours consommés en congés, les jours pour valorisation financière et les jours pour cotisation RAFP. | BN3: CET_C_027 | BO3: =VLOOKUP(BN3,'Axe 2 Règles de gestion'!$D$2:$F$84,3, FALSE) -> Lorsque le sens de l'opération est égal à "consommé", l'origine des jours n'est pas à renseigner.
A4: 24.10.00 | B4: M | C4: 45628.724 | D4: D0007 | E4: Congés/Absence | F4: S0049 | G4: Compte épargne temps | H4: E0466 | I4: Compte épargne temps | J4: La date d'observation saisie du CET est non vide | K4: A_CET_DAGCET [Saisi] <> Vide | L4: T1129 | M4: Compte épargne temps - Ouverture et opération "Consommation" | N4: Création Modification | O4: La date de l'opération saisie est non vide et le sens de l'opération est "Consommé". | P4: A_CET_DOOCET [Saisi] <> Vide ET A_CET_SEOCET [Saisi] = 'C' | Q4: Titulaire ou magistrat | R4: P0001 | S4: Général | T4: Passant | U4: 43436 | V4: 43436 | W4: CET_I_002 ET CET_I_001 ET CET_I_004 ET CET_I_011 ET CET_I_012 ET CET_I_016 ET CET_D_020 ET CET_D_059 ET CET_D_056 ET CET_D_301 ET CET_C_004 ET CET_C_010 ET CET_C_011 ET CET_C_017 ET CET_C_019 ET CET_C_024 ET CET_C_027 | X4: CET_I_002 | Y4: =VLOOKUP(X4,'Axe 2 Règles de gestion'!$D$2:$F$84,3, FALSE) -> L'agent doit être employé de manière continue et avoir accompli au moins 1 an de service. | Z4: CET_I_001 | AA4: =VLOOKUP(Z4,'Axe 2 Règles de gestion'!$D$2:$F$84,3, FALSE) -> L'agent demande l'ouverture d'un compte épargne-temps auprès du service gestionnaire. | AB4: CET_I_004 | AC4: =VLOOKUP(AB4,'Axe 2 Règles de gestion'!$D$2:$F$84,3, FALSE) -> Un arrêté de la fonction publique, du budget et du ministre intéressé, pris après consultation du comité technique paritaire, détermine, dans le respect de l'intérêt du service, les règles de fonctionnement du compte épargne-temps. | AD4: CET_I_011 | AE4: =VLOOKUP(AD4,'Axe 2 Règles de gestion'!$D$2:$F$84,3, FALSE) -> L'agent exerce son droit d'option au plus tard le 31 janvier de l'année suivant la période de référence de l'épargne. | AF4: CET_I_012 | AG4: =VLOOKUP(AF4,'Axe 2 Règles de gestion'!$D$2:$F$84,3, FALSE) -> L'agent indique au service gestionnaire son choix entre maintien sur le compte en vue de congés, indemnisation et épargne-retraite, surtout s'il souhaite conserver ces jours sur son compte épargne-temps. | AH4: CET_I_016 | AI4: =VLOOKUP(AH4,'Axe 2 Règles de gestion'!$D$2:$F$84,3, FALSE) -> En l'absence d'exercice d'une option par l'agent, les jours au-delà de 15 sont automatiquement placés au titre du régime de retraite additionnelle de la fonction publique. | AL4: CET_D_020 | AM4: =VLOOKUP(AL4,'Axe 2 Règles de gestion'!$D$2:$F$84,3, FALSE) -> L'agent ne doit pas être soumis à des obligations de service fixées par le statut particulier de son corps ou par un décret commun à plusieurs corps. | AN4: CET_D_059 | AO4: =VLOOKUP(AN4,'Axe 2 Règles de gestion'!$D$2:$F$84,3, FALSE) -> Le nombre de jours maximum du compteur global doit être inférieur ou égal à 60 jours à l'issue de l'exercice du droit d'option. | AP4: CET_D_056 | AQ4: =VLOOKUP(AP4,'Axe 2 Règles de gestion'!$D$2:$F$84,3, FALSE) -> La différence entre le nombre de jours du compteur global du CET et le nombre de jours pour valorisation financière doit être strictement supérieure à 15 jours. | AR4: CET_D_301 | AS4: =VLOOKUP(AR4,'Axe 2 Règles de gestion'!$D$2:$F$84,3, FALSE) -> La différence entre le nombre de jours du compteur global du CET et le nombre de jours pour cotisation RAFP doit être strictement supérieure à 15 jours. | BB4: CET_C_004 | BC4: =VLOOKUP(BB4,'Axe 2 Règles de gestion'!$D$2:$F$84,3, FALSE) -> Le nombre de jours de l'opération doit être inférieur ou égal au nombre de jours du compteur global du CET. | BD4: CET_C_010 | BE4: =VLOOKUP(BD4,'Axe 2 Règles de gestion'!$D$2:$F$84,3, FALSE) -> La date de fermeture du CET doit être antérieure ou égale à la date limite de départ en retraite. | BF4: CET_C_011 | BG4: =VLOOKUP(BF4,'Axe 2 Règles de gestion'!$D$2:$F$84,3, FALSE) -> La date de fermeture du CET doit être antérieure ou égale à la date de fin réelle ou prévisionnelle du lien juridique. | BH4: CET_C_017 | BI4: =VLOOKUP(BH4,'Axe 2 Règles de gestion'!$D$2:$F$84,3, FALSE) -> La date d'ouverture du compte épargne temps global doit être postérieure ou égale à la date d'entrée dans le SIRH. | BJ4: CET_C_019 | BK4: =VLOOKUP(BJ4,'Axe 2 Règles de gestion'!$D$2:$F$84,3, FALSE) -> La date d'ouverture du CET doit être renseignée. | BL4: CET_C_024 | BM4: =VLOOKUP(BL4,'Axe 2 Règles de gestion'!$D$2:$F$84,3, FALSE) -> Lorsque le sens de l'opération est à "consommé", le compteur global saisi est égal au compteur global de l'occurrence précédente duquel sont soustraits les jours consommés en congés, les jours pour valorisation financière et les jours pour cotisation RAFP. | BN4: CET_C_027 | BO4: =VLOOKUP(BN4,'Axe 2 Règles de gestion'!$D$2:$F$84,3, FALSE) -> Lorsque le sens de l'opération est égal à "consommé", l'origine des jours n'est pas à renseigner.
A5: 18.10.00 | B5: M | C5: 43509.73 | D5: D0007 | E5: Congés/Absence | F5: S0049 | G5: Compte épargne temps | H5: E0466 | I5: Compte épargne temps | J5: La date d'observation saisie du CET est non vide | K5: A_CET_DAGCET [Saisi] <> Vide | L5: T1130 | M5: Compte épargne temps - Ouverture et opération "Versement" | N5: Création Modification | O5: La date de l'opération saisie est non vide et le sens de l'opération est "Versé". | P5: A_CET_DOOCET [Saisi] <> Vide ET A_CET_SEOCET [Saisi] = 'V' | Q5: Titulaire ou magistrat | R5: P0001 | S5: Général | T5: Passant | U5: 40725 | V5: 43435 | W5: CET_I_002 ET CET_I_001 ET CET_I_004 ET CET_I_006 ET CET_I_010 ET CET_D_012 ET CET_D_205 ET CET_D_059 ET CET_D_014 ET CET_D_210 ET CET_D_900 ET CET_D_959 ET CET_C_004 ET CET_C_010 ET CET_C_011 ET CET_C_017 ET CET_C_019 ET CET_C_023 ET CET_C_026 | X5: CET_I_002 | Y5: =VLOOKUP(X5,'Axe 2 Règles de gestion'!$D$2:$F$84,3, FALSE) -> L'agent doit être employé de manière continue et avoir accompli au moins 1 an de service. | Z5: CET_I_001 | AA5: =VLOOKUP(Z5,'Axe 2 Règles de gestion'!$D$2:$F$84,3, FALSE) -> L'agent demande l'ouverture d'un compte épargne-temps auprès du service gestionnaire. | AB5: CET_I_004 | AC5: =VLOOKUP(AB5,'Axe 2 Règles de gestion'!$D$2:$F$84,3, FALSE) -> Un arrêté de la fonction publique, du budget et du ministre intéressé, pris après consultation du comité technique paritaire, détermine, dans le respect de l'intérêt du service, les règles de fonctionnement du compte épargne-temps. | AD5: CET_I_006 | AE5: =VLOOKUP(AD5,'Axe 2 Règles de gestion'!$D$2:$F$84,3, FALSE) -> Si le statut de l'agent est régi par le Code de justice administrative, le compte épargne-temps est ouvert de droit après sa formation complémentaire de 6 mois. Il est alimenté annuellement par report de 8 jours de réduction de temps de travail. | AF5: CET_I_010 | AG5: =VLOOKUP(AF5,'Axe 2 Règles de gestion'!$D$2:$F$84,3, FALSE) -> L'agent demande au service gestionnaire l'alimentation de son compte épargne-temps selon les modalités d'usage. | AL5: CET_D_012 | AM5: =VLOOKUP(AL5,'Axe 2 Règles de gestion'!$D$2:$F$84,3, FALSE) -> Le CET est alimenté par le report de jours de réduction du temps de travail (ARTT), jours supplémentaires hors période et par le report de congés annuels, tels que prévus par le décret du 26 octobre 1984. | AN5: CET_D_205 | AO5: =VLOOKUP(AN5,'Axe 2 Règles de gestion'!$D$2:$F$84,3, FALSE) -> Le CET est alimenté, pour les personnels relevant du décret du 28 mars 1967, par le report de congés annuels dont ils bénéficient au titre du pays dans lequel ils sont affectés. | AP5: CET_D_059 | AQ5: =VLOOKUP(AP5,'Axe 2 Règles de gestion'!$D$2:$F$84,3, FALSE) -> Le nombre de jours maximum du compteur global doit être inférieur ou égal à 60 jours à l'issue de l'exercice du droit d'option. | AR5: CET_D_014 | AS5: =VLOOKUP(AR5,'Axe 2 Règles de gestion'!$D$2:$F$84,3, FALSE) -> Le nombre de jours de congés pris dans l'année doit être supérieur ou égal à 20 jours. | AT5: CET_D_210 | AU5: =VLOOKUP(AT5,'Axe 2 Règles de gestion'!$D$2:$F$84,3, FALSE) -> Le nombre de jours de congés pris dans l'année doit être supérieur ou égal à 20 jours. | AV5: CET_D_900 | AW5: =VLOOKUP(AV5,'Axe 2 Règles de gestion'!$D$2:$F$84,3, FALSE) -> Si le compteur global du CET est inférieur à 20 jours et le sens de l'opération est égal à "versé" alors le nombre de jours du compteur global du CET après saisie doit être inférieur ou égal à 30 jours. | AX5: CET_D_959 | AY5: =VLOOKUP(AX5,'Axe 2 Règles de gestion'!$D$2:$F$84,3, FALSE) -> Si le compte épargne global est supérieur ou égal à 20 jours et le sens de l'opération est égal à "versé" alors le nombre de jours de l'opération conservés en congés doit être inférieur ou égal à 10 jours. | BB5: CET_C_004 | BC5: =VLOOKUP(BB5,'Axe 2 Règles de gestion'!$D$2:$F$84,3, FALSE) -> Le nombre de jours de l'opération doit être inférieur ou égal au nombre de jours du compteur global du CET. | BD5: CET_C_010 | BE5: =VLOOKUP(BD5,'Axe 2 Règles de gestion'!$D$2:$F$84,3, FALSE) -> La date de fermeture du CET doit être antérieure ou égale à la date limite de départ en retraite. | BF5: CET_C_011 | BG5: =VLOOKUP(BF5,'Axe 2 Règles de gestion'!$D$2:$F$84,3, FALSE) -> La date de fermeture du CET doit être antérieure ou égale à la date de fin réelle ou prévisionnelle du lien juridique. | BH5: CET_C_017 | BI5: =VLOOKUP(BH5,'Axe 2 Règles de gestion'!$D$2:$F$84,3, FALSE) -> La date d'ouverture du compte épargne temps global doit être postérieure ou égale à la date d'entrée dans le SIRH. | BJ5: CET_C_019 | BK5: =VLOOKUP(BJ5,'Axe 2 Règles de gestion'!$D$2:$F$84,3, FALSE) -> La date d'ouverture du CET doit être renseignée. | BL5: CET_C_023 | BM5: =VLOOKUP(BL5,'Axe 2 Règles de gestion'!$D$2:$F$84,3, FALSE) -> Lorsque le sens de l'opération est à "Versé", le compteur global saisi est égal au compteur global de l'occurrence précédente auquel sont ajoutés les jours versés. | BN5: CET_C_026 | BO5: =VLOOKUP(BN5,'Axe 2 Règles de gestion'!$D$2:$F$84,3, FALSE) -> Lorsque le sens de l'opération est égal à "versé", le nombre de jours pour valorisation financière et le nombre de jours pour cotisation RAFP ne doivent pas être renseignés.
A6: 24.10.00 | B6: M | C6: 45628.701 | D6: D0007 | E6: Congés/Absence | F6: S0049 | G6: Compte épargne temps | H6: E0466 | I6: Compte épargne temps | J6: La date d'observation saisie du CET est non vide | K6: A_CET_DAGCET [Saisi] <> Vide | L6: T1130 | M6: Compte épargne temps - Ouverture et opération "Versement" | N6: Création Modification | O6: La date de l'opération saisie est non vide et le sens de l'opération est "Versé". | P6: A_CET_DOOCET [Saisi] <> Vide ET A_CET_SEOCET [Saisi] = 'V' | Q6: Titulaire ou magistrat | R6: P0001 | S6: Général | T6: Passant | U6: 43436 | V6: 43436 | W6: CET_I_002 ET CET_I_001 ET CET_I_004 ET CET_I_006 ET CET_I_010 ET CET_D_012 ET CET_D_205 ET CET_D_059 ET CET_D_014 ET CET_D_210 ET CET_D_901 ET CET_D_960 ET CET_C_004 ET CET_C_010 ET CET_C_011 ET CET_C_017 ET CET_C_019 ET CET_C_023 ET CET_C_026 | X6: CET_I_002 | Y6: =VLOOKUP(X6,'Axe 2 Règles de gestion'!$D$2:$F$84,3, FALSE) -> L'agent doit être employé de manière continue et avoir accompli au moins 1 an de service. | Z6: CET_I_001 | AA6: =VLOOKUP(Z6,'Axe 2 Règles de gestion'!$D$2:$F$84,3, FALSE) -> L'agent demande l'ouverture d'un compte épargne-temps auprès du service gestionnaire. | AB6: CET_I_004 | AC6: =VLOOKUP(AB6,'Axe 2 Règles de gestion'!$D$2:$F$84,3, FALSE) -> Un arrêté de la fonction publique, du budget et du ministre intéressé, pris après consultation du comité technique paritaire, détermine, dans le respect de l'intérêt du service, les règles de fonctionnement du compte épargne-temps. | AD6: CET_I_006 | AE6: =VLOOKUP(AD6,'Axe 2 Règles de gestion'!$D$2:$F$84,3, FALSE) -> Si le statut de l'agent est régi par le Code de justice administrative, le compte épargne-temps est ouvert de droit après sa formation complémentaire de 6 mois. Il est alimenté annuellement par report de 8 jours de réduction de temps de travail. | AF6: CET_I_010 | AG6: =VLOOKUP(AF6,'Axe 2 Règles de gestion'!$D$2:$F$84,3, FALSE) -> L'agent demande au service gestionnaire l'alimentation de son compte épargne-temps selon les modalités d'usage. | AL6: CET_D_012 | AM6: =VLOOKUP(AL6,'Axe 2 Règles de gestion'!$D$2:$F$84,3, FALSE) -> Le CET est alimenté par le report de jours de réduction du temps de travail (ARTT), jours supplémentaires hors période et par le report de congés annuels, tels que prévus par le décret du 26 octobre 1984. | AN6: CET_D_205 | AO6: =VLOOKUP(AN6,'Axe 2 Règles de gestion'!$D$2:$F$84,3, FALSE) -> Le CET est alimenté, pour les personnels relevant du décret du 28 mars 1967, par le report de congés annuels dont ils bénéficient au titre du pays dans lequel ils sont affectés. | AP6: CET_D_059 | AQ6: =VLOOKUP(AP6,'Axe 2 Règles de gestion'!$D$2:$F$84,3, FALSE) -> Le nombre de jours maximum du compteur global doit être inférieur ou égal à 60 jours à l'issue de l'exercice du droit d'option. | AR6: CET_D_014 | AS6: =VLOOKUP(AR6,'Axe 2 Règles de gestion'!$D$2:$F$84,3, FALSE) -> Le nombre de jours de congés pris dans l'année doit être supérieur ou égal à 20 jours. | AT6: CET_D_210 | AU6: =VLOOKUP(AT6,'Axe 2 Règles de gestion'!$D$2:$F$84,3, FALSE) -> Le nombre de jours de congés pris dans l'année doit être supérieur ou égal à 20 jours. | AV6: CET_D_901 | AW6: =VLOOKUP(AV6,'Axe 2 Règles de gestion'!$D$2:$F$84,3, FALSE) -> Si le compteur global du CET est inférieur à 15 jours et le sens de l'opération est égal à "versé" alors le nombre de jours du compteur global du CET après saisie doit être inférieur ou égal à 25 jours. | AX6: CET_D_960 | AY6: =VLOOKUP(AX6,'Axe 2 Règles de gestion'!$D$2:$F$84,3, FALSE) -> Si le compte épargne global est supérieur ou égal à 15 jours et le sens de l'opération est égal à "versé" alors le nombre de jours de l'opération conservés en congés doit être inférieur ou égal à 10 jours. | BB6: CET_C_004 | BC6: =VLOOKUP(BB6,'Axe 2 Règles de gestion'!$D$2:$F$84,3, FALSE) -> Le nombre de jours de l'opération doit être inférieur ou égal au nombre de jours du compteur global du CET. | BD6: CET_C_010 | BE6: =VLOOKUP(BD6,'Axe 2 Règles de gestion'!$D$2:$F$84,3, FALSE) -> La date de fermeture du CET doit être antérieure ou égale à la date limite de départ en retraite. | BF6: CET_C_011 | BG6: =VLOOKUP(BF6,'Axe 2 Règles de gestion'!$D$2:$F$84,3, FALSE) -> La date de fermeture du CET doit être antérieure ou égale à la date de fin réelle ou prévisionnelle du lien juridique. | BH6: CET_C_017 | BI6: =VLOOKUP(BH6,'Axe 2 Règles de gestion'!$D$2:$F$84,3, FALSE) -> La date d'ouverture du compte épargne temps global doit être postérieure ou égale à la date d'entrée dans le SIRH. | BJ6: CET_C_019 | BK6: =VLOOKUP(BJ6,'Axe 2 Règles de gestion'!$D$2:$F$84,3, FALSE) -> La date d'ouverture du CET doit être renseignée. | BL6: CET_C_023 | BM6: =VLOOKUP(BL6,'Axe 2 Règles de gestion'!$D$2:$F$84,3, FALSE) -> Lorsque le sens de l'opération est à "Versé", le compteur global saisi est égal au compteur global de l'occurrence précédente auquel sont ajoutés les jours versés. | BN6: CET_C_026 | BO6: =VLOOKUP(BN6,'Axe 2 Règles de gestion'!$D$2:$F$84,3, FALSE) -> Lorsque le sens de l'opération est égal à "versé", le nombre de jours pour valorisation financière et le nombre de jours pour cotisation RAFP ne doivent pas être renseignés.
A7: 24.10.00 | B7: M | C7: 45628.701 | D7: D0007 | E7: Congés/Absence | F7: S0049 | G7: Compte épargne temps | H7: E0466 | I7: Compte épargne temps | J7: La date d'observation saisie du CET est non vide | K7: A_CET_DAGCET [Saisi] <> Vide | L7: T1128 | M7: Compte épargne temps - Ouverture sans opération | N7: Création Modification | O7: La date de l'opération saisie est vide. | P7: A_CET_DOOCET [Saisi] = Vide | Q7: Militaire | R7: P0002 | S7: Général | T7: Exclu | U7: 43831 | V7: 43831
A8: 24.10.00 | B8: M | C8: 45628.703 | D8: D0007 | E8: Congés/Absence | F8: S0049 | G8: Compte épargne temps | H8: E0466 | I8: Compte épargne temps | J8: La date d'observation saisie du CET est non vide | K8: A_CET_DAGCET [Saisi] <> Vide | L8: T1129 | M8: Compte épargne temps - Ouverture et opération "Consommation" | N8: Création Modification | O8: La date de l'opération saisie est non vide et le sens de l'opération est "Consommé". | P8: A_CET_DOOCET [Saisi] <> Vide ET A_CET_SEOCET [Saisi] = 'C' | Q8: Militaire | R8: P0002 | S8: Général | T8: Exclu | U8: 43831 | V8: 43831
A9: 24.10.00 | B9: M | C9: 45628.703 | D9: D0007 | E9: Congés/Absence | F9: S0049 | G9: Compte épargne temps | H9: E0466 | I9: Compte épargne temps | J9: La date d'observation saisie du CET est non vide | K9: A_CET_DAGCET [Saisi] <> Vide | L9: T1130 | M9: Compte épargne temps - Ouverture et opération "Versement" | N9: Création Modification | O9: La date de l'opération saisie est non vide et le sens de l'opération est "Versé". | P9: A_CET_DOOCET [Saisi] <> Vide ET A_CET_SEOCET [Saisi] = 'V' | Q9: Militaire | R9: P0002 | S9: Général | T9: Exclu | U9: 43831 | V9: 43831
A10: 24.10.00 | B10: M | C10: 45628.699 | D10: D0007 | E10: Congés/Absence | F10: S0049 | G10: Compte épargne temps | H10: E0466 | I10: Compte épargne temps | J10: La date d'observation saisie du CET est non vide | K10: A_CET_DAGCET [Saisi] <> Vide | L10: T1128 | M10: Compte épargne temps - Ouverture sans opération | N10: Création Modification | O10: La date de l'opération saisie est vide. | P10: A_CET_DOOCET [Saisi] = Vide | Q10: Contractuel | R10: P0003 | S10: Général | T10: Passant | U10: 40725 | V10: 40725 | W10: CET_I_002 ET CET_I_001 ET CET_I_004 ET CET_D_020 ET CET_D_059 ET CET_C_004 ET CET_C_010 ET CET_C_011 ET CET_C_017 ET CET_C_019 ET CET_C_031 | X10: CET_I_002 | Y10: =VLOOKUP(X10,'Axe 2 Règles de gestion'!$D$2:$F$84,3, FALSE) -> L'agent doit être employé de manière continue et avoir accompli au moins 1 an de service. | Z10: CET_I_001 | AA10: =VLOOKUP(Z10,'Axe 2 Règles de gestion'!$D$2:$F$84,3, FALSE) -> L'agent demande l'ouverture d'un compte épargne-temps auprès du service gestionnaire. | AB10: CET_I_004 | AC10: =VLOOKUP(AB10,'Axe 2 Règles de gestion'!$D$2:$F$84,3, FALSE) -> Un arrêté de la fonction publique, du budget et du ministre intéressé, pris après consultation du comité technique paritaire, détermine, dans le respect de l'intérêt du service, les règles de fonctionnement du compte épargne-temps. | AL10: CET_D_020 | AM10: =VLOOKUP(AL10,'Axe 2 Règles de gestion'!$D$2:$F$84,3, FALSE) -> L'agent ne doit pas être soumis à des obligations de service fixées par le statut particulier de son corps ou par un décret commun à plusieurs corps. | AN10: CET_D_059 | AO10: =VLOOKUP(AN10,'Axe 2 Règles de gestion'!$D$2:$F$84,3, FALSE) -> Le nombre de jours maximum du compteur global doit être inférieur ou égal à 60 jours à l'issue de l'exercice du droit d'option. | BB10: CET_C_004 | BC10: =VLOOKUP(BB10,'Axe 2 Règles de gestion'!$D$2:$F$84,3, FALSE) -> Le nombre de jours de l'opération doit être inférieur ou égal au nombre de jours du compteur global du CET. | BD10: CET_C_010 | BE10: =VLOOKUP(BD10,'Axe 2 Règles de gestion'!$D$2:$F$84,3, FALSE) -> La date de fermeture du CET doit être antérieure ou égale à la date limite de départ en retraite. | BF10: CET_C_011 | BG10: =VLOOKUP(BF10,'Axe 2 Règles de gestion'!$D$2:$F$84,3, FALSE) -> La date de fermeture du CET doit être antérieure ou égale à la date de fin réelle ou prévisionnelle du lien juridique. | BH10: CET_C_017 | BI10: =VLOOKUP(BH10,'Axe 2 Règles de gestion'!$D$2:$F$84,3, FALSE) -> La date d'ouverture du compte épargne temps global doit être postérieure ou égale à la date d'entrée dans le SIRH. | BJ10: CET_C_019 | BK10: =VLOOKUP(BJ10,'Axe 2 Règles de gestion'!$D$2:$F$84,3, FALSE) -> La date d'ouverture du CET doit être renseignée. | BL10: CET_C_031 | BM10: =VLOOKUP(BL10,'Axe 2 Règles de gestion'!$D$2:$F$84,3, FALSE) -> Les champs "Origine", "Nombre de jours de l'opération", "Nombre de jours pour valorisation financière" et "Nombre de jours pour cotisation RAFP" ne doivent pas être renseignés.
A11: 20.10.00 | B11: M | C11: 44053.458 | D11: D0007 | E11: Congés/Absence | F11: S0049 | G11: Compte épargne temps | H11: E0466 | I11: Compte épargne temps | J11: La date d'observation saisie du CET est non vide | K11: A_CET_DAGCET [Saisi] <> Vide | L11: T1129 | M11: Compte épargne temps - Ouverture et opération "Consommation" | N11: Création Modification | O11: La date de l'opération saisie est non vide et le sens de l'opération est "Consommé". | P11: A_CET_DOOCET [Saisi] <> Vide ET A_CET_SEOCET [Saisi] = 'C' | Q11: Contractuel | R11: P0003 | S11: Général | T11: Passant | U11: 40725 | V11: 43435 | W11: CET_I_002 ET CET_I_001 ET CET_I_004 ET CET_I_011 ET CET_I_013 ET CET_I_017 ET CET_D_020 ET CET_D_059 ET CET_D_055 ET CET_C_004 ET CET_C_010 ET CET_C_011 ET CET_C_017 ET CET_C_019 ET CET_C_022 ET CET_C_024 ET CET_C_027 | X11: CET_I_002 | Y11: =VLOOKUP(X11,'Axe 2 Règles de gestion'!$D$2:$F$84,3, FALSE) -> L'agent doit être employé de manière continue et avoir accompli au moins 1 an de service. | Z11: CET_I_001 | AA11: =VLOOKUP(Z11,'Axe 2 Règles de gestion'!$D$2:$F$84,3, FALSE) -> L'agent demande l'ouverture d'un compte épargne-temps auprès du service gestionnaire. | AB11: CET_I_004 | AC11: =VLOOKUP(AB11,'Axe 2 Règles de gestion'!$D$2:$F$84,3, FALSE) -> Un arrêté de la fonction publique, du budget et du ministre intéressé, pris après consultation du comité technique paritaire, détermine, dans le respect de l'intérêt du service, les règles de fonctionnement du compte épargne-temps. | AD11: CET_I_011 | AE11: =VLOOKUP(AD11,'Axe 2 Règles de gestion'!$D$2:$F$84,3, FALSE) -> L'agent exerce son droit d'option au plus tard le 31 janvier de l'année suivant la période de référence de l'épargne. | AF11: CET_I_013 | AG11: =VLOOKUP(AF11,'Axe 2 Règles de gestion'!$D$2:$F$84,3, FALSE) -> L'agent indique au service gestionnaire son choix entre maintien sur le compte en vue de congés et indemnisation, surtout s'il souhaite conserver ces jours sur son compte épargne-temps. | AH11: CET_I_017 | AI11: =VLOOKUP(AH11,'Axe 2 Règles de gestion'!$D$2:$F$84,3, FALSE) -> En l'absence d'exercice d'une option par l'agent, les jours au-delà de 15 sont automatiquement indemnisés. | AL11: CET_D_020 | AM11: =VLOOKUP(AL11,'Axe 2 Règles de gestion'!$D$2:$F$84,3, FALSE) -> L'agent ne doit pas être soumis à des obligations de service fixées par le statut particulier de son corps ou par un décret commun à plusieurs corps. | AN11: CET_D_059 | AO11: =VLOOKUP(AN11,'Axe 2 Règles de gestion'!$D$2:$F$84,3, FALSE) -> Le nombre de jours maximum du compteur global doit être inférieur ou égal à 60 jours à l'issue de l'exercice du droit d'option. | AP11: CET_D_055 | AQ11: =VLOOKUP(AP11,'Axe 2 Règles de gestion'!$D$2:$F$84,3, FALSE) -> La différence entre le nombre de jours du compteur global du CET et le nombre de jours pour valorisation financière doit être strictement supérieure à 20 jours. | BB11: CET_C_004 | BC11: =VLOOKUP(BB11,'Axe 2 Règles de gestion'!$D$2:$F$84,3, FALSE) -> Le nombre de jours de l'opération doit être inférieur ou égal au nombre de jours du compteur global du CET. | BD11: CET_C_010 | BE11: =VLOOKUP(BD11,'Axe 2 Règles de gestion'!$D$2:$F$84,3, FALSE) -> La date de fermeture du CET doit être antérieure ou égale à la date limite de départ en retraite. | BF11: CET_C_011 | BG11: =VLOOKUP(BF11,'Axe 2 Règles de gestion'!$D$2:$F$84,3, FALSE) -> La date de fermeture du CET doit être antérieure ou égale à la date de fin réelle ou prévisionnelle du lien juridique. | BH11: CET_C_017 | BI11: =VLOOKUP(BH11,'Axe 2 Règles de gestion'!$D$2:$F$84,3, FALSE) -> La date d'ouverture du compte épargne temps global doit être postérieure ou égale à la date d'entrée dans le SIRH. | BJ11: CET_C_019 | BK11: =VLOOKUP(BJ11,'Axe 2 Règles de gestion'!$D$2:$F$84,3, FALSE) -> La date d'ouverture du CET doit être renseignée. | BL11: CET_C_022 | BM11: =VLOOKUP(BL11,'Axe 2 Règles de gestion'!$D$2:$F$84,3, FALSE) -> Lorsque le sens de l'opération est égal à "consommé", le nombre de jours pour la cotisation RAFP n'est pas à renseigner. | BN11: CET_C_024 | BO11: =VLOOKUP(BN11,'Axe 2 Règles de gestion'!$D$2:$F$84,3, FALSE) -> Lorsque le sens de l'opération est à "consommé", le compteur global saisi est égal au compteur global de l'occurrence précédente duquel sont soustraits les jours consommés en congés, les jours pour valorisation financière et les jours pour cotisation RAFP. | BP11: CET_C_027 | BQ11: =VLOOKUP(BP11,'Axe 2 Règles de gestion'!$D$2:$F$84,3, FALSE) -> Lorsque le sens de l'opération est égal à "consommé", l'origine des jours n'est pas à renseigner.
A12: 24.10.00 | B12: M | C12: 45677.426 | D12: D0007 | E12: Congés/Absence | F12: S0049 | G12: Compte épargne temps | H12: E0466 | I12: Compte épargne temps | J12: La date d'observation saisie du CET est non vide | K12: A_CET_DAGCET [Saisi] <> Vide | L12: T1129 | M12: Compte épargne temps - Ouverture et opération "Consommation" | N12: Création Modification | O12: La date de l'opération saisie est non vide et le sens de l'opération est "Consommé". | P12: A_CET_DOOCET [Saisi] <> Vide ET A_CET_SEOCET [Saisi] = 'C' | Q12: Contractuel | R12: P0003 | S12: Général | T12: Passant | U12: 43436 | V12: 43436 | W12: CET_I_002 ET CET_I_001 ET CET_I_004 ET CET_I_011 ET CET_I_013 ET CET_I_017 ET CET_D_020 ET CET_D_059 ET CET_D_056 ET CET_C_004 ET CET_C_010 ET CET_C_011 ET CET_C_017 ET CET_C_019 ET CET_C_022 ET CET_C_024 ET CET_C_027 | X12: CET_I_002 | Y12: =VLOOKUP(X12,'Axe 2 Règles de gestion'!$D$2:$F$84,3, FALSE) -> L'agent doit être employé de manière continue et avoir accompli au moins 1 an de service. | Z12: CET_I_001 | AA12: =VLOOKUP(Z12,'Axe 2 Règles de gestion'!$D$2:$F$84,3, FALSE) -> L'agent demande l'ouverture d'un compte épargne-temps auprès du service gestionnaire. | AB12: CET_I_004 | AC12: =VLOOKUP(AB12,'Axe 2 Règles de gestion'!$D$2:$F$84,3, FALSE) -> Un arrêté de la fonction publique, du budget et du ministre intéressé, pris après consultation du comité technique paritaire, détermine, dans le respect de l'intérêt du service, les règles de fonctionnement du compte épargne-temps. | AD12: CET_I_011 | AE12: =VLOOKUP(AD12,'Axe 2 Règles de gestion'!$D$2:$F$84,3, FALSE) -> L'agent exerce son droit d'option au plus tard le 31 janvier de l'année suivant la période de référence de l'épargne. | AF12: CET_I_013 | AG12: =VLOOKUP(AF12,'Axe 2 Règles de gestion'!$D$2:$F$84,3, FALSE) -> L'agent indique au service gestionnaire son choix entre maintien sur le compte en vue de congés et indemnisation, surtout s'il souhaite conserver ces jours sur son compte épargne-temps. | AH12: CET_I_017 | AI12: =VLOOKUP(AH12,'Axe 2 Règles de gestion'!$D$2:$F$84,3, FALSE) -> En l'absence d'exercice d'une option par l'agent, les jours au-delà de 15 sont automatiquement indemnisés. | AL12: CET_D_020 | AM12: =VLOOKUP(AL12,'Axe 2 Règles de gestion'!$D$2:$F$84,3, FALSE) -> L'agent ne doit pas être soumis à des obligations de service fixées par le statut particulier de son corps ou par un décret commun à plusieurs corps. | AN12: CET_D_059 | AO12: =VLOOKUP(AN12,'Axe 2 Règles de gestion'!$D$2:$F$84,3, FALSE) -> Le nombre de jours maximum du compteur global doit être inférieur ou égal à 60 jours à l'issue de l'exercice du droit d'option. | AP12: CET_D_056 | AQ12: =VLOOKUP(AP12,'Axe 2 Règles de gestion'!$D$2:$F$84,3, FALSE) -> La différence entre le nombre de jours du compteur global du CET et le nombre de jours pour valorisation financière doit être strictement supérieure à 15 jours. | BB12: CET_C_004 | BC12: =VLOOKUP(BB12,'Axe 2 Règles de gestion'!$D$2:$F$84,3, FALSE) -> Le nombre de jours de l'opération doit être inférieur ou égal au nombre de jours du compteur global du CET. | BD12: CET_C_010 | BE12: =VLOOKUP(BD12,'Axe 2 Règles de gestion'!$D$2:$F$84,3, FALSE) -> La date de fermeture du CET doit être antérieure ou égale à la date limite de départ en retraite. | BF12: CET_C_011 | BG12: =VLOOKUP(BF12,'Axe 2 Règles de gestion'!$D$2:$F$84,3, FALSE) -> La date de fermeture du CET doit être antérieure ou égale à la date de fin réelle ou prévisionnelle du lien juridique. | BH12: CET_C_017 | BI12: =VLOOKUP(BH12,'Axe 2 Règles de gestion'!$D$2:$F$84,3, FALSE) -> La date d'ouverture du compte épargne temps global doit être postérieure ou égale à la date d'entrée dans le SIRH. | BJ12: CET_C_019 | BK12: =VLOOKUP(BJ12,'Axe 2 Règles de gestion'!$D$2:$F$84,3, FALSE) -> La date d'ouverture du CET doit être renseignée. | BL12: CET_C_022 | BM12: =VLOOKUP(BL12,'Axe 2 Règles de gestion'!$D$2:$F$84,3, FALSE) -> Lorsque le sens de l'opération est égal à "consommé", le nombre de jours pour la cotisation RAFP n'est pas à renseigner. | BN12: CET_C_024 | BO12: =VLOOKUP(BN12,'Axe 2 Règles de gestion'!$D$2:$F$84,3, FALSE) -> Lorsque le sens de l'opération est à "consommé", le compteur global saisi est égal au compteur global de l'occurrence précédente duquel sont soustraits les jours consommés en congés, les jours pour valorisation financière et les jours pour cotisation RAFP. | BP12: CET_C_027 | BQ12: =VLOOKUP(BP12,'Axe 2 Règles de gestion'!$D$2:$F$84,3, FALSE) -> Lorsque le sens de l'opération est égal à "consommé", l'origine des jours n'est pas à renseigner.
A13: 20.10.00 | B13: M | C13: 44053.463 | D13: D0007 | E13: Congés/Absence | F13: S0049 | G13: Compte épargne temps | H13: E0466 | I13: Compte épargne temps | J13: La date d'observation saisie du CET est non vide | K13: A_CET_DAGCET [Saisi] <> Vide | L13: T1130 | M13: Compte épargne temps - Ouverture et opération "Versement" | N13: Création Modification | O13: La date de l'opération saisie est non vide et le sens de l'opération est "Versé". | P13: A_CET_DOOCET [Saisi] <> Vide ET A_CET_SEOCET [Saisi] = 'V' | Q13: Contractuel | R13: P0003 | S13: Général | T13: Passant | U13: 40725 | V13: 43435 | W13: CET_I_002 ET CET_I_001 ET CET_I_004 ET CET_I_010 ET CET_D_020 ET CET_D_012 ET CET_D_205 ET CET_D_059 ET CET_D_014 ET CET_D_210 ET CET_D_900 ET CET_D_959 ET CET_C_004 ET CET_C_010 ET CET_C_011 ET CET_C_017 ET CET_C_019 ET CET_C_023 ET CET_C_026 | X13: CET_I_002 | Y13: =VLOOKUP(X13,'Axe 2 Règles de gestion'!$D$2:$F$84,3, FALSE) -> L'agent doit être employé de manière continue et avoir accompli au moins 1 an de service. | Z13: CET_I_001 | AA13: =VLOOKUP(Z13,'Axe 2 Règles de gestion'!$D$2:$F$84,3, FALSE) -> L'agent demande l'ouverture d'un compte épargne-temps auprès du service gestionnaire. | AB13: CET_I_004 | AC13: =VLOOKUP(AB13,'Axe 2 Règles de gestion'!$D$2:$F$84,3, FALSE) -> Un arrêté de la fonction publique, du budget et du ministre intéressé, pris après consultation du comité technique paritaire, détermine, dans le respect de l'intérêt du service, les règles de fonctionnement du compte épargne-temps. | AD13: CET_I_010 | AE13: =VLOOKUP(AD13,'Axe 2 Règles de gestion'!$D$2:$F$84,3, FALSE) -> L'agent demande au service gestionnaire l'alimentation de son compte épargne-temps selon les modalités d'usage. | AL13: CET_D_020 | AM13: =VLOOKUP(AL13,'Axe 2 Règles de gestion'!$D$2:$F$84,3, FALSE) -> L'agent ne doit pas être soumis à des obligations de service fixées par le statut particulier de son corps ou par un décret commun à plusieurs corps. | AN13: CET_D_012 | AO13: =VLOOKUP(AN13,'Axe 2 Règles de gestion'!$D$2:$F$84,3, FALSE) -> Le CET est alimenté par le report de jours de réduction du temps de travail (ARTT), jours supplémentaires hors période et par le report de congés annuels, tels que prévus par le décret du 26 octobre 1984. | AP13: CET_D_205 | AQ13: =VLOOKUP(AP13,'Axe 2 Règles de gestion'!$D$2:$F$84,3, FALSE) -> Le CET est alimenté, pour les personnels relevant du décret du 28 mars 1967, par le report de congés annuels dont ils bénéficient au titre du pays dans lequel ils sont affectés. | AR13: CET_D_059 | AS13: =VLOOKUP(AR13,'Axe 2 Règles de gestion'!$D$2:$F$84,3, FALSE) -> Le nombre de jours maximum du compteur global doit être inférieur ou égal à 60 jours à l'issue de l'exercice du droit d'option. | AT13: CET_D_014 | AU13: =VLOOKUP(AT13,'Axe 2 Règles de gestion'!$D$2:$F$84,3, FALSE) -> Le nombre de jours de congés pris dans l'année doit être supérieur ou égal à 20 jours. | AV13: CET_D_210 | AW13: =VLOOKUP(AV13,'Axe 2 Règles de gestion'!$D$2:$F$84,3, FALSE) -> Le nombre de jours de congés pris dans l'année doit être supérieur ou égal à 20 jours. | AX13: CET_D_900 | AY13: =VLOOKUP(AX13,'Axe 2 Règles de gestion'!$D$2:$F$84,3, FALSE) -> Si le compteur global du CET est inférieur à 20 jours et le sens de l'opération est égal à "versé" alors le nombre de jours du compteur global du CET après saisie doit être inférieur ou égal à 30 jours. | AZ13: CET_D_959 | BA13: =VLOOKUP(AZ13,'Axe 2 Règles de gestion'!$D$2:$F$84,3, FALSE) -> Si le compte épargne global est supérieur ou égal à 20 jours et le sens de l'opération est égal à "versé" alors le nombre de jours de l'opération conservés en congés doit être inférieur ou égal à 10 jours. | BB13: CET_C_004 | BC13: =VLOOKUP(BB13,'Axe 2 Règles de gestion'!$D$2:$F$84,3, FALSE) -> Le nombre de jours de l'opération doit être inférieur ou égal au nombre de jours du compteur global du CET. | BD13: CET_C_010 | BE13: =VLOOKUP(BD13,'Axe 2 Règles de gestion'!$D$2:$F$84,3, FALSE) -> La date de fermeture du CET doit être antérieure ou égale à la date limite de départ en retraite. | BF13: CET_C_011 | BG13: =VLOOKUP(BF13,'Axe 2 Règles de gestion'!$D$2:$F$84,3, FALSE) -> La date de fermeture du CET doit être antérieure ou égale à la date de fin réelle ou prévisionnelle du lien juridique. | BH13: CET_C_017 | BI13: =VLOOKUP(BH13,'Axe 2 Règles de gestion'!$D$2:$F$84,3, FALSE) -> La date d'ouverture du compte épargne temps global doit être postérieure ou égale à la date d'entrée dans le SIRH. | BJ13: CET_C_019 | BK13: =VLOOKUP(BJ13,'Axe 2 Règles de gestion'!$D$2:$F$84,3, FALSE) -> La date d'ouverture du CET doit être renseignée. | BL13: CET_C_023 | BM13: =VLOOKUP(BL13,'Axe 2 Règles de gestion'!$D$2:$F$84,3, FALSE) -> Lorsque le sens de l'opération est à "Versé", le compteur global saisi est égal au compteur global de l'occurrence précédente auquel sont ajoutés les jours versés. | BN13: CET_C_026 | BO13: =VLOOKUP(BN13,'Axe 2 Règles de gestion'!$D$2:$F$84,3, FALSE) -> Lorsque le sens de l'opération est égal à "versé", le nombre de jours pour valorisation financière et le nombre de jours pour cotisation RAFP ne doivent pas être renseignés.
A14: 24.10.00 | B14: M | C14: 45628.726 | D14: D0007 | E14: Congés/Absence | F14: S0049 | G14: Compte épargne temps | H14: E0466 | I14: Compte épargne temps | J14: La date d'observation saisie du CET est non vide | K14: A_CET_DAGCET [Saisi] <> Vide | L14: T1130 | M14: Compte épargne temps - Ouverture et opération "Versement" | N14: Création Modification | O14: La date de l'opération saisie est non vide et le sens de l'opération est "Versé". | P14: A_CET_DOOCET [Saisi] <> Vide ET A_CET_SEOCET [Saisi] = 'V' | Q14: Contractuel | R14: P0003 | S14: Général | T14: Passant | U14: 43436 | V14: 43436 | W14: CET_I_002 ET CET_I_001 ET CET_I_004 ET CET_I_010 ET CET_D_020 ET CET_D_012 ET CET_D_205 ET CET_D_059 ET CET_D_014 ET CET_D_210 ET CET_D_901 ET CET_D_960 ET CET_C_004 ET CET_C_010 ET CET_C_011 ET CET_C_017 ET CET_C_019 ET CET_C_023 ET CET_C_026 | X14: CET_I_002 | Y14: =VLOOKUP(X14,'Axe 2 Règles de gestion'!$D$2:$F$84,3, FALSE) -> L'agent doit être employé de manière continue et avoir accompli au moins 1 an de service. | Z14: CET_I_001 | AA14: =VLOOKUP(Z14,'Axe 2 Règles de gestion'!$D$2:$F$84,3, FALSE) -> L'agent demande l'ouverture d'un compte épargne-temps auprès du service gestionnaire. | AB14: CET_I_004 | AC14: =VLOOKUP(AB14,'Axe 2 Règles de gestion'!$D$2:$F$84,3, FALSE) -> Un arrêté de la fonction publique, du budget et du ministre intéressé, pris après consultation du comité technique paritaire, détermine, dans le respect de l'intérêt du service, les règles de fonctionnement du compte épargne-temps. | AD14: CET_I_010 | AE14: =VLOOKUP(AD14,'Axe 2 Règles de gestion'!$D$2:$F$84,3, FALSE) -> L'agent demande au service gestionnaire l'alimentation de son compte épargne-temps selon les modalités d'usage. | AL14: CET_D_020 | AM14: =VLOOKUP(AL14,'Axe 2 Règles de gestion'!$D$2:$F$84,3, FALSE) -> L'agent ne doit pas être soumis à des obligations de service fixées par le statut particulier de son corps ou par un décret commun à plusieurs corps. | AN14: CET_D_012 | AO14: =VLOOKUP(AN14,'Axe 2 Règles de gestion'!$D$2:$F$84,3, FALSE) -> Le CET est alimenté par le report de jours de réduction du temps de travail (ARTT), jours supplémentaires hors période et par le report de congés annuels, tels que prévus par le décret du 26 octobre 1984. | AP14: CET_D_205 | AQ14: =VLOOKUP(AP14,'Axe 2 Règles de gestion'!$D$2:$F$84,3, FALSE) -> Le CET est alimenté, pour les personnels relevant du décret du 28 mars 1967, par le report de congés annuels dont ils bénéficient au titre du pays dans lequel ils sont affectés. | AR14: CET_D_059 | AS14: =VLOOKUP(AR14,'Axe 2 Règles de gestion'!$D$2:$F$84,3, FALSE) -> Le nombre de jours maximum du compteur global doit être inférieur ou égal à 60 jours à l'issue de l'exercice du droit d'option. | AT14: CET_D_014 | AU14: =VLOOKUP(AT14,'Axe 2 Règles de gestion'!$D$2:$F$84,3, FALSE) -> Le nombre de jours de congés pris dans l'année doit être supérieur ou égal à 20 jours. | AV14: CET_D_210 | AW14: =VLOOKUP(AV14,'Axe 2 Règles de gestion'!$D$2:$F$84,3, FALSE) -> Le nombre de jours de congés pris dans l'année doit être supérieur ou égal à 20 jours. | AX14: CET_D_901 | AY14: =VLOOKUP(AX14,'Axe 2 Règles de gestion'!$D$2:$F$84,3, FALSE) -> Si le compteur global du CET est inférieur à 15 jours et le sens de l'opération est égal à "versé" alors le nombre de jours du compteur global du CET après saisie doit être inférieur ou égal à 25 jours. | AZ14: CET_D_960 | BA14: =VLOOKUP(AZ14,'Axe 2 Règles de gestion'!$D$2:$F$84,3, FALSE) -> Si le compte épargne global est supérieur ou égal à 15 jours et le sens de l'opération est égal à "versé" alors le nombre de jours de l'opération conservés en congés doit être inférieur ou égal à 10 jours. | BB14: CET_C_004 | BC14: =VLOOKUP(BB14,'Axe 2 Règles de gestion'!$D$2:$F$84,3, FALSE) -> Le nombre de jours de l'opération doit être inférieur ou égal au nombre de jours du compteur global du CET. | BD14: CET_C_010 | BE14: =VLOOKUP(BD14,'Axe 2 Règles de gestion'!$D$2:$F$84,3, FALSE) -> La date de fermeture du CET doit être antérieure ou égale à la date limite de départ en retraite. | BF14: CET_C_011 | BG14: =VLOOKUP(BF14,'Axe 2 Règles de gestion'!$D$2:$F$84,3, FALSE) -> La date de fermeture du CET doit être antérieure ou égale à la date de fin réelle ou prévisionnelle du lien juridique. | BH14: CET_C_017 | BI14: =VLOOKUP(BH14,'Axe 2 Règles de gestion'!$D$2:$F$84,3, FALSE) -> La date d'ouverture du compte épargne temps global doit être postérieure ou égale à la date d'entrée dans le SIRH. | BJ14: CET_C_019 | BK14: =VLOOKUP(BJ14,'Axe 2 Règles de gestion'!$D$2:$F$84,3, FALSE) -> La date d'ouverture du CET doit être renseignée. | BL14: CET_C_023 | BM14: =VLOOKUP(BL14,'Axe 2 Règles de gestion'!$D$2:$F$84,3, FALSE) -> Lorsque le sens de l'opération est à "Versé", le compteur global saisi est égal au compteur global de l'occurrence précédente auquel sont ajoutés les jours versés. | BN14: CET_C_026 | BO14: =VLOOKUP(BN14,'Axe 2 Règles de gestion'!$D$2:$F$84,3, FALSE) -> Lorsque le sens de l'opération est égal à "versé", le nombre de jours pour valorisation financière et le nombre de jours pour cotisation RAFP ne doivent pas être renseignés.
A15: 24.10.00 | B15: M | C15: 45628.702 | D15: D0007 | E15: Congés/Absence | F15: S0049 | G15: Compte épargne temps | H15: E0466 | I15: Compte épargne temps | J15: La date d'observation saisie du CET est non vide | K15: A_CET_DAGCET [Saisi] <> Vide | L15: T1128 | M15: Compte épargne temps - Ouverture sans opération | N15: Création Modification | O15: La date de l'opération saisie est vide. | P15: A_CET_DOOCET [Saisi] = Vide | Q15: Stagiaire ou auditeur ou élève | R15: P0004 | S15: Général | T15: Exclu | U15: 40725 | V15: 40725
A16: 24.10.00 | B16: M | C16: 45628.703 | D16: D0007 | E16: Congés/Absence | F16: S0049 | G16: Compte épargne temps | H16: E0466 | I16: Compte épargne temps | J16: La date d'observation saisie du CET est non vide | K16: A_CET_DAGCET [Saisi] <> Vide | L16: T1129 | M16: Compte épargne temps - Ouverture et opération "Consommation" | N16: Création Modification | O16: La date de l'opération saisie est non vide et le sens de l'opération est "Consommé". | P16: A_CET_DOOCET [Saisi] <> Vide ET A_CET_SEOCET [Saisi] = 'C' | Q16: Stagiaire ou auditeur ou élève | R16: P0004 | S16: Général | T16: Exclu | U16: 40725 | V16: 40725
A17: 24.10.00 | B17: M | C17: 45628.705 | D17: D0007 | E17: Congés/Absence | F17: S0049 | G17: Compte épargne temps | H17: E0466 | I17: Compte épargne temps | J17: La date d'observation saisie du CET est non vide | K17: A_CET_DAGCET [Saisi] <> Vide | L17: T1130 | M17: Compte épargne temps - Ouverture et opération "Versement" | N17: Création Modification | O17: La date de l'opération saisie est non vide et le sens de l'opération est "Versé". | P17: A_CET_DOOCET [Saisi] <> Vide ET A_CET_SEOCET [Saisi] = 'V' | Q17: Stagiaire ou auditeur ou élève | R17: P0004 | S17: Général | T17: Exclu | U17: 40725 | V17: 40725
A18: 24.10.00 | B18: M | C18: 45628.702 | D18: D0007 | E18: Congés/Absence | F18: S0049 | G18: Compte épargne temps | H18: E0466 | I18: Compte épargne temps | J18: La date d'observation saisie du CET est non vide | K18: A_CET_DAGCET [Saisi] <> Vide | L18: T1128 | M18: Compte épargne temps - Ouverture sans opération | N18: Création Modification | O18: La date de l'opération saisie est vide. | P18: A_CET_DOOCET [Saisi] = Vide | Q18: Ouvrier d'état | R18: P0005 | S18: Général | T18: Exclu | U18: 40725 | V18: 40725
A19: 24.10.00 | B19: M | C19: 45628.703 | D19: D0007 | E19: Congés/Absence | F19: S0049 | G19: Compte épargne temps | H19: E0466 | I19: Compte épargne temps | J19: La date d'observation saisie du CET est non vide | K19: A_CET_DAGCET [Saisi] <> Vide | L19: T1129 | M19: Compte épargne temps - Ouverture et opération "Consommation" | N19: Création Modification | O19: La date de l'opération saisie est non vide et le sens de l'opération est "Consommé". | P19: A_CET_DOOCET [Saisi] <> Vide ET A_CET_SEOCET [Saisi] = 'C' | Q19: Ouvrier d'état | R19: P0005 | S19: Général | T19: Exclu | U19: 40725 | V19: 40725
A20: 24.10.00 | B20: M | C20: 45628.705 | D20: D0007 | E20: Congés/Absence | F20: S0049 | G20: Compte épargne temps | H20: E0466 | I20: Compte épargne temps | J20: La date d'observation saisie du CET est non vide | K20: A_CET_DAGCET [Saisi] <> Vide | L20: T1130 | M20: Compte épargne temps - Ouverture et opération "Versement" | N20: Création Modification | O20: La date de l'opération saisie est non vide et le sens de l'opération est "Versé". | P20: A_CET_DOOCET [Saisi] <> Vide ET A_CET_SEOCET [Saisi] = 'V' | Q20: Ouvrier d'état | R20: P0005 | S20: Général | T20: Exclu | U20: 40725 | V20: 40725
A21: 24.10.00 | B21: M | C21: 45628.706 | D21: D0007 | E21: Congés/Absence | F21: S0049 | G21: Compte épargne temps | H21: E0466 | I21: Compte épargne temps | J21: La date d'observation saisie du CET est non vide | K21: A_CET_DAGCET [Saisi] <> Vide | L21: T1128 | M21: Compte épargne temps - Ouverture sans opération | N21: Création Modification | O21: La date de l'opération saisie est vide. | P21: A_CET_DOOCET [Saisi] = Vide | Q21: Expert technique international | R21: P0018 | S21: Particulier | T21: Exclu | U21: 40725 | V21: 40725
A22: 24.10.00 | B22: M | C22: 45628.707 | D22: D0007 | E22: Congés/Absence | F22: S0049 | G22: Compte épargne temps | H22: E0466 | I22: Compte épargne temps | J22: La date d'observation saisie du CET est non vide | K22: A_CET_DAGCET [Saisi] <> Vide | L22: T1129 | M22: Compte épargne temps - Ouverture et opération "Consommation" | N22: Création Modification | O22: La date de l'opération saisie est non vide et le sens de l'opération est "Consommé". | P22: A_CET_DOOCET [Saisi] <> Vide ET A_CET_SEOCET [Saisi] = 'C' | Q22: Expert technique international | R22: P0018 | S22: Particulier | T22: Exclu | U22: 40725 | V22: 40725
A23: 24.10.00 | B23: M | C23: 45628.708 | D23: D0007 | E23: Congés/Absence | F23: S0049 | G23: Compte épargne temps | H23: E0466 | I23: Compte épargne temps | J23: La date d'observation saisie du CET est non vide | K23: A_CET_DAGCET [Saisi] <> Vide | L23: T1130 | M23: Compte épargne temps - Ouverture et opération "Versement" | N23: Création Modification | O23: La date de l'opération saisie est non vide et le sens de l'opération est "Versé". | P23: A_CET_DOOCET [Saisi] <> Vide ET A_CET_SEOCET [Saisi] = 'V' | Q23: Expert technique international | R23: P0018 | S23: Particulier | T23: Exclu | U23: 40725 | V23: 40725
A24: 24.10.00 | B24: M | C24: 45628.706 | D24: D0007 | E24: Congés/Absence | F24: S0049 | G24: Compte épargne temps | H24: E0466 | I24: Compte épargne temps | J24: La date d'observation saisie du CET est non vide | K24: A_CET_DAGCET [Saisi] <> Vide | L24: T1128 | M24: Compte épargne temps - Ouverture sans opération | N24: Création Modification | O24: La date de l'opération saisie est vide. | P24: A_CET_DOOCET [Saisi] = Vide | Q24: Personnel civil payé à l'acte ou à la tâche | R24: P0054 | S24: Particulier | T24: Exclu | U24: 40725 | V24: 40725
A25: 24.10.00 | B25: M | C25: 45628.707 | D25: D0007 | E25: Congés/Absence | F25: S0049 | G25: Compte épargne temps | H25: E0466 | I25: Compte épargne temps | J25: La date d'observation saisie du CET est non vide | K25: A_CET_DAGCET [Saisi] <> Vide | L25: T1129 | M25: Compte épargne temps - Ouverture et opération "Consommation" | N25: Création Modification | O25: La date de l'opération saisie est non vide et le sens de l'opération est "Consommé". | P25: A_CET_DOOCET [Saisi] <> Vide ET A_CET_SEOCET [Saisi] = 'C' | Q25: Personnel civil payé à l'acte ou à la tâche | R25: P0054 | S25: Particulier | T25: Exclu | U25: 40725 | V25: 40725
A26: 24.10.00 | B26: M | C26: 45628.709 | D26: D0007 | E26: Congés/Absence | F26: S0049 | G26: Compte épargne temps | H26: E0466 | I26: Compte épargne temps | J26: La date d'observation saisie du CET est non vide | K26: A_CET_DAGCET [Saisi] <> Vide | L26: T1130 | M26: Compte épargne temps - Ouverture et opération "Versement" | N26: Création Modification | O26: La date de l'opération saisie est non vide et le sens de l'opération est "Versé". | P26: A_CET_DOOCET [Saisi] <> Vide ET A_CET_SEOCET [Saisi] = 'V' | Q26: Personnel civil payé à l'acte ou à la tâche | R26: P0054 | S26: Particulier | T26: Exclu | U26: 40725 | V26: 40725
... A29: 24.10.00 | B29: M | C29: 45628.709 | D29: D0007 | E29: Congés/Absence | F29: S0049 | G29: Compte épargne temps | H29: E0466 | I29: Compte épargne temps | J29: La date d'observation saisie du CET est non vide | K29: A_CET_DAGCET [Saisi] <> Vide | L29: T1130 | M29: Compte épargne temps - Ouverture et opération "Versement" | N29: Création Modification | O29: La date de l'opération saisie est non vide et le sens de l'opération est "Versé". | P29: A_CET_DOOCET [Saisi] <> Vide ET A_CET_SEOCET [Saisi] = 'V' | Q29: Contractuel de droit privé | R29: P0072 | S29: Particulier | T29: Exclu | U29: 40725 | V29: 40725
A30: 18.10.00 | B30: M | C30: 43152.5 | D30: D0007 | E30: Congés/Absence | F30: S0049 | G30: Compte épargne temps | H30: E0466 | I30: Compte épargne temps | J30: La date d'observation saisie du CET est non vide | K30: A_CET_DAGCET [Saisi] <> Vide | L30: T1128 | M30: Compte épargne temps - Ouverture sans opération | N30: Création Modification | O30: La date de l'opération saisie est vide. | P30: A_CET_DOOCET [Saisi] = Vide | Q30: Ouvrier de la défense réglementé affilié | R30: P0093 | S30: Particulier | T30: Passant | U30: 40725 | W30: CET_I_003 ET CET_I_031 ET CET_I_005 ET CET_D_100 ET CET_C_004 ET CET_C_010 ET CET_C_011 ET CET_C_017 ET CET_C_019 ET CET_C_031 | X30: CET_I_003 | Y30: =VLOOKUP(X30,'Axe 2 Règles de gestion'!$D$2:$F$84,3, FALSE) -> L'agent doit être employé de manière continue et avoir accompli au moins 1 année de service au sein du ministère de la Défense ou de ses établissements publics. | Z30: CET_I_031 | AA30: =VLOOKUP(Z30,'Axe 2 Règles de gestion'!$D$2:$F$84,3, FALSE) -> L'agent demande l'ouverture d'un compte épargne-temps auprès du service gestionnaire. | AB30: CET_I_005 | AC30: =VLOOKUP(AB30,'Axe 2 Règles de gestion'!$D$2:$F$84,3, FALSE) -> Une instruction du ministre de la Défense détermine, dans le respect de l'intérêt du service, les règles d'ouverture, de fonctionnement, de gestion et de fermeture du compte épargne-temps, ainsi que les modalités de son utilisation par l'agent. | AL30: CET_D_100 | AM30: =VLOOKUP(AL30,'Axe 2 Règles de gestion'!$D$2:$F$84,3, FALSE) -> Le nombre de jours maximum du compteur global doit être inférieur ou égal à 60 jours à l'issue de l'exercice du droit d'option. | BB30: CET_C_004 | BC30: =VLOOKUP(BB30,'Axe 2 Règles de gestion'!$D$2:$F$84,3, FALSE) -> Le nombre de jours de l'opération doit être inférieur ou égal au nombre de jours du compteur global du CET. | BD30: CET_C_010 | BE30: =VLOOKUP(BD30,'Axe 2 Règles de gestion'!$D$2:$F$84,3, FALSE) -> La date de fermeture du CET doit être antérieure ou égale à la date limite de départ en retraite. | BF30: CET_C_011 | BG30: =VLOOKUP(BF30,'Axe 2 Règles de gestion'!$D$2:$F$84,3, FALSE) -> La date de fermeture du CET doit être antérieure ou égale à la date de fin réelle ou prévisionnelle du lien juridique. | BH30: CET_C_017 | BI30: =VLOOKUP(BH30,'Axe 2 Règles de gestion'!$D$2:$F$84,3, FALSE) -> La date d'ouverture du compte épargne temps global doit être postérieure ou égale à la date d'entrée dans le SIRH. | BJ30: CET_C_019 | BK30: =VLOOKUP(BJ30,'Axe 2 Règles de gestion'!$D$2:$F$84,3, FALSE) -> La date d'ouverture du CET doit être renseignée. | BL30: CET_C_031 | BM30: =VLOOKUP(BL30,'Axe 2 Règles de gestion'!$D$2:$F$84,3, FALSE) -> Les champs "Origine", "Nombre de jours de l'opération", "Nombre de jours pour valorisation financière" et "Nombre de jours pour cotisation RAFP" ne doivent pas être renseignés.
A31: 19.00.00 | B31: M | C31: 43633.714 | D31: D0007 | E31: Congés/Absence | F31: S0049 | G31: Compte épargne temps | H31: E0466 | I31: Compte épargne temps | J31: La date d'observation saisie du CET est non vide | K31: A_CET_DAGCET [Saisi] <> Vide | L31: T1129 | M31: Compte épargne temps - Ouverture et opération "Consommation" | N31: Création Modification | O31: La date de l'opération saisie est non vide et le sens de l'opération est "Consommé". | P31: A_CET_DOOCET [Saisi] <> Vide ET A_CET_SEOCET [Saisi] = 'C' | Q31: Ouvrier de la défense réglementé affilié | R31: P0093 | S31: Particulier | T31: Passant | U31: 40725 | V31: 43435 | W31: CET_I_003 ET CET_I_031 ET CET_I_005 ET CET_I_011 ET CET_I_013 ET CET_I_017 ET CET_I_034 ET CET_D_100 ET CET_D_096 ET CET_C_004 ET CET_C_010 ET CET_C_011 ET CET_C_017 ET CET_C_019 ET CET_C_022 ET CET_C_024 ET CET_C_027 | X31: CET_I_003 | Y31: =VLOOKUP(X31,'Axe 2 Règles de gestion'!$D$2:$F$84,3, FALSE) -> L'agent doit être employé de manière continue et avoir accompli au moins 1 année de service au sein du ministère de la Défense ou de ses établissements publics. | Z31: CET_I_031 | AA31: =VLOOKUP(Z31,'Axe 2 Règles de gestion'!$D$2:$F$84,3, FALSE) -> L'agent demande l'ouverture d'un compte épargne-temps auprès du service gestionnaire. | AB31: CET_I_005 | AC31: =VLOOKUP(AB31,'Axe 2 Règles de gestion'!$D$2:$F$84,3, FALSE) -> Une instruction du ministre de la Défense détermine, dans le respect de l'intérêt du service, les règles d'ouverture, de fonctionnement, de gestion et de fermeture du compte épargne-temps, ainsi que les modalités de son utilisation par l'agent. | AD31: CET_I_011 | AE31: =VLOOKUP(AD31,'Axe 2 Règles de gestion'!$D$2:$F$84,3, FALSE) -> L'agent exerce son droit d'option au plus tard le 31 janvier de l'année suivant la période de référence de l'épargne. | AF31: CET_I_013 | AG31: =VLOOKUP(AF31,'Axe 2 Règles de gestion'!$D$2:$F$84,3, FALSE) -> L'agent indique au service gestionnaire son choix entre maintien sur le compte en vue de congés et indemnisation, surtout s'il souhaite conserver ces jours sur son compte épargne-temps. | AH31: CET_I_017 | AI31: =VLOOKUP(AH31,'Axe 2 Règles de gestion'!$D$2:$F$84,3, FALSE) -> En l'absence d'exercice d'une option par l'agent, les jours au-delà de 15 sont automatiquement indemnisés. | AJ31: CET_I_034 | AK31: =VLOOKUP(AJ31,'Axe 2 Règles de gestion'!$D$2:$F$84,3, FALSE) -> La demande d'utilisation du compte épargne-temps de l'agent doit être déposée auprès du service gestionnaire dans un délai de 2 mois avant un congé d'au plus 40 jours ouvrés pris en continu et dans un délai de 4 mois s'il est d'une plus longue durée. | AL31: CET_D_100 | AM31: =VLOOKUP(AL31,'Axe 2 Règles de gestion'!$D$2:$F$84,3, FALSE) -> Le nombre de jours maximum du compteur global doit être inférieur ou égal à 60 jours à l'issue de l'exercice du droit d'option. | AN31: CET_D_096 | AO31: =VLOOKUP(AN31,'Axe 2 Règles de gestion'!$D$2:$F$84,3, FALSE) -> La différence entre le nombre de jours du compteur global du CET et le nombre de jours pour valorisation financière doit être strictement supérieure à 20 jours. | BB31: CET_C_004 | BC31: =VLOOKUP(BB31,'Axe 2 Règles de gestion'!$D$2:$F$84,3, FALSE) -> Le nombre de jours de l'opération doit être inférieur ou égal au nombre de jours du compteur global du CET. | BD31: CET_C_010 | BE31: =VLOOKUP(BD31,'Axe 2 Règles de gestion'!$D$2:$F$84,3, FALSE) -> La date de fermeture du CET doit être antérieure ou égale à la date limite de départ en retraite. | BF31: CET_C_011 | BG31: =VLOOKUP(BF31,'Axe 2 Règles de gestion'!$D$2:$F$84,3, FALSE) -> La date de fermeture du CET doit être antérieure ou égale à la date de fin réelle ou prévisionnelle du lien juridique. | BH31: CET_C_017 | BI31: =VLOOKUP(BH31,'Axe 2 Règles de gestion'!$D$2:$F$84,3, FALSE) -> La date d'ouverture du compte épargne temps global doit être postérieure ou égale à la date d'entrée dans le SIRH. | BJ31: CET_C_019 | BK31: =VLOOKUP(BJ31,'Axe 2 Règles de gestion'!$D$2:$F$84,3, FALSE) -> La date d'ouverture du CET doit être renseignée. | BL31: CET_C_022 | BM31: =VLOOKUP(BL31,'Axe 2 Règles de gestion'!$D$2:$F$84,3, FALSE) -> Lorsque le sens de l'opération est égal à "consommé", le nombre de jours pour la cotisation RAFP n'est pas à renseigner. | BN31: CET_C_024 | BO31: =VLOOKUP(BN31,'Axe 2 Règles de gestion'!$D$2:$F$84,3, FALSE) -> Lorsque le sens de l'opération est à "consommé", le compteur global saisi est égal au compteur global de l'occurrence précédente duquel sont soustraits les jours consommés en congés, les jours pour valorisation financière et les jours pour cotisation RAFP. | BP31: CET_C_027 | BQ31: =VLOOKUP(BP31,'Axe 2 Règles de gestion'!$D$2:$F$84,3, FALSE) -> Lorsque le sens de l'opération est égal à "consommé", l'origine des jours n'est pas à renseigner.
A32: 19.00.00 | B32: M | C32: 43633.715 | D32: D0007 | E32: Congés/Absence | F32: S0049 | G32: Compte épargne temps | H32: E0466 | I32: Compte épargne temps | J32: La date d'observation saisie du CET est non vide | K32: A_CET_DAGCET [Saisi] <> Vide | L32: T1129 | M32: Compte épargne temps - Ouverture et opération "Consommation" | N32: Création Modification | O32: La date de l'opération saisie est non vide et le sens de l'opération est "Consommé". | P32: A_CET_DOOCET [Saisi] <> Vide ET A_CET_SEOCET [Saisi] = 'C' | Q32: Ouvrier de la défense réglementé affilié | R32: P0093 | S32: Particulier | T32: Passant | U32: 43436 | W32: CET_I_003 ET CET_I_031 ET CET_I_005 ET CET_I_011 ET CET_I_013 ET CET_I_017 ET CET_I_034 ET CET_D_100 ET CET_D_097 ET CET_C_004 ET CET_C_010 ET CET_C_011 ET CET_C_017 ET CET_C_019 ET CET_C_022 ET CET_C_024 ET CET_C_027 | X32: CET_I_003 | Y32: =VLOOKUP(X32,'Axe 2 Règles de gestion'!$D$2:$F$84,3, FALSE) -> L'agent doit être employé de manière continue et avoir accompli au moins 1 année de service au sein du ministère de la Défense ou de ses établissements publics. | Z32: CET_I_031 | AA32: =VLOOKUP(Z32,'Axe 2 Règles de gestion'!$D$2:$F$84,3, FALSE) -> L'agent demande l'ouverture d'un compte épargne-temps auprès du service gestionnaire. | AB32: CET_I_005 | AC32: =VLOOKUP(AB32,'Axe 2 Règles de gestion'!$D$2:$F$84,3, FALSE) -> Une instruction du ministre de la Défense détermine, dans le respect de l'intérêt du service, les règles d'ouverture, de fonctionnement, de gestion et de fermeture du compte épargne-temps, ainsi que les modalités de son utilisation par l'agent. | AD32: CET_I_011 | AE32: =VLOOKUP(AD32,'Axe 2 Règles de gestion'!$D$2:$F$84,3, FALSE) -> L'agent exerce son droit d'option au plus tard le 31 janvier de l'année suivant la période de référence de l'épargne. | AF32: CET_I_013 | AG32: =VLOOKUP(AF32,'Axe 2 Règles de gestion'!$D$2:$F$84,3, FALSE) -> L'agent indique au service gestionnaire son choix entre maintien sur le compte en vue de congés et indemnisation, surtout s'il souhaite conserver ces jours sur son compte épargne-temps. | AH32: CET_I_017 | AI32: =VLOOKUP(AH32,'Axe 2 Règles de gestion'!$D$2:$F$84,3, FALSE) -> En l'absence d'exercice d'une option par l'agent, les jours au-delà de 15 sont automatiquement indemnisés. | AJ32: CET_I_034 | AK32: =VLOOKUP(AJ32,'Axe 2 Règles de gestion'!$D$2:$F$84,3, FALSE) -> La demande d'utilisation du compte épargne-temps de l'agent doit être déposée auprès du service gestionnaire dans un délai de 2 mois avant un congé d'au plus 40 jours ouvrés pris en continu et dans un délai de 4 mois s'il est d'une plus longue durée. | AL32: CET_D_100 | AM32: =VLOOKUP(AL32,'Axe 2 Règles de gestion'!$D$2:$F$84,3, FALSE) -> Le nombre de jours maximum du compteur global doit être inférieur ou égal à 60 jours à l'issue de l'exercice du droit d'option. | AN32: CET_D_097 | AO32: =VLOOKUP(AN32,'Axe 2 Règles de gestion'!$D$2:$F$84,3, FALSE) -> La différence entre le nombre de jours du compteur global du CET et le nombre de jours pour valorisation financière doit être strictement supérieure à 15 jours. | BB32: CET_C_004 | BC32: =VLOOKUP(BB32,'Axe 2 Règles de gestion'!$D$2:$F$84,3, FALSE) -> Le nombre de jours de l'opération doit être inférieur ou égal au nombre de jours du compteur global du CET. | BD32: CET_C_010 | BE32: =VLOOKUP(BD32,'Axe 2 Règles de gestion'!$D$2:$F$84,3, FALSE) -> La date de fermeture du CET doit être antérieure ou égale à la date limite de départ en retraite. | BF32: CET_C_011 | BG32: =VLOOKUP(BF32,'Axe 2 Règles de gestion'!$D$2:$F$84,3, FALSE) -> La date de fermeture du CET doit être antérieure ou égale à la date de fin réelle ou prévisionnelle du lien juridique. | BH32: CET_C_017 | BI32: =VLOOKUP(BH32,'Axe 2 Règles de gestion'!$D$2:$F$84,3, FALSE) -> La date d'ouverture du compte épargne temps global doit être postérieure ou égale à la date d'entrée dans le SIRH. | BJ32: CET_C_019 | BK32: =VLOOKUP(BJ32,'Axe 2 Règles de gestion'!$D$2:$F$84,3, FALSE) -> La date d'ouverture du CET doit être renseignée. | BL32: CET_C_022 | BM32: =VLOOKUP(BL32,'Axe 2 Règles de gestion'!$D$2:$F$84,3, FALSE) -> Lorsque le sens de l'opération est égal à "consommé", le nombre de jours pour la cotisation RAFP n'est pas à renseigner. | BN32: CET_C_024 | BO32: =VLOOKUP(BN32,'Axe 2 Règles de gestion'!$D$2:$F$84,3, FALSE) -> Lorsque le sens de l'opération est à "consommé", le compteur global saisi est égal au compteur global de l'occurrence précédente duquel sont soustraits les jours consommés en congés, les jours pour valorisation financière et les jours pour cotisation RAFP. | BP32: CET_C_027 | BQ32: =VLOOKUP(BP32,'Axe 2 Règles de gestion'!$D$2:$F$84,3, FALSE) -> Lorsque le sens de l'opération est égal à "consommé", l'origine des jours n'est pas à renseigner.
A33: 18.10.00 | B33: M | C33: 43509.74 | D33: D0007 | E33: Congés/Absence | F33: S0049 | G33: Compte épargne temps | H33: E0466 | I33: Compte épargne temps | J33: La date d'observation saisie du CET est non vide | K33: A_CET_DAGCET [Saisi] <> Vide | L33: T1130 | M33: Compte épargne temps - Ouverture et opération "Versement" | N33: Création Modification | O33: La date de l'opération saisie est non vide et le sens de l'opération est "Versé". | P33: A_CET_DOOCET [Saisi] <> Vide ET A_CET_SEOCET [Saisi] = 'V' | Q33: Ouvrier de la défense réglementé affilié | R33: P0093 | S33: Particulier | T33: Passant | U33: 40725 | V33: 43435 | W33: CET_I_003 ET CET_I_031 ET CET_I_005 ET CET_I_032 ET CET_D_092 ET CET_D_100 ET CET_D_215 ET CET_D_220 ET CET_D_221 ET CET_C_004 ET CET_C_010 ET CET_C_011 ET CET_C_017 ET CET_C_019 ET CET_C_023 ET CET_C_026 | X33: CET_I_003 | Y33: =VLOOKUP(X33,'Axe 2 Règles de gestion'!$D$2:$F$84,3, FALSE) -> L'agent doit être employé de manière continue et avoir accompli au moins 1 année de service au sein du ministère de la Défense ou de ses établissements publics. | Z33: CET_I_031 | AA33: =VLOOKUP(Z33,'Axe 2 Règles de gestion'!$D$2:$F$84,3, FALSE) -> L'agent demande l'ouverture d'un compte épargne-temps auprès du service gestionnaire. | AB33: CET_I_005 | AC33: =VLOOKUP(AB33,'Axe 2 Règles de gestion'!$D$2:$F$84,3, FALSE) -> Une instruction du ministre de la Défense détermine, dans le respect de l'intérêt du service, les règles d'ouverture, de fonctionnement, de gestion et de fermeture du compte épargne-temps, ainsi que les modalités de son utilisation par l'agent. | AD33: CET_I_032 | AE33: =VLOOKUP(AD33,'Axe 2 Règles de gestion'!$D$2:$F$84,3, FALSE) -> L'agent demande au service gestionnaire l'alimentation de son compte épargne-temps avant le 31 décembre de l'année en cours. | AL33: CET_D_092 | AM33: =VLOOKUP(AL33,'Axe 2 Règles de gestion'!$D$2:$F$84,3, FALSE) -> Le CET est alimenté par le report de jours de réduction du temps de travail (ARTT), par le report de congés annuels, le report des jours de repos compensateur et/ou le report d'une partie des congés de fin de séjour pour les ouvriers de l'Etat mutés dans les DOM, les TOM ou à l'étranger. | AN33: CET_D_100 | AO33: =VLOOKUP(AN33,'Axe 2 Règles de gestion'!$D$2:$F$84,3, FALSE) -> Le nombre de jours maximum du compteur global doit être inférieur ou égal à 60 jours à l'issue de l'exercice du droit d'option. | AP33: CET_D_215 | AQ33: =VLOOKUP(AP33,'Axe 2 Règles de gestion'!$D$2:$F$84,3, FALSE) -> Le nombre de jours de congés pris dans l'année doit être supérieur ou égal à 20 jours. | AR33: CET_D_220 | AS33: =VLOOKUP(AR33,'Axe 2 Règles de gestion'!$D$2:$F$84,3, FALSE) -> Si le compte épargne global est supérieur ou égal à 20 jours et le sens de l'opération est égal à "versé" alors le nombre de jours de l'opération conservés en congés doit être inférieur ou égal à 10 jours. | AT33: CET_D_221 | AU33: =VLOOKUP(AT33,'Axe 2 Règles de gestion'!$D$2:$F$84,3, FALSE) -> Si le compteur global du CET est inférieur à 20 jours et le sens de l'opération est égal à "versé" alors le nombre de jours du compteur global du CET après saisie doit être inférieur ou égal à 30 jours. | BB33: CET_C_004 | BC33: =VLOOKUP(BB33,'Axe 2 Règles de gestion'!$D$2:$F$84,3, FALSE) -> Le nombre de jours de l'opération doit être inférieur ou égal au nombre de jours du compteur global du CET. | BD33: CET_C_010 | BE33: =VLOOKUP(BD33,'Axe 2 Règles de gestion'!$D$2:$F$84,3, FALSE) -> La date de fermeture du CET doit être antérieure ou égale à la date limite de départ en retraite. | BF33: CET_C_011 | BG33: =VLOOKUP(BF33,'Axe 2 Règles de gestion'!$D$2:$F$84,3, FALSE) -> La date de fermeture du CET doit être antérieure ou égale à la date de fin réelle ou prévisionnelle du lien juridique. | BH33: CET_C_017 | BI33: =VLOOKUP(BH33,'Axe 2 Règles de gestion'!$D$2:$F$84,3, FALSE) -> La date d'ouverture du compte épargne temps global doit être postérieure ou égale à la date d'entrée dans le SIRH. | BJ33: CET_C_019 | BK33: =VLOOKUP(BJ33,'Axe 2 Règles de gestion'!$D$2:$F$84,3, FALSE) -> La date d'ouverture du CET doit être renseignée. | BL33: CET_C_023 | BM33: =VLOOKUP(BL33,'Axe 2 Règles de gestion'!$D$2:$F$84,3, FALSE) -> Lorsque le sens de l'opération est à "Versé", le compteur global saisi est égal au compteur global de l'occurrence précédente auquel sont ajoutés les jours versés. | BN33: CET_C_026 | BO33: =VLOOKUP(BN33,'Axe 2 Règles de gestion'!$D$2:$F$84,3, FALSE) -> Lorsque le sens de l'opération est égal à "versé", le nombre de jours pour valorisation financière et le nombre de jours pour cotisation RAFP ne doivent pas être renseignés.
A34: 18.10.00 | B34: A | C34: 43509.74 | D34: D0007 | E34: Congés/Absence | F34: S0049 | G34: Compte épargne temps | H34: E0466 | I34: Compte épargne temps | J34: La date d'observation saisie du CET est non vide | K34: A_CET_DAGCET [Saisi] <> Vide | L34: T1130 | M34: Compte épargne temps - Ouverture et opération "Versement" | N34: Création Modification | O34: La date de l'opération saisie est non vide et le sens de l'opération est "Versé". | P34: A_CET_DOOCET [Saisi] <> Vide ET A_CET_SEOCET [Saisi] = 'V' | Q34: Ouvrier de la défense réglementé affilié | R34: P0093 | S34: Particulier | T34: Passant | U34: 43436 | W34: CET_I_003 ET CET_I_031 ET CET_I_005 ET CET_I_032 ET CET_D_092 ET CET_D_100 ET CET_D_215 ET CET_D_222 ET CET_D_223 ET CET_C_004 ET CET_C_010 ET CET_C_011 ET CET_C_017 ET CET_C_019 ET CET_C_023 ET CET_C_026 | X34: CET_I_003 | Y34: =VLOOKUP(X34,'Axe 2 Règles de gestion'!$D$2:$F$84,3, FALSE) -> L'agent doit être employé de manière continue et avoir accompli au moins 1 année de service au sein du ministère de la Défense ou de ses établissements publics. | Z34: CET_I_031 | AA34: =VLOOKUP(Z34,'Axe 2 Règles de gestion'!$D$2:$F$84,3, FALSE) -> L'agent demande l'ouverture d'un compte épargne-temps auprès du service gestionnaire. | AB34: CET_I_005 | AC34: =VLOOKUP(AB34,'Axe 2 Règles de gestion'!$D$2:$F$84,3, FALSE) -> Une instruction du ministre de la Défense détermine, dans le respect de l'intérêt du service, les règles d'ouverture, de fonctionnement, de gestion et de fermeture du compte épargne-temps, ainsi que les modalités de son utilisation par l'agent. | AD34: CET_I_032 | AE34: =VLOOKUP(AD34,'Axe 2 Règles de gestion'!$D$2:$F$84,3, FALSE) -> L'agent demande au service gestionnaire l'alimentation de son compte épargne-temps avant le 31 décembre de l'année en cours. | AL34: CET_D_092 | AM34: =VLOOKUP(AL34,'Axe 2 Règles de gestion'!$D$2:$F$84,3, FALSE) -> Le CET est alimenté par le report de jours de réduction du temps de travail (ARTT), par le report de congés annuels, le report des jours de repos compensateur et/ou le report d'une partie des congés de fin de séjour pour les ouvriers de l'Etat mutés dans les DOM, les TOM ou à l'étranger. | AN34: CET_D_100 | AO34: =VLOOKUP(AN34,'Axe 2 Règles de gestion'!$D$2:$F$84,3, FALSE) -> Le nombre de jours maximum du compteur global doit être inférieur ou égal à 60 jours à l'issue de l'exercice du droit d'option. | AP34: CET_D_215 | AQ34: =VLOOKUP(AP34,'Axe 2 Règles de gestion'!$D$2:$F$84,3, FALSE) -> Le nombre de jours de congés pris dans l'année doit être supérieur ou égal à 20 jours. | AR34: CET_D_222 | AS34: =VLOOKUP(AR34,'Axe 2 Règles de gestion'!$D$2:$F$84,3, FALSE) -> Si le compte épargne global est supérieur ou égal à 15 jours et le sens de l'opération est égal à "versé" alors le nombre de jours de l'opération conservés en congés doit être inférieur ou égal à 10 jours. | AT34: CET_D_223 | AU34: =VLOOKUP(AT34,'Axe 2 Règles de gestion'!$D$2:$F$84,3, FALSE) -> Si le compteur global du CET est inférieur à 15 jours et le sens de l'opération est égal à "versé" alors le nombre de jours du compteur global du CET après saisie doit être inférieur ou égal à 25 jours. | BB34: CET_C_004 | BC34: =VLOOKUP(BB34,'Axe 2 Règles de gestion'!$D$2:$F$84,3, FALSE) -> Le nombre de jours de l'opération doit être inférieur ou égal au nombre de jours du compteur global du CET. | BD34: CET_C_010 | BE34: =VLOOKUP(BD34,'Axe 2 Règles de gestion'!$D$2:$F$84,3, FALSE) -> La date de fermeture du CET doit être antérieure ou égale à la date limite de départ en retraite. | BF34: CET_C_011 | BG34: =VLOOKUP(BF34,'Axe 2 Règles de gestion'!$D$2:$F$84,3, FALSE) -> La date de fermeture du CET doit être antérieure ou égale à la date de fin réelle ou prévisionnelle du lien juridique. | BH34: CET_C_017 | BI34: =VLOOKUP(BH34,'Axe 2 Règles de gestion'!$D$2:$F$84,3, FALSE) -> La date d'ouverture du compte épargne temps global doit être postérieure ou égale à la date d'entrée dans le SIRH. | BJ34: CET_C_019 | BK34: =VLOOKUP(BJ34,'Axe 2 Règles de gestion'!$D$2:$F$84,3, FALSE) -> La date d'ouverture du CET doit être renseignée. | BL34: CET_C_023 | BM34: =VLOOKUP(BL34,'Axe 2 Règles de gestion'!$D$2:$F$84,3, FALSE) -> Lorsque le sens de l'opération est à "Versé", le compteur global saisi est égal au compteur global de l'occurrence précédente auquel sont ajoutés les jours versés. | BN34: CET_C_026 | BO34: =VLOOKUP(BN34,'Axe 2 Règles de gestion'!$D$2:$F$84,3, FALSE) -> Lorsque le sens de l'opération est égal à "versé", le nombre de jours pour valorisation financière et le nombre de jours pour cotisation RAFP ne doivent pas être renseignés.
A35: 20.10.00 | B35: M | C35: 44053.427 | D35: D0007 | E35: Congés/Absence | F35: S0049 | G35: Compte épargne temps | H35: E0466 | I35: Compte épargne temps | J35: La date d'observation saisie du CET est non vide | K35: A_CET_DAGCET [Saisi] <> Vide | L35: T1128 | M35: Compte épargne temps - Ouverture sans opération | N35: Création Modification | O35: La date de l'opération saisie est vide. | P35: A_CET_DOOCET [Saisi] = Vide | Q35: Ouvrier du service des alcools | R35: P0094 | S35: Particulier | T35: Passant | U35: 40725 | W35: CET_I_002 ET CET_I_001 ET CET_I_004 ET CET_D_020 ET CET_D_059 ET CET_C_004 ET CET_C_010 ET CET_C_011 ET CET_C_017 ET CET_C_019 ET CET_C_031 | X35: CET_I_002 | Y35: =VLOOKUP(X35,'Axe 2 Règles de gestion'!$D$2:$F$84,3, FALSE) -> L'agent doit être employé de manière continue et avoir accompli au moins 1 an de service. | Z35: CET_I_001 | AA35: =VLOOKUP(Z35,'Axe 2 Règles de gestion'!$D$2:$F$84,3, FALSE) -> L'agent demande l'ouverture d'un compte épargne-temps auprès du service gestionnaire. | AB35: CET_I_004 | AC35: =VLOOKUP(AB35,'Axe 2 Règles de gestion'!$D$2:$F$84,3, FALSE) -> Un arrêté de la fonction publique, du budget et du ministre intéressé, pris après consultation du comité technique paritaire, détermine, dans le respect de l'intérêt du service, les règles de fonctionnement du compte épargne-temps. | AL35: CET_D_020 | AM35: =VLOOKUP(AL35,'Axe 2 Règles de gestion'!$D$2:$F$84,3, FALSE) -> L'agent ne doit pas être soumis à des obligations de service fixées par le statut particulier de son corps ou par un décret commun à plusieurs corps. | AN35: CET_D_059 | AO35: =VLOOKUP(AN35,'Axe 2 Règles de gestion'!$D$2:$F$84,3, FALSE) -> Le nombre de jours maximum du compteur global doit être inférieur ou égal à 60 jours à l'issue de l'exercice du droit d'option. | BB35: CET_C_004 | BC35: =VLOOKUP(BB35,'Axe 2 Règles de gestion'!$D$2:$F$84,3, FALSE) -> Le nombre de jours de l'opération doit être inférieur ou égal au nombre de jours du compteur global du CET. | BD35: CET_C_010 | BE35: =VLOOKUP(BD35,'Axe 2 Règles de gestion'!$D$2:$F$84,3, FALSE) -> La date de fermeture du CET doit être antérieure ou égale à la date limite de départ en retraite. | BF35: CET_C_011 | BG35: =VLOOKUP(BF35,'Axe 2 Règles de gestion'!$D$2:$F$84,3, FALSE) -> La date de fermeture du CET doit être antérieure ou égale à la date de fin réelle ou prévisionnelle du lien juridique. | BH35: CET_C_017 | BI35: =VLOOKUP(BH35,'Axe 2 Règles de gestion'!$D$2:$F$84,3, FALSE) -> La date d'ouverture du compte épargne temps global doit être postérieure ou égale à la date d'entrée dans le SIRH. | BJ35: CET_C_019 | BK35: =VLOOKUP(BJ35,'Axe 2 Règles de gestion'!$D$2:$F$84,3, FALSE) -> La date d'ouverture du CET doit être renseignée. | BL35: CET_C_031 | BM35: =VLOOKUP(BL35,'Axe 2 Règles de gestion'!$D$2:$F$84,3, FALSE) -> Les champs "Origine", "Nombre de jours de l'opération", "Nombre de jours pour valorisation financière" et "Nombre de jours pour cotisation RAFP" ne doivent pas être renseignés.
A36: 20.10.00 | B36: M | C36: 44053.459 | D36: D0007 | E36: Congés/Absence | F36: S0049 | G36: Compte épargne temps | H36: E0466 | I36: Compte épargne temps | J36: La date d'observation saisie du CET est non vide | K36: A_CET_DAGCET [Saisi] <> Vide | L36: T1129 | M36: Compte épargne temps - Ouverture et opération "Consommation" | N36: Création Modification | O36: La date de l'opération saisie est non vide et le sens de l'opération est "Consommé". | P36: A_CET_DOOCET [Saisi] <> Vide ET A_CET_SEOCET [Saisi] = 'C' | Q36: Ouvrier du service des alcools | R36: P0094 | S36: Particulier | T36: Passant | U36: 40725 | V36: 43435 | W36: CET_I_002 ET CET_I_001 ET CET_I_004 ET CET_I_011 ET CET_I_013 ET CET_I_017 ET CET_D_020 ET CET_D_055 ET CET_D_059 ET CET_C_004 ET CET_C_010 ET CET_C_011 ET CET_C_017 ET CET_C_019 ET CET_C_022 ET CET_C_024 ET CET_C_027 | X36: CET_I_002 | Y36: =VLOOKUP(X36,'Axe 2 Règles de gestion'!$D$2:$F$84,3, FALSE) -> L'agent doit être employé de manière continue et avoir accompli au moins 1 an de service. | Z36: CET_I_001 | AA36: =VLOOKUP(Z36,'Axe 2 Règles de gestion'!$D$2:$F$84,3, FALSE) -> L'agent demande l'ouverture d'un compte épargne-temps auprès du service gestionnaire. | AB36: CET_I_004 | AC36: =VLOOKUP(AB36,'Axe 2 Règles de gestion'!$D$2:$F$84,3, FALSE) -> Un arrêté de la fonction publique, du budget et du ministre intéressé, pris après consultation du comité technique paritaire, détermine, dans le respect de l'intérêt du service, les règles de fonctionnement du compte épargne-temps. | AD36: CET_I_011 | AE36: =VLOOKUP(AD36,'Axe 2 Règles de gestion'!$D$2:$F$84,3, FALSE) -> L'agent exerce son droit d'option au plus tard le 31 janvier de l'année suivant la période de référence de l'épargne. | AF36: CET_I_013 | AG36: =VLOOKUP(AF36,'Axe 2 Règles de gestion'!$D$2:$F$84,3, FALSE) -> L'agent indique au service gestionnaire son choix entre maintien sur le compte en vue de congés et indemnisation, surtout s'il souhaite conserver ces jours sur son compte épargne-temps. | AH36: CET_I_017 | AI36: =VLOOKUP(AH36,'Axe 2 Règles de gestion'!$D$2:$F$84,3, FALSE) -> En l'absence d'exercice d'une option par l'agent, les jours au-delà de 15 sont automatiquement indemnisés. | AL36: CET_D_020 | AM36: =VLOOKUP(AL36,'Axe 2 Règles de gestion'!$D$2:$F$84,3, FALSE) -> L'agent ne doit pas être soumis à des obligations de service fixées par le statut particulier de son corps ou par un décret commun à plusieurs corps. | AN36: CET_D_055 | AO36: =VLOOKUP(AN36,'Axe 2 Règles de gestion'!$D$2:$F$84,3, FALSE) -> La différence entre le nombre de jours du compteur global du CET et le nombre de jours pour valorisation financière doit être strictement supérieure à 20 jours. | AP36: CET_D_059 | AQ36: =VLOOKUP(AP36,'Axe 2 Règles de gestion'!$D$2:$F$84,3, FALSE) -> Le nombre de jours maximum du compteur global doit être inférieur ou égal à 60 jours à l'issue de l'exercice du droit d'option. | BB36: CET_C_004 | BC36: =VLOOKUP(BB36,'Axe 2 Règles de gestion'!$D$2:$F$84,3, FALSE) -> Le nombre de jours de l'opération doit être inférieur ou égal au nombre de jours du compteur global du CET. | BD36: CET_C_010 | BE36: =VLOOKUP(BD36,'Axe 2 Règles de gestion'!$D$2:$F$84,3, FALSE) -> La date de fermeture du CET doit être antérieure ou égale à la date limite de départ en retraite. | BF36: CET_C_011 | BG36: =VLOOKUP(BF36,'Axe 2 Règles de gestion'!$D$2:$F$84,3, FALSE) -> La date de fermeture du CET doit être antérieure ou égale à la date de fin réelle ou prévisionnelle du lien juridique. | BH36: CET_C_017 | BI36: =VLOOKUP(BH36,'Axe 2 Règles de gestion'!$D$2:$F$84,3, FALSE) -> La date d'ouverture du compte épargne temps global doit être postérieure ou égale à la date d'entrée dans le SIRH. | BJ36: CET_C_019 | BK36: =VLOOKUP(BJ36,'Axe 2 Règles de gestion'!$D$2:$F$84,3, FALSE) -> La date d'ouverture du CET doit être renseignée. | BL36: CET_C_022 | BM36: =VLOOKUP(BL36,'Axe 2 Règles de gestion'!$D$2:$F$84,3, FALSE) -> Lorsque le sens de l'opération est égal à "consommé", le nombre de jours pour la cotisation RAFP n'est pas à renseigner. | BN36: CET_C_024 | BO36: =VLOOKUP(BN36,'Axe 2 Règles de gestion'!$D$2:$F$84,3, FALSE) -> Lorsque le sens de l'opération est à "consommé", le compteur global saisi est égal au compteur global de l'occurrence précédente duquel sont soustraits les jours consommés en congés, les jours pour valorisation financière et les jours pour cotisation RAFP. | BP36: CET_C_027 | BQ36: =VLOOKUP(BP36,'Axe 2 Règles de gestion'!$D$2:$F$84,3, FALSE) -> Lorsque le sens de l'opération est égal à "consommé", l'origine des jours n'est pas à renseigner.
A37: 20.10.00 | B37: M | C37: 44053.421 | D37: D0007 | E37: Congés/Absence | F37: S0049 | G37: Compte épargne temps | H37: E0466 | I37: Compte épargne temps | J37: La date d'observation saisie du CET est non vide | K37: A_CET_DAGCET [Saisi] <> Vide | L37: T1129 | M37: Compte épargne temps - Ouverture et opération "Consommation" | N37: Création Modification | O37: La date de l'opération saisie est non vide et le sens de l'opération est "Consommé". | P37: A_CET_DOOCET [Saisi] <> Vide ET A_CET_SEOCET [Saisi] = 'C' | Q37: Ouvrier du service des alcools | R37: P0094 | S37: Particulier | T37: Passant | U37: 43436 | W37: CET_I_002 ET CET_I_001 ET CET_I_004 ET CET_I_011 ET CET_I_013 ET CET_I_017 ET CET_D_020 ET CET_D_056 ET CET_D_059 ET CET_C_004 ET CET_C_010 ET CET_C_011 ET CET_C_017 ET CET_C_019 ET CET_C_022 ET CET_C_024 ET CET_C_027 | X37: CET_I_002 | Y37: =VLOOKUP(X37,'Axe 2 Règles de gestion'!$D$2:$F$84,3, FALSE) -> L'agent doit être employé de manière continue et avoir accompli au moins 1 an de service. | Z37: CET_I_001 | AA37: =VLOOKUP(Z37,'Axe 2 Règles de gestion'!$D$2:$F$84,3, FALSE) -> L'agent demande l'ouverture d'un compte épargne-temps auprès du service gestionnaire. | AB37: CET_I_004 | AC37: =VLOOKUP(AB37,'Axe 2 Règles de gestion'!$D$2:$F$84,3, FALSE) -> Un arrêté de la fonction publique, du budget et du ministre intéressé, pris après consultation du comité technique paritaire, détermine, dans le respect de l'intérêt du service, les règles de fonctionnement du compte épargne-temps. | AD37: CET_I_011 | AE37: =VLOOKUP(AD37,'Axe 2 Règles de gestion'!$D$2:$F$84,3, FALSE) -> L'agent exerce son droit d'option au plus tard le 31 janvier de l'année suivant la période de référence de l'épargne. | AF37: CET_I_013 | AG37: =VLOOKUP(AF37,'Axe 2 Règles de gestion'!$D$2:$F$84,3, FALSE) -> L'agent indique au service gestionnaire son choix entre maintien sur le compte en vue de congés et indemnisation, surtout s'il souhaite conserver ces jours sur son compte épargne-temps. | AH37: CET_I_017 | AI37: =VLOOKUP(AH37,'Axe 2 Règles de gestion'!$D$2:$F$84,3, FALSE) -> En l'absence d'exercice d'une option par l'agent, les jours au-delà de 15 sont automatiquement indemnisés. | AL37: CET_D_020 | AM37: =VLOOKUP(AL37,'Axe 2 Règles de gestion'!$D$2:$F$84,3, FALSE) -> L'agent ne doit pas être soumis à des obligations de service fixées par le statut particulier de son corps ou par un décret commun à plusieurs corps. | AN37: CET_D_056 | AO37: =VLOOKUP(AN37,'Axe 2 Règles de gestion'!$D$2:$F$84,3, FALSE) -> La différence entre le nombre de jours du compteur global du CET et le nombre de jours pour valorisation financière doit être strictement supérieure à 15 jours. | AP37: CET_D_059 | AQ37: =VLOOKUP(AP37,'Axe 2 Règles de gestion'!$D$2:$F$84,3, FALSE) -> Le nombre de jours maximum du compteur global doit être inférieur ou égal à 60 jours à l'issue de l'exercice du droit d'option. | BB37: CET_C_004 | BC37: =VLOOKUP(BB37,'Axe 2 Règles de gestion'!$D$2:$F$84,3, FALSE) -> Le nombre de jours de l'opération doit être inférieur ou égal au nombre de jours du compteur global du CET. | BD37: CET_C_010 | BE37: =VLOOKUP(BD37,'Axe 2 Règles de gestion'!$D$2:$F$84,3, FALSE) -> La date de fermeture du CET doit être antérieure ou égale à la date limite de départ en retraite. | BF37: CET_C_011 | BG37: =VLOOKUP(BF37,'Axe 2 Règles de gestion'!$D$2:$F$84,3, FALSE) -> La date de fermeture du CET doit être antérieure ou égale à la date de fin réelle ou prévisionnelle du lien juridique. | BH37: CET_C_017 | BI37: =VLOOKUP(BH37,'Axe 2 Règles de gestion'!$D$2:$F$84,3, FALSE) -> La date d'ouverture du compte épargne temps global doit être postérieure ou égale à la date d'entrée dans le SIRH. | BJ37: CET_C_019 | BK37: =VLOOKUP(BJ37,'Axe 2 Règles de gestion'!$D$2:$F$84,3, FALSE) -> La date d'ouverture du CET doit être renseignée. | BL37: CET_C_022 | BM37: =VLOOKUP(BL37,'Axe 2 Règles de gestion'!$D$2:$F$84,3, FALSE) -> Lorsque le sens de l'opération est égal à "consommé", le nombre de jours pour la cotisation RAFP n'est pas à renseigner. | BN37: CET_C_024 | BO37: =VLOOKUP(BN37,'Axe 2 Règles de gestion'!$D$2:$F$84,3, FALSE) -> Lorsque le sens de l'opération est à "consommé", le compteur global saisi est égal au compteur global de l'occurrence précédente duquel sont soustraits les jours consommés en congés, les jours pour valorisation financière et les jours pour cotisation RAFP. | BP37: CET_C_027 | BQ37: =VLOOKUP(BP37,'Axe 2 Règles de gestion'!$D$2:$F$84,3, FALSE) -> Lorsque le sens de l'opération est égal à "consommé", l'origine des jours n'est pas à renseigner.
A38: 20.10.00 | B38: M | C38: 44053.463 | D38: D0007 | E38: Congés/Absence | F38: S0049 | G38: Compte épargne temps | H38: E0466 | I38: Compte épargne temps | J38: La date d'observation saisie du CET est non vide | K38: A_CET_DAGCET [Saisi] <> Vide | L38: T1130 | M38: Compte épargne temps - Ouverture et opération "Versement" | N38: Création Modification | O38: La date de l'opération saisie est non vide et le sens de l'opération est "Versé". | P38: A_CET_DOOCET [Saisi] <> Vide ET A_CET_SEOCET [Saisi] = 'V' | Q38: Ouvrier du service des alcools | R38: P0094 | S38: Particulier | T38: Passant | U38: 40725 | V38: 43435 | W38: CET_I_002 ET CET_I_001 ET CET_I_004 ET CET_I_010 ET CET_D_020 ET CET_D_012 ET CET_D_205 ET CET_D_059 ET CET_D_014 ET CET_D_210 ET CET_D_900 ET CET_D_959 ET CET_C_004 ET CET_C_010 ET CET_C_011 ET CET_C_017 ET CET_C_019 ET CET_C_023 ET CET_C_026 | X38: CET_I_002 | Y38: =VLOOKUP(X38,'Axe 2 Règles de gestion'!$D$2:$F$84,3, FALSE) -> L'agent doit être employé de manière continue et avoir accompli au moins 1 an de service. | Z38: CET_I_001 | AA38: =VLOOKUP(Z38,'Axe 2 Règles de gestion'!$D$2:$F$84,3, FALSE) -> L'agent demande l'ouverture d'un compte épargne-temps auprès du service gestionnaire. | AB38: CET_I_004 | AC38: =VLOOKUP(AB38,'Axe 2 Règles de gestion'!$D$2:$F$84,3, FALSE) -> Un arrêté de la fonction publique, du budget et du ministre intéressé, pris après consultation du comité technique paritaire, détermine, dans le respect de l'intérêt du service, les règles de fonctionnement du compte épargne-temps. | AD38: CET_I_010 | AE38: =VLOOKUP(AD38,'Axe 2 Règles de gestion'!$D$2:$F$84,3, FALSE) -> L'agent demande au service gestionnaire l'alimentation de son compte épargne-temps selon les modalités d'usage. | AL38: CET_D_020 | AM38: =VLOOKUP(AL38,'Axe 2 Règles de gestion'!$D$2:$F$84,3, FALSE) -> L'agent ne doit pas être soumis à des obligations de service fixées par le statut particulier de son corps ou par un décret commun à plusieurs corps. | AN38: CET_D_012 | AO38: =VLOOKUP(AN38,'Axe 2 Règles de gestion'!$D$2:$F$84,3, FALSE) -> Le CET est alimenté par le report de jours de réduction du temps de travail (ARTT), jours supplémentaires hors période et par le report de congés annuels, tels que prévus par le décret du 26 octobre 1984. | AP38: CET_D_205 | AQ38: =VLOOKUP(AP38,'Axe 2 Règles de gestion'!$D$2:$F$84,3, FALSE) -> Le CET est alimenté, pour les personnels relevant du décret du 28 mars 1967, par le report de congés annuels dont ils bénéficient au titre du pays dans lequel ils sont affectés. | AR38: CET_D_059 | AS38: =VLOOKUP(AR38,'Axe 2 Règles de gestion'!$D$2:$F$84,3, FALSE) -> Le nombre de jours maximum du compteur global doit être inférieur ou égal à 60 jours à l'issue de l'exercice du droit d'option. | AT38: CET_D_014 | AU38: =VLOOKUP(AT38,'Axe 2 Règles de gestion'!$D$2:$F$84,3, FALSE) -> Le nombre de jours de congés pris dans l'année doit être supérieur ou égal à 20 jours. | AV38: CET_D_210 | AW38: =VLOOKUP(AV38,'Axe 2 Règles de gestion'!$D$2:$F$84,3, FALSE) -> Le nombre de jours de congés pris dans l'année doit être supérieur ou égal à 20 jours. | AX38: CET_D_900 | AY38: =VLOOKUP(AX38,'Axe 2 Règles de gestion'!$D$2:$F$84,3, FALSE) -> Si le compteur global du CET est inférieur à 20 jours et le sens de l'opération est égal à "versé" alors le nombre de jours du compteur global du CET après saisie doit être inférieur ou égal à 30 jours. | AZ38: CET_D_959 | BA38: =VLOOKUP(AZ38,'Axe 2 Règles de gestion'!$D$2:$F$84,3, FALSE) -> Si le compte épargne global est supérieur ou égal à 20 jours et le sens de l'opération est égal à "versé" alors le nombre de jours de l'opération conservés en congés doit être inférieur ou égal à 10 jours. | BB38: CET_C_004 | BC38: =VLOOKUP(BB38,'Axe 2 Règles de gestion'!$D$2:$F$84,3, FALSE) -> Le nombre de jours de l'opération doit être inférieur ou égal au nombre de jours du compteur global du CET. | BD38: CET_C_010 | BE38: =VLOOKUP(BD38,'Axe 2 Règles de gestion'!$D$2:$F$84,3, FALSE) -> La date de fermeture du CET doit être antérieure ou égale à la date limite de départ en retraite. | BF38: CET_C_011 | BG38: =VLOOKUP(BF38,'Axe 2 Règles de gestion'!$D$2:$F$84,3, FALSE) -> La date de fermeture du CET doit être antérieure ou égale à la date de fin réelle ou prévisionnelle du lien juridique. | BH38: CET_C_017 | BI38: =VLOOKUP(BH38,'Axe 2 Règles de gestion'!$D$2:$F$84,3, FALSE) -> La date d'ouverture du compte épargne temps global doit être postérieure ou égale à la date d'entrée dans le SIRH. | BJ38: CET_C_019 | BK38: =VLOOKUP(BJ38,'Axe 2 Règles de gestion'!$D$2:$F$84,3, FALSE) -> La date d'ouverture du CET doit être renseignée. | BL38: CET_C_023 | BM38: =VLOOKUP(BL38,'Axe 2 Règles de gestion'!$D$2:$F$84,3, FALSE) -> Lorsque le sens de l'opération est à "Versé", le compteur global saisi est égal au compteur global de l'occurrence précédente auquel sont ajoutés les jours versés. | BN38: CET_C_026 | BO38: =VLOOKUP(BN38,'Axe 2 Règles de gestion'!$D$2:$F$84,3, FALSE) -> Lorsque le sens de l'opération est égal à "versé", le nombre de jours pour valorisation financière et le nombre de jours pour cotisation RAFP ne doivent pas être renseignés.
A39: 20.10.00 | B39: M | C39: 44053.438 | D39: D0007 | E39: Congés/Absence | F39: S0049 | G39: Compte épargne temps | H39: E0466 | I39: Compte épargne temps | J39: La date d'observation saisie du CET est non vide | K39: A_CET_DAGCET [Saisi] <> Vide | L39: T1130 | M39: Compte épargne temps - Ouverture et opération "Versement" | N39: Création Modification | O39: La date de l'opération saisie est non vide et le sens de l'opération est "Versé". | P39: A_CET_DOOCET [Saisi] <> Vide ET A_CET_SEOCET [Saisi] = 'V' | Q39: Ouvrier du service des alcools | R39: P0094 | S39: Particulier | T39: Passant | U39: 43436 | W39: CET_I_002 ET CET_I_001 ET CET_I_004 ET CET_I_010 ET CET_D_020 ET CET_D_012 ET CET_D_205 ET CET_D_059 ET CET_D_014 ET CET_D_210 ET CET_D_901 ET CET_D_960 ET CET_C_004 ET CET_C_010 ET CET_C_011 ET CET_C_017 ET CET_C_019 ET CET_C_023 ET CET_C_026 | X39: CET_I_002 | Y39: =VLOOKUP(X39,'Axe 2 Règles de gestion'!$D$2:$F$84,3, FALSE) -> L'agent doit être employé de manière continue et avoir accompli au moins 1 an de service. | Z39: CET_I_001 | AA39: =VLOOKUP(Z39,'Axe 2 Règles de gestion'!$D$2:$F$84,3, FALSE) -> L'agent demande l'ouverture d'un compte épargne-temps auprès du service gestionnaire. | AB39: CET_I_004 | AC39: =VLOOKUP(AB39,'Axe 2 Règles de gestion'!$D$2:$F$84,3, FALSE) -> Un arrêté de la fonction publique, du budget et du ministre intéressé, pris après consultation du comité technique paritaire, détermine, dans le respect de l'intérêt du service, les règles de fonctionnement du compte épargne-temps. | AD39: CET_I_010 | AE39: =VLOOKUP(AD39,'Axe 2 Règles de gestion'!$D$2:$F$84,3, FALSE) -> L'agent demande au service gestionnaire l'alimentation de son compte épargne-temps selon les modalités d'usage. | AL39: CET_D_020 | AM39: =VLOOKUP(AL39,'Axe 2 Règles de gestion'!$D$2:$F$84,3, FALSE) -> L'agent ne doit pas être soumis à des obligations de service fixées par le statut particulier de son corps ou par un décret commun à plusieurs corps. | AN39: CET_D_012 | AO39: =VLOOKUP(AN39,'Axe 2 Règles de gestion'!$D$2:$F$84,3, FALSE) -> Le CET est alimenté par le report de jours de réduction du temps de travail (ARTT), jours supplémentaires hors période et par le report de congés annuels, tels que prévus par le décret du 26 octobre 1984. | AP39: CET_D_205 | AQ39: =VLOOKUP(AP39,'Axe 2 Règles de gestion'!$D$2:$F$84,3, FALSE) -> Le CET est alimenté, pour les personnels relevant du décret du 28 mars 1967, par le report de congés annuels dont ils bénéficient au titre du pays dans lequel ils sont affectés. | AR39: CET_D_059 | AS39: =VLOOKUP(AR39,'Axe 2 Règles de gestion'!$D$2:$F$84,3, FALSE) -> Le nombre de jours maximum du compteur global doit être inférieur ou égal à 60 jours à l'issue de l'exercice du droit d'option. | AT39: CET_D_014 | AU39: =VLOOKUP(AT39,'Axe 2 Règles de gestion'!$D$2:$F$84,3, FALSE) -> Le nombre de jours de congés pris dans l'année doit être supérieur ou égal à 20 jours. | AV39: CET_D_210 | AW39: =VLOOKUP(AV39,'Axe 2 Règles de gestion'!$D$2:$F$84,3, FALSE) -> Le nombre de jours de congés pris dans l'année doit être supérieur ou égal à 20 jours. | AX39: CET_D_901 | AY39: =VLOOKUP(AX39,'Axe 2 Règles de gestion'!$D$2:$F$84,3, FALSE) -> Si le compteur global du CET est inférieur à 15 jours et le sens de l'opération est égal à "versé" alors le nombre de jours du compteur global du CET après saisie doit être inférieur ou égal à 25 jours. | AZ39: CET_D_960 | BA39: =VLOOKUP(AZ39,'Axe 2 Règles de gestion'!$D$2:$F$84,3, FALSE) -> Si le compte épargne global est supérieur ou égal à 15 jours et le sens de l'opération est égal à "versé" alors le nombre de jours de l'opération conservés en congés doit être inférieur ou égal à 10 jours. | BB39: CET_C_004 | BC39: =VLOOKUP(BB39,'Axe 2 Règles de gestion'!$D$2:$F$84,3, FALSE) -> Le nombre de jours de l'opération doit être inférieur ou égal au nombre de jours du compteur global du CET. | BD39: CET_C_010 | BE39: =VLOOKUP(BD39,'Axe 2 Règles de gestion'!$D$2:$F$84,3, FALSE) -> La date de fermeture du CET doit être antérieure ou égale à la date limite de départ en retraite. | BF39: CET_C_011 | BG39: =VLOOKUP(BF39,'Axe 2 Règles de gestion'!$D$2:$F$84,3, FALSE) -> La date de fermeture du CET doit être antérieure ou égale à la date de fin réelle ou prévisionnelle du lien juridique. | BH39: CET_C_017 | BI39: =VLOOKUP(BH39,'Axe 2 Règles de gestion'!$D$2:$F$84,3, FALSE) -> La date d'ouverture du compte épargne temps global doit être postérieure ou égale à la date d'entrée dans le SIRH. | BJ39: CET_C_019 | BK39: =VLOOKUP(BJ39,'Axe 2 Règles de gestion'!$D$2:$F$84,3, FALSE) -> La date d'ouverture du CET doit être renseignée. | BL39: CET_C_023 | BM39: =VLOOKUP(BL39,'Axe 2 Règles de gestion'!$D$2:$F$84,3, FALSE) -> Lorsque le sens de l'opération est à "Versé", le compteur global saisi est égal au compteur global de l'occurrence précédente auquel sont ajoutés les jours versés. | BN39: CET_C_026 | BO39: =VLOOKUP(BN39,'Axe 2 Règles de gestion'!$D$2:$F$84,3, FALSE) -> Lorsque le sens de l'opération est égal à "versé", le nombre de jours pour valorisation financière et le nombre de jours pour cotisation RAFP ne doivent pas être renseignés.
A40: 20.10.00 | B40: M | C40: 44053.427 | D40: D0007 | E40: Congés/Absence | F40: S0049 | G40: Compte épargne temps | H40: E0466 | I40: Compte épargne temps | J40: La date d'observation saisie du CET est non vide | K40: A_CET_DAGCET [Saisi] <> Vide | L40: T1128 | M40: Compte épargne temps - Ouverture sans opération | N40: Création Modification | O40: La date de l'opération saisie est vide. | P40: A_CET_DOOCET [Saisi] = Vide | Q40: Ouvrier du service du cadastre confirmé affilié | R40: P0095 | S40: Particulier | T40: Passant | U40: 40725 | W40: CET_I_002 ET CET_I_001 ET CET_I_004 ET CET_D_020 ET CET_D_059 ET CET_C_004 ET CET_C_010 ET CET_C_011 ET CET_C_017 ET CET_C_019 ET CET_C_031 | X40: CET_I_002 | Y40: =VLOOKUP(X40,'Axe 2 Règles de gestion'!$D$2:$F$84,3, FALSE) -> L'agent doit être employé de manière continue et avoir accompli au moins 1 an de service. | Z40: CET_I_001 | AA40: =VLOOKUP(Z40,'Axe 2 Règles de gestion'!$D$2:$F$84,3, FALSE) -> L'agent demande l'ouverture d'un compte épargne-temps auprès du service gestionnaire. | AB40: CET_I_004 | AC40: =VLOOKUP(AB40,'Axe 2 Règles de gestion'!$D$2:$F$84,3, FALSE) -> Un arrêté de la fonction publique, du budget et du ministre intéressé, pris après consultation du comité technique paritaire, détermine, dans le respect de l'intérêt du service, les règles de fonctionnement du compte épargne-temps. | AL40: CET_D_020 | AM40: =VLOOKUP(AL40,'Axe 2 Règles de gestion'!$D$2:$F$84,3, FALSE) -> L'agent ne doit pas être soumis à des obligations de service fixées par le statut particulier de son corps ou par un décret commun à plusieurs corps. | AN40: CET_D_059 | AO40: =VLOOKUP(AN40,'Axe 2 Règles de gestion'!$D$2:$F$84,3, FALSE) -> Le nombre de jours maximum du compteur global doit être inférieur ou égal à 60 jours à l'issue de l'exercice du droit d'option. | BB40: CET_C_004 | BC40: =VLOOKUP(BB40,'Axe 2 Règles de gestion'!$D$2:$F$84,3, FALSE) -> Le nombre de jours de l'opération doit être inférieur ou égal au nombre de jours du compteur global du CET. | BD40: CET_C_010 | BE40: =VLOOKUP(BD40,'Axe 2 Règles de gestion'!$D$2:$F$84,3, FALSE) -> La date de fermeture du CET doit être antérieure ou égale à la date limite de départ en retraite. | BF40: CET_C_011 | BG40: =VLOOKUP(BF40,'Axe 2 Règles de gestion'!$D$2:$F$84,3, FALSE) -> La date de fermeture du CET doit être antérieure ou égale à la date de fin réelle ou prévisionnelle du lien juridique. | BH40: CET_C_017 | BI40: =VLOOKUP(BH40,'Axe 2 Règles de gestion'!$D$2:$F$84,3, FALSE) -> La date d'ouverture du compte épargne temps global doit être postérieure ou égale à la date d'entrée dans le SIRH. | BJ40: CET_C_019 | BK40: =VLOOKUP(BJ40,'Axe 2 Règles de gestion'!$D$2:$F$84,3, FALSE) -> La date d'ouverture du CET doit être renseignée. | BL40: CET_C_031 | BM40: =VLOOKUP(BL40,'Axe 2 Règles de gestion'!$D$2:$F$84,3, FALSE) -> Les champs "Origine", "Nombre de jours de l'opération", "Nombre de jours pour valorisation financière" et "Nombre de jours pour cotisation RAFP" ne doivent pas être renseignés.
A41: 20.10.00 | B41: M | C41: 44053.46 | D41: D0007 | E41: Congés/Absence | F41: S0049 | G41: Compte épargne temps | H41: E0466 | I41: Compte épargne temps | J41: La date d'observation saisie du CET est non vide | K41: A_CET_DAGCET [Saisi] <> Vide | L41: T1129 | M41: Compte épargne temps - Ouverture et opération "Consommation" | N41: Création Modification | O41: La date de l'opération saisie est non vide et le sens de l'opération est "Consommé". | P41: A_CET_DOOCET [Saisi] <> Vide ET A_CET_SEOCET [Saisi] = 'C' | Q41: Ouvrier du service du cadastre confirmé affilié | R41: P0095 | S41: Particulier | T41: Passant | U41: 40725 | V41: 43435 | W41: CET_I_002 ET CET_I_001 ET CET_I_004 ET CET_I_011 ET CET_I_013 ET CET_I_017 ET CET_D_020 ET CET_D_059 ET CET_D_055 ET CET_C_004 ET CET_C_010 ET CET_C_011 ET CET_C_017 ET CET_C_019 ET CET_C_022 ET CET_C_024 ET CET_C_027 | X41: CET_I_002 | Y41: =VLOOKUP(X41,'Axe 2 Règles de gestion'!$D$2:$F$84,3, FALSE) -> L'agent doit être employé de manière continue et avoir accompli au moins 1 an de service. | Z41: CET_I_001 | AA41: =VLOOKUP(Z41,'Axe 2 Règles de gestion'!$D$2:$F$84,3, FALSE) -> L'agent demande l'ouverture d'un compte épargne-temps auprès du service gestionnaire. | AB41: CET_I_004 | AC41: =VLOOKUP(AB41,'Axe 2 Règles de gestion'!$D$2:$F$84,3, FALSE) -> Un arrêté de la fonction publique, du budget et du ministre intéressé, pris après consultation du comité technique paritaire, détermine, dans le respect de l'intérêt du service, les règles de fonctionnement du compte épargne-temps. | AD41: CET_I_011 | AE41: =VLOOKUP(AD41,'Axe 2 Règles de gestion'!$D$2:$F$84,3, FALSE) -> L'agent exerce son droit d'option au plus tard le 31 janvier de l'année suivant la période de référence de l'épargne. | AF41: CET_I_013 | AG41: =VLOOKUP(AF41,'Axe 2 Règles de gestion'!$D$2:$F$84,3, FALSE) -> L'agent indique au service gestionnaire son choix entre maintien sur le compte en vue de congés et indemnisation, surtout s'il souhaite conserver ces jours sur son compte épargne-temps. | AH41: CET_I_017 | AI41: =VLOOKUP(AH41,'Axe 2 Règles de gestion'!$D$2:$F$84,3, FALSE) -> En l'absence d'exercice d'une option par l'agent, les jours au-delà de 15 sont automatiquement indemnisés. | AL41: CET_D_020 | AM41: =VLOOKUP(AL41,'Axe 2 Règles de gestion'!$D$2:$F$84,3, FALSE) -> L'agent ne doit pas être soumis à des obligations de service fixées par le statut particulier de son corps ou par un décret commun à plusieurs corps. | AN41: CET_D_059 | AO41: =VLOOKUP(AN41,'Axe 2 Règles de gestion'!$D$2:$F$84,3, FALSE) -> Le nombre de jours maximum du compteur global doit être inférieur ou égal à 60 jours à l'issue de l'exercice du droit d'option. | AP41: CET_D_055 | AQ41: =VLOOKUP(AP41,'Axe 2 Règles de gestion'!$D$2:$F$84,3, FALSE) -> La différence entre le nombre de jours du compteur global du CET et le nombre de jours pour valorisation financière doit être strictement supérieure à 20 jours. | BB41: CET_C_004 | BC41: =VLOOKUP(BB41,'Axe 2 Règles de gestion'!$D$2:$F$84,3, FALSE) -> Le nombre de jours de l'opération doit être inférieur ou égal au nombre de jours du compteur global du CET. | BD41: CET_C_010 | BE41: =VLOOKUP(BD41,'Axe 2 Règles de gestion'!$D$2:$F$84,3, FALSE) -> La date de fermeture du CET doit être antérieure ou égale à la date limite de départ en retraite. | BF41: CET_C_011 | BG41: =VLOOKUP(BF41,'Axe 2 Règles de gestion'!$D$2:$F$84,3, FALSE) -> La date de fermeture du CET doit être antérieure ou égale à la date de fin réelle ou prévisionnelle du lien juridique. | BH41: CET_C_017 | BI41: =VLOOKUP(BH41,'Axe 2 Règles de gestion'!$D$2:$F$84,3, FALSE) -> La date d'ouverture du compte épargne temps global doit être postérieure ou égale à la date d'entrée dans le SIRH. | BJ41: CET_C_019 | BK41: =VLOOKUP(BJ41,'Axe 2 Règles de gestion'!$D$2:$F$84,3, FALSE) -> La date d'ouverture du CET doit être renseignée. | BL41: CET_C_022 | BM41: =VLOOKUP(BL41,'Axe 2 Règles de gestion'!$D$2:$F$84,3, FALSE) -> Lorsque le sens de l'opération est égal à "consommé", le nombre de jours pour la cotisation RAFP n'est pas à renseigner. | BN41: CET_C_024 | BO41: =VLOOKUP(BN41,'Axe 2 Règles de gestion'!$D$2:$F$84,3, FALSE) -> Lorsque le sens de l'opération est à "consommé", le compteur global saisi est égal au compteur global de l'occurrence précédente duquel sont soustraits les jours consommés en congés, les jours pour valorisation financière et les jours pour cotisation RAFP. | BP41: CET_C_027 | BQ41: =VLOOKUP(BP41,'Axe 2 Règles de gestion'!$D$2:$F$84,3, FALSE) -> Lorsque le sens de l'opération est égal à "consommé", l'origine des jours n'est pas à renseigner.
A42: 20.10.00 | B42: M | C42: 44053.422 | D42: D0007 | E42: Congés/Absence | F42: S0049 | G42: Compte épargne temps | H42: E0466 | I42: Compte épargne temps | J42: La date d'observation saisie du CET est non vide | K42: A_CET_DAGCET [Saisi] <> Vide | L42: T1129 | M42: Compte épargne temps - Ouverture et opération "Consommation" | N42: Création Modification | O42: La date de l'opération saisie est non vide et le sens de l'opération est "Consommé". | P42: A_CET_DOOCET [Saisi] <> Vide ET A_CET_SEOCET [Saisi] = 'C' | Q42: Ouvrier du service du cadastre confirmé affilié | R42: P0095 | S42: Particulier | T42: Passant | U42: 43436 | W42: CET_I_002 ET CET_I_001 ET CET_I_004 ET CET_I_011 ET CET_I_013 ET CET_I_017 ET CET_D_020 ET CET_D_059 ET CET_D_056 ET CET_C_004 ET CET_C_010 ET CET_C_011 ET CET_C_017 ET CET_C_019 ET CET_C_022 ET CET_C_024 ET CET_C_027 | X42: CET_I_002 | Y42: =VLOOKUP(X42,'Axe 2 Règles de gestion'!$D$2:$F$84,3, FALSE) -> L'agent doit être employé de manière continue et avoir accompli au moins 1 an de service. | Z42: CET_I_001 | AA42: =VLOOKUP(Z42,'Axe 2 Règles de gestion'!$D$2:$F$84,3, FALSE) -> L'agent demande l'ouverture d'un compte épargne-temps auprès du service gestionnaire. | AB42: CET_I_004 | AC42: =VLOOKUP(AB42,'Axe 2 Règles de gestion'!$D$2:$F$84,3, FALSE) -> Un arrêté de la fonction publique, du budget et du ministre intéressé, pris après consultation du comité technique paritaire, détermine, dans le respect de l'intérêt du service, les règles de fonctionnement du compte épargne-temps. | AD42: CET_I_011 | AE42: =VLOOKUP(AD42,'Axe 2 Règles de gestion'!$D$2:$F$84,3, FALSE) -> L'agent exerce son droit d'option au plus tard le 31 janvier de l'année suivant la période de référence de l'épargne. | AF42: CET_I_013 | AG42: =VLOOKUP(AF42,'Axe 2 Règles de gestion'!$D$2:$F$84,3, FALSE) -> L'agent indique au service gestionnaire son choix entre maintien sur le compte en vue de congés et indemnisation, surtout s'il souhaite conserver ces jours sur son compte épargne-temps. | AH42: CET_I_017 | AI42: =VLOOKUP(AH42,'Axe 2 Règles de gestion'!$D$2:$F$84,3, FALSE) -> En l'absence d'exercice d'une option par l'agent, les jours au-delà de 15 sont automatiquement indemnisés. | AL42: CET_D_020 | AM42: =VLOOKUP(AL42,'Axe 2 Règles de gestion'!$D$2:$F$84,3, FALSE) -> L'agent ne doit pas être soumis à des obligations de service fixées par le statut particulier de son corps ou par un décret commun à plusieurs corps. | AN42: CET_D_059 | AO42: =VLOOKUP(AN42,'Axe 2 Règles de gestion'!$D$2:$F$84,3, FALSE) -> Le nombre de jours maximum du compteur global doit être inférieur ou égal à 60 jours à l'issue de l'exercice du droit d'option. | AP42: CET_D_056 | AQ42: =VLOOKUP(AP42,'Axe 2 Règles de gestion'!$D$2:$F$84,3, FALSE) -> La différence entre le nombre de jours du compteur global du CET et le nombre de jours pour valorisation financière doit être strictement supérieure à 15 jours. | BB42: CET_C_004 | BC42: =VLOOKUP(BB42,'Axe 2 Règles de gestion'!$D$2:$F$84,3, FALSE) -> Le nombre de jours de l'opération doit être inférieur ou égal au nombre de jours du compteur global du CET. | BD42: CET_C_010 | BE42: =VLOOKUP(BD42,'Axe 2 Règles de gestion'!$D$2:$F$84,3, FALSE) -> La date de fermeture du CET doit être antérieure ou égale à la date limite de départ en retraite. | BF42: CET_C_011 | BG42: =VLOOKUP(BF42,'Axe 2 Règles de gestion'!$D$2:$F$84,3, FALSE) -> La date de fermeture du CET doit être antérieure ou égale à la date de fin réelle ou prévisionnelle du lien juridique. | BH42: CET_C_017 | BI42: =VLOOKUP(BH42,'Axe 2 Règles de gestion'!$D$2:$F$84,3, FALSE) -> La date d'ouverture du compte épargne temps global doit être postérieure ou égale à la date d'entrée dans le SIRH. | BJ42: CET_C_019 | BK42: =VLOOKUP(BJ42,'Axe 2 Règles de gestion'!$D$2:$F$84,3, FALSE) -> La date d'ouverture du CET doit être renseignée. | BL42: CET_C_022 | BM42: =VLOOKUP(BL42,'Axe 2 Règles de gestion'!$D$2:$F$84,3, FALSE) -> Lorsque le sens de l'opération est égal à "consommé", le nombre de jours pour la cotisation RAFP n'est pas à renseigner. | BN42: CET_C_024 | BO42: =VLOOKUP(BN42,'Axe 2 Règles de gestion'!$D$2:$F$84,3, FALSE) -> Lorsque le sens de l'opération est à "consommé", le compteur global saisi est égal au compteur global de l'occurrence précédente duquel sont soustraits les jours consommés en congés, les jours pour valorisation financière et les jours pour cotisation RAFP. | BP42: CET_C_027 | BQ42: =VLOOKUP(BP42,'Axe 2 Règles de gestion'!$D$2:$F$84,3, FALSE) -> Lorsque le sens de l'opération est égal à "consommé", l'origine des jours n'est pas à renseigner.
A43: 20.10.00 | B43: M | C43: 44053.464 | D43: D0007 | E43: Congés/Absence | F43: S0049 | G43: Compte épargne temps | H43: E0466 | I43: Compte épargne temps | J43: La date d'observation saisie du CET est non vide | K43: A_CET_DAGCET [Saisi] <> Vide | L43: T1130 | M43: Compte épargne temps - Ouverture et opération "Versement" | N43: Création Modification | O43: La date de l'opération saisie est non vide et le sens de l'opération est "Versé". | P43: A_CET_DOOCET [Saisi] <> Vide ET A_CET_SEOCET [Saisi] = 'V' | Q43: Ouvrier du service du cadastre confirmé affilié | R43: P0095 | S43: Particulier | T43: Passant | U43: 40725 | V43: 43435 | W43: CET_I_002 ET CET_I_001 ET CET_I_004 ET CET_I_010 ET CET_D_020 ET CET_D_012 ET CET_D_205 ET CET_D_059 ET CET_D_014 ET CET_D_210 ET CET_D_900 ET CET_D_959 ET CET_C_004 ET CET_C_010 ET CET_C_011 ET CET_C_017 ET CET_C_019 ET CET_C_023 ET CET_C_026 | X43: CET_I_002 | Y43: =VLOOKUP(X43,'Axe 2 Règles de gestion'!$D$2:$F$84,3, FALSE) -> L'agent doit être employé de manière continue et avoir accompli au moins 1 an de service. | Z43: CET_I_001 | AA43: =VLOOKUP(Z43,'Axe 2 Règles de gestion'!$D$2:$F$84,3, FALSE) -> L'agent demande l'ouverture d'un compte épargne-temps auprès du service gestionnaire. | AB43: CET_I_004 | AC43: =VLOOKUP(AB43,'Axe 2 Règles de gestion'!$D$2:$F$84,3, FALSE) -> Un arrêté de la fonction publique, du budget et du ministre intéressé, pris après consultation du comité technique paritaire, détermine, dans le respect de l'intérêt du service, les règles de fonctionnement du compte épargne-temps. | AD43: CET_I_010 | AE43: =VLOOKUP(AD43,'Axe 2 Règles de gestion'!$D$2:$F$84,3, FALSE) -> L'agent demande au service gestionnaire l'alimentation de son compte épargne-temps selon les modalités d'usage. | AL43: CET_D_020 | AM43: =VLOOKUP(AL43,'Axe 2 Règles de gestion'!$D$2:$F$84,3, FALSE) -> L'agent ne doit pas être soumis à des obligations de service fixées par le statut particulier de son corps ou par un décret commun à plusieurs corps. | AN43: CET_D_012 | AO43: =VLOOKUP(AN43,'Axe 2 Règles de gestion'!$D$2:$F$84,3, FALSE) -> Le CET est alimenté par le report de jours de réduction du temps de travail (ARTT), jours supplémentaires hors période et par le report de congés annuels, tels que prévus par le décret du 26 octobre 1984. | AP43: CET_D_205 | AQ43: =VLOOKUP(AP43,'Axe 2 Règles de gestion'!$D$2:$F$84,3, FALSE) -> Le CET est alimenté, pour les personnels relevant du décret du 28 mars 1967, par le report de congés annuels dont ils bénéficient au titre du pays dans lequel ils sont affectés. | AR43: CET_D_059 | AS43: =VLOOKUP(AR43,'Axe 2 Règles de gestion'!$D$2:$F$84,3, FALSE) -> Le nombre de jours maximum du compteur global doit être inférieur ou égal à 60 jours à l'issue de l'exercice du droit d'option. | AT43: CET_D_014 | AU43: =VLOOKUP(AT43,'Axe 2 Règles de gestion'!$D$2:$F$84,3, FALSE) -> Le nombre de jours de congés pris dans l'année doit être supérieur ou égal à 20 jours. | AV43: CET_D_210 | AW43: =VLOOKUP(AV43,'Axe 2 Règles de gestion'!$D$2:$F$84,3, FALSE) -> Le nombre de jours de congés pris dans l'année doit être supérieur ou égal à 20 jours. | AX43: CET_D_900 | AY43: =VLOOKUP(AX43,'Axe 2 Règles de gestion'!$D$2:$F$84,3, FALSE) -> Si le compteur global du CET est inférieur à 20 jours et le sens de l'opération est égal à "versé" alors le nombre de jours du compteur global du CET après saisie doit être inférieur ou égal à 30 jours. | AZ43: CET_D_959 | BA43: =VLOOKUP(AZ43,'Axe 2 Règles de gestion'!$D$2:$F$84,3, FALSE) -> Si le compte épargne global est supérieur ou égal à 20 jours et le sens de l'opération est égal à "versé" alors le nombre de jours de l'opération conservés en congés doit être inférieur ou égal à 10 jours. | BB43: CET_C_004 | BC43: =VLOOKUP(BB43,'Axe 2 Règles de gestion'!$D$2:$F$84,3, FALSE) -> Le nombre de jours de l'opération doit être inférieur ou égal au nombre de jours du compteur global du CET. | BD43: CET_C_010 | BE43: =VLOOKUP(BD43,'Axe 2 Règles de gestion'!$D$2:$F$84,3, FALSE) -> La date de fermeture du CET doit être antérieure ou égale à la date limite de départ en retraite. | BF43: CET_C_011 | BG43: =VLOOKUP(BF43,'Axe 2 Règles de gestion'!$D$2:$F$84,3, FALSE) -> La date de fermeture du CET doit être antérieure ou égale à la date de fin réelle ou prévisionnelle du lien juridique. | BH43: CET_C_017 | BI43: =VLOOKUP(BH43,'Axe 2 Règles de gestion'!$D$2:$F$84,3, FALSE) -> La date d'ouverture du compte épargne temps global doit être postérieure ou égale à la date d'entrée dans le SIRH. | BJ43: CET_C_019 | BK43: =VLOOKUP(BJ43,'Axe 2 Règles de gestion'!$D$2:$F$84,3, FALSE) -> La date d'ouverture du CET doit être renseignée. | BL43: CET_C_023 | BM43: =VLOOKUP(BL43,'Axe 2 Règles de gestion'!$D$2:$F$84,3, FALSE) -> Lorsque le sens de l'opération est à "Versé", le compteur global saisi est égal au compteur global de l'occurrence précédente auquel sont ajoutés les jours versés. | BN43: CET_C_026 | BO43: =VLOOKUP(BN43,'Axe 2 Règles de gestion'!$D$2:$F$84,3, FALSE) -> Lorsque le sens de l'opération est égal à "versé", le nombre de jours pour valorisation financière et le nombre de jours pour cotisation RAFP ne doivent pas être renseignés.
A44: 20.10.00 | B44: M | C44: 44053.439 | D44: D0007 | E44: Congés/Absence | F44: S0049 | G44: Compte épargne temps | H44: E0466 | I44: Compte épargne temps | J44: La date d'observation saisie du CET est non vide | K44: A_CET_DAGCET [Saisi] <> Vide | L44: T1130 | M44: Compte épargne temps - Ouverture et opération "Versement" | N44: Création Modification | O44: La date de l'opération saisie est non vide et le sens de l'opération est "Versé". | P44: A_CET_DOOCET [Saisi] <> Vide ET A_CET_SEOCET [Saisi] = 'V' | Q44: Ouvrier du service du cadastre confirmé affilié | R44: P0095 | S44: Particulier | T44: Passant | U44: 43436 | W44: CET_I_002 ET CET_I_001 ET CET_I_004 ET CET_I_010 ET CET_D_020 ET CET_D_012 ET CET_D_205 ET CET_D_059 ET CET_D_014 ET CET_D_210 ET CET_D_901 ET CET_D_960 ET CET_C_004 ET CET_C_010 ET CET_C_011 ET CET_C_017 ET CET_C_019 ET CET_C_023 ET CET_C_026 | X44: CET_I_002 | Y44: =VLOOKUP(X44,'Axe 2 Règles de gestion'!$D$2:$F$84,3, FALSE) -> L'agent doit être employé de manière continue et avoir accompli au moins 1 an de service. | Z44: CET_I_001 | AA44: =VLOOKUP(Z44,'Axe 2 Règles de gestion'!$D$2:$F$84,3, FALSE) -> L'agent demande l'ouverture d'un compte épargne-temps auprès du service gestionnaire. | AB44: CET_I_004 | AC44: =VLOOKUP(AB44,'Axe 2 Règles de gestion'!$D$2:$F$84,3, FALSE) -> Un arrêté de la fonction publique, du budget et du ministre intéressé, pris après consultation du comité technique paritaire, détermine, dans le respect de l'intérêt du service, les règles de fonctionnement du compte épargne-temps. | AD44: CET_I_010 | AE44: =VLOOKUP(AD44,'Axe 2 Règles de gestion'!$D$2:$F$84,3, FALSE) -> L'agent demande au service gestionnaire l'alimentation de son compte épargne-temps selon les modalités d'usage. | AL44: CET_D_020 | AM44: =VLOOKUP(AL44,'Axe 2 Règles de gestion'!$D$2:$F$84,3, FALSE) -> L'agent ne doit pas être soumis à des obligations de service fixées par le statut particulier de son corps ou par un décret commun à plusieurs corps. | AN44: CET_D_012 | AO44: =VLOOKUP(AN44,'Axe 2 Règles de gestion'!$D$2:$F$84,3, FALSE) -> Le CET est alimenté par le report de jours de réduction du temps de travail (ARTT), jours supplémentaires hors période et par le report de congés annuels, tels que prévus par le décret du 26 octobre 1984. | AP44: CET_D_205 | AQ44: =VLOOKUP(AP44,'Axe 2 Règles de gestion'!$D$2:$F$84,3, FALSE) -> Le CET est alimenté, pour les personnels relevant du décret du 28 mars 1967, par le report de congés annuels dont ils bénéficient au titre du pays dans lequel ils sont affectés. | AR44: CET_D_059 | AS44: =VLOOKUP(AR44,'Axe 2 Règles de gestion'!$D$2:$F$84,3, FALSE) -> Le nombre de jours maximum du compteur global doit être inférieur ou égal à 60 jours à l'issue de l'exercice du droit d'option. | AT44: CET_D_014 | AU44: =VLOOKUP(AT44,'Axe 2 Règles de gestion'!$D$2:$F$84,3, FALSE) -> Le nombre de jours de congés pris dans l'année doit être supérieur ou égal à 20 jours. | AV44: CET_D_210 | AW44: =VLOOKUP(AV44,'Axe 2 Règles de gestion'!$D$2:$F$84,3, FALSE) -> Le nombre de jours de congés pris dans l'année doit être supérieur ou égal à 20 jours. | AX44: CET_D_901 | AY44: =VLOOKUP(AX44,'Axe 2 Règles de gestion'!$D$2:$F$84,3, FALSE) -> Si le compteur global du CET est inférieur à 15 jours et le sens de l'opération est égal à "versé" alors le nombre de jours du compteur global du CET après saisie doit être inférieur ou égal à 25 jours. | AZ44: CET_D_960 | BA44: =VLOOKUP(AZ44,'Axe 2 Règles de gestion'!$D$2:$F$84,3, FALSE) -> Si le compte épargne global est supérieur ou égal à 15 jours et le sens de l'opération est égal à "versé" alors le nombre de jours de l'opération conservés en congés doit être inférieur ou égal à 10 jours. | BB44: CET_C_004 | BC44: =VLOOKUP(BB44,'Axe 2 Règles de gestion'!$D$2:$F$84,3, FALSE) -> Le nombre de jours de l'opération doit être inférieur ou égal au nombre de jours du compteur global du CET. | BD44: CET_C_010 | BE44: =VLOOKUP(BD44,'Axe 2 Règles de gestion'!$D$2:$F$84,3, FALSE) -> La date de fermeture du CET doit être antérieure ou égale à la date limite de départ en retraite. | BF44: CET_C_011 | BG44: =VLOOKUP(BF44,'Axe 2 Règles de gestion'!$D$2:$F$84,3, FALSE) -> La date de fermeture du CET doit être antérieure ou égale à la date de fin réelle ou prévisionnelle du lien juridique. | BH44: CET_C_017 | BI44: =VLOOKUP(BH44,'Axe 2 Règles de gestion'!$D$2:$F$84,3, FALSE) -> La date d'ouverture du compte épargne temps global doit être postérieure ou égale à la date d'entrée dans le SIRH. | BJ44: CET_C_019 | BK44: =VLOOKUP(BJ44,'Axe 2 Règles de gestion'!$D$2:$F$84,3, FALSE) -> La date d'ouverture du CET doit être renseignée. | BL44: CET_C_023 | BM44: =VLOOKUP(BL44,'Axe 2 Règles de gestion'!$D$2:$F$84,3, FALSE) -> Lorsque le sens de l'opération est à "Versé", le compteur global saisi est égal au compteur global de l'occurrence précédente auquel sont ajoutés les jours versés. | BN44: CET_C_026 | BO44: =VLOOKUP(BN44,'Axe 2 Règles de gestion'!$D$2:$F$84,3, FALSE) -> Lorsque le sens de l'opération est égal à "versé", le nombre de jours pour valorisation financière et le nombre de jours pour cotisation RAFP ne doivent pas être renseignés.
A45: 25.10.00 | B45: M | C45: 45994.431 | D45: D0007 | E45: Congés/Absence | F45: S0049 | G45: Compte épargne temps | H45: E0466 | I45: Compte épargne temps | J45: La date d'observation saisie du CET est non vide | K45: A_CET_DAGCET [Saisi] <> Vide | L45: T1128 | M45: Compte épargne temps - Ouverture sans opération | N45: Création Modification | O45: La date de l'opération saisie est vide. | P45: A_CET_DOOCET [Saisi] = Vide | Q45: Ouvrier des parcs et ateliers ou assimilé confirmé | R45: P0096 | S45: Particulier | T45: Passant | U45: 40725 | V45: 45900 | W45: CET_I_002 ET CET_I_001 ET CET_I_004 ET CET_D_020 ET CET_D_059 ET CET_C_004 ET CET_C_010 ET CET_C_011 ET CET_C_017 ET CET_C_019 ET CET_C_031 | X45: CET_I_002 | Y45: =VLOOKUP(X45,'Axe 2 Règles de gestion'!$D$2:$F$84,3, FALSE) -> L'agent doit être employé de manière continue et avoir accompli au moins 1 an de service. | Z45: CET_I_001 | AA45: =VLOOKUP(Z45,'Axe 2 Règles de gestion'!$D$2:$F$84,3, FALSE) -> L'agent demande l'ouverture d'un compte épargne-temps auprès du service gestionnaire. | AB45: CET_I_004 | AC45: =VLOOKUP(AB45,'Axe 2 Règles de gestion'!$D$2:$F$84,3, FALSE) -> Un arrêté de la fonction publique, du budget et du ministre intéressé, pris après consultation du comité technique paritaire, détermine, dans le respect de l'intérêt du service, les règles de fonctionnement du compte épargne-temps. | AL45: CET_D_020 | AM45: =VLOOKUP(AL45,'Axe 2 Règles de gestion'!$D$2:$F$84,3, FALSE) -> L'agent ne doit pas être soumis à des obligations de service fixées par le statut particulier de son corps ou par un décret commun à plusieurs corps. | AN45: CET_D_059 | AO45: =VLOOKUP(AN45,'Axe 2 Règles de gestion'!$D$2:$F$84,3, FALSE) -> Le nombre de jours maximum du compteur global doit être inférieur ou égal à 60 jours à l'issue de l'exercice du droit d'option. | BB45: CET_C_004 | BC45: =VLOOKUP(BB45,'Axe 2 Règles de gestion'!$D$2:$F$84,3, FALSE) -> Le nombre de jours de l'opération doit être inférieur ou égal au nombre de jours du compteur global du CET. | BD45: CET_C_010 | BE45: =VLOOKUP(BD45,'Axe 2 Règles de gestion'!$D$2:$F$84,3, FALSE) -> La date de fermeture du CET doit être antérieure ou égale à la date limite de départ en retraite. | BF45: CET_C_011 | BG45: =VLOOKUP(BF45,'Axe 2 Règles de gestion'!$D$2:$F$84,3, FALSE) -> La date de fermeture du CET doit être antérieure ou égale à la date de fin réelle ou prévisionnelle du lien juridique. | BH45: CET_C_017 | BI45: =VLOOKUP(BH45,'Axe 2 Règles de gestion'!$D$2:$F$84,3, FALSE) -> La date d'ouverture du compte épargne temps global doit être postérieure ou égale à la date d'entrée dans le SIRH. | BJ45: CET_C_019 | BK45: =VLOOKUP(BJ45,'Axe 2 Règles de gestion'!$D$2:$F$84,3, FALSE) -> La date d'ouverture du CET doit être renseignée. | BL45: CET_C_031 | BM45: =VLOOKUP(BL45,'Axe 2 Règles de gestion'!$D$2:$F$84,3, FALSE) -> Les champs "Origine", "Nombre de jours de l'opération", "Nombre de jours pour valorisation financière" et "Nombre de jours pour cotisation RAFP" ne doivent pas être renseignés. | BV45: 2025-114
A46: 20.10.00 | B46: M | C46: 44053.461 | D46: D0007 | E46: Congés/Absence | F46: S0049 | G46: Compte épargne temps | H46: E0466 | I46: Compte épargne temps | J46: La date d'observation saisie du CET est non vide | K46: A_CET_DAGCET [Saisi] <> Vide | L46: T1129 | M46: Compte épargne temps - Ouverture et opération "Consommation" | N46: Création Modification | O46: La date de l'opération saisie est non vide et le sens de l'opération est "Consommé". | P46: A_CET_DOOCET [Saisi] <> Vide ET A_CET_SEOCET [Saisi] = 'C' | Q46: Ouvrier des parcs et ateliers ou assimilé confirmé | R46: P0096 | S46: Particulier | T46: Passant | U46: 40725 | V46: 43435 | W46: CET_I_002 ET CET_I_001 ET CET_I_004 ET CET_I_011 ET CET_I_013 ET CET_I_017 ET CET_D_020 ET CET_D_059 ET CET_D_055 ET CET_C_004 ET CET_C_010 ET CET_C_011 ET CET_C_017 ET CET_C_019 ET CET_C_022 ET CET_C_024 ET CET_C_027 | X46: CET_I_002 | Y46: =VLOOKUP(X46,'Axe 2 Règles de gestion'!$D$2:$F$84,3, FALSE) -> L'agent doit être employé de manière continue et avoir accompli au moins 1 an de service. | Z46: CET_I_001 | AA46: =VLOOKUP(Z46,'Axe 2 Règles de gestion'!$D$2:$F$84,3, FALSE) -> L'agent demande l'ouverture d'un compte épargne-temps auprès du service gestionnaire. | AB46: CET_I_004 | AC46: =VLOOKUP(AB46,'Axe 2 Règles de gestion'!$D$2:$F$84,3, FALSE) -> Un arrêté de la fonction publique, du budget et du ministre intéressé, pris après consultation du comité technique paritaire, détermine, dans le respect de l'intérêt du service, les règles de fonctionnement du compte épargne-temps. | AD46: CET_I_011 | AE46: =VLOOKUP(AD46,'Axe 2 Règles de gestion'!$D$2:$F$84,3, FALSE) -> L'agent exerce son droit d'option au plus tard le 31 janvier de l'année suivant la période de référence de l'épargne. | AF46: CET_I_013 | AG46: =VLOOKUP(AF46,'Axe 2 Règles de gestion'!$D$2:$F$84,3, FALSE) -> L'agent indique au service gestionnaire son choix entre maintien sur le compte en vue de congés et indemnisation, surtout s'il souhaite conserver ces jours sur son compte épargne-temps. | AH46: CET_I_017 | AI46: =VLOOKUP(AH46,'Axe 2 Règles de gestion'!$D$2:$F$84,3, FALSE) -> En l'absence d'exercice d'une option par l'agent, les jours au-delà de 15 sont automatiquement indemnisés. | AL46: CET_D_020 | AM46: =VLOOKUP(AL46,'Axe 2 Règles de gestion'!$D$2:$F$84,3, FALSE) -> L'agent ne doit pas être soumis à des obligations de service fixées par le statut particulier de son corps ou par un décret commun à plusieurs corps. | AN46: CET_D_059 | AO46: =VLOOKUP(AN46,'Axe 2 Règles de gestion'!$D$2:$F$84,3, FALSE) -> Le nombre de jours maximum du compteur global doit être inférieur ou égal à 60 jours à l'issue de l'exercice du droit d'option. | AP46: CET_D_055 | AQ46: =VLOOKUP(AP46,'Axe 2 Règles de gestion'!$D$2:$F$84,3, FALSE) -> La différence entre le nombre de jours du compteur global du CET et le nombre de jours pour valorisation financière doit être strictement supérieure à 20 jours. | BB46: CET_C_004 | BC46: =VLOOKUP(BB46,'Axe 2 Règles de gestion'!$D$2:$F$84,3, FALSE) -> Le nombre de jours de l'opération doit être inférieur ou égal au nombre de jours du compteur global du CET. | BD46: CET_C_010 | BE46: =VLOOKUP(BD46,'Axe 2 Règles de gestion'!$D$2:$F$84,3, FALSE) -> La date de fermeture du CET doit être antérieure ou égale à la date limite de départ en retraite. | BF46: CET_C_011 | BG46: =VLOOKUP(BF46,'Axe 2 Règles de gestion'!$D$2:$F$84,3, FALSE) -> La date de fermeture du CET doit être antérieure ou égale à la date de fin réelle ou prévisionnelle du lien juridique. | BH46: CET_C_017 | BI46: =VLOOKUP(BH46,'Axe 2 Règles de gestion'!$D$2:$F$84,3, FALSE) -> La date d'ouverture du compte épargne temps global doit être postérieure ou égale à la date d'entrée dans le SIRH. | BJ46: CET_C_019 | BK46: =VLOOKUP(BJ46,'Axe 2 Règles de gestion'!$D$2:$F$84,3, FALSE) -> La date d'ouverture du CET doit être renseignée. | BL46: CET_C_022 | BM46: =VLOOKUP(BL46,'Axe 2 Règles de gestion'!$D$2:$F$84,3, FALSE) -> Lorsque le sens de l'opération est égal à "consommé", le nombre de jours pour la cotisation RAFP n'est pas à renseigner. | BN46: CET_C_024 | BO46: =VLOOKUP(BN46,'Axe 2 Règles de gestion'!$D$2:$F$84,3, FALSE) -> Lorsque le sens de l'opération est à "consommé", le compteur global saisi est égal au compteur global de l'occurrence précédente duquel sont soustraits les jours consommés en congés, les jours pour valorisation financière et les jours pour cotisation RAFP. | BP46: CET_C_027 | BQ46: =VLOOKUP(BP46,'Axe 2 Règles de gestion'!$D$2:$F$84,3, FALSE) -> Lorsque le sens de l'opération est égal à "consommé", l'origine des jours n'est pas à renseigner.
A47: 25.10.00 | B47: M | C47: 45994.432 | D47: D0007 | E47: Congés/Absence | F47: S0049 | G47: Compte épargne temps | H47: E0466 | I47: Compte épargne temps | J47: La date d'observation saisie du CET est non vide | K47: A_CET_DAGCET [Saisi] <> Vide | L47: T1129 | M47: Compte épargne temps - Ouverture et opération "Consommation" | N47: Création Modification | O47: La date de l'opération saisie est non vide et le sens de l'opération est "Consommé". | P47: A_CET_DOOCET [Saisi] <> Vide ET A_CET_SEOCET [Saisi] = 'C' | Q47: Ouvrier des parcs et ateliers ou assimilé confirmé | R47: P0096 | S47: Particulier | T47: Passant | U47: 43436 | V47: 45900 | W47: CET_I_002 ET CET_I_001 ET CET_I_004 ET CET_I_011 ET CET_I_013 ET CET_I_017 ET CET_D_020 ET CET_D_059 ET CET_D_056 ET CET_C_004 ET CET_C_010 ET CET_C_011 ET CET_C_017 ET CET_C_019 ET CET_C_022 ET CET_C_024 ET CET_C_027 | X47: CET_I_002 | Y47: =VLOOKUP(X47,'Axe 2 Règles de gestion'!$D$2:$F$84,3, FALSE) -> L'agent doit être employé de manière continue et avoir accompli au moins 1 an de service. | Z47: CET_I_001 | AA47: =VLOOKUP(Z47,'Axe 2 Règles de gestion'!$D$2:$F$84,3, FALSE) -> L'agent demande l'ouverture d'un compte épargne-temps auprès du service gestionnaire. | AB47: CET_I_004 | AC47: =VLOOKUP(AB47,'Axe 2 Règles de gestion'!$D$2:$F$84,3, FALSE) -> Un arrêté de la fonction publique, du budget et du ministre intéressé, pris après consultation du comité technique paritaire, détermine, dans le respect de l'intérêt du service, les règles de fonctionnement du compte épargne-temps. | AD47: CET_I_011 | AE47: =VLOOKUP(AD47,'Axe 2 Règles de gestion'!$D$2:$F$84,3, FALSE) -> L'agent exerce son droit d'option au plus tard le 31 janvier de l'année suivant la période de référence de l'épargne. | AF47: CET_I_013 | AG47: =VLOOKUP(AF47,'Axe 2 Règles de gestion'!$D$2:$F$84,3, FALSE) -> L'agent indique au service gestionnaire son choix entre maintien sur le compte en vue de congés et indemnisation, surtout s'il souhaite conserver ces jours sur son compte épargne-temps. | AH47: CET_I_017 | AI47: =VLOOKUP(AH47,'Axe 2 Règles de gestion'!$D$2:$F$84,3, FALSE) -> En l'absence d'exercice d'une option par l'agent, les jours au-delà de 15 sont automatiquement indemnisés. | AL47: CET_D_020 | AM47: =VLOOKUP(AL47,'Axe 2 Règles de gestion'!$D$2:$F$84,3, FALSE) -> L'agent ne doit pas être soumis à des obligations de service fixées par le statut particulier de son corps ou par un décret commun à plusieurs corps. | AN47: CET_D_059 | AO47: =VLOOKUP(AN47,'Axe 2 Règles de gestion'!$D$2:$F$84,3, FALSE) -> Le nombre de jours maximum du compteur global doit être inférieur ou égal à 60 jours à l'issue de l'exercice du droit d'option. | AP47: CET_D_056 | AQ47: =VLOOKUP(AP47,'Axe 2 Règles de gestion'!$D$2:$F$84,3, FALSE) -> La différence entre le nombre de jours du compteur global du CET et le nombre de jours pour valorisation financière doit être strictement supérieure à 15 jours. | BB47: CET_C_004 | BC47: =VLOOKUP(BB47,'Axe 2 Règles de gestion'!$D$2:$F$84,3, FALSE) -> Le nombre de jours de l'opération doit être inférieur ou égal au nombre de jours du compteur global du CET. | BD47: CET_C_010 | BE47: =VLOOKUP(BD47,'Axe 2 Règles de gestion'!$D$2:$F$84,3, FALSE) -> La date de fermeture du CET doit être antérieure ou égale à la date limite de départ en retraite. | BF47: CET_C_011 | BG47: =VLOOKUP(BF47,'Axe 2 Règles de gestion'!$D$2:$F$84,3, FALSE) -> La date de fermeture du CET doit être antérieure ou égale à la date de fin réelle ou prévisionnelle du lien juridique. | BH47: CET_C_017 | BI47: =VLOOKUP(BH47,'Axe 2 Règles de gestion'!$D$2:$F$84,3, FALSE) -> La date d'ouverture du compte épargne temps global doit être postérieure ou égale à la date d'entrée dans le SIRH. | BJ47: CET_C_019 | BK47: =VLOOKUP(BJ47,'Axe 2 Règles de gestion'!$D$2:$F$84,3, FALSE) -> La date d'ouverture du CET doit être renseignée. | BL47: CET_C_022 | BM47: =VLOOKUP(BL47,'Axe 2 Règles de gestion'!$D$2:$F$84,3, FALSE) -> Lorsque le sens de l'opération est égal à "consommé", le nombre de jours pour la cotisation RAFP n'est pas à renseigner. | BN47: CET_C_024 | BO47: =VLOOKUP(BN47,'Axe 2 Règles de gestion'!$D$2:$F$84,3, FALSE) -> Lorsque le sens de l'opération est à "consommé", le compteur global saisi est égal au compteur global de l'occurrence précédente duquel sont soustraits les jours consommés en congés, les jours pour valorisation financière et les jours pour cotisation RAFP. | BP47: CET_C_027 | BQ47: =VLOOKUP(BP47,'Axe 2 Règles de gestion'!$D$2:$F$84,3, FALSE) -> Lorsque le sens de l'opération est égal à "consommé", l'origine des jours n'est pas à renseigner. | BV47: 2025-114
A48: 20.10.00 | B48: M | C48: 44053.465 | D48: D0007 | E48: Congés/Absence | F48: S0049 | G48: Compte épargne temps | H48: E0466 | I48: Compte épargne temps | J48: La date d'observation saisie du CET est non vide | K48: A_CET_DAGCET [Saisi] <> Vide | L48: T1130 | M48: Compte épargne temps - Ouverture et opération "Versement" | N48: Création Modification | O48: La date de l'opération saisie est non vide et le sens de l'opération est "Versé". | P48: A_CET_DOOCET [Saisi] <> Vide ET A_CET_SEOCET [Saisi] = 'V' | Q48: Ouvrier des parcs et ateliers ou assimilé confirmé | R48: P0096 | S48: Particulier | T48: Passant | U48: 40725 | V48: 43435 | W48: CET_I_002 ET CET_I_001 ET CET_I_004 ET CET_I_010 ET CET_D_020 ET CET_D_012 ET CET_D_205 ET CET_D_059 ET CET_D_014 ET CET_D_210 ET CET_D_900 ET CET_D_959 ET CET_C_004 ET CET_C_010 ET CET_C_011 ET CET_C_017 ET CET_C_019 ET CET_C_023 ET CET_C_026 | X48: CET_I_002 | Y48: =VLOOKUP(X48,'Axe 2 Règles de gestion'!$D$2:$F$84,3, FALSE) -> L'agent doit être employé de manière continue et avoir accompli au moins 1 an de service. | Z48: CET_I_001 | AA48: =VLOOKUP(Z48,'Axe 2 Règles de gestion'!$D$2:$F$84,3, FALSE) -> L'agent demande l'ouverture d'un compte épargne-temps auprès du service gestionnaire. | AB48: CET_I_004 | AC48: =VLOOKUP(AB48,'Axe 2 Règles de gestion'!$D$2:$F$84,3, FALSE) -> Un arrêté de la fonction publique, du budget et du ministre intéressé, pris après consultation du comité technique paritaire, détermine, dans le respect de l'intérêt du service, les règles de fonctionnement du compte épargne-temps. | AD48: CET_I_010 | AE48: =VLOOKUP(AD48,'Axe 2 Règles de gestion'!$D$2:$F$84,3, FALSE) -> L'agent demande au service gestionnaire l'alimentation de son compte épargne-temps selon les modalités d'usage. | AL48: CET_D_020 | AM48: =VLOOKUP(AL48,'Axe 2 Règles de gestion'!$D$2:$F$84,3, FALSE) -> L'agent ne doit pas être soumis à des obligations de service fixées par le statut particulier de son corps ou par un décret commun à plusieurs corps. | AN48: CET_D_012 | AO48: =VLOOKUP(AN48,'Axe 2 Règles de gestion'!$D$2:$F$84,3, FALSE) -> Le CET est alimenté par le report de jours de réduction du temps de travail (ARTT), jours supplémentaires hors période et par le report de congés annuels, tels que prévus par le décret du 26 octobre 1984. | AP48: CET_D_205 | AQ48: =VLOOKUP(AP48,'Axe 2 Règles de gestion'!$D$2:$F$84,3, FALSE) -> Le CET est alimenté, pour les personnels relevant du décret du 28 mars 1967, par le report de congés annuels dont ils bénéficient au titre du pays dans lequel ils sont affectés. | AR48: CET_D_059 | AS48: =VLOOKUP(AR48,'Axe 2 Règles de gestion'!$D$2:$F$84,3, FALSE) -> Le nombre de jours maximum du compteur global doit être inférieur ou égal à 60 jours à l'issue de l'exercice du droit d'option. | AT48: CET_D_014 | AU48: =VLOOKUP(AT48,'Axe 2 Règles de gestion'!$D$2:$F$84,3, FALSE) -> Le nombre de jours de congés pris dans l'année doit être supérieur ou égal à 20 jours. | AV48: CET_D_210 | AW48: =VLOOKUP(AV48,'Axe 2 Règles de gestion'!$D$2:$F$84,3, FALSE) -> Le nombre de jours de congés pris dans l'année doit être supérieur ou égal à 20 jours. | AX48: CET_D_900 | AY48: =VLOOKUP(AX48,'Axe 2 Règles de gestion'!$D$2:$F$84,3, FALSE) -> Si le compteur global du CET est inférieur à 20 jours et le sens de l'opération est égal à "versé" alors le nombre de jours du compteur global du CET après saisie doit être inférieur ou égal à 30 jours. | AZ48: CET_D_959 | BA48: =VLOOKUP(AZ48,'Axe 2 Règles de gestion'!$D$2:$F$84,3, FALSE) -> Si le compte épargne global est supérieur ou égal à 20 jours et le sens de l'opération est égal à "versé" alors le nombre de jours de l'opération conservés en congés doit être inférieur ou égal à 10 jours. | BB48: CET_C_004 | BC48: =VLOOKUP(BB48,'Axe 2 Règles de gestion'!$D$2:$F$84,3, FALSE) -> Le nombre de jours de l'opération doit être inférieur ou égal au nombre de jours du compteur global du CET. | BD48: CET_C_010 | BE48: =VLOOKUP(BD48,'Axe 2 Règles de gestion'!$D$2:$F$84,3, FALSE) -> La date de fermeture du CET doit être antérieure ou égale à la date limite de départ en retraite. | BF48: CET_C_011 | BG48: =VLOOKUP(BF48,'Axe 2 Règles de gestion'!$D$2:$F$84,3, FALSE) -> La date de fermeture du CET doit être antérieure ou égale à la date de fin réelle ou prévisionnelle du lien juridique. | BH48: CET_C_017 | BI48: =VLOOKUP(BH48,'Axe 2 Règles de gestion'!$D$2:$F$84,3, FALSE) -> La date d'ouverture du compte épargne temps global doit être postérieure ou égale à la date d'entrée dans le SIRH. | BJ48: CET_C_019 | BK48: =VLOOKUP(BJ48,'Axe 2 Règles de gestion'!$D$2:$F$84,3, FALSE) -> La date d'ouverture du CET doit être renseignée. | BL48: CET_C_023 | BM48: =VLOOKUP(BL48,'Axe 2 Règles de gestion'!$D$2:$F$84,3, FALSE) -> Lorsque le sens de l'opération est à "Versé", le compteur global saisi est égal au compteur global de l'occurrence précédente auquel sont ajoutés les jours versés. | BN48: CET_C_026 | BO48: =VLOOKUP(BN48,'Axe 2 Règles de gestion'!$D$2:$F$84,3, FALSE) -> Lorsque le sens de l'opération est égal à "versé", le nombre de jours pour valorisation financière et le nombre de jours pour cotisation RAFP ne doivent pas être renseignés.
A49: 25.10.00 | B49: M | C49: 45994.433 | D49: D0007 | E49: Congés/Absence | F49: S0049 | G49: Compte épargne temps | H49: E0466 | I49: Compte épargne temps | J49: La date d'observation saisie du CET est non vide | K49: A_CET_DAGCET [Saisi] <> Vide | L49: T1130 | M49: Compte épargne temps - Ouverture et opération "Versement" | N49: Création Modification | O49: La date de l'opération saisie est non vide et le sens de l'opération est "Versé". | P49: A_CET_DOOCET [Saisi] <> Vide ET A_CET_SEOCET [Saisi] = 'V' | Q49: Ouvrier des parcs et ateliers ou assimilé confirmé | R49: P0096 | S49: Particulier | T49: Passant | U49: 43436 | V49: 45900 | W49: CET_I_002 ET CET_I_001 ET CET_I_004 ET CET_I_010 ET CET_D_020 ET CET_D_012 ET CET_D_205 ET CET_D_059 ET CET_D_014 ET CET_D_210 ET CET_D_901 ET CET_D_960 ET CET_C_004 ET CET_C_010 ET CET_C_011 ET CET_C_017 ET CET_C_019 ET CET_C_023 ET CET_C_026 | X49: CET_I_002 | Y49: =VLOOKUP(X49,'Axe 2 Règles de gestion'!$D$2:$F$84,3, FALSE) -> L'agent doit être employé de manière continue et avoir accompli au moins 1 an de service. | Z49: CET_I_001 | AA49: =VLOOKUP(Z49,'Axe 2 Règles de gestion'!$D$2:$F$84,3, FALSE) -> L'agent demande l'ouverture d'un compte épargne-temps auprès du service gestionnaire. | AB49: CET_I_004 | AC49: =VLOOKUP(AB49,'Axe 2 Règles de gestion'!$D$2:$F$84,3, FALSE) -> Un arrêté de la fonction publique, du budget et du ministre intéressé, pris après consultation du comité technique paritaire, détermine, dans le respect de l'intérêt du service, les règles de fonctionnement du compte épargne-temps. | AD49: CET_I_010 | AE49: =VLOOKUP(AD49,'Axe 2 Règles de gestion'!$D$2:$F$84,3, FALSE) -> L'agent demande au service gestionnaire l'alimentation de son compte épargne-temps selon les modalités d'usage. | AL49: CET_D_020 | AM49: =VLOOKUP(AL49,'Axe 2 Règles de gestion'!$D$2:$F$84,3, FALSE) -> L'agent ne doit pas être soumis à des obligations de service fixées par le statut particulier de son corps ou par un décret commun à plusieurs corps. | AN49: CET_D_012 | AO49: =VLOOKUP(AN49,'Axe 2 Règles de gestion'!$D$2:$F$84,3, FALSE) -> Le CET est alimenté par le report de jours de réduction du temps de travail (ARTT), jours supplémentaires hors période et par le report de congés annuels, tels que prévus par le décret du 26 octobre 1984. | AP49: CET_D_205 | AQ49: =VLOOKUP(AP49,'Axe 2 Règles de gestion'!$D$2:$F$84,3, FALSE) -> Le CET est alimenté, pour les personnels relevant du décret du 28 mars 1967, par le report de congés annuels dont ils bénéficient au titre du pays dans lequel ils sont affectés. | AR49: CET_D_059 | AS49: =VLOOKUP(AR49,'Axe 2 Règles de gestion'!$D$2:$F$84,3, FALSE) -> Le nombre de jours maximum du compteur global doit être inférieur ou égal à 60 jours à l'issue de l'exercice du droit d'option. | AT49: CET_D_014 | AU49: =VLOOKUP(AT49,'Axe 2 Règles de gestion'!$D$2:$F$84,3, FALSE) -> Le nombre de jours de congés pris dans l'année doit être supérieur ou égal à 20 jours. | AV49: CET_D_210 | AW49: =VLOOKUP(AV49,'Axe 2 Règles de gestion'!$D$2:$F$84,3, FALSE) -> Le nombre de jours de congés pris dans l'année doit être supérieur ou égal à 20 jours. | AX49: CET_D_901 | AY49: =VLOOKUP(AX49,'Axe 2 Règles de gestion'!$D$2:$F$84,3, FALSE) -> Si le compteur global du CET est inférieur à 15 jours et le sens de l'opération est égal à "versé" alors le nombre de jours du compteur global du CET après saisie doit être inférieur ou égal à 25 jours. | AZ49: CET_D_960 | BA49: =VLOOKUP(AZ49,'Axe 2 Règles de gestion'!$D$2:$F$84,3, FALSE) -> Si le compte épargne global est supérieur ou égal à 15 jours et le sens de l'opération est égal à "versé" alors le nombre de jours de l'opération conservés en congés doit être inférieur ou égal à 10 jours. | BB49: CET_C_004 | BC49: =VLOOKUP(BB49,'Axe 2 Règles de gestion'!$D$2:$F$84,3, FALSE) -> Le nombre de jours de l'opération doit être inférieur ou égal au nombre de jours du compteur global du CET. | BD49: CET_C_010 | BE49: =VLOOKUP(BD49,'Axe 2 Règles de gestion'!$D$2:$F$84,3, FALSE) -> La date de fermeture du CET doit être antérieure ou égale à la date limite de départ en retraite. | BF49: CET_C_011 | BG49: =VLOOKUP(BF49,'Axe 2 Règles de gestion'!$D$2:$F$84,3, FALSE) -> La date de fermeture du CET doit être antérieure ou égale à la date de fin réelle ou prévisionnelle du lien juridique. | BH49: CET_C_017 | BI49: =VLOOKUP(BH49,'Axe 2 Règles de gestion'!$D$2:$F$84,3, FALSE) -> La date d'ouverture du compte épargne temps global doit être postérieure ou égale à la date d'entrée dans le SIRH. | BJ49: CET_C_019 | BK49: =VLOOKUP(BJ49,'Axe 2 Règles de gestion'!$D$2:$F$84,3, FALSE) -> La date d'ouverture du CET doit être renseignée. | BL49: CET_C_023 | BM49: =VLOOKUP(BL49,'Axe 2 Règles de gestion'!$D$2:$F$84,3, FALSE) -> Lorsque le sens de l'opération est à "Versé", le compteur global saisi est égal au compteur global de l'occurrence précédente auquel sont ajoutés les jours versés. | BN49: CET_C_026 | BO49: =VLOOKUP(BN49,'Axe 2 Règles de gestion'!$D$2:$F$84,3, FALSE) -> Lorsque le sens de l'opération est égal à "versé", le nombre de jours pour valorisation financière et le nombre de jours pour cotisation RAFP ne doivent pas être renseignés. | BV49: 2025-114
A50: 24.10.00 | B50: M | C50: 45628.706 | D50: D0007 | E50: Congés/Absence | F50: S0049 | G50: Compte épargne temps | H50: E0466 | I50: Compte épargne temps | J50: La date d'observation saisie du CET est non vide | K50: A_CET_DAGCET [Saisi] <> Vide | L50: T1128 | M50: Compte épargne temps - Ouverture sans opération | N50: Création Modification | O50: La date de l'opération saisie est vide. | P50: A_CET_DOOCET [Saisi] = Vide | Q50: Volontaire International | R50: P0178 | S50: Particulier | T50: Exclu | U50: 40725 | V50: 40725
A51: 24.10.00 | B51: M | C51: 45628.708 | D51: D0007 | E51: Congés/Absence | F51: S0049 | G51: Compte épargne temps | H51: E0466 | I51: Compte épargne temps | J51: La date d'observation saisie du CET est non vide | K51: A_CET_DAGCET [Saisi] <> Vide | L51: T1129 | M51: Compte épargne temps - Ouverture et opération "Consommation" | N51: Création Modification | O51: La date de l'opération saisie est non vide et le sens de l'opération est "Consommé". | P51: A_CET_DOOCET [Saisi] <> Vide ET A_CET_SEOCET [Saisi] = 'C' | Q51: Volontaire International | R51: P0178 | S51: Particulier | T51: Exclu | U51: 40725 | V51: 40725
A52: 24.10.00 | B52: M | C52: 45628.71 | D52: D0007 | E52: Congés/Absence | F52: S0049 | G52: Compte épargne temps | H52: E0466 | I52: Compte épargne temps | J52: La date d'observation saisie du CET est non vide | K52: A_CET_DAGCET [Saisi] <> Vide | L52: T1130 | M52: Compte épargne temps - Ouverture et opération "Versement" | N52: Création Modification | O52: La date de l'opération saisie est non vide et le sens de l'opération est "Versé". | P52: A_CET_DOOCET [Saisi] <> Vide ET A_CET_SEOCET [Saisi] = 'V' | Q52: Volontaire International | R52: P0178 | S52: Particulier | T52: Exclu | U52: 40725 | V52: 40725
A53: 24.10.00 | B53: M | C53: 45628.707 | D53: D0007 | E53: Congés/Absence | F53: S0049 | G53: Compte épargne temps | H53: E0466 | I53: Compte épargne temps | J53: La date d'observation saisie du CET est non vide | K53: A_CET_DAGCET [Saisi] <> Vide | L53: T1128 | M53: Compte épargne temps - Ouverture sans opération | N53: Création Modification | O53: La date de l'opération saisie est vide. | P53: A_CET_DOOCET [Saisi] = Vide | Q53: Personnel civil de coopération (assistant technique) | R53: P0214 | S53: Particulier | T53: Exclu | U53: 40725 | V53: 40725
A54: 24.10.00 | B54: M | C54: 45628.708 | D54: D0007 | E54: Congés/Absence | F54: S0049 | G54: Compte épargne temps | H54: E0466 | I54: Compte épargne temps | J54: La date d'observation saisie du CET est non vide | K54: A_CET_DAGCET [Saisi] <> Vide | L54: T1129 | M54: Compte épargne temps - Ouverture et opération "Consommation" | N54: Création Modification | O54: La date de l'opération saisie est non vide et le sens de l'opération est "Consommé". | P54: A_CET_DOOCET [Saisi] <> Vide ET A_CET_SEOCET [Saisi] = 'C' | Q54: Personnel civil de coopération (assistant technique) | R54: P0214 | S54: Particulier | T54: Exclu | U54: 40725 | V54: 40725
A55: 24.10.00 | B55: M | C55: 45628.71 | D55: D0007 | E55: Congés/Absence | F55: S0049 | G55: Compte épargne temps | H55: E0466 | I55: Compte épargne temps | J55: La date d'observation saisie du CET est non vide | K55: A_CET_DAGCET [Saisi] <> Vide | L55: T1130 | M55: Compte épargne temps - Ouverture et opération "Versement" | N55: Création Modification | O55: La date de l'opération saisie est non vide et le sens de l'opération est "Versé". | P55: A_CET_DOOCET [Saisi] <> Vide ET A_CET_SEOCET [Saisi] = 'V' | Q55: Personnel civil de coopération (assistant technique) | R55: P0214 | S55: Particulier | T55: Exclu | U55: 40725 | V55: 40725
A56: 24.10.00 | B56: M | C56: 45628.715 | D56: D0007 | E56: Congés/Absence | F56: S0049 | G56: Compte épargne temps | H56: E0468 | I56: Compte épargne temps transitoire | J56: La date d'observation saisie du CET est non vide | K56: A_CET_DAGTRA [Saisi] <> Vide | L56: T1131 | M56: Compte épargne temps transitoire - Ouverture sans opération | N56: Création Modification | O56: La date de l'opération saisie est vide. | P56: A_CET_DOOCET [Saisi] = Vide | Q56: Titulaire ou magistrat | R56: P0001 | S56: Général | T56: Passant | U56: 40725 | V56: 40725 | W56: CET_C_021 ET CET_C_012 ET CET_C_014 ET CET_C_015 ET CET_C_018 ET CET_C_031 | BB56: CET_C_021 | BC56: =VLOOKUP(BB56,'Axe 2 Règles de gestion'!$D$2:$F$84,3, FALSE) -> La date d'ouverture du CET transitoire doit être antérieure ou égale au 31/12/2008. | BD56: CET_C_012 | BE56: =VLOOKUP(BD56,'Axe 2 Règles de gestion'!$D$2:$F$84,3, FALSE) -> Le nombre de jours de l'opération doit être inférieur ou égal au nombre de jours du compteur global du CET transitoire. | BF56: CET_C_014 | BG56: =VLOOKUP(BF56,'Axe 2 Règles de gestion'!$D$2:$F$84,3, FALSE) -> La date de fermeture du CET transitoire doit être antérieure ou égale à la date limite de départ en retraite. | BH56: CET_C_015 | BI56: =VLOOKUP(BH56,'Axe 2 Règles de gestion'!$D$2:$F$84,3, FALSE) -> La date de fermeture du CET transitoire doit être antérieure ou égale à la date de fin réelle ou prévisionnelle du lien juridique. | BJ56: CET_C_018 | BK56: =VLOOKUP(BJ56,'Axe 2 Règles de gestion'!$D$2:$F$84,3, FALSE) -> La date d'ouverture du compte épargne temps transitoire doit être postérieure ou égale à la date d'entrée dans le SIRH. | BL56: CET_C_031 | BM56: =VLOOKUP(BL56,'Axe 2 Règles de gestion'!$D$2:$F$84,3, FALSE) -> Les champs "Origine", "Nombre de jours de l'opération", "Nombre de jours pour valorisation financière" et "Nombre de jours pour cotisation RAFP" ne doivent pas être renseignés.
A57: 18.10.00 | B57: M | C57: 43509.742 | D57: D0007 | E57: Congés/Absence | F57: S0049 | G57: Compte épargne temps | H57: E0468 | I57: Compte épargne temps transitoire | J57: La date d'observation saisie du CET est non vide | K57: A_CET_DAGTRA [Saisi] <> Vide | L57: T1132 | M57: Compte épargne temps transitoire - Ouverture et opération "Consommation" | N57: Création Modification | O57: La date de l'opération saisie est non vide. | P57: A_CET_DOOCET [Saisi] <> Vide | Q57: Titulaire ou magistrat | R57: P0001 | S57: Général | T57: Passant | U57: 40725 | V57: 43435 | W57: CET_I_026 ET CET_I_027 ET CET_I_023 ET CET_I_024 ET CET_D_055 ET CET_D_300 ET CET_C_021 ET CET_C_012 ET CET_C_014 ET CET_C_015 ET CET_C_018 ET CET_C_025 ET CET_C_027 ET CET_C_028 ET CET_C_030 | X57: CET_I_026 | Y57: =VLOOKUP(X57,'Axe 2 Règles de gestion'!$D$2:$F$84,3, FALSE) -> L'agent qui a demandé au 31 décembre 2009 le maintien de jours de congés sur son compte épargne-temps historique peut opter pour leur prise en compte au titre de l'épargne-retraite suivant les dispositions du régime pérenne. | Z57: CET_I_027 | AA57: =VLOOKUP(Z57,'Axe 2 Règles de gestion'!$D$2:$F$84,3, FALSE) -> L'agent qui a demandé au 31 décembre 2009 le maintien de jours de congés sur son compte épargne-temps historique peut opter pour leur indemnisation suivant les dispositions du régime pérenne. | AB57: CET_I_023 | AC57: =VLOOKUP(AB57,'Axe 2 Règles de gestion'!$D$2:$F$84,3, FALSE) -> Le versement s'effectue à hauteur de 4 jours par an jusqu'à épuisement du solde. | AD57: CET_I_024 | AE57: =VLOOKUP(AD57,'Axe 2 Règles de gestion'!$D$2:$F$84,3, FALSE) -> Si la durée de versement est supérieure à 4 ans, celui-ci est opéré en 4 fractions annuelles d'égal montant. | AL57: CET_D_055 | AM57: =VLOOKUP(AL57,'Axe 2 Règles de gestion'!$D$2:$F$84,3, FALSE) -> La différence entre le nombre de jours du compteur global du CET et le nombre de jours pour valorisation financière doit être strictement supérieure à 20 jours. | AN57: CET_D_300 | AO57: =VLOOKUP(AN57,'Axe 2 Règles de gestion'!$D$2:$F$84,3, FALSE) -> La différence entre le nombre de jours du compteur global du CET et le nombre de jours pour cotisation RAFP doit être strictement supérieure à 20 jours. | BB57: CET_C_021 | BC57: =VLOOKUP(BB57,'Axe 2 Règles de gestion'!$D$2:$F$84,3, FALSE) -> La date d'ouverture du CET transitoire doit être antérieure ou égale au 31/12/2008. | BD57: CET_C_012 | BE57: =VLOOKUP(BD57,'Axe 2 Règles de gestion'!$D$2:$F$84,3, FALSE) -> Le nombre de jours de l'opération doit être inférieur ou égal au nombre de jours du compteur global du CET transitoire. | BF57: CET_C_014 | BG57: =VLOOKUP(BF57,'Axe 2 Règles de gestion'!$D$2:$F$84,3, FALSE) -> La date de fermeture du CET transitoire doit être antérieure ou égale à la date limite de départ en retraite. | BH57: CET_C_015 | BI57: =VLOOKUP(BH57,'Axe 2 Règles de gestion'!$D$2:$F$84,3, FALSE) -> La date de fermeture du CET transitoire doit être antérieure ou égale à la date de fin réelle ou prévisionnelle du lien juridique. | BJ57: CET_C_018 | BK57: =VLOOKUP(BJ57,'Axe 2 Règles de gestion'!$D$2:$F$84,3, FALSE) -> La date d'ouverture du compte épargne temps transitoire doit être postérieure ou égale à la date d'entrée dans le SIRH. | BL57: CET_C_025 | BM57: =VLOOKUP(BL57,'Axe 2 Règles de gestion'!$D$2:$F$84,3, FALSE) -> Lorsque le sens de l'opération est à "consommé", le compteur global transitoire saisi est égal au compteur global transitoire de l'occurrence précédente duquel sont soustraits les jours consommés en congés. | BN57: CET_C_027 | BO57: =VLOOKUP(BN57,'Axe 2 Règles de gestion'!$D$2:$F$84,3, FALSE) -> Lorsque le sens de l'opération est égal à "consommé", l'origine des jours n'est pas à renseigner. | BP57: CET_C_028 | BQ57: =VLOOKUP(BP57,'Axe 2 Règles de gestion'!$D$2:$F$84,3, FALSE) -> Pour le compte épargne temps transitoire, seule l'opération de consommation en jours de congés est autorisée. Dans ce cas, l'origine des jours, le nombre de jours pour valorisation financière et le nombre de jours pour cotisation RAFP ne sont pas à renseigner. | BR57: CET_C_030 | BS57: =VLOOKUP(BR57,'Axe 2 Règles de gestion'!$D$2:$F$84,3, FALSE) -> Le sens de l'opération doit être à "consommé".
A58: 24.10.00 | B58: M | C58: 45628.717 | D58: D0007 | E58: Congés/Absence | F58: S0049 | G58: Compte épargne temps | H58: E0468 | I58: Compte épargne temps transitoire | J58: La date d'observation saisie du CET est non vide | K58: A_CET_DAGTRA [Saisi] <> Vide | L58: T1132 | M58: Compte épargne temps transitoire - Ouverture et opération "Consommation" | N58: Création Modification | O58: La date de l'opération saisie est non vide. | P58: A_CET_DOOCET [Saisi] <> Vide | Q58: Titulaire ou magistrat | R58: P0001 | S58: Général | T58: Passant | U58: 43436 | V58: 43436 | W58: CET_I_026 ET CET_I_027 ET CET_I_023 ET CET_I_024 ET CET_D_056 ET CET_D_301 ET CET_C_021 ET CET_C_012 ET CET_C_014 ET CET_C_015 ET CET_C_018 ET CET_C_025 ET CET_C_027 ET CET_C_028 ET CET_C_030 | X58: CET_I_026 | Y58: =VLOOKUP(X58,'Axe 2 Règles de gestion'!$D$2:$F$84,3, FALSE) -> L'agent qui a demandé au 31 décembre 2009 le maintien de jours de congés sur son compte épargne-temps historique peut opter pour leur prise en compte au titre de l'épargne-retraite suivant les dispositions du régime pérenne. | Z58: CET_I_027 | AA58: =VLOOKUP(Z58,'Axe 2 Règles de gestion'!$D$2:$F$84,3, FALSE) -> L'agent qui a demandé au 31 décembre 2009 le maintien de jours de congés sur son compte épargne-temps historique peut opter pour leur indemnisation suivant les dispositions du régime pérenne. | AB58: CET_I_023 | AC58: =VLOOKUP(AB58,'Axe 2 Règles de gestion'!$D$2:$F$84,3, FALSE) -> Le versement s'effectue à hauteur de 4 jours par an jusqu'à épuisement du solde. | AD58: CET_I_024 | AE58: =VLOOKUP(AD58,'Axe 2 Règles de gestion'!$D$2:$F$84,3, FALSE) -> Si la durée de versement est supérieure à 4 ans, celui-ci est opéré en 4 fractions annuelles d'égal montant. | AL58: CET_D_056 | AM58: =VLOOKUP(AL58,'Axe 2 Règles de gestion'!$D$2:$F$84,3, FALSE) -> La différence entre le nombre de jours du compteur global du CET et le nombre de jours pour valorisation financière doit être strictement supérieure à 15 jours. | AN58: CET_D_301 | AO58: =VLOOKUP(AN58,'Axe 2 Règles de gestion'!$D$2:$F$84,3, FALSE) -> La différence entre le nombre de jours du compteur global du CET et le nombre de jours pour cotisation RAFP doit être strictement supérieure à 15 jours. | BB58: CET_C_021 | BC58: =VLOOKUP(BB58,'Axe 2 Règles de gestion'!$D$2:$F$84,3, FALSE) -> La date d'ouverture du CET transitoire doit être antérieure ou égale au 31/12/2008. | BD58: CET_C_012 | BE58: =VLOOKUP(BD58,'Axe 2 Règles de gestion'!$D$2:$F$84,3, FALSE) -> Le nombre de jours de l'opération doit être inférieur ou égal au nombre de jours du compteur global du CET transitoire. | BF58: CET_C_014 | BG58: =VLOOKUP(BF58,'Axe 2 Règles de gestion'!$D$2:$F$84,3, FALSE) -> La date de fermeture du CET transitoire doit être antérieure ou égale à la date limite de départ en retraite. | BH58: CET_C_015 | BI58: =VLOOKUP(BH58,'Axe 2 Règles de gestion'!$D$2:$F$84,3, FALSE) -> La date de fermeture du CET transitoire doit être antérieure ou égale à la date de fin réelle ou prévisionnelle du lien juridique. | BJ58: CET_C_018 | BK58: =VLOOKUP(BJ58,'Axe 2 Règles de gestion'!$D$2:$F$84,3, FALSE) -> La date d'ouverture du compte épargne temps transitoire doit être postérieure ou égale à la date d'entrée dans le SIRH. | BL58: CET_C_025 | BM58: =VLOOKUP(BL58,'Axe 2 Règles de gestion'!$D$2:$F$84,3, FALSE) -> Lorsque le sens de l'opération est à "consommé", le compteur global transitoire saisi est égal au compteur global transitoire de l'occurrence précédente duquel sont soustraits les jours consommés en congés. | BN58: CET_C_027 | BO58: =VLOOKUP(BN58,'Axe 2 Règles de gestion'!$D$2:$F$84,3, FALSE) -> Lorsque le sens de l'opération est égal à "consommé", l'origine des jours n'est pas à renseigner. | BP58: CET_C_028 | BQ58: =VLOOKUP(BP58,'Axe 2 Règles de gestion'!$D$2:$F$84,3, FALSE) -> Pour le compte épargne temps transitoire, seule l'opération de consommation en jours de congés est autorisée. Dans ce cas, l'origine des jours, le nombre de jours pour valorisation financière et le nombre de jours pour cotisation RAFP ne sont pas à renseigner. | BR58: CET_C_030 | BS58: =VLOOKUP(BR58,'Axe 2 Règles de gestion'!$D$2:$F$84,3, FALSE) -> Le sens de l'opération doit être à "consommé".
A59: 24.10.00 | B59: M | C59: 45628.714 | D59: D0007 | E59: Congés/Absence | F59: S0049 | G59: Compte épargne temps | H59: E0468 | I59: Compte épargne temps transitoire | J59: La date d'observation saisie du CET est non vide | K59: A_CET_DAGTRA [Saisi] <> Vide | L59: T1131 | M59: Compte épargne temps transitoire - Ouverture sans opération | N59: Création Modification | O59: La date de l'opération saisie est vide. | P59: A_CET_DOOCET [Saisi] = Vide | Q59: Militaire | R59: P0002 | S59: Général | T59: Exclu | U59: 43831 | V59: 43831
A60: 24.10.00 | B60: M | C60: 45628.716 | D60: D0007 | E60: Congés/Absence | F60: S0049 | G60: Compte épargne temps | H60: E0468 | I60: Compte épargne temps transitoire | J60: La date d'observation saisie du CET est non vide | K60: A_CET_DAGTRA [Saisi] <> Vide | L60: T1132 | M60: Compte épargne temps transitoire - Ouverture et opération "Consommation" | N60: Création Modification | O60: La date de l'opération saisie est non vide. | P60: A_CET_DOOCET [Saisi] <> Vide | Q60: Militaire | R60: P0002 | S60: Général | T60: Exclu | U60: 43831 | V60: 43831
A61: 24.10.00 | B61: M | C61: 45628.714 | D61: D0007 | E61: Congés/Absence | F61: S0049 | G61: Compte épargne temps | H61: E0468 | I61: Compte épargne temps transitoire | J61: La date d'observation saisie du CET est non vide | K61: A_CET_DAGTRA [Saisi] <> Vide | L61: T1131 | M61: Compte épargne temps transitoire - Ouverture sans opération | N61: Création Modification | O61: La date de l'opération saisie est vide. | P61: A_CET_DOOCET [Saisi] = Vide | Q61: Contractuel | R61: P0003 | S61: Général | T61: Passant | U61: 40725 | V61: 40725 | W61: CET_C_021 ET CET_C_012 ET CET_C_014 ET CET_C_015 ET CET_C_018 ET CET_C_031 | BB61: CET_C_021 | BC61: =VLOOKUP(BB61,'Axe 2 Règles de gestion'!$D$2:$F$84,3, FALSE) -> La date d'ouverture du CET transitoire doit être antérieure ou égale au 31/12/2008. | BD61: CET_C_012 | BE61: =VLOOKUP(BD61,'Axe 2 Règles de gestion'!$D$2:$F$84,3, FALSE) -> Le nombre de jours de l'opération doit être inférieur ou égal au nombre de jours du compteur global du CET transitoire. | BF61: CET_C_014 | BG61: =VLOOKUP(BF61,'Axe 2 Règles de gestion'!$D$2:$F$84,3, FALSE) -> La date de fermeture du CET transitoire doit être antérieure ou égale à la date limite de départ en retraite. | BH61: CET_C_015 | BI61: =VLOOKUP(BH61,'Axe 2 Règles de gestion'!$D$2:$F$84,3, FALSE) -> La date de fermeture du CET transitoire doit être antérieure ou égale à la date de fin réelle ou prévisionnelle du lien juridique. | BJ61: CET_C_018 | BK61: =VLOOKUP(BJ61,'Axe 2 Règles de gestion'!$D$2:$F$84,3, FALSE) -> La date d'ouverture du compte épargne temps transitoire doit être postérieure ou égale à la date d'entrée dans le SIRH. | BL61: CET_C_031 | BM61: =VLOOKUP(BL61,'Axe 2 Règles de gestion'!$D$2:$F$84,3, FALSE) -> Les champs "Origine", "Nombre de jours de l'opération", "Nombre de jours pour valorisation financière" et "Nombre de jours pour cotisation RAFP" ne doivent pas être renseignés.
A62: 18.10.00 | B62: M | C62: 43509.747 | D62: D0007 | E62: Congés/Absence | F62: S0049 | G62: Compte épargne temps | H62: E0468 | I62: Compte épargne temps transitoire | J62: La date d'observation saisie du CET est non vide | K62: A_CET_DAGTRA [Saisi] <> Vide | L62: T1132 | M62: Compte épargne temps transitoire - Ouverture et opération "Consommation" | N62: Création Modification | O62: La date de l'opération saisie est non vide. | P62: A_CET_DOOCET [Saisi] <> Vide | Q62: Contractuel | R62: P0003 | S62: Général | T62: Passant | U62: 40725 | V62: 43435 | W62: CET_I_027 ET CET_I_023 ET CET_I_024 ET CET_D_055 ET CET_C_021 ET CET_C_012 ET CET_C_014 ET CET_C_015 ET CET_C_018 ET CET_C_022 ET CET_C_025 ET CET_C_027 ET CET_C_028 ET CET_C_030 | X62: CET_I_027 | Y62: =VLOOKUP(X62,'Axe 2 Règles de gestion'!$D$2:$F$84,3, FALSE) -> L'agent qui a demandé au 31 décembre 2009 le maintien de jours de congés sur son compte épargne-temps historique peut opter pour leur indemnisation suivant les dispositions du régime pérenne. | Z62: CET_I_023 | AA62: =VLOOKUP(Z62,'Axe 2 Règles de gestion'!$D$2:$F$84,3, FALSE) -> Le versement s'effectue à hauteur de 4 jours par an jusqu'à épuisement du solde. | AB62: CET_I_024 | AC62: =VLOOKUP(AB62,'Axe 2 Règles de gestion'!$D$2:$F$84,3, FALSE) -> Si la durée de versement est supérieure à 4 ans, celui-ci est opéré en 4 fractions annuelles d'égal montant. | AL62: CET_D_055 | AM62: =VLOOKUP(AL62,'Axe 2 Règles de gestion'!$D$2:$F$84,3, FALSE) -> La différence entre le nombre de jours du compteur global du CET et le nombre de jours pour valorisation financière doit être strictement supérieure à 20 jours. | BB62: CET_C_021 | BC62: =VLOOKUP(BB62,'Axe 2 Règles de gestion'!$D$2:$F$84,3, FALSE) -> La date d'ouverture du CET transitoire doit être antérieure ou égale au 31/12/2008. | BD62: CET_C_012 | BE62: =VLOOKUP(BD62,'Axe 2 Règles de gestion'!$D$2:$F$84,3, FALSE) -> Le nombre de jours de l'opération doit être inférieur ou égal au nombre de jours du compteur global du CET transitoire. | BF62: CET_C_014 | BG62: =VLOOKUP(BF62,'Axe 2 Règles de gestion'!$D$2:$F$84,3, FALSE) -> La date de fermeture du CET transitoire doit être antérieure ou égale à la date limite de départ en retraite. | BH62: CET_C_015 | BI62: =VLOOKUP(BH62,'Axe 2 Règles de gestion'!$D$2:$F$84,3, FALSE) -> La date de fermeture du CET transitoire doit être antérieure ou égale à la date de fin réelle ou prévisionnelle du lien juridique. | BJ62: CET_C_018 | BK62: =VLOOKUP(BJ62,'Axe 2 Règles de gestion'!$D$2:$F$84,3, FALSE) -> La date d'ouverture du compte épargne temps transitoire doit être postérieure ou égale à la date d'entrée dans le SIRH. | BL62: CET_C_022 | BM62: =VLOOKUP(BL62,'Axe 2 Règles de gestion'!$D$2:$F$84,3, FALSE) -> Lorsque le sens de l'opération est égal à "consommé", le nombre de jours pour la cotisation RAFP n'est pas à renseigner. | BN62: CET_C_025 | BO62: =VLOOKUP(BN62,'Axe 2 Règles de gestion'!$D$2:$F$84,3, FALSE) -> Lorsque le sens de l'opération est à "consommé", le compteur global transitoire saisi est égal au compteur global transitoire de l'occurrence précédente duquel sont soustraits les jours consommés en congés. | BP62: CET_C_027 | BQ62: =VLOOKUP(BP62,'Axe 2 Règles de gestion'!$D$2:$F$84,3, FALSE) -> Lorsque le sens de l'opération est égal à "consommé", l'origine des jours n'est pas à renseigner. | BR62: CET_C_028 | BS62: =VLOOKUP(BR62,'Axe 2 Règles de gestion'!$D$2:$F$84,3, FALSE) -> Pour le compte épargne temps transitoire, seule l'opération de consommation en jours de congés est autorisée. Dans ce cas, l'origine des jours, le nombre de jours pour valorisation financière et le nombre de jours pour cotisation RAFP ne sont pas à renseigner. | BT62: CET_C_030 | BU62: =VLOOKUP(BT62,'Axe 2 Règles de gestion'!$D$2:$F$84,3, FALSE) -> Le sens de l'opération doit être à "consommé".
A63: 24.10.00 | B63: M | C63: 45628.716 | D63: D0007 | E63: Congés/Absence | F63: S0049 | G63: Compte épargne temps | H63: E0468 | I63: Compte épargne temps transitoire | J63: La date d'observation saisie du CET est non vide | K63: A_CET_DAGTRA [Saisi] <> Vide | L63: T1132 | M63: Compte épargne temps transitoire - Ouverture et opération "Consommation" | N63: Création Modification | O63: La date de l'opération saisie est non vide. | P63: A_CET_DOOCET [Saisi] <> Vide | Q63: Contractuel | R63: P0003 | S63: Général | T63: Passant | U63: 43436 | V63: 43436 | W63: CET_I_027 ET CET_I_023 ET CET_I_024 ET CET_D_056 ET CET_C_021 ET CET_C_012 ET CET_C_014 ET CET_C_015 ET CET_C_018 ET CET_C_022 ET CET_C_025 ET CET_C_027 ET CET_C_028 ET CET_C_030 | X63: CET_I_027 | Y63: =VLOOKUP(X63,'Axe 2 Règles de gestion'!$D$2:$F$84,3, FALSE) -> L'agent qui a demandé au 31 décembre 2009 le maintien de jours de congés sur son compte épargne-temps historique peut opter pour leur indemnisation suivant les dispositions du régime pérenne. | Z63: CET_I_023 | AA63: =VLOOKUP(Z63,'Axe 2 Règles de gestion'!$D$2:$F$84,3, FALSE) -> Le versement s'effectue à hauteur de 4 jours par an jusqu'à épuisement du solde. | AB63: CET_I_024 | AC63: =VLOOKUP(AB63,'Axe 2 Règles de gestion'!$D$2:$F$84,3, FALSE) -> Si la durée de versement est supérieure à 4 ans, celui-ci est opéré en 4 fractions annuelles d'égal montant. | AL63: CET_D_056 | AM63: =VLOOKUP(AL63,'Axe 2 Règles de gestion'!$D$2:$F$84,3, FALSE) -> La différence entre le nombre de jours du compteur global du CET et le nombre de jours pour valorisation financière doit être strictement supérieure à 15 jours. | BB63: CET_C_021 | BC63: =VLOOKUP(BB63,'Axe 2 Règles de gestion'!$D$2:$F$84,3, FALSE) -> La date d'ouverture du CET transitoire doit être antérieure ou égale au 31/12/2008. | BD63: CET_C_012 | BE63: =VLOOKUP(BD63,'Axe 2 Règles de gestion'!$D$2:$F$84,3, FALSE) -> Le nombre de jours de l'opération doit être inférieur ou égal au nombre de jours du compteur global du CET transitoire. | BF63: CET_C_014 | BG63: =VLOOKUP(BF63,'Axe 2 Règles de gestion'!$D$2:$F$84,3, FALSE) -> La date de fermeture du CET transitoire doit être antérieure ou égale à la date limite de départ en retraite. | BH63: CET_C_015 | BI63: =VLOOKUP(BH63,'Axe 2 Règles de gestion'!$D$2:$F$84,3, FALSE) -> La date de fermeture du CET transitoire doit être antérieure ou égale à la date de fin réelle ou prévisionnelle du lien juridique. | BJ63: CET_C_018 | BK63: =VLOOKUP(BJ63,'Axe 2 Règles de gestion'!$D$2:$F$84,3, FALSE) -> La date d'ouverture du compte épargne temps transitoire doit être postérieure ou égale à la date d'entrée dans le SIRH. | BL63: CET_C_022 | BM63: =VLOOKUP(BL63,'Axe 2 Règles de gestion'!$D$2:$F$84,3, FALSE) -> Lorsque le sens de l'opération est égal à "consommé", le nombre de jours pour la cotisation RAFP n'est pas à renseigner. | BN63: CET_C_025 | BO63: =VLOOKUP(BN63,'Axe 2 Règles de gestion'!$D$2:$F$84,3, FALSE) -> Lorsque le sens de l'opération est à "consommé", le compteur global transitoire saisi est égal au compteur global transitoire de l'occurrence précédente duquel sont soustraits les jours consommés en congés. | BP63: CET_C_027 | BQ63: =VLOOKUP(BP63,'Axe 2 Règles de gestion'!$D$2:$F$84,3, FALSE) -> Lorsque le sens de l'opération est égal à "consommé", l'origine des jours n'est pas à renseigner. | BR63: CET_C_028 | BS63: =VLOOKUP(BR63,'Axe 2 Règles de gestion'!$D$2:$F$84,3, FALSE) -> Pour le compte épargne temps transitoire, seule l'opération de consommation en jours de congés est autorisée. Dans ce cas, l'origine des jours, le nombre de jours pour valorisation financière et le nombre de jours pour cotisation RAFP ne sont pas à renseigner. | BT63: CET_C_030 | BU63: =VLOOKUP(BT63,'Axe 2 Règles de gestion'!$D$2:$F$84,3, FALSE) -> Le sens de l'opération doit être à "consommé".
A64: 24.10.00 | B64: M | C64: 45628.715 | D64: D0007 | E64: Congés/Absence | F64: S0049 | G64: Compte épargne temps | H64: E0468 | I64: Compte épargne temps transitoire | J64: La date d'observation saisie du CET est non vide | K64: A_CET_DAGTRA [Saisi] <> Vide | L64: T1131 | M64: Compte épargne temps transitoire - Ouverture sans opération | N64: Création Modification | O64: La date de l'opération saisie est vide. | P64: A_CET_DOOCET [Saisi] = Vide | Q64: Stagiaire ou auditeur ou élève | R64: P0004 | S64: Général | T64: Exclu | U64: 40725 | V64: 40725
A65: 24.10.00 | B65: M | C65: 45628.717 | D65: D0007 | E65: Congés/Absence | F65: S0049 | G65: Compte épargne temps | H65: E0468 | I65: Compte épargne temps transitoire | J65: La date d'observation saisie du CET est non vide | K65: A_CET_DAGTRA [Saisi] <> Vide | L65: T1132 | M65: Compte épargne temps transitoire - Ouverture et opération "Consommation" | N65: Création Modification | O65: La date de l'opération saisie est non vide. | P65: A_CET_DOOCET [Saisi] <> Vide | Q65: Stagiaire ou auditeur ou élève | R65: P0004 | S65: Général | T65: Exclu | U65: 40725 | V65: 40725
A66: 24.10.00 | B66: M | C66: 45628.715 | D66: D0007 | E66: Congés/Absence | F66: S0049 | G66: Compte épargne temps | H66: E0468 | I66: Compte épargne temps transitoire | J66: La date d'observation saisie du CET est non vide | K66: A_CET_DAGTRA [Saisi] <> Vide | L66: T1131 | M66: Compte épargne temps transitoire - Ouverture sans opération | N66: Création Modification | O66: La date de l'opération saisie est vide. | P66: A_CET_DOOCET [Saisi] = Vide | Q66: Ouvrier d'état | R66: P0005 | S66: Général | T66: Exclu | U66: 40725 | V66: 40725
A67: 24.10.00 | B67: M | C67: 45628.717 | D67: D0007 | E67: Congés/Absence | F67: S0049 | G67: Compte épargne temps | H67: E0468 | I67: Compte épargne temps transitoire | J67: La date d'observation saisie du CET est non vide | K67: A_CET_DAGTRA [Saisi] <> Vide | L67: T1132 | M67: Compte épargne temps transitoire - Ouverture et opération "Consommation" | N67: Création Modification | O67: La date de l'opération saisie est non vide. | P67: A_CET_DOOCET [Saisi] <> Vide | Q67: Ouvrier d'état | R67: P0005 | S67: Général | T67: Exclu | U67: 40725 | V67: 40725
A68: 24.10.00 | B68: M | C68: 45628.717 | D68: D0007 | E68: Congés/Absence | F68: S0049 | G68: Compte épargne temps | H68: E0468 | I68: Compte épargne temps transitoire | J68: La date d'observation saisie du CET est non vide | K68: A_CET_DAGTRA [Saisi] <> Vide | L68: T1131 | M68: Compte épargne temps transitoire - Ouverture sans opération | N68: Création Modification | O68: La date de l'opération saisie est vide. | P68: A_CET_DOOCET [Saisi] = Vide | Q68: Expert technique international | R68: P0018 | S68: Particulier | T68: Exclu | U68: 40725 | V68: 40725
A69: 24.10.00 | B69: M | C69: 45628.719 | D69: D0007 | E69: Congés/Absence | F69: S0049 | G69: Compte épargne temps | H69: E0468 | I69: Compte épargne temps transitoire | J69: La date d'observation saisie du CET est non vide | K69: A_CET_DAGTRA [Saisi] <> Vide | L69: T1132 | M69: Compte épargne temps transitoire - Ouverture et opération "Consommation" | N69: Création Modification | O69: La date de l'opération saisie est non vide. | P69: A_CET_DOOCET [Saisi] <> Vide | Q69: Expert technique international | R69: P0018 | S69: Particulier | T69: Exclu | U69: 40725 | V69: 40725
A70: 24.10.00 | B70: M | C70: 45628.718 | D70: D0007 | E70: Congés/Absence | F70: S0049 | G70: Compte épargne temps | H70: E0468 | I70: Compte épargne temps transitoire | J70: La date d'observation saisie du CET est non vide | K70: A_CET_DAGTRA [Saisi] <> Vide | L70: T1131 | M70: Compte épargne temps transitoire - Ouverture sans opération | N70: Création Modification | O70: La date de l'opération saisie est vide. | P70: A_CET_DOOCET [Saisi] = Vide | Q70: Personnel civil payé à l'acte ou à la tâche | R70: P0054 | S70: Particulier | T70: Exclu | U70: 40725 | V70: 40725
A71: 24.10.00 | B71: M | C71: 45628.719 | D71: D0007 | E71: Congés/Absence | F71: S0049 | G71: Compte épargne temps | H71: E0468 | I71: Compte épargne temps transitoire | J71: La date d'observation saisie du CET est non vide | K71: A_CET_DAGTRA [Saisi] <> Vide | L71: T1132 | M71: Compte épargne temps transitoire - Ouverture et opération "Consommation" | N71: Création Modification | O71: La date de l'opération saisie est non vide. | P71: A_CET_DOOCET [Saisi] <> Vide | Q71: Personnel civil payé à l'acte ou à la tâche | R71: P0054 | S71: Particulier | T71: Exclu | U71: 40725 | V71: 40725
A72: 24.10.00 | B72: M | C72: 45628.718 | D72: D0007 | E72: Congés/Absence | F72: S0049 | G72: Compte épargne temps | H72: E0468 | I72: Compte épargne temps transitoire | J72: La date d'observation saisie du CET est non vide | K72: A_CET_DAGTRA [Saisi] <> Vide | L72: T1131 | M72: Compte épargne temps transitoire - Ouverture sans opération | N72: Création Modification | O72: La date de l'opération saisie est vide. | P72: A_CET_DOOCET [Saisi] = Vide | Q72: Contractuel de droit privé | R72: P0072 | S72: Particulier | T72: Exclu | U72: 40725 | V72: 40725
A73: 24.10.00 | B73: M | C73: 45628.719 | D73: D0007 | E73: Congés/Absence | F73: S0049 | G73: Compte épargne temps | H73: E0468 | I73: Compte épargne temps transitoire | J73: La date d'observation saisie du CET est non vide | K73: A_CET_DAGTRA [Saisi] <> Vide | L73: T1132 | M73: Compte épargne temps transitoire - Ouverture et opération "Consommation" | N73: Création Modification | O73: La date de l'opération saisie est non vide. | P73: A_CET_DOOCET [Saisi] <> Vide | Q73: Contractuel de droit privé | R73: P0072 | S73: Particulier | T73: Exclu | U73: 40725 | V73: 40725
A74: 18.10.00 | B74: M | C74: 43152.5 | D74: D0007 | E74: Congés/Absence | F74: S0049 | G74: Compte épargne temps | H74: E0468 | I74: Compte épargne temps transitoire | J74: La date d'observation saisie du CET est non vide | K74: A_CET_DAGTRA [Saisi] <> Vide | L74: T1131 | M74: Compte épargne temps transitoire - Ouverture sans opération | N74: Création Modification | O74: La date de l'opération saisie est vide. | P74: A_CET_DOOCET [Saisi] = Vide | Q74: Ouvrier de la défense réglementé affilié | R74: P0093 | S74: Particulier | T74: Passant | U74: 40725 | W74: CET_C_021 ET CET_C_012 ET CET_C_014 ET CET_C_015 ET CET_C_018 ET CET_C_031 | BB74: CET_C_021 | BC74: =VLOOKUP(BB74,'Axe 2 Règles de gestion'!$D$2:$F$84,3, FALSE) -> La date d'ouverture du CET transitoire doit être antérieure ou égale au 31/12/2008. | BD74: CET_C_012 | BE74: =VLOOKUP(BD74,'Axe 2 Règles de gestion'!$D$2:$F$84,3, FALSE) -> Le nombre de jours de l'opération doit être inférieur ou égal au nombre de jours du compteur global du CET transitoire. | BF74: CET_C_014 | BG74: =VLOOKUP(BF74,'Axe 2 Règles de gestion'!$D$2:$F$84,3, FALSE) -> La date de fermeture du CET transitoire doit être antérieure ou égale à la date limite de départ en retraite. | BH74: CET_C_015 | BI74: =VLOOKUP(BH74,'Axe 2 Règles de gestion'!$D$2:$F$84,3, FALSE) -> La date de fermeture du CET transitoire doit être antérieure ou égale à la date de fin réelle ou prévisionnelle du lien juridique. | BJ74: CET_C_018 | BK74: =VLOOKUP(BJ74,'Axe 2 Règles de gestion'!$D$2:$F$84,3, FALSE) -> La date d'ouverture du compte épargne temps transitoire doit être postérieure ou égale à la date d'entrée dans le SIRH. | BL74: CET_C_031 | BM74: =VLOOKUP(BL74,'Axe 2 Règles de gestion'!$D$2:$F$84,3, FALSE) -> Les champs "Origine", "Nombre de jours de l'opération", "Nombre de jours pour valorisation financière" et "Nombre de jours pour cotisation RAFP" ne doivent pas être renseignés.
A75: 18.10.00 | B75: M | C75: 43545.809 | D75: D0007 | E75: Congés/Absence | F75: S0049 | G75: Compte épargne temps | H75: E0468 | I75: Compte épargne temps transitoire | J75: La date d'observation saisie du CET est non vide | K75: A_CET_DAGTRA [Saisi] <> Vide | L75: T1132 | M75: Compte épargne temps transitoire - Ouverture et opération "Consommation" | N75: Création Modification | O75: La date de l'opération saisie est non vide. | P75: A_CET_DOOCET [Saisi] <> Vide | Q75: Ouvrier de la défense réglementé affilié | R75: P0093 | S75: Particulier | T75: Passant | U75: 40725 | V75: 43435 | W75: CET_I_027 ET CET_D_096 ET CET_C_021 ET CET_C_012 ET CET_C_014 ET CET_C_015 ET CET_C_018 ET CET_C_022 ET CET_C_025 ET CET_C_027 ET CET_C_028 ET CET_C_030 | X75: CET_I_027 | Y75: =VLOOKUP(X75,'Axe 2 Règles de gestion'!$D$2:$F$84,3, FALSE) -> L'agent qui a demandé au 31 décembre 2009 le maintien de jours de congés sur son compte épargne-temps historique peut opter pour leur indemnisation suivant les dispositions du régime pérenne. | AL75: CET_D_096 | AM75: =VLOOKUP(AL75,'Axe 2 Règles de gestion'!$D$2:$F$84,3, FALSE) -> La différence entre le nombre de jours du compteur global du CET et le nombre de jours pour valorisation financière doit être strictement supérieure à 20 jours. | BB75: CET_C_021 | BC75: =VLOOKUP(BB75,'Axe 2 Règles de gestion'!$D$2:$F$84,3, FALSE) -> La date d'ouverture du CET transitoire doit être antérieure ou égale au 31/12/2008. | BD75: CET_C_012 | BE75: =VLOOKUP(BD75,'Axe 2 Règles de gestion'!$D$2:$F$84,3, FALSE) -> Le nombre de jours de l'opération doit être inférieur ou égal au nombre de jours du compteur global du CET transitoire. | BF75: CET_C_014 | BG75: =VLOOKUP(BF75,'Axe 2 Règles de gestion'!$D$2:$F$84,3, FALSE) -> La date de fermeture du CET transitoire doit être antérieure ou égale à la date limite de départ en retraite. | BH75: CET_C_015 | BI75: =VLOOKUP(BH75,'Axe 2 Règles de gestion'!$D$2:$F$84,3, FALSE) -> La date de fermeture du CET transitoire doit être antérieure ou égale à la date de fin réelle ou prévisionnelle du lien juridique. | BJ75: CET_C_018 | BK75: =VLOOKUP(BJ75,'Axe 2 Règles de gestion'!$D$2:$F$84,3, FALSE) -> La date d'ouverture du compte épargne temps transitoire doit être postérieure ou égale à la date d'entrée dans le SIRH. | BL75: CET_C_022 | BM75: =VLOOKUP(BL75,'Axe 2 Règles de gestion'!$D$2:$F$84,3, FALSE) -> Lorsque le sens de l'opération est égal à "consommé", le nombre de jours pour la cotisation RAFP n'est pas à renseigner. | BN75: CET_C_025 | BO75: =VLOOKUP(BN75,'Axe 2 Règles de gestion'!$D$2:$F$84,3, FALSE) -> Lorsque le sens de l'opération est à "consommé", le compteur global transitoire saisi est égal au compteur global transitoire de l'occurrence précédente duquel sont soustraits les jours consommés en congés. | BP75: CET_C_027 | BQ75: =VLOOKUP(BP75,'Axe 2 Règles de gestion'!$D$2:$F$84,3, FALSE) -> Lorsque le sens de l'opération est égal à "consommé", l'origine des jours n'est pas à renseigner. | BR75: CET_C_028 | BS75: =VLOOKUP(BR75,'Axe 2 Règles de gestion'!$D$2:$F$84,3, FALSE) -> Pour le compte épargne temps transitoire, seule l'opération de consommation en jours de congés est autorisée. Dans ce cas, l'origine des jours, le nombre de jours pour valorisation financière et le nombre de jours pour cotisation RAFP ne sont pas à renseigner. | BT75: CET_C_030 | BU75: =VLOOKUP(BT75,'Axe 2 Règles de gestion'!$D$2:$F$84,3, FALSE) -> Le sens de l'opération doit être à "consommé".
A76: 18.10.00 | B76: A | C76: 43545.809 | D76: D0007 | E76: Congés/Absence | F76: S0049 | G76: Compte épargne temps | H76: E0468 | I76: Compte épargne temps transitoire | J76: La date d'observation saisie du CET est non vide | K76: A_CET_DAGTRA [Saisi] <> Vide | L76: T1132 | M76: Compte épargne temps transitoire - Ouverture et opération "Consommation" | N76: Création Modification | O76: La date de l'opération saisie est non vide. | P76: A_CET_DOOCET [Saisi] <> Vide | Q76: Ouvrier de la défense réglementé affilié | R76: P0093 | S76: Particulier | T76: Passant | U76: 43436 | W76: CET_I_027 ET CET_D_097 ET CET_C_021 ET CET_C_012 ET CET_C_014 ET CET_C_015 ET CET_C_018 ET CET_C_022 ET CET_C_025 ET CET_C_027 ET CET_C_028 ET CET_C_030 | X76: CET_I_027 | Y76: =VLOOKUP(X76,'Axe 2 Règles de gestion'!$D$2:$F$84,3, FALSE) -> L'agent qui a demandé au 31 décembre 2009 le maintien de jours de congés sur son compte épargne-temps historique peut opter pour leur indemnisation suivant les dispositions du régime pérenne. | AL76: CET_D_097 | AM76: =VLOOKUP(AL76,'Axe 2 Règles de gestion'!$D$2:$F$84,3, FALSE) -> La différence entre le nombre de jours du compteur global du CET et le nombre de jours pour valorisation financière doit être strictement supérieure à 15 jours. | BB76: CET_C_021 | BC76: =VLOOKUP(BB76,'Axe 2 Règles de gestion'!$D$2:$F$84,3, FALSE) -> La date d'ouverture du CET transitoire doit être antérieure ou égale au 31/12/2008. | BD76: CET_C_012 | BE76: =VLOOKUP(BD76,'Axe 2 Règles de gestion'!$D$2:$F$84,3, FALSE) -> Le nombre de jours de l'opération doit être inférieur ou égal au nombre de jours du compteur global du CET transitoire. | BF76: CET_C_014 | BG76: =VLOOKUP(BF76,'Axe 2 Règles de gestion'!$D$2:$F$84,3, FALSE) -> La date de fermeture du CET transitoire doit être antérieure ou égale à la date limite de départ en retraite. | BH76: CET_C_015 | BI76: =VLOOKUP(BH76,'Axe 2 Règles de gestion'!$D$2:$F$84,3, FALSE) -> La date de fermeture du CET transitoire doit être antérieure ou égale à la date de fin réelle ou prévisionnelle du lien juridique. | BJ76: CET_C_018 | BK76: =VLOOKUP(BJ76,'Axe 2 Règles de gestion'!$D$2:$F$84,3, FALSE) -> La date d'ouverture du compte épargne temps transitoire doit être postérieure ou égale à la date d'entrée dans le SIRH. | BL76: CET_C_022 | BM76: =VLOOKUP(BL76,'Axe 2 Règles de gestion'!$D$2:$F$84,3, FALSE) -> Lorsque le sens de l'opération est égal à "consommé", le nombre de jours pour la cotisation RAFP n'est pas à renseigner. | BN76: CET_C_025 | BO76: =VLOOKUP(BN76,'Axe 2 Règles de gestion'!$D$2:$F$84,3, FALSE) -> Lorsque le sens de l'opération est à "consommé", le compteur global transitoire saisi est égal au compteur global transitoire de l'occurrence précédente duquel sont soustraits les jours consommés en congés. | BP76: CET_C_027 | BQ76: =VLOOKUP(BP76,'Axe 2 Règles de gestion'!$D$2:$F$84,3, FALSE) -> Lorsque le sens de l'opération est égal à "consommé", l'origine des jours n'est pas à renseigner. | BR76: CET_C_028 | BS76: =VLOOKUP(BR76,'Axe 2 Règles de gestion'!$D$2:$F$84,3, FALSE) -> Pour le compte épargne temps transitoire, seule l'opération de consommation en jours de congés est autorisée. Dans ce cas, l'origine des jours, le nombre de jours pour valorisation financière et le nombre de jours pour cotisation RAFP ne sont pas à renseigner. | BT76: CET_C_030 | BU76: =VLOOKUP(BT76,'Axe 2 Règles de gestion'!$D$2:$F$84,3, FALSE) -> Le sens de l'opération doit être à "consommé".
A77: 18.10.00 | B77: M | C77: 43152.5 | D77: D0007 | E77: Congés/Absence | F77: S0049 | G77: Compte épargne temps | H77: E0468 | I77: Compte épargne temps transitoire | J77: La date d'observation saisie du CET est non vide | K77: A_CET_DAGTRA [Saisi] <> Vide | L77: T1131 | M77: Compte épargne temps transitoire - Ouverture sans opération | N77: Création Modification | O77: La date de l'opération saisie est vide. | P77: A_CET_DOOCET [Saisi] = Vide | Q77: Ouvrier du service des alcools | R77: P0094 | S77: Particulier | T77: Passant | U77: 40725 | W77: CET_C_021 ET CET_C_012 ET CET_C_014 ET CET_C_015 ET CET_C_018 ET CET_C_031 | BB77: CET_C_021 | BC77: =VLOOKUP(BB77,'Axe 2 Règles de gestion'!$D$2:$F$84,3, FALSE) -> La date d'ouverture du CET transitoire doit être antérieure ou égale au 31/12/2008. | BD77: CET_C_012 | BE77: =VLOOKUP(BD77,'Axe 2 Règles de gestion'!$D$2:$F$84,3, FALSE) -> Le nombre de jours de l'opération doit être inférieur ou égal au nombre de jours du compteur global du CET transitoire. | BF77: CET_C_014 | BG77: =VLOOKUP(BF77,'Axe 2 Règles de gestion'!$D$2:$F$84,3, FALSE) -> La date de fermeture du CET transitoire doit être antérieure ou égale à la date limite de départ en retraite. | BH77: CET_C_015 | BI77: =VLOOKUP(BH77,'Axe 2 Règles de gestion'!$D$2:$F$84,3, FALSE) -> La date de fermeture du CET transitoire doit être antérieure ou égale à la date de fin réelle ou prévisionnelle du lien juridique. | BJ77: CET_C_018 | BK77: =VLOOKUP(BJ77,'Axe 2 Règles de gestion'!$D$2:$F$84,3, FALSE) -> La date d'ouverture du compte épargne temps transitoire doit être postérieure ou égale à la date d'entrée dans le SIRH. | BL77: CET_C_031 | BM77: =VLOOKUP(BL77,'Axe 2 Règles de gestion'!$D$2:$F$84,3, FALSE) -> Les champs "Origine", "Nombre de jours de l'opération", "Nombre de jours pour valorisation financière" et "Nombre de jours pour cotisation RAFP" ne doivent pas être renseignés.
A78: 18.10.00 | B78: M | C78: 43509.749 | D78: D0007 | E78: Congés/Absence | F78: S0049 | G78: Compte épargne temps | H78: E0468 | I78: Compte épargne temps transitoire | J78: La date d'observation saisie du CET est non vide | K78: A_CET_DAGTRA [Saisi] <> Vide | L78: T1132 | M78: Compte épargne temps transitoire - Ouverture et opération "Consommation" | N78: Création Modification | O78: La date de l'opération saisie est non vide. | P78: A_CET_DOOCET [Saisi] <> Vide | Q78: Ouvrier du service des alcools | R78: P0094 | S78: Particulier | T78: Passant | U78: 40725 | V78: 43435 | W78: CET_I_027 ET CET_I_023 ET CET_I_024 ET CET_D_055 ET CET_C_021 ET CET_C_012 ET CET_C_014 ET CET_C_015 ET CET_C_018 ET CET_C_022 ET CET_C_025 ET CET_C_027 ET CET_C_028 ET CET_C_030 | X78: CET_I_027 | Y78: =VLOOKUP(X78,'Axe 2 Règles de gestion'!$D$2:$F$84,3, FALSE) -> L'agent qui a demandé au 31 décembre 2009 le maintien de jours de congés sur son compte épargne-temps historique peut opter pour leur indemnisation suivant les dispositions du régime pérenne. | Z78: CET_I_023 | AA78: =VLOOKUP(Z78,'Axe 2 Règles de gestion'!$D$2:$F$84,3, FALSE) -> Le versement s'effectue à hauteur de 4 jours par an jusqu'à épuisement du solde. | AB78: CET_I_024 | AC78: =VLOOKUP(AB78,'Axe 2 Règles de gestion'!$D$2:$F$84,3, FALSE) -> Si la durée de versement est supérieure à 4 ans, celui-ci est opéré en 4 fractions annuelles d'égal montant. | AL78: CET_D_055 | AM78: =VLOOKUP(AL78,'Axe 2 Règles de gestion'!$D$2:$F$84,3, FALSE) -> La différence entre le nombre de jours du compteur global du CET et le nombre de jours pour valorisation financière doit être strictement supérieure à 20 jours. | BB78: CET_C_021 | BC78: =VLOOKUP(BB78,'Axe 2 Règles de gestion'!$D$2:$F$84,3, FALSE) -> La date d'ouverture du CET transitoire doit être antérieure ou égale au 31/12/2008. | BD78: CET_C_012 | BE78: =VLOOKUP(BD78,'Axe 2 Règles de gestion'!$D$2:$F$84,3, FALSE) -> Le nombre de jours de l'opération doit être inférieur ou égal au nombre de jours du compteur global du CET transitoire. | BF78: CET_C_014 | BG78: =VLOOKUP(BF78,'Axe 2 Règles de gestion'!$D$2:$F$84,3, FALSE) -> La date de fermeture du CET transitoire doit être antérieure ou égale à la date limite de départ en retraite. | BH78: CET_C_015 | BI78: =VLOOKUP(BH78,'Axe 2 Règles de gestion'!$D$2:$F$84,3, FALSE) -> La date de fermeture du CET transitoire doit être antérieure ou égale à la date de fin réelle ou prévisionnelle du lien juridique. | BJ78: CET_C_018 | BK78: =VLOOKUP(BJ78,'Axe 2 Règles de gestion'!$D$2:$F$84,3, FALSE) -> La date d'ouverture du compte épargne temps transitoire doit être postérieure ou égale à la date d'entrée dans le SIRH. | BL78: CET_C_022 | BM78: =VLOOKUP(BL78,'Axe 2 Règles de gestion'!$D$2:$F$84,3, FALSE) -> Lorsque le sens de l'opération est égal à "consommé", le nombre de jours pour la cotisation RAFP n'est pas à renseigner. | BN78: CET_C_025 | BO78: =VLOOKUP(BN78,'Axe 2 Règles de gestion'!$D$2:$F$84,3, FALSE) -> Lorsque le sens de l'opération est à "consommé", le compteur global transitoire saisi est égal au compteur global transitoire de l'occurrence précédente duquel sont soustraits les jours consommés en congés. | BP78: CET_C_027 | BQ78: =VLOOKUP(BP78,'Axe 2 Règles de gestion'!$D$2:$F$84,3, FALSE) -> Lorsque le sens de l'opération est égal à "consommé", l'origine des jours n'est pas à renseigner. | BR78: CET_C_028 | BS78: =VLOOKUP(BR78,'Axe 2 Règles de gestion'!$D$2:$F$84,3, FALSE) -> Pour le compte épargne temps transitoire, seule l'opération de consommation en jours de congés est autorisée. Dans ce cas, l'origine des jours, le nombre de jours pour valorisation financière et le nombre de jours pour cotisation RAFP ne sont pas à renseigner. | BT78: CET_C_030 | BU78: =VLOOKUP(BT78,'Axe 2 Règles de gestion'!$D$2:$F$84,3, FALSE) -> Le sens de l'opération doit être à "consommé".
A79: 18.10.00 | B79: A | C79: 43509.749 | D79: D0007 | E79: Congés/Absence | F79: S0049 | G79: Compte épargne temps | H79: E0468 | I79: Compte épargne temps transitoire | J79: La date d'observation saisie du CET est non vide | K79: A_CET_DAGTRA [Saisi] <> Vide | L79: T1132 | M79: Compte épargne temps transitoire - Ouverture et opération "Consommation" | N79: Création Modification | O79: La date de l'opération saisie est non vide. | P79: A_CET_DOOCET [Saisi] <> Vide | Q79: Ouvrier du service des alcools | R79: P0094 | S79: Particulier | T79: Passant | U79: 43436 | W79: CET_I_027 ET CET_I_023 ET CET_I_024 ET CET_D_056 ET CET_C_021 ET CET_C_012 ET CET_C_014 ET CET_C_015 ET CET_C_018 ET CET_C_022 ET CET_C_025 ET CET_C_027 ET CET_C_028 ET CET_C_030 | X79: CET_I_027 | Y79: =VLOOKUP(X79,'Axe 2 Règles de gestion'!$D$2:$F$84,3, FALSE) -> L'agent qui a demandé au 31 décembre 2009 le maintien de jours de congés sur son compte épargne-temps historique peut opter pour leur indemnisation suivant les dispositions du régime pérenne. | Z79: CET_I_023 | AA79: =VLOOKUP(Z79,'Axe 2 Règles de gestion'!$D$2:$F$84,3, FALSE) -> Le versement s'effectue à hauteur de 4 jours par an jusqu'à épuisement du solde. | AB79: CET_I_024 | AC79: =VLOOKUP(AB79,'Axe 2 Règles de gestion'!$D$2:$F$84,3, FALSE) -> Si la durée de versement est supérieure à 4 ans, celui-ci est opéré en 4 fractions annuelles d'égal montant. | AL79: CET_D_056 | AM79: =VLOOKUP(AL79,'Axe 2 Règles de gestion'!$D$2:$F$84,3, FALSE) -> La différence entre le nombre de jours du compteur global du CET et le nombre de jours pour valorisation financière doit être strictement supérieure à 15 jours. | BB79: CET_C_021 | BC79: =VLOOKUP(BB79,'Axe 2 Règles de gestion'!$D$2:$F$84,3, FALSE) -> La date d'ouverture du CET transitoire doit être antérieure ou égale au 31/12/2008. | BD79: CET_C_012 | BE79: =VLOOKUP(BD79,'Axe 2 Règles de gestion'!$D$2:$F$84,3, FALSE) -> Le nombre de jours de l'opération doit être inférieur ou égal au nombre de jours du compteur global du CET transitoire. | BF79: CET_C_014 | BG79: =VLOOKUP(BF79,'Axe 2 Règles de gestion'!$D$2:$F$84,3, FALSE) -> La date de fermeture du CET transitoire doit être antérieure ou égale à la date limite de départ en retraite. | BH79: CET_C_015 | BI79: =VLOOKUP(BH79,'Axe 2 Règles de gestion'!$D$2:$F$84,3, FALSE) -> La date de fermeture du CET transitoire doit être antérieure ou égale à la date de fin réelle ou prévisionnelle du lien juridique. | BJ79: CET_C_018 | BK79: =VLOOKUP(BJ79,'Axe 2 Règles de gestion'!$D$2:$F$84,3, FALSE) -> La date d'ouverture du compte épargne temps transitoire doit être postérieure ou égale à la date d'entrée dans le SIRH. | BL79: CET_C_022 | BM79: =VLOOKUP(BL79,'Axe 2 Règles de gestion'!$D$2:$F$84,3, FALSE) -> Lorsque le sens de l'opération est égal à "consommé", le nombre de jours pour la cotisation RAFP n'est pas à renseigner. | BN79: CET_C_025 | BO79: =VLOOKUP(BN79,'Axe 2 Règles de gestion'!$D$2:$F$84,3, FALSE) -> Lorsque le sens de l'opération est à "consommé", le compteur global transitoire saisi est égal au compteur global transitoire de l'occurrence précédente duquel sont soustraits les jours consommés en congés. | BP79: CET_C_027 | BQ79: =VLOOKUP(BP79,'Axe 2 Règles de gestion'!$D$2:$F$84,3, FALSE) -> Lorsque le sens de l'opération est égal à "consommé", l'origine des jours n'est pas à renseigner. | BR79: CET_C_028 | BS79: =VLOOKUP(BR79,'Axe 2 Règles de gestion'!$D$2:$F$84,3, FALSE) -> Pour le compte épargne temps transitoire, seule l'opération de consommation en jours de congés est autorisée. Dans ce cas, l'origine des jours, le nombre de jours pour valorisation financière et le nombre de jours pour cotisation RAFP ne sont pas à renseigner. | BT79: CET_C_030 | BU79: =VLOOKUP(BT79,'Axe 2 Règles de gestion'!$D$2:$F$84,3, FALSE) -> Le sens de l'opération doit être à "consommé".
A80: 18.10.00 | B80: M | C80: 43152.5 | D80: D0007 | E80: Congés/Absence | F80: S0049 | G80: Compte épargne temps | H80: E0468 | I80: Compte épargne temps transitoire | J80: La date d'observation saisie du CET est non vide | K80: A_CET_DAGTRA [Saisi] <> Vide | L80: T1131 | M80: Compte épargne temps transitoire - Ouverture sans opération | N80: Création Modification | O80: La date de l'opération saisie est vide. | P80: A_CET_DOOCET [Saisi] = Vide | Q80: Ouvrier du service du cadastre confirmé affilié | R80: P0095 | S80: Particulier | T80: Passant | U80: 40725 | W80: CET_C_021 ET CET_C_012 ET CET_C_014 ET CET_C_015 ET CET_C_018 ET CET_C_031 | BB80: CET_C_021 | BC80: =VLOOKUP(BB80,'Axe 2 Règles de gestion'!$D$2:$F$84,3, FALSE) -> La date d'ouverture du CET transitoire doit être antérieure ou égale au 31/12/2008. | BD80: CET_C_012 | BE80: =VLOOKUP(BD80,'Axe 2 Règles de gestion'!$D$2:$F$84,3, FALSE) -> Le nombre de jours de l'opération doit être inférieur ou égal au nombre de jours du compteur global du CET transitoire. | BF80: CET_C_014 | BG80: =VLOOKUP(BF80,'Axe 2 Règles de gestion'!$D$2:$F$84,3, FALSE) -> La date de fermeture du CET transitoire doit être antérieure ou égale à la date limite de départ en retraite. | BH80: CET_C_015 | BI80: =VLOOKUP(BH80,'Axe 2 Règles de gestion'!$D$2:$F$84,3, FALSE) -> La date de fermeture du CET transitoire doit être antérieure ou égale à la date de fin réelle ou prévisionnelle du lien juridique. | BJ80: CET_C_018 | BK80: =VLOOKUP(BJ80,'Axe 2 Règles de gestion'!$D$2:$F$84,3, FALSE) -> La date d'ouverture du compte épargne temps transitoire doit être postérieure ou égale à la date d'entrée dans le SIRH. | BL80: CET_C_031 | BM80: =VLOOKUP(BL80,'Axe 2 Règles de gestion'!$D$2:$F$84,3, FALSE) -> Les champs "Origine", "Nombre de jours de l'opération", "Nombre de jours pour valorisation financière" et "Nombre de jours pour cotisation RAFP" ne doivent pas être renseignés.
