Workbook

Sheet Mode opératoire
B1: MODE OPERATOIRE
B2: La transaction s'effectue au niveau de la rubrique "Cessation définitive de fonction ou de l'état militaire" qui comporte les deux sous rubriques "Cessation définitive de fonction ou de l'état militaire" et "Réalisation d'un préavis" On notera que pour une occurrence de la sous-rubrique "Cessation définitive de fonction ou de l'état militaire" il n'existe au maximum qu'une seule occurrence de la sous-rubrique "Réalisation d'un préavis"

Sheet Axe 1 Enchainement des RG
A1: Version | B1: Type de mise à jour | C1: Date de mise à jour | D1: Identifiant Domaine | E1: Libellé du Domaine | F1: Identifiant Sous-domaine | G1: Libellé du Sous-domaine | H1: Identifiant Evénement | I1: Libellé de l'évènement | J1: Libellé condition déclenchement Evènement | K1: Condition déclenchement Evènement | L1: Identifiant type d'évènement | M1: Libellé type d'évènement | N1: Type de mise à jour | O1: Libellé condition déclenchement Type Evènement | P1: Condition déclenchement Type Evènement | Q1: Libellé Population | R1: Codification Population | S1: Général / Particulier | T1: Passant / Exclu | U1: Date de début | V1: Date de fin | W1: Règles mobilisées | X1: Identifiant Règle de contrôle intellectuel 1 | Y1: Libellé Règle de contrôle intellectuel 1 | Z1: Identifiant Règle de contrôle intellectuel 2 | AA1: Libellé Règle de contrôle intellectuel 2 | AB1: Identifiant Règle de contrôle intellectuel 3 | AC1: Libellé Règle de contrôle intellectuel 3 | AD1: Identifiant Règle de contrôle intellectuel 4 | AE1: Libellé Règle de contrôle intellectuel 4 | AF1: Identifiant Règle de contrôle intellectuel 5 | AG1: Libellé Règle de contrôle intellectuel 5 | AH1: Identifiant Règle de contrôle intellectuel 6 | AI1: Libellé Règle de contrôle intellectuel 6 | AJ1: Identifiant Règle de contrôle intellectuel 7 | AK1: Libellé Règle de contrôle intellectuel 7 | AL1: Identifiant Règle de contrôle intellectuel 8 | AM1: Libellé Règle de contrôle intellectuel 8 | AN1: Identifiant Règle de contrôle intellectuel 9 | AO1: Libellé Règle de contrôle intellectuel 9 | AP1: Identifiant Règle de contrôle intellectuel 10 | AQ1: Libellé Règle de contrôle intellectuel 10 | AR1: Identifiant Règle de contrôle intellectuel 11 | AS1: Libellé Règle de contrôle intellectuel 11 | AT1: Identifiant Règle de contrôle intellectuel 12 | AU1: Libellé Règle de contrôle intellectuel 12 | AV1: Identifiant Règle de contrôle intellectuel 13 | AW1: Libellé Règle de contrôle intellectuel 13 | AX1: Identifiant Règle de contrôle intellectuel 14 | AY1: Libellé Règle de contrôle intellectuel 14 | AZ1: Identifiant Règle de contrôle intellectuel 15 | BA1: Libellé Règle de contrôle intellectuel 15 | BB1: Identifiant Règle de contrôle intellectuel 16 | BC1: Libellé Règle de contrôle intellectuel 16 | BD1: Identifiant Règle de contrôle intellectuel 17 | BE1: Libellé Règle de contrôle intellectuel 17 | BF1: Identifiant Règle de contrôle intellectuel 18 | BG1: Libellé Règle de contrôle intellectuel 18 | BH1: Identifiant Règle de condition 1 | BI1: Libellé Règle de condition 1 | BJ1: Identifiant Règle de condition 2 | BK1: Libellé Règle de condition 2 | BL1: Identifiant Règle de condition 3 | BM1: Libellé Règle de condition 3 | BN1: Identifiant Règle de contrôle 1 | BO1: Libellé Règle de contrôle 1 | BP1: Identifiant Règle de contrôle 2 | BQ1: Libellé Règle de contrôle 2 | BR1: Identifiant Règle de contrôle 3 | BS1: Libellé Règle de contrôle 3 | BT1: Identifiant Règle de contrôle 4 | BU1: Libellé Règle de contrôle 4 | BV1: Identifiant Règle de contrôle 5 | BW1: Libellé Règle de contrôle 5 | BX1: Identifiant Règle de contrôle 6 | BY1: Libellé Règle de contrôle 6 | BZ1: Identifiant Règle de contrôle 7 | CA1: Libellé Règle de contrôle 7 | CB1: Identifiant Règle de contrôle 8 | CC1: Libellé Règle de contrôle 8 | CD1: Identifiant Règle de contrôle 9 | CE1: Libellé Règle de contrôle 9 | CF1: Identifiant Règle de contrôle 10 | CG1: Libellé Règle de contrôle 10 | CH1: Identifiant Règle de contrôle 11 | CI1: Libellé Règle de contrôle 11 | CJ1: Identifiant Règle de contrôle 12 | CK1: Libellé Règle de contrôle 12 | CL1: Identifiant Règle de contrôle 13 | CM1: Libellé Règle de contrôle 13 | CN1: FIME | CO1: Statut de travail
A2: 23.10.00 | B2: M | C2: 45225.622 | D2: D0006 | E2: Cessation de fonction | F2: S0042 | G2: Cessation de fonction | H2: E0340 | I2: Révocation | J2: Motif cessation de fonction saisi égal à 'Révocation' | K2: A_CDF_MOTCFT [Saisi] = 'MC170' | L2: T0993 | M2: Révocation | N2: Création Modification | Q2: Titulaire ou magistrat | R2: P0001 | S2: Général | T2: Passant | U2: 40725 | W2: CEF_C_001 ET CEF_C_002 ET CEF_C_009 ET CEF_C_013 ET CEF_C_014 ET CEF_C_031 ET CEF_C_032 ET CEF_C_033 ET CEF_C_038 | BN2: CEF_C_001 | BO2: =VLOOKUP(BN2,'Axe 2 Règles de gestion'!$D$2:$F$379,3, FALSE) -> La date de cessation de fonctions doit être postérieure ou égale à la date d'entrée dans la FPE ou dans la carrière militaire. | BP2: CEF_C_002 | BQ2: =VLOOKUP(BP2,'Axe 2 Règles de gestion'!$D$2:$F$379,3, FALSE) -> La date de la cessation de fonctions doit être postérieure ou égale à la date de début de la dernière position en cours. | BR2: CEF_C_009 | BS2: =VLOOKUP(BR2,'Axe 2 Règles de gestion'!$D$2:$F$379,3, FALSE) -> Si les dates de début et de fin de préavis sont saisies, alors la date de fin du préavis doit être postérieure ou égale à la date de début du préavis. | BT2: CEF_C_013 | BU2: =VLOOKUP(BT2,'Axe 2 Règles de gestion'!$D$2:$F$379,3, FALSE) -> Si la date du dernier jour travaillé payé est saisie alors elle doit être antérieure ou égale à la date de cessation de fonctions. | BV2: CEF_C_014 | BW2: =VLOOKUP(BV2,'Axe 2 Règles de gestion'!$D$2:$F$379,3, FALSE) -> Si la date de début du préavis est saisie alors elle doit être postérieure ou égale à la date d'entrée dans la FPE ou dans la carrière militaire. | BX2: CEF_C_031 | BY2: =VLOOKUP(BX2,'Axe 2 Règles de gestion'!$D$2:$F$379,3, FALSE) -> Si l'agent est placé sur une position payée, alors le champ « Date du dernier jour travaillé payé » doit être saisi. | BZ2: CEF_C_032 | CA2: =VLOOKUP(BZ2,'Axe 2 Règles de gestion'!$D$2:$F$379,3, FALSE) -> La date de cessation de fonction doit être antérieure ou égale à la date limite de départ à la retraite | CB2: CEF_C_033 | CC2: =VLOOKUP(CB2,'Axe 2 Règles de gestion'!$D$2:$F$379,3, FALSE) -> Si la date de fin de préavis est saisie alors elle doit être antérieure ou égale à la date de cessation de fonction. | CD2: CEF_C_038 | CE2: =VLOOKUP(CD2,'Axe 2 Règles de gestion'!$D$2:$F$379,3, FALSE) -> Le champ " Date d'effet de la radiation des cadres ou des contrôles " doit être renseigné.
A3: 17.10.00 | B3: A | C3: 43152.5 | D3: D0006 | E3: Cessation de fonction | F3: S0042 | G3: Cessation de fonction | H3: E0340 | I3: Révocation | J3: Motif cessation de fonction saisi égal à 'Révocation' | K3: A_CDF_MOTCFT [Saisi] = 'MC170' | L3: T0993 | M3: Révocation | N3: Création Modification | Q3: Contractuel | R3: P0003 | S3: Général | T3: Exclu | U3: 40725 | V3: 42481
A4: 18.10.00 | B4: M | C4: 43389.366 | D4: D0006 | E4: Cessation de fonction | F4: S0042 | G4: Cessation de fonction | H4: E0340 | I4: Révocation | J4: Motif cessation de fonction saisi égal à 'Révocation' | K4: A_CDF_MOTCFT [Saisi] = 'MC170' | L4: T0993 | M4: Révocation | N4: Création Modification | Q4: Contractuel | R4: P0003 | S4: Général | T4: Passant | U4: 42482 | W4: CEF_C_002 ET CEF_C_004 ET CEF_C_008 ET CEF_C_011 ET CEF_C_012 ET CEF_C_013 ET CEF_C_027 ET CEF_C_031 ET CEF_C_032 ET CEF_C_033 | BN4: CEF_C_002 | BO4: =VLOOKUP(BN4,'Axe 2 Règles de gestion'!$D$2:$F$379,3, FALSE) -> La date de la cessation de fonctions doit être postérieure ou égale à la date de début de la dernière position en cours. | BP4: CEF_C_004 | BQ4: =VLOOKUP(BP4,'Axe 2 Règles de gestion'!$D$2:$F$379,3, FALSE) -> La date de cessation de fonction doit être postérieure ou égale à la date de début du lien juridique | BR4: CEF_C_008 | BS4: =VLOOKUP(BR4,'Axe 2 Règles de gestion'!$D$2:$F$379,3, FALSE) -> La date du dernier jour travaillé payé doit être antérieure ou égale à la date de fin réelle ou prévisionnelle du lien juridique | BT4: CEF_C_011 | BU4: =VLOOKUP(BT4,'Axe 2 Règles de gestion'!$D$2:$F$379,3, FALSE) -> La date de début du préavis doit être postérieure à la date de début du contrat. | BV4: CEF_C_012 | BW4: =VLOOKUP(BV4,'Axe 2 Règles de gestion'!$D$2:$F$379,3, FALSE) -> La date de fin du préavis doit être antérieure ou égale à la date de fin réelle ou prévisionnelle du lien juridique. | BX4: CEF_C_013 | BY4: =VLOOKUP(BX4,'Axe 2 Règles de gestion'!$D$2:$F$379,3, FALSE) -> Si la date du dernier jour travaillé payé est saisie alors elle doit être antérieure ou égale à la date de cessation de fonctions. | BZ4: CEF_C_027 | CA4: =VLOOKUP(BZ4,'Axe 2 Règles de gestion'!$D$2:$F$379,3, FALSE) -> La date de début du préavis doit être postérieure ou égale à la date de début de l'avenant au contrat. | CB4: CEF_C_031 | CC4: =VLOOKUP(CB4,'Axe 2 Règles de gestion'!$D$2:$F$379,3, FALSE) -> Si l'agent est placé sur une position payée, alors le champ « Date du dernier jour travaillé payé » doit être saisi. | CD4: CEF_C_032 | CE4: =VLOOKUP(CD4,'Axe 2 Règles de gestion'!$D$2:$F$379,3, FALSE) -> La date de cessation de fonction doit être antérieure ou égale à la date limite de départ à la retraite | CF4: CEF_C_033 | CG4: =VLOOKUP(CF4,'Axe 2 Règles de gestion'!$D$2:$F$379,3, FALSE) -> Si la date de fin de préavis est saisie alors elle doit être antérieure ou égale à la date de cessation de fonction.
A5: 17.10.00 | B5: A | C5: 43152.5 | D5: D0006 | E5: Cessation de fonction | F5: S0042 | G5: Cessation de fonction | H5: E0340 | I5: Révocation | J5: Motif cessation de fonction saisi égal à 'Révocation' | K5: A_CDF_MOTCFT [Saisi] = 'MC170' | L5: T0993 | M5: Révocation | N5: Création Modification | Q5: Stagiaire ou auditeur ou élève | R5: P0004 | S5: Général | T5: Exclu | U5: 40725
A6: 17.10.00 | B6: A | C6: 43189.5 | D6: D0006 | E6: Cessation de fonction | F6: S0042 | G6: Cessation de fonction | H6: E0340 | I6: Révocation | J6: Motif cessation de fonction saisi égal à 'Révocation' | K6: A_CDF_MOTCFT [Saisi] = 'MC170' | L6: T0993 | M6: Révocation | N6: Création Modification | Q6: Ouvrier d'état | R6: P0005 | S6: Général | T6: Exclu | U6: 40725
A7: 17.10.00 | B7: A | C7: 43152.5 | D7: D0006 | E7: Cessation de fonction | F7: S0042 | G7: Cessation de fonction | H7: E0340 | I7: Révocation | J7: Motif cessation de fonction saisi égal à 'Révocation' | K7: A_CDF_MOTCFT [Saisi] = 'MC170' | L7: T0993 | M7: Révocation | N7: Création Modification | Q7: Personnel civil payé à l'acte ou à la tâche | R7: P0054 | S7: Particulier | T7: Exclu | U7: 42482
A8: 17.10.00 | B8: A | C8: 43152.5 | D8: D0006 | E8: Cessation de fonction | F8: S0042 | G8: Cessation de fonction | H8: E0340 | I8: Révocation | J8: Motif cessation de fonction saisi égal à 'Révocation' | K8: A_CDF_MOTCFT [Saisi] = 'MC170' | L8: T0993 | M8: Révocation | N8: Création Modification | Q8: Contractuel de droit privé | R8: P0072 | S8: Particulier | T8: Exclu | U8: 42482
A9: 17.10.00 | B9: A | C9: 43152.5 | D9: D0006 | E9: Cessation de fonction | F9: S0042 | G9: Cessation de fonction | H9: E0340 | I9: Révocation | J9: Motif cessation de fonction saisi égal à 'Révocation' | K9: A_CDF_MOTCFT [Saisi] = 'MC170' | L9: T0993 | M9: Révocation | N9: Création Modification | Q9: Contractuel sous contrat PACTE | R9: P0166 | S9: Particulier | T9: Exclu | U9: 42482
A10: 17.10.00 | B10: A | C10: 43152.5 | D10: D0006 | E10: Cessation de fonction | F10: S0042 | G10: Cessation de fonction | H10: E0340 | I10: Révocation | J10: Motif cessation de fonction saisi égal à 'Révocation' | K10: A_CDF_MOTCFT [Saisi] = 'MC170' | L10: T0993 | M10: Révocation | N10: Création Modification | Q10: Contractuel en situation de handicap ou contractuel conjoint de militaire décédé | R10: P0167 | S10: Particulier | T10: Exclu | U10: 42482
A11: 17.10.00 | B11: A | C11: 43165.465 | D11: D0006 | E11: Cessation de fonction | F11: S0042 | G11: Cessation de fonction | H11: E0340 | I11: Révocation | J11: Motif cessation de fonction saisi égal à 'Révocation' | K11: A_CDF_MOTCFT [Saisi] = 'MC170' | L11: T0993 | M11: Révocation | N11: Création Modification | Q11: Contractuel recruté pour présenter un concours administratif pour accéder à un corps ou cadre d'emplois de la fonction publique de l'Etat | R11: P0225 | S11: Particulier | T11: Exclu | U11: 43101
A12: 23.10.00 | B12: M | C12: 45225.649 | D12: D0006 | E12: Cessation de fonction | F12: S0042 | G12: Cessation de fonction | H12: E0341 | I12: Démission acceptée sur demande | J12: Motif cessation de fonction saisi égal à 'Démission acceptée sur demande' | K12: A_CDF_MOTCFT [Saisi] = 'MC121' | L12: T0994 | M12: Démission acceptée sur demande | N12: Création Modification | Q12: Titulaire ou magistrat | R12: P0001 | S12: Général | T12: Passant | U12: 40725 | W12: CEF_I_003 ET CEF_I_004 ET CEF_I_005 ET CEF_I_006 ET CEF_I_008 ET CEF_I_007 ET CEF_C_001 ET CEF_C_002 ET CEF_C_009 ET CEF_C_013 ET CEF_C_014 ET CEF_C_031 ET CEF_C_032 ET CEF_C_033 ET CEF_C_038 | X12: CEF_I_003 | Y12: =VLOOKUP(X12,'Axe 2 Règles de gestion'!$D$2:$F$379,3, FALSE) -> La démission ne peut résulter que d'une demande écrite de l'intéressé marquant sa volonté expresse de quitter son administration ou son service. | Z12: CEF_I_004 | AA12: =VLOOKUP(Z12,'Axe 2 Règles de gestion'!$D$2:$F$379,3, FALSE) -> La démission ne prend effet qu'à partir du moment où elle est acceptée par l'autorité investie du pouvoir de nomination et à la date fixée par cette autorité. | AB12: CEF_I_005 | AC12: =VLOOKUP(AB12,'Axe 2 Règles de gestion'!$D$2:$F$379,3, FALSE) -> La décision de l'autorité compétente doit intervenir dans un délai de 4 mois à compter de la réception de la demande de démission. | AD12: CEF_I_006 | AE12: =VLOOKUP(AD12,'Axe 2 Règles de gestion'!$D$2:$F$379,3, FALSE) -> En cas de refus, l'agent peut saisir la commission administrative paritaire compétente qui émettra un avis motivé et le transmettra à l'autorité compétente. | AF12: CEF_I_008 | AG12: =VLOOKUP(AF12,'Axe 2 Règles de gestion'!$D$2:$F$379,3, FALSE) -> L'acceptation de la démission la rend irrévocable. | AH12: CEF_I_007 | AI12: =VLOOKUP(AH12,'Axe 2 Règles de gestion'!$D$2:$F$379,3, FALSE) -> L'agent cessant ses fonctions avant la date fixée par l'administration peut faire l'objet d'une sanction disciplinaire. | BN12: CEF_C_001 | BO12: =VLOOKUP(BN12,'Axe 2 Règles de gestion'!$D$2:$F$379,3, FALSE) -> La date de cessation de fonctions doit être postérieure ou égale à la date d'entrée dans la FPE ou dans la carrière militaire. | BP12: CEF_C_002 | BQ12: =VLOOKUP(BP12,'Axe 2 Règles de gestion'!$D$2:$F$379,3, FALSE) -> La date de la cessation de fonctions doit être postérieure ou égale à la date de début de la dernière position en cours. | BR12: CEF_C_009 | BS12: =VLOOKUP(BR12,'Axe 2 Règles de gestion'!$D$2:$F$379,3, FALSE) -> Si les dates de début et de fin de préavis sont saisies, alors la date de fin du préavis doit être postérieure ou égale à la date de début du préavis. | BT12: CEF_C_013 | BU12: =VLOOKUP(BT12,'Axe 2 Règles de gestion'!$D$2:$F$379,3, FALSE) -> Si la date du dernier jour travaillé payé est saisie alors elle doit être antérieure ou égale à la date de cessation de fonctions. | BV12: CEF_C_014 | BW12: =VLOOKUP(BV12,'Axe 2 Règles de gestion'!$D$2:$F$379,3, FALSE) -> Si la date de début du préavis est saisie alors elle doit être postérieure ou égale à la date d'entrée dans la FPE ou dans la carrière militaire. | BX12: CEF_C_031 | BY12: =VLOOKUP(BX12,'Axe 2 Règles de gestion'!$D$2:$F$379,3, FALSE) -> Si l'agent est placé sur une position payée, alors le champ « Date du dernier jour travaillé payé » doit être saisi. | BZ12: CEF_C_032 | CA12: =VLOOKUP(BZ12,'Axe 2 Règles de gestion'!$D$2:$F$379,3, FALSE) -> La date de cessation de fonction doit être antérieure ou égale à la date limite de départ à la retraite | CB12: CEF_C_033 | CC12: =VLOOKUP(CB12,'Axe 2 Règles de gestion'!$D$2:$F$379,3, FALSE) -> Si la date de fin de préavis est saisie alors elle doit être antérieure ou égale à la date de cessation de fonction. | CD12: CEF_C_038 | CE12: =VLOOKUP(CD12,'Axe 2 Règles de gestion'!$D$2:$F$379,3, FALSE) -> Le champ " Date d'effet de la radiation des cadres ou des contrôles " doit être renseigné.
A13: 24.10.00 | B13: M | C13: 45608.61 | D13: D0006 | E13: Cessation de fonction | F13: S0042 | G13: Cessation de fonction | H13: E0341 | I13: Démission acceptée sur demande | J13: Motif cessation de fonction saisi égal à 'Démission acceptée sur demande' | K13: A_CDF_MOTCFT [Saisi] = 'MC121' | L13: T0994 | M13: Démission acceptée sur demande | N13: Création Modification | Q13: Contractuel | R13: P0003 | S13: Général | T13: Passant | U13: 40725 | W13: CEF_I_003 ET CEF_I_012 ET CEF_I_013 ET CEF_I_014 ET CEF_I_015 ET CEF_C_002 ET CEF_C_004 ET CEF_C_006 ET CEF_C_007 ET CEF_C_008 ET CEF_C_011 ET CEF_C_012 ET CEF_C_013 ET CEF_C_027 ET CEF_C_031 ET CEF_C_032 ET CEF_C_033 ET CEF_C_016 | X13: CEF_I_003 | Y13: =VLOOKUP(X13,'Axe 2 Règles de gestion'!$D$2:$F$379,3, FALSE) -> La démission ne peut résulter que d'une demande écrite de l'intéressé marquant sa volonté expresse de quitter son administration ou son service. | Z13: CEF_I_012 | AA13: =VLOOKUP(Z13,'Axe 2 Règles de gestion'!$D$2:$F$379,3, FALSE) -> La demande doit être envoyée par courrier recommandé. | AB13: CEF_I_013 | AC13: =VLOOKUP(AB13,'Axe 2 Règles de gestion'!$D$2:$F$379,3, FALSE) -> Le préavis à respecter est de 8 jours pour l'agent qui justifie auprès de l'autorité qui le recrute d'une ancienneté de services inférieure à 6 mois de services. | AD13: CEF_I_014 | AE13: =VLOOKUP(AD13,'Axe 2 Règles de gestion'!$D$2:$F$379,3, FALSE) -> Le préavis à respecter est de 1 mois pour celui qui justifie auprès de l'autorité qui le recrute d'une ancienneté de services comprise entre 6 mois et 2 ans. | AF13: CEF_I_015 | AG13: =VLOOKUP(AF13,'Axe 2 Règles de gestion'!$D$2:$F$379,3, FALSE) -> Le préavis à respecter est de 2 mois pour celui qui justifie auprès de l'autorité qui le recrute d'une ancienneté de services d'au moins 2 ans. | BN13: CEF_C_002 | BO13: =VLOOKUP(BN13,'Axe 2 Règles de gestion'!$D$2:$F$379,3, FALSE) -> La date de la cessation de fonctions doit être postérieure ou égale à la date de début de la dernière position en cours. | BP13: CEF_C_004 | BQ13: =VLOOKUP(BP13,'Axe 2 Règles de gestion'!$D$2:$F$379,3, FALSE) -> La date de cessation de fonction doit être postérieure ou égale à la date de début du lien juridique | BR13: CEF_C_006 | BS13: =VLOOKUP(BR13,'Axe 2 Règles de gestion'!$D$2:$F$379,3, FALSE) -> La date de notification de la rupture du contrat doit être antérieure à la date de fin réelle ou prévisionnelle du lien juridique | BT13: CEF_C_007 | BU13: =VLOOKUP(BT13,'Axe 2 Règles de gestion'!$D$2:$F$379,3, FALSE) -> La date de notification de la rupture du contrat doit être renseignée | BV13: CEF_C_008 | BW13: =VLOOKUP(BV13,'Axe 2 Règles de gestion'!$D$2:$F$379,3, FALSE) -> La date du dernier jour travaillé payé doit être antérieure ou égale à la date de fin réelle ou prévisionnelle du lien juridique | BX13: CEF_C_011 | BY13: =VLOOKUP(BX13,'Axe 2 Règles de gestion'!$D$2:$F$379,3, FALSE) -> La date de début du préavis doit être postérieure à la date de début du contrat. | BZ13: CEF_C_012 | CA13: =VLOOKUP(BZ13,'Axe 2 Règles de gestion'!$D$2:$F$379,3, FALSE) -> La date de fin du préavis doit être antérieure ou égale à la date de fin réelle ou prévisionnelle du lien juridique. | CB13: CEF_C_013 | CC13: =VLOOKUP(CB13,'Axe 2 Règles de gestion'!$D$2:$F$379,3, FALSE) -> Si la date du dernier jour travaillé payé est saisie alors elle doit être antérieure ou égale à la date de cessation de fonctions. | CD13: CEF_C_027 | CE13: =VLOOKUP(CD13,'Axe 2 Règles de gestion'!$D$2:$F$379,3, FALSE) -> La date de début du préavis doit être postérieure ou égale à la date de début de l'avenant au contrat. | CF13: CEF_C_031 | CG13: =VLOOKUP(CF13,'Axe 2 Règles de gestion'!$D$2:$F$379,3, FALSE) -> Si l'agent est placé sur une position payée, alors le champ « Date du dernier jour travaillé payé » doit être saisi. | CH13: CEF_C_032 | CI13: =VLOOKUP(CH13,'Axe 2 Règles de gestion'!$D$2:$F$379,3, FALSE) -> La date de cessation de fonction doit être antérieure ou égale à la date limite de départ à la retraite | CJ13: CEF_C_033 | CK13: =VLOOKUP(CJ13,'Axe 2 Règles de gestion'!$D$2:$F$379,3, FALSE) -> Si la date de fin de préavis est saisie alors elle doit être antérieure ou égale à la date de cessation de fonction. | CL13: CEF_C_016 | CM13: =VLOOKUP(CL13,'Axe 2 Règles de gestion'!$D$2:$F$379,3, FALSE) -> Attention : La date d'effet de la demande de l'agent doit être saisie afin d'être récupérée automatiquement lors de la génération de l'acte.
A14: 25.10.00 | B14: M | C14: 45967.454 | D14: D0006 | E14: Cessation de fonction | F14: S0042 | G14: Cessation de fonction | H14: E0341 | I14: Démission acceptée sur demande | J14: Motif cessation de fonction saisi égal à 'Démission acceptée sur demande' | K14: A_CDF_MOTCFT [Saisi] = 'MC121' | L14: T0994 | M14: Démission acceptée sur demande | N14: Création Modification | Q14: Stagiaire ou auditeur ou élève | R14: P0004 | S14: Général | T14: Passant | U14: 40725 | V14: 45930 | W14: CEF_I_009 ET CEF_I_010 ET CEF_I_011 ET CEF_C_001 ET CEF_C_002 ET CEF_C_009 ET CEF_C_013 ET CEF_C_014 ET CEF_C_031 ET CEF_C_032 ET CEF_C_033 | X14: CEF_I_009 | Y14: =VLOOKUP(X14,'Axe 2 Règles de gestion'!$D$2:$F$379,3, FALSE) -> L'agent adresse sa demande par écrit à l'autorité ayant le pouvoir de nomination. | Z14: CEF_I_010 | AA14: =VLOOKUP(Z14,'Axe 2 Règles de gestion'!$D$2:$F$379,3, FALSE) -> L'acceptation de la démission d'un fonctionnaire stagiaire la rend irrévocable. | AB14: CEF_I_011 | AC14: =VLOOKUP(AB14,'Axe 2 Règles de gestion'!$D$2:$F$379,3, FALSE) -> La demande de démission doit être adressée 1 mois au moins avant la date prévue pour la cessation de fonctions. | BN14: CEF_C_001 | BO14: =VLOOKUP(BN14,'Axe 2 Règles de gestion'!$D$2:$F$379,3, FALSE) -> La date de cessation de fonctions doit être postérieure ou égale à la date d'entrée dans la FPE ou dans la carrière militaire. | BP14: CEF_C_002 | BQ14: =VLOOKUP(BP14,'Axe 2 Règles de gestion'!$D$2:$F$379,3, FALSE) -> La date de la cessation de fonctions doit être postérieure ou égale à la date de début de la dernière position en cours. | BR14: CEF_C_009 | BS14: =VLOOKUP(BR14,'Axe 2 Règles de gestion'!$D$2:$F$379,3, FALSE) -> Si les dates de début et de fin de préavis sont saisies, alors la date de fin du préavis doit être postérieure ou égale à la date de début du préavis. | BT14: CEF_C_013 | BU14: =VLOOKUP(BT14,'Axe 2 Règles de gestion'!$D$2:$F$379,3, FALSE) -> Si la date du dernier jour travaillé payé est saisie alors elle doit être antérieure ou égale à la date de cessation de fonctions. | BV14: CEF_C_014 | BW14: =VLOOKUP(BV14,'Axe 2 Règles de gestion'!$D$2:$F$379,3, FALSE) -> Si la date de début du préavis est saisie alors elle doit être postérieure ou égale à la date d'entrée dans la FPE ou dans la carrière militaire. | BX14: CEF_C_031 | BY14: =VLOOKUP(BX14,'Axe 2 Règles de gestion'!$D$2:$F$379,3, FALSE) -> Si l'agent est placé sur une position payée, alors le champ « Date du dernier jour travaillé payé » doit être saisi. | BZ14: CEF_C_032 | CA14: =VLOOKUP(BZ14,'Axe 2 Règles de gestion'!$D$2:$F$379,3, FALSE) -> La date de cessation de fonction doit être antérieure ou égale à la date limite de départ à la retraite | CB14: CEF_C_033 | CC14: =VLOOKUP(CB14,'Axe 2 Règles de gestion'!$D$2:$F$379,3, FALSE) -> Si la date de fin de préavis est saisie alors elle doit être antérieure ou égale à la date de cessation de fonction. | CN14: 2025-96
A15: 25.10.00 | B15: A | C15: 45967.455 | D15: D0006 | E15: Cessation de fonction | F15: S0042 | G15: Cessation de fonction | H15: E0341 | I15: Démission acceptée sur demande | J15: Motif cessation de fonction saisi égal à 'Démission acceptée sur demande' | K15: A_CDF_MOTCFT [Saisi] = 'MC121' | L15: T0994 | M15: Démission acceptée sur demande | N15: Création Modification | Q15: Stagiaire ou auditeur ou élève | R15: P0004 | S15: Général | T15: Passant | U15: 45931 | W15: CEF_I_009 ET CEF_I_011 ET CEF_C_001 ET CEF_C_002 ET CEF_C_009 ET CEF_C_013 ET CEF_C_014 ET CEF_C_031 ET CEF_C_032 ET CEF_C_033 | X15: CEF_I_009 | Y15: =VLOOKUP(X15,'Axe 2 Règles de gestion'!$D$2:$F$379,3, FALSE) -> L'agent adresse sa demande par écrit à l'autorité ayant le pouvoir de nomination. | Z15: CEF_I_011 | AA15: =VLOOKUP(Z15,'Axe 2 Règles de gestion'!$D$2:$F$379,3, FALSE) -> La demande de démission doit être adressée 1 mois au moins avant la date prévue pour la cessation de fonctions. | BN15: CEF_C_001 | BO15: =VLOOKUP(BN15,'Axe 2 Règles de gestion'!$D$2:$F$379,3, FALSE) -> La date de cessation de fonctions doit être postérieure ou égale à la date d'entrée dans la FPE ou dans la carrière militaire. | BP15: CEF_C_002 | BQ15: =VLOOKUP(BP15,'Axe 2 Règles de gestion'!$D$2:$F$379,3, FALSE) -> La date de la cessation de fonctions doit être postérieure ou égale à la date de début de la dernière position en cours. | BR15: CEF_C_009 | BS15: =VLOOKUP(BR15,'Axe 2 Règles de gestion'!$D$2:$F$379,3, FALSE) -> Si les dates de début et de fin de préavis sont saisies, alors la date de fin du préavis doit être postérieure ou égale à la date de début du préavis. | BT15: CEF_C_013 | BU15: =VLOOKUP(BT15,'Axe 2 Règles de gestion'!$D$2:$F$379,3, FALSE) -> Si la date du dernier jour travaillé payé est saisie alors elle doit être antérieure ou égale à la date de cessation de fonctions. | BV15: CEF_C_014 | BW15: =VLOOKUP(BV15,'Axe 2 Règles de gestion'!$D$2:$F$379,3, FALSE) -> Si la date de début du préavis est saisie alors elle doit être postérieure ou égale à la date d'entrée dans la FPE ou dans la carrière militaire. | BX15: CEF_C_031 | BY15: =VLOOKUP(BX15,'Axe 2 Règles de gestion'!$D$2:$F$379,3, FALSE) -> Si l'agent est placé sur une position payée, alors le champ « Date du dernier jour travaillé payé » doit être saisi. | BZ15: CEF_C_032 | CA15: =VLOOKUP(BZ15,'Axe 2 Règles de gestion'!$D$2:$F$379,3, FALSE) -> La date de cessation de fonction doit être antérieure ou égale à la date limite de départ à la retraite | CB15: CEF_C_033 | CC15: =VLOOKUP(CB15,'Axe 2 Règles de gestion'!$D$2:$F$379,3, FALSE) -> Si la date de fin de préavis est saisie alors elle doit être antérieure ou égale à la date de cessation de fonction. | CN15: 2025-96
A16: 17.10.00 | B16: A | C16: 43189.5 | D16: D0006 | E16: Cessation de fonction | F16: S0042 | G16: Cessation de fonction | H16: E0341 | I16: Démission acceptée sur demande | J16: Motif cessation de fonction saisi égal à 'Démission acceptée sur demande' | K16: A_CDF_MOTCFT [Saisi] = 'MC121' | L16: T0994 | M16: Démission acceptée sur demande | N16: Création Modification | Q16: Ouvrier d'état | R16: P0005 | S16: Général | T16: Exclu | U16: 40725
A17: 17.10.00 | B17: A | C17: 43152.5 | D17: D0006 | E17: Cessation de fonction | F17: S0042 | G17: Cessation de fonction | H17: E0341 | I17: Démission acceptée sur demande | J17: Motif cessation de fonction saisi égal à 'Démission acceptée sur demande' | K17: A_CDF_MOTCFT [Saisi] = 'MC121' | L17: T0994 | M17: Démission acceptée sur demande | N17: Création Modification | Q17: Personnel civil payé à l'acte ou à la tâche | R17: P0054 | S17: Particulier | T17: Exclu | U17: 40725
A18: 18.10.00 | B18: M | C18: 43152.5 | D18: D0006 | E18: Cessation de fonction | F18: S0042 | G18: Cessation de fonction | H18: E0341 | I18: Démission acceptée sur demande | J18: Motif cessation de fonction saisi égal à 'Démission acceptée sur demande' | K18: A_CDF_MOTCFT [Saisi] = 'MC121' | L18: T0994 | M18: Démission acceptée sur demande | N18: Création Modification | Q18: Contractuel en service à l'étranger | R18: P0069 | S18: Particulier | T18: Passant | U18: 40725 | W18: CEF_C_002 ET CEF_C_004 ET CEF_C_006 ET CEF_C_007 ET CEF_C_008 ET CEF_C_011 ET CEF_C_012 ET CEF_C_013 ET CEF_C_027 ET CEF_C_031 ET CEF_C_032 ET CEF_C_033 | BN18: CEF_C_002 | BO18: =VLOOKUP(BN18,'Axe 2 Règles de gestion'!$D$2:$F$379,3, FALSE) -> La date de la cessation de fonctions doit être postérieure ou égale à la date de début de la dernière position en cours. | BP18: CEF_C_004 | BQ18: =VLOOKUP(BP18,'Axe 2 Règles de gestion'!$D$2:$F$379,3, FALSE) -> La date de cessation de fonction doit être postérieure ou égale à la date de début du lien juridique | BR18: CEF_C_006 | BS18: =VLOOKUP(BR18,'Axe 2 Règles de gestion'!$D$2:$F$379,3, FALSE) -> La date de notification de la rupture du contrat doit être antérieure à la date de fin réelle ou prévisionnelle du lien juridique | BT18: CEF_C_007 | BU18: =VLOOKUP(BT18,'Axe 2 Règles de gestion'!$D$2:$F$379,3, FALSE) -> La date de notification de la rupture du contrat doit être renseignée | BV18: CEF_C_008 | BW18: =VLOOKUP(BV18,'Axe 2 Règles de gestion'!$D$2:$F$379,3, FALSE) -> La date du dernier jour travaillé payé doit être antérieure ou égale à la date de fin réelle ou prévisionnelle du lien juridique | BX18: CEF_C_011 | BY18: =VLOOKUP(BX18,'Axe 2 Règles de gestion'!$D$2:$F$379,3, FALSE) -> La date de début du préavis doit être postérieure à la date de début du contrat. | BZ18: CEF_C_012 | CA18: =VLOOKUP(BZ18,'Axe 2 Règles de gestion'!$D$2:$F$379,3, FALSE) -> La date de fin du préavis doit être antérieure ou égale à la date de fin réelle ou prévisionnelle du lien juridique. | CB18: CEF_C_013 | CC18: =VLOOKUP(CB18,'Axe 2 Règles de gestion'!$D$2:$F$379,3, FALSE) -> Si la date du dernier jour travaillé payé est saisie alors elle doit être antérieure ou égale à la date de cessation de fonctions. | CD18: CEF_C_027 | CE18: =VLOOKUP(CD18,'Axe 2 Règles de gestion'!$D$2:$F$379,3, FALSE) -> La date de début du préavis doit être postérieure ou égale à la date de début de l'avenant au contrat. | CF18: CEF_C_031 | CG18: =VLOOKUP(CF18,'Axe 2 Règles de gestion'!$D$2:$F$379,3, FALSE) -> Si l'agent est placé sur une position payée, alors le champ « Date du dernier jour travaillé payé » doit être saisi. | CH18: CEF_C_032 | CI18: =VLOOKUP(CH18,'Axe 2 Règles de gestion'!$D$2:$F$379,3, FALSE) -> La date de cessation de fonction doit être antérieure ou égale à la date limite de départ à la retraite | CJ18: CEF_C_033 | CK18: =VLOOKUP(CJ18,'Axe 2 Règles de gestion'!$D$2:$F$379,3, FALSE) -> Si la date de fin de préavis est saisie alors elle doit être antérieure ou égale à la date de cessation de fonction.
A19: 18.10.00 | B19: M | C19: 43152.5 | D19: D0006 | E19: Cessation de fonction | F19: S0042 | G19: Cessation de fonction | H19: E0341 | I19: Démission acceptée sur demande | J19: Motif cessation de fonction saisi égal à 'Démission acceptée sur demande' | K19: A_CDF_MOTCFT [Saisi] = 'MC121' | L19: T0994 | M19: Démission acceptée sur demande | N19: Création Modification | Q19: Contractuel de droit privé | R19: P0072 | S19: Particulier | T19: Passant | U19: 40725 | W19: CEF_C_002 ET CEF_C_004 ET CEF_C_006 ET CEF_C_007 ET CEF_C_008 ET CEF_C_011 ET CEF_C_012 ET CEF_C_013 ET CEF_C_027 ET CEF_C_031 ET CEF_C_032 ET CEF_C_033 | BN19: CEF_C_002 | BO19: =VLOOKUP(BN19,'Axe 2 Règles de gestion'!$D$2:$F$379,3, FALSE) -> La date de la cessation de fonctions doit être postérieure ou égale à la date de début de la dernière position en cours. | BP19: CEF_C_004 | BQ19: =VLOOKUP(BP19,'Axe 2 Règles de gestion'!$D$2:$F$379,3, FALSE) -> La date de cessation de fonction doit être postérieure ou égale à la date de début du lien juridique | BR19: CEF_C_006 | BS19: =VLOOKUP(BR19,'Axe 2 Règles de gestion'!$D$2:$F$379,3, FALSE) -> La date de notification de la rupture du contrat doit être antérieure à la date de fin réelle ou prévisionnelle du lien juridique | BT19: CEF_C_007 | BU19: =VLOOKUP(BT19,'Axe 2 Règles de gestion'!$D$2:$F$379,3, FALSE) -> La date de notification de la rupture du contrat doit être renseignée | BV19: CEF_C_008 | BW19: =VLOOKUP(BV19,'Axe 2 Règles de gestion'!$D$2:$F$379,3, FALSE) -> La date du dernier jour travaillé payé doit être antérieure ou égale à la date de fin réelle ou prévisionnelle du lien juridique | BX19: CEF_C_011 | BY19: =VLOOKUP(BX19,'Axe 2 Règles de gestion'!$D$2:$F$379,3, FALSE) -> La date de début du préavis doit être postérieure à la date de début du contrat. | BZ19: CEF_C_012 | CA19: =VLOOKUP(BZ19,'Axe 2 Règles de gestion'!$D$2:$F$379,3, FALSE) -> La date de fin du préavis doit être antérieure ou égale à la date de fin réelle ou prévisionnelle du lien juridique. | CB19: CEF_C_013 | CC19: =VLOOKUP(CB19,'Axe 2 Règles de gestion'!$D$2:$F$379,3, FALSE) -> Si la date du dernier jour travaillé payé est saisie alors elle doit être antérieure ou égale à la date de cessation de fonctions. | CD19: CEF_C_027 | CE19: =VLOOKUP(CD19,'Axe 2 Règles de gestion'!$D$2:$F$379,3, FALSE) -> La date de début du préavis doit être postérieure ou égale à la date de début de l'avenant au contrat. | CF19: CEF_C_031 | CG19: =VLOOKUP(CF19,'Axe 2 Règles de gestion'!$D$2:$F$379,3, FALSE) -> Si l'agent est placé sur une position payée, alors le champ « Date du dernier jour travaillé payé » doit être saisi. | CH19: CEF_C_032 | CI19: =VLOOKUP(CH19,'Axe 2 Règles de gestion'!$D$2:$F$379,3, FALSE) -> La date de cessation de fonction doit être antérieure ou égale à la date limite de départ à la retraite | CJ19: CEF_C_033 | CK19: =VLOOKUP(CJ19,'Axe 2 Règles de gestion'!$D$2:$F$379,3, FALSE) -> Si la date de fin de préavis est saisie alors elle doit être antérieure ou égale à la date de cessation de fonction.
A20: 18.10.00 | B20: M | C20: 43152.5 | D20: D0006 | E20: Cessation de fonction | F20: S0042 | G20: Cessation de fonction | H20: E0341 | I20: Démission acceptée sur demande | J20: Motif cessation de fonction saisi égal à 'Démission acceptée sur demande' | K20: A_CDF_MOTCFT [Saisi] = 'MC121' | L20: T0994 | M20: Démission acceptée sur demande | N20: Création Modification | Q20: Enseignant contractuel de l'enseignement agricole privé sous contrat non définitif - Agriculture | R20: P0078 | S20: Particulier | T20: Passant | U20: 40725 | W20: CEF_C_002 ET CEF_C_004 ET CEF_C_006 ET CEF_C_007 ET CEF_C_008 ET CEF_C_011 ET CEF_C_012 ET CEF_C_013 ET CEF_C_027 ET CEF_C_031 ET CEF_C_032 ET CEF_C_033 | BN20: CEF_C_002 | BO20: =VLOOKUP(BN20,'Axe 2 Règles de gestion'!$D$2:$F$379,3, FALSE) -> La date de la cessation de fonctions doit être postérieure ou égale à la date de début de la dernière position en cours. | BP20: CEF_C_004 | BQ20: =VLOOKUP(BP20,'Axe 2 Règles de gestion'!$D$2:$F$379,3, FALSE) -> La date de cessation de fonction doit être postérieure ou égale à la date de début du lien juridique | BR20: CEF_C_006 | BS20: =VLOOKUP(BR20,'Axe 2 Règles de gestion'!$D$2:$F$379,3, FALSE) -> La date de notification de la rupture du contrat doit être antérieure à la date de fin réelle ou prévisionnelle du lien juridique | BT20: CEF_C_007 | BU20: =VLOOKUP(BT20,'Axe 2 Règles de gestion'!$D$2:$F$379,3, FALSE) -> La date de notification de la rupture du contrat doit être renseignée | BV20: CEF_C_008 | BW20: =VLOOKUP(BV20,'Axe 2 Règles de gestion'!$D$2:$F$379,3, FALSE) -> La date du dernier jour travaillé payé doit être antérieure ou égale à la date de fin réelle ou prévisionnelle du lien juridique | BX20: CEF_C_011 | BY20: =VLOOKUP(BX20,'Axe 2 Règles de gestion'!$D$2:$F$379,3, FALSE) -> La date de début du préavis doit être postérieure à la date de début du contrat. | BZ20: CEF_C_012 | CA20: =VLOOKUP(BZ20,'Axe 2 Règles de gestion'!$D$2:$F$379,3, FALSE) -> La date de fin du préavis doit être antérieure ou égale à la date de fin réelle ou prévisionnelle du lien juridique. | CB20: CEF_C_013 | CC20: =VLOOKUP(CB20,'Axe 2 Règles de gestion'!$D$2:$F$379,3, FALSE) -> Si la date du dernier jour travaillé payé est saisie alors elle doit être antérieure ou égale à la date de cessation de fonctions. | CD20: CEF_C_027 | CE20: =VLOOKUP(CD20,'Axe 2 Règles de gestion'!$D$2:$F$379,3, FALSE) -> La date de début du préavis doit être postérieure ou égale à la date de début de l'avenant au contrat. | CF20: CEF_C_031 | CG20: =VLOOKUP(CF20,'Axe 2 Règles de gestion'!$D$2:$F$379,3, FALSE) -> Si l'agent est placé sur une position payée, alors le champ « Date du dernier jour travaillé payé » doit être saisi. | CH20: CEF_C_032 | CI20: =VLOOKUP(CH20,'Axe 2 Règles de gestion'!$D$2:$F$379,3, FALSE) -> La date de cessation de fonction doit être antérieure ou égale à la date limite de départ à la retraite | CJ20: CEF_C_033 | CK20: =VLOOKUP(CJ20,'Axe 2 Règles de gestion'!$D$2:$F$379,3, FALSE) -> Si la date de fin de préavis est saisie alors elle doit être antérieure ou égale à la date de cessation de fonction.
A21: 18.10.00 | B21: M | C21: 43152.5 | D21: D0006 | E21: Cessation de fonction | F21: S0042 | G21: Cessation de fonction | H21: E0341 | I21: Démission acceptée sur demande | J21: Motif cessation de fonction saisi égal à 'Démission acceptée sur demande' | K21: A_CDF_MOTCFT [Saisi] = 'MC121' | L21: T0994 | M21: Démission acceptée sur demande | N21: Création Modification | Q21: Enseignant contractuel de l'enseignement agricole privé sous contrat définitif - Agriculture | R21: P0079 | S21: Particulier | T21: Passant | U21: 40725 | W21: CEF_C_002 ET CEF_C_004 ET CEF_C_006 ET CEF_C_007 ET CEF_C_008 ET CEF_C_011 ET CEF_C_012 ET CEF_C_013 ET CEF_C_027 ET CEF_C_031 ET CEF_C_032 ET CEF_C_033 | BN21: CEF_C_002 | BO21: =VLOOKUP(BN21,'Axe 2 Règles de gestion'!$D$2:$F$379,3, FALSE) -> La date de la cessation de fonctions doit être postérieure ou égale à la date de début de la dernière position en cours. | BP21: CEF_C_004 | BQ21: =VLOOKUP(BP21,'Axe 2 Règles de gestion'!$D$2:$F$379,3, FALSE) -> La date de cessation de fonction doit être postérieure ou égale à la date de début du lien juridique | BR21: CEF_C_006 | BS21: =VLOOKUP(BR21,'Axe 2 Règles de gestion'!$D$2:$F$379,3, FALSE) -> La date de notification de la rupture du contrat doit être antérieure à la date de fin réelle ou prévisionnelle du lien juridique | BT21: CEF_C_007 | BU21: =VLOOKUP(BT21,'Axe 2 Règles de gestion'!$D$2:$F$379,3, FALSE) -> La date de notification de la rupture du contrat doit être renseignée | BV21: CEF_C_008 | BW21: =VLOOKUP(BV21,'Axe 2 Règles de gestion'!$D$2:$F$379,3, FALSE) -> La date du dernier jour travaillé payé doit être antérieure ou égale à la date de fin réelle ou prévisionnelle du lien juridique | BX21: CEF_C_011 | BY21: =VLOOKUP(BX21,'Axe 2 Règles de gestion'!$D$2:$F$379,3, FALSE) -> La date de début du préavis doit être postérieure à la date de début du contrat. | BZ21: CEF_C_012 | CA21: =VLOOKUP(BZ21,'Axe 2 Règles de gestion'!$D$2:$F$379,3, FALSE) -> La date de fin du préavis doit être antérieure ou égale à la date de fin réelle ou prévisionnelle du lien juridique. | CB21: CEF_C_013 | CC21: =VLOOKUP(CB21,'Axe 2 Règles de gestion'!$D$2:$F$379,3, FALSE) -> Si la date du dernier jour travaillé payé est saisie alors elle doit être antérieure ou égale à la date de cessation de fonctions. | CD21: CEF_C_027 | CE21: =VLOOKUP(CD21,'Axe 2 Règles de gestion'!$D$2:$F$379,3, FALSE) -> La date de début du préavis doit être postérieure ou égale à la date de début de l'avenant au contrat. | CF21: CEF_C_031 | CG21: =VLOOKUP(CF21,'Axe 2 Règles de gestion'!$D$2:$F$379,3, FALSE) -> Si l'agent est placé sur une position payée, alors le champ « Date du dernier jour travaillé payé » doit être saisi. | CH21: CEF_C_032 | CI21: =VLOOKUP(CH21,'Axe 2 Règles de gestion'!$D$2:$F$379,3, FALSE) -> La date de cessation de fonction doit être antérieure ou égale à la date limite de départ à la retraite | CJ21: CEF_C_033 | CK21: =VLOOKUP(CJ21,'Axe 2 Règles de gestion'!$D$2:$F$379,3, FALSE) -> Si la date de fin de préavis est saisie alors elle doit être antérieure ou égale à la date de cessation de fonction.
A22: 18.10.00 | B22: M | C22: 43189.5 | D22: D0006 | E22: Cessation de fonction | F22: S0042 | G22: Cessation de fonction | H22: E0341 | I22: Démission acceptée sur demande | J22: Motif cessation de fonction saisi égal à 'Démission acceptée sur demande' | K22: A_CDF_MOTCFT [Saisi] = 'MC121' | L22: T0994 | M22: Démission acceptée sur demande | N22: Création Modification | Q22: Ouvrier du service des alcools | R22: P0094 | S22: Particulier | T22: Passant | U22: 40725 | W22: CEF_I_003 ET CEF_I_012 ET CEF_D_364 ET CEF_C_002 ET CEF_C_004 ET CEF_C_006 ET CEF_C_007 ET CEF_C_008 ET CEF_C_011 ET CEF_C_012 ET CEF_C_013 ET CEF_C_027 ET CEF_C_031 ET CEF_C_032 ET CEF_C_033 | X22: CEF_I_003 | Y22: =VLOOKUP(X22,'Axe 2 Règles de gestion'!$D$2:$F$379,3, FALSE) -> La démission ne peut résulter que d'une demande écrite de l'intéressé marquant sa volonté expresse de quitter son administration ou son service. | Z22: CEF_I_012 | AA22: =VLOOKUP(Z22,'Axe 2 Règles de gestion'!$D$2:$F$379,3, FALSE) -> La demande doit être envoyée par courrier recommandé. | BH22: CEF_D_364 | BI22: =VLOOKUP(BH22,'Axe 2 Règles de gestion'!$D$2:$F$379,3, FALSE) -> En cas de démission, le préavis est au minimum de un mois. | BN22: CEF_C_002 | BO22: =VLOOKUP(BN22,'Axe 2 Règles de gestion'!$D$2:$F$379,3, FALSE) -> La date de la cessation de fonctions doit être postérieure ou égale à la date de début de la dernière position en cours. | BP22: CEF_C_004 | BQ22: =VLOOKUP(BP22,'Axe 2 Règles de gestion'!$D$2:$F$379,3, FALSE) -> La date de cessation de fonction doit être postérieure ou égale à la date de début du lien juridique | BR22: CEF_C_006 | BS22: =VLOOKUP(BR22,'Axe 2 Règles de gestion'!$D$2:$F$379,3, FALSE) -> La date de notification de la rupture du contrat doit être antérieure à la date de fin réelle ou prévisionnelle du lien juridique | BT22: CEF_C_007 | BU22: =VLOOKUP(BT22,'Axe 2 Règles de gestion'!$D$2:$F$379,3, FALSE) -> La date de notification de la rupture du contrat doit être renseignée | BV22: CEF_C_008 | BW22: =VLOOKUP(BV22,'Axe 2 Règles de gestion'!$D$2:$F$379,3, FALSE) -> La date du dernier jour travaillé payé doit être antérieure ou égale à la date de fin réelle ou prévisionnelle du lien juridique | BX22: CEF_C_011 | BY22: =VLOOKUP(BX22,'Axe 2 Règles de gestion'!$D$2:$F$379,3, FALSE) -> La date de début du préavis doit être postérieure à la date de début du contrat. | BZ22: CEF_C_012 | CA22: =VLOOKUP(BZ22,'Axe 2 Règles de gestion'!$D$2:$F$379,3, FALSE) -> La date de fin du préavis doit être antérieure ou égale à la date de fin réelle ou prévisionnelle du lien juridique. | CB22: CEF_C_013 | CC22: =VLOOKUP(CB22,'Axe 2 Règles de gestion'!$D$2:$F$379,3, FALSE) -> Si la date du dernier jour travaillé payé est saisie alors elle doit être antérieure ou égale à la date de cessation de fonctions. | CD22: CEF_C_027 | CE22: =VLOOKUP(CD22,'Axe 2 Règles de gestion'!$D$2:$F$379,3, FALSE) -> La date de début du préavis doit être postérieure ou égale à la date de début de l'avenant au contrat. | CF22: CEF_C_031 | CG22: =VLOOKUP(CF22,'Axe 2 Règles de gestion'!$D$2:$F$379,3, FALSE) -> Si l'agent est placé sur une position payée, alors le champ « Date du dernier jour travaillé payé » doit être saisi. | CH22: CEF_C_032 | CI22: =VLOOKUP(CH22,'Axe 2 Règles de gestion'!$D$2:$F$379,3, FALSE) -> La date de cessation de fonction doit être antérieure ou égale à la date limite de départ à la retraite | CJ22: CEF_C_033 | CK22: =VLOOKUP(CJ22,'Axe 2 Règles de gestion'!$D$2:$F$379,3, FALSE) -> Si la date de fin de préavis est saisie alors elle doit être antérieure ou égale à la date de cessation de fonction.
A23: 18.10.00 | B23: M | C23: 43189.5 | D23: D0006 | E23: Cessation de fonction | F23: S0042 | G23: Cessation de fonction | H23: E0341 | I23: Démission acceptée sur demande | J23: Motif cessation de fonction saisi égal à 'Démission acceptée sur demande' | K23: A_CDF_MOTCFT [Saisi] = 'MC121' | L23: T0994 | M23: Démission acceptée sur demande | N23: Création Modification | Q23: Ouvrier du service du cadastre confirmé affilié | R23: P0095 | S23: Particulier | T23: Passant | U23: 40725 | W23: CEF_I_003 ET CEF_I_012 ET CEF_I_084 ET CEF_I_086 ET CEF_D_419 ET CEF_C_002 ET CEF_C_004 ET CEF_C_006 ET CEF_C_007 ET CEF_C_008 ET CEF_C_011 ET CEF_C_012 ET CEF_C_013 ET CEF_C_027 ET CEF_C_031 ET CEF_C_032 ET CEF_C_033 | X23: CEF_I_003 | Y23: =VLOOKUP(X23,'Axe 2 Règles de gestion'!$D$2:$F$379,3, FALSE) -> La démission ne peut résulter que d'une demande écrite de l'intéressé marquant sa volonté expresse de quitter son administration ou son service. | Z23: CEF_I_012 | AA23: =VLOOKUP(Z23,'Axe 2 Règles de gestion'!$D$2:$F$379,3, FALSE) -> La demande doit être envoyée par courrier recommandé. | AB23: CEF_I_084 | AC23: =VLOOKUP(AB23,'Axe 2 Règles de gestion'!$D$2:$F$379,3, FALSE) -> Si l'agent désire quitter son emploi, il doit en aviser par écrit le chef de service au moins 1 mois à l'avance, 8 jours s'il est stagiaire. | AD23: CEF_I_086 | AE23: =VLOOKUP(AD23,'Axe 2 Règles de gestion'!$D$2:$F$379,3, FALSE) -> La démission ne devient définitive qu'après acceptation par le Directeur Général des Impôts. | BH23: CEF_D_419 | BI23: =VLOOKUP(BH23,'Axe 2 Règles de gestion'!$D$2:$F$379,3, FALSE) -> Le préavis est de 8 jours, quelque soit la durée de services. | BN23: CEF_C_002 | BO23: =VLOOKUP(BN23,'Axe 2 Règles de gestion'!$D$2:$F$379,3, FALSE) -> La date de la cessation de fonctions doit être postérieure ou égale à la date de début de la dernière position en cours. | BP23: CEF_C_004 | BQ23: =VLOOKUP(BP23,'Axe 2 Règles de gestion'!$D$2:$F$379,3, FALSE) -> La date de cessation de fonction doit être postérieure ou égale à la date de début du lien juridique | BR23: CEF_C_006 | BS23: =VLOOKUP(BR23,'Axe 2 Règles de gestion'!$D$2:$F$379,3, FALSE) -> La date de notification de la rupture du contrat doit être antérieure à la date de fin réelle ou prévisionnelle du lien juridique | BT23: CEF_C_007 | BU23: =VLOOKUP(BT23,'Axe 2 Règles de gestion'!$D$2:$F$379,3, FALSE) -> La date de notification de la rupture du contrat doit être renseignée | BV23: CEF_C_008 | BW23: =VLOOKUP(BV23,'Axe 2 Règles de gestion'!$D$2:$F$379,3, FALSE) -> La date du dernier jour travaillé payé doit être antérieure ou égale à la date de fin réelle ou prévisionnelle du lien juridique | BX23: CEF_C_011 | BY23: =VLOOKUP(BX23,'Axe 2 Règles de gestion'!$D$2:$F$379,3, FALSE) -> La date de début du préavis doit être postérieure à la date de début du contrat. | BZ23: CEF_C_012 | CA23: =VLOOKUP(BZ23,'Axe 2 Règles de gestion'!$D$2:$F$379,3, FALSE) -> La date de fin du préavis doit être antérieure ou égale à la date de fin réelle ou prévisionnelle du lien juridique. | CB23: CEF_C_013 | CC23: =VLOOKUP(CB23,'Axe 2 Règles de gestion'!$D$2:$F$379,3, FALSE) -> Si la date du dernier jour travaillé payé est saisie alors elle doit être antérieure ou égale à la date de cessation de fonctions. | CD23: CEF_C_027 | CE23: =VLOOKUP(CD23,'Axe 2 Règles de gestion'!$D$2:$F$379,3, FALSE) -> La date de début du préavis doit être postérieure ou égale à la date de début de l'avenant au contrat. | CF23: CEF_C_031 | CG23: =VLOOKUP(CF23,'Axe 2 Règles de gestion'!$D$2:$F$379,3, FALSE) -> Si l'agent est placé sur une position payée, alors le champ « Date du dernier jour travaillé payé » doit être saisi. | CH23: CEF_C_032 | CI23: =VLOOKUP(CH23,'Axe 2 Règles de gestion'!$D$2:$F$379,3, FALSE) -> La date de cessation de fonction doit être antérieure ou égale à la date limite de départ à la retraite | CJ23: CEF_C_033 | CK23: =VLOOKUP(CJ23,'Axe 2 Règles de gestion'!$D$2:$F$379,3, FALSE) -> Si la date de fin de préavis est saisie alors elle doit être antérieure ou égale à la date de cessation de fonction.
A24: 25.10.00 | B24: M | C24: 45974.401 | D24: D0006 | E24: Cessation de fonction | F24: S0042 | G24: Cessation de fonction | H24: E0341 | I24: Démission acceptée sur demande | J24: Motif cessation de fonction saisi égal à 'Démission acceptée sur demande' | K24: A_CDF_MOTCFT [Saisi] = 'MC121' | L24: T0994 | M24: Démission acceptée sur demande | N24: Création Modification | Q24: Ouvrier des parcs et ateliers ou assimilé confirmé | R24: P0096 | S24: Particulier | T24: Passant | U24: 40725 | V24: 45900 | W24: CEF_I_003 ET CEF_I_012 ET CEF_I_099 ET CEF_D_117 ET CEF_C_002 ET CEF_C_004 ET CEF_C_006 ET CEF_C_007 ET CEF_C_008 ET CEF_C_011 ET CEF_C_012 ET CEF_C_013 ET CEF_C_027 ET CEF_C_031 ET CEF_C_032 ET CEF_C_033 | X24: CEF_I_003 | Y24: =VLOOKUP(X24,'Axe 2 Règles de gestion'!$D$2:$F$379,3, FALSE) -> La démission ne peut résulter que d'une demande écrite de l'intéressé marquant sa volonté expresse de quitter son administration ou son service. | Z24: CEF_I_012 | AA24: =VLOOKUP(Z24,'Axe 2 Règles de gestion'!$D$2:$F$379,3, FALSE) -> La demande doit être envoyée par courrier recommandé. | AB24: CEF_I_099 | AC24: =VLOOKUP(AB24,'Axe 2 Règles de gestion'!$D$2:$F$379,3, FALSE) -> Si l'agent désire quitter son emploi, il doit en aviser par écrit le chef de service au moins 1 mois à l'avance, 8 jours s'il est stagiaire. | BH24: CEF_D_117 | BI24: =VLOOKUP(BH24,'Axe 2 Règles de gestion'!$D$2:$F$379,3, FALSE) -> En cas de démission, le préavis est au minimum de un mois. | BN24: CEF_C_002 | BO24: =VLOOKUP(BN24,'Axe 2 Règles de gestion'!$D$2:$F$379,3, FALSE) -> La date de la cessation de fonctions doit être postérieure ou égale à la date de début de la dernière position en cours. | BP24: CEF_C_004 | BQ24: =VLOOKUP(BP24,'Axe 2 Règles de gestion'!$D$2:$F$379,3, FALSE) -> La date de cessation de fonction doit être postérieure ou égale à la date de début du lien juridique | BR24: CEF_C_006 | BS24: =VLOOKUP(BR24,'Axe 2 Règles de gestion'!$D$2:$F$379,3, FALSE) -> La date de notification de la rupture du contrat doit être antérieure à la date de fin réelle ou prévisionnelle du lien juridique | BT24: CEF_C_007 | BU24: =VLOOKUP(BT24,'Axe 2 Règles de gestion'!$D$2:$F$379,3, FALSE) -> La date de notification de la rupture du contrat doit être renseignée | BV24: CEF_C_008 | BW24: =VLOOKUP(BV24,'Axe 2 Règles de gestion'!$D$2:$F$379,3, FALSE) -> La date du dernier jour travaillé payé doit être antérieure ou égale à la date de fin réelle ou prévisionnelle du lien juridique | BX24: CEF_C_011 | BY24: =VLOOKUP(BX24,'Axe 2 Règles de gestion'!$D$2:$F$379,3, FALSE) -> La date de début du préavis doit être postérieure à la date de début du contrat. | BZ24: CEF_C_012 | CA24: =VLOOKUP(BZ24,'Axe 2 Règles de gestion'!$D$2:$F$379,3, FALSE) -> La date de fin du préavis doit être antérieure ou égale à la date de fin réelle ou prévisionnelle du lien juridique. | CB24: CEF_C_013 | CC24: =VLOOKUP(CB24,'Axe 2 Règles de gestion'!$D$2:$F$379,3, FALSE) -> Si la date du dernier jour travaillé payé est saisie alors elle doit être antérieure ou égale à la date de cessation de fonctions. | CD24: CEF_C_027 | CE24: =VLOOKUP(CD24,'Axe 2 Règles de gestion'!$D$2:$F$379,3, FALSE) -> La date de début du préavis doit être postérieure ou égale à la date de début de l'avenant au contrat. | CF24: CEF_C_031 | CG24: =VLOOKUP(CF24,'Axe 2 Règles de gestion'!$D$2:$F$379,3, FALSE) -> Si l'agent est placé sur une position payée, alors le champ « Date du dernier jour travaillé payé » doit être saisi. | CH24: CEF_C_032 | CI24: =VLOOKUP(CH24,'Axe 2 Règles de gestion'!$D$2:$F$379,3, FALSE) -> La date de cessation de fonction doit être antérieure ou égale à la date limite de départ à la retraite | CJ24: CEF_C_033 | CK24: =VLOOKUP(CJ24,'Axe 2 Règles de gestion'!$D$2:$F$379,3, FALSE) -> Si la date de fin de préavis est saisie alors elle doit être antérieure ou égale à la date de cessation de fonction. | CN24: 2025-112
A25: 18.10.00 | B25: M | C25: 43152.5 | D25: D0006 | E25: Cessation de fonction | F25: S0042 | G25: Cessation de fonction | H25: E0341 | I25: Démission acceptée sur demande | J25: Motif cessation de fonction saisi égal à 'Démission acceptée sur demande' | K25: A_CDF_MOTCFT [Saisi] = 'MC121' | L25: T0994 | M25: Démission acceptée sur demande | N25: Création Modification | Q25: Ministre ou personnel des secrétariats des cultes (Alsace Moselle) | R25: P0142 | S25: Particulier | T25: Passant | U25: 40725 | W25: CEF_C_002 ET CEF_C_004 ET CEF_C_006 ET CEF_C_007 ET CEF_C_008 ET CEF_C_011 ET CEF_C_012 ET CEF_C_013 ET CEF_C_027 ET CEF_C_031 ET CEF_C_032 ET CEF_C_033 | BN25: CEF_C_002 | BO25: =VLOOKUP(BN25,'Axe 2 Règles de gestion'!$D$2:$F$379,3, FALSE) -> La date de la cessation de fonctions doit être postérieure ou égale à la date de début de la dernière position en cours. | BP25: CEF_C_004 | BQ25: =VLOOKUP(BP25,'Axe 2 Règles de gestion'!$D$2:$F$379,3, FALSE) -> La date de cessation de fonction doit être postérieure ou égale à la date de début du lien juridique | BR25: CEF_C_006 | BS25: =VLOOKUP(BR25,'Axe 2 Règles de gestion'!$D$2:$F$379,3, FALSE) -> La date de notification de la rupture du contrat doit être antérieure à la date de fin réelle ou prévisionnelle du lien juridique | BT25: CEF_C_007 | BU25: =VLOOKUP(BT25,'Axe 2 Règles de gestion'!$D$2:$F$379,3, FALSE) -> La date de notification de la rupture du contrat doit être renseignée | BV25: CEF_C_008 | BW25: =VLOOKUP(BV25,'Axe 2 Règles de gestion'!$D$2:$F$379,3, FALSE) -> La date du dernier jour travaillé payé doit être antérieure ou égale à la date de fin réelle ou prévisionnelle du lien juridique | BX25: CEF_C_011 | BY25: =VLOOKUP(BX25,'Axe 2 Règles de gestion'!$D$2:$F$379,3, FALSE) -> La date de début du préavis doit être postérieure à la date de début du contrat. | BZ25: CEF_C_012 | CA25: =VLOOKUP(BZ25,'Axe 2 Règles de gestion'!$D$2:$F$379,3, FALSE) -> La date de fin du préavis doit être antérieure ou égale à la date de fin réelle ou prévisionnelle du lien juridique. | CB25: CEF_C_013 | CC25: =VLOOKUP(CB25,'Axe 2 Règles de gestion'!$D$2:$F$379,3, FALSE) -> Si la date du dernier jour travaillé payé est saisie alors elle doit être antérieure ou égale à la date de cessation de fonctions. | CD25: CEF_C_027 | CE25: =VLOOKUP(CD25,'Axe 2 Règles de gestion'!$D$2:$F$379,3, FALSE) -> La date de début du préavis doit être postérieure ou égale à la date de début de l'avenant au contrat. | CF25: CEF_C_031 | CG25: =VLOOKUP(CF25,'Axe 2 Règles de gestion'!$D$2:$F$379,3, FALSE) -> Si l'agent est placé sur une position payée, alors le champ « Date du dernier jour travaillé payé » doit être saisi. | CH25: CEF_C_032 | CI25: =VLOOKUP(CH25,'Axe 2 Règles de gestion'!$D$2:$F$379,3, FALSE) -> La date de cessation de fonction doit être antérieure ou égale à la date limite de départ à la retraite | CJ25: CEF_C_033 | CK25: =VLOOKUP(CJ25,'Axe 2 Règles de gestion'!$D$2:$F$379,3, FALSE) -> Si la date de fin de préavis est saisie alors elle doit être antérieure ou égale à la date de cessation de fonction.
A26: 25.10.00 | B26: A | C26: 45974.397 | D26: D0006 | E26: Cessation de fonction | F26: S0042 | G26: Cessation de fonction | H26: E0341 | I26: Démission acceptée sur demande | J26: Motif cessation de fonction saisi égal à 'Démission acceptée sur demande' | K26: A_CDF_MOTCFT [Saisi] = 'MC121' | L26: T0994 | M26: Démission acceptée sur demande | N26: Création Modification | Q26: Ouvrier des parcs et ateliers confirmé ou stagiaire | R26: P0143 | S26: Particulier | T26: Passant | U26: 45901 | W26: CEF_I_446 ET CEF_D_004 ET CEF_C_002 ET CEF_C_004 ET CEF_C_006 ET CEF_C_007 ET CEF_C_008 ET CEF_C_011 ET CEF_C_012 ET CEF_C_013 ET CEF_C_027 ET CEF_C_031 ET CEF_C_032 ET CEF_C_033 | X26: CEF_I_446 | Y26: =VLOOKUP(X26,'Axe 2 Règles de gestion'!$D$2:$F$379,3, FALSE) -> L'agent informe le chef de service ou le directeur de l'établissement de son intention de démissionner par lettre recommandée avec demande d'avis de réception. | BH26: CEF_D_004 | BI26: =VLOOKUP(BH26,'Axe 2 Règles de gestion'!$D$2:$F$379,3, FALSE) -> L'agent est tenu, dans ce cas, de respecter un préavis de 2 mois. | BN26: CEF_C_002 | BO26: =VLOOKUP(BN26,'Axe 2 Règles de gestion'!$D$2:$F$379,3, FALSE) -> La date de la cessation de fonctions doit être postérieure ou égale à la date de début de la dernière position en cours. | BP26: CEF_C_004 | BQ26: =VLOOKUP(BP26,'Axe 2 Règles de gestion'!$D$2:$F$379,3, FALSE) -> La date de cessation de fonction doit être postérieure ou égale à la date de début du lien juridique | BR26: CEF_C_006 | BS26: =VLOOKUP(BR26,'Axe 2 Règles de gestion'!$D$2:$F$379,3, FALSE) -> La date de notification de la rupture du contrat doit être antérieure à la date de fin réelle ou prévisionnelle du lien juridique | BT26: CEF_C_007 | BU26: =VLOOKUP(BT26,'Axe 2 Règles de gestion'!$D$2:$F$379,3, FALSE) -> La date de notification de la rupture du contrat doit être renseignée | BV26: CEF_C_008 | BW26: =VLOOKUP(BV26,'Axe 2 Règles de gestion'!$D$2:$F$379,3, FALSE) -> La date du dernier jour travaillé payé doit être antérieure ou égale à la date de fin réelle ou prévisionnelle du lien juridique | BX26: CEF_C_011 | BY26: =VLOOKUP(BX26,'Axe 2 Règles de gestion'!$D$2:$F$379,3, FALSE) -> La date de début du préavis doit être postérieure à la date de début du contrat. | BZ26: CEF_C_012 | CA26: =VLOOKUP(BZ26,'Axe 2 Règles de gestion'!$D$2:$F$379,3, FALSE) -> La date de fin du préavis doit être antérieure ou égale à la date de fin réelle ou prévisionnelle du lien juridique. | CB26: CEF_C_013 | CC26: =VLOOKUP(CB26,'Axe 2 Règles de gestion'!$D$2:$F$379,3, FALSE) -> Si la date du dernier jour travaillé payé est saisie alors elle doit être antérieure ou égale à la date de cessation de fonctions. | CD26: CEF_C_027 | CE26: =VLOOKUP(CD26,'Axe 2 Règles de gestion'!$D$2:$F$379,3, FALSE) -> La date de début du préavis doit être postérieure ou égale à la date de début de l'avenant au contrat. | CF26: CEF_C_031 | CG26: =VLOOKUP(CF26,'Axe 2 Règles de gestion'!$D$2:$F$379,3, FALSE) -> Si l'agent est placé sur une position payée, alors le champ « Date du dernier jour travaillé payé » doit être saisi. | CH26: CEF_C_032 | CI26: =VLOOKUP(CH26,'Axe 2 Règles de gestion'!$D$2:$F$379,3, FALSE) -> La date de cessation de fonction doit être antérieure ou égale à la date limite de départ à la retraite | CJ26: CEF_C_033 | CK26: =VLOOKUP(CJ26,'Axe 2 Règles de gestion'!$D$2:$F$379,3, FALSE) -> Si la date de fin de préavis est saisie alors elle doit être antérieure ou égale à la date de cessation de fonction. | CN26: 2025-112
A27: 18.10.00 | B27: M | C27: 43152.5 | D27: D0006 | E27: Cessation de fonction | F27: S0042 | G27: Cessation de fonction | H27: E0341 | I27: Démission acceptée sur demande | J27: Motif cessation de fonction saisi égal à 'Démission acceptée sur demande' | K27: A_CDF_MOTCFT [Saisi] = 'MC121' | L27: T0994 | M27: Démission acceptée sur demande | N27: Création Modification | Q27: Contractuel sous contrat PACTE | R27: P0166 | S27: Particulier | T27: Passant | U27: 40725 | W27: CEF_I_071 ET CEF_I_072 ET CEF_C_002 ET CEF_C_004 ET CEF_C_006 ET CEF_C_007 ET CEF_C_008 ET CEF_C_011 ET CEF_C_012 ET CEF_C_013 ET CEF_C_027 ET CEF_C_031 ET CEF_C_032 ET CEF_C_033 | X27: CEF_I_071 | Y27: =VLOOKUP(X27,'Axe 2 Règles de gestion'!$D$2:$F$379,3, FALSE) -> Après la période d'essai, l'agent informe l'autorité signataire de son intention de démissionner par lettre recommandée avec demande d'avis de réception ou par lettre remise en main propre contre décharge. | Z27: CEF_I_072 | AA27: =VLOOKUP(Z27,'Axe 2 Règles de gestion'!$D$2:$F$379,3, FALSE) -> L'agent doit respecter un préavis de 15 jours pour les agents qui ont moins de 6 moins d'ancienneté, 1 mois pour ceux qui ont 6 mois d'ancienneté et plus. | BN27: CEF_C_002 | BO27: =VLOOKUP(BN27,'Axe 2 Règles de gestion'!$D$2:$F$379,3, FALSE) -> La date de la cessation de fonctions doit être postérieure ou égale à la date de début de la dernière position en cours. | BP27: CEF_C_004 | BQ27: =VLOOKUP(BP27,'Axe 2 Règles de gestion'!$D$2:$F$379,3, FALSE) -> La date de cessation de fonction doit être postérieure ou égale à la date de début du lien juridique | BR27: CEF_C_006 | BS27: =VLOOKUP(BR27,'Axe 2 Règles de gestion'!$D$2:$F$379,3, FALSE) -> La date de notification de la rupture du contrat doit être antérieure à la date de fin réelle ou prévisionnelle du lien juridique | BT27: CEF_C_007 | BU27: =VLOOKUP(BT27,'Axe 2 Règles de gestion'!$D$2:$F$379,3, FALSE) -> La date de notification de la rupture du contrat doit être renseignée | BV27: CEF_C_008 | BW27: =VLOOKUP(BV27,'Axe 2 Règles de gestion'!$D$2:$F$379,3, FALSE) -> La date du dernier jour travaillé payé doit être antérieure ou égale à la date de fin réelle ou prévisionnelle du lien juridique | BX27: CEF_C_011 | BY27: =VLOOKUP(BX27,'Axe 2 Règles de gestion'!$D$2:$F$379,3, FALSE) -> La date de début du préavis doit être postérieure à la date de début du contrat. | BZ27: CEF_C_012 | CA27: =VLOOKUP(BZ27,'Axe 2 Règles de gestion'!$D$2:$F$379,3, FALSE) -> La date de fin du préavis doit être antérieure ou égale à la date de fin réelle ou prévisionnelle du lien juridique. | CB27: CEF_C_013 | CC27: =VLOOKUP(CB27,'Axe 2 Règles de gestion'!$D$2:$F$379,3, FALSE) -> Si la date du dernier jour travaillé payé est saisie alors elle doit être antérieure ou égale à la date de cessation de fonctions. | CD27: CEF_C_027 | CE27: =VLOOKUP(CD27,'Axe 2 Règles de gestion'!$D$2:$F$379,3, FALSE) -> La date de début du préavis doit être postérieure ou égale à la date de début de l'avenant au contrat. | CF27: CEF_C_031 | CG27: =VLOOKUP(CF27,'Axe 2 Règles de gestion'!$D$2:$F$379,3, FALSE) -> Si l'agent est placé sur une position payée, alors le champ « Date du dernier jour travaillé payé » doit être saisi. | CH27: CEF_C_032 | CI27: =VLOOKUP(CH27,'Axe 2 Règles de gestion'!$D$2:$F$379,3, FALSE) -> La date de cessation de fonction doit être antérieure ou égale à la date limite de départ à la retraite | CJ27: CEF_C_033 | CK27: =VLOOKUP(CJ27,'Axe 2 Règles de gestion'!$D$2:$F$379,3, FALSE) -> Si la date de fin de préavis est saisie alors elle doit être antérieure ou égale à la date de cessation de fonction.
A28: 17.10.00 | B28: A | C28: 43152.5 | D28: D0006 | E28: Cessation de fonction | F28: S0042 | G28: Cessation de fonction | H28: E0341 | I28: Démission acceptée sur demande | J28: Motif cessation de fonction saisi égal à 'Démission acceptée sur demande' | K28: A_CDF_MOTCFT [Saisi] = 'MC121' | L28: T0994 | M28: Démission acceptée sur demande | N28: Création Modification | Q28: Contractuel en situation de handicap ou contractuel conjoint de militaire décédé | R28: P0167 | S28: Particulier | T28: Passant | U28: 40725 | W28: CEF_C_031 ET CEF_C_033 ET CEF_C_004 ET CEF_C_006 ET CEF_C_007 ET CEF_C_008 ET CEF_C_011 ET CEF_C_012 ET CEF_C_027 ET CEF_C_002 ET CEF_C_032 ET CEF_C_013 | BN28: CEF_C_031 | BO28: =VLOOKUP(BN28,'Axe 2 Règles de gestion'!$D$2:$F$379,3, FALSE) -> Si l'agent est placé sur une position payée, alors le champ « Date du dernier jour travaillé payé » doit être saisi. | BP28: CEF_C_033 | BQ28: =VLOOKUP(BP28,'Axe 2 Règles de gestion'!$D$2:$F$379,3, FALSE) -> Si la date de fin de préavis est saisie alors elle doit être antérieure ou égale à la date de cessation de fonction. | BR28: CEF_C_004 | BS28: =VLOOKUP(BR28,'Axe 2 Règles de gestion'!$D$2:$F$379,3, FALSE) -> La date de cessation de fonction doit être postérieure ou égale à la date de début du lien juridique | BT28: CEF_C_006 | BU28: =VLOOKUP(BT28,'Axe 2 Règles de gestion'!$D$2:$F$379,3, FALSE) -> La date de notification de la rupture du contrat doit être antérieure à la date de fin réelle ou prévisionnelle du lien juridique | BV28: CEF_C_007 | BW28: =VLOOKUP(BV28,'Axe 2 Règles de gestion'!$D$2:$F$379,3, FALSE) -> La date de notification de la rupture du contrat doit être renseignée | BX28: CEF_C_008 | BY28: =VLOOKUP(BX28,'Axe 2 Règles de gestion'!$D$2:$F$379,3, FALSE) -> La date du dernier jour travaillé payé doit être antérieure ou égale à la date de fin réelle ou prévisionnelle du lien juridique | BZ28: CEF_C_011 | CA28: =VLOOKUP(BZ28,'Axe 2 Règles de gestion'!$D$2:$F$379,3, FALSE) -> La date de début du préavis doit être postérieure à la date de début du contrat. | CB28: CEF_C_012 | CC28: =VLOOKUP(CB28,'Axe 2 Règles de gestion'!$D$2:$F$379,3, FALSE) -> La date de fin du préavis doit être antérieure ou égale à la date de fin réelle ou prévisionnelle du lien juridique. | CD28: CEF_C_027 | CE28: =VLOOKUP(CD28,'Axe 2 Règles de gestion'!$D$2:$F$379,3, FALSE) -> La date de début du préavis doit être postérieure ou égale à la date de début de l'avenant au contrat. | CF28: CEF_C_002 | CG28: =VLOOKUP(CF28,'Axe 2 Règles de gestion'!$D$2:$F$379,3, FALSE) -> La date de la cessation de fonctions doit être postérieure ou égale à la date de début de la dernière position en cours. | CH28: CEF_C_032 | CI28: =VLOOKUP(CH28,'Axe 2 Règles de gestion'!$D$2:$F$379,3, FALSE) -> La date de cessation de fonction doit être antérieure ou égale à la date limite de départ à la retraite | CJ28: CEF_C_013 | CK28: =VLOOKUP(CJ28,'Axe 2 Règles de gestion'!$D$2:$F$379,3, FALSE) -> Si la date du dernier jour travaillé payé est saisie alors elle doit être antérieure ou égale à la date de cessation de fonctions.
A29: 18.10.00 | B29: M | C29: 43152.5 | D29: D0006 | E29: Cessation de fonction | F29: S0042 | G29: Cessation de fonction | H29: E0341 | I29: Démission acceptée sur demande | J29: Motif cessation de fonction saisi égal à 'Démission acceptée sur demande' | K29: A_CDF_MOTCFT [Saisi] = 'MC121' | L29: T0994 | M29: Démission acceptée sur demande | N29: Création Modification | Q29: Assistant de justice | R29: P0173 | S29: Particulier | T29: Passant | U29: 40725 | W29: CEF_D_269 ET CEF_C_002 ET CEF_C_004 ET CEF_C_006 ET CEF_C_007 ET CEF_C_008 ET CEF_C_011 ET CEF_C_012 ET CEF_C_013 ET CEF_C_027 ET CEF_C_031 ET CEF_C_032 ET CEF_C_033 | BH29: CEF_D_269 | BI29: =VLOOKUP(BH29,'Axe 2 Règles de gestion'!$D$2:$F$379,3, FALSE) -> Le préavis est de 15 jours avant la date prévue de cessation de fonction en cas de démission | BN29: CEF_C_002 | BO29: =VLOOKUP(BN29,'Axe 2 Règles de gestion'!$D$2:$F$379,3, FALSE) -> La date de la cessation de fonctions doit être postérieure ou égale à la date de début de la dernière position en cours. | BP29: CEF_C_004 | BQ29: =VLOOKUP(BP29,'Axe 2 Règles de gestion'!$D$2:$F$379,3, FALSE) -> La date de cessation de fonction doit être postérieure ou égale à la date de début du lien juridique | BR29: CEF_C_006 | BS29: =VLOOKUP(BR29,'Axe 2 Règles de gestion'!$D$2:$F$379,3, FALSE) -> La date de notification de la rupture du contrat doit être antérieure à la date de fin réelle ou prévisionnelle du lien juridique | BT29: CEF_C_007 | BU29: =VLOOKUP(BT29,'Axe 2 Règles de gestion'!$D$2:$F$379,3, FALSE) -> La date de notification de la rupture du contrat doit être renseignée | BV29: CEF_C_008 | BW29: =VLOOKUP(BV29,'Axe 2 Règles de gestion'!$D$2:$F$379,3, FALSE) -> La date du dernier jour travaillé payé doit être antérieure ou égale à la date de fin réelle ou prévisionnelle du lien juridique | BX29: CEF_C_011 | BY29: =VLOOKUP(BX29,'Axe 2 Règles de gestion'!$D$2:$F$379,3, FALSE) -> La date de début du préavis doit être postérieure à la date de début du contrat. | BZ29: CEF_C_012 | CA29: =VLOOKUP(BZ29,'Axe 2 Règles de gestion'!$D$2:$F$379,3, FALSE) -> La date de fin du préavis doit être antérieure ou égale à la date de fin réelle ou prévisionnelle du lien juridique. | CB29: CEF_C_013 | CC29: =VLOOKUP(CB29,'Axe 2 Règles de gestion'!$D$2:$F$379,3, FALSE) -> Si la date du dernier jour travaillé payé est saisie alors elle doit être antérieure ou égale à la date de cessation de fonctions. | CD29: CEF_C_027 | CE29: =VLOOKUP(CD29,'Axe 2 Règles de gestion'!$D$2:$F$379,3, FALSE) -> La date de début du préavis doit être postérieure ou égale à la date de début de l'avenant au contrat. | CF29: CEF_C_031 | CG29: =VLOOKUP(CF29,'Axe 2 Règles de gestion'!$D$2:$F$379,3, FALSE) -> Si l'agent est placé sur une position payée, alors le champ « Date du dernier jour travaillé payé » doit être saisi. | CH29: CEF_C_032 | CI29: =VLOOKUP(CH29,'Axe 2 Règles de gestion'!$D$2:$F$379,3, FALSE) -> La date de cessation de fonction doit être antérieure ou égale à la date limite de départ à la retraite | CJ29: CEF_C_033 | CK29: =VLOOKUP(CJ29,'Axe 2 Règles de gestion'!$D$2:$F$379,3, FALSE) -> Si la date de fin de préavis est saisie alors elle doit être antérieure ou égale à la date de cessation de fonction.
A30: 18.10.00 | B30: M | C30: 43152.5 | D30: D0006 | E30: Cessation de fonction | F30: S0042 | G30: Cessation de fonction | H30: E0341 | I30: Démission acceptée sur demande | J30: Motif cessation de fonction saisi égal à 'Démission acceptée sur demande' | K30: A_CDF_MOTCFT [Saisi] = 'MC121' | L30: T0994 | M30: Démission acceptée sur demande | N30: Création Modification | Q30: Volontaire International | R30: P0178 | S30: Particulier | T30: Passant | U30: 40725 | W30: CEF_C_002 ET CEF_C_004 ET CEF_C_006 ET CEF_C_007 ET CEF_C_008 ET CEF_C_011 ET CEF_C_012 ET CEF_C_013 ET CEF_C_027 ET CEF_C_031 ET CEF_C_032 ET CEF_C_033 | BN30: CEF_C_002 | BO30: =VLOOKUP(BN30,'Axe 2 Règles de gestion'!$D$2:$F$379,3, FALSE) -> La date de la cessation de fonctions doit être postérieure ou égale à la date de début de la dernière position en cours. | BP30: CEF_C_004 | BQ30: =VLOOKUP(BP30,'Axe 2 Règles de gestion'!$D$2:$F$379,3, FALSE) -> La date de cessation de fonction doit être postérieure ou égale à la date de début du lien juridique | BR30: CEF_C_006 | BS30: =VLOOKUP(BR30,'Axe 2 Règles de gestion'!$D$2:$F$379,3, FALSE) -> La date de notification de la rupture du contrat doit être antérieure à la date de fin réelle ou prévisionnelle du lien juridique | BT30: CEF_C_007 | BU30: =VLOOKUP(BT30,'Axe 2 Règles de gestion'!$D$2:$F$379,3, FALSE) -> La date de notification de la rupture du contrat doit être renseignée | BV30: CEF_C_008 | BW30: =VLOOKUP(BV30,'Axe 2 Règles de gestion'!$D$2:$F$379,3, FALSE) -> La date du dernier jour travaillé payé doit être antérieure ou égale à la date de fin réelle ou prévisionnelle du lien juridique | BX30: CEF_C_011 | BY30: =VLOOKUP(BX30,'Axe 2 Règles de gestion'!$D$2:$F$379,3, FALSE) -> La date de début du préavis doit être postérieure à la date de début du contrat. | BZ30: CEF_C_012 | CA30: =VLOOKUP(BZ30,'Axe 2 Règles de gestion'!$D$2:$F$379,3, FALSE) -> La date de fin du préavis doit être antérieure ou égale à la date de fin réelle ou prévisionnelle du lien juridique. | CB30: CEF_C_013 | CC30: =VLOOKUP(CB30,'Axe 2 Règles de gestion'!$D$2:$F$379,3, FALSE) -> Si la date du dernier jour travaillé payé est saisie alors elle doit être antérieure ou égale à la date de cessation de fonctions. | CD30: CEF_C_027 | CE30: =VLOOKUP(CD30,'Axe 2 Règles de gestion'!$D$2:$F$379,3, FALSE) -> La date de début du préavis doit être postérieure ou égale à la date de début de l'avenant au contrat. | CF30: CEF_C_031 | CG30: =VLOOKUP(CF30,'Axe 2 Règles de gestion'!$D$2:$F$379,3, FALSE) -> Si l'agent est placé sur une position payée, alors le champ « Date du dernier jour travaillé payé » doit être saisi. | CH30: CEF_C_032 | CI30: =VLOOKUP(CH30,'Axe 2 Règles de gestion'!$D$2:$F$379,3, FALSE) -> La date de cessation de fonction doit être antérieure ou égale à la date limite de départ à la retraite | CJ30: CEF_C_033 | CK30: =VLOOKUP(CJ30,'Axe 2 Règles de gestion'!$D$2:$F$379,3, FALSE) -> Si la date de fin de préavis est saisie alors elle doit être antérieure ou égale à la date de cessation de fonction.
A31: 19.00.00 | B31: M | C31: 43636.591 | D31: D0006 | E31: Cessation de fonction | F31: S0042 | G31: Cessation de fonction | H31: E0341 | I31: Démission acceptée sur demande | J31: Motif cessation de fonction saisi égal à 'Démission acceptée sur demande' | K31: A_CDF_MOTCFT [Saisi] = 'MC121' | L31: T0994 | M31: Démission acceptée sur demande | N31: Création Modification | Q31: Ouvrier de la défense ou assimilé | R31: P0197 | S31: Particulier | T31: Passant | U31: 40725 | W31: CEF_C_002 ET CEF_C_004 ET CEF_C_006 ET CEF_C_007 ET CEF_C_008 ET CEF_C_011 ET CEF_C_012 ET CEF_C_013 ET CEF_C_027 ET CEF_C_031 ET CEF_C_032 ET CEF_C_033 ET CEF_C_036 | BN31: CEF_C_002 | BO31: =VLOOKUP(BN31,'Axe 2 Règles de gestion'!$D$2:$F$379,3, FALSE) -> La date de la cessation de fonctions doit être postérieure ou égale à la date de début de la dernière position en cours. | BP31: CEF_C_004 | BQ31: =VLOOKUP(BP31,'Axe 2 Règles de gestion'!$D$2:$F$379,3, FALSE) -> La date de cessation de fonction doit être postérieure ou égale à la date de début du lien juridique | BR31: CEF_C_006 | BS31: =VLOOKUP(BR31,'Axe 2 Règles de gestion'!$D$2:$F$379,3, FALSE) -> La date de notification de la rupture du contrat doit être antérieure à la date de fin réelle ou prévisionnelle du lien juridique | BT31: CEF_C_007 | BU31: =VLOOKUP(BT31,'Axe 2 Règles de gestion'!$D$2:$F$379,3, FALSE) -> La date de notification de la rupture du contrat doit être renseignée | BV31: CEF_C_008 | BW31: =VLOOKUP(BV31,'Axe 2 Règles de gestion'!$D$2:$F$379,3, FALSE) -> La date du dernier jour travaillé payé doit être antérieure ou égale à la date de fin réelle ou prévisionnelle du lien juridique | BX31: CEF_C_011 | BY31: =VLOOKUP(BX31,'Axe 2 Règles de gestion'!$D$2:$F$379,3, FALSE) -> La date de début du préavis doit être postérieure à la date de début du contrat. | BZ31: CEF_C_012 | CA31: =VLOOKUP(BZ31,'Axe 2 Règles de gestion'!$D$2:$F$379,3, FALSE) -> La date de fin du préavis doit être antérieure ou égale à la date de fin réelle ou prévisionnelle du lien juridique. | CB31: CEF_C_013 | CC31: =VLOOKUP(CB31,'Axe 2 Règles de gestion'!$D$2:$F$379,3, FALSE) -> Si la date du dernier jour travaillé payé est saisie alors elle doit être antérieure ou égale à la date de cessation de fonctions. | CD31: CEF_C_027 | CE31: =VLOOKUP(CD31,'Axe 2 Règles de gestion'!$D$2:$F$379,3, FALSE) -> La date de début du préavis doit être postérieure ou égale à la date de début de l'avenant au contrat. | CF31: CEF_C_031 | CG31: =VLOOKUP(CF31,'Axe 2 Règles de gestion'!$D$2:$F$379,3, FALSE) -> Si l'agent est placé sur une position payée, alors le champ « Date du dernier jour travaillé payé » doit être saisi. | CH31: CEF_C_032 | CI31: =VLOOKUP(CH31,'Axe 2 Règles de gestion'!$D$2:$F$379,3, FALSE) -> La date de cessation de fonction doit être antérieure ou égale à la date limite de départ à la retraite | CJ31: CEF_C_033 | CK31: =VLOOKUP(CJ31,'Axe 2 Règles de gestion'!$D$2:$F$379,3, FALSE) -> Si la date de fin de préavis est saisie alors elle doit être antérieure ou égale à la date de cessation de fonction. | CL31: CEF_C_036 | CM31: =VLOOKUP(CL31,'Axe 2 Règles de gestion'!$D$2:$F$379,3, FALSE) -> Le préavis est de 8 jours, quelle que soit la durée de service.
A32: 18.10.00 | B32: M | C32: 43152.5 | D32: D0006 | E32: Cessation de fonction | F32: S0042 | G32: Cessation de fonction | H32: E0341 | I32: Démission acceptée sur demande | J32: Motif cessation de fonction saisi égal à 'Démission acceptée sur demande' | K32: A_CDF_MOTCFT [Saisi] = 'MC121' | L32: T0994 | M32: Démission acceptée sur demande | N32: Création Modification | Q32: Personnel civil de coopération (assistant technique) | R32: P0214 | S32: Particulier | T32: Passant | U32: 40725 | W32: CEF_C_002 ET CEF_C_004 ET CEF_C_006 ET CEF_C_007 ET CEF_C_008 ET CEF_C_011 ET CEF_C_012 ET CEF_C_013 ET CEF_C_027 ET CEF_C_031 ET CEF_C_032 ET CEF_C_033 | BN32: CEF_C_002 | BO32: =VLOOKUP(BN32,'Axe 2 Règles de gestion'!$D$2:$F$379,3, FALSE) -> La date de la cessation de fonctions doit être postérieure ou égale à la date de début de la dernière position en cours. | BP32: CEF_C_004 | BQ32: =VLOOKUP(BP32,'Axe 2 Règles de gestion'!$D$2:$F$379,3, FALSE) -> La date de cessation de fonction doit être postérieure ou égale à la date de début du lien juridique | BR32: CEF_C_006 | BS32: =VLOOKUP(BR32,'Axe 2 Règles de gestion'!$D$2:$F$379,3, FALSE) -> La date de notification de la rupture du contrat doit être antérieure à la date de fin réelle ou prévisionnelle du lien juridique | BT32: CEF_C_007 | BU32: =VLOOKUP(BT32,'Axe 2 Règles de gestion'!$D$2:$F$379,3, FALSE) -> La date de notification de la rupture du contrat doit être renseignée | BV32: CEF_C_008 | BW32: =VLOOKUP(BV32,'Axe 2 Règles de gestion'!$D$2:$F$379,3, FALSE) -> La date du dernier jour travaillé payé doit être antérieure ou égale à la date de fin réelle ou prévisionnelle du lien juridique | BX32: CEF_C_011 | BY32: =VLOOKUP(BX32,'Axe 2 Règles de gestion'!$D$2:$F$379,3, FALSE) -> La date de début du préavis doit être postérieure à la date de début du contrat. | BZ32: CEF_C_012 | CA32: =VLOOKUP(BZ32,'Axe 2 Règles de gestion'!$D$2:$F$379,3, FALSE) -> La date de fin du préavis doit être antérieure ou égale à la date de fin réelle ou prévisionnelle du lien juridique. | CB32: CEF_C_013 | CC32: =VLOOKUP(CB32,'Axe 2 Règles de gestion'!$D$2:$F$379,3, FALSE) -> Si la date du dernier jour travaillé payé est saisie alors elle doit être antérieure ou égale à la date de cessation de fonctions. | CD32: CEF_C_027 | CE32: =VLOOKUP(CD32,'Axe 2 Règles de gestion'!$D$2:$F$379,3, FALSE) -> La date de début du préavis doit être postérieure ou égale à la date de début de l'avenant au contrat. | CF32: CEF_C_031 | CG32: =VLOOKUP(CF32,'Axe 2 Règles de gestion'!$D$2:$F$379,3, FALSE) -> Si l'agent est placé sur une position payée, alors le champ « Date du dernier jour travaillé payé » doit être saisi. | CH32: CEF_C_032 | CI32: =VLOOKUP(CH32,'Axe 2 Règles de gestion'!$D$2:$F$379,3, FALSE) -> La date de cessation de fonction doit être antérieure ou égale à la date limite de départ à la retraite | CJ32: CEF_C_033 | CK32: =VLOOKUP(CJ32,'Axe 2 Règles de gestion'!$D$2:$F$379,3, FALSE) -> Si la date de fin de préavis est saisie alors elle doit être antérieure ou égale à la date de cessation de fonction.
A33: 18.10.00 | B33: M | C33: 43165.466 | D33: D0006 | E33: Cessation de fonction | F33: S0042 | G33: Cessation de fonction | H33: E0341 | I33: Démission acceptée sur demande | J33: Motif cessation de fonction saisi égal à 'Démission acceptée sur demande' | K33: A_CDF_MOTCFT [Saisi] = 'MC121' | L33: T0994 | M33: Démission acceptée sur demande | N33: Création Modification | Q33: Contractuel recruté pour présenter un concours administratif pour accéder à un corps ou cadre d'emplois de la fonction publique de l'Etat | R33: P0225 | S33: Particulier | T33: Passant | U33: 43101 | W33: CEF_C_002 ET CEF_C_004 ET CEF_C_006 ET CEF_C_007 ET CEF_C_008 ET CEF_C_011 ET CEF_C_012 ET CEF_C_013 ET CEF_C_027 ET CEF_C_031 ET CEF_C_032 ET CEF_C_033 | BN33: CEF_C_002 | BO33: =VLOOKUP(BN33,'Axe 2 Règles de gestion'!$D$2:$F$379,3, FALSE) -> La date de la cessation de fonctions doit être postérieure ou égale à la date de début de la dernière position en cours. | BP33: CEF_C_004 | BQ33: =VLOOKUP(BP33,'Axe 2 Règles de gestion'!$D$2:$F$379,3, FALSE) -> La date de cessation de fonction doit être postérieure ou égale à la date de début du lien juridique | BR33: CEF_C_006 | BS33: =VLOOKUP(BR33,'Axe 2 Règles de gestion'!$D$2:$F$379,3, FALSE) -> La date de notification de la rupture du contrat doit être antérieure à la date de fin réelle ou prévisionnelle du lien juridique | BT33: CEF_C_007 | BU33: =VLOOKUP(BT33,'Axe 2 Règles de gestion'!$D$2:$F$379,3, FALSE) -> La date de notification de la rupture du contrat doit être renseignée | BV33: CEF_C_008 | BW33: =VLOOKUP(BV33,'Axe 2 Règles de gestion'!$D$2:$F$379,3, FALSE) -> La date du dernier jour travaillé payé doit être antérieure ou égale à la date de fin réelle ou prévisionnelle du lien juridique | BX33: CEF_C_011 | BY33: =VLOOKUP(BX33,'Axe 2 Règles de gestion'!$D$2:$F$379,3, FALSE) -> La date de début du préavis doit être postérieure à la date de début du contrat. | BZ33: CEF_C_012 | CA33: =VLOOKUP(BZ33,'Axe 2 Règles de gestion'!$D$2:$F$379,3, FALSE) -> La date de fin du préavis doit être antérieure ou égale à la date de fin réelle ou prévisionnelle du lien juridique. | CB33: CEF_C_013 | CC33: =VLOOKUP(CB33,'Axe 2 Règles de gestion'!$D$2:$F$379,3, FALSE) -> Si la date du dernier jour travaillé payé est saisie alors elle doit être antérieure ou égale à la date de cessation de fonctions. | CD33: CEF_C_027 | CE33: =VLOOKUP(CD33,'Axe 2 Règles de gestion'!$D$2:$F$379,3, FALSE) -> La date de début du préavis doit être postérieure ou égale à la date de début de l'avenant au contrat. | CF33: CEF_C_031 | CG33: =VLOOKUP(CF33,'Axe 2 Règles de gestion'!$D$2:$F$379,3, FALSE) -> Si l'agent est placé sur une position payée, alors le champ « Date du dernier jour travaillé payé » doit être saisi. | CH33: CEF_C_032 | CI33: =VLOOKUP(CH33,'Axe 2 Règles de gestion'!$D$2:$F$379,3, FALSE) -> La date de cessation de fonction doit être antérieure ou égale à la date limite de départ à la retraite | CJ33: CEF_C_033 | CK33: =VLOOKUP(CJ33,'Axe 2 Règles de gestion'!$D$2:$F$379,3, FALSE) -> Si la date de fin de préavis est saisie alors elle doit être antérieure ou égale à la date de cessation de fonction.
A34: 25.10.00 | B34: M | C34: 45974.401 | D34: D0006 | E34: Cessation de fonction | F34: S0042 | G34: Cessation de fonction | H34: E0341 | I34: Démission acceptée sur demande | J34: Motif cessation de fonction saisi égal à 'Démission acceptée sur demande' | K34: A_CDF_MOTCFT [Saisi] = 'MC121' | L34: T0994 | M34: Démission acceptée sur demande | N34: Création Modification | Q34: Ouvrier des parcs et ateliers stagiaire | R34: P0226 | S34: Particulier | T34: Passant | U34: 40725 | V34: 45900 | W34: CEF_I_003 ET CEF_I_012 ET CEF_I_099 ET CEF_D_118 ET CEF_C_002 ET CEF_C_004 ET CEF_C_006 ET CEF_C_007 ET CEF_C_008 ET CEF_C_011 ET CEF_C_012 ET CEF_C_013 ET CEF_C_027 ET CEF_C_031 ET CEF_C_032 ET CEF_C_033 | X34: CEF_I_003 | Y34: =VLOOKUP(X34,'Axe 2 Règles de gestion'!$D$2:$F$379,3, FALSE) -> La démission ne peut résulter que d'une demande écrite de l'intéressé marquant sa volonté expresse de quitter son administration ou son service. | Z34: CEF_I_012 | AA34: =VLOOKUP(Z34,'Axe 2 Règles de gestion'!$D$2:$F$379,3, FALSE) -> La demande doit être envoyée par courrier recommandé. | AB34: CEF_I_099 | AC34: =VLOOKUP(AB34,'Axe 2 Règles de gestion'!$D$2:$F$379,3, FALSE) -> Si l'agent désire quitter son emploi, il doit en aviser par écrit le chef de service au moins 1 mois à l'avance, 8 jours s'il est stagiaire. | BH34: CEF_D_118 | BI34: =VLOOKUP(BH34,'Axe 2 Règles de gestion'!$D$2:$F$379,3, FALSE) -> Le préavis est de 8 jours, quelle que soit la durée de services. | BN34: CEF_C_002 | BO34: =VLOOKUP(BN34,'Axe 2 Règles de gestion'!$D$2:$F$379,3, FALSE) -> La date de la cessation de fonctions doit être postérieure ou égale à la date de début de la dernière position en cours. | BP34: CEF_C_004 | BQ34: =VLOOKUP(BP34,'Axe 2 Règles de gestion'!$D$2:$F$379,3, FALSE) -> La date de cessation de fonction doit être postérieure ou égale à la date de début du lien juridique | BR34: CEF_C_006 | BS34: =VLOOKUP(BR34,'Axe 2 Règles de gestion'!$D$2:$F$379,3, FALSE) -> La date de notification de la rupture du contrat doit être antérieure à la date de fin réelle ou prévisionnelle du lien juridique | BT34: CEF_C_007 | BU34: =VLOOKUP(BT34,'Axe 2 Règles de gestion'!$D$2:$F$379,3, FALSE) -> La date de notification de la rupture du contrat doit être renseignée | BV34: CEF_C_008 | BW34: =VLOOKUP(BV34,'Axe 2 Règles de gestion'!$D$2:$F$379,3, FALSE) -> La date du dernier jour travaillé payé doit être antérieure ou égale à la date de fin réelle ou prévisionnelle du lien juridique | BX34: CEF_C_011 | BY34: =VLOOKUP(BX34,'Axe 2 Règles de gestion'!$D$2:$F$379,3, FALSE) -> La date de début du préavis doit être postérieure à la date de début du contrat. | BZ34: CEF_C_012 | CA34: =VLOOKUP(BZ34,'Axe 2 Règles de gestion'!$D$2:$F$379,3, FALSE) -> La date de fin du préavis doit être antérieure ou égale à la date de fin réelle ou prévisionnelle du lien juridique. | CB34: CEF_C_013 | CC34: =VLOOKUP(CB34,'Axe 2 Règles de gestion'!$D$2:$F$379,3, FALSE) -> Si la date du dernier jour travaillé payé est saisie alors elle doit être antérieure ou égale à la date de cessation de fonctions. | CD34: CEF_C_027 | CE34: =VLOOKUP(CD34,'Axe 2 Règles de gestion'!$D$2:$F$379,3, FALSE) -> La date de début du préavis doit être postérieure ou égale à la date de début de l'avenant au contrat. | CF34: CEF_C_031 | CG34: =VLOOKUP(CF34,'Axe 2 Règles de gestion'!$D$2:$F$379,3, FALSE) -> Si l'agent est placé sur une position payée, alors le champ « Date du dernier jour travaillé payé » doit être saisi. | CH34: CEF_C_032 | CI34: =VLOOKUP(CH34,'Axe 2 Règles de gestion'!$D$2:$F$379,3, FALSE) -> La date de cessation de fonction doit être antérieure ou égale à la date limite de départ à la retraite | CJ34: CEF_C_033 | CK34: =VLOOKUP(CJ34,'Axe 2 Règles de gestion'!$D$2:$F$379,3, FALSE) -> Si la date de fin de préavis est saisie alors elle doit être antérieure ou égale à la date de cessation de fonction. | CN34: 2025-112
A35: 22.00.00 | B35: A | C35: 44715.667 | D35: D0006 | E35: Cessation de fonction | F35: S0042 | G35: Cessation de fonction | H35: E0341 | I35: Démission acceptée sur demande | J35: Motif cessation de fonction saisi égal à 'Démission acceptée sur demande' | K35: A_CDF_MOTCFT [Saisi] = 'MC121' | L35: T0994 | M35: Démission acceptée sur demande | N35: Création Modification | Q35: Contractuel recruté sur contrat de mission scientifique | R35: P0266 | S35: Particulier | T35: Passant | U35: 44507 | W35: CEF_I_383 ET CEF_I_003 ET CEF_I_012 ET CEF_I_013 ET CEF_I_014 ET CEF_I_015 ET CEF_C_002 ET CEF_C_004 ET CEF_C_006 ET CEF_C_007 ET CEF_C_008 ET CEF_C_011 ET CEF_C_012 ET CEF_C_013 ET CEF_C_027 ET CEF_C_031 ET CEF_C_032 ET CEF_C_033 | X35: CEF_I_383 | Y35: =VLOOKUP(X35,'Axe 2 Règles de gestion'!$D$2:$F$379,3, FALSE) -> L'agent bénéficie des dispositions applicables aux agents contractuels en cas de démission acceptée sur demande, sauf dispositions particulières. | Z35: CEF_I_003 | AA35: =VLOOKUP(Z35,'Axe 2 Règles de gestion'!$D$2:$F$379,3, FALSE) -> La démission ne peut résulter que d'une demande écrite de l'intéressé marquant sa volonté expresse de quitter son administration ou son service. | AB35: CEF_I_012 | AC35: =VLOOKUP(AB35,'Axe 2 Règles de gestion'!$D$2:$F$379,3, FALSE) -> La demande doit être envoyée par courrier recommandé. | AD35: CEF_I_013 | AE35: =VLOOKUP(AD35,'Axe 2 Règles de gestion'!$D$2:$F$379,3, FALSE) -> Le préavis à respecter est de 8 jours pour l'agent qui justifie auprès de l'autorité qui le recrute d'une ancienneté de services inférieure à 6 mois de services. | AF35: CEF_I_014 | AG35: =VLOOKUP(AF35,'Axe 2 Règles de gestion'!$D$2:$F$379,3, FALSE) -> Le préavis à respecter est de 1 mois pour celui qui justifie auprès de l'autorité qui le recrute d'une ancienneté de services comprise entre 6 mois et 2 ans. | AH35: CEF_I_015 | AI35: =VLOOKUP(AH35,'Axe 2 Règles de gestion'!$D$2:$F$379,3, FALSE) -> Le préavis à respecter est de 2 mois pour celui qui justifie auprès de l'autorité qui le recrute d'une ancienneté de services d'au moins 2 ans. | BN35: CEF_C_002 | BO35: =VLOOKUP(BN35,'Axe 2 Règles de gestion'!$D$2:$F$379,3, FALSE) -> La date de la cessation de fonctions doit être postérieure ou égale à la date de début de la dernière position en cours. | BP35: CEF_C_004 | BQ35: =VLOOKUP(BP35,'Axe 2 Règles de gestion'!$D$2:$F$379,3, FALSE) -> La date de cessation de fonction doit être postérieure ou égale à la date de début du lien juridique | BR35: CEF_C_006 | BS35: =VLOOKUP(BR35,'Axe 2 Règles de gestion'!$D$2:$F$379,3, FALSE) -> La date de notification de la rupture du contrat doit être antérieure à la date de fin réelle ou prévisionnelle du lien juridique | BT35: CEF_C_007 | BU35: =VLOOKUP(BT35,'Axe 2 Règles de gestion'!$D$2:$F$379,3, FALSE) -> La date de notification de la rupture du contrat doit être renseignée | BV35: CEF_C_008 | BW35: =VLOOKUP(BV35,'Axe 2 Règles de gestion'!$D$2:$F$379,3, FALSE) -> La date du dernier jour travaillé payé doit être antérieure ou égale à la date de fin réelle ou prévisionnelle du lien juridique | BX35: CEF_C_011 | BY35: =VLOOKUP(BX35,'Axe 2 Règles de gestion'!$D$2:$F$379,3, FALSE) -> La date de début du préavis doit être postérieure à la date de début du contrat. | BZ35: CEF_C_012 | CA35: =VLOOKUP(BZ35,'Axe 2 Règles de gestion'!$D$2:$F$379,3, FALSE) -> La date de fin du préavis doit être antérieure ou égale à la date de fin réelle ou prévisionnelle du lien juridique. | CB35: CEF_C_013 | CC35: =VLOOKUP(CB35,'Axe 2 Règles de gestion'!$D$2:$F$379,3, FALSE) -> Si la date du dernier jour travaillé payé est saisie alors elle doit être antérieure ou égale à la date de cessation de fonctions. | CD35: CEF_C_027 | CE35: =VLOOKUP(CD35,'Axe 2 Règles de gestion'!$D$2:$F$379,3, FALSE) -> La date de début du préavis doit être postérieure ou égale à la date de début de l'avenant au contrat. | CF35: CEF_C_031 | CG35: =VLOOKUP(CF35,'Axe 2 Règles de gestion'!$D$2:$F$379,3, FALSE) -> Si l'agent est placé sur une position payée, alors le champ « Date du dernier jour travaillé payé » doit être saisi. | CH35: CEF_C_032 | CI35: =VLOOKUP(CH35,'Axe 2 Règles de gestion'!$D$2:$F$379,3, FALSE) -> La date de cessation de fonction doit être antérieure ou égale à la date limite de départ à la retraite | CJ35: CEF_C_033 | CK35: =VLOOKUP(CJ35,'Axe 2 Règles de gestion'!$D$2:$F$379,3, FALSE) -> Si la date de fin de préavis est saisie alors elle doit être antérieure ou égale à la date de cessation de fonction.
A36: 22.00.00 | B36: A | C36: 44720.366 | D36: D0006 | E36: Cessation de fonction | F36: S0042 | G36: Cessation de fonction | H36: E0341 | I36: Démission acceptée sur demande | J36: Motif cessation de fonction saisi égal à 'Démission acceptée sur demande' | K36: A_CDF_MOTCFT [Saisi] = 'MC121' | L36: T0994 | M36: Démission acceptée sur demande | N36: Création Modification | Q36: Contractuel recruté sur contrat post doctoral | R36: P0267 | S36: Particulier | T36: Passant | U36: 44507 | W36: CEF_I_393 ET CEF_I_003 ET CEF_I_012 ET CEF_I_013 ET CEF_I_014 ET CEF_I_015 ET CEF_C_002 ET CEF_C_004 ET CEF_C_006 ET CEF_C_007 ET CEF_C_008 ET CEF_C_011 ET CEF_C_012 ET CEF_C_013 ET CEF_C_027 ET CEF_C_031 ET CEF_C_032 ET CEF_C_033 | X36: CEF_I_393 | Y36: =VLOOKUP(X36,'Axe 2 Règles de gestion'!$D$2:$F$379,3, FALSE) -> L'agent bénéficie des dispositions applicables aux agents contractuels en cas de démission acceptée sur demande, sauf dispositions particulières. | Z36: CEF_I_003 | AA36: =VLOOKUP(Z36,'Axe 2 Règles de gestion'!$D$2:$F$379,3, FALSE) -> La démission ne peut résulter que d'une demande écrite de l'intéressé marquant sa volonté expresse de quitter son administration ou son service. | AB36: CEF_I_012 | AC36: =VLOOKUP(AB36,'Axe 2 Règles de gestion'!$D$2:$F$379,3, FALSE) -> La demande doit être envoyée par courrier recommandé. | AD36: CEF_I_013 | AE36: =VLOOKUP(AD36,'Axe 2 Règles de gestion'!$D$2:$F$379,3, FALSE) -> Le préavis à respecter est de 8 jours pour l'agent qui justifie auprès de l'autorité qui le recrute d'une ancienneté de services inférieure à 6 mois de services. | AF36: CEF_I_014 | AG36: =VLOOKUP(AF36,'Axe 2 Règles de gestion'!$D$2:$F$379,3, FALSE) -> Le préavis à respecter est de 1 mois pour celui qui justifie auprès de l'autorité qui le recrute d'une ancienneté de services comprise entre 6 mois et 2 ans. | AH36: CEF_I_015 | AI36: =VLOOKUP(AH36,'Axe 2 Règles de gestion'!$D$2:$F$379,3, FALSE) -> Le préavis à respecter est de 2 mois pour celui qui justifie auprès de l'autorité qui le recrute d'une ancienneté de services d'au moins 2 ans. | BN36: CEF_C_002 | BO36: =VLOOKUP(BN36,'Axe 2 Règles de gestion'!$D$2:$F$379,3, FALSE) -> La date de la cessation de fonctions doit être postérieure ou égale à la date de début de la dernière position en cours. | BP36: CEF_C_004 | BQ36: =VLOOKUP(BP36,'Axe 2 Règles de gestion'!$D$2:$F$379,3, FALSE) -> La date de cessation de fonction doit être postérieure ou égale à la date de début du lien juridique | BR36: CEF_C_006 | BS36: =VLOOKUP(BR36,'Axe 2 Règles de gestion'!$D$2:$F$379,3, FALSE) -> La date de notification de la rupture du contrat doit être antérieure à la date de fin réelle ou prévisionnelle du lien juridique | BT36: CEF_C_007 | BU36: =VLOOKUP(BT36,'Axe 2 Règles de gestion'!$D$2:$F$379,3, FALSE) -> La date de notification de la rupture du contrat doit être renseignée | BV36: CEF_C_008 | BW36: =VLOOKUP(BV36,'Axe 2 Règles de gestion'!$D$2:$F$379,3, FALSE) -> La date du dernier jour travaillé payé doit être antérieure ou égale à la date de fin réelle ou prévisionnelle du lien juridique | BX36: CEF_C_011 | BY36: =VLOOKUP(BX36,'Axe 2 Règles de gestion'!$D$2:$F$379,3, FALSE) -> La date de début du préavis doit être postérieure à la date de début du contrat. | BZ36: CEF_C_012 | CA36: =VLOOKUP(BZ36,'Axe 2 Règles de gestion'!$D$2:$F$379,3, FALSE) -> La date de fin du préavis doit être antérieure ou égale à la date de fin réelle ou prévisionnelle du lien juridique. | CB36: CEF_C_013 | CC36: =VLOOKUP(CB36,'Axe 2 Règles de gestion'!$D$2:$F$379,3, FALSE) -> Si la date du dernier jour travaillé payé est saisie alors elle doit être antérieure ou égale à la date de cessation de fonctions. | CD36: CEF_C_027 | CE36: =VLOOKUP(CD36,'Axe 2 Règles de gestion'!$D$2:$F$379,3, FALSE) -> La date de début du préavis doit être postérieure ou égale à la date de début de l'avenant au contrat. | CF36: CEF_C_031 | CG36: =VLOOKUP(CF36,'Axe 2 Règles de gestion'!$D$2:$F$379,3, FALSE) -> Si l'agent est placé sur une position payée, alors le champ « Date du dernier jour travaillé payé » doit être saisi. | CH36: CEF_C_032 | CI36: =VLOOKUP(CH36,'Axe 2 Règles de gestion'!$D$2:$F$379,3, FALSE) -> La date de cessation de fonction doit être antérieure ou égale à la date limite de départ à la retraite | CJ36: CEF_C_033 | CK36: =VLOOKUP(CJ36,'Axe 2 Règles de gestion'!$D$2:$F$379,3, FALSE) -> Si la date de fin de préavis est saisie alors elle doit être antérieure ou égale à la date de cessation de fonction.
A37: 22.00.00 | B37: M | C37: 44748.431 | D37: D0006 | E37: Cessation de fonction | F37: S0042 | G37: Cessation de fonction | H37: E0341 | I37: Démission acceptée sur demande | J37: Motif cessation de fonction saisi égal à 'Démission acceptée sur demande' | K37: A_CDF_MOTCFT [Saisi] = 'MC121' | L37: T0994 | M37: Démission acceptée sur demande | N37: Création Modification | Q37: Chaire professeur junior emploi donnant lieu à titularisation dans un corps de directeur de recherche | R37: P0268 | S37: Particulier | T37: Passant | U37: 44550 | W37: CEF_I_376 ET CEF_I_373 ET CEF_I_375 ET CEF_I_378 ET CEF_C_002 ET CEF_C_004 ET CEF_C_006 ET CEF_C_007 ET CEF_C_008 ET CEF_C_011 ET CEF_C_012 ET CEF_C_013 ET CEF_C_027 ET CEF_C_031 ET CEF_C_032 ET CEF_C_033 | X37: CEF_I_376 | Y37: =VLOOKUP(X37,'Axe 2 Règles de gestion'!$D$2:$F$379,3, FALSE) -> En cas de démission postérieure à la période d'essai, l'agent est tenu de respecter un préavis. | Z37: CEF_I_373 | AA37: =VLOOKUP(Z37,'Axe 2 Règles de gestion'!$D$2:$F$379,3, FALSE) -> Le préavis est de 15 jours pour les agents qui ont moins de 6 mois d'ancienneté, d'1 mois pour ceux qui ont une ancienneté comprise entre 6 mois et 2 ans et de 2 mois pour ceux qui ont une ancienneté d'au moins 2 ans. | AB37: CEF_I_375 | AC37: =VLOOKUP(AB37,'Axe 2 Règles de gestion'!$D$2:$F$379,3, FALSE) -> L'agent informe l'autorité signataire du contrat de son intention de démissionner par lettre recommandée avec demande d'avis de réception ou remise en main propre contre signature. | AD37: CEF_I_378 | AE37: =VLOOKUP(AD37,'Axe 2 Règles de gestion'!$D$2:$F$379,3, FALSE) -> Dans le cadre de la titularisation, le refus de signature ou la rupture de l'engagement du fait de l'agent est considéré comme une démission. | BN37: CEF_C_002 | BO37: =VLOOKUP(BN37,'Axe 2 Règles de gestion'!$D$2:$F$379,3, FALSE) -> La date de la cessation de fonctions doit être postérieure ou égale à la date de début de la dernière position en cours. | BP37: CEF_C_004 | BQ37: =VLOOKUP(BP37,'Axe 2 Règles de gestion'!$D$2:$F$379,3, FALSE) -> La date de cessation de fonction doit être postérieure ou égale à la date de début du lien juridique | BR37: CEF_C_006 | BS37: =VLOOKUP(BR37,'Axe 2 Règles de gestion'!$D$2:$F$379,3, FALSE) -> La date de notification de la rupture du contrat doit être antérieure à la date de fin réelle ou prévisionnelle du lien juridique | BT37: CEF_C_007 | BU37: =VLOOKUP(BT37,'Axe 2 Règles de gestion'!$D$2:$F$379,3, FALSE) -> La date de notification de la rupture du contrat doit être renseignée | BV37: CEF_C_008 | BW37: =VLOOKUP(BV37,'Axe 2 Règles de gestion'!$D$2:$F$379,3, FALSE) -> La date du dernier jour travaillé payé doit être antérieure ou égale à la date de fin réelle ou prévisionnelle du lien juridique | BX37: CEF_C_011 | BY37: =VLOOKUP(BX37,'Axe 2 Règles de gestion'!$D$2:$F$379,3, FALSE) -> La date de début du préavis doit être postérieure à la date de début du contrat. | BZ37: CEF_C_012 | CA37: =VLOOKUP(BZ37,'Axe 2 Règles de gestion'!$D$2:$F$379,3, FALSE) -> La date de fin du préavis doit être antérieure ou égale à la date de fin réelle ou prévisionnelle du lien juridique. | CB37: CEF_C_013 | CC37: =VLOOKUP(CB37,'Axe 2 Règles de gestion'!$D$2:$F$379,3, FALSE) -> Si la date du dernier jour travaillé payé est saisie alors elle doit être antérieure ou égale à la date de cessation de fonctions. | CD37: CEF_C_027 | CE37: =VLOOKUP(CD37,'Axe 2 Règles de gestion'!$D$2:$F$379,3, FALSE) -> La date de début du préavis doit être postérieure ou égale à la date de début de l'avenant au contrat. | CF37: CEF_C_031 | CG37: =VLOOKUP(CF37,'Axe 2 Règles de gestion'!$D$2:$F$379,3, FALSE) -> Si l'agent est placé sur une position payée, alors le champ « Date du dernier jour travaillé payé » doit être saisi. | CH37: CEF_C_032 | CI37: =VLOOKUP(CH37,'Axe 2 Règles de gestion'!$D$2:$F$379,3, FALSE) -> La date de cessation de fonction doit être antérieure ou égale à la date limite de départ à la retraite | CJ37: CEF_C_033 | CK37: =VLOOKUP(CJ37,'Axe 2 Règles de gestion'!$D$2:$F$379,3, FALSE) -> Si la date de fin de préavis est saisie alors elle doit être antérieure ou égale à la date de cessation de fonction.
A38: 22.00.00 | B38: M | C38: 44748.432 | D38: D0006 | E38: Cessation de fonction | F38: S0042 | G38: Cessation de fonction | H38: E0341 | I38: Démission acceptée sur demande | J38: Motif cessation de fonction saisi égal à 'Démission acceptée sur demande' | K38: A_CDF_MOTCFT [Saisi] = 'MC121' | L38: T0994 | M38: Démission acceptée sur demande | N38: Création Modification | Q38: Chaire professeur junior emploi donnant lieu à titularisation dans un corps de professeur | R38: P0269 | S38: Particulier | T38: Passant | U38: 44550 | W38: CEF_I_376 ET CEF_I_373 ET CEF_I_375 ET CEF_I_378 ET CEF_C_002 ET CEF_C_004 ET CEF_C_006 ET CEF_C_007 ET CEF_C_008 ET CEF_C_011 ET CEF_C_012 ET CEF_C_013 ET CEF_C_027 ET CEF_C_031 ET CEF_C_032 ET CEF_C_033 | X38: CEF_I_376 | Y38: =VLOOKUP(X38,'Axe 2 Règles de gestion'!$D$2:$F$379,3, FALSE) -> En cas de démission postérieure à la période d'essai, l'agent est tenu de respecter un préavis. | Z38: CEF_I_373 | AA38: =VLOOKUP(Z38,'Axe 2 Règles de gestion'!$D$2:$F$379,3, FALSE) -> Le préavis est de 15 jours pour les agents qui ont moins de 6 mois d'ancienneté, d'1 mois pour ceux qui ont une ancienneté comprise entre 6 mois et 2 ans et de 2 mois pour ceux qui ont une ancienneté d'au moins 2 ans. | AB38: CEF_I_375 | AC38: =VLOOKUP(AB38,'Axe 2 Règles de gestion'!$D$2:$F$379,3, FALSE) -> L'agent informe l'autorité signataire du contrat de son intention de démissionner par lettre recommandée avec demande d'avis de réception ou remise en main propre contre signature. | AD38: CEF_I_378 | AE38: =VLOOKUP(AD38,'Axe 2 Règles de gestion'!$D$2:$F$379,3, FALSE) -> Dans le cadre de la titularisation, le refus de signature ou la rupture de l'engagement du fait de l'agent est considéré comme une démission. | BN38: CEF_C_002 | BO38: =VLOOKUP(BN38,'Axe 2 Règles de gestion'!$D$2:$F$379,3, FALSE) -> La date de la cessation de fonctions doit être postérieure ou égale à la date de début de la dernière position en cours. | BP38: CEF_C_004 | BQ38: =VLOOKUP(BP38,'Axe 2 Règles de gestion'!$D$2:$F$379,3, FALSE) -> La date de cessation de fonction doit être postérieure ou égale à la date de début du lien juridique | BR38: CEF_C_006 | BS38: =VLOOKUP(BR38,'Axe 2 Règles de gestion'!$D$2:$F$379,3, FALSE) -> La date de notification de la rupture du contrat doit être antérieure à la date de fin réelle ou prévisionnelle du lien juridique | BT38: CEF_C_007 | BU38: =VLOOKUP(BT38,'Axe 2 Règles de gestion'!$D$2:$F$379,3, FALSE) -> La date de notification de la rupture du contrat doit être renseignée | BV38: CEF_C_008 | BW38: =VLOOKUP(BV38,'Axe 2 Règles de gestion'!$D$2:$F$379,3, FALSE) -> La date du dernier jour travaillé payé doit être antérieure ou égale à la date de fin réelle ou prévisionnelle du lien juridique | BX38: CEF_C_011 | BY38: =VLOOKUP(BX38,'Axe 2 Règles de gestion'!$D$2:$F$379,3, FALSE) -> La date de début du préavis doit être postérieure à la date de début du contrat. | BZ38: CEF_C_012 | CA38: =VLOOKUP(BZ38,'Axe 2 Règles de gestion'!$D$2:$F$379,3, FALSE) -> La date de fin du préavis doit être antérieure ou égale à la date de fin réelle ou prévisionnelle du lien juridique. | CB38: CEF_C_013 | CC38: =VLOOKUP(CB38,'Axe 2 Règles de gestion'!$D$2:$F$379,3, FALSE) -> Si la date du dernier jour travaillé payé est saisie alors elle doit être antérieure ou égale à la date de cessation de fonctions. | CD38: CEF_C_027 | CE38: =VLOOKUP(CD38,'Axe 2 Règles de gestion'!$D$2:$F$379,3, FALSE) -> La date de début du préavis doit être postérieure ou égale à la date de début de l'avenant au contrat. | CF38: CEF_C_031 | CG38: =VLOOKUP(CF38,'Axe 2 Règles de gestion'!$D$2:$F$379,3, FALSE) -> Si l'agent est placé sur une position payée, alors le champ « Date du dernier jour travaillé payé » doit être saisi. | CH38: CEF_C_032 | CI38: =VLOOKUP(CH38,'Axe 2 Règles de gestion'!$D$2:$F$379,3, FALSE) -> La date de cessation de fonction doit être antérieure ou égale à la date limite de départ à la retraite | CJ38: CEF_C_033 | CK38: =VLOOKUP(CJ38,'Axe 2 Règles de gestion'!$D$2:$F$379,3, FALSE) -> Si la date de fin de préavis est saisie alors elle doit être antérieure ou égale à la date de cessation de fonction.
A39: 17.10.00 | B39: A | C39: 43152.5 | D39: D0006 | E39: Cessation de fonction | F39: S0042 | G39: Cessation de fonction | H39: E0342 | I39: Démission d'office | J39: Motif cessation de fonction saisi égal à 'Démission d'office' | K39: A_CDF_MOTCFT [Saisi] = 'MC12A' | L39: T0995 | M39: Démission d'office | N39: Création Modification | Q39: Titulaire ou magistrat | R39: P0001 | S39: Général | T39: Exclu | U39: 40725
A40: 17.10.00 | B40: A | C40: 43152.5 | D40: D0006 | E40: Cessation de fonction | F40: S0042 | G40: Cessation de fonction | H40: E0342 | I40: Démission d'office | J40: Motif cessation de fonction saisi égal à 'Démission d'office' | K40: A_CDF_MOTCFT [Saisi] = 'MC12A' | L40: T0995 | M40: Démission d'office | N40: Création Modification | Q40: Contractuel | R40: P0003 | S40: Général | T40: Exclu | U40: 40725
A41: 17.10.00 | B41: A | C41: 43152.5 | D41: D0006 | E41: Cessation de fonction | F41: S0042 | G41: Cessation de fonction | H41: E0342 | I41: Démission d'office | J41: Motif cessation de fonction saisi égal à 'Démission d'office' | K41: A_CDF_MOTCFT [Saisi] = 'MC12A' | L41: T0995 | M41: Démission d'office | N41: Création Modification | Q41: Stagiaire ou auditeur ou élève | R41: P0004 | S41: Général | T41: Exclu | U41: 40725
A42: 17.10.00 | B42: A | C42: 43189.5 | D42: D0006 | E42: Cessation de fonction | F42: S0042 | G42: Cessation de fonction | H42: E0342 | I42: Démission d'office | J42: Motif cessation de fonction saisi égal à 'Démission d'office' | K42: A_CDF_MOTCFT [Saisi] = 'MC12A' | L42: T0995 | M42: Démission d'office | N42: Création Modification | Q42: Ouvrier d'état | R42: P0005 | S42: Général | T42: Exclu | U42: 40725
A43: 18.10.00 | B43: M | C43: 43152.5 | D43: D0006 | E43: Cessation de fonction | F43: S0042 | G43: Cessation de fonction | H43: E0342 | I43: Démission d'office | J43: Motif cessation de fonction saisi égal à 'Démission d'office' | K43: A_CDF_MOTCFT [Saisi] = 'MC12A' | L43: T0995 | M43: Démission d'office | N43: Création Modification | Q43: Magistrat de l'ordre judiciaire | R43: P0007 | S43: Particulier | T43: Passant | U43: 40725 | W43: CEF_C_001 ET CEF_C_002 ET CEF_C_009 ET CEF_C_013 ET CEF_C_014 ET CEF_C_031 ET CEF_C_032 ET CEF_C_033 | BN43: CEF_C_001 | BO43: =VLOOKUP(BN43,'Axe 2 Règles de gestion'!$D$2:$F$379,3, FALSE) -> La date de cessation de fonctions doit être postérieure ou égale à la date d'entrée dans la FPE ou dans la carrière militaire. | BP43: CEF_C_002 | BQ43: =VLOOKUP(BP43,'Axe 2 Règles de gestion'!$D$2:$F$379,3, FALSE) -> La date de la cessation de fonctions doit être postérieure ou égale à la date de début de la dernière position en cours. | BR43: CEF_C_009 | BS43: =VLOOKUP(BR43,'Axe 2 Règles de gestion'!$D$2:$F$379,3, FALSE) -> Si les dates de début et de fin de préavis sont saisies, alors la date de fin du préavis doit être postérieure ou égale à la date de début du préavis. | BT43: CEF_C_013 | BU43: =VLOOKUP(BT43,'Axe 2 Règles de gestion'!$D$2:$F$379,3, FALSE) -> Si la date du dernier jour travaillé payé est saisie alors elle doit être antérieure ou égale à la date de cessation de fonctions. | BV43: CEF_C_014 | BW43: =VLOOKUP(BV43,'Axe 2 Règles de gestion'!$D$2:$F$379,3, FALSE) -> Si la date de début du préavis est saisie alors elle doit être postérieure ou égale à la date d'entrée dans la FPE ou dans la carrière militaire. | BX43: CEF_C_031 | BY43: =VLOOKUP(BX43,'Axe 2 Règles de gestion'!$D$2:$F$379,3, FALSE) -> Si l'agent est placé sur une position payée, alors le champ « Date du dernier jour travaillé payé » doit être saisi. | BZ43: CEF_C_032 | CA43: =VLOOKUP(BZ43,'Axe 2 Règles de gestion'!$D$2:$F$379,3, FALSE) -> La date de cessation de fonction doit être antérieure ou égale à la date limite de départ à la retraite | CB43: CEF_C_033 | CC43: =VLOOKUP(CB43,'Axe 2 Règles de gestion'!$D$2:$F$379,3, FALSE) -> Si la date de fin de préavis est saisie alors elle doit être antérieure ou égale à la date de cessation de fonction.
A44: 18.10.00 | B44: M | C44: 43152.5 | D44: D0006 | E44: Cessation de fonction | F44: S0042 | G44: Cessation de fonction | H44: E0342 | I44: Démission d'office | J44: Motif cessation de fonction saisi égal à 'Démission d'office' | K44: A_CDF_MOTCFT [Saisi] = 'MC12A' | L44: T0995 | M44: Démission d'office | N44: Création Modification | Q44: Auditeur de justice | R44: P0009 | S44: Particulier | T44: Passant | U44: 40725 | W44: CEF_I_043 ET CEF_I_044 ET CEF_I_045 ET CEF_C_001 ET CEF_C_002 ET CEF_C_006 ET CEF_C_007 ET CEF_C_009 ET CEF_C_013 ET CEF_C_014 ET CEF_C_031 ET CEF_C_032 ET CEF_C_033 | X44: CEF_I_043 | Y44: =VLOOKUP(X44,'Axe 2 Règles de gestion'!$D$2:$F$379,3, FALSE) -> Un auditeur de justice qui n'a pas exprimé de choix fait d'office l'objet d'une proposition de nomination et s'il refuse cette proposition, il est considéré comme démissionnaire. | Z44: CEF_I_044 | AA44: =VLOOKUP(Z44,'Axe 2 Règles de gestion'!$D$2:$F$379,3, FALSE) -> Si avis défavorable pour la nomination d'un agent à un emploi du siège une nouvelle proposition est faite après consultation de l'agent et soumise pour avis à la formation compétente du Conseil supérieur. Son refus est considéré comme une démission. | AB44: CEF_I_045 | AC44: =VLOOKUP(AB44,'Axe 2 Règles de gestion'!$D$2:$F$379,3, FALSE) -> Si avis défavorable pour la nomination d'un agent à un emploi du parquet, le garde des sceaux peut passer outre ou faire une autre proposition après consultation de l'agent puis avis du Conseil supérieur. Le refus de l'auditeur équivaut à une démission. | BN44: CEF_C_001 | BO44: =VLOOKUP(BN44,'Axe 2 Règles de gestion'!$D$2:$F$379,3, FALSE) -> La date de cessation de fonctions doit être postérieure ou égale à la date d'entrée dans la FPE ou dans la carrière militaire. | BP44: CEF_C_002 | BQ44: =VLOOKUP(BP44,'Axe 2 Règles de gestion'!$D$2:$F$379,3, FALSE) -> La date de la cessation de fonctions doit être postérieure ou égale à la date de début de la dernière position en cours. | BR44: CEF_C_006 | BS44: =VLOOKUP(BR44,'Axe 2 Règles de gestion'!$D$2:$F$379,3, FALSE) -> La date de notification de la rupture du contrat doit être antérieure à la date de fin réelle ou prévisionnelle du lien juridique | BT44: CEF_C_007 | BU44: =VLOOKUP(BT44,'Axe 2 Règles de gestion'!$D$2:$F$379,3, FALSE) -> La date de notification de la rupture du contrat doit être renseignée | BV44: CEF_C_009 | BW44: =VLOOKUP(BV44,'Axe 2 Règles de gestion'!$D$2:$F$379,3, FALSE) -> Si les dates de début et de fin de préavis sont saisies, alors la date de fin du préavis doit être postérieure ou égale à la date de début du préavis. | BX44: CEF_C_013 | BY44: =VLOOKUP(BX44,'Axe 2 Règles de gestion'!$D$2:$F$379,3, FALSE) -> Si la date du dernier jour travaillé payé est saisie alors elle doit être antérieure ou égale à la date de cessation de fonctions. | BZ44: CEF_C_014 | CA44: =VLOOKUP(BZ44,'Axe 2 Règles de gestion'!$D$2:$F$379,3, FALSE) -> Si la date de début du préavis est saisie alors elle doit être postérieure ou égale à la date d'entrée dans la FPE ou dans la carrière militaire. | CB44: CEF_C_031 | CC44: =VLOOKUP(CB44,'Axe 2 Règles de gestion'!$D$2:$F$379,3, FALSE) -> Si l'agent est placé sur une position payée, alors le champ « Date du dernier jour travaillé payé » doit être saisi. | CD44: CEF_C_032 | CE44: =VLOOKUP(CD44,'Axe 2 Règles de gestion'!$D$2:$F$379,3, FALSE) -> La date de cessation de fonction doit être antérieure ou égale à la date limite de départ à la retraite | CF44: CEF_C_033 | CG44: =VLOOKUP(CF44,'Axe 2 Règles de gestion'!$D$2:$F$379,3, FALSE) -> Si la date de fin de préavis est saisie alors elle doit être antérieure ou égale à la date de cessation de fonction.
A45: 17.10.00 | B45: A | C45: 43152.5 | D45: D0006 | E45: Cessation de fonction | F45: S0042 | G45: Cessation de fonction | H45: E0343 | I45: Démission à la fin de la période d'essai | J45: Motif cessation de fonction saisi égal à 'Démission à la fin de la période d'essai' | K45: A_CDF_MOTCFT [Saisi] = 'MC12B' | L45: T0996 | M45: Démission à la fin de la période d'essai | N45: Création Modification | Q45: Titulaire ou magistrat | R45: P0001 | S45: Général | T45: Exclu | U45: 40725
A46: 18.10.00 | B46: M | C46: 43389.367 | D46: D0006 | E46: Cessation de fonction | F46: S0042 | G46: Cessation de fonction | H46: E0343 | I46: Démission à la fin de la période d'essai | J46: Motif cessation de fonction saisi égal à 'Démission à la fin de la période d'essai' | K46: A_CDF_MOTCFT [Saisi] = 'MC12B' | L46: T0996 | M46: Démission à la fin de la période d'essai | N46: Création Modification | Q46: Contractuel | R46: P0003 | S46: Général | T46: Passant | U46: 40725 | W46: CEF_C_002 ET CEF_C_004 ET CEF_C_006 ET CEF_C_007 ET CEF_C_008 ET CEF_C_011 ET CEF_C_012 ET CEF_C_013 ET CEF_C_027 ET CEF_C_031 ET CEF_C_032 ET CEF_C_033 | BN46: CEF_C_002 | BO46: =VLOOKUP(BN46,'Axe 2 Règles de gestion'!$D$2:$F$379,3, FALSE) -> La date de la cessation de fonctions doit être postérieure ou égale à la date de début de la dernière position en cours. | BP46: CEF_C_004 | BQ46: =VLOOKUP(BP46,'Axe 2 Règles de gestion'!$D$2:$F$379,3, FALSE) -> La date de cessation de fonction doit être postérieure ou égale à la date de début du lien juridique | BR46: CEF_C_006 | BS46: =VLOOKUP(BR46,'Axe 2 Règles de gestion'!$D$2:$F$379,3, FALSE) -> La date de notification de la rupture du contrat doit être antérieure à la date de fin réelle ou prévisionnelle du lien juridique | BT46: CEF_C_007 | BU46: =VLOOKUP(BT46,'Axe 2 Règles de gestion'!$D$2:$F$379,3, FALSE) -> La date de notification de la rupture du contrat doit être renseignée | BV46: CEF_C_008 | BW46: =VLOOKUP(BV46,'Axe 2 Règles de gestion'!$D$2:$F$379,3, FALSE) -> La date du dernier jour travaillé payé doit être antérieure ou égale à la date de fin réelle ou prévisionnelle du lien juridique | BX46: CEF_C_011 | BY46: =VLOOKUP(BX46,'Axe 2 Règles de gestion'!$D$2:$F$379,3, FALSE) -> La date de début du préavis doit être postérieure à la date de début du contrat. | BZ46: CEF_C_012 | CA46: =VLOOKUP(BZ46,'Axe 2 Règles de gestion'!$D$2:$F$379,3, FALSE) -> La date de fin du préavis doit être antérieure ou égale à la date de fin réelle ou prévisionnelle du lien juridique. | CB46: CEF_C_013 | CC46: =VLOOKUP(CB46,'Axe 2 Règles de gestion'!$D$2:$F$379,3, FALSE) -> Si la date du dernier jour travaillé payé est saisie alors elle doit être antérieure ou égale à la date de cessation de fonctions. | CD46: CEF_C_027 | CE46: =VLOOKUP(CD46,'Axe 2 Règles de gestion'!$D$2:$F$379,3, FALSE) -> La date de début du préavis doit être postérieure ou égale à la date de début de l'avenant au contrat. | CF46: CEF_C_031 | CG46: =VLOOKUP(CF46,'Axe 2 Règles de gestion'!$D$2:$F$379,3, FALSE) -> Si l'agent est placé sur une position payée, alors le champ « Date du dernier jour travaillé payé » doit être saisi. | CH46: CEF_C_032 | CI46: =VLOOKUP(CH46,'Axe 2 Règles de gestion'!$D$2:$F$379,3, FALSE) -> La date de cessation de fonction doit être antérieure ou égale à la date limite de départ à la retraite | CJ46: CEF_C_033 | CK46: =VLOOKUP(CJ46,'Axe 2 Règles de gestion'!$D$2:$F$379,3, FALSE) -> Si la date de fin de préavis est saisie alors elle doit être antérieure ou égale à la date de cessation de fonction.
A47: 17.10.00 | B47: A | C47: 43152.5 | D47: D0006 | E47: Cessation de fonction | F47: S0042 | G47: Cessation de fonction | H47: E0343 | I47: Démission à la fin de la période d'essai | J47: Motif cessation de fonction saisi égal à 'Démission à la fin de la période d'essai' | K47: A_CDF_MOTCFT [Saisi] = 'MC12B' | L47: T0996 | M47: Démission à la fin de la période d'essai | N47: Création Modification | Q47: Stagiaire ou auditeur ou élève | R47: P0004 | S47: Général | T47: Exclu | U47: 40725
A48: 17.10.00 | B48: A | C48: 43189.5 | D48: D0006 | E48: Cessation de fonction | F48: S0042 | G48: Cessation de fonction | H48: E0343 | I48: Démission à la fin de la période d'essai | J48: Motif cessation de fonction saisi égal à 'Démission à la fin de la période d'essai' | K48: A_CDF_MOTCFT [Saisi] = 'MC12B' | L48: T0996 | M48: Démission à la fin de la période d'essai | N48: Création Modification | Q48: Ouvrier d'état | R48: P0005 | S48: Général | T48: Exclu | U48: 40725
A49: 17.10.00 | B49: A | C49: 43152.5 | D49: D0006 | E49: Cessation de fonction | F49: S0042 | G49: Cessation de fonction | H49: E0343 | I49: Démission à la fin de la période d'essai | J49: Motif cessation de fonction saisi égal à 'Démission à la fin de la période d'essai' | K49: A_CDF_MOTCFT [Saisi] = 'MC12B' | L49: T0996 | M49: Démission à la fin de la période d'essai | N49: Création Modification | Q49: Personnel civil payé à l'acte ou à la tâche | R49: P0054 | S49: Particulier | T49: Exclu | U49: 40725
A50: 18.10.00 | B50: M | C50: 43152.5 | D50: D0006 | E50: Cessation de fonction | F50: S0042 | G50: Cessation de fonction | H50: E0343 | I50: Démission à la fin de la période d'essai | J50: Motif cessation de fonction saisi égal à 'Démission à la fin de la période d'essai' | K50: A_CDF_MOTCFT [Saisi] = 'MC12B' | L50: T0996 | M50: Démission à la fin de la période d'essai | N50: Création Modification | Q50: Assistant de justice | R50: P0173 | S50: Particulier | T50: Passant | U50: 40725 | W50: CEF_C_002 ET CEF_C_004 ET CEF_C_006 ET CEF_C_007 ET CEF_C_008 ET CEF_C_011 ET CEF_C_012 ET CEF_C_013 ET CEF_C_027 ET CEF_C_031 ET CEF_C_032 ET CEF_C_033 | BN50: CEF_C_002 | BO50: =VLOOKUP(BN50,'Axe 2 Règles de gestion'!$D$2:$F$379,3, FALSE) -> La date de la cessation de fonctions doit être postérieure ou égale à la date de début de la dernière position en cours. | BP50: CEF_C_004 | BQ50: =VLOOKUP(BP50,'Axe 2 Règles de gestion'!$D$2:$F$379,3, FALSE) -> La date de cessation de fonction doit être postérieure ou égale à la date de début du lien juridique | BR50: CEF_C_006 | BS50: =VLOOKUP(BR50,'Axe 2 Règles de gestion'!$D$2:$F$379,3, FALSE) -> La date de notification de la rupture du contrat doit être antérieure à la date de fin réelle ou prévisionnelle du lien juridique | BT50: CEF_C_007 | BU50: =VLOOKUP(BT50,'Axe 2 Règles de gestion'!$D$2:$F$379,3, FALSE) -> La date de notification de la rupture du contrat doit être renseignée | BV50: CEF_C_008 | BW50: =VLOOKUP(BV50,'Axe 2 Règles de gestion'!$D$2:$F$379,3, FALSE) -> La date du dernier jour travaillé payé doit être antérieure ou égale à la date de fin réelle ou prévisionnelle du lien juridique | BX50: CEF_C_011 | BY50: =VLOOKUP(BX50,'Axe 2 Règles de gestion'!$D$2:$F$379,3, FALSE) -> La date de début du préavis doit être postérieure à la date de début du contrat. | BZ50: CEF_C_012 | CA50: =VLOOKUP(BZ50,'Axe 2 Règles de gestion'!$D$2:$F$379,3, FALSE) -> La date de fin du préavis doit être antérieure ou égale à la date de fin réelle ou prévisionnelle du lien juridique. | CB50: CEF_C_013 | CC50: =VLOOKUP(CB50,'Axe 2 Règles de gestion'!$D$2:$F$379,3, FALSE) -> Si la date du dernier jour travaillé payé est saisie alors elle doit être antérieure ou égale à la date de cessation de fonctions. | CD50: CEF_C_027 | CE50: =VLOOKUP(CD50,'Axe 2 Règles de gestion'!$D$2:$F$379,3, FALSE) -> La date de début du préavis doit être postérieure ou égale à la date de début de l'avenant au contrat. | CF50: CEF_C_031 | CG50: =VLOOKUP(CF50,'Axe 2 Règles de gestion'!$D$2:$F$379,3, FALSE) -> Si l'agent est placé sur une position payée, alors le champ « Date du dernier jour travaillé payé » doit être saisi. | CH50: CEF_C_032 | CI50: =VLOOKUP(CH50,'Axe 2 Règles de gestion'!$D$2:$F$379,3, FALSE) -> La date de cessation de fonction doit être antérieure ou égale à la date limite de départ à la retraite | CJ50: CEF_C_033 | CK50: =VLOOKUP(CJ50,'Axe 2 Règles de gestion'!$D$2:$F$379,3, FALSE) -> Si la date de fin de préavis est saisie alors elle doit être antérieure ou égale à la date de cessation de fonction.
A51: 24.10.00 | B51: M | C51: 45608.611 | D51: D0006 | E51: Cessation de fonction | F51: S0042 | G51: Cessation de fonction | H51: E0344 | I51: Démission en cas de restructuration | J51: Motif cessation de fonction saisi égal à 'Démission en cas de restructuration' | K51: A_CDF_MOTCFT [Saisi] = 'MC123' | L51: T0997 | M51: Démission en cas de restructuration | N51: Création Modification | Q51: Titulaire ou magistrat | R51: P0001 | S51: Général | T51: Passant | U51: 40725 | W51: CEF_C_001 ET CEF_C_002 ET CEF_C_009 ET CEF_C_013 ET CEF_C_014 ET CEF_C_031 ET CEF_C_032 ET CEF_C_033 ET CEF_C_038 ET CEF_C_016 | BN51: CEF_C_001 | BO51: =VLOOKUP(BN51,'Axe 2 Règles de gestion'!$D$2:$F$379,3, FALSE) -> La date de cessation de fonctions doit être postérieure ou égale à la date d'entrée dans la FPE ou dans la carrière militaire. | BP51: CEF_C_002 | BQ51: =VLOOKUP(BP51,'Axe 2 Règles de gestion'!$D$2:$F$379,3, FALSE) -> La date de la cessation de fonctions doit être postérieure ou égale à la date de début de la dernière position en cours. | BR51: CEF_C_009 | BS51: =VLOOKUP(BR51,'Axe 2 Règles de gestion'!$D$2:$F$379,3, FALSE) -> Si les dates de début et de fin de préavis sont saisies, alors la date de fin du préavis doit être postérieure ou égale à la date de début du préavis. | BT51: CEF_C_013 | BU51: =VLOOKUP(BT51,'Axe 2 Règles de gestion'!$D$2:$F$379,3, FALSE) -> Si la date du dernier jour travaillé payé est saisie alors elle doit être antérieure ou égale à la date de cessation de fonctions. | BV51: CEF_C_014 | BW51: =VLOOKUP(BV51,'Axe 2 Règles de gestion'!$D$2:$F$379,3, FALSE) -> Si la date de début du préavis est saisie alors elle doit être postérieure ou égale à la date d'entrée dans la FPE ou dans la carrière militaire. | BX51: CEF_C_031 | BY51: =VLOOKUP(BX51,'Axe 2 Règles de gestion'!$D$2:$F$379,3, FALSE) -> Si l'agent est placé sur une position payée, alors le champ « Date du dernier jour travaillé payé » doit être saisi. | BZ51: CEF_C_032 | CA51: =VLOOKUP(BZ51,'Axe 2 Règles de gestion'!$D$2:$F$379,3, FALSE) -> La date de cessation de fonction doit être antérieure ou égale à la date limite de départ à la retraite | CB51: CEF_C_033 | CC51: =VLOOKUP(CB51,'Axe 2 Règles de gestion'!$D$2:$F$379,3, FALSE) -> Si la date de fin de préavis est saisie alors elle doit être antérieure ou égale à la date de cessation de fonction. | CD51: CEF_C_038 | CE51: =VLOOKUP(CD51,'Axe 2 Règles de gestion'!$D$2:$F$379,3, FALSE) -> Le champ " Date d'effet de la radiation des cadres ou des contrôles " doit être renseigné. | CF51: CEF_C_016 | CG51: =VLOOKUP(CF51,'Axe 2 Règles de gestion'!$D$2:$F$379,3, FALSE) -> Attention : La date d'effet de la demande de l'agent doit être saisie afin d'être récupérée automatiquement lors de la génération de l'acte.
A52: 24.10.00 | B52: M | C52: 45608.61 | D52: D0006 | E52: Cessation de fonction | F52: S0042 | G52: Cessation de fonction | H52: E0344 | I52: Démission en cas de restructuration | J52: Motif cessation de fonction saisi égal à 'Démission en cas de restructuration' | K52: A_CDF_MOTCFT [Saisi] = 'MC123' | L52: T0997 | M52: Démission en cas de restructuration | N52: Création Modification | Q52: Contractuel | R52: P0003 | S52: Général | T52: Passant | U52: 40725 | W52: CEF_C_002 ET CEF_C_004 ET CEF_C_006 ET CEF_C_007 ET CEF_C_008 ET CEF_C_011 ET CEF_C_012 ET CEF_C_013 ET CEF_C_027 ET CEF_C_031 ET CEF_C_032 ET CEF_C_033 ET CEF_C_016 | BN52: CEF_C_002 | BO52: =VLOOKUP(BN52,'Axe 2 Règles de gestion'!$D$2:$F$379,3, FALSE) -> La date de la cessation de fonctions doit être postérieure ou égale à la date de début de la dernière position en cours. | BP52: CEF_C_004 | BQ52: =VLOOKUP(BP52,'Axe 2 Règles de gestion'!$D$2:$F$379,3, FALSE) -> La date de cessation de fonction doit être postérieure ou égale à la date de début du lien juridique | BR52: CEF_C_006 | BS52: =VLOOKUP(BR52,'Axe 2 Règles de gestion'!$D$2:$F$379,3, FALSE) -> La date de notification de la rupture du contrat doit être antérieure à la date de fin réelle ou prévisionnelle du lien juridique | BT52: CEF_C_007 | BU52: =VLOOKUP(BT52,'Axe 2 Règles de gestion'!$D$2:$F$379,3, FALSE) -> La date de notification de la rupture du contrat doit être renseignée | BV52: CEF_C_008 | BW52: =VLOOKUP(BV52,'Axe 2 Règles de gestion'!$D$2:$F$379,3, FALSE) -> La date du dernier jour travaillé payé doit être antérieure ou égale à la date de fin réelle ou prévisionnelle du lien juridique | BX52: CEF_C_011 | BY52: =VLOOKUP(BX52,'Axe 2 Règles de gestion'!$D$2:$F$379,3, FALSE) -> La date de début du préavis doit être postérieure à la date de début du contrat. | BZ52: CEF_C_012 | CA52: =VLOOKUP(BZ52,'Axe 2 Règles de gestion'!$D$2:$F$379,3, FALSE) -> La date de fin du préavis doit être antérieure ou égale à la date de fin réelle ou prévisionnelle du lien juridique. | CB52: CEF_C_013 | CC52: =VLOOKUP(CB52,'Axe 2 Règles de gestion'!$D$2:$F$379,3, FALSE) -> Si la date du dernier jour travaillé payé est saisie alors elle doit être antérieure ou égale à la date de cessation de fonctions. | CD52: CEF_C_027 | CE52: =VLOOKUP(CD52,'Axe 2 Règles de gestion'!$D$2:$F$379,3, FALSE) -> La date de début du préavis doit être postérieure ou égale à la date de début de l'avenant au contrat. | CF52: CEF_C_031 | CG52: =VLOOKUP(CF52,'Axe 2 Règles de gestion'!$D$2:$F$379,3, FALSE) -> Si l'agent est placé sur une position payée, alors le champ « Date du dernier jour travaillé payé » doit être saisi. | CH52: CEF_C_032 | CI52: =VLOOKUP(CH52,'Axe 2 Règles de gestion'!$D$2:$F$379,3, FALSE) -> La date de cessation de fonction doit être antérieure ou égale à la date limite de départ à la retraite | CJ52: CEF_C_033 | CK52: =VLOOKUP(CJ52,'Axe 2 Règles de gestion'!$D$2:$F$379,3, FALSE) -> Si la date de fin de préavis est saisie alors elle doit être antérieure ou égale à la date de cessation de fonction. | CL52: CEF_C_016 | CM52: =VLOOKUP(CL52,'Axe 2 Règles de gestion'!$D$2:$F$379,3, FALSE) -> Attention : La date d'effet de la demande de l'agent doit être saisie afin d'être récupérée automatiquement lors de la génération de l'acte.
A53: 20.10.00 | B53: M | C53: 44242.396 | D53: D0006 | E53: Cessation de fonction | F53: S0042 | G53: Cessation de fonction | H53: E0344 | I53: Démission en cas de restructuration | J53: Motif cessation de fonction saisi égal à 'Démission en cas de restructuration' | K53: A_CDF_MOTCFT [Saisi] = 'MC123' | L53: T0997 | M53: Démission en cas de restructuration | N53: Création Modification | Q53: Stagiaire ou auditeur ou élève | R53: P0004 | S53: Général | T53: Passant | U53: 40725 | W53: CEF_I_011 ET CEF_C_001 ET CEF_C_002 ET CEF_C_009 ET CEF_C_013 ET CEF_C_014 ET CEF_C_031 ET CEF_C_032 ET CEF_C_033 | X53: CEF_I_011 | Y53: =VLOOKUP(X53,'Axe 2 Règles de gestion'!$D$2:$F$379,3, FALSE) -> La demande de démission doit être adressée 1 mois au moins avant la date prévue pour la cessation de fonctions. | BN53: CEF_C_001 | BO53: =VLOOKUP(BN53,'Axe 2 Règles de gestion'!$D$2:$F$379,3, FALSE) -> La date de cessation de fonctions doit être postérieure ou égale à la date d'entrée dans la FPE ou dans la carrière militaire. | BP53: CEF_C_002 | BQ53: =VLOOKUP(BP53,'Axe 2 Règles de gestion'!$D$2:$F$379,3, FALSE) -> La date de la cessation de fonctions doit être postérieure ou égale à la date de début de la dernière position en cours. | BR53: CEF_C_009 | BS53: =VLOOKUP(BR53,'Axe 2 Règles de gestion'!$D$2:$F$379,3, FALSE) -> Si les dates de début et de fin de préavis sont saisies, alors la date de fin du préavis doit être postérieure ou égale à la date de début du préavis. | BT53: CEF_C_013 | BU53: =VLOOKUP(BT53,'Axe 2 Règles de gestion'!$D$2:$F$379,3, FALSE) -> Si la date du dernier jour travaillé payé est saisie alors elle doit être antérieure ou égale à la date de cessation de fonctions. | BV53: CEF_C_014 | BW53: =VLOOKUP(BV53,'Axe 2 Règles de gestion'!$D$2:$F$379,3, FALSE) -> Si la date de début du préavis est saisie alors elle doit être postérieure ou égale à la date d'entrée dans la FPE ou dans la carrière militaire. | BX53: CEF_C_031 | BY53: =VLOOKUP(BX53,'Axe 2 Règles de gestion'!$D$2:$F$379,3, FALSE) -> Si l'agent est placé sur une position payée, alors le champ « Date du dernier jour travaillé payé » doit être saisi. | BZ53: CEF_C_032 | CA53: =VLOOKUP(BZ53,'Axe 2 Règles de gestion'!$D$2:$F$379,3, FALSE) -> La date de cessation de fonction doit être antérieure ou égale à la date limite de départ à la retraite | CB53: CEF_C_033 | CC53: =VLOOKUP(CB53,'Axe 2 Règles de gestion'!$D$2:$F$379,3, FALSE) -> Si la date de fin de préavis est saisie alors elle doit être antérieure ou égale à la date de cessation de fonction.
A54: 17.10.00 | B54: A | C54: 43189.5 | D54: D0006 | E54: Cessation de fonction | F54: S0042 | G54: Cessation de fonction | H54: E0344 | I54: Démission en cas de restructuration | J54: Motif cessation de fonction saisi égal à 'Démission en cas de restructuration' | K54: A_CDF_MOTCFT [Saisi] = 'MC123' | L54: T0997 | M54: Démission en cas de restructuration | N54: Création Modification | Q54: Ouvrier d'état | R54: P0005 | S54: Général | T54: Exclu | U54: 40725
A55: 17.10.00 | B55: A | C55: 43152.5 | D55: D0006 | E55: Cessation de fonction | F55: S0042 | G55: Cessation de fonction | H55: E0344 | I55: Démission en cas de restructuration | J55: Motif cessation de fonction saisi égal à 'Démission en cas de restructuration' | K55: A_CDF_MOTCFT [Saisi] = 'MC123' | L55: T0997 | M55: Démission en cas de restructuration | N55: Création Modification | Q55: Magistrat de l'ordre judiciaire | R55: P0007 | S55: Particulier | T55: Exclu | U55: 40725
A56: 17.10.00 | B56: A | C56: 43152.5 | D56: D0006 | E56: Cessation de fonction | F56: S0042 | G56: Cessation de fonction | H56: E0344 | I56: Démission en cas de restructuration | J56: Motif cessation de fonction saisi égal à 'Démission en cas de restructuration' | K56: A_CDF_MOTCFT [Saisi] = 'MC123' | L56: T0997 | M56: Démission en cas de restructuration | N56: Création Modification | Q56: Auditeur de justice | R56: P0009 | S56: Particulier | T56: Exclu | U56: 40725
A57: 17.10.00 | B57: A | C57: 43152.5 | D57: D0006 | E57: Cessation de fonction | F57: S0042 | G57: Cessation de fonction | H57: E0344 | I57: Démission en cas de restructuration | J57: Motif cessation de fonction saisi égal à 'Démission en cas de restructuration' | K57: A_CDF_MOTCFT [Saisi] = 'MC123' | L57: T0997 | M57: Démission en cas de restructuration | N57: Création Modification | Q57: Personnel civil payé à l'acte ou à la tâche | R57: P0054 | S57: Particulier | T57: Exclu | U57: 40725
A58: 19.00.00 | B58: A | C58: 43636.586 | D58: D0006 | E58: Cessation de fonction | F58: S0042 | G58: Cessation de fonction | H58: E0344 | I58: Démission en cas de restructuration | J58: Motif cessation de fonction saisi égal à 'Démission en cas de restructuration' | K58: A_CDF_MOTCFT [Saisi] = 'MC123' | L58: T0997 | M58: Démission en cas de restructuration | N58: Création Modification | Q58: Ouvrier de la défense réglementé affilié | R58: P0093 | S58: Particulier | T58: Passant | U58: 40725 | W58: CEF_I_107 ET CEF_C_002 ET CEF_C_004 ET CEF_C_006 ET CEF_C_007 ET CEF_C_008 ET CEF_C_011 ET CEF_C_012 ET CEF_C_013 ET CEF_C_027 ET CEF_C_031 ET CEF_C_032 ET CEF_C_033 | X58: CEF_I_107 | Y58: =VLOOKUP(X58,'Axe 2 Règles de gestion'!$D$2:$F$379,3, FALSE) -> Le préavis est d'un mois si l'agent a une ancienneté au moins égale à 6 mois et de 8 jours si l'ancienneté est inférieure à 6 mois. | BN58: CEF_C_002 | BO58: =VLOOKUP(BN58,'Axe 2 Règles de gestion'!$D$2:$F$379,3, FALSE) -> La date de la cessation de fonctions doit être postérieure ou égale à la date de début de la dernière position en cours. | BP58: CEF_C_004 | BQ58: =VLOOKUP(BP58,'Axe 2 Règles de gestion'!$D$2:$F$379,3, FALSE) -> La date de cessation de fonction doit être postérieure ou égale à la date de début du lien juridique | BR58: CEF_C_006 | BS58: =VLOOKUP(BR58,'Axe 2 Règles de gestion'!$D$2:$F$379,3, FALSE) -> La date de notification de la rupture du contrat doit être antérieure à la date de fin réelle ou prévisionnelle du lien juridique | BT58: CEF_C_007 | BU58: =VLOOKUP(BT58,'Axe 2 Règles de gestion'!$D$2:$F$379,3, FALSE) -> La date de notification de la rupture du contrat doit être renseignée | BV58: CEF_C_008 | BW58: =VLOOKUP(BV58,'Axe 2 Règles de gestion'!$D$2:$F$379,3, FALSE) -> La date du dernier jour travaillé payé doit être antérieure ou égale à la date de fin réelle ou prévisionnelle du lien juridique | BX58: CEF_C_011 | BY58: =VLOOKUP(BX58,'Axe 2 Règles de gestion'!$D$2:$F$379,3, FALSE) -> La date de début du préavis doit être postérieure à la date de début du contrat. | BZ58: CEF_C_012 | CA58: =VLOOKUP(BZ58,'Axe 2 Règles de gestion'!$D$2:$F$379,3, FALSE) -> La date de fin du préavis doit être antérieure ou égale à la date de fin réelle ou prévisionnelle du lien juridique. | CB58: CEF_C_013 | CC58: =VLOOKUP(CB58,'Axe 2 Règles de gestion'!$D$2:$F$379,3, FALSE) -> Si la date du dernier jour travaillé payé est saisie alors elle doit être antérieure ou égale à la date de cessation de fonctions. | CD58: CEF_C_027 | CE58: =VLOOKUP(CD58,'Axe 2 Règles de gestion'!$D$2:$F$379,3, FALSE) -> La date de début du préavis doit être postérieure ou égale à la date de début de l'avenant au contrat. | CF58: CEF_C_031 | CG58: =VLOOKUP(CF58,'Axe 2 Règles de gestion'!$D$2:$F$379,3, FALSE) -> Si l'agent est placé sur une position payée, alors le champ « Date du dernier jour travaillé payé » doit être saisi. | CH58: CEF_C_032 | CI58: =VLOOKUP(CH58,'Axe 2 Règles de gestion'!$D$2:$F$379,3, FALSE) -> La date de cessation de fonction doit être antérieure ou égale à la date limite de départ à la retraite | CJ58: CEF_C_033 | CK58: =VLOOKUP(CJ58,'Axe 2 Règles de gestion'!$D$2:$F$379,3, FALSE) -> Si la date de fin de préavis est saisie alors elle doit être antérieure ou égale à la date de cessation de fonction.
A59: 25.10.00 | B59: M | C59: 45974.402 | D59: D0006 | E59: Cessation de fonction | F59: S0042 | G59: Cessation de fonction | H59: E0344 | I59: Démission en cas de restructuration | J59: Motif cessation de fonction saisi égal à 'Démission en cas de restructuration' | K59: A_CDF_MOTCFT [Saisi] = 'MC123' | L59: T0997 | M59: Démission en cas de restructuration | N59: Création Modification | Q59: Ouvrier des parcs et ateliers ou assimilé confirmé | R59: P0096 | S59: Particulier | T59: Passant | U59: 40725 | V59: 45900 | W59: CEF_D_117 ET CEF_C_002 ET CEF_C_004 ET CEF_C_006 ET CEF_C_007 ET CEF_C_008 ET CEF_C_011 ET CEF_C_012 ET CEF_C_013 ET CEF_C_027 ET CEF_C_031 ET CEF_C_032 ET CEF_C_033 | BH59: CEF_D_117 | BI59: =VLOOKUP(BH59,'Axe 2 Règles de gestion'!$D$2:$F$379,3, FALSE) -> En cas de démission, le préavis est au minimum de un mois. | BN59: CEF_C_002 | BO59: =VLOOKUP(BN59,'Axe 2 Règles de gestion'!$D$2:$F$379,3, FALSE) -> La date de la cessation de fonctions doit être postérieure ou égale à la date de début de la dernière position en cours. | BP59: CEF_C_004 | BQ59: =VLOOKUP(BP59,'Axe 2 Règles de gestion'!$D$2:$F$379,3, FALSE) -> La date de cessation de fonction doit être postérieure ou égale à la date de début du lien juridique | BR59: CEF_C_006 | BS59: =VLOOKUP(BR59,'Axe 2 Règles de gestion'!$D$2:$F$379,3, FALSE) -> La date de notification de la rupture du contrat doit être antérieure à la date de fin réelle ou prévisionnelle du lien juridique | BT59: CEF_C_007 | BU59: =VLOOKUP(BT59,'Axe 2 Règles de gestion'!$D$2:$F$379,3, FALSE) -> La date de notification de la rupture du contrat doit être renseignée | BV59: CEF_C_008 | BW59: =VLOOKUP(BV59,'Axe 2 Règles de gestion'!$D$2:$F$379,3, FALSE) -> La date du dernier jour travaillé payé doit être antérieure ou égale à la date de fin réelle ou prévisionnelle du lien juridique | BX59: CEF_C_011 | BY59: =VLOOKUP(BX59,'Axe 2 Règles de gestion'!$D$2:$F$379,3, FALSE) -> La date de début du préavis doit être postérieure à la date de début du contrat. | BZ59: CEF_C_012 | CA59: =VLOOKUP(BZ59,'Axe 2 Règles de gestion'!$D$2:$F$379,3, FALSE) -> La date de fin du préavis doit être antérieure ou égale à la date de fin réelle ou prévisionnelle du lien juridique. | CB59: CEF_C_013 | CC59: =VLOOKUP(CB59,'Axe 2 Règles de gestion'!$D$2:$F$379,3, FALSE) -> Si la date du dernier jour travaillé payé est saisie alors elle doit être antérieure ou égale à la date de cessation de fonctions. | CD59: CEF_C_027 | CE59: =VLOOKUP(CD59,'Axe 2 Règles de gestion'!$D$2:$F$379,3, FALSE) -> La date de début du préavis doit être postérieure ou égale à la date de début de l'avenant au contrat. | CF59: CEF_C_031 | CG59: =VLOOKUP(CF59,'Axe 2 Règles de gestion'!$D$2:$F$379,3, FALSE) -> Si l'agent est placé sur une position payée, alors le champ « Date du dernier jour travaillé payé » doit être saisi. | CH59: CEF_C_032 | CI59: =VLOOKUP(CH59,'Axe 2 Règles de gestion'!$D$2:$F$379,3, FALSE) -> La date de cessation de fonction doit être antérieure ou égale à la date limite de départ à la retraite | CJ59: CEF_C_033 | CK59: =VLOOKUP(CJ59,'Axe 2 Règles de gestion'!$D$2:$F$379,3, FALSE) -> Si la date de fin de préavis est saisie alors elle doit être antérieure ou égale à la date de cessation de fonction. | CN59: 2025-112
A60: 25.10.00 | B60: A | C60: 45974.419 | D60: D0006 | E60: Cessation de fonction | F60: S0042 | G60: Cessation de fonction | H60: E0344 | I60: Démission en cas de restructuration | J60: Motif cessation de fonction saisi égal à 'Démission en cas de restructuration' | K60: A_CDF_MOTCFT [Saisi] = 'MC123' | L60: T0997 | M60: Démission en cas de restructuration | N60: Création Modification | Q60: Ouvrier des parcs et ateliers confirmé ou stagiaire | R60: P0143 | S60: Particulier | T60: Passant | U60: 45901 | W60: CEF_I_446 ET CEF_I_452 ET CEF_D_004 ET CEF_C_002 ET CEF_C_004 ET CEF_C_006 ET CEF_C_007 ET CEF_C_008 ET CEF_C_011 ET CEF_C_012 ET CEF_C_013 ET CEF_C_027 ET CEF_C_031 ET CEF_C_032 ET CEF_C_033 | X60: CEF_I_446 | Y60: =VLOOKUP(X60,'Axe 2 Règles de gestion'!$D$2:$F$379,3, FALSE) -> L'agent informe le chef de service ou le directeur de l'établissement de son intention de démissionner par lettre recommandée avec demande d'avis de réception. | Z60: CEF_I_452 | AA60: =VLOOKUP(Z60,'Axe 2 Règles de gestion'!$D$2:$F$379,3, FALSE) -> En cas de restructuration du poste ou de suppression de l'emploi, l'agent peut démissionner. | BH60: CEF_D_004 | BI60: =VLOOKUP(BH60,'Axe 2 Règles de gestion'!$D$2:$F$379,3, FALSE) -> L'agent est tenu, dans ce cas, de respecter un préavis de 2 mois. | BN60: CEF_C_002 | BO60: =VLOOKUP(BN60,'Axe 2 Règles de gestion'!$D$2:$F$379,3, FALSE) -> La date de la cessation de fonctions doit être postérieure ou égale à la date de début de la dernière position en cours. | BP60: CEF_C_004 | BQ60: =VLOOKUP(BP60,'Axe 2 Règles de gestion'!$D$2:$F$379,3, FALSE) -> La date de cessation de fonction doit être postérieure ou égale à la date de début du lien juridique | BR60: CEF_C_006 | BS60: =VLOOKUP(BR60,'Axe 2 Règles de gestion'!$D$2:$F$379,3, FALSE) -> La date de notification de la rupture du contrat doit être antérieure à la date de fin réelle ou prévisionnelle du lien juridique | BT60: CEF_C_007 | BU60: =VLOOKUP(BT60,'Axe 2 Règles de gestion'!$D$2:$F$379,3, FALSE) -> La date de notification de la rupture du contrat doit être renseignée | BV60: CEF_C_008 | BW60: =VLOOKUP(BV60,'Axe 2 Règles de gestion'!$D$2:$F$379,3, FALSE) -> La date du dernier jour travaillé payé doit être antérieure ou égale à la date de fin réelle ou prévisionnelle du lien juridique | BX60: CEF_C_011 | BY60: =VLOOKUP(BX60,'Axe 2 Règles de gestion'!$D$2:$F$379,3, FALSE) -> La date de début du préavis doit être postérieure à la date de début du contrat. | BZ60: CEF_C_012 | CA60: =VLOOKUP(BZ60,'Axe 2 Règles de gestion'!$D$2:$F$379,3, FALSE) -> La date de fin du préavis doit être antérieure ou égale à la date de fin réelle ou prévisionnelle du lien juridique. | CB60: CEF_C_013 | CC60: =VLOOKUP(CB60,'Axe 2 Règles de gestion'!$D$2:$F$379,3, FALSE) -> Si la date du dernier jour travaillé payé est saisie alors elle doit être antérieure ou égale à la date de cessation de fonctions. | CD60: CEF_C_027 | CE60: =VLOOKUP(CD60,'Axe 2 Règles de gestion'!$D$2:$F$379,3, FALSE) -> La date de début du préavis doit être postérieure ou égale à la date de début de l'avenant au contrat. | CF60: CEF_C_031 | CG60: =VLOOKUP(CF60,'Axe 2 Règles de gestion'!$D$2:$F$379,3, FALSE) -> Si l'agent est placé sur une position payée, alors le champ « Date du dernier jour travaillé payé » doit être saisi. | CH60: CEF_C_032 | CI60: =VLOOKUP(CH60,'Axe 2 Règles de gestion'!$D$2:$F$379,3, FALSE) -> La date de cessation de fonction doit être antérieure ou égale à la date limite de départ à la retraite | CJ60: CEF_C_033 | CK60: =VLOOKUP(CJ60,'Axe 2 Règles de gestion'!$D$2:$F$379,3, FALSE) -> Si la date de fin de préavis est saisie alors elle doit être antérieure ou égale à la date de cessation de fonction. | CN60: 2025-112
A61: 22.00.00 | B61: A | C61: 44715.67 | D61: D0006 | E61: Cessation de fonction | F61: S0042 | G61: Cessation de fonction | H61: E0344 | I61: Démission en cas de restructuration | J61: Motif cessation de fonction saisi égal à 'Démission en cas de restructuration' | K61: A_CDF_MOTCFT [Saisi] = 'MC123' | L61: T0997 | M61: Démission en cas de restructuration | N61: Création Modification | Q61: Contractuel recruté sur contrat de mission scientifique | R61: P0266 | S61: Particulier | T61: Passant | U61: 44507 | W61: CEF_C_002 ET CEF_C_004 ET CEF_C_006 ET CEF_C_007 ET CEF_C_008 ET CEF_C_011 ET CEF_C_012 ET CEF_C_013 ET CEF_C_027 ET CEF_C_031 ET CEF_C_032 ET CEF_C_033 | BN61: CEF_C_002 | BO61: =VLOOKUP(BN61,'Axe 2 Règles de gestion'!$D$2:$F$379,3, FALSE) -> La date de la cessation de fonctions doit être postérieure ou égale à la date de début de la dernière position en cours. | BP61: CEF_C_004 | BQ61: =VLOOKUP(BP61,'Axe 2 Règles de gestion'!$D$2:$F$379,3, FALSE) -> La date de cessation de fonction doit être postérieure ou égale à la date de début du lien juridique | BR61: CEF_C_006 | BS61: =VLOOKUP(BR61,'Axe 2 Règles de gestion'!$D$2:$F$379,3, FALSE) -> La date de notification de la rupture du contrat doit être antérieure à la date de fin réelle ou prévisionnelle du lien juridique | BT61: CEF_C_007 | BU61: =VLOOKUP(BT61,'Axe 2 Règles de gestion'!$D$2:$F$379,3, FALSE) -> La date de notification de la rupture du contrat doit être renseignée | BV61: CEF_C_008 | BW61: =VLOOKUP(BV61,'Axe 2 Règles de gestion'!$D$2:$F$379,3, FALSE) -> La date du dernier jour travaillé payé doit être antérieure ou égale à la date de fin réelle ou prévisionnelle du lien juridique | BX61: CEF_C_011 | BY61: =VLOOKUP(BX61,'Axe 2 Règles de gestion'!$D$2:$F$379,3, FALSE) -> La date de début du préavis doit être postérieure à la date de début du contrat. | BZ61: CEF_C_012 | CA61: =VLOOKUP(BZ61,'Axe 2 Règles de gestion'!$D$2:$F$379,3, FALSE) -> La date de fin du préavis doit être antérieure ou égale à la date de fin réelle ou prévisionnelle du lien juridique. | CB61: CEF_C_013 | CC61: =VLOOKUP(CB61,'Axe 2 Règles de gestion'!$D$2:$F$379,3, FALSE) -> Si la date du dernier jour travaillé payé est saisie alors elle doit être antérieure ou égale à la date de cessation de fonctions. | CD61: CEF_C_027 | CE61: =VLOOKUP(CD61,'Axe 2 Règles de gestion'!$D$2:$F$379,3, FALSE) -> La date de début du préavis doit être postérieure ou égale à la date de début de l'avenant au contrat. | CF61: CEF_C_031 | CG61: =VLOOKUP(CF61,'Axe 2 Règles de gestion'!$D$2:$F$379,3, FALSE) -> Si l'agent est placé sur une position payée, alors le champ « Date du dernier jour travaillé payé » doit être saisi. | CH61: CEF_C_032 | CI61: =VLOOKUP(CH61,'Axe 2 Règles de gestion'!$D$2:$F$379,3, FALSE) -> La date de cessation de fonction doit être antérieure ou égale à la date limite de départ à la retraite | CJ61: CEF_C_033 | CK61: =VLOOKUP(CJ61,'Axe 2 Règles de gestion'!$D$2:$F$379,3, FALSE) -> Si la date de fin de préavis est saisie alors elle doit être antérieure ou égale à la date de cessation de fonction.
A62: 22.00.00 | B62: A | C62: 44720.367 | D62: D0006 | E62: Cessation de fonction | F62: S0042 | G62: Cessation de fonction | H62: E0344 | I62: Démission en cas de restructuration | J62: Motif cessation de fonction saisi égal à 'Démission en cas de restructuration' | K62: A_CDF_MOTCFT [Saisi] = 'MC123' | L62: T0997 | M62: Démission en cas de restructuration | N62: Création Modification | Q62: Contractuel recruté sur contrat post doctoral | R62: P0267 | S62: Particulier | T62: Exclu | U62: 44507
A63: 22.00.00 | B63: A | C63: 44720.403 | D63: D0006 | E63: Cessation de fonction | F63: S0042 | G63: Cessation de fonction | H63: E0344 | I63: Démission en cas de restructuration | J63: Motif cessation de fonction saisi égal à 'Démission en cas de restructuration' | K63: A_CDF_MOTCFT [Saisi] = 'MC123' | L63: T0997 | M63: Démission en cas de restructuration | N63: Création Modification | Q63: Chaire professeur junior emploi donnant lieu à titularisation dans un corps de directeur de recherche | R63: P0268 | S63: Particulier | T63: Exclu | U63: 44550
A64: 22.00.00 | B64: A | C64: 44720.426 | D64: D0006 | E64: Cessation de fonction | F64: S0042 | G64: Cessation de fonction | H64: E0344 | I64: Démission en cas de restructuration | J64: Motif cessation de fonction saisi égal à 'Démission en cas de restructuration' | K64: A_CDF_MOTCFT [Saisi] = 'MC123' | L64: T0997 | M64: Démission en cas de restructuration | N64: Création Modification | Q64: Chaire professeur junior emploi donnant lieu à titularisation dans un corps de professeur | R64: P0269 | S64: Particulier | T64: Exclu | U64: 44550
A65: 23.10.00 | B65: M | C65: 45225.663 | D65: D0006 | E65: Cessation de fonction | F65: S0042 | G65: Cessation de fonction | H65: E0345 | I65: Démission pour créer ou reprendre une entreprise | J65: Motif cessation de fonction saisi égal à 'Démission pour créer ou reprendre une entreprise' | K65: A_CDF_MOTCFT [Saisi] = 'MC124' | L65: T0998 | M65: Démission pour créer ou reprendre une entreprise | N65: Création Modification | Q65: Titulaire ou magistrat | R65: P0001 | S65: Général | T65: Passant | U65: 40725 | W65: CEF_C_001 ET CEF_C_002 ET CEF_C_009 ET CEF_C_013 ET CEF_C_014 ET CEF_C_031 ET CEF_C_032 ET CEF_C_033 ET CEF_C_038 | BN65: CEF_C_001 | BO65: =VLOOKUP(BN65,'Axe 2 Règles de gestion'!$D$2:$F$379,3, FALSE) -> La date de cessation de fonctions doit être postérieure ou égale à la date d'entrée dans la FPE ou dans la carrière militaire. | BP65: CEF_C_002 | BQ65: =VLOOKUP(BP65,'Axe 2 Règles de gestion'!$D$2:$F$379,3, FALSE) -> La date de la cessation de fonctions doit être postérieure ou égale à la date de début de la dernière position en cours. | BR65: CEF_C_009 | BS65: =VLOOKUP(BR65,'Axe 2 Règles de gestion'!$D$2:$F$379,3, FALSE) -> Si les dates de début et de fin de préavis sont saisies, alors la date de fin du préavis doit être postérieure ou égale à la date de début du préavis. | BT65: CEF_C_013 | BU65: =VLOOKUP(BT65,'Axe 2 Règles de gestion'!$D$2:$F$379,3, FALSE) -> Si la date du dernier jour travaillé payé est saisie alors elle doit être antérieure ou égale à la date de cessation de fonctions. | BV65: CEF_C_014 | BW65: =VLOOKUP(BV65,'Axe 2 Règles de gestion'!$D$2:$F$379,3, FALSE) -> Si la date de début du préavis est saisie alors elle doit être postérieure ou égale à la date d'entrée dans la FPE ou dans la carrière militaire. | BX65: CEF_C_031 | BY65: =VLOOKUP(BX65,'Axe 2 Règles de gestion'!$D$2:$F$379,3, FALSE) -> Si l'agent est placé sur une position payée, alors le champ « Date du dernier jour travaillé payé » doit être saisi. | BZ65: CEF_C_032 | CA65: =VLOOKUP(BZ65,'Axe 2 Règles de gestion'!$D$2:$F$379,3, FALSE) -> La date de cessation de fonction doit être antérieure ou égale à la date limite de départ à la retraite | CB65: CEF_C_033 | CC65: =VLOOKUP(CB65,'Axe 2 Règles de gestion'!$D$2:$F$379,3, FALSE) -> Si la date de fin de préavis est saisie alors elle doit être antérieure ou égale à la date de cessation de fonction. | CD65: CEF_C_038 | CE65: =VLOOKUP(CD65,'Axe 2 Règles de gestion'!$D$2:$F$379,3, FALSE) -> Le champ " Date d'effet de la radiation des cadres ou des contrôles " doit être renseigné.
A66: 18.10.00 | B66: M | C66: 43389.372 | D66: D0006 | E66: Cessation de fonction | F66: S0042 | G66: Cessation de fonction | H66: E0345 | I66: Démission pour créer ou reprendre une entreprise | J66: Motif cessation de fonction saisi égal à 'Démission pour créer ou reprendre une entreprise' | K66: A_CDF_MOTCFT [Saisi] = 'MC124' | L66: T0998 | M66: Démission pour créer ou reprendre une entreprise | N66: Création Modification | Q66: Contractuel | R66: P0003 | S66: Général | T66: Passant | U66: 40725 | W66: CEF_C_002 ET CEF_C_004 ET CEF_C_006 ET CEF_C_007 ET CEF_C_008 ET CEF_C_011 ET CEF_C_012 ET CEF_C_013 ET CEF_C_027 ET CEF_C_031 ET CEF_C_032 ET CEF_C_033 | BN66: CEF_C_002 | BO66: =VLOOKUP(BN66,'Axe 2 Règles de gestion'!$D$2:$F$379,3, FALSE) -> La date de la cessation de fonctions doit être postérieure ou égale à la date de début de la dernière position en cours. | BP66: CEF_C_004 | BQ66: =VLOOKUP(BP66,'Axe 2 Règles de gestion'!$D$2:$F$379,3, FALSE) -> La date de cessation de fonction doit être postérieure ou égale à la date de début du lien juridique | BR66: CEF_C_006 | BS66: =VLOOKUP(BR66,'Axe 2 Règles de gestion'!$D$2:$F$379,3, FALSE) -> La date de notification de la rupture du contrat doit être antérieure à la date de fin réelle ou prévisionnelle du lien juridique | BT66: CEF_C_007 | BU66: =VLOOKUP(BT66,'Axe 2 Règles de gestion'!$D$2:$F$379,3, FALSE) -> La date de notification de la rupture du contrat doit être renseignée | BV66: CEF_C_008 | BW66: =VLOOKUP(BV66,'Axe 2 Règles de gestion'!$D$2:$F$379,3, FALSE) -> La date du dernier jour travaillé payé doit être antérieure ou égale à la date de fin réelle ou prévisionnelle du lien juridique | BX66: CEF_C_011 | BY66: =VLOOKUP(BX66,'Axe 2 Règles de gestion'!$D$2:$F$379,3, FALSE) -> La date de début du préavis doit être postérieure à la date de début du contrat. | BZ66: CEF_C_012 | CA66: =VLOOKUP(BZ66,'Axe 2 Règles de gestion'!$D$2:$F$379,3, FALSE) -> La date de fin du préavis doit être antérieure ou égale à la date de fin réelle ou prévisionnelle du lien juridique. | CB66: CEF_C_013 | CC66: =VLOOKUP(CB66,'Axe 2 Règles de gestion'!$D$2:$F$379,3, FALSE) -> Si la date du dernier jour travaillé payé est saisie alors elle doit être antérieure ou égale à la date de cessation de fonctions. | CD66: CEF_C_027 | CE66: =VLOOKUP(CD66,'Axe 2 Règles de gestion'!$D$2:$F$379,3, FALSE) -> La date de début du préavis doit être postérieure ou égale à la date de début de l'avenant au contrat. | CF66: CEF_C_031 | CG66: =VLOOKUP(CF66,'Axe 2 Règles de gestion'!$D$2:$F$379,3, FALSE) -> Si l'agent est placé sur une position payée, alors le champ « Date du dernier jour travaillé payé » doit être saisi. | CH66: CEF_C_032 | CI66: =VLOOKUP(CH66,'Axe 2 Règles de gestion'!$D$2:$F$379,3, FALSE) -> La date de cessation de fonction doit être antérieure ou égale à la date limite de départ à la retraite | CJ66: CEF_C_033 | CK66: =VLOOKUP(CJ66,'Axe 2 Règles de gestion'!$D$2:$F$379,3, FALSE) -> Si la date de fin de préavis est saisie alors elle doit être antérieure ou égale à la date de cessation de fonction.
A67: 20.10.00 | B67: M | C67: 44242.397 | D67: D0006 | E67: Cessation de fonction | F67: S0042 | G67: Cessation de fonction | H67: E0345 | I67: Démission pour créer ou reprendre une entreprise | J67: Motif cessation de fonction saisi égal à 'Démission pour créer ou reprendre une entreprise' | K67: A_CDF_MOTCFT [Saisi] = 'MC124' | L67: T0998 | M67: Démission pour créer ou reprendre une entreprise | N67: Création Modification | Q67: Stagiaire ou auditeur ou élève | R67: P0004 | S67: Général | T67: Passant | U67: 40725 | W67: CEF_I_011 ET CEF_C_001 ET CEF_C_002 ET CEF_C_009 ET CEF_C_013 ET CEF_C_014 ET CEF_C_031 ET CEF_C_032 ET CEF_C_033 | X67: CEF_I_011 | Y67: =VLOOKUP(X67,'Axe 2 Règles de gestion'!$D$2:$F$379,3, FALSE) -> La demande de démission doit être adressée 1 mois au moins avant la date prévue pour la cessation de fonctions. | BN67: CEF_C_001 | BO67: =VLOOKUP(BN67,'Axe 2 Règles de gestion'!$D$2:$F$379,3, FALSE) -> La date de cessation de fonctions doit être postérieure ou égale à la date d'entrée dans la FPE ou dans la carrière militaire. | BP67: CEF_C_002 | BQ67: =VLOOKUP(BP67,'Axe 2 Règles de gestion'!$D$2:$F$379,3, FALSE) -> La date de la cessation de fonctions doit être postérieure ou égale à la date de début de la dernière position en cours. | BR67: CEF_C_009 | BS67: =VLOOKUP(BR67,'Axe 2 Règles de gestion'!$D$2:$F$379,3, FALSE) -> Si les dates de début et de fin de préavis sont saisies, alors la date de fin du préavis doit être postérieure ou égale à la date de début du préavis. | BT67: CEF_C_013 | BU67: =VLOOKUP(BT67,'Axe 2 Règles de gestion'!$D$2:$F$379,3, FALSE) -> Si la date du dernier jour travaillé payé est saisie alors elle doit être antérieure ou égale à la date de cessation de fonctions. | BV67: CEF_C_014 | BW67: =VLOOKUP(BV67,'Axe 2 Règles de gestion'!$D$2:$F$379,3, FALSE) -> Si la date de début du préavis est saisie alors elle doit être postérieure ou égale à la date d'entrée dans la FPE ou dans la carrière militaire. | BX67: CEF_C_031 | BY67: =VLOOKUP(BX67,'Axe 2 Règles de gestion'!$D$2:$F$379,3, FALSE) -> Si l'agent est placé sur une position payée, alors le champ « Date du dernier jour travaillé payé » doit être saisi. | BZ67: CEF_C_032 | CA67: =VLOOKUP(BZ67,'Axe 2 Règles de gestion'!$D$2:$F$379,3, FALSE) -> La date de cessation de fonction doit être antérieure ou égale à la date limite de départ à la retraite | CB67: CEF_C_033 | CC67: =VLOOKUP(CB67,'Axe 2 Règles de gestion'!$D$2:$F$379,3, FALSE) -> Si la date de fin de préavis est saisie alors elle doit être antérieure ou égale à la date de cessation de fonction.
A68: 17.10.00 | B68: A | C68: 43189.5 | D68: D0006 | E68: Cessation de fonction | F68: S0042 | G68: Cessation de fonction | H68: E0345 | I68: Démission pour créer ou reprendre une entreprise | J68: Motif cessation de fonction saisi égal à 'Démission pour créer ou reprendre une entreprise' | K68: A_CDF_MOTCFT [Saisi] = 'MC124' | L68: T0998 | M68: Démission pour créer ou reprendre une entreprise | N68: Création Modification | Q68: Ouvrier d'état | R68: P0005 | S68: Général | T68: Exclu | U68: 40725
A69: 17.10.00 | B69: A | C69: 43152.5 | D69: D0006 | E69: Cessation de fonction | F69: S0042 | G69: Cessation de fonction | H69: E0345 | I69: Démission pour créer ou reprendre une entreprise | J69: Motif cessation de fonction saisi égal à 'Démission pour créer ou reprendre une entreprise' | K69: A_CDF_MOTCFT [Saisi] = 'MC124' | L69: T0998 | M69: Démission pour créer ou reprendre une entreprise | N69: Création Modification | Q69: Magistrat de l'ordre judiciaire | R69: P0007 | S69: Particulier | T69: Exclu | U69: 40725
A70: 17.10.00 | B70: A | C70: 43152.5 | D70: D0006 | E70: Cessation de fonction | F70: S0042 | G70: Cessation de fonction | H70: E0345 | I70: Démission pour créer ou reprendre une entreprise | J70: Motif cessation de fonction saisi égal à 'Démission pour créer ou reprendre une entreprise' | K70: A_CDF_MOTCFT [Saisi] = 'MC124' | L70: T0998 | M70: Démission pour créer ou reprendre une entreprise | N70: Création Modification | Q70: Auditeur de justice | R70: P0009 | S70: Particulier | T70: Exclu | U70: 40725
A71: 17.10.00 | B71: A | C71: 43152.5 | D71: D0006 | E71: Cessation de fonction | F71: S0042 | G71: Cessation de fonction | H71: E0345 | I71: Démission pour créer ou reprendre une entreprise | J71: Motif cessation de fonction saisi égal à 'Démission pour créer ou reprendre une entreprise' | K71: A_CDF_MOTCFT [Saisi] = 'MC124' | L71: T0998 | M71: Démission pour créer ou reprendre une entreprise | N71: Création Modification | Q71: Personnel civil payé à l'acte ou à la tâche | R71: P0054 | S71: Particulier | T71: Exclu | U71: 40725
A72: 19.00.00 | B72: A | C72: 43636.588 | D72: D0006 | E72: Cessation de fonction | F72: S0042 | G72: Cessation de fonction | H72: E0345 | I72: Démission pour créer ou reprendre une entreprise | J72: Motif cessation de fonction saisi égal à 'Démission pour créer ou reprendre une entreprise' | K72: A_CDF_MOTCFT [Saisi] = 'MC124' | L72: T0998 | M72: Démission pour créer ou reprendre une entreprise | N72: Création Modification | Q72: Ouvrier de la défense réglementé affilié | R72: P0093 | S72: Particulier | T72: Passant | U72: 40725 | W72: CEF_I_107 ET CEF_C_002 ET CEF_C_004 ET CEF_C_006 ET CEF_C_007 ET CEF_C_008 ET CEF_C_011 ET CEF_C_012 ET CEF_C_013 ET CEF_C_027 ET CEF_C_031 ET CEF_C_032 ET CEF_C_033 | X72: CEF_I_107 | Y72: =VLOOKUP(X72,'Axe 2 Règles de gestion'!$D$2:$F$379,3, FALSE) -> Le préavis est d'un mois si l'agent a une ancienneté au moins égale à 6 mois et de 8 jours si l'ancienneté est inférieure à 6 mois. | BN72: CEF_C_002 | BO72: =VLOOKUP(BN72,'Axe 2 Règles de gestion'!$D$2:$F$379,3, FALSE) -> La date de la cessation de fonctions doit être postérieure ou égale à la date de début de la dernière position en cours. | BP72: CEF_C_004 | BQ72: =VLOOKUP(BP72,'Axe 2 Règles de gestion'!$D$2:$F$379,3, FALSE) -> La date de cessation de fonction doit être postérieure ou égale à la date de début du lien juridique | BR72: CEF_C_006 | BS72: =VLOOKUP(BR72,'Axe 2 Règles de gestion'!$D$2:$F$379,3, FALSE) -> La date de notification de la rupture du contrat doit être antérieure à la date de fin réelle ou prévisionnelle du lien juridique | BT72: CEF_C_007 | BU72: =VLOOKUP(BT72,'Axe 2 Règles de gestion'!$D$2:$F$379,3, FALSE) -> La date de notification de la rupture du contrat doit être renseignée | BV72: CEF_C_008 | BW72: =VLOOKUP(BV72,'Axe 2 Règles de gestion'!$D$2:$F$379,3, FALSE) -> La date du dernier jour travaillé payé doit être antérieure ou égale à la date de fin réelle ou prévisionnelle du lien juridique | BX72: CEF_C_011 | BY72: =VLOOKUP(BX72,'Axe 2 Règles de gestion'!$D$2:$F$379,3, FALSE) -> La date de début du préavis doit être postérieure à la date de début du contrat. | BZ72: CEF_C_012 | CA72: =VLOOKUP(BZ72,'Axe 2 Règles de gestion'!$D$2:$F$379,3, FALSE) -> La date de fin du préavis doit être antérieure ou égale à la date de fin réelle ou prévisionnelle du lien juridique. | CB72: CEF_C_013 | CC72: =VLOOKUP(CB72,'Axe 2 Règles de gestion'!$D$2:$F$379,3, FALSE) -> Si la date du dernier jour travaillé payé est saisie alors elle doit être antérieure ou égale à la date de cessation de fonctions. | CD72: CEF_C_027 | CE72: =VLOOKUP(CD72,'Axe 2 Règles de gestion'!$D$2:$F$379,3, FALSE) -> La date de début du préavis doit être postérieure ou égale à la date de début de l'avenant au contrat. | CF72: CEF_C_031 | CG72: =VLOOKUP(CF72,'Axe 2 Règles de gestion'!$D$2:$F$379,3, FALSE) -> Si l'agent est placé sur une position payée, alors le champ « Date du dernier jour travaillé payé » doit être saisi. | CH72: CEF_C_032 | CI72: =VLOOKUP(CH72,'Axe 2 Règles de gestion'!$D$2:$F$379,3, FALSE) -> La date de cessation de fonction doit être antérieure ou égale à la date limite de départ à la retraite | CJ72: CEF_C_033 | CK72: =VLOOKUP(CJ72,'Axe 2 Règles de gestion'!$D$2:$F$379,3, FALSE) -> Si la date de fin de préavis est saisie alors elle doit être antérieure ou égale à la date de cessation de fonction.
A73: 25.10.00 | B73: M | C73: 45974.403 | D73: D0006 | E73: Cessation de fonction | F73: S0042 | G73: Cessation de fonction | H73: E0345 | I73: Démission pour créer ou reprendre une entreprise | J73: Motif cessation de fonction saisi égal à 'Démission pour créer ou reprendre une entreprise' | K73: A_CDF_MOTCFT [Saisi] = 'MC124' | L73: T0998 | M73: Démission pour créer ou reprendre une entreprise | N73: Création Modification | Q73: Ouvrier des parcs et ateliers ou assimilé confirmé | R73: P0096 | S73: Particulier | T73: Passant | U73: 40725 | V73: 45900 | W73: CEF_D_117 ET CEF_C_002 ET CEF_C_004 ET CEF_C_006 ET CEF_C_007 ET CEF_C_008 ET CEF_C_011 ET CEF_C_012 ET CEF_C_013 ET CEF_C_027 ET CEF_C_031 ET CEF_C_032 ET CEF_C_033 | BH73: CEF_D_117 | BI73: =VLOOKUP(BH73,'Axe 2 Règles de gestion'!$D$2:$F$379,3, FALSE) -> En cas de démission, le préavis est au minimum de un mois. | BN73: CEF_C_002 | BO73: =VLOOKUP(BN73,'Axe 2 Règles de gestion'!$D$2:$F$379,3, FALSE) -> La date de la cessation de fonctions doit être postérieure ou égale à la date de début de la dernière position en cours. | BP73: CEF_C_004 | BQ73: =VLOOKUP(BP73,'Axe 2 Règles de gestion'!$D$2:$F$379,3, FALSE) -> La date de cessation de fonction doit être postérieure ou égale à la date de début du lien juridique | BR73: CEF_C_006 | BS73: =VLOOKUP(BR73,'Axe 2 Règles de gestion'!$D$2:$F$379,3, FALSE) -> La date de notification de la rupture du contrat doit être antérieure à la date de fin réelle ou prévisionnelle du lien juridique | BT73: CEF_C_007 | BU73: =VLOOKUP(BT73,'Axe 2 Règles de gestion'!$D$2:$F$379,3, FALSE) -> La date de notification de la rupture du contrat doit être renseignée | BV73: CEF_C_008 | BW73: =VLOOKUP(BV73,'Axe 2 Règles de gestion'!$D$2:$F$379,3, FALSE) -> La date du dernier jour travaillé payé doit être antérieure ou égale à la date de fin réelle ou prévisionnelle du lien juridique | BX73: CEF_C_011 | BY73: =VLOOKUP(BX73,'Axe 2 Règles de gestion'!$D$2:$F$379,3, FALSE) -> La date de début du préavis doit être postérieure à la date de début du contrat. | BZ73: CEF_C_012 | CA73: =VLOOKUP(BZ73,'Axe 2 Règles de gestion'!$D$2:$F$379,3, FALSE) -> La date de fin du préavis doit être antérieure ou égale à la date de fin réelle ou prévisionnelle du lien juridique. | CB73: CEF_C_013 | CC73: =VLOOKUP(CB73,'Axe 2 Règles de gestion'!$D$2:$F$379,3, FALSE) -> Si la date du dernier jour travaillé payé est saisie alors elle doit être antérieure ou égale à la date de cessation de fonctions. | CD73: CEF_C_027 | CE73: =VLOOKUP(CD73,'Axe 2 Règles de gestion'!$D$2:$F$379,3, FALSE) -> La date de début du préavis doit être postérieure ou égale à la date de début de l'avenant au contrat. | CF73: CEF_C_031 | CG73: =VLOOKUP(CF73,'Axe 2 Règles de gestion'!$D$2:$F$379,3, FALSE) -> Si l'agent est placé sur une position payée, alors le champ « Date du dernier jour travaillé payé » doit être saisi. | CH73: CEF_C_032 | CI73: =VLOOKUP(CH73,'Axe 2 Règles de gestion'!$D$2:$F$379,3, FALSE) -> La date de cessation de fonction doit être antérieure ou égale à la date limite de départ à la retraite | CJ73: CEF_C_033 | CK73: =VLOOKUP(CJ73,'Axe 2 Règles de gestion'!$D$2:$F$379,3, FALSE) -> Si la date de fin de préavis est saisie alors elle doit être antérieure ou égale à la date de cessation de fonction. | CN73: 2025-112
A74: 18.10.00 | B74: M | C74: 43152.5 | D74: D0006 | E74: Cessation de fonction | F74: S0042 | G74: Cessation de fonction | H74: E0346 | I74: Démission pour mener un projet personnel | J74: Motif cessation de fonction saisi égal à 'Démission pour mener un projet personnel' | K74: A_CDF_MOTCFT [Saisi] = 'MC128' | L74: T0999 | M74: Démission pour mener un projet personnel | N74: Création Modification | Q74: Titulaire ou magistrat | R74: P0001 | S74: Général | T74: Passant | U74: 40725 | V74: 41781 | W74: CEF_C_001 ET CEF_C_002 ET CEF_C_009 ET CEF_C_013 ET CEF_C_014 ET CEF_C_031 ET CEF_C_032 ET CEF_C_033 | BN74: CEF_C_001 | BO74: =VLOOKUP(BN74,'Axe 2 Règles de gestion'!$D$2:$F$379,3, FALSE) -> La date de cessation de fonctions doit être postérieure ou égale à la date d'entrée dans la FPE ou dans la carrière militaire. | BP74: CEF_C_002 | BQ74: =VLOOKUP(BP74,'Axe 2 Règles de gestion'!$D$2:$F$379,3, FALSE) -> La date de la cessation de fonctions doit être postérieure ou égale à la date de début de la dernière position en cours. | BR74: CEF_C_009 | BS74: =VLOOKUP(BR74,'Axe 2 Règles de gestion'!$D$2:$F$379,3, FALSE) -> Si les dates de début et de fin de préavis sont saisies, alors la date de fin du préavis doit être postérieure ou égale à la date de début du préavis. | BT74: CEF_C_013 | BU74: =VLOOKUP(BT74,'Axe 2 Règles de gestion'!$D$2:$F$379,3, FALSE) -> Si la date du dernier jour travaillé payé est saisie alors elle doit être antérieure ou égale à la date de cessation de fonctions. | BV74: CEF_C_014 | BW74: =VLOOKUP(BV74,'Axe 2 Règles de gestion'!$D$2:$F$379,3, FALSE) -> Si la date de début du préavis est saisie alors elle doit être postérieure ou égale à la date d'entrée dans la FPE ou dans la carrière militaire. | BX74: CEF_C_031 | BY74: =VLOOKUP(BX74,'Axe 2 Règles de gestion'!$D$2:$F$379,3, FALSE) -> Si l'agent est placé sur une position payée, alors le champ « Date du dernier jour travaillé payé » doit être saisi. | BZ74: CEF_C_032 | CA74: =VLOOKUP(BZ74,'Axe 2 Règles de gestion'!$D$2:$F$379,3, FALSE) -> La date de cessation de fonction doit être antérieure ou égale à la date limite de départ à la retraite | CB74: CEF_C_033 | CC74: =VLOOKUP(CB74,'Axe 2 Règles de gestion'!$D$2:$F$379,3, FALSE) -> Si la date de fin de préavis est saisie alors elle doit être antérieure ou égale à la date de cessation de fonction.
A75: 18.10.00 | B75: M | C75: 43152.5 | D75: D0006 | E75: Cessation de fonction | F75: S0042 | G75: Cessation de fonction | H75: E0346 | I75: Démission pour mener un projet personnel | J75: Motif cessation de fonction saisi égal à 'Démission pour mener un projet personnel' | K75: A_CDF_MOTCFT [Saisi] = 'MC128' | L75: T0999 | M75: Démission pour mener un projet personnel | N75: Création Modification | Q75: Contractuel | R75: P0003 | S75: Général | T75: Passant | U75: 40725 | V75: 41780 | W75: CEF_C_002 ET CEF_C_004 ET CEF_C_006 ET CEF_C_007 ET CEF_C_008 ET CEF_C_011 ET CEF_C_012 ET CEF_C_013 ET CEF_C_027 ET CEF_C_031 ET CEF_C_032 ET CEF_C_033 | BN75: CEF_C_002 | BO75: =VLOOKUP(BN75,'Axe 2 Règles de gestion'!$D$2:$F$379,3, FALSE) -> La date de la cessation de fonctions doit être postérieure ou égale à la date de début de la dernière position en cours. | BP75: CEF_C_004 | BQ75: =VLOOKUP(BP75,'Axe 2 Règles de gestion'!$D$2:$F$379,3, FALSE) -> La date de cessation de fonction doit être postérieure ou égale à la date de début du lien juridique | BR75: CEF_C_006 | BS75: =VLOOKUP(BR75,'Axe 2 Règles de gestion'!$D$2:$F$379,3, FALSE) -> La date de notification de la rupture du contrat doit être antérieure à la date de fin réelle ou prévisionnelle du lien juridique | BT75: CEF_C_007 | BU75: =VLOOKUP(BT75,'Axe 2 Règles de gestion'!$D$2:$F$379,3, FALSE) -> La date de notification de la rupture du contrat doit être renseignée | BV75: CEF_C_008 | BW75: =VLOOKUP(BV75,'Axe 2 Règles de gestion'!$D$2:$F$379,3, FALSE) -> La date du dernier jour travaillé payé doit être antérieure ou égale à la date de fin réelle ou prévisionnelle du lien juridique | BX75: CEF_C_011 | BY75: =VLOOKUP(BX75,'Axe 2 Règles de gestion'!$D$2:$F$379,3, FALSE) -> La date de début du préavis doit être postérieure à la date de début du contrat. | BZ75: CEF_C_012 | CA75: =VLOOKUP(BZ75,'Axe 2 Règles de gestion'!$D$2:$F$379,3, FALSE) -> La date de fin du préavis doit être antérieure ou égale à la date de fin réelle ou prévisionnelle du lien juridique. | CB75: CEF_C_013 | CC75: =VLOOKUP(CB75,'Axe 2 Règles de gestion'!$D$2:$F$379,3, FALSE) -> Si la date du dernier jour travaillé payé est saisie alors elle doit être antérieure ou égale à la date de cessation de fonctions. | CD75: CEF_C_027 | CE75: =VLOOKUP(CD75,'Axe 2 Règles de gestion'!$D$2:$F$379,3, FALSE) -> La date de début du préavis doit être postérieure ou égale à la date de début de l'avenant au contrat. | CF75: CEF_C_031 | CG75: =VLOOKUP(CF75,'Axe 2 Règles de gestion'!$D$2:$F$379,3, FALSE) -> Si l'agent est placé sur une position payée, alors le champ « Date du dernier jour travaillé payé » doit être saisi. | CH75: CEF_C_032 | CI75: =VLOOKUP(CH75,'Axe 2 Règles de gestion'!$D$2:$F$379,3, FALSE) -> La date de cessation de fonction doit être antérieure ou égale à la date limite de départ à la retraite | CJ75: CEF_C_033 | CK75: =VLOOKUP(CJ75,'Axe 2 Règles de gestion'!$D$2:$F$379,3, FALSE) -> Si la date de fin de préavis est saisie alors elle doit être antérieure ou égale à la date de cessation de fonction.
A76: 18.10.00 | B76: M | C76: 43152.5 | D76: D0006 | E76: Cessation de fonction | F76: S0042 | G76: Cessation de fonction | H76: E0346 | I76: Démission pour mener un projet personnel | J76: Motif cessation de fonction saisi égal à 'Démission pour mener un projet personnel' | K76: A_CDF_MOTCFT [Saisi] = 'MC128' | L76: T0999 | M76: Démission pour mener un projet personnel | N76: Création Modification | Q76: Stagiaire ou auditeur ou élève | R76: P0004 | S76: Général | T76: Passant | U76: 40725 | V76: 41781 | W76: CEF_C_001 ET CEF_C_002 ET CEF_C_009 ET CEF_C_013 ET CEF_C_014 ET CEF_C_031 ET CEF_C_032 ET CEF_C_033 | BN76: CEF_C_001 | BO76: =VLOOKUP(BN76,'Axe 2 Règles de gestion'!$D$2:$F$379,3, FALSE) -> La date de cessation de fonctions doit être postérieure ou égale à la date d'entrée dans la FPE ou dans la carrière militaire. | BP76: CEF_C_002 | BQ76: =VLOOKUP(BP76,'Axe 2 Règles de gestion'!$D$2:$F$379,3, FALSE) -> La date de la cessation de fonctions doit être postérieure ou égale à la date de début de la dernière position en cours. | BR76: CEF_C_009 | BS76: =VLOOKUP(BR76,'Axe 2 Règles de gestion'!$D$2:$F$379,3, FALSE) -> Si les dates de début et de fin de préavis sont saisies, alors la date de fin du préavis doit être postérieure ou égale à la date de début du préavis. | BT76: CEF_C_013 | BU76: =VLOOKUP(BT76,'Axe 2 Règles de gestion'!$D$2:$F$379,3, FALSE) -> Si la date du dernier jour travaillé payé est saisie alors elle doit être antérieure ou égale à la date de cessation de fonctions. | BV76: CEF_C_014 | BW76: =VLOOKUP(BV76,'Axe 2 Règles de gestion'!$D$2:$F$379,3, FALSE) -> Si la date de début du préavis est saisie alors elle doit être postérieure ou égale à la date d'entrée dans la FPE ou dans la carrière militaire. | BX76: CEF_C_031 | BY76: =VLOOKUP(BX76,'Axe 2 Règles de gestion'!$D$2:$F$379,3, FALSE) -> Si l'agent est placé sur une position payée, alors le champ « Date du dernier jour travaillé payé » doit être saisi. | BZ76: CEF_C_032 | CA76: =VLOOKUP(BZ76,'Axe 2 Règles de gestion'!$D$2:$F$379,3, FALSE) -> La date de cessation de fonction doit être antérieure ou égale à la date limite de départ à la retraite | CB76: CEF_C_033 | CC76: =VLOOKUP(CB76,'Axe 2 Règles de gestion'!$D$2:$F$379,3, FALSE) -> Si la date de fin de préavis est saisie alors elle doit être antérieure ou égale à la date de cessation de fonction.
A77: 17.10.00 | B77: A | C77: 43189.5 | D77: D0006 | E77: Cessation de fonction | F77: S0042 | G77: Cessation de fonction | H77: E0346 | I77: Démission pour mener un projet personnel | J77: Motif cessation de fonction saisi égal à 'Démission pour mener un projet personnel' | K77: A_CDF_MOTCFT [Saisi] = 'MC128' | L77: T0999 | M77: Démission pour mener un projet personnel | N77: Création Modification | Q77: Ouvrier d'état | R77: P0005 | S77: Général | T77: Exclu | U77: 40725 | V77: 41781
A78: 17.10.00 | B78: A | C78: 43152.5 | D78: D0006 | E78: Cessation de fonction | F78: S0042 | G78: Cessation de fonction | H78: E0346 | I78: Démission pour mener un projet personnel | J78: Motif cessation de fonction saisi égal à 'Démission pour mener un projet personnel' | K78: A_CDF_MOTCFT [Saisi] = 'MC128' | L78: T0999 | M78: Démission pour mener un projet personnel | N78: Création Modification | Q78: Auditeur de justice | R78: P0009 | S78: Particulier | T78: Exclu | U78: 40725 | V78: 41781
A79: 17.10.00 | B79: A | C79: 43152.5 | D79: D0006 | E79: Cessation de fonction | F79: S0042 | G79: Cessation de fonction | H79: E0346 | I79: Démission pour mener un projet personnel | J79: Motif cessation de fonction saisi égal à 'Démission pour mener un projet personnel' | K79: A_CDF_MOTCFT [Saisi] = 'MC128' | L79: T0999 | M79: Démission pour mener un projet personnel | N79: Création Modification | Q79: Personnel civil payé à l'acte ou à la tâche | R79: P0054 | S79: Particulier | T79: Exclu | U79: 40725 | V79: 41781
A80: 18.10.00 | B80: M | C80: 43189.5 | D80: D0006 | E80: Cessation de fonction | F80: S0042 | G80: Cessation de fonction | H80: E0346 | I80: Démission pour mener un projet personnel | J80: Motif cessation de fonction saisi égal à 'Démission pour mener un projet personnel' | K80: A_CDF_MOTCFT [Saisi] = 'MC128' | L80: T0999 | M80: Démission pour mener un projet personnel | N80: Création Modification | Q80: Ouvrier des parcs et ateliers ou assimilé confirmé | R80: P0096 | S80: Particulier | T80: Passant | U80: 40725 | V80: 41781 | W80: CEF_D_117 ET CEF_C_002 ET CEF_C_004 ET CEF_C_006 ET CEF_C_007 ET CEF_C_008 ET CEF_C_011 ET CEF_C_012 ET CEF_C_013 ET CEF_C_027 ET CEF_C_031 ET CEF_C_032 ET CEF_C_033 | BH80: CEF_D_117 | BI80: =VLOOKUP(BH80,'Axe 2 Règles de gestion'!$D$2:$F$379,3, FALSE) -> En cas de démission, le préavis est au minimum de un mois. | BN80: CEF_C_002 | BO80: =VLOOKUP(BN80,'Axe 2 Règles de gestion'!$D$2:$F$379,3, FALSE) -> La date de la cessation de fonctions doit être postérieure ou égale à la date de début de la dernière position en cours. | BP80: CEF_C_004 | BQ80: =VLOOKUP(BP80,'Axe 2 Règles de gestion'!$D$2:$F$379,3, FALSE) -> La date de cessation de fonction doit être postérieure ou égale à la date de début du lien juridique | BR80: CEF_C_006 | BS80: =VLOOKUP(BR80,'Axe 2 Règles de gestion'!$D$2:$F$379,3, FALSE) -> La date de notification de la rupture du contrat doit être antérieure à la date de fin réelle ou prévisionnelle du lien juridique | BT80: CEF_C_007 | BU80: =VLOOKUP(BT80,'Axe 2 Règles de gestion'!$D$2:$F$379,3, FALSE) -> La date de notification de la rupture du contrat doit être renseignée | BV80: CEF_C_008 | BW80: =VLOOKUP(BV80,'Axe 2 Règles de gestion'!$D$2:$F$379,3, FALSE) -> La date du dernier jour travaillé payé doit être antérieure ou égale à la date de fin réelle ou prévisionnelle du lien juridique | BX80: CEF_C_011 | BY80: =VLOOKUP(BX80,'Axe 2 Règles de gestion'!$D$2:$F$379,3, FALSE) -> La date de début du préavis doit être postérieure à la date de début du contrat. | BZ80: CEF_C_012 | CA80: =VLOOKUP(BZ80,'Axe 2 Règles de gestion'!$D$2:$F$379,3, FALSE) -> La date de fin du préavis doit être antérieure ou égale à la date de fin réelle ou prévisionnelle du lien juridique. | CB80: CEF_C_013 | CC80: =VLOOKUP(CB80,'Axe 2 Règles de gestion'!$D$2:$F$379,3, FALSE) -> Si la date du dernier jour travaillé payé est saisie alors elle doit être antérieure ou égale à la date de cessation de fonctions. | CD80: CEF_C_027 | CE80: =VLOOKUP(CD80,'Axe 2 Règles de gestion'!$D$2:$F$379,3, FALSE) -> La date de début du préavis doit être postérieure ou égale à la date de début de l'avenant au contrat. | CF80: CEF_C_031 | CG80: =VLOOKUP(CF80,'Axe 2 Règles de gestion'!$D$2:$F$379,3, FALSE) -> Si l'agent est placé sur une position payée, alors le champ « Date du dernier jour travaillé payé » doit être saisi. | CH80: CEF_C_032 | CI80: =VLOOKUP(CH80,'Axe 2 Règles de gestion'!$D$2:$F$379,3, FALSE) -> La date de cessation de fonction doit être antérieure ou égale à la date limite de départ à la retraite | CJ80: CEF_C_033 | CK80: =VLOOKUP(CJ80,'Axe 2 Règles de gestion'!$D$2:$F$379,3, FALSE) -> Si la date de fin de préavis est saisie alors elle doit être antérieure ou égale à la date de cessation de fonction.
A81: 23.10.00 | B81: M | C81: 45225.665 | D81: D0006 | E81: Cessation de fonction | F81: S0042 | G81: Cessation de fonction | H81: E0348 | I81: Licenciement suite à abandon de poste | J81: Motif cessation de fonction saisi égal à 'Licenciement suite à abandon de poste' | K81: A_CDF_MOTCFT [Saisi] = 'MC139' | L81: T1001 | M81: Licenciement suite à abandon de poste | N81: Création Modification | Q81: Titulaire ou magistrat | R81: P0001 | S81: Général | T81: Passant | U81: 40725 | W81: CEF_I_017 ET CEF_C_001 ET CEF_C_002 ET CEF_C_009 ET CEF_C_013 ET CEF_C_014 ET CEF_C_031 ET CEF_C_032 ET CEF_C_033 ET CEF_C_038 | X81: CEF_I_017 | Y81: =VLOOKUP(X81,'Axe 2 Règles de gestion'!$D$2:$F$379,3, FALSE) -> La radiation des cadres peut intervenir suite à abandon de poste après refus de déférer à une mise en demeure par laquelle il a été invité à fournir des explications et informé des mesures auxquelles il s'expose s'il ne reprend pas ses fonctions. | BN81: CEF_C_001 | BO81: =VLOOKUP(BN81,'Axe 2 Règles de gestion'!$D$2:$F$379,3, FALSE) -> La date de cessation de fonctions doit être postérieure ou égale à la date d'entrée dans la FPE ou dans la carrière militaire. | BP81: CEF_C_002 | BQ81: =VLOOKUP(BP81,'Axe 2 Règles de gestion'!$D$2:$F$379,3, FALSE) -> La date de la cessation de fonctions doit être postérieure ou égale à la date de début de la dernière position en cours. | BR81: CEF_C_009 | BS81: =VLOOKUP(BR81,'Axe 2 Règles de gestion'!$D$2:$F$379,3, FALSE) -> Si les dates de début et de fin de préavis sont saisies, alors la date de fin du préavis doit être postérieure ou égale à la date de début du préavis. | BT81: CEF_C_013 | BU81: =VLOOKUP(BT81,'Axe 2 Règles de gestion'!$D$2:$F$379,3, FALSE) -> Si la date du dernier jour travaillé payé est saisie alors elle doit être antérieure ou égale à la date de cessation de fonctions. | BV81: CEF_C_014 | BW81: =VLOOKUP(BV81,'Axe 2 Règles de gestion'!$D$2:$F$379,3, FALSE) -> Si la date de début du préavis est saisie alors elle doit être postérieure ou égale à la date d'entrée dans la FPE ou dans la carrière militaire. | BX81: CEF_C_031 | BY81: =VLOOKUP(BX81,'Axe 2 Règles de gestion'!$D$2:$F$379,3, FALSE) -> Si l'agent est placé sur une position payée, alors le champ « Date du dernier jour travaillé payé » doit être saisi. | BZ81: CEF_C_032 | CA81: =VLOOKUP(BZ81,'Axe 2 Règles de gestion'!$D$2:$F$379,3, FALSE) -> La date de cessation de fonction doit être antérieure ou égale à la date limite de départ à la retraite | CB81: CEF_C_033 | CC81: =VLOOKUP(CB81,'Axe 2 Règles de gestion'!$D$2:$F$379,3, FALSE) -> Si la date de fin de préavis est saisie alors elle doit être antérieure ou égale à la date de cessation de fonction. | CD81: CEF_C_038 | CE81: =VLOOKUP(CD81,'Axe 2 Règles de gestion'!$D$2:$F$379,3, FALSE) -> Le champ " Date d'effet de la radiation des cadres ou des contrôles " doit être renseigné.
A82: 22.10.00 | B82: M | C82: 44837.6 | D82: D0006 | E82: Cessation de fonction | F82: S0042 | G82: Cessation de fonction | H82: E0348 | I82: Licenciement suite à abandon de poste | J82: Motif cessation de fonction saisi égal à 'Licenciement suite à abandon de poste' | K82: A_CDF_MOTCFT [Saisi] = 'MC139' | L82: T1001 | M82: Licenciement suite à abandon de poste | N82: Création Modification | Q82: Contractuel | R82: P0003 | S82: Général | T82: Passant | U82: 40725 | V82: 44677 | W82: CEF_I_024 ET CEF_I_028 ET CEF_I_030 ET CEF_I_031 ET CEF_I_032 ET CEF_I_033 ET CEF_I_034 ET CEF_C_002 ET CEF_C_004 ET CEF_C_008 ET CEF_C_011 ET CEF_C_012 ET CEF_C_013 ET CEF_C_027 ET CEF_C_031 ET CEF_C_032 ET CEF_C_033 | X82: CEF_I_024 | Y82: =VLOOKUP(X82,'Axe 2 Règles de gestion'!$D$2:$F$379,3, FALSE) -> Le licenciement intervient pour abandon de poste après refus de déférer à une mise en demeure par laquelle l'agent a été invité à fournir des explications et informé des mesures auxquelles il s'expose s'il ne reprend pas ses fonctions. | Z82: CEF_I_028 | AA82: =VLOOKUP(Z82,'Axe 2 Règles de gestion'!$D$2:$F$379,3, FALSE) -> L'agent recruté pour une durée déterminée ou indéterminée licencié avant le terme de son contrat, a droit à un préavis de 8 jours s'il a moins de 6 mois de service, 1 mois s'il a entre 6 mois et 2 ans de service, 2 mois s'il a au moins 2 ans de service. | AB82: CEF_I_030 | AC82: =VLOOKUP(AB82,'Axe 2 Règles de gestion'!$D$2:$F$379,3, FALSE) -> Le licenciement ne peut intervenir qu'à l'issue d'un entretien préalable. La convocation à l'entretien préalable est effectuée par lettre recommandée ou par lettre remise en main propre contre décharge. Cette lettre indique l'objet de la convocation. | AD82: CEF_I_031 | AE82: =VLOOKUP(AD82,'Axe 2 Règles de gestion'!$D$2:$F$379,3, FALSE) -> Au cours de l'entretien préalable, l'administration indique à l'agent les motifs du licenciement et le cas échéant le délai pendant lequel il doit présenter sa demande écrite de reclassement ainsi que les conditions de présentation des offres de reclassement. | AF82: CEF_I_032 | AG82: =VLOOKUP(AF82,'Axe 2 Règles de gestion'!$D$2:$F$379,3, FALSE) -> L'administration notifie sa décision de licenciement à l'agent par lettre recommandée avec AR ou remise en main propre contre décharge. La lettre précise le(s) motif(s) ainsi que la date compte tenu des congés annuels restant et de la durée du préavis. | AH82: CEF_I_033 | AI82: =VLOOKUP(AH82,'Axe 2 Règles de gestion'!$D$2:$F$379,3, FALSE) -> Aucun licenciement ne peut être prononcé lorsque l'agent se trouve en état de grossesse médicalement constaté, en congé de maternité, de paternité ou d'adoption, ou pendant une période de 4 semaines suivant l'expiration d'un de ces congés. | AJ82: CEF_I_034 | AK82: =VLOOKUP(AJ82,'Axe 2 Règles de gestion'!$D$2:$F$379,3, FALSE) -> L'avis de licenciement avant la constatation médicale de grossesse ou dans les 15 jours précédant l'arrivée d'un enfant en vue de son adoption peut être annulée si dans les 15 jours de cet avis l'agent donne un justificatif médical ou d'adoption. | BN82: CEF_C_002 | BO82: =VLOOKUP(BN82,'Axe 2 Règles de gestion'!$D$2:$F$379,3, FALSE) -> La date de la cessation de fonctions doit être postérieure ou égale à la date de début de la dernière position en cours. | BP82: CEF_C_004 | BQ82: =VLOOKUP(BP82,'Axe 2 Règles de gestion'!$D$2:$F$379,3, FALSE) -> La date de cessation de fonction doit être postérieure ou égale à la date de début du lien juridique | BR82: CEF_C_008 | BS82: =VLOOKUP(BR82,'Axe 2 Règles de gestion'!$D$2:$F$379,3, FALSE) -> La date du dernier jour travaillé payé doit être antérieure ou égale à la date de fin réelle ou prévisionnelle du lien juridique | BT82: CEF_C_011 | BU82: =VLOOKUP(BT82,'Axe 2 Règles de gestion'!$D$2:$F$379,3, FALSE) -> La date de début du préavis doit être postérieure à la date de début du contrat. | BV82: CEF_C_012 | BW82: =VLOOKUP(BV82,'Axe 2 Règles de gestion'!$D$2:$F$379,3, FALSE) -> La date de fin du préavis doit être antérieure ou égale à la date de fin réelle ou prévisionnelle du lien juridique. | BX82: CEF_C_013 | BY82: =VLOOKUP(BX82,'Axe 2 Règles de gestion'!$D$2:$F$379,3, FALSE) -> Si la date du dernier jour travaillé payé est saisie alors elle doit être antérieure ou égale à la date de cessation de fonctions. | BZ82: CEF_C_027 | CA82: =VLOOKUP(BZ82,'Axe 2 Règles de gestion'!$D$2:$F$379,3, FALSE) -> La date de début du préavis doit être postérieure ou égale à la date de début de l'avenant au contrat. | CB82: CEF_C_031 | CC82: =VLOOKUP(CB82,'Axe 2 Règles de gestion'!$D$2:$F$379,3, FALSE) -> Si l'agent est placé sur une position payée, alors le champ « Date du dernier jour travaillé payé » doit être saisi. | CD82: CEF_C_032 | CE82: =VLOOKUP(CD82,'Axe 2 Règles de gestion'!$D$2:$F$379,3, FALSE) -> La date de cessation de fonction doit être antérieure ou égale à la date limite de départ à la retraite | CF82: CEF_C_033 | CG82: =VLOOKUP(CF82,'Axe 2 Règles de gestion'!$D$2:$F$379,3, FALSE) -> Si la date de fin de préavis est saisie alors elle doit être antérieure ou égale à la date de cessation de fonction.
A83: 22.10.00 | B83: A | C83: 44837.692 | D83: D0006 | E83: Cessation de fonction | F83: S0042 | G83: Cessation de fonction | H83: E0348 | I83: Licenciement suite à abandon de poste | J83: Motif cessation de fonction saisi égal à 'Licenciement suite à abandon de poste' | K83: A_CDF_MOTCFT [Saisi] = 'MC139' | L83: T1001 | M83: Licenciement suite à abandon de poste | N83: Création Modification | Q83: Contractuel | R83: P0003 | S83: Général | T83: Passant | U83: 44678 | W83: CEF_I_024 ET CEF_I_028 ET CEF_I_408 ET CEF_I_031 ET CEF_I_409 ET CEF_I_405 ET CEF_I_034 ET CEF_C_002 ET CEF_C_004 ET CEF_C_008 ET CEF_C_011 ET CEF_C_012 ET CEF_C_013 ET CEF_C_027 ET CEF_C_031 ET CEF_C_032 ET CEF_C_033 | X83: CEF_I_024 | Y83: =VLOOKUP(X83,'Axe 2 Règles de gestion'!$D$2:$F$379,3, FALSE) -> Le licenciement intervient pour abandon de poste après refus de déférer à une mise en demeure par laquelle l'agent a été invité à fournir des explications et informé des mesures auxquelles il s'expose s'il ne reprend pas ses fonctions. | Z83: CEF_I_028 | AA83: =VLOOKUP(Z83,'Axe 2 Règles de gestion'!$D$2:$F$379,3, FALSE) -> L'agent recruté pour une durée déterminée ou indéterminée licencié avant le terme de son contrat, a droit à un préavis de 8 jours s'il a moins de 6 mois de service, 1 mois s'il a entre 6 mois et 2 ans de service, 2 mois s'il a au moins 2 ans de service. | AB83: CEF_I_408 | AC83: =VLOOKUP(AB83,'Axe 2 Règles de gestion'!$D$2:$F$379,3, FALSE) -> Le licenciement ne peut intervenir qu'à l'issue d'un entretien préalable. La convocation à l'entretien préalable est effectuée par lettre recommandée ou par lettre remise en main propre contre signature. Cette lettre indique l'objet de la convocation. | AD83: CEF_I_031 | AE83: =VLOOKUP(AD83,'Axe 2 Règles de gestion'!$D$2:$F$379,3, FALSE) -> Au cours de l'entretien préalable, l'administration indique à l'agent les motifs du licenciement et le cas échéant le délai pendant lequel il doit présenter sa demande écrite de reclassement ainsi que les conditions de présentation des offres de reclassement. | AF83: CEF_I_409 | AG83: =VLOOKUP(AF83,'Axe 2 Règles de gestion'!$D$2:$F$379,3, FALSE) -> L'administration notifie sa décision de licenciement à l'agent par lettre recommandée avec AR ou remise en main propre contre signature. La lettre précise le(s) motif(s) ainsi que la date compte tenu des congés annuels restant et de la durée du préavis. | AH83: CEF_I_405 | AI83: =VLOOKUP(AH83,'Axe 2 Règles de gestion'!$D$2:$F$379,3, FALSE) -> Aucun licenciement ne peut être prononcé lorsque l'agent se trouve en état de grossesse médicalement constaté, en congé de maternité, en tout autre congé lié à la parentalité ou pendant une période de 10 semaines suivant l'expiration d'un de ces congés. | AJ83: CEF_I_034 | AK83: =VLOOKUP(AJ83,'Axe 2 Règles de gestion'!$D$2:$F$379,3, FALSE) -> L'avis de licenciement avant la constatation médicale de grossesse ou dans les 15 jours précédant l'arrivée d'un enfant en vue de son adoption peut être annulée si dans les 15 jours de cet avis l'agent donne un justificatif médical ou d'adoption. | BN83: CEF_C_002 | BO83: =VLOOKUP(BN83,'Axe 2 Règles de gestion'!$D$2:$F$379,3, FALSE) -> La date de la cessation de fonctions doit être postérieure ou égale à la date de début de la dernière position en cours. | BP83: CEF_C_004 | BQ83: =VLOOKUP(BP83,'Axe 2 Règles de gestion'!$D$2:$F$379,3, FALSE) -> La date de cessation de fonction doit être postérieure ou égale à la date de début du lien juridique | BR83: CEF_C_008 | BS83: =VLOOKUP(BR83,'Axe 2 Règles de gestion'!$D$2:$F$379,3, FALSE) -> La date du dernier jour travaillé payé doit être antérieure ou égale à la date de fin réelle ou prévisionnelle du lien juridique | BT83: CEF_C_011 | BU83: =VLOOKUP(BT83,'Axe 2 Règles de gestion'!$D$2:$F$379,3, FALSE) -> La date de début du préavis doit être postérieure à la date de début du contrat. | BV83: CEF_C_012 | BW83: =VLOOKUP(BV83,'Axe 2 Règles de gestion'!$D$2:$F$379,3, FALSE) -> La date de fin du préavis doit être antérieure ou égale à la date de fin réelle ou prévisionnelle du lien juridique. | BX83: CEF_C_013 | BY83: =VLOOKUP(BX83,'Axe 2 Règles de gestion'!$D$2:$F$379,3, FALSE) -> Si la date du dernier jour travaillé payé est saisie alors elle doit être antérieure ou égale à la date de cessation de fonctions. | BZ83: CEF_C_027 | CA83: =VLOOKUP(BZ83,'Axe 2 Règles de gestion'!$D$2:$F$379,3, FALSE) -> La date de début du préavis doit être postérieure ou égale à la date de début de l'avenant au contrat. | CB83: CEF_C_031 | CC83: =VLOOKUP(CB83,'Axe 2 Règles de gestion'!$D$2:$F$379,3, FALSE) -> Si l'agent est placé sur une position payée, alors le champ « Date du dernier jour travaillé payé » doit être saisi. | CD83: CEF_C_032 | CE83: =VLOOKUP(CD83,'Axe 2 Règles de gestion'!$D$2:$F$379,3, FALSE) -> La date de cessation de fonction doit être antérieure ou égale à la date limite de départ à la retraite | CF83: CEF_C_033 | CG83: =VLOOKUP(CF83,'Axe 2 Règles de gestion'!$D$2:$F$379,3, FALSE) -> Si la date de fin de préavis est saisie alors elle doit être antérieure ou égale à la date de cessation de fonction.
A84: 18.10.00 | B84: M | C84: 43389.374 | D84: D0006 | E84: Cessation de fonction | F84: S0042 | G84: Cessation de fonction | H84: E0348 | I84: Licenciement suite à abandon de poste | J84: Motif cessation de fonction saisi égal à 'Licenciement suite à abandon de poste' | K84: A_CDF_MOTCFT [Saisi] = 'MC139' | L84: T1001 | M84: Licenciement suite à abandon de poste | N84: Création Modification | Q84: Stagiaire ou auditeur ou élève | R84: P0004 | S84: Général | T84: Passant | U84: 40725 | W84: CEF_C_001 ET CEF_C_002 ET CEF_C_009 ET CEF_C_013 ET CEF_C_014 ET CEF_C_031 ET CEF_C_032 ET CEF_C_033 | BN84: CEF_C_001 | BO84: =VLOOKUP(BN84,'Axe 2 Règles de gestion'!$D$2:$F$379,3, FALSE) -> La date de cessation de fonctions doit être postérieure ou égale à la date d'entrée dans la FPE ou dans la carrière militaire. | BP84: CEF_C_002 | BQ84: =VLOOKUP(BP84,'Axe 2 Règles de gestion'!$D$2:$F$379,3, FALSE) -> La date de la cessation de fonctions doit être postérieure ou égale à la date de début de la dernière position en cours. | BR84: CEF_C_009 | BS84: =VLOOKUP(BR84,'Axe 2 Règles de gestion'!$D$2:$F$379,3, FALSE) -> Si les dates de début et de fin de préavis sont saisies, alors la date de fin du préavis doit être postérieure ou égale à la date de début du préavis. | BT84: CEF_C_013 | BU84: =VLOOKUP(BT84,'Axe 2 Règles de gestion'!$D$2:$F$379,3, FALSE) -> Si la date du dernier jour travaillé payé est saisie alors elle doit être antérieure ou égale à la date de cessation de fonctions. | BV84: CEF_C_014 | BW84: =VLOOKUP(BV84,'Axe 2 Règles de gestion'!$D$2:$F$379,3, FALSE) -> Si la date de début du préavis est saisie alors elle doit être postérieure ou égale à la date d'entrée dans la FPE ou dans la carrière militaire. | BX84: CEF_C_031 | BY84: =VLOOKUP(BX84,'Axe 2 Règles de gestion'!$D$2:$F$379,3, FALSE) -> Si l'agent est placé sur une position payée, alors le champ « Date du dernier jour travaillé payé » doit être saisi. | BZ84: CEF_C_032 | CA84: =VLOOKUP(BZ84,'Axe 2 Règles de gestion'!$D$2:$F$379,3, FALSE) -> La date de cessation de fonction doit être antérieure ou égale à la date limite de départ à la retraite | CB84: CEF_C_033 | CC84: =VLOOKUP(CB84,'Axe 2 Règles de gestion'!$D$2:$F$379,3, FALSE) -> Si la date de fin de préavis est saisie alors elle doit être antérieure ou égale à la date de cessation de fonction.
A85: 17.10.00 | B85: A | C85: 43189.5 | D85: D0006 | E85: Cessation de fonction | F85: S0042 | G85: Cessation de fonction | H85: E0348 | I85: Licenciement suite à abandon de poste | J85: Motif cessation de fonction saisi égal à 'Licenciement suite à abandon de poste' | K85: A_CDF_MOTCFT [Saisi] = 'MC139' | L85: T1001 | M85: Licenciement suite à abandon de poste | N85: Création Modification | Q85: Ouvrier d'état | R85: P0005 | S85: Général | T85: Exclu | U85: 40725
A86: 17.10.00 | B86: A | C86: 43152.5 | D86: D0006 | E86: Cessation de fonction | F86: S0042 | G86: Cessation de fonction | H86: E0348 | I86: Licenciement suite à abandon de poste | J86: Motif cessation de fonction saisi égal à 'Licenciement suite à abandon de poste' | K86: A_CDF_MOTCFT [Saisi] = 'MC139' | L86: T1001 | M86: Licenciement suite à abandon de poste | N86: Création Modification | Q86: Magistrat de l'ordre judiciaire | R86: P0007 | S86: Particulier | T86: Exclu | U86: 40725
A87: 17.10.00 | B87: A | C87: 43152.5 | D87: D0006 | E87: Cessation de fonction | F87: S0042 | G87: Cessation de fonction | H87: E0348 | I87: Licenciement suite à abandon de poste | J87: Motif cessation de fonction saisi égal à 'Licenciement suite à abandon de poste' | K87: A_CDF_MOTCFT [Saisi] = 'MC139' | L87: T1001 | M87: Licenciement suite à abandon de poste | N87: Création Modification | Q87: Auditeur de justice | R87: P0009 | S87: Particulier | T87: Exclu | U87: 40725
A88: 17.10.00 | B88: A | C88: 43152.5 | D88: D0006 | E88: Cessation de fonction | F88: S0042 | G88: Cessation de fonction | H88: E0348 | I88: Licenciement suite à abandon de poste | J88: Motif cessation de fonction saisi égal à 'Licenciement suite à abandon de poste' | K88: A_CDF_MOTCFT [Saisi] = 'MC139' | L88: T1001 | M88: Licenciement suite à abandon de poste | N88: Création Modification | Q88: Personnel civil payé à l'acte ou à la tâche | R88: P0054 | S88: Particulier | T88: Exclu | U88: 40725
A89: 18.10.00 | B89: M | C89: 43152.5 | D89: D0006 | E89: Cessation de fonction | F89: S0042 | G89: Cessation de fonction | H89: E0348 | I89: Licenciement suite à abandon de poste | J89: Motif cessation de fonction saisi égal à 'Licenciement suite à abandon de poste' | K89: A_CDF_MOTCFT [Saisi] = 'MC139' | L89: T1001 | M89: Licenciement suite à abandon de poste | N89: Création Modification | Q89: Volontaire International | R89: P0178 | S89: Particulier | T89: Passant | U89: 40725 | W89: CEF_I_094 ET CEF_C_002 ET CEF_C_004 ET CEF_C_008 ET CEF_C_013 ET CEF_C_031 ET CEF_C_032 | X89: CEF_I_094 | Y89: =VLOOKUP(X89,'Axe 2 Règles de gestion'!$D$2:$F$379,3, FALSE) -> Sauf motif légitime apprécié par l'autorité administrative compétente l'agent qui ne se présente pas dans son organisme d'accueil à la date fixée par le ministre ou l'organisme gestionnaire est réputé avoir renoncé à son volontariat. | BN89: CEF_C_002 | BO89: =VLOOKUP(BN89,'Axe 2 Règles de gestion'!$D$2:$F$379,3, FALSE) -> La date de la cessation de fonctions doit être postérieure ou égale à la date de début de la dernière position en cours. | BP89: CEF_C_004 | BQ89: =VLOOKUP(BP89,'Axe 2 Règles de gestion'!$D$2:$F$379,3, FALSE) -> La date de cessation de fonction doit être postérieure ou égale à la date de début du lien juridique | BR89: CEF_C_008 | BS89: =VLOOKUP(BR89,'Axe 2 Règles de gestion'!$D$2:$F$379,3, FALSE) -> La date du dernier jour travaillé payé doit être antérieure ou égale à la date de fin réelle ou prévisionnelle du lien juridique | BT89: CEF_C_013 | BU89: =VLOOKUP(BT89,'Axe 2 Règles de gestion'!$D$2:$F$379,3, FALSE) -> Si la date du dernier jour travaillé payé est saisie alors elle doit être antérieure ou égale à la date de cessation de fonctions. | BV89: CEF_C_031 | BW89: =VLOOKUP(BV89,'Axe 2 Règles de gestion'!$D$2:$F$379,3, FALSE) -> Si l'agent est placé sur une position payée, alors le champ « Date du dernier jour travaillé payé » doit être saisi. | BX89: CEF_C_032 | BY89: =VLOOKUP(BX89,'Axe 2 Règles de gestion'!$D$2:$F$379,3, FALSE) -> La date de cessation de fonction doit être antérieure ou égale à la date limite de départ à la retraite
A90: 18.10.00 | B90: M | C90: 43152.5 | D90: D0006 | E90: Cessation de fonction | F90: S0042 | G90: Cessation de fonction | H90: E0348 | I90: Licenciement suite à abandon de poste | J90: Motif cessation de fonction saisi égal à 'Licenciement suite à abandon de poste' | K90: A_CDF_MOTCFT [Saisi] = 'MC139' | L90: T1001 | M90: Licenciement suite à abandon de poste | N90: Création Modification | Q90: Enseignant contractuel de l'enseignement agricole privé sous contrat - Agriculture | R90: P0192 | S90: Particulier | T90: Passant | U90: 40725 | W90: CEF_C_002 ET CEF_C_004 ET CEF_C_008 ET CEF_C_013 ET CEF_C_031 ET CEF_C_032 | BN90: CEF_C_002 | BO90: =VLOOKUP(BN90,'Axe 2 Règles de gestion'!$D$2:$F$379,3, FALSE) -> La date de la cessation de fonctions doit être postérieure ou égale à la date de début de la dernière position en cours. | BP90: CEF_C_004 | BQ90: =VLOOKUP(BP90,'Axe 2 Règles de gestion'!$D$2:$F$379,3, FALSE) -> La date de cessation de fonction doit être postérieure ou égale à la date de début du lien juridique | BR90: CEF_C_008 | BS90: =VLOOKUP(BR90,'Axe 2 Règles de gestion'!$D$2:$F$379,3, FALSE) -> La date du dernier jour travaillé payé doit être antérieure ou égale à la date de fin réelle ou prévisionnelle du lien juridique | BT90: CEF_C_013 | BU90: =VLOOKUP(BT90,'Axe 2 Règles de gestion'!$D$2:$F$379,3, FALSE) -> Si la date du dernier jour travaillé payé est saisie alors elle doit être antérieure ou égale à la date de cessation de fonctions. | BV90: CEF_C_031 | BW90: =VLOOKUP(BV90,'Axe 2 Règles de gestion'!$D$2:$F$379,3, FALSE) -> Si l'agent est placé sur une position payée, alors le champ « Date du dernier jour travaillé payé » doit être saisi. | BX90: CEF_C_032 | BY90: =VLOOKUP(BX90,'Axe 2 Règles de gestion'!$D$2:$F$379,3, FALSE) -> La date de cessation de fonction doit être antérieure ou égale à la date limite de départ à la retraite
A91: 18.10.00 | B91: M | C91: 43189.5 | D91: D0006 | E91: Cessation de fonction | F91: S0042 | G91: Cessation de fonction | H91: E0348 | I91: Licenciement suite à abandon de poste | J91: Motif cessation de fonction saisi égal à 'Licenciement suite à abandon de poste' | K91: A_CDF_MOTCFT [Saisi] = 'MC139' | L91: T1001 | M91: Licenciement suite à abandon de poste | N91: Création Modification | Q91: Ouvrier de la défense ou assimilé | R91: P0197 | S91: Particulier | T91: Passant | U91: 40725 | W91: CEF_I_093 ET CEF_C_002 ET CEF_C_004 ET CEF_C_008 ET CEF_C_011 ET CEF_C_012 ET CEF_C_013 ET CEF_C_027 ET CEF_C_031 ET CEF_C_032 ET CEF_C_033 | X91: CEF_I_093 | Y91: =VLOOKUP(X91,'Axe 2 Règles de gestion'!$D$2:$F$379,3, FALSE) -> La radiation des contrôles peut intervenir suite à abandon de poste après refus de déférer à une mise en demeure par laquelle l'agent a été invité à fournir des explications et informé des mesures auxquelles il s'expose s'il ne reprend pas ses fonctions. | BN91: CEF_C_002 | BO91: =VLOOKUP(BN91,'Axe 2 Règles de gestion'!$D$2:$F$379,3, FALSE) -> La date de la cessation de fonctions doit être postérieure ou égale à la date de début de la dernière position en cours. | BP91: CEF_C_004 | BQ91: =VLOOKUP(BP91,'Axe 2 Règles de gestion'!$D$2:$F$379,3, FALSE) -> La date de cessation de fonction doit être postérieure ou égale à la date de début du lien juridique | BR91: CEF_C_008 | BS91: =VLOOKUP(BR91,'Axe 2 Règles de gestion'!$D$2:$F$379,3, FALSE) -> La date du dernier jour travaillé payé doit être antérieure ou égale à la date de fin réelle ou prévisionnelle du lien juridique | BT91: CEF_C_011 | BU91: =VLOOKUP(BT91,'Axe 2 Règles de gestion'!$D$2:$F$379,3, FALSE) -> La date de début du préavis doit être postérieure à la date de début du contrat. | BV91: CEF_C_012 | BW91: =VLOOKUP(BV91,'Axe 2 Règles de gestion'!$D$2:$F$379,3, FALSE) -> La date de fin du préavis doit être antérieure ou égale à la date de fin réelle ou prévisionnelle du lien juridique. | BX91: CEF_C_013 | BY91: =VLOOKUP(BX91,'Axe 2 Règles de gestion'!$D$2:$F$379,3, FALSE) -> Si la date du dernier jour travaillé payé est saisie alors elle doit être antérieure ou égale à la date de cessation de fonctions. | BZ91: CEF_C_027 | CA91: =VLOOKUP(BZ91,'Axe 2 Règles de gestion'!$D$2:$F$379,3, FALSE) -> La date de début du préavis doit être postérieure ou égale à la date de début de l'avenant au contrat. | CB91: CEF_C_031 | CC91: =VLOOKUP(CB91,'Axe 2 Règles de gestion'!$D$2:$F$379,3, FALSE) -> Si l'agent est placé sur une position payée, alors le champ « Date du dernier jour travaillé payé » doit être saisi. | CD91: CEF_C_032 | CE91: =VLOOKUP(CD91,'Axe 2 Règles de gestion'!$D$2:$F$379,3, FALSE) -> La date de cessation de fonction doit être antérieure ou égale à la date limite de départ à la retraite | CF91: CEF_C_033 | CG91: =VLOOKUP(CF91,'Axe 2 Règles de gestion'!$D$2:$F$379,3, FALSE) -> Si la date de fin de préavis est saisie alors elle doit être antérieure ou égale à la date de cessation de fonction.
A92: 23.10.00 | B92: M | C92: 45225.669 | D92: D0006 | E92: Cessation de fonction | F92: S0042 | G92: Cessation de fonction | H92: E0349 | I92: Licenciement suite au refus de trois postes après disponibilité ou congé sans salaire/SRP | J92: Motif cessation de fonction saisi égal à 'Licenciement suite au refus de trois postes après disponibilité ou congé sans salaire/SRP ' | K92: A_CDF_MOTCFT [Saisi] = 'MC132' | L92: T1002 | M92: Licenciement suite au refus de trois postes après disponibilité ou congé sans salaire/SRP | N92: Création Modification | Q92: Titulaire ou magistrat | R92: P0001 | S92: Général | T92: Passant | U92: 40725 | W92: CEF_I_018 ET CEF_C_001 ET CEF_C_002 ET CEF_C_009 ET CEF_C_013 ET CEF_C_014 ET CEF_C_031 ET CEF_C_032 ET CEF_C_033 ET CEF_C_038 | X92: CEF_I_018 | Y92: =VLOOKUP(X92,'Axe 2 Règles de gestion'!$D$2:$F$379,3, FALSE) -> Le licenciement peut intervenir suite à refus de 3 propositions d'affectation après une disponibilité en vue de réintégration et avis préalable de la commission administrative paritaire et s'il n'a pas le droit à pension pour être admis à la retraite. | BN92: CEF_C_001 | BO92: =VLOOKUP(BN92,'Axe 2 Règles de gestion'!$D$2:$F$379,3, FALSE) -> La date de cessation de fonctions doit être postérieure ou égale à la date d'entrée dans la FPE ou dans la carrière militaire. | BP92: CEF_C_002 | BQ92: =VLOOKUP(BP92,'Axe 2 Règles de gestion'!$D$2:$F$379,3, FALSE) -> La date de la cessation de fonctions doit être postérieure ou égale à la date de début de la dernière position en cours. | BR92: CEF_C_009 | BS92: =VLOOKUP(BR92,'Axe 2 Règles de gestion'!$D$2:$F$379,3, FALSE) -> Si les dates de début et de fin de préavis sont saisies, alors la date de fin du préavis doit être postérieure ou égale à la date de début du préavis. | BT92: CEF_C_013 | BU92: =VLOOKUP(BT92,'Axe 2 Règles de gestion'!$D$2:$F$379,3, FALSE) -> Si la date du dernier jour travaillé payé est saisie alors elle doit être antérieure ou égale à la date de cessation de fonctions. | BV92: CEF_C_014 | BW92: =VLOOKUP(BV92,'Axe 2 Règles de gestion'!$D$2:$F$379,3, FALSE) -> Si la date de début du préavis est saisie alors elle doit être postérieure ou égale à la date d'entrée dans la FPE ou dans la carrière militaire. | BX92: CEF_C_031 | BY92: =VLOOKUP(BX92,'Axe 2 Règles de gestion'!$D$2:$F$379,3, FALSE) -> Si l'agent est placé sur une position payée, alors le champ « Date du dernier jour travaillé payé » doit être saisi. | BZ92: CEF_C_032 | CA92: =VLOOKUP(BZ92,'Axe 2 Règles de gestion'!$D$2:$F$379,3, FALSE) -> La date de cessation de fonction doit être antérieure ou égale à la date limite de départ à la retraite | CB92: CEF_C_033 | CC92: =VLOOKUP(CB92,'Axe 2 Règles de gestion'!$D$2:$F$379,3, FALSE) -> Si la date de fin de préavis est saisie alors elle doit être antérieure ou égale à la date de cessation de fonction. | CD92: CEF_C_038 | CE92: =VLOOKUP(CD92,'Axe 2 Règles de gestion'!$D$2:$F$379,3, FALSE) -> Le champ " Date d'effet de la radiation des cadres ou des contrôles " doit être renseigné.
